begin_compilation
  name " HotSpotCompilation-708[bench.ListBench.iteratorFoldLeft()]"
  method "HotSpotCompilation-708[bench.ListBench.iteratorFoldLeft()]"
  date 1526685938163
end_compilation
begin_cfg
  name "Final HIR schedule"
  begin_block
    name "B0"
    from_bci -1
    to_bci -1
    predecessors 
    successors "B1" "B2" 
    xhandlers
    flags 
    probability 4607182418800017408
    begin_IR
      HIR
f <@#|@fixed with next>@ <|@
tid v0 <|@
d <@d|@=== Debug Properties ===
stamp: void
=== Inputs ===
stateAfter: - 
=== Succesors ===
next: a124 
=== Usages ===
=== Predecessor ===
- >@ <|@
instruction <@StartNode|@org.graalvm.compiler.nodes.StartNode>@ stateAfter: - #next: a124  <|@  <|@
f <@~|@floating>@ <|@
tid a1 <|@
d <@d|@=== Debug Properties ===
index: 0
stamp: a! Lbench/ListBench;
uncheckedStamp: [null]
=== Inputs ===
=== Succesors ===
=== Usages ===
?2 v126 
=== Predecessor ===
- >@ <|@
instruction <@Parameter|@org.graalvm.compiler.nodes.ParameterNode>@  <|@  <|@
f <@~|@floating>@ <|@
tid v126 <|@
d <@d|@=== Debug Properties ===
displacement: 16
scale: Times1
stamp: void*
=== Inputs ===
base: a1 
index: - 
=== Succesors ===
=== Usages ===
a124 
=== Predecessor ===
- >@ <|@
instruction <@AMD64Address|@org.graalvm.compiler.core.amd64.AMD64AddressNode>@ base: a1 index: -  <|@  <|@
f <@#|@fixed with next>@ <|@
tid a124 <|@
d <@d|@=== Debug Properties ===
barrierType: NONE
forceFixed: false
location: ListBench.list
nullCheck: false
stamp: n Lscala/collection/immutable/List;
=== Inputs ===
stateBefore: - 
guard: - 
address: v126 
=== Succesors ===
next: v125 
=== Usages ===
v127 
=== Predecessor ===
v0 >@ <|@
instruction <@Read|@org.graalvm.compiler.nodes.memory.ReadNode>@ stateBefore: - guard: - address: v126 #next: v125  <|@  <|@
tid ?2 <|@
d <@d|@=== Debug Properties ===
bci: 0
code: ResolvedJavaMethodBytecode<ListBench.iteratorFoldLeft()>
duringCall: false
localsSize: 3
locksSize: 0
rethrowException: false
sourceFile: Bench.scala
sourceLine: 26
stackSize: 0
=== Inputs ===
outerFrameState: - 
values: a1 - - 
=== Succesors ===
=== Usages ===
v115 v125 
=== Predecessor ===
- >@ <|@
instruction <@FrameState|@org.graalvm.compiler.nodes.FrameState>@ outerFrameState: - values: a1 - -  <|@  <|@
f <@~|@floating>@ <|@
tid v127 <|@
d <@d|@=== Debug Properties ===
displacement: 8
scale: Times8
stamp: void*
=== Inputs ===
base: - 
index: a124 
=== Succesors ===
=== Usages ===
v125 
=== Predecessor ===
- >@ <|@
instruction <@AMD64Address|@org.graalvm.compiler.core.amd64.AMD64AddressNode>@ base: - index: a124  <|@  <|@
f <@#|@fixed with next>@ <|@
tid v125 <|@
d <@d|@=== Debug Properties ===
barrierType: NONE
forceFixed: false
location: CompressedHub:final
nullCheck: true
stamp: Klass*!(compressed base: 0 shift: 3)
=== Inputs ===
stateBefore: ?2 
guard: - 
address: v127 
=== Succesors ===
next: v87 
=== Usages ===
v123 
=== Predecessor ===
a124 >@ <|@
instruction <@Read|@org.graalvm.compiler.nodes.memory.ReadNode>@ stateBefore: ?2 guard: - address: v127 #next: v87  <|@  <|@
f <@~|@floating>@ <|@
tid v122 <|@
d <@d|@=== Debug Properties ===
isDefaultStable: false
rawvalue: meta{HotSpotType<Lscala/collection/immutable/Nil$;, resolved>;compressed}
stableDimension: 0
stamp: Klass*!(compressed base: 0 shift: 3)
stampKind: Klass*(compressed base: 0 shift: 3)
value: meta{HotSpotType<Lscala/collection/immutable/Nil$;, resolved>;compressed}
=== Inputs ===
=== Succesors ===
=== Usages ===
v123 
=== Predecessor ===
- >@ <|@
instruction <@Constant|@org.graalvm.compiler.nodes.ConstantNode>@  <|@  <|@
f <@~|@floating>@ <|@
tid v123 <|@
d <@d|@=== Debug Properties ===
condition: EQ
stamp: void
unorderedIsTrue: false
=== Inputs ===
x: v125 
y: v122 
=== Succesors ===
=== Usages ===
v87 
=== Predecessor ===
- >@ <|@
instruction <@==|@org.graalvm.compiler.nodes.calc.PointerEqualsNode>@ x: v125 y: v122  <|@  <|@
f <@*|@fixed>@ <|@
tid v87 <|@
d <@d|@=== Debug Properties ===
stamp: void
trueSuccessorProbability: 1.0
=== Inputs ===
condition: v123 
=== Succesors ===
trueSuccessor: v84 
falseSuccessor: v86 
=== Usages ===
=== Predecessor ===
v125 >@ <|@
instruction <@If|@org.graalvm.compiler.nodes.IfNode>@ condition: v123 #trueSuccessor: v84 #falseSuccessor: v86  <|@  <|@
    end_IR
  end_block
  begin_block
    name "B1"
    from_bci -1
    to_bci -1
    predecessors "B0" 
    successors 
    xhandlers
    flags 
    probability 4607182418800017408
    begin_IR
      HIR
f <@#|@fixed with next>@ <|@
tid v84 <|@
d <@d|@=== Debug Properties ===
stamp: void
=== Inputs ===
=== Succesors ===
next: v34 
=== Usages ===
=== Predecessor ===
v87 >@ <|@
instruction <@Begin|@org.graalvm.compiler.nodes.BeginNode>@ #next: v34  <|@  <|@
f <@~|@floating>@ <|@
tid i19 <|@
d <@d|@=== Debug Properties ===
isDefaultStable: false
rawvalue: 0
stableDimension: 0
stamp: i32 [0] ⇈0000000000000000
stampKind: i32
value: int[0|0x0]
=== Inputs ===
=== Succesors ===
=== Usages ===
v34 
=== Predecessor ===
- >@ <|@
instruction <@Constant|@org.graalvm.compiler.nodes.ConstantNode>@  <|@  <|@
f <@*|@fixed>@ <|@
tid v34 <|@
d <@d|@=== Debug Properties ===
stamp: void
=== Inputs ===
result: i19 
memoryMap: - 
=== Succesors ===
=== Usages ===
=== Predecessor ===
v84 >@ <|@
instruction <@Return|@org.graalvm.compiler.nodes.ReturnNode>@ result: i19 memoryMap: -  <|@  <|@
    end_IR
  end_block
  begin_block
    name "B2"
    from_bci -1
    to_bci -1
    predecessors "B0" 
    successors 
    xhandlers
    flags 
    probability 2355382605114769408
    begin_IR
      HIR
f <@#|@fixed with next>@ <|@
tid v86 <|@
d <@d|@=== Debug Properties ===
stamp: void
=== Inputs ===
=== Succesors ===
next: v115 
=== Usages ===
=== Predecessor ===
v87 >@ <|@
instruction <@Begin|@org.graalvm.compiler.nodes.BeginNode>@ #next: v115  <|@  <|@
f <@~|@floating>@ <|@
tid a112 <|@
d <@d|@=== Debug Properties ===
isDefaultStable: false
rawvalue: null
stableDimension: 0
stamp: a - NULL
stampKind: a -
value: Object[null]
=== Inputs ===
=== Succesors ===
=== Usages ===
v115 
=== Predecessor ===
- >@ <|@
instruction <@Constant|@org.graalvm.compiler.nodes.ConstantNode>@  <|@  <|@
f <@~|@floating>@ <|@
tid i117 <|@
d <@d|@=== Debug Properties ===
isDefaultStable: false
rawvalue: -19763
stableDimension: 0
stamp: i32 [-19763] ⇊00000000ffffb2cd ⇈00000000ffffb2cd
stampKind: i32
value: int[-19763|0xffffffffffffb2cd]
=== Inputs ===
=== Succesors ===
=== Usages ===
v115 
=== Predecessor ===
- >@ <|@
instruction <@Constant|@org.graalvm.compiler.nodes.ConstantNode>@  <|@  <|@
f <@*|@fixed>@ <|@
tid v115 <|@
d <@d|@=== Debug Properties ===
stamp: void
=== Inputs ===
stateBefore: ?2 
actionAndReason: i117 
speculation: a112 
=== Succesors ===
=== Usages ===
=== Predecessor ===
v86 >@ <|@
instruction <@DynamicDeoptimize|@org.graalvm.compiler.nodes.DynamicDeoptimizeNode>@ stateBefore: ?2 actionAndReason: i117 speculation: a112  <|@  <|@
    end_IR
  end_block
end_cfg
begin_cfg
  name "After LIR generation"
  begin_block
    name "B0"
    from_bci -1
    to_bci -1
    predecessors 
    successors "B1" "B2" 
    xhandlers
    flags 
    probability 4607182418800017408
    begin_IR
      HIR
f <@#|@fixed with next>@ <|@
tid v0 <|@
d <@d|@=== Debug Properties ===
stamp: void
=== Inputs ===
stateAfter: - 
=== Succesors ===
next: a124 
=== Usages ===
=== Predecessor ===
- >@ <|@
instruction <@StartNode|@org.graalvm.compiler.nodes.StartNode>@ stateAfter: - #next: a124  <|@  <|@
f <@~|@floating>@ <|@
tid a1 <|@
result v0|QWORD[.] <|@
d <@d|@=== Debug Properties ===
index: 0
stamp: a! Lbench/ListBench;
uncheckedStamp: [null]
=== Inputs ===
=== Succesors ===
=== Usages ===
?2 v126 
=== Predecessor ===
- >@ <|@
instruction <@Parameter|@org.graalvm.compiler.nodes.ParameterNode>@  <|@  <|@
f <@~|@floating>@ <|@
tid v126 <|@
result [v0|QWORD[.] + 16] <|@
d <@d|@=== Debug Properties ===
displacement: 16
scale: Times1
stamp: void*
=== Inputs ===
base: a1 
index: - 
=== Succesors ===
=== Usages ===
a124 
=== Predecessor ===
- >@ <|@
instruction <@AMD64Address|@org.graalvm.compiler.core.amd64.AMD64AddressNode>@ base: a1 index: -  <|@  <|@
f <@#|@fixed with next>@ <|@
tid a124 <|@
result v1|DWORD[.] <|@
d <@d|@=== Debug Properties ===
barrierType: NONE
forceFixed: false
location: ListBench.list
nullCheck: false
stamp: n Lscala/collection/immutable/List;
=== Inputs ===
stateBefore: - 
guard: - 
address: v126 
=== Succesors ===
next: v125 
=== Usages ===
v127 
=== Predecessor ===
v0 >@ <|@
instruction <@Read|@org.graalvm.compiler.nodes.memory.ReadNode>@ stateBefore: - guard: - address: v126 #next: v125  <|@  <|@
tid ?2 <|@
d <@d|@=== Debug Properties ===
bci: 0
code: ResolvedJavaMethodBytecode<ListBench.iteratorFoldLeft()>
duringCall: false
localsSize: 3
locksSize: 0
rethrowException: false
sourceFile: Bench.scala
sourceLine: 26
stackSize: 0
=== Inputs ===
outerFrameState: - 
values: a1 - - 
=== Succesors ===
=== Usages ===
v115 v125 
=== Predecessor ===
- >@ <|@
instruction <@FrameState|@org.graalvm.compiler.nodes.FrameState>@ outerFrameState: - values: a1 - -  <|@  <|@
f <@~|@floating>@ <|@
tid v127 <|@
result [v1|DWORD[.] * 8 + 8] <|@
d <@d|@=== Debug Properties ===
displacement: 8
scale: Times8
stamp: void*
=== Inputs ===
base: - 
index: a124 
=== Succesors ===
=== Usages ===
v125 
=== Predecessor ===
- >@ <|@
instruction <@AMD64Address|@org.graalvm.compiler.core.amd64.AMD64AddressNode>@ base: - index: a124  <|@  <|@
f <@#|@fixed with next>@ <|@
tid v125 <|@
result INTERIOR_MATCH <|@
d <@d|@=== Debug Properties ===
barrierType: NONE
forceFixed: false
location: CompressedHub:final
nullCheck: true
stamp: Klass*!(compressed base: 0 shift: 3)
=== Inputs ===
stateBefore: ?2 
guard: - 
address: v127 
=== Succesors ===
next: v87 
=== Usages ===
v123 
=== Predecessor ===
a124 >@ <|@
instruction <@Read|@org.graalvm.compiler.nodes.memory.ReadNode>@ stateBefore: ?2 guard: - address: v127 #next: v87  <|@  <|@
f <@~|@floating>@ <|@
tid v122 <|@
result meta{HotSpotType<Lscala/collection/immutable/Nil$;, resolved>;compressed} <|@
d <@d|@=== Debug Properties ===
isDefaultStable: false
rawvalue: meta{HotSpotType<Lscala/collection/immutable/Nil$;, resolved>;compressed}
stableDimension: 0
stamp: Klass*!(compressed base: 0 shift: 3)
stampKind: Klass*(compressed base: 0 shift: 3)
value: meta{HotSpotType<Lscala/collection/immutable/Nil$;, resolved>;compressed}
=== Inputs ===
=== Succesors ===
=== Usages ===
v123 
=== Predecessor ===
- >@ <|@
instruction <@Constant|@org.graalvm.compiler.nodes.ConstantNode>@  <|@  <|@
f <@~|@floating>@ <|@
tid v123 <|@
result INTERIOR_MATCH <|@
d <@d|@=== Debug Properties ===
condition: EQ
stamp: void
unorderedIsTrue: false
=== Inputs ===
x: v125 
y: v122 
=== Succesors ===
=== Usages ===
v87 
=== Predecessor ===
- >@ <|@
instruction <@==|@org.graalvm.compiler.nodes.calc.PointerEqualsNode>@ x: v125 y: v122  <|@  <|@
f <@*|@fixed>@ <|@
tid v87 <|@
result org.graalvm.compiler.core.match.ComplexMatchValue@3b0ad7b8 <|@
d <@d|@=== Debug Properties ===
stamp: void
trueSuccessorProbability: 1.0
=== Inputs ===
condition: v123 
=== Succesors ===
trueSuccessor: v84 
falseSuccessor: v86 
=== Usages ===
=== Predecessor ===
v125 >@ <|@
instruction <@If|@org.graalvm.compiler.nodes.IfNode>@ condition: v123 #trueSuccessor: v84 #falseSuccessor: v86  <|@  <|@
    end_IR
    begin_IR
      LIR
      nr   -1  <|@ instruction [rsi|QWORD[.], rbp|QWORD] = LABEL numbPhis: 0 align: false label: ? <|@ <|@
      nr   -1  <|@ instruction stack:16|QWORD = MOVE rbp|QWORD moveKind: QWORD <|@ <|@
      nr   -1  <|@ instruction [] = HOTSPOTLOCKSTACK frameMapBuilder: org.graalvm.compiler.lir.amd64.AMD64FrameMapBuilder@29fc28da slotKind: QWORD <|@ <|@
      nr   -1  <|@ instruction v0|QWORD[.] = MOVE rsi|QWORD[.] moveKind: QWORD <|@ <|@
      nr   -1  <|@ instruction v1|DWORD[.] = MOV [v0|QWORD[.] + 16] size: DWORD <|@ <|@
      nr   -1  <|@ st <@st|@bench.ListBench.iteratorFoldLeft(Bench.scala:26) [bci: 0]
locals: v0|QWORD[.] - - 
>@ <|@ instruction CMP [v1|DWORD[.] * 8 + 8] y: -559030611 size: DWORD c: meta{HotSpotType<Lscala/collection/immutable/Nil$;, resolved>;compressed} state [bci:0] <|@ <|@
      nr   -1  <|@ instruction BRANCH trueDestinationProbability: 1.0 condition: = trueDestination: B0 -> B1 falseDestination: B0 -> B2 <|@ <|@
    end_IR
  end_block
  begin_block
    name "B1"
    from_bci -1
    to_bci -1
    predecessors "B0" 
    successors 
    xhandlers
    flags 
    probability 4607182418800017408
    begin_IR
      HIR
f <@#|@fixed with next>@ <|@
tid v84 <|@
d <@d|@=== Debug Properties ===
stamp: void
=== Inputs ===
=== Succesors ===
next: v34 
=== Usages ===
=== Predecessor ===
v87 >@ <|@
instruction <@Begin|@org.graalvm.compiler.nodes.BeginNode>@ #next: v34  <|@  <|@
f <@~|@floating>@ <|@
tid i19 <|@
result int[0|0x0] <|@
d <@d|@=== Debug Properties ===
isDefaultStable: false
rawvalue: 0
stableDimension: 0
stamp: i32 [0] ⇈0000000000000000
stampKind: i32
value: int[0|0x0]
=== Inputs ===
=== Succesors ===
=== Usages ===
v34 
=== Predecessor ===
- >@ <|@
instruction <@Constant|@org.graalvm.compiler.nodes.ConstantNode>@  <|@  <|@
f <@*|@fixed>@ <|@
tid v34 <|@
d <@d|@=== Debug Properties ===
stamp: void
=== Inputs ===
result: i19 
memoryMap: - 
=== Succesors ===
=== Usages ===
=== Predecessor ===
v84 >@ <|@
instruction <@Return|@org.graalvm.compiler.nodes.ReturnNode>@ result: i19 memoryMap: -  <|@  <|@
    end_IR
    begin_IR
      LIR
      nr   -1  <|@ instruction [] = LABEL numbPhis: 0 align: false label: ? <|@ <|@
      nr   -1  <|@ instruction rax|DWORD = MOVE input: int[0|0x0] <|@ <|@
      nr   -1  <|@ instruction RETURN (savedRbp: stack:16|QWORD, value: rax|DWORD) isStub: false thread: r15 scratchForSafepointOnReturn: rcx config: org.graalvm.compiler.hotspot.GraalHotSpotVMConfig@53def7b0 <|@ <|@
    end_IR
  end_block
  begin_block
    name "B2"
    from_bci -1
    to_bci -1
    predecessors "B0" 
    successors 
    xhandlers
    flags 
    probability 2355382605114769408
    begin_IR
      HIR
f <@#|@fixed with next>@ <|@
tid v86 <|@
d <@d|@=== Debug Properties ===
stamp: void
=== Inputs ===
=== Succesors ===
next: v115 
=== Usages ===
=== Predecessor ===
v87 >@ <|@
instruction <@Begin|@org.graalvm.compiler.nodes.BeginNode>@ #next: v115  <|@  <|@
f <@~|@floating>@ <|@
tid a112 <|@
result Object[null] <|@
d <@d|@=== Debug Properties ===
isDefaultStable: false
rawvalue: null
stableDimension: 0
stamp: a - NULL
stampKind: a -
value: Object[null]
=== Inputs ===
=== Succesors ===
=== Usages ===
v115 
=== Predecessor ===
- >@ <|@
instruction <@Constant|@org.graalvm.compiler.nodes.ConstantNode>@  <|@  <|@
f <@~|@floating>@ <|@
tid i117 <|@
result int[-19763|0xffffffffffffb2cd] <|@
d <@d|@=== Debug Properties ===
isDefaultStable: false
rawvalue: -19763
stableDimension: 0
stamp: i32 [-19763] ⇊00000000ffffb2cd ⇈00000000ffffb2cd
stampKind: i32
value: int[-19763|0xffffffffffffb2cd]
=== Inputs ===
=== Succesors ===
=== Usages ===
v115 
=== Predecessor ===
- >@ <|@
instruction <@Constant|@org.graalvm.compiler.nodes.ConstantNode>@  <|@  <|@
f <@*|@fixed>@ <|@
tid v115 <|@
d <@d|@=== Debug Properties ===
stamp: void
=== Inputs ===
stateBefore: ?2 
actionAndReason: i117 
speculation: a112 
=== Succesors ===
=== Usages ===
=== Predecessor ===
v86 >@ <|@
instruction <@DynamicDeoptimize|@org.graalvm.compiler.nodes.DynamicDeoptimizeNode>@ stateBefore: ?2 actionAndReason: i117 speculation: a112  <|@  <|@
    end_IR
    begin_IR
      LIR
      nr   -1  <|@ instruction [] = LABEL numbPhis: 0 align: false label: ? <|@ <|@
      nr   -1  <|@ instruction MOV [r15|QWORD + 668] y: -19763 size: DWORD <|@ <|@
      nr   -1  <|@ instruction MOV (x: [r15|QWORD + 680], y: r12|ILLEGAL) size: QWORD <|@ <|@
      nr   -1  <|@ st <@st|@bench.ListBench.iteratorFoldLeft(Bench.scala:26) [bci: 0]
locals: v0|QWORD[.] - - 
>@ <|@ instruction DEOPT info [bci:0] <|@ <|@
    end_IR
  end_block
end_cfg
begin_cfg
  name "After PreAllocationOptimizationStage"
  begin_block
    name "B0"
    from_bci -1
    to_bci -1
    predecessors 
    successors "B1" "B2" 
    xhandlers
    flags 
    probability 4607182418800017408
    begin_IR
      LIR
      nr   -1  <|@ instruction [rsi|QWORD[.], rbp|QWORD] = LABEL numbPhis: 0 align: false label: ? <|@ <|@
      nr   -1  <|@ instruction stack:16|QWORD = MOVE rbp|QWORD moveKind: QWORD <|@ <|@
      nr   -1  <|@ instruction [] = HOTSPOTLOCKSTACK frameMapBuilder: org.graalvm.compiler.lir.amd64.AMD64FrameMapBuilder@29fc28da slotKind: QWORD <|@ <|@
      nr   -1  <|@ instruction v0|QWORD[.] = MOVE rsi|QWORD[.] moveKind: QWORD <|@ <|@
      nr   -1  <|@ instruction v1|DWORD[.] = MOV [v0|QWORD[.] + 16] size: DWORD <|@ <|@
      nr   -1  <|@ st <@st|@bench.ListBench.iteratorFoldLeft(Bench.scala:26) [bci: 0]
locals: v0|QWORD[.] - - 
>@ <|@ instruction CMP [v1|DWORD[.] * 8 + 8] y: -559030611 size: DWORD c: meta{HotSpotType<Lscala/collection/immutable/Nil$;, resolved>;compressed} state [bci:0] <|@ <|@
      nr   -1  <|@ instruction BRANCH trueDestinationProbability: 1.0 condition: = trueDestination: B0 -> B1 falseDestination: B0 -> B2 <|@ <|@
    end_IR
  end_block
  begin_block
    name "B1"
    from_bci -1
    to_bci -1
    predecessors "B0" 
    successors 
    xhandlers
    flags 
    probability 4607182418800017408
    begin_IR
      LIR
      nr   -1  <|@ instruction [] = LABEL numbPhis: 0 align: false label: ? <|@ <|@
      nr   -1  <|@ instruction rax|DWORD = MOVE input: int[0|0x0] <|@ <|@
      nr   -1  <|@ instruction RETURN (savedRbp: stack:16|QWORD, value: rax|DWORD) isStub: false thread: r15 scratchForSafepointOnReturn: rcx config: org.graalvm.compiler.hotspot.GraalHotSpotVMConfig@53def7b0 <|@ <|@
    end_IR
  end_block
  begin_block
    name "B2"
    from_bci -1
    to_bci -1
    predecessors "B0" 
    successors 
    xhandlers
    flags 
    probability 2355382605114769408
    begin_IR
      LIR
      nr   -1  <|@ instruction [] = LABEL numbPhis: 0 align: false label: ? <|@ <|@
      nr   -1  <|@ instruction MOV [r15|QWORD + 668] y: -19763 size: DWORD <|@ <|@
      nr   -1  <|@ instruction MOV (x: [r15|QWORD + 680], y: r12|ILLEGAL) size: QWORD <|@ <|@
      nr   -1  <|@ st <@st|@bench.ListBench.iteratorFoldLeft(Bench.scala:26) [bci: 0]
locals: v0|QWORD[.] - - 
>@ <|@ instruction DEOPT info [bci:0] <|@ <|@
    end_IR
  end_block
end_cfg
begin_bytecodes
     0: aload_0       
     1: invokevirtual #2          // list:()scala.collection.immutable.List
     4: invokevirtual #8          // scala.collection.immutable.List.iterator:()scala.collection.Iterator
     7: astore_1      
     8: iconst_0      
     9: istore_2      
    10: aload_1       
    11: invokeinterface#9, 1       // scala.collection.Iterator.hasNext:()boolean
    16: ifeq          50
    19: iload_2       
    20: new           #91         // scala.collection.immutable.StringOps
    23: dup           
    24: getstatic     #10         // scala.Predef$.MODULE$:scala.Predef$
    27: aload_1       
    28: invokeinterface#11, 1      // scala.collection.Iterator.next:()java.lang.Object
    33: checkcast     #103        // java.lang.String
    36: invokevirtual #12         // scala.Predef$.augmentString:(java.lang.String)java.lang.String
    39: invokespecial #13         // scala.collection.immutable.StringOps.<init>:(java.lang.String)void
    42: invokevirtual #14         // scala.collection.immutable.StringOps.size:()int
    45: iadd          
    46: istore_2      
    47: goto          10
    50: iload_2       
    51: ireturn       
   <|@
end_bytecodes
begin_cfg
  name "After AllocationStage"
  begin_block
    name "B0"
    from_bci -1
    to_bci -1
    predecessors 
    successors "B1" "B2" 
    xhandlers
    flags 
    probability 4607182418800017408
    begin_IR
      LIR
      nr    0  <|@ instruction [rsi|QWORD[.], rbp|QWORD] = LABEL numbPhis: 0 align: false label: ? <|@ <|@
      nr    2  <|@ instruction stack:16|QWORD = MOVE rbp|QWORD moveKind: QWORD <|@ <|@
      nr    4  <|@ instruction [] = HOTSPOTLOCKSTACK frameMapBuilder: org.graalvm.compiler.lir.amd64.AMD64FrameMapBuilder@29fc28da slotKind: QWORD <|@ <|@
      nr    8  <|@ instruction rax|DWORD[.] = MOV [rsi|QWORD[.] + 16] size: DWORD <|@ <|@
      nr   10  <|@ st <@st|@reference-map: [rsi:0]
live-base-pointers: []
bench.ListBench.iteratorFoldLeft(Bench.scala:26) [bci: 0]
locals: rsi|QWORD[.] - - 
>@ <|@ instruction CMP [rax|DWORD[.] * 8 + 8] y: -559030611 size: DWORD c: meta{HotSpotType<Lscala/collection/immutable/Nil$;, resolved>;compressed} state [bci:0] <|@ <|@
      nr   12  <|@ instruction BRANCH trueDestinationProbability: 1.0 condition: = trueDestination: B0 -> B1 falseDestination: B0 -> B2 <|@ <|@
    end_IR
  end_block
  begin_block
    name "B1"
    from_bci -1
    to_bci -1
    predecessors "B0" 
    successors 
    xhandlers
    flags 
    probability 4607182418800017408
    begin_IR
      LIR
      nr   14  <|@ instruction [] = LABEL numbPhis: 0 align: false label: ? <|@ <|@
      nr   16  <|@ instruction rax|DWORD = MOVE input: int[0|0x0] <|@ <|@
      nr   18  <|@ instruction RETURN (savedRbp: stack:16|QWORD, value: rax|DWORD) isStub: false thread: r15 scratchForSafepointOnReturn: rcx config: org.graalvm.compiler.hotspot.GraalHotSpotVMConfig@53def7b0 <|@ <|@
    end_IR
  end_block
  begin_block
    name "B2"
    from_bci -1
    to_bci -1
    predecessors "B0" 
    successors 
    xhandlers
    flags 
    probability 2355382605114769408
    begin_IR
      LIR
      nr   20  <|@ instruction [] = LABEL numbPhis: 0 align: false label: ? <|@ <|@
      nr   22  <|@ instruction MOV [r15|QWORD + 668] y: -19763 size: DWORD <|@ <|@
      nr   24  <|@ instruction MOV (x: [r15|QWORD + 680], y: r12|ILLEGAL) size: QWORD <|@ <|@
      nr   26  <|@ st <@st|@reference-map: [rsi:0]
live-base-pointers: []
bench.ListBench.iteratorFoldLeft(Bench.scala:26) [bci: 0]
locals: rsi|QWORD[.] - - 
>@ <|@ instruction DEOPT info [bci:0] <|@ <|@
    end_IR
  end_block
end_cfg
begin_bytecodes
     0: aload_0       
     1: invokevirtual #2          // list:()scala.collection.immutable.List
     4: invokevirtual #8          // scala.collection.immutable.List.iterator:()scala.collection.Iterator
     7: astore_1      
     8: iconst_0      
     9: istore_2      
    10: aload_1       
    11: invokeinterface#9, 1       // scala.collection.Iterator.hasNext:()boolean
    16: ifeq          50
    19: iload_2       
    20: new           #91         // scala.collection.immutable.StringOps
    23: dup           
    24: getstatic     #10         // scala.Predef$.MODULE$:scala.Predef$
    27: aload_1       
    28: invokeinterface#11, 1      // scala.collection.Iterator.next:()java.lang.Object
    33: checkcast     #103        // java.lang.String
    36: invokevirtual #12         // scala.Predef$.augmentString:(java.lang.String)java.lang.String
    39: invokespecial #13         // scala.collection.immutable.StringOps.<init>:(java.lang.String)void
    42: invokevirtual #14         // scala.collection.immutable.StringOps.size:()int
    45: iadd          
    46: istore_2      
    47: goto          10
    50: iload_2       
    51: ireturn       
   <|@
end_bytecodes
begin_cfg
  name "After PostAllocationOptimizationStage"
  begin_block
    name "B0"
    from_bci -1
    to_bci -1
    predecessors 
    successors "B1" "B2" 
    xhandlers
    flags 
    probability 4607182418800017408
    begin_IR
      LIR
      nr    0  <|@ instruction [rsi|QWORD[.], rbp|QWORD] = LABEL numbPhis: 0 align: false label: ? <|@ <|@
      nr    2  <|@ instruction stack:16|QWORD = MOVE rbp|QWORD moveKind: QWORD <|@ <|@
      nr    4  <|@ instruction [] = HOTSPOTLOCKSTACK frameMapBuilder: org.graalvm.compiler.lir.amd64.AMD64FrameMapBuilder@29fc28da slotKind: QWORD <|@ <|@
      nr    8  <|@ instruction rax|DWORD[.] = MOV [rsi|QWORD[.] + 16] size: DWORD <|@ <|@
      nr   10  <|@ st <@st|@reference-map: [rsi:0]
live-base-pointers: []
bench.ListBench.iteratorFoldLeft(Bench.scala:26) [bci: 0]
locals: rsi|QWORD[.] - - 
>@ <|@ instruction CMP [rax|DWORD[.] * 8 + 8] y: -559030611 size: DWORD c: meta{HotSpotType<Lscala/collection/immutable/Nil$;, resolved>;compressed} state [bci:0] <|@ <|@
      nr   12  <|@ instruction BRANCH trueDestinationProbability: 1.0 condition: = trueDestination: B0 -> B1 falseDestination: B0 -> B2 <|@ <|@
    end_IR
  end_block
  begin_block
    name "B1"
    from_bci -1
    to_bci -1
    predecessors "B0" 
    successors 
    xhandlers
    flags 
    probability 4607182418800017408
    begin_IR
      LIR
      nr   14  <|@ instruction [] = LABEL numbPhis: 0 align: false label: ? <|@ <|@
      nr   16  <|@ instruction rax|DWORD = MOVE input: int[0|0x0] <|@ <|@
      nr   18  <|@ instruction RETURN (savedRbp: stack:16|QWORD, value: rax|DWORD) isStub: false thread: r15 scratchForSafepointOnReturn: rcx config: org.graalvm.compiler.hotspot.GraalHotSpotVMConfig@53def7b0 <|@ <|@
    end_IR
  end_block
  begin_block
    name "B2"
    from_bci -1
    to_bci -1
    predecessors "B0" 
    successors 
    xhandlers
    flags 
    probability 2355382605114769408
    begin_IR
      LIR
      nr   20  <|@ instruction [] = LABEL numbPhis: 0 align: false label: ? <|@ <|@
      nr   22  <|@ instruction MOV [r15|QWORD + 668] y: -19763 size: DWORD <|@ <|@
      nr   24  <|@ instruction MOV (x: [r15|QWORD + 680], y: r12|ILLEGAL) size: QWORD <|@ <|@
      nr   26  <|@ st <@st|@reference-map: [rsi:0]
live-base-pointers: []
bench.ListBench.iteratorFoldLeft(Bench.scala:26) [bci: 0]
locals: rsi|QWORD[.] - - 
>@ <|@ instruction DEOPT info [bci:0] <|@ <|@
    end_IR
  end_block
end_cfg
begin_bytecodes
     0: aload_0       
     1: invokevirtual #2          // list:()scala.collection.immutable.List
     4: invokevirtual #8          // scala.collection.immutable.List.iterator:()scala.collection.Iterator
     7: astore_1      
     8: iconst_0      
     9: istore_2      
    10: aload_1       
    11: invokeinterface#9, 1       // scala.collection.Iterator.hasNext:()boolean
    16: ifeq          50
    19: iload_2       
    20: new           #91         // scala.collection.immutable.StringOps
    23: dup           
    24: getstatic     #10         // scala.Predef$.MODULE$:scala.Predef$
    27: aload_1       
    28: invokeinterface#11, 1      // scala.collection.Iterator.next:()java.lang.Object
    33: checkcast     #103        // java.lang.String
    36: invokevirtual #12         // scala.Predef$.augmentString:(java.lang.String)java.lang.String
    39: invokespecial #13         // scala.collection.immutable.StringOps.<init>:(java.lang.String)void
    42: invokevirtual #14         // scala.collection.immutable.StringOps.size:()int
    45: iadd          
    46: istore_2      
    47: goto          10
    50: iload_2       
    51: ireturn       
   <|@
end_bytecodes
begin_cfg
  name "After code generation"
end_cfg
begin_nmethod
  <<<HexCodeFile
  Platform AMD64 64  <||@
  HexCode 0 448b560849c1e203493bc20f85efffffff900f1f80000000000f1f800000000089842400c0feff4883ec1848896c24108b4610813cc508000000addeadde0f8518000000b800000000488b6c24104883c418850500000000c5f877c341c7879c020000cdb2ffff4d89a7a8020000e80000000090e80000000090e80000000090  <||@
  Comment 0 2  <||@
  Comment 11 {Field[name=CompilerToVM::Data::SharedRuntime_ic_miss_stub, type=address, offset=0, address=0x10fea1f78, value=0x113a41e60]:0x113a41e60}  <||@
  Comment 32 [stack overflow check]  <||@
  Comment 32 3  <||@
  Comment 32 1  <||@
  Comment 43 block B0 null  <||@
  Comment 43 0 [rsi|QWORD[.], rbp|QWORD] = LABEL numbPhis: 0 align: false label: ?  <||@
  Comment 43 2 stack:16|QWORD = MOVE rbp|QWORD moveKind: QWORD  <||@
  Comment 48 4 [] = HOTSPOTLOCKSTACK frameMapBuilder: org.graalvm.compiler.lir.amd64.AMD64FrameMapBuilder@29fc28da slotKind: QWORD  <||@
  Comment 48 8 rax|DWORD[.] = MOV [rsi|QWORD[.] + 16] size: DWORD  <||@
  Comment 51 10 CMP [rax|DWORD[.] * 8 + 8] y: -559030611 size: DWORD c: meta{HotSpotType<Lscala/collection/immutable/Nil$;, resolved>;compressed} state [bci:0]  <||@
  Comment 51 [rsi:0]at bench.ListBench.iteratorFoldLeft(Bench.scala:26) [bci: 0, duringCall: false, rethrow: false]
              |0             |1  |2 
     locals:  |rsi|QWORD[.]  |-  |-   <||@
  Comment 51 {infopoint: IMPLICIT_EXCEPTION}  <||@
  Comment 51 {meta{HotSpotType<Lscala/collection/immutable/Nil$;, resolved>;compressed}}  <||@
  Comment 62 12 BRANCH trueDestinationProbability: 1.0 condition: = trueDestination: B0 -> B1 falseDestination: B0 -> B2  <||@
  Comment 68 block B1 null  <||@
  Comment 68 14 [] = LABEL numbPhis: 0 align: false label: ?  <||@
  Comment 68 16 rax|DWORD = MOVE input: int[0|0x0]  <||@
  Comment 73 18 RETURN (savedRbp: stack:16|QWORD, value: rax|DWORD) isStub: false thread: r15 scratchForSafepointOnReturn: rcx config: org.graalvm.compiler.hotspot.GraalHotSpotVMConfig@53def7b0  <||@
  Comment 82 12  <||@
  Comment 92 block B2 null  <||@
  Comment 92 20 [] = LABEL numbPhis: 0 align: false label: ?  <||@
  Comment 92 22 MOV [r15|QWORD + 668] y: -19763 size: DWORD  <||@
  Comment 103 24 MOV (x: [r15|QWORD + 680], y: r12|ILLEGAL) size: QWORD  <||@
  Comment 110 26 DEOPT info [bci:0]  <||@
  Comment 110 {Field[name=CompilerToVM::Data::SharedRuntime_deopt_blob_uncommon_trap, type=address, offset=0, address=0x10fea1f90, value=0x113a435fe]:0x113a435fe}  <||@
  Comment 115 [rsi:0]at bench.ListBench.iteratorFoldLeft(Bench.scala:26) [bci: 0, duringCall: false, rethrow: false]
              |0             |1  |2 
     locals:  |rsi|QWORD[.]  |-  |-   <||@
  Comment 116 {Stub<ExceptionHandlerStub.exceptionHandler>@0x113dbe360:CallingConvention[rax|QWORD[.], rdx|QWORD]:CallingConvention[rax|QWORD[.], rdx|QWORD]; temps=rdi|ILLEGAL,xmm0|ILLEGAL,xmm1|ILLEGAL,xmm2|ILLEGAL,xmm3|ILLEGAL,xmm4|ILLEGAL,xmm5|ILLEGAL,xmm6|ILLEGAL,xmm7|ILLEGAL,xmm8|ILLEGAL,xmm9|ILLEGAL,xmm10|ILLEGAL,xmm11|ILLEGAL,xmm12|ILLEGAL,xmm13|ILLEGAL,xmm14|ILLEGAL,xmm15|ILLEGAL,xmm16|ILLEGAL,xmm17|ILLEGAL,xmm18|ILLEGAL,xmm19|ILLEGAL,xmm20|ILLEGAL,xmm21|ILLEGAL,xmm22|ILLEGAL,xmm23|ILLEGAL,xmm24|ILLEGAL,xmm25|ILLEGAL,xmm26|ILLEGAL,xmm27|ILLEGAL,xmm28|ILLEGAL,xmm29|ILLEGAL,xmm30|ILLEGAL,xmm31|ILLEGAL,rax|ILLEGAL,rcx|ILLEGAL,rdx|ILLEGAL,rsi|ILLEGAL,r8|ILLEGAL,r9|ILLEGAL,r10|ILLEGAL,r11|ILLEGAL}  <||@
  Comment 116 4  <||@
  Comment 122 {Field[name=CompilerToVM::Data::SharedRuntime_deopt_blob_unpack, type=address, offset=0, address=0x10fea1f88, value=0x113a43500]:0x113a43500}  <||@
  Comment 122 5  <||@
  HexCodeFile>>> <|@
end_nmethod
begin_compilation
  name " HotSpotCompilation-708[bench.ListBench.iteratorFoldLeft()]"
  method "HotSpotCompilation-708[bench.ListBench.iteratorFoldLeft()]"
  date 1526685938264
end_compilation
begin_cfg
  name "After code installation"
end_cfg
begin_nmethod
  <<<HexCodeFile
  Platform AMD64 64  <||@
  HexCode 114135c20 448b560849c1e203493bc20f852fc290ff900f1f80000000000f1f800000000089842400c0feff4883ec1848896c24108b4610813cc508000000852702f80f8518000000b800000000488b6c24104883c41885058e03cbfac5f877c341c7879c020000cdb2ffff4d89a7a8020000e86bd990ff90e8c786c8ff90e861d890ff90  <||@
  Comment 0 2  <||@
  Comment 11 {Field[name=CompilerToVM::Data::SharedRuntime_ic_miss_stub, type=address, offset=0, address=0x10fea1f78, value=0x113a41e60]:0x113a41e60}  <||@
  Comment 32 [stack overflow check]  <||@
  Comment 32 3  <||@
  Comment 32 1  <||@
  Comment 43 block B0 null  <||@
  Comment 43 0 [rsi|QWORD[.], rbp|QWORD] = LABEL numbPhis: 0 align: false label: ?  <||@
  Comment 43 2 stack:16|QWORD = MOVE rbp|QWORD moveKind: QWORD  <||@
  Comment 48 4 [] = HOTSPOTLOCKSTACK frameMapBuilder: org.graalvm.compiler.lir.amd64.AMD64FrameMapBuilder@29fc28da slotKind: QWORD  <||@
  Comment 48 8 rax|DWORD[.] = MOV [rsi|QWORD[.] + 16] size: DWORD  <||@
  Comment 51 10 CMP [rax|DWORD[.] * 8 + 8] y: -559030611 size: DWORD c: meta{HotSpotType<Lscala/collection/immutable/Nil$;, resolved>;compressed} state [bci:0]  <||@
  Comment 51 [rsi:0]at bench.ListBench.iteratorFoldLeft(Bench.scala:26) [bci: 0, duringCall: false, rethrow: false]
              |0             |1  |2 
     locals:  |rsi|QWORD[.]  |-  |-   <||@
  Comment 51 {infopoint: IMPLICIT_EXCEPTION}  <||@
  Comment 51 {meta{HotSpotType<Lscala/collection/immutable/Nil$;, resolved>;compressed}}  <||@
  Comment 62 12 BRANCH trueDestinationProbability: 1.0 condition: = trueDestination: B0 -> B1 falseDestination: B0 -> B2  <||@
  Comment 68 block B1 null  <||@
  Comment 68 14 [] = LABEL numbPhis: 0 align: false label: ?  <||@
  Comment 68 16 rax|DWORD = MOVE input: int[0|0x0]  <||@
  Comment 73 18 RETURN (savedRbp: stack:16|QWORD, value: rax|DWORD) isStub: false thread: r15 scratchForSafepointOnReturn: rcx config: org.graalvm.compiler.hotspot.GraalHotSpotVMConfig@53def7b0  <||@
  Comment 82 12  <||@
  Comment 92 block B2 null  <||@
  Comment 92 20 [] = LABEL numbPhis: 0 align: false label: ?  <||@
  Comment 92 22 MOV [r15|QWORD + 668] y: -19763 size: DWORD  <||@
  Comment 103 24 MOV (x: [r15|QWORD + 680], y: r12|ILLEGAL) size: QWORD  <||@
  Comment 110 26 DEOPT info [bci:0]  <||@
  Comment 110 {Field[name=CompilerToVM::Data::SharedRuntime_deopt_blob_uncommon_trap, type=address, offset=0, address=0x10fea1f90, value=0x113a435fe]:0x113a435fe}  <||@
  Comment 115 [rsi:0]at bench.ListBench.iteratorFoldLeft(Bench.scala:26) [bci: 0, duringCall: false, rethrow: false]
              |0             |1  |2 
     locals:  |rsi|QWORD[.]  |-  |-   <||@
  Comment 116 {Stub<ExceptionHandlerStub.exceptionHandler>@0x113dbe360:CallingConvention[rax|QWORD[.], rdx|QWORD]:CallingConvention[rax|QWORD[.], rdx|QWORD]; temps=rdi|ILLEGAL,xmm0|ILLEGAL,xmm1|ILLEGAL,xmm2|ILLEGAL,xmm3|ILLEGAL,xmm4|ILLEGAL,xmm5|ILLEGAL,xmm6|ILLEGAL,xmm7|ILLEGAL,xmm8|ILLEGAL,xmm9|ILLEGAL,xmm10|ILLEGAL,xmm11|ILLEGAL,xmm12|ILLEGAL,xmm13|ILLEGAL,xmm14|ILLEGAL,xmm15|ILLEGAL,xmm16|ILLEGAL,xmm17|ILLEGAL,xmm18|ILLEGAL,xmm19|ILLEGAL,xmm20|ILLEGAL,xmm21|ILLEGAL,xmm22|ILLEGAL,xmm23|ILLEGAL,xmm24|ILLEGAL,xmm25|ILLEGAL,xmm26|ILLEGAL,xmm27|ILLEGAL,xmm28|ILLEGAL,xmm29|ILLEGAL,xmm30|ILLEGAL,xmm31|ILLEGAL,rax|ILLEGAL,rcx|ILLEGAL,rdx|ILLEGAL,rsi|ILLEGAL,r8|ILLEGAL,r9|ILLEGAL,r10|ILLEGAL,r11|ILLEGAL}  <||@
  Comment 116 4  <||@
  Comment 122 {Field[name=CompilerToVM::Data::SharedRuntime_deopt_blob_unpack, type=address, offset=0, address=0x10fea1f88, value=0x113a43500]:0x113a43500}  <||@
  Comment 122 5  <||@
  HexCodeFile>>> <|@
end_nmethod
