begin_compilation
  name " HotSpotCompilation-2418[java.util.Objects.requireNonNull(Object)]"
  method "HotSpotCompilation-2418[java.util.Objects.requireNonNull(Object)]"
  date 1526687562863
end_compilation
begin_cfg
  name "Final HIR schedule"
  begin_block
    name "B0"
    from_bci -1
    to_bci -1
    predecessors 
    successors 
    xhandlers
    flags 
    probability 4607182418800017408
    begin_IR
      HIR
f <@#|@fixed with next>@ <|@
tid v0 <|@
d <@d|@=== Debug Properties ===
stamp: void
=== Inputs ===
stateAfter: - 
=== Succesors ===
next: v13 
=== Usages ===
=== Predecessor ===
- >@ <|@
instruction <@StartNode|@org.graalvm.compiler.nodes.StartNode>@ stateAfter: - #next: v13  <|@  <|@
f <@~|@floating>@ <|@
tid a12 <|@
d <@d|@=== Debug Properties ===
isDefaultStable: false
rawvalue: null
stableDimension: 0
stamp: a - NULL
stampKind: a -
value: Object[null]
=== Inputs ===
=== Succesors ===
=== Usages ===
?2 
=== Predecessor ===
- >@ <|@
instruction <@Constant|@org.graalvm.compiler.nodes.ConstantNode>@  <|@  <|@
tid ?2 <|@
d <@d|@=== Debug Properties ===
bci: 0
code: ResolvedJavaMethodBytecode<Objects.requireNonNull(Object)>
duringCall: false
localsSize: 1
locksSize: 0
rethrowException: false
sourceFile: Objects.java
sourceLine: 202
stackSize: 0
=== Inputs ===
outerFrameState: - 
values: a12 
=== Succesors ===
=== Usages ===
v13 
=== Predecessor ===
- >@ <|@
instruction <@FrameState|@org.graalvm.compiler.nodes.FrameState>@ outerFrameState: - values: a12  <|@  <|@
f <@~|@floating>@ <|@
tid a1 <|@
d <@d|@=== Debug Properties ===
index: 0
stamp: a Ljava/lang/Object;
uncheckedStamp: [null]
=== Inputs ===
=== Succesors ===
=== Usages ===
v6 v13 
=== Predecessor ===
- >@ <|@
instruction <@Parameter|@org.graalvm.compiler.nodes.ParameterNode>@  <|@  <|@
f <@#|@fixed with next>@ <|@
tid v13 <|@
d <@d|@=== Debug Properties ===
stamp: void
=== Inputs ===
stateBefore: ?2 
object: a1 
=== Succesors ===
next: v6 
=== Usages ===
=== Predecessor ===
v0 >@ <|@
instruction <@NullCheck|@org.graalvm.compiler.nodes.extended.NullCheckNode>@ stateBefore: ?2 object: a1 #next: v6  <|@  <|@
f <@*|@fixed>@ <|@
tid v6 <|@
d <@d|@=== Debug Properties ===
nodeSourcePosition: at java.util.Objects.requireNonNull(Objects.java:204) [bci: 13]
stamp: void
=== Inputs ===
result: a1 
memoryMap: - 
=== Succesors ===
=== Usages ===
=== Predecessor ===
v13 >@ <|@
instruction <@Return|@org.graalvm.compiler.nodes.ReturnNode>@ result: a1 memoryMap: -  <|@  <|@
    end_IR
  end_block
end_cfg
begin_cfg
  name "After LIR generation"
  begin_block
    name "B0"
    from_bci -1
    to_bci -1
    predecessors 
    successors 
    xhandlers
    flags 
    probability 4607182418800017408
    begin_IR
      HIR
f <@#|@fixed with next>@ <|@
tid v0 <|@
d <@d|@=== Debug Properties ===
stamp: void
=== Inputs ===
stateAfter: - 
=== Succesors ===
next: v13 
=== Usages ===
=== Predecessor ===
- >@ <|@
instruction <@StartNode|@org.graalvm.compiler.nodes.StartNode>@ stateAfter: - #next: v13  <|@  <|@
f <@~|@floating>@ <|@
tid a12 <|@
result Object[null] <|@
d <@d|@=== Debug Properties ===
isDefaultStable: false
rawvalue: null
stableDimension: 0
stamp: a - NULL
stampKind: a -
value: Object[null]
=== Inputs ===
=== Succesors ===
=== Usages ===
?2 
=== Predecessor ===
- >@ <|@
instruction <@Constant|@org.graalvm.compiler.nodes.ConstantNode>@  <|@  <|@
tid ?2 <|@
d <@d|@=== Debug Properties ===
bci: 0
code: ResolvedJavaMethodBytecode<Objects.requireNonNull(Object)>
duringCall: false
localsSize: 1
locksSize: 0
rethrowException: false
sourceFile: Objects.java
sourceLine: 202
stackSize: 0
=== Inputs ===
outerFrameState: - 
values: a12 
=== Succesors ===
=== Usages ===
v13 
=== Predecessor ===
- >@ <|@
instruction <@FrameState|@org.graalvm.compiler.nodes.FrameState>@ outerFrameState: - values: a12  <|@  <|@
f <@~|@floating>@ <|@
tid a1 <|@
result v0|QWORD[.] <|@
d <@d|@=== Debug Properties ===
index: 0
stamp: a Ljava/lang/Object;
uncheckedStamp: [null]
=== Inputs ===
=== Succesors ===
=== Usages ===
v6 v13 
=== Predecessor ===
- >@ <|@
instruction <@Parameter|@org.graalvm.compiler.nodes.ParameterNode>@  <|@  <|@
f <@#|@fixed with next>@ <|@
tid v13 <|@
d <@d|@=== Debug Properties ===
stamp: void
=== Inputs ===
stateBefore: ?2 
object: a1 
=== Succesors ===
next: v6 
=== Usages ===
=== Predecessor ===
v0 >@ <|@
instruction <@NullCheck|@org.graalvm.compiler.nodes.extended.NullCheckNode>@ stateBefore: ?2 object: a1 #next: v6  <|@  <|@
f <@*|@fixed>@ <|@
tid v6 <|@
d <@d|@=== Debug Properties ===
nodeSourcePosition: at java.util.Objects.requireNonNull(Objects.java:204) [bci: 13]
stamp: void
=== Inputs ===
result: a1 
memoryMap: - 
=== Succesors ===
=== Usages ===
=== Predecessor ===
v13 >@ <|@
instruction <@Return|@org.graalvm.compiler.nodes.ReturnNode>@ result: a1 memoryMap: -  <|@  <|@
    end_IR
    begin_IR
      LIR
      nr   -1  <|@ instruction [rsi|QWORD[.], rbp|QWORD] = LABEL numbPhis: 0 align: false label: ? <|@ <|@
      nr   -1  <|@ instruction stack:16|QWORD = MOVE rbp|QWORD moveKind: QWORD <|@ <|@
      nr   -1  <|@ instruction [] = HOTSPOTLOCKSTACK frameMapBuilder: org.graalvm.compiler.lir.amd64.AMD64FrameMapBuilder@50360dea slotKind: QWORD <|@ <|@
      nr   -1  <|@ instruction v0|QWORD[.] = MOVE rsi|QWORD[.] moveKind: QWORD <|@ <|@
      nr   -1  <|@ st <@st|@java.util.Objects.requireNonNull(Objects.java:202) [bci: 0]
locals: Object[null] 
>@ <|@ instruction NULLCHECK [v0|QWORD[.]] state [bci:0] <|@ <|@
      nr   -1  <|@ instruction rax|QWORD[.] = MOVE v0|QWORD[.] moveKind: QWORD <|@ <|@
      nr   -1  <|@ instruction RETURN (savedRbp: stack:16|QWORD, value: rax|QWORD[.]) isStub: false thread: r15 scratchForSafepointOnReturn: rcx config: org.graalvm.compiler.hotspot.GraalHotSpotVMConfig@69d7a7b <|@ <|@
    end_IR
  end_block
end_cfg
begin_cfg
  name "After PreAllocationOptimizationStage"
  begin_block
    name "B0"
    from_bci -1
    to_bci -1
    predecessors 
    successors 
    xhandlers
    flags 
    probability 4607182418800017408
    begin_IR
      LIR
      nr   -1  <|@ instruction [rsi|QWORD[.], rbp|QWORD] = LABEL numbPhis: 0 align: false label: ? <|@ <|@
      nr   -1  <|@ instruction stack:16|QWORD = MOVE rbp|QWORD moveKind: QWORD <|@ <|@
      nr   -1  <|@ instruction [] = HOTSPOTLOCKSTACK frameMapBuilder: org.graalvm.compiler.lir.amd64.AMD64FrameMapBuilder@50360dea slotKind: QWORD <|@ <|@
      nr   -1  <|@ instruction v0|QWORD[.] = MOVE rsi|QWORD[.] moveKind: QWORD <|@ <|@
      nr   -1  <|@ st <@st|@java.util.Objects.requireNonNull(Objects.java:202) [bci: 0]
locals: Object[null] 
>@ <|@ instruction NULLCHECK [v0|QWORD[.]] state [bci:0] <|@ <|@
      nr   -1  <|@ instruction rax|QWORD[.] = MOVE v0|QWORD[.] moveKind: QWORD <|@ <|@
      nr   -1  <|@ instruction RETURN (savedRbp: stack:16|QWORD, value: rax|QWORD[.]) isStub: false thread: r15 scratchForSafepointOnReturn: rcx config: org.graalvm.compiler.hotspot.GraalHotSpotVMConfig@69d7a7b <|@ <|@
    end_IR
  end_block
end_cfg
begin_bytecodes
     0: aload_0       
     1: ifnonnull     12
     4: new           #12         // java.lang.NullPointerException
     7: dup           
     8: invokespecial #9          // java.lang.NullPointerException.<init>:()void
    11: athrow        
    12: aload_0       
    13: areturn       
   <|@
end_bytecodes
begin_cfg
  name "After AllocationStage"
  begin_block
    name "B0"
    from_bci -1
    to_bci -1
    predecessors 
    successors 
    xhandlers
    flags 
    probability 4607182418800017408
    begin_IR
      LIR
      nr    0  <|@ instruction [rsi|QWORD[.], rbp|QWORD] = LABEL numbPhis: 0 align: false label: ? <|@ <|@
      nr    2  <|@ instruction stack:16|QWORD = MOVE rbp|QWORD moveKind: QWORD <|@ <|@
      nr    4  <|@ instruction [] = HOTSPOTLOCKSTACK frameMapBuilder: org.graalvm.compiler.lir.amd64.AMD64FrameMapBuilder@50360dea slotKind: QWORD <|@ <|@
      nr    8  <|@ st <@st|@reference-map: [rsi:0]
live-base-pointers: []
java.util.Objects.requireNonNull(Objects.java:202) [bci: 0]
locals: Object[null] 
>@ <|@ instruction NULLCHECK [rsi|QWORD[.]] state [bci:0] <|@ <|@
      nr   10  <|@ instruction rax|QWORD[.] = MOVE rsi|QWORD[.] moveKind: QWORD <|@ <|@
      nr   12  <|@ instruction RETURN (savedRbp: stack:16|QWORD, value: rax|QWORD[.]) isStub: false thread: r15 scratchForSafepointOnReturn: rcx config: org.graalvm.compiler.hotspot.GraalHotSpotVMConfig@69d7a7b <|@ <|@
    end_IR
  end_block
end_cfg
begin_bytecodes
     0: aload_0       
     1: ifnonnull     12
     4: new           #12         // java.lang.NullPointerException
     7: dup           
     8: invokespecial #9          // java.lang.NullPointerException.<init>:()void
    11: athrow        
    12: aload_0       
    13: areturn       
   <|@
end_bytecodes
begin_cfg
  name "After PostAllocationOptimizationStage"
  begin_block
    name "B0"
    from_bci -1
    to_bci -1
    predecessors 
    successors 
    xhandlers
    flags 
    probability 4607182418800017408
    begin_IR
      LIR
      nr    0  <|@ instruction [rsi|QWORD[.], rbp|QWORD] = LABEL numbPhis: 0 align: false label: ? <|@ <|@
      nr    2  <|@ instruction stack:16|QWORD = MOVE rbp|QWORD moveKind: QWORD <|@ <|@
      nr    4  <|@ instruction [] = HOTSPOTLOCKSTACK frameMapBuilder: org.graalvm.compiler.lir.amd64.AMD64FrameMapBuilder@50360dea slotKind: QWORD <|@ <|@
      nr    8  <|@ st <@st|@reference-map: [rsi:0]
live-base-pointers: []
java.util.Objects.requireNonNull(Objects.java:202) [bci: 0]
locals: Object[null] 
>@ <|@ instruction NULLCHECK [rsi|QWORD[.]] state [bci:0] <|@ <|@
      nr   10  <|@ instruction rax|QWORD[.] = MOVE rsi|QWORD[.] moveKind: QWORD <|@ <|@
      nr   12  <|@ instruction RETURN (savedRbp: stack:16|QWORD, value: rax|QWORD[.]) isStub: false thread: r15 scratchForSafepointOnReturn: rcx config: org.graalvm.compiler.hotspot.GraalHotSpotVMConfig@69d7a7b <|@ <|@
    end_IR
  end_block
end_cfg
begin_bytecodes
     0: aload_0       
     1: ifnonnull     12
     4: new           #12         // java.lang.NullPointerException
     7: dup           
     8: invokespecial #9          // java.lang.NullPointerException.<init>:()void
    11: athrow        
    12: aload_0       
    13: areturn       
   <|@
end_bytecodes
begin_cfg
  name "After code generation"
end_cfg
begin_nmethod
  <<<HexCodeFile
  Platform AMD64 64  <||@
  HexCode 0 89842400c0feff4883ec1848896c24108506488bc6488b6c24104883c418850500000000c5f877c3e80000000090e80000000090  <||@
  Comment 0 [stack overflow check]  <||@
  Comment 0 3  <||@
  Comment 0 1  <||@
  Comment 11 block B0 null  <||@
  Comment 11 0 [rsi|QWORD[.], rbp|QWORD] = LABEL numbPhis: 0 align: false label: ?  <||@
  Comment 11 2 stack:16|QWORD = MOVE rbp|QWORD moveKind: QWORD  <||@
  Comment 16 4 [] = HOTSPOTLOCKSTACK frameMapBuilder: org.graalvm.compiler.lir.amd64.AMD64FrameMapBuilder@50360dea slotKind: QWORD  <||@
  Comment 16 8 NULLCHECK [rsi|QWORD[.]] state [bci:0]  <||@
  Comment 16 [rsi:0]at java.util.Objects.requireNonNull(Objects.java:202) [bci: 0, duringCall: false, rethrow: false]
              |0            
     locals:  |Object[null]   <||@
  Comment 16 {infopoint: IMPLICIT_EXCEPTION}  <||@
  Comment 18 10 rax|QWORD[.] = MOVE rsi|QWORD[.] moveKind: QWORD  <||@
  Comment 21 12 RETURN (savedRbp: stack:16|QWORD, value: rax|QWORD[.]) isStub: false thread: r15 scratchForSafepointOnReturn: rcx config: org.graalvm.compiler.hotspot.GraalHotSpotVMConfig@69d7a7b  <||@
  Comment 30 12  <||@
  Comment 40 {Stub<ExceptionHandlerStub.exceptionHandler>@0x118dff7a0:CallingConvention[rax|QWORD[.], rdx|QWORD]:CallingConvention[rax|QWORD[.], rdx|QWORD]; temps=rdi|ILLEGAL,xmm0|ILLEGAL,xmm1|ILLEGAL,xmm2|ILLEGAL,xmm3|ILLEGAL,xmm4|ILLEGAL,xmm5|ILLEGAL,xmm6|ILLEGAL,xmm7|ILLEGAL,xmm8|ILLEGAL,xmm9|ILLEGAL,xmm10|ILLEGAL,xmm11|ILLEGAL,xmm12|ILLEGAL,xmm13|ILLEGAL,xmm14|ILLEGAL,xmm15|ILLEGAL,xmm16|ILLEGAL,xmm17|ILLEGAL,xmm18|ILLEGAL,xmm19|ILLEGAL,xmm20|ILLEGAL,xmm21|ILLEGAL,xmm22|ILLEGAL,xmm23|ILLEGAL,xmm24|ILLEGAL,xmm25|ILLEGAL,xmm26|ILLEGAL,xmm27|ILLEGAL,xmm28|ILLEGAL,xmm29|ILLEGAL,xmm30|ILLEGAL,xmm31|ILLEGAL,rax|ILLEGAL,rcx|ILLEGAL,rdx|ILLEGAL,rsi|ILLEGAL,r8|ILLEGAL,r9|ILLEGAL,r10|ILLEGAL,r11|ILLEGAL}  <||@
  Comment 40 4  <||@
  Comment 46 {Field[name=CompilerToVM::Data::SharedRuntime_deopt_blob_unpack, type=address, offset=0, address=0x10b0a1f88, value=0x118a06500]:0x118a06500}  <||@
  Comment 46 5  <||@
  HexCodeFile>>> <|@
end_nmethod
begin_compilation
  name " HotSpotCompilation-2418[java.util.Objects.requireNonNull(Object)]"
  method "HotSpotCompilation-2418[java.util.Objects.requireNonNull(Object)]"
  date 1526687562878
end_compilation
begin_cfg
  name "After code installation"
end_cfg
begin_nmethod
  <<<HexCodeFile
  Platform AMD64 64  <||@
  HexCode 1195ed460 89842400c0feff4883ec1848896c24108506488bc6488b6c24104883c418850582eb8ef0c5f877c3e8132381ff90e86d9041ff90f4f4f4f4  <||@
  Comment 0 [stack overflow check]  <||@
  Comment 0 3  <||@
  Comment 0 1  <||@
  Comment 11 block B0 null  <||@
  Comment 11 0 [rsi|QWORD[.], rbp|QWORD] = LABEL numbPhis: 0 align: false label: ?  <||@
  Comment 11 2 stack:16|QWORD = MOVE rbp|QWORD moveKind: QWORD  <||@
  Comment 16 4 [] = HOTSPOTLOCKSTACK frameMapBuilder: org.graalvm.compiler.lir.amd64.AMD64FrameMapBuilder@50360dea slotKind: QWORD  <||@
  Comment 16 8 NULLCHECK [rsi|QWORD[.]] state [bci:0]  <||@
  Comment 16 [rsi:0]at java.util.Objects.requireNonNull(Objects.java:202) [bci: 0, duringCall: false, rethrow: false]
              |0            
     locals:  |Object[null]   <||@
  Comment 16 {infopoint: IMPLICIT_EXCEPTION}  <||@
  Comment 18 10 rax|QWORD[.] = MOVE rsi|QWORD[.] moveKind: QWORD  <||@
  Comment 21 12 RETURN (savedRbp: stack:16|QWORD, value: rax|QWORD[.]) isStub: false thread: r15 scratchForSafepointOnReturn: rcx config: org.graalvm.compiler.hotspot.GraalHotSpotVMConfig@69d7a7b  <||@
  Comment 30 12  <||@
  Comment 40 {Stub<ExceptionHandlerStub.exceptionHandler>@0x118dff7a0:CallingConvention[rax|QWORD[.], rdx|QWORD]:CallingConvention[rax|QWORD[.], rdx|QWORD]; temps=rdi|ILLEGAL,xmm0|ILLEGAL,xmm1|ILLEGAL,xmm2|ILLEGAL,xmm3|ILLEGAL,xmm4|ILLEGAL,xmm5|ILLEGAL,xmm6|ILLEGAL,xmm7|ILLEGAL,xmm8|ILLEGAL,xmm9|ILLEGAL,xmm10|ILLEGAL,xmm11|ILLEGAL,xmm12|ILLEGAL,xmm13|ILLEGAL,xmm14|ILLEGAL,xmm15|ILLEGAL,xmm16|ILLEGAL,xmm17|ILLEGAL,xmm18|ILLEGAL,xmm19|ILLEGAL,xmm20|ILLEGAL,xmm21|ILLEGAL,xmm22|ILLEGAL,xmm23|ILLEGAL,xmm24|ILLEGAL,xmm25|ILLEGAL,xmm26|ILLEGAL,xmm27|ILLEGAL,xmm28|ILLEGAL,xmm29|ILLEGAL,xmm30|ILLEGAL,xmm31|ILLEGAL,rax|ILLEGAL,rcx|ILLEGAL,rdx|ILLEGAL,rsi|ILLEGAL,r8|ILLEGAL,r9|ILLEGAL,r10|ILLEGAL,r11|ILLEGAL}  <||@
  Comment 40 4  <||@
  Comment 46 {Field[name=CompilerToVM::Data::SharedRuntime_deopt_blob_unpack, type=address, offset=0, address=0x10b0a1f88, value=0x118a06500]:0x118a06500}  <||@
  Comment 46 5  <||@
  HexCodeFile>>> <|@
end_nmethod
