begin_compilation
  name " HotSpotCompilation-7373[java.util.Formatter.ensureOpen()]"
  method "HotSpotCompilation-7373[java.util.Formatter.ensureOpen()]"
  date 1526687597119
end_compilation
begin_cfg
  name "Final HIR schedule"
  begin_block
    name "B0"
    from_bci -1
    to_bci -1
    predecessors 
    successors 
    xhandlers
    flags 
    probability 4607182418800017408
    begin_IR
      HIR
f <@#|@fixed with next>@ <|@
tid v0 <|@
d <@d|@=== Debug Properties ===
stamp: void
=== Inputs ===
stateAfter: - 
=== Succesors ===
next: a19 
=== Usages ===
=== Predecessor ===
- >@ <|@
instruction <@StartNode|@org.graalvm.compiler.nodes.StartNode>@ stateAfter: - #next: a19  <|@  <|@
f <@~|@floating>@ <|@
tid a1 <|@
d <@d|@=== Debug Properties ===
index: 0
stamp: a!# Ljava/util/Formatter;
uncheckedStamp: [null]
=== Inputs ===
=== Succesors ===
=== Usages ===
?2 v20 
=== Predecessor ===
- >@ <|@
instruction <@Parameter|@org.graalvm.compiler.nodes.ParameterNode>@  <|@  <|@
f <@~|@floating>@ <|@
tid v20 <|@
d <@d|@=== Debug Properties ===
displacement: 16
scale: Times1
stamp: void*
=== Inputs ===
base: a1 
index: - 
=== Succesors ===
=== Usages ===
a19 
=== Predecessor ===
- >@ <|@
instruction <@AMD64Address|@org.graalvm.compiler.core.amd64.AMD64AddressNode>@ base: a1 index: -  <|@  <|@
f <@#|@fixed with next>@ <|@
tid a19 <|@
d <@d|@=== Debug Properties ===
barrierType: NONE
forceFixed: false
location: Formatter.a
nodeSourcePosition: at java.util.Formatter.ensureOpen(Formatter.java:2406) [bci: 1]
nullCheck: false
stamp: n -
=== Inputs ===
stateBefore: - 
guard: - 
address: v20 
=== Succesors ===
next: v21 
=== Usages ===
v21 
=== Predecessor ===
v0 >@ <|@
instruction <@Read|@org.graalvm.compiler.nodes.memory.ReadNode>@ stateBefore: - guard: - address: v20 #next: v21  <|@  <|@
tid ?2 <|@
d <@d|@=== Debug Properties ===
bci: 0
code: ResolvedJavaMethodBytecode<Formatter.ensureOpen()>
duringCall: false
localsSize: 1
locksSize: 0
rethrowException: false
sourceFile: Formatter.java
sourceLine: 2406
stackSize: 0
=== Inputs ===
outerFrameState: - 
values: a1 
=== Succesors ===
=== Usages ===
v21 
=== Predecessor ===
- >@ <|@
instruction <@FrameState|@org.graalvm.compiler.nodes.FrameState>@ outerFrameState: - values: a1  <|@  <|@
f <@#|@fixed with next>@ <|@
tid v21 <|@
d <@d|@=== Debug Properties ===
stamp: void
=== Inputs ===
stateBefore: ?2 
object: a19 
=== Succesors ===
next: v7 
=== Usages ===
=== Predecessor ===
a19 >@ <|@
instruction <@NullCheck|@org.graalvm.compiler.nodes.extended.NullCheckNode>@ stateBefore: ?2 object: a19 #next: v7  <|@  <|@
f <@*|@fixed>@ <|@
tid v7 <|@
d <@d|@=== Debug Properties ===
nodeSourcePosition: at java.util.Formatter.ensureOpen(Formatter.java:2408) [bci: 15]
stamp: void
=== Inputs ===
result: - 
memoryMap: - 
=== Succesors ===
=== Usages ===
=== Predecessor ===
v21 >@ <|@
instruction <@Return|@org.graalvm.compiler.nodes.ReturnNode>@ result: - memoryMap: -  <|@  <|@
    end_IR
  end_block
end_cfg
begin_cfg
  name "After LIR generation"
  begin_block
    name "B0"
    from_bci -1
    to_bci -1
    predecessors 
    successors 
    xhandlers
    flags 
    probability 4607182418800017408
    begin_IR
      HIR
f <@#|@fixed with next>@ <|@
tid v0 <|@
d <@d|@=== Debug Properties ===
stamp: void
=== Inputs ===
stateAfter: - 
=== Succesors ===
next: a19 
=== Usages ===
=== Predecessor ===
- >@ <|@
instruction <@StartNode|@org.graalvm.compiler.nodes.StartNode>@ stateAfter: - #next: a19  <|@  <|@
f <@~|@floating>@ <|@
tid a1 <|@
result v0|QWORD[.] <|@
d <@d|@=== Debug Properties ===
index: 0
stamp: a!# Ljava/util/Formatter;
uncheckedStamp: [null]
=== Inputs ===
=== Succesors ===
=== Usages ===
?2 v20 
=== Predecessor ===
- >@ <|@
instruction <@Parameter|@org.graalvm.compiler.nodes.ParameterNode>@  <|@  <|@
f <@~|@floating>@ <|@
tid v20 <|@
result [v0|QWORD[.] + 16] <|@
d <@d|@=== Debug Properties ===
displacement: 16
scale: Times1
stamp: void*
=== Inputs ===
base: a1 
index: - 
=== Succesors ===
=== Usages ===
a19 
=== Predecessor ===
- >@ <|@
instruction <@AMD64Address|@org.graalvm.compiler.core.amd64.AMD64AddressNode>@ base: a1 index: -  <|@  <|@
f <@#|@fixed with next>@ <|@
tid a19 <|@
result v1|DWORD[.] <|@
d <@d|@=== Debug Properties ===
barrierType: NONE
forceFixed: false
location: Formatter.a
nodeSourcePosition: at java.util.Formatter.ensureOpen(Formatter.java:2406) [bci: 1]
nullCheck: false
stamp: n -
=== Inputs ===
stateBefore: - 
guard: - 
address: v20 
=== Succesors ===
next: v21 
=== Usages ===
v21 
=== Predecessor ===
v0 >@ <|@
instruction <@Read|@org.graalvm.compiler.nodes.memory.ReadNode>@ stateBefore: - guard: - address: v20 #next: v21  <|@  <|@
tid ?2 <|@
d <@d|@=== Debug Properties ===
bci: 0
code: ResolvedJavaMethodBytecode<Formatter.ensureOpen()>
duringCall: false
localsSize: 1
locksSize: 0
rethrowException: false
sourceFile: Formatter.java
sourceLine: 2406
stackSize: 0
=== Inputs ===
outerFrameState: - 
values: a1 
=== Succesors ===
=== Usages ===
v21 
=== Predecessor ===
- >@ <|@
instruction <@FrameState|@org.graalvm.compiler.nodes.FrameState>@ outerFrameState: - values: a1  <|@  <|@
f <@#|@fixed with next>@ <|@
tid v21 <|@
d <@d|@=== Debug Properties ===
stamp: void
=== Inputs ===
stateBefore: ?2 
object: a19 
=== Succesors ===
next: v7 
=== Usages ===
=== Predecessor ===
a19 >@ <|@
instruction <@NullCheck|@org.graalvm.compiler.nodes.extended.NullCheckNode>@ stateBefore: ?2 object: a19 #next: v7  <|@  <|@
f <@*|@fixed>@ <|@
tid v7 <|@
d <@d|@=== Debug Properties ===
nodeSourcePosition: at java.util.Formatter.ensureOpen(Formatter.java:2408) [bci: 15]
stamp: void
=== Inputs ===
result: - 
memoryMap: - 
=== Succesors ===
=== Usages ===
=== Predecessor ===
v21 >@ <|@
instruction <@Return|@org.graalvm.compiler.nodes.ReturnNode>@ result: - memoryMap: -  <|@  <|@
    end_IR
    begin_IR
      LIR
      nr   -1  <|@ instruction [rsi|QWORD[.], rbp|QWORD] = LABEL numbPhis: 0 align: false label: ? <|@ <|@
      nr   -1  <|@ instruction stack:16|QWORD = MOVE rbp|QWORD moveKind: QWORD <|@ <|@
      nr   -1  <|@ instruction [] = HOTSPOTLOCKSTACK frameMapBuilder: org.graalvm.compiler.lir.amd64.AMD64FrameMapBuilder@21cf63 slotKind: QWORD <|@ <|@
      nr   -1  <|@ instruction v0|QWORD[.] = MOVE rsi|QWORD[.] moveKind: QWORD <|@ <|@
      nr   -1  <|@ instruction v1|DWORD[.] = MOV [v0|QWORD[.] + 16] size: DWORD <|@ <|@
      nr   -1  <|@ st <@st|@java.util.Formatter.ensureOpen(Formatter.java:2406) [bci: 0]
locals: v0|QWORD[.] 
>@ <|@ instruction NULLCHECK [r12|QWORD[*] + v1|DWORD[.] * 8] state [bci:0] <|@ <|@
      nr   -1  <|@ instruction RETURN (savedRbp: stack:16|QWORD, value: -) isStub: false thread: r15 scratchForSafepointOnReturn: rcx config: org.graalvm.compiler.hotspot.GraalHotSpotVMConfig@69d7a7b <|@ <|@
    end_IR
  end_block
end_cfg
begin_cfg
  name "After PreAllocationOptimizationStage"
  begin_block
    name "B0"
    from_bci -1
    to_bci -1
    predecessors 
    successors 
    xhandlers
    flags 
    probability 4607182418800017408
    begin_IR
      LIR
      nr   -1  <|@ instruction [rsi|QWORD[.], rbp|QWORD] = LABEL numbPhis: 0 align: false label: ? <|@ <|@
      nr   -1  <|@ instruction stack:16|QWORD = MOVE rbp|QWORD moveKind: QWORD <|@ <|@
      nr   -1  <|@ instruction [] = HOTSPOTLOCKSTACK frameMapBuilder: org.graalvm.compiler.lir.amd64.AMD64FrameMapBuilder@21cf63 slotKind: QWORD <|@ <|@
      nr   -1  <|@ instruction v0|QWORD[.] = MOVE rsi|QWORD[.] moveKind: QWORD <|@ <|@
      nr   -1  <|@ instruction v1|DWORD[.] = MOV [v0|QWORD[.] + 16] size: DWORD <|@ <|@
      nr   -1  <|@ st <@st|@java.util.Formatter.ensureOpen(Formatter.java:2406) [bci: 0]
locals: v0|QWORD[.] 
>@ <|@ instruction NULLCHECK [r12|QWORD[*] + v1|DWORD[.] * 8] state [bci:0] <|@ <|@
      nr   -1  <|@ instruction RETURN (savedRbp: stack:16|QWORD, value: -) isStub: false thread: r15 scratchForSafepointOnReturn: rcx config: org.graalvm.compiler.hotspot.GraalHotSpotVMConfig@69d7a7b <|@ <|@
    end_IR
  end_block
end_cfg
begin_bytecodes
     0: aload_0       
     1: getfield      #2          // a:java.lang.Appendable
     4: ifnonnull     15
     7: new           #50         // java.util.FormatterClosedException
    10: dup           
    11: invokespecial #36         // java.util.FormatterClosedException.<init>:()void
    14: athrow        
    15: return        
   <|@
end_bytecodes
begin_cfg
  name "After AllocationStage"
  begin_block
    name "B0"
    from_bci -1
    to_bci -1
    predecessors 
    successors 
    xhandlers
    flags 
    probability 4607182418800017408
    begin_IR
      LIR
      nr    0  <|@ instruction [rsi|QWORD[.], rbp|QWORD] = LABEL numbPhis: 0 align: false label: ? <|@ <|@
      nr    2  <|@ instruction stack:16|QWORD = MOVE rbp|QWORD moveKind: QWORD <|@ <|@
      nr    4  <|@ instruction [] = HOTSPOTLOCKSTACK frameMapBuilder: org.graalvm.compiler.lir.amd64.AMD64FrameMapBuilder@21cf63 slotKind: QWORD <|@ <|@
      nr    8  <|@ instruction r10|DWORD[.] = MOV [rsi|QWORD[.] + 16] size: DWORD <|@ <|@
      nr   10  <|@ st <@st|@reference-map: [rsi:0]
live-base-pointers: []
java.util.Formatter.ensureOpen(Formatter.java:2406) [bci: 0]
locals: rsi|QWORD[.] 
>@ <|@ instruction NULLCHECK [r12|QWORD[*] + r10|DWORD[.] * 8] state [bci:0] <|@ <|@
      nr   12  <|@ instruction RETURN (savedRbp: stack:16|QWORD, value: -) isStub: false thread: r15 scratchForSafepointOnReturn: rcx config: org.graalvm.compiler.hotspot.GraalHotSpotVMConfig@69d7a7b <|@ <|@
    end_IR
  end_block
end_cfg
begin_bytecodes
     0: aload_0       
     1: getfield      #2          // a:java.lang.Appendable
     4: ifnonnull     15
     7: new           #50         // java.util.FormatterClosedException
    10: dup           
    11: invokespecial #36         // java.util.FormatterClosedException.<init>:()void
    14: athrow        
    15: return        
   <|@
end_bytecodes
begin_cfg
  name "After PostAllocationOptimizationStage"
  begin_block
    name "B0"
    from_bci -1
    to_bci -1
    predecessors 
    successors 
    xhandlers
    flags 
    probability 4607182418800017408
    begin_IR
      LIR
      nr    0  <|@ instruction [rsi|QWORD[.], rbp|QWORD] = LABEL numbPhis: 0 align: false label: ? <|@ <|@
      nr    2  <|@ instruction stack:16|QWORD = MOVE rbp|QWORD moveKind: QWORD <|@ <|@
      nr    4  <|@ instruction [] = HOTSPOTLOCKSTACK frameMapBuilder: org.graalvm.compiler.lir.amd64.AMD64FrameMapBuilder@21cf63 slotKind: QWORD <|@ <|@
      nr    8  <|@ instruction r10|DWORD[.] = MOV [rsi|QWORD[.] + 16] size: DWORD <|@ <|@
      nr   10  <|@ st <@st|@reference-map: [rsi:0]
live-base-pointers: []
java.util.Formatter.ensureOpen(Formatter.java:2406) [bci: 0]
locals: rsi|QWORD[.] 
>@ <|@ instruction NULLCHECK [r12|QWORD[*] + r10|DWORD[.] * 8] state [bci:0] <|@ <|@
      nr   12  <|@ instruction RETURN (savedRbp: stack:16|QWORD, value: -) isStub: false thread: r15 scratchForSafepointOnReturn: rcx config: org.graalvm.compiler.hotspot.GraalHotSpotVMConfig@69d7a7b <|@ <|@
    end_IR
  end_block
end_cfg
begin_bytecodes
     0: aload_0       
     1: getfield      #2          // a:java.lang.Appendable
     4: ifnonnull     15
     7: new           #50         // java.util.FormatterClosedException
    10: dup           
    11: invokespecial #36         // java.util.FormatterClosedException.<init>:()void
    14: athrow        
    15: return        
   <|@
end_bytecodes
begin_cfg
  name "After code generation"
end_cfg
begin_nmethod
  <<<HexCodeFile
  Platform AMD64 64  <||@
  HexCode 0 448b560849c1e203493bc20f85efffffff900f1f80000000000f1f800000000089842400c0feff4883ec1848896c2410448b5610438504d4488b6c24104883c418850500000000c5f877c3e80000000090e80000000090  <||@
  Comment 0 2  <||@
  Comment 11 {Field[name=CompilerToVM::Data::SharedRuntime_ic_miss_stub, type=address, offset=0, address=0x10b0a1f78, value=0x118a04e60]:0x118a04e60}  <||@
  Comment 32 [stack overflow check]  <||@
  Comment 32 3  <||@
  Comment 32 1  <||@
  Comment 43 block B0 null  <||@
  Comment 43 0 [rsi|QWORD[.], rbp|QWORD] = LABEL numbPhis: 0 align: false label: ?  <||@
  Comment 43 2 stack:16|QWORD = MOVE rbp|QWORD moveKind: QWORD  <||@
  Comment 48 4 [] = HOTSPOTLOCKSTACK frameMapBuilder: org.graalvm.compiler.lir.amd64.AMD64FrameMapBuilder@21cf63 slotKind: QWORD  <||@
  Comment 48 8 r10|DWORD[.] = MOV [rsi|QWORD[.] + 16] size: DWORD  <||@
  Comment 52 10 NULLCHECK [r12|QWORD[*] + r10|DWORD[.] * 8] state [bci:0]  <||@
  Comment 52 [rsi:0]at java.util.Formatter.ensureOpen(Formatter.java:2406) [bci: 0, duringCall: false, rethrow: false]
              |0            
     locals:  |rsi|QWORD[.]   <||@
  Comment 52 {infopoint: IMPLICIT_EXCEPTION}  <||@
  Comment 56 12 RETURN (savedRbp: stack:16|QWORD, value: -) isStub: false thread: r15 scratchForSafepointOnReturn: rcx config: org.graalvm.compiler.hotspot.GraalHotSpotVMConfig@69d7a7b  <||@
  Comment 65 12  <||@
  Comment 75 {Stub<ExceptionHandlerStub.exceptionHandler>@0x118dff7a0:CallingConvention[rax|QWORD[.], rdx|QWORD]:CallingConvention[rax|QWORD[.], rdx|QWORD]; temps=rdi|ILLEGAL,xmm0|ILLEGAL,xmm1|ILLEGAL,xmm2|ILLEGAL,xmm3|ILLEGAL,xmm4|ILLEGAL,xmm5|ILLEGAL,xmm6|ILLEGAL,xmm7|ILLEGAL,xmm8|ILLEGAL,xmm9|ILLEGAL,xmm10|ILLEGAL,xmm11|ILLEGAL,xmm12|ILLEGAL,xmm13|ILLEGAL,xmm14|ILLEGAL,xmm15|ILLEGAL,xmm16|ILLEGAL,xmm17|ILLEGAL,xmm18|ILLEGAL,xmm19|ILLEGAL,xmm20|ILLEGAL,xmm21|ILLEGAL,xmm22|ILLEGAL,xmm23|ILLEGAL,xmm24|ILLEGAL,xmm25|ILLEGAL,xmm26|ILLEGAL,xmm27|ILLEGAL,xmm28|ILLEGAL,xmm29|ILLEGAL,xmm30|ILLEGAL,xmm31|ILLEGAL,rax|ILLEGAL,rcx|ILLEGAL,rdx|ILLEGAL,rsi|ILLEGAL,r8|ILLEGAL,r9|ILLEGAL,r10|ILLEGAL,r11|ILLEGAL}  <||@
  Comment 75 4  <||@
  Comment 81 {Field[name=CompilerToVM::Data::SharedRuntime_deopt_blob_unpack, type=address, offset=0, address=0x10b0a1f88, value=0x118a06500]:0x118a06500}  <||@
  Comment 81 5  <||@
  HexCodeFile>>> <|@
end_nmethod
begin_compilation
  name " HotSpotCompilation-7373[java.util.Formatter.ensureOpen()]"
  method "HotSpotCompilation-7373[java.util.Formatter.ensureOpen()]"
  date 1526687597144
end_compilation
begin_cfg
  name "After code installation"
end_cfg
begin_nmethod
  <<<HexCodeFile
  Platform AMD64 64  <||@
  HexCode 118add2a0 448b560849c1e203493bc20f85af7bf2ff900f1f80000000000f1f800000000089842400c0feff4883ec1848896c2410448b5610438504d4488b6c24104883c41885051fed3ff1c5f877c3e8b024320090e80a92f2ff90f4  <||@
  Comment 0 2  <||@
  Comment 11 {Field[name=CompilerToVM::Data::SharedRuntime_ic_miss_stub, type=address, offset=0, address=0x10b0a1f78, value=0x118a04e60]:0x118a04e60}  <||@
  Comment 32 [stack overflow check]  <||@
  Comment 32 3  <||@
  Comment 32 1  <||@
  Comment 43 block B0 null  <||@
  Comment 43 0 [rsi|QWORD[.], rbp|QWORD] = LABEL numbPhis: 0 align: false label: ?  <||@
  Comment 43 2 stack:16|QWORD = MOVE rbp|QWORD moveKind: QWORD  <||@
  Comment 48 4 [] = HOTSPOTLOCKSTACK frameMapBuilder: org.graalvm.compiler.lir.amd64.AMD64FrameMapBuilder@21cf63 slotKind: QWORD  <||@
  Comment 48 8 r10|DWORD[.] = MOV [rsi|QWORD[.] + 16] size: DWORD  <||@
  Comment 52 10 NULLCHECK [r12|QWORD[*] + r10|DWORD[.] * 8] state [bci:0]  <||@
  Comment 52 [rsi:0]at java.util.Formatter.ensureOpen(Formatter.java:2406) [bci: 0, duringCall: false, rethrow: false]
              |0            
     locals:  |rsi|QWORD[.]   <||@
  Comment 52 {infopoint: IMPLICIT_EXCEPTION}  <||@
  Comment 56 12 RETURN (savedRbp: stack:16|QWORD, value: -) isStub: false thread: r15 scratchForSafepointOnReturn: rcx config: org.graalvm.compiler.hotspot.GraalHotSpotVMConfig@69d7a7b  <||@
  Comment 65 12  <||@
  Comment 75 {Stub<ExceptionHandlerStub.exceptionHandler>@0x118dff7a0:CallingConvention[rax|QWORD[.], rdx|QWORD]:CallingConvention[rax|QWORD[.], rdx|QWORD]; temps=rdi|ILLEGAL,xmm0|ILLEGAL,xmm1|ILLEGAL,xmm2|ILLEGAL,xmm3|ILLEGAL,xmm4|ILLEGAL,xmm5|ILLEGAL,xmm6|ILLEGAL,xmm7|ILLEGAL,xmm8|ILLEGAL,xmm9|ILLEGAL,xmm10|ILLEGAL,xmm11|ILLEGAL,xmm12|ILLEGAL,xmm13|ILLEGAL,xmm14|ILLEGAL,xmm15|ILLEGAL,xmm16|ILLEGAL,xmm17|ILLEGAL,xmm18|ILLEGAL,xmm19|ILLEGAL,xmm20|ILLEGAL,xmm21|ILLEGAL,xmm22|ILLEGAL,xmm23|ILLEGAL,xmm24|ILLEGAL,xmm25|ILLEGAL,xmm26|ILLEGAL,xmm27|ILLEGAL,xmm28|ILLEGAL,xmm29|ILLEGAL,xmm30|ILLEGAL,xmm31|ILLEGAL,rax|ILLEGAL,rcx|ILLEGAL,rdx|ILLEGAL,rsi|ILLEGAL,r8|ILLEGAL,r9|ILLEGAL,r10|ILLEGAL,r11|ILLEGAL}  <||@
  Comment 75 4  <||@
  Comment 81 {Field[name=CompilerToVM::Data::SharedRuntime_deopt_blob_unpack, type=address, offset=0, address=0x10b0a1f88, value=0x118a06500]:0x118a06500}  <||@
  Comment 81 5  <||@
  HexCodeFile>>> <|@
end_nmethod
