begin_compilation
  name " HotSpotCompilation-3553[java.nio.Buffer.<init>(int, int, int, int)]"
  method "HotSpotCompilation-3553[java.nio.Buffer.<init>(int, int, int, int)]"
  date 1526687584037
end_compilation
begin_cfg
  name "Final HIR schedule"
  begin_block
    name "B0"
    from_bci -1
    to_bci -1
    predecessors 
    successors "B1" "B2" 
    xhandlers
    flags 
    probability 4607182418800017408
    begin_IR
      HIR
f <@#|@fixed with next>@ <|@
tid v0 <|@
d <@d|@=== Debug Properties ===
stamp: void
=== Inputs ===
stateAfter: - 
=== Succesors ===
next: v80 
=== Usages ===
=== Predecessor ===
- >@ <|@
instruction <@StartNode|@org.graalvm.compiler.nodes.StartNode>@ stateAfter: - #next: v80  <|@  <|@
f <@~|@floating>@ <|@
tid a1 <|@
d <@d|@=== Debug Properties ===
index: 0
stamp: a! Ljava/nio/Buffer;
uncheckedStamp: [null]
=== Inputs ===
=== Succesors ===
=== Usages ===
?6 v118 v120 v119 v121 
=== Predecessor ===
- >@ <|@
instruction <@Parameter|@org.graalvm.compiler.nodes.ParameterNode>@  <|@  <|@
f <@~|@floating>@ <|@
tid i2 <|@
d <@d|@=== Debug Properties ===
index: 1
stamp: i32
uncheckedStamp: [null]
=== Inputs ===
=== Succesors ===
=== Usages ===
?6 v23 
=== Predecessor ===
- >@ <|@
instruction <@Parameter|@org.graalvm.compiler.nodes.ParameterNode>@  <|@  <|@
f <@~|@floating>@ <|@
tid i3 <|@
d <@d|@=== Debug Properties ===
index: 2
stamp: i32
uncheckedStamp: [null]
=== Inputs ===
=== Succesors ===
=== Usages ===
?6 v75 v46 v44 
=== Predecessor ===
- >@ <|@
instruction <@Parameter|@org.graalvm.compiler.nodes.ParameterNode>@  <|@  <|@
f <@~|@floating>@ <|@
tid i4 <|@
d <@d|@=== Debug Properties ===
index: 3
stamp: i32
uncheckedStamp: [null]
=== Inputs ===
=== Succesors ===
=== Usages ===
?6 v44 v72 v29 v27 
=== Predecessor ===
- >@ <|@
instruction <@Parameter|@org.graalvm.compiler.nodes.ParameterNode>@  <|@  <|@
f <@~|@floating>@ <|@
tid i5 <|@
d <@d|@=== Debug Properties ===
index: 4
stamp: i32
uncheckedStamp: [null]
=== Inputs ===
=== Succesors ===
=== Usages ===
?6 v27 v67 v13 
=== Predecessor ===
- >@ <|@
instruction <@Parameter|@org.graalvm.compiler.nodes.ParameterNode>@  <|@  <|@
f <@~|@floating>@ <|@
tid i10 <|@
d <@d|@=== Debug Properties ===
isDefaultStable: false
nodeSourcePosition: at java.nio.Buffer.<init>(Buffer.java:186) [bci: 10]
rawvalue: 0
stableDimension: 0
stamp: i32 [0] ⇈0000000000000000
stampKind: i32
value: int[0|0x0]
=== Inputs ===
=== Succesors ===
=== Usages ===
v63 v13 v23 v29 v46 
=== Predecessor ===
- >@ <|@
instruction <@Constant|@org.graalvm.compiler.nodes.ConstantNode>@  <|@  <|@
f <@~|@floating>@ <|@
tid v13 <|@
d <@d|@=== Debug Properties ===
condition: LT
nodeSourcePosition: at java.nio.Buffer.<init>(Buffer.java:198) [bci: 16]
op: org.graalvm.compiler.nodes.calc.IntegerLessThanNode$LessThanOp@33a89f26
stamp: void
unorderedIsTrue: false
=== Inputs ===
x: i5 
y: i10 
=== Succesors ===
=== Usages ===
v80 
=== Predecessor ===
- >@ <|@
instruction <@<|@org.graalvm.compiler.nodes.calc.IntegerLessThanNode>@ x: i5 y: i10  <|@  <|@
f <@*|@fixed>@ <|@
tid v80 <|@
d <@d|@=== Debug Properties ===
nodeSourcePosition: at java.nio.Buffer.<init>(Buffer.java:198) [bci: 16]
stamp: void
trueSuccessorProbability: 0.0
=== Inputs ===
condition: v13 
=== Succesors ===
trueSuccessor: v79 
falseSuccessor: v77 
=== Usages ===
=== Predecessor ===
v0 >@ <|@
instruction <@If|@org.graalvm.compiler.nodes.IfNode>@ condition: v13 #trueSuccessor: v79 #falseSuccessor: v77  <|@  <|@
    end_IR
  end_block
  begin_block
    name "B1"
    from_bci -1
    to_bci -1
    predecessors "B0" 
    successors "B13" 
    xhandlers
    flags 
    probability 2355382605114769408
    begin_IR
      HIR
f <@#|@fixed with next>@ <|@
tid v79 <|@
d <@d|@=== Debug Properties ===
nodeSourcePosition: at java.nio.Buffer.<init>(Buffer.java:198) [bci: 16]
stamp: void
=== Inputs ===
=== Succesors ===
next: v102 
=== Usages ===
=== Predecessor ===
v80 >@ <|@
instruction <@Begin|@org.graalvm.compiler.nodes.BeginNode>@ #next: v102  <|@  <|@
f <@~|@floating>@ <|@
tid i103 <|@
d <@d|@=== Debug Properties ===
isDefaultStable: false
rawvalue: -16403
stableDimension: 0
stamp: i32 [-16403] ⇊00000000ffffbfed ⇈00000000ffffbfed
stampKind: i32
value: int[-16403|0xffffffffffffbfed]
=== Inputs ===
=== Succesors ===
=== Usages ===
i105 
=== Predecessor ===
- >@ <|@
instruction <@Constant|@org.graalvm.compiler.nodes.ConstantNode>@  <|@  <|@
f <@*|@fixed>@ <|@
tid v102 <|@
d <@d|@=== Debug Properties ===
stamp: void
=== Inputs ===
=== Succesors ===
=== Usages ===
v101 
=== Predecessor ===
v79 >@ <|@
instruction <@EndNode|@org.graalvm.compiler.nodes.EndNode>@  <|@  <|@
    end_IR
  end_block
  begin_block
    name "B2"
    from_bci -1
    to_bci -1
    predecessors "B0" 
    successors "B3" "B4" 
    xhandlers
    flags 
    probability 4607182418800017408
    begin_IR
      HIR
f <@#|@fixed with next>@ <|@
tid v77 <|@
d <@d|@=== Debug Properties ===
nodeSourcePosition: at java.nio.Buffer.<init>(Buffer.java:198) [bci: 16]
stamp: void
=== Inputs ===
=== Succesors ===
next: v84 
=== Usages ===
=== Predecessor ===
v80 >@ <|@
instruction <@Begin|@org.graalvm.compiler.nodes.BeginNode>@ #next: v84  <|@  <|@
f <@~|@floating>@ <|@
tid v27 <|@
d <@d|@=== Debug Properties ===
condition: LT
nodeSourcePosition: at java.nio.Buffer.limit(Buffer.java:274) [bci: 5]
at java.nio.Buffer.<init>(Buffer.java:201) [bci: 55]
op: org.graalvm.compiler.nodes.calc.IntegerLessThanNode$LessThanOp@33a89f26
stamp: void
unorderedIsTrue: false
=== Inputs ===
x: i5 
y: i4 
=== Succesors ===
=== Usages ===
v84 
=== Predecessor ===
- >@ <|@
instruction <@<|@org.graalvm.compiler.nodes.calc.IntegerLessThanNode>@ x: i5 y: i4  <|@  <|@
f <@*|@fixed>@ <|@
tid v84 <|@
d <@d|@=== Debug Properties ===
nodeSourcePosition: at java.nio.Buffer.limit(Buffer.java:274) [bci: 5]
at java.nio.Buffer.<init>(Buffer.java:201) [bci: 55]
stamp: void
trueSuccessorProbability: 0.0
=== Inputs ===
condition: v27 
=== Succesors ===
trueSuccessor: v83 
falseSuccessor: v81 
=== Usages ===
=== Predecessor ===
v77 >@ <|@
instruction <@If|@org.graalvm.compiler.nodes.IfNode>@ condition: v27 #trueSuccessor: v83 #falseSuccessor: v81  <|@  <|@
    end_IR
  end_block
  begin_block
    name "B3"
    from_bci -1
    to_bci -1
    predecessors "B2" 
    successors "B13" 
    xhandlers
    flags 
    probability 2355382605114769408
    begin_IR
      HIR
f <@#|@fixed with next>@ <|@
tid v83 <|@
d <@d|@=== Debug Properties ===
nodeSourcePosition: at java.nio.Buffer.limit(Buffer.java:274) [bci: 5]
at java.nio.Buffer.<init>(Buffer.java:201) [bci: 55]
stamp: void
=== Inputs ===
=== Succesors ===
next: v108 
=== Usages ===
=== Predecessor ===
v84 >@ <|@
instruction <@Begin|@org.graalvm.compiler.nodes.BeginNode>@ #next: v108  <|@  <|@
f <@~|@floating>@ <|@
tid i109 <|@
d <@d|@=== Debug Properties ===
isDefaultStable: false
rawvalue: -17427
stableDimension: 0
stamp: i32 [-17427] ⇊00000000ffffbbed ⇈00000000ffffbbed
stampKind: i32
value: int[-17427|0xffffffffffffbbed]
=== Inputs ===
=== Succesors ===
=== Usages ===
i105 
=== Predecessor ===
- >@ <|@
instruction <@Constant|@org.graalvm.compiler.nodes.ConstantNode>@  <|@  <|@
f <@*|@fixed>@ <|@
tid v108 <|@
d <@d|@=== Debug Properties ===
stamp: void
=== Inputs ===
=== Succesors ===
=== Usages ===
v101 
=== Predecessor ===
v83 >@ <|@
instruction <@EndNode|@org.graalvm.compiler.nodes.EndNode>@  <|@  <|@
    end_IR
  end_block
  begin_block
    name "B4"
    from_bci -1
    to_bci -1
    predecessors "B2" 
    successors "B5" "B6" 
    xhandlers
    flags 
    probability 4607182418800017408
    begin_IR
      HIR
f <@#|@fixed with next>@ <|@
tid v81 <|@
d <@d|@=== Debug Properties ===
nodeSourcePosition: at java.nio.Buffer.limit(Buffer.java:274) [bci: 5]
at java.nio.Buffer.<init>(Buffer.java:201) [bci: 55]
stamp: void
=== Inputs ===
=== Succesors ===
next: v88 
=== Usages ===
=== Predecessor ===
v84 >@ <|@
instruction <@Begin|@org.graalvm.compiler.nodes.BeginNode>@ #next: v88  <|@  <|@
f <@~|@floating>@ <|@
tid v29 <|@
d <@d|@=== Debug Properties ===
condition: LT
nodeSourcePosition: at java.nio.Buffer.limit(Buffer.java:274) [bci: 9]
at java.nio.Buffer.<init>(Buffer.java:201) [bci: 55]
op: org.graalvm.compiler.nodes.calc.IntegerLessThanNode$LessThanOp@33a89f26
stamp: void
unorderedIsTrue: false
=== Inputs ===
x: i4 
y: i10 
=== Succesors ===
=== Usages ===
v88 
=== Predecessor ===
- >@ <|@
instruction <@<|@org.graalvm.compiler.nodes.calc.IntegerLessThanNode>@ x: i4 y: i10  <|@  <|@
f <@*|@fixed>@ <|@
tid v88 <|@
d <@d|@=== Debug Properties ===
nodeSourcePosition: at java.nio.Buffer.limit(Buffer.java:274) [bci: 9]
at java.nio.Buffer.<init>(Buffer.java:201) [bci: 55]
stamp: void
trueSuccessorProbability: 0.0
=== Inputs ===
condition: v29 
=== Succesors ===
trueSuccessor: v87 
falseSuccessor: v85 
=== Usages ===
=== Predecessor ===
v81 >@ <|@
instruction <@If|@org.graalvm.compiler.nodes.IfNode>@ condition: v29 #trueSuccessor: v87 #falseSuccessor: v85  <|@  <|@
    end_IR
  end_block
  begin_block
    name "B5"
    from_bci -1
    to_bci -1
    predecessors "B4" 
    successors "B13" 
    xhandlers
    flags 
    probability 2355382605114769408
    begin_IR
      HIR
f <@#|@fixed with next>@ <|@
tid v87 <|@
d <@d|@=== Debug Properties ===
nodeSourcePosition: at java.nio.Buffer.limit(Buffer.java:274) [bci: 9]
at java.nio.Buffer.<init>(Buffer.java:201) [bci: 55]
stamp: void
=== Inputs ===
=== Succesors ===
next: v110 
=== Usages ===
=== Predecessor ===
v88 >@ <|@
instruction <@Begin|@org.graalvm.compiler.nodes.BeginNode>@ #next: v110  <|@  <|@
f <@~|@floating>@ <|@
tid i111 <|@
d <@d|@=== Debug Properties ===
isDefaultStable: false
rawvalue: -17683
stableDimension: 0
stamp: i32 [-17683] ⇊00000000ffffbaed ⇈00000000ffffbaed
stampKind: i32
value: int[-17683|0xffffffffffffbaed]
=== Inputs ===
=== Succesors ===
=== Usages ===
i105 
=== Predecessor ===
- >@ <|@
instruction <@Constant|@org.graalvm.compiler.nodes.ConstantNode>@  <|@  <|@
f <@*|@fixed>@ <|@
tid v110 <|@
d <@d|@=== Debug Properties ===
stamp: void
=== Inputs ===
=== Succesors ===
=== Usages ===
v101 
=== Predecessor ===
v87 >@ <|@
instruction <@EndNode|@org.graalvm.compiler.nodes.EndNode>@  <|@  <|@
    end_IR
  end_block
  begin_block
    name "B6"
    from_bci -1
    to_bci -1
    predecessors "B4" 
    successors "B7" "B8" 
    xhandlers
    flags 
    probability 4607182418800017408
    begin_IR
      HIR
f <@#|@fixed with next>@ <|@
tid v85 <|@
d <@d|@=== Debug Properties ===
nodeSourcePosition: at java.nio.Buffer.limit(Buffer.java:274) [bci: 9]
at java.nio.Buffer.<init>(Buffer.java:201) [bci: 55]
stamp: void
=== Inputs ===
=== Succesors ===
next: v92 
=== Usages ===
=== Predecessor ===
v88 >@ <|@
instruction <@Begin|@org.graalvm.compiler.nodes.BeginNode>@ #next: v92  <|@  <|@
f <@~|@floating>@ <|@
tid v44 <|@
d <@d|@=== Debug Properties ===
condition: LT
nodeSourcePosition: at java.nio.Buffer.position(Buffer.java:243) [bci: 5]
at java.nio.Buffer.<init>(Buffer.java:202) [bci: 61]
op: org.graalvm.compiler.nodes.calc.IntegerLessThanNode$LessThanOp@33a89f26
stamp: void
unorderedIsTrue: false
=== Inputs ===
x: i4 
y: i3 
=== Succesors ===
=== Usages ===
v92 
=== Predecessor ===
- >@ <|@
instruction <@<|@org.graalvm.compiler.nodes.calc.IntegerLessThanNode>@ x: i4 y: i3  <|@  <|@
f <@*|@fixed>@ <|@
tid v92 <|@
d <@d|@=== Debug Properties ===
nodeSourcePosition: at java.nio.Buffer.position(Buffer.java:243) [bci: 5]
at java.nio.Buffer.<init>(Buffer.java:202) [bci: 61]
stamp: void
trueSuccessorProbability: 0.0
=== Inputs ===
condition: v44 
=== Succesors ===
trueSuccessor: v91 
falseSuccessor: v89 
=== Usages ===
=== Predecessor ===
v85 >@ <|@
instruction <@If|@org.graalvm.compiler.nodes.IfNode>@ condition: v44 #trueSuccessor: v91 #falseSuccessor: v89  <|@  <|@
    end_IR
  end_block
  begin_block
    name "B7"
    from_bci -1
    to_bci -1
    predecessors "B6" 
    successors "B13" 
    xhandlers
    flags 
    probability 2355382605114769408
    begin_IR
      HIR
f <@#|@fixed with next>@ <|@
tid v91 <|@
d <@d|@=== Debug Properties ===
nodeSourcePosition: at java.nio.Buffer.position(Buffer.java:243) [bci: 5]
at java.nio.Buffer.<init>(Buffer.java:202) [bci: 61]
stamp: void
=== Inputs ===
=== Succesors ===
next: v112 
=== Usages ===
=== Predecessor ===
v92 >@ <|@
instruction <@Begin|@org.graalvm.compiler.nodes.BeginNode>@ #next: v112  <|@  <|@
f <@~|@floating>@ <|@
tid i113 <|@
d <@d|@=== Debug Properties ===
isDefaultStable: false
rawvalue: -18707
stableDimension: 0
stamp: i32 [-18707] ⇊00000000ffffb6ed ⇈00000000ffffb6ed
stampKind: i32
value: int[-18707|0xffffffffffffb6ed]
=== Inputs ===
=== Succesors ===
=== Usages ===
i105 
=== Predecessor ===
- >@ <|@
instruction <@Constant|@org.graalvm.compiler.nodes.ConstantNode>@  <|@  <|@
f <@*|@fixed>@ <|@
tid v112 <|@
d <@d|@=== Debug Properties ===
stamp: void
=== Inputs ===
=== Succesors ===
=== Usages ===
v101 
=== Predecessor ===
v91 >@ <|@
instruction <@EndNode|@org.graalvm.compiler.nodes.EndNode>@  <|@  <|@
    end_IR
  end_block
  begin_block
    name "B8"
    from_bci -1
    to_bci -1
    predecessors "B6" 
    successors "B9" "B10" 
    xhandlers
    flags 
    probability 4607182418800017408
    begin_IR
      HIR
f <@#|@fixed with next>@ <|@
tid v89 <|@
d <@d|@=== Debug Properties ===
nodeSourcePosition: at java.nio.Buffer.position(Buffer.java:243) [bci: 5]
at java.nio.Buffer.<init>(Buffer.java:202) [bci: 61]
stamp: void
=== Inputs ===
=== Succesors ===
next: v96 
=== Usages ===
=== Predecessor ===
v92 >@ <|@
instruction <@Begin|@org.graalvm.compiler.nodes.BeginNode>@ #next: v96  <|@  <|@
f <@~|@floating>@ <|@
tid v46 <|@
d <@d|@=== Debug Properties ===
condition: LT
nodeSourcePosition: at java.nio.Buffer.position(Buffer.java:243) [bci: 9]
at java.nio.Buffer.<init>(Buffer.java:202) [bci: 61]
op: org.graalvm.compiler.nodes.calc.IntegerLessThanNode$LessThanOp@33a89f26
stamp: void
unorderedIsTrue: false
=== Inputs ===
x: i3 
y: i10 
=== Succesors ===
=== Usages ===
v96 
=== Predecessor ===
- >@ <|@
instruction <@<|@org.graalvm.compiler.nodes.calc.IntegerLessThanNode>@ x: i3 y: i10  <|@  <|@
f <@*|@fixed>@ <|@
tid v96 <|@
d <@d|@=== Debug Properties ===
nodeSourcePosition: at java.nio.Buffer.position(Buffer.java:243) [bci: 9]
at java.nio.Buffer.<init>(Buffer.java:202) [bci: 61]
stamp: void
trueSuccessorProbability: 0.0
=== Inputs ===
condition: v46 
=== Succesors ===
trueSuccessor: v95 
falseSuccessor: v93 
=== Usages ===
=== Predecessor ===
v89 >@ <|@
instruction <@If|@org.graalvm.compiler.nodes.IfNode>@ condition: v46 #trueSuccessor: v95 #falseSuccessor: v93  <|@  <|@
    end_IR
  end_block
  begin_block
    name "B9"
    from_bci -1
    to_bci -1
    predecessors "B8" 
    successors "B13" 
    xhandlers
    flags 
    probability 2355382605114769408
    begin_IR
      HIR
f <@#|@fixed with next>@ <|@
tid v95 <|@
d <@d|@=== Debug Properties ===
nodeSourcePosition: at java.nio.Buffer.position(Buffer.java:243) [bci: 9]
at java.nio.Buffer.<init>(Buffer.java:202) [bci: 61]
stamp: void
=== Inputs ===
=== Succesors ===
next: v114 
=== Usages ===
=== Predecessor ===
v96 >@ <|@
instruction <@Begin|@org.graalvm.compiler.nodes.BeginNode>@ #next: v114  <|@  <|@
f <@~|@floating>@ <|@
tid i115 <|@
d <@d|@=== Debug Properties ===
isDefaultStable: false
rawvalue: -18963
stableDimension: 0
stamp: i32 [-18963] ⇊00000000ffffb5ed ⇈00000000ffffb5ed
stampKind: i32
value: int[-18963|0xffffffffffffb5ed]
=== Inputs ===
=== Succesors ===
=== Usages ===
i105 
=== Predecessor ===
- >@ <|@
instruction <@Constant|@org.graalvm.compiler.nodes.ConstantNode>@  <|@  <|@
f <@*|@fixed>@ <|@
tid v114 <|@
d <@d|@=== Debug Properties ===
stamp: void
=== Inputs ===
=== Succesors ===
=== Usages ===
v101 
=== Predecessor ===
v95 >@ <|@
instruction <@EndNode|@org.graalvm.compiler.nodes.EndNode>@  <|@  <|@
    end_IR
  end_block
  begin_block
    name "B10"
    from_bci -1
    to_bci -1
    predecessors "B8" 
    successors "B11" "B12" 
    xhandlers
    flags 
    probability 4607182418800017408
    begin_IR
      HIR
f <@#|@fixed with next>@ <|@
tid v93 <|@
d <@d|@=== Debug Properties ===
nodeSourcePosition: at java.nio.Buffer.position(Buffer.java:243) [bci: 9]
at java.nio.Buffer.<init>(Buffer.java:202) [bci: 61]
stamp: void
=== Inputs ===
=== Succesors ===
next: v100 
=== Usages ===
=== Predecessor ===
v96 >@ <|@
instruction <@Begin|@org.graalvm.compiler.nodes.BeginNode>@ #next: v100  <|@  <|@
f <@~|@floating>@ <|@
tid v23 <|@
d <@d|@=== Debug Properties ===
condition: LT
nodeSourcePosition: at java.nio.Buffer.<init>(Buffer.java:203) [bci: 66]
op: org.graalvm.compiler.nodes.calc.IntegerLessThanNode$LessThanOp@33a89f26
stamp: void
unorderedIsTrue: false
=== Inputs ===
x: i2 
y: i10 
=== Succesors ===
=== Usages ===
v100 
=== Predecessor ===
- >@ <|@
instruction <@<|@org.graalvm.compiler.nodes.calc.IntegerLessThanNode>@ x: i2 y: i10  <|@  <|@
f <@*|@fixed>@ <|@
tid v100 <|@
d <@d|@=== Debug Properties ===
nodeSourcePosition: at java.nio.Buffer.<init>(Buffer.java:203) [bci: 66]
stamp: void
trueSuccessorProbability: 1.0
=== Inputs ===
condition: v23 
=== Succesors ===
trueSuccessor: v97 
falseSuccessor: v99 
=== Usages ===
=== Predecessor ===
v93 >@ <|@
instruction <@If|@org.graalvm.compiler.nodes.IfNode>@ condition: v23 #trueSuccessor: v97 #falseSuccessor: v99  <|@  <|@
    end_IR
  end_block
  begin_block
    name "B11"
    from_bci -1
    to_bci -1
    predecessors "B10" 
    successors 
    xhandlers
    flags 
    probability 4607182418800017408
    begin_IR
      HIR
f <@#|@fixed with next>@ <|@
tid v97 <|@
d <@d|@=== Debug Properties ===
nodeSourcePosition: at java.nio.Buffer.<init>(Buffer.java:203) [bci: 66]
stamp: void
=== Inputs ===
=== Succesors ===
next: v60 
=== Usages ===
=== Predecessor ===
v100 >@ <|@
instruction <@Begin|@org.graalvm.compiler.nodes.BeginNode>@ #next: v60  <|@  <|@
f <@~|@floating>@ <|@
tid v118 <|@
d <@d|@=== Debug Properties ===
displacement: 12
scale: Times1
stamp: void*
=== Inputs ===
base: a1 
index: - 
=== Succesors ===
=== Usages ===
v60 
=== Predecessor ===
- >@ <|@
instruction <@AMD64Address|@org.graalvm.compiler.core.amd64.AMD64AddressNode>@ base: a1 index: -  <|@  <|@
f <@~|@floating>@ <|@
tid i7 <|@
d <@d|@=== Debug Properties ===
isDefaultStable: false
nodeSourcePosition: at java.nio.Buffer.<init>(Buffer.java:185) [bci: 5]
rawvalue: -1
stableDimension: 0
stamp: i32 [-1] ⇊00000000ffffffff
stampKind: i32
value: int[-1|0xffffffffffffffff]
=== Inputs ===
=== Succesors ===
=== Usages ===
v60 
=== Predecessor ===
- >@ <|@
instruction <@Constant|@org.graalvm.compiler.nodes.ConstantNode>@  <|@  <|@
f <@#|@fixed with next>@ <|@
tid v60 <|@
d <@d|@=== Debug Properties ===
barrierType: NONE
location: Buffer.mark
nodeSourcePosition: at java.nio.Buffer.<init>(Buffer.java:185) [bci: 6]
nullCheck: false
stamp: void
=== Inputs ===
stateBefore: - 
guard: - 
address: v118 
value: i7 
stateAfter: - 
lastLocationAccess: - 
=== Succesors ===
next: v63 
=== Usages ===
=== Predecessor ===
v97 >@ <|@
instruction <@Write|@org.graalvm.compiler.nodes.memory.WriteNode>@ stateBefore: - guard: - address: v118 value: i7 stateAfter: - lastLocationAccess: - #next: v63  <|@  <|@
f <@~|@floating>@ <|@
tid v119 <|@
d <@d|@=== Debug Properties ===
displacement: 24
scale: Times1
stamp: void*
=== Inputs ===
base: a1 
index: - 
=== Succesors ===
=== Usages ===
v63 v75 
=== Predecessor ===
- >@ <|@
instruction <@AMD64Address|@org.graalvm.compiler.core.amd64.AMD64AddressNode>@ base: a1 index: -  <|@  <|@
f <@#|@fixed with next>@ <|@
tid v63 <|@
d <@d|@=== Debug Properties ===
barrierType: NONE
location: Buffer.position
nodeSourcePosition: at java.nio.Buffer.<init>(Buffer.java:186) [bci: 11]
nullCheck: false
stamp: void
=== Inputs ===
stateBefore: - 
guard: - 
address: v119 
value: i10 
stateAfter: - 
lastLocationAccess: - 
=== Succesors ===
next: v67 
=== Usages ===
=== Predecessor ===
v60 >@ <|@
instruction <@Write|@org.graalvm.compiler.nodes.memory.WriteNode>@ stateBefore: - guard: - address: v119 value: i10 stateAfter: - lastLocationAccess: - #next: v67  <|@  <|@
f <@~|@floating>@ <|@
tid v120 <|@
d <@d|@=== Debug Properties ===
displacement: 32
scale: Times1
stamp: void*
=== Inputs ===
base: a1 
index: - 
=== Succesors ===
=== Usages ===
v67 
=== Predecessor ===
- >@ <|@
instruction <@AMD64Address|@org.graalvm.compiler.core.amd64.AMD64AddressNode>@ base: a1 index: -  <|@  <|@
f <@#|@fixed with next>@ <|@
tid v67 <|@
d <@d|@=== Debug Properties ===
barrierType: NONE
location: Buffer.capacity
nodeSourcePosition: at java.nio.Buffer.<init>(Buffer.java:200) [bci: 50]
nullCheck: false
stamp: void
=== Inputs ===
stateBefore: - 
guard: - 
address: v120 
value: i5 
stateAfter: - 
lastLocationAccess: - 
=== Succesors ===
next: v72 
=== Usages ===
=== Predecessor ===
v63 >@ <|@
instruction <@Write|@org.graalvm.compiler.nodes.memory.WriteNode>@ stateBefore: - guard: - address: v120 value: i5 stateAfter: - lastLocationAccess: - #next: v72  <|@  <|@
f <@~|@floating>@ <|@
tid v121 <|@
d <@d|@=== Debug Properties ===
displacement: 28
scale: Times1
stamp: void*
=== Inputs ===
base: a1 
index: - 
=== Succesors ===
=== Usages ===
v72 
=== Predecessor ===
- >@ <|@
instruction <@AMD64Address|@org.graalvm.compiler.core.amd64.AMD64AddressNode>@ base: a1 index: -  <|@  <|@
f <@#|@fixed with next>@ <|@
tid v72 <|@
d <@d|@=== Debug Properties ===
barrierType: NONE
location: Buffer.limit
nodeSourcePosition: at java.nio.Buffer.limit(Buffer.java:276) [bci: 22]
at java.nio.Buffer.<init>(Buffer.java:201) [bci: 55]
nullCheck: false
stamp: void
=== Inputs ===
stateBefore: - 
guard: - 
address: v121 
value: i4 
stateAfter: - 
lastLocationAccess: - 
=== Succesors ===
next: v75 
=== Usages ===
=== Predecessor ===
v67 >@ <|@
instruction <@Write|@org.graalvm.compiler.nodes.memory.WriteNode>@ stateBefore: - guard: - address: v121 value: i4 stateAfter: - lastLocationAccess: - #next: v75  <|@  <|@
f <@#|@fixed with next>@ <|@
tid v75 <|@
d <@d|@=== Debug Properties ===
barrierType: NONE
location: Buffer.position
nodeSourcePosition: at java.nio.Buffer.position(Buffer.java:245) [bci: 22]
at java.nio.Buffer.<init>(Buffer.java:202) [bci: 61]
nullCheck: false
stamp: void
=== Inputs ===
stateBefore: - 
guard: - 
address: v119 
value: i3 
stateAfter: - 
lastLocationAccess: - 
=== Succesors ===
next: v25 
=== Usages ===
=== Predecessor ===
v72 >@ <|@
instruction <@Write|@org.graalvm.compiler.nodes.memory.WriteNode>@ stateBefore: - guard: - address: v119 value: i3 stateAfter: - lastLocationAccess: - #next: v25  <|@  <|@
f <@*|@fixed>@ <|@
tid v25 <|@
d <@d|@=== Debug Properties ===
nodeSourcePosition: at java.nio.Buffer.<init>(Buffer.java:209) [bci: 120]
stamp: void
=== Inputs ===
result: - 
memoryMap: - 
=== Succesors ===
=== Usages ===
=== Predecessor ===
v75 >@ <|@
instruction <@Return|@org.graalvm.compiler.nodes.ReturnNode>@ result: - memoryMap: -  <|@  <|@
    end_IR
  end_block
  begin_block
    name "B12"
    from_bci -1
    to_bci -1
    predecessors "B10" 
    successors "B13" 
    xhandlers
    flags 
    probability 2355382605114769408
    begin_IR
      HIR
f <@#|@fixed with next>@ <|@
tid v99 <|@
d <@d|@=== Debug Properties ===
nodeSourcePosition: at java.nio.Buffer.<init>(Buffer.java:203) [bci: 66]
stamp: void
=== Inputs ===
=== Succesors ===
next: v116 
=== Usages ===
=== Predecessor ===
v100 >@ <|@
instruction <@Begin|@org.graalvm.compiler.nodes.BeginNode>@ #next: v116  <|@  <|@
f <@~|@floating>@ <|@
tid i117 <|@
d <@d|@=== Debug Properties ===
isDefaultStable: false
rawvalue: -19475
stableDimension: 0
stamp: i32 [-19475] ⇊00000000ffffb3ed ⇈00000000ffffb3ed
stampKind: i32
value: int[-19475|0xffffffffffffb3ed]
=== Inputs ===
=== Succesors ===
=== Usages ===
i105 
=== Predecessor ===
- >@ <|@
instruction <@Constant|@org.graalvm.compiler.nodes.ConstantNode>@  <|@  <|@
f <@*|@fixed>@ <|@
tid v116 <|@
d <@d|@=== Debug Properties ===
stamp: void
=== Inputs ===
=== Succesors ===
=== Usages ===
v101 
=== Predecessor ===
v99 >@ <|@
instruction <@EndNode|@org.graalvm.compiler.nodes.EndNode>@  <|@  <|@
    end_IR
  end_block
  begin_block
    name "B13"
    from_bci -1
    to_bci -1
    predecessors "B1" "B3" "B5" "B7" "B9" "B12" 
    successors 
    xhandlers
    flags 
    probability 2366641604183195648
    begin_IR
      HIR
f <@~|@floating>@ <|@
tid i105 <|@
d <@d|@=== Debug Properties ===
stamp: i32 [-19475 - -16403] ⇊00000000ffffb0ed ⇈00000000ffffbfed
valueDescription: i32
=== Inputs ===
merge: v101 
values: i103 i109 i111 i113 i115 i117 
=== Succesors ===
=== Usages ===
v107 
=== Predecessor ===
- >@ <|@
instruction <@ValuePhi|@org.graalvm.compiler.nodes.ValuePhiNode>@ merge: v101 values: i103 i109 i111 i113 i115 i117  <|@  <|@
f <@#|@fixed with next>@ <|@
tid v101 <|@
d <@d|@=== Debug Properties ===
stamp: void
=== Inputs ===
stateAfter: - 
ends: v102 v108 v110 v112 v114 v116 
=== Succesors ===
next: v107 
=== Usages ===
i105 
=== Predecessor ===
- >@ <|@
instruction <@Merge|@org.graalvm.compiler.nodes.MergeNode>@ stateAfter: - ends: v102 v108 v110 v112 v114 v116 #next: v107  <|@  <|@
f <@~|@floating>@ <|@
tid a104 <|@
d <@d|@=== Debug Properties ===
isDefaultStable: false
rawvalue: null
stableDimension: 0
stamp: a - NULL
stampKind: a -
value: Object[null]
=== Inputs ===
=== Succesors ===
=== Usages ===
v107 
=== Predecessor ===
- >@ <|@
instruction <@Constant|@org.graalvm.compiler.nodes.ConstantNode>@  <|@  <|@
tid ?6 <|@
d <@d|@=== Debug Properties ===
bci: 0
code: ResolvedJavaMethodBytecode<Buffer.<init>(int, int, int, int)>
duringCall: false
localsSize: 5
locksSize: 0
rethrowException: false
sourceFile: Buffer.java
sourceLine: 197
stackSize: 0
=== Inputs ===
outerFrameState: - 
values: a1 i2 i3 i4 i5 
=== Succesors ===
=== Usages ===
v107 
=== Predecessor ===
- >@ <|@
instruction <@FrameState|@org.graalvm.compiler.nodes.FrameState>@ outerFrameState: - values: a1 i2 i3 i4 i5  <|@  <|@
f <@*|@fixed>@ <|@
tid v107 <|@
d <@d|@=== Debug Properties ===
stamp: void
=== Inputs ===
stateBefore: ?6 
actionAndReason: i105 
speculation: a104 
=== Succesors ===
=== Usages ===
=== Predecessor ===
v101 >@ <|@
instruction <@DynamicDeoptimize|@org.graalvm.compiler.nodes.DynamicDeoptimizeNode>@ stateBefore: ?6 actionAndReason: i105 speculation: a104  <|@  <|@
    end_IR
  end_block
end_cfg
begin_cfg
  name "After LIR generation"
  begin_block
    name "B0"
    from_bci -1
    to_bci -1
    predecessors 
    successors "B1" "B2" 
    xhandlers
    flags 
    probability 4607182418800017408
    begin_IR
      HIR
f <@#|@fixed with next>@ <|@
tid v0 <|@
d <@d|@=== Debug Properties ===
stamp: void
=== Inputs ===
stateAfter: - 
=== Succesors ===
next: v80 
=== Usages ===
=== Predecessor ===
- >@ <|@
instruction <@StartNode|@org.graalvm.compiler.nodes.StartNode>@ stateAfter: - #next: v80  <|@  <|@
f <@~|@floating>@ <|@
tid a1 <|@
result v0|QWORD[.] <|@
d <@d|@=== Debug Properties ===
index: 0
stamp: a! Ljava/nio/Buffer;
uncheckedStamp: [null]
=== Inputs ===
=== Succesors ===
=== Usages ===
?6 v118 v120 v119 v121 
=== Predecessor ===
- >@ <|@
instruction <@Parameter|@org.graalvm.compiler.nodes.ParameterNode>@  <|@  <|@
f <@~|@floating>@ <|@
tid i2 <|@
result v1|DWORD <|@
d <@d|@=== Debug Properties ===
index: 1
stamp: i32
uncheckedStamp: [null]
=== Inputs ===
=== Succesors ===
=== Usages ===
?6 v23 
=== Predecessor ===
- >@ <|@
instruction <@Parameter|@org.graalvm.compiler.nodes.ParameterNode>@  <|@  <|@
f <@~|@floating>@ <|@
tid i3 <|@
result v2|DWORD <|@
d <@d|@=== Debug Properties ===
index: 2
stamp: i32
uncheckedStamp: [null]
=== Inputs ===
=== Succesors ===
=== Usages ===
?6 v75 v46 v44 
=== Predecessor ===
- >@ <|@
instruction <@Parameter|@org.graalvm.compiler.nodes.ParameterNode>@  <|@  <|@
f <@~|@floating>@ <|@
tid i4 <|@
result v3|DWORD <|@
d <@d|@=== Debug Properties ===
index: 3
stamp: i32
uncheckedStamp: [null]
=== Inputs ===
=== Succesors ===
=== Usages ===
?6 v44 v72 v29 v27 
=== Predecessor ===
- >@ <|@
instruction <@Parameter|@org.graalvm.compiler.nodes.ParameterNode>@  <|@  <|@
f <@~|@floating>@ <|@
tid i5 <|@
result v4|DWORD <|@
d <@d|@=== Debug Properties ===
index: 4
stamp: i32
uncheckedStamp: [null]
=== Inputs ===
=== Succesors ===
=== Usages ===
?6 v27 v67 v13 
=== Predecessor ===
- >@ <|@
instruction <@Parameter|@org.graalvm.compiler.nodes.ParameterNode>@  <|@  <|@
f <@~|@floating>@ <|@
tid i10 <|@
result int[0|0x0] <|@
d <@d|@=== Debug Properties ===
isDefaultStable: false
nodeSourcePosition: at java.nio.Buffer.<init>(Buffer.java:186) [bci: 10]
rawvalue: 0
stableDimension: 0
stamp: i32 [0] ⇈0000000000000000
stampKind: i32
value: int[0|0x0]
=== Inputs ===
=== Succesors ===
=== Usages ===
v63 v13 v23 v29 v46 
=== Predecessor ===
- >@ <|@
instruction <@Constant|@org.graalvm.compiler.nodes.ConstantNode>@  <|@  <|@
f <@~|@floating>@ <|@
tid v13 <|@
d <@d|@=== Debug Properties ===
condition: LT
nodeSourcePosition: at java.nio.Buffer.<init>(Buffer.java:198) [bci: 16]
op: org.graalvm.compiler.nodes.calc.IntegerLessThanNode$LessThanOp@33a89f26
stamp: void
unorderedIsTrue: false
=== Inputs ===
x: i5 
y: i10 
=== Succesors ===
=== Usages ===
v80 
=== Predecessor ===
- >@ <|@
instruction <@<|@org.graalvm.compiler.nodes.calc.IntegerLessThanNode>@ x: i5 y: i10  <|@  <|@
f <@*|@fixed>@ <|@
tid v80 <|@
d <@d|@=== Debug Properties ===
nodeSourcePosition: at java.nio.Buffer.<init>(Buffer.java:198) [bci: 16]
stamp: void
trueSuccessorProbability: 0.0
=== Inputs ===
condition: v13 
=== Succesors ===
trueSuccessor: v79 
falseSuccessor: v77 
=== Usages ===
=== Predecessor ===
v0 >@ <|@
instruction <@If|@org.graalvm.compiler.nodes.IfNode>@ condition: v13 #trueSuccessor: v79 #falseSuccessor: v77  <|@  <|@
    end_IR
    begin_IR
      LIR
      nr   -1  <|@ instruction [rsi|QWORD[.], rdx|DWORD, rcx|DWORD, r8|DWORD, r9|DWORD, rbp|QWORD] = LABEL numbPhis: 0 align: false label: ? <|@ <|@
      nr   -1  <|@ instruction stack:16|QWORD = MOVE rbp|QWORD moveKind: QWORD <|@ <|@
      nr   -1  <|@ instruction [] = HOTSPOTLOCKSTACK frameMapBuilder: org.graalvm.compiler.lir.amd64.AMD64FrameMapBuilder@69596961 slotKind: QWORD <|@ <|@
      nr   -1  <|@ instruction v0|QWORD[.] = MOVE rsi|QWORD[.] moveKind: QWORD <|@ <|@
      nr   -1  <|@ instruction v1|DWORD = MOVE rdx|DWORD moveKind: DWORD <|@ <|@
      nr   -1  <|@ instruction v2|DWORD = MOVE rcx|DWORD moveKind: DWORD <|@ <|@
      nr   -1  <|@ instruction v3|DWORD = MOVE r8|DWORD moveKind: DWORD <|@ <|@
      nr   -1  <|@ instruction v4|DWORD = MOVE r9|DWORD moveKind: DWORD <|@ <|@
      nr   -1  <|@ instruction TEST (x: v4|DWORD, y: v4|DWORD) size: DWORD <|@ <|@
      nr   -1  <|@ instruction BRANCH trueDestinationProbability: 0.0 condition: < trueDestination: B0 -> B1 falseDestination: B0 -> B2 <|@ <|@
    end_IR
  end_block
  begin_block
    name "B1"
    from_bci -1
    to_bci -1
    predecessors "B0" 
    successors "B13" 
    xhandlers
    flags 
    probability 2355382605114769408
    begin_IR
      HIR
f <@#|@fixed with next>@ <|@
tid v79 <|@
d <@d|@=== Debug Properties ===
nodeSourcePosition: at java.nio.Buffer.<init>(Buffer.java:198) [bci: 16]
stamp: void
=== Inputs ===
=== Succesors ===
next: v102 
=== Usages ===
=== Predecessor ===
v80 >@ <|@
instruction <@Begin|@org.graalvm.compiler.nodes.BeginNode>@ #next: v102  <|@  <|@
f <@~|@floating>@ <|@
tid i103 <|@
result int[-16403|0xffffffffffffbfed] <|@
d <@d|@=== Debug Properties ===
isDefaultStable: false
rawvalue: -16403
stableDimension: 0
stamp: i32 [-16403] ⇊00000000ffffbfed ⇈00000000ffffbfed
stampKind: i32
value: int[-16403|0xffffffffffffbfed]
=== Inputs ===
=== Succesors ===
=== Usages ===
i105 
=== Predecessor ===
- >@ <|@
instruction <@Constant|@org.graalvm.compiler.nodes.ConstantNode>@  <|@  <|@
f <@*|@fixed>@ <|@
tid v102 <|@
d <@d|@=== Debug Properties ===
stamp: void
=== Inputs ===
=== Succesors ===
=== Usages ===
v101 
=== Predecessor ===
v79 >@ <|@
instruction <@EndNode|@org.graalvm.compiler.nodes.EndNode>@  <|@  <|@
    end_IR
    begin_IR
      LIR
      nr   -1  <|@ instruction [] = LABEL numbPhis: 0 align: false label: ? <|@ <|@
      nr   -1  <|@ instruction JUMP ~[int[-16403|0xffffffffffffbfed]] destination: B1 -> B13 <|@ <|@
    end_IR
  end_block
  begin_block
    name "B2"
    from_bci -1
    to_bci -1
    predecessors "B0" 
    successors "B3" "B4" 
    xhandlers
    flags 
    probability 4607182418800017408
    begin_IR
      HIR
f <@#|@fixed with next>@ <|@
tid v77 <|@
d <@d|@=== Debug Properties ===
nodeSourcePosition: at java.nio.Buffer.<init>(Buffer.java:198) [bci: 16]
stamp: void
=== Inputs ===
=== Succesors ===
next: v84 
=== Usages ===
=== Predecessor ===
v80 >@ <|@
instruction <@Begin|@org.graalvm.compiler.nodes.BeginNode>@ #next: v84  <|@  <|@
f <@~|@floating>@ <|@
tid v27 <|@
d <@d|@=== Debug Properties ===
condition: LT
nodeSourcePosition: at java.nio.Buffer.limit(Buffer.java:274) [bci: 5]
at java.nio.Buffer.<init>(Buffer.java:201) [bci: 55]
op: org.graalvm.compiler.nodes.calc.IntegerLessThanNode$LessThanOp@33a89f26
stamp: void
unorderedIsTrue: false
=== Inputs ===
x: i5 
y: i4 
=== Succesors ===
=== Usages ===
v84 
=== Predecessor ===
- >@ <|@
instruction <@<|@org.graalvm.compiler.nodes.calc.IntegerLessThanNode>@ x: i5 y: i4  <|@  <|@
f <@*|@fixed>@ <|@
tid v84 <|@
d <@d|@=== Debug Properties ===
nodeSourcePosition: at java.nio.Buffer.limit(Buffer.java:274) [bci: 5]
at java.nio.Buffer.<init>(Buffer.java:201) [bci: 55]
stamp: void
trueSuccessorProbability: 0.0
=== Inputs ===
condition: v27 
=== Succesors ===
trueSuccessor: v83 
falseSuccessor: v81 
=== Usages ===
=== Predecessor ===
v77 >@ <|@
instruction <@If|@org.graalvm.compiler.nodes.IfNode>@ condition: v27 #trueSuccessor: v83 #falseSuccessor: v81  <|@  <|@
    end_IR
    begin_IR
      LIR
      nr   -1  <|@ instruction [] = LABEL numbPhis: 0 align: false label: ? <|@ <|@
      nr   -1  <|@ instruction CMP (x: v3|DWORD, y: v4|DWORD) size: DWORD <|@ <|@
      nr   -1  <|@ instruction BRANCH trueDestinationProbability: 0.0 condition: > trueDestination: B2 -> B3 falseDestination: B2 -> B4 <|@ <|@
    end_IR
  end_block
  begin_block
    name "B3"
    from_bci -1
    to_bci -1
    predecessors "B2" 
    successors "B13" 
    xhandlers
    flags 
    probability 2355382605114769408
    begin_IR
      HIR
f <@#|@fixed with next>@ <|@
tid v83 <|@
d <@d|@=== Debug Properties ===
nodeSourcePosition: at java.nio.Buffer.limit(Buffer.java:274) [bci: 5]
at java.nio.Buffer.<init>(Buffer.java:201) [bci: 55]
stamp: void
=== Inputs ===
=== Succesors ===
next: v108 
=== Usages ===
=== Predecessor ===
v84 >@ <|@
instruction <@Begin|@org.graalvm.compiler.nodes.BeginNode>@ #next: v108  <|@  <|@
f <@~|@floating>@ <|@
tid i109 <|@
result int[-17427|0xffffffffffffbbed] <|@
d <@d|@=== Debug Properties ===
isDefaultStable: false
rawvalue: -17427
stableDimension: 0
stamp: i32 [-17427] ⇊00000000ffffbbed ⇈00000000ffffbbed
stampKind: i32
value: int[-17427|0xffffffffffffbbed]
=== Inputs ===
=== Succesors ===
=== Usages ===
i105 
=== Predecessor ===
- >@ <|@
instruction <@Constant|@org.graalvm.compiler.nodes.ConstantNode>@  <|@  <|@
f <@*|@fixed>@ <|@
tid v108 <|@
d <@d|@=== Debug Properties ===
stamp: void
=== Inputs ===
=== Succesors ===
=== Usages ===
v101 
=== Predecessor ===
v83 >@ <|@
instruction <@EndNode|@org.graalvm.compiler.nodes.EndNode>@  <|@  <|@
    end_IR
    begin_IR
      LIR
      nr   -1  <|@ instruction [] = LABEL numbPhis: 0 align: false label: ? <|@ <|@
      nr   -1  <|@ instruction JUMP ~[int[-17427|0xffffffffffffbbed]] destination: B3 -> B13 <|@ <|@
    end_IR
  end_block
  begin_block
    name "B4"
    from_bci -1
    to_bci -1
    predecessors "B2" 
    successors "B5" "B6" 
    xhandlers
    flags 
    probability 4607182418800017408
    begin_IR
      HIR
f <@#|@fixed with next>@ <|@
tid v81 <|@
d <@d|@=== Debug Properties ===
nodeSourcePosition: at java.nio.Buffer.limit(Buffer.java:274) [bci: 5]
at java.nio.Buffer.<init>(Buffer.java:201) [bci: 55]
stamp: void
=== Inputs ===
=== Succesors ===
next: v88 
=== Usages ===
=== Predecessor ===
v84 >@ <|@
instruction <@Begin|@org.graalvm.compiler.nodes.BeginNode>@ #next: v88  <|@  <|@
f <@~|@floating>@ <|@
tid v29 <|@
d <@d|@=== Debug Properties ===
condition: LT
nodeSourcePosition: at java.nio.Buffer.limit(Buffer.java:274) [bci: 9]
at java.nio.Buffer.<init>(Buffer.java:201) [bci: 55]
op: org.graalvm.compiler.nodes.calc.IntegerLessThanNode$LessThanOp@33a89f26
stamp: void
unorderedIsTrue: false
=== Inputs ===
x: i4 
y: i10 
=== Succesors ===
=== Usages ===
v88 
=== Predecessor ===
- >@ <|@
instruction <@<|@org.graalvm.compiler.nodes.calc.IntegerLessThanNode>@ x: i4 y: i10  <|@  <|@
f <@*|@fixed>@ <|@
tid v88 <|@
d <@d|@=== Debug Properties ===
nodeSourcePosition: at java.nio.Buffer.limit(Buffer.java:274) [bci: 9]
at java.nio.Buffer.<init>(Buffer.java:201) [bci: 55]
stamp: void
trueSuccessorProbability: 0.0
=== Inputs ===
condition: v29 
=== Succesors ===
trueSuccessor: v87 
falseSuccessor: v85 
=== Usages ===
=== Predecessor ===
v81 >@ <|@
instruction <@If|@org.graalvm.compiler.nodes.IfNode>@ condition: v29 #trueSuccessor: v87 #falseSuccessor: v85  <|@  <|@
    end_IR
    begin_IR
      LIR
      nr   -1  <|@ instruction [] = LABEL numbPhis: 0 align: false label: ? <|@ <|@
      nr   -1  <|@ instruction TEST (x: v3|DWORD, y: v3|DWORD) size: DWORD <|@ <|@
      nr   -1  <|@ instruction BRANCH trueDestinationProbability: 0.0 condition: < trueDestination: B4 -> B5 falseDestination: B4 -> B6 <|@ <|@
    end_IR
  end_block
  begin_block
    name "B5"
    from_bci -1
    to_bci -1
    predecessors "B4" 
    successors "B13" 
    xhandlers
    flags 
    probability 2355382605114769408
    begin_IR
      HIR
f <@#|@fixed with next>@ <|@
tid v87 <|@
d <@d|@=== Debug Properties ===
nodeSourcePosition: at java.nio.Buffer.limit(Buffer.java:274) [bci: 9]
at java.nio.Buffer.<init>(Buffer.java:201) [bci: 55]
stamp: void
=== Inputs ===
=== Succesors ===
next: v110 
=== Usages ===
=== Predecessor ===
v88 >@ <|@
instruction <@Begin|@org.graalvm.compiler.nodes.BeginNode>@ #next: v110  <|@  <|@
f <@~|@floating>@ <|@
tid i111 <|@
result int[-17683|0xffffffffffffbaed] <|@
d <@d|@=== Debug Properties ===
isDefaultStable: false
rawvalue: -17683
stableDimension: 0
stamp: i32 [-17683] ⇊00000000ffffbaed ⇈00000000ffffbaed
stampKind: i32
value: int[-17683|0xffffffffffffbaed]
=== Inputs ===
=== Succesors ===
=== Usages ===
i105 
=== Predecessor ===
- >@ <|@
instruction <@Constant|@org.graalvm.compiler.nodes.ConstantNode>@  <|@  <|@
f <@*|@fixed>@ <|@
tid v110 <|@
d <@d|@=== Debug Properties ===
stamp: void
=== Inputs ===
=== Succesors ===
=== Usages ===
v101 
=== Predecessor ===
v87 >@ <|@
instruction <@EndNode|@org.graalvm.compiler.nodes.EndNode>@  <|@  <|@
    end_IR
    begin_IR
      LIR
      nr   -1  <|@ instruction [] = LABEL numbPhis: 0 align: false label: ? <|@ <|@
      nr   -1  <|@ instruction JUMP ~[int[-17683|0xffffffffffffbaed]] destination: B5 -> B13 <|@ <|@
    end_IR
  end_block
  begin_block
    name "B6"
    from_bci -1
    to_bci -1
    predecessors "B4" 
    successors "B7" "B8" 
    xhandlers
    flags 
    probability 4607182418800017408
    begin_IR
      HIR
f <@#|@fixed with next>@ <|@
tid v85 <|@
d <@d|@=== Debug Properties ===
nodeSourcePosition: at java.nio.Buffer.limit(Buffer.java:274) [bci: 9]
at java.nio.Buffer.<init>(Buffer.java:201) [bci: 55]
stamp: void
=== Inputs ===
=== Succesors ===
next: v92 
=== Usages ===
=== Predecessor ===
v88 >@ <|@
instruction <@Begin|@org.graalvm.compiler.nodes.BeginNode>@ #next: v92  <|@  <|@
f <@~|@floating>@ <|@
tid v44 <|@
d <@d|@=== Debug Properties ===
condition: LT
nodeSourcePosition: at java.nio.Buffer.position(Buffer.java:243) [bci: 5]
at java.nio.Buffer.<init>(Buffer.java:202) [bci: 61]
op: org.graalvm.compiler.nodes.calc.IntegerLessThanNode$LessThanOp@33a89f26
stamp: void
unorderedIsTrue: false
=== Inputs ===
x: i4 
y: i3 
=== Succesors ===
=== Usages ===
v92 
=== Predecessor ===
- >@ <|@
instruction <@<|@org.graalvm.compiler.nodes.calc.IntegerLessThanNode>@ x: i4 y: i3  <|@  <|@
f <@*|@fixed>@ <|@
tid v92 <|@
d <@d|@=== Debug Properties ===
nodeSourcePosition: at java.nio.Buffer.position(Buffer.java:243) [bci: 5]
at java.nio.Buffer.<init>(Buffer.java:202) [bci: 61]
stamp: void
trueSuccessorProbability: 0.0
=== Inputs ===
condition: v44 
=== Succesors ===
trueSuccessor: v91 
falseSuccessor: v89 
=== Usages ===
=== Predecessor ===
v85 >@ <|@
instruction <@If|@org.graalvm.compiler.nodes.IfNode>@ condition: v44 #trueSuccessor: v91 #falseSuccessor: v89  <|@  <|@
    end_IR
    begin_IR
      LIR
      nr   -1  <|@ instruction [] = LABEL numbPhis: 0 align: false label: ? <|@ <|@
      nr   -1  <|@ instruction CMP (x: v2|DWORD, y: v3|DWORD) size: DWORD <|@ <|@
      nr   -1  <|@ instruction BRANCH trueDestinationProbability: 0.0 condition: > trueDestination: B6 -> B7 falseDestination: B6 -> B8 <|@ <|@
    end_IR
  end_block
  begin_block
    name "B7"
    from_bci -1
    to_bci -1
    predecessors "B6" 
    successors "B13" 
    xhandlers
    flags 
    probability 2355382605114769408
    begin_IR
      HIR
f <@#|@fixed with next>@ <|@
tid v91 <|@
d <@d|@=== Debug Properties ===
nodeSourcePosition: at java.nio.Buffer.position(Buffer.java:243) [bci: 5]
at java.nio.Buffer.<init>(Buffer.java:202) [bci: 61]
stamp: void
=== Inputs ===
=== Succesors ===
next: v112 
=== Usages ===
=== Predecessor ===
v92 >@ <|@
instruction <@Begin|@org.graalvm.compiler.nodes.BeginNode>@ #next: v112  <|@  <|@
f <@~|@floating>@ <|@
tid i113 <|@
result int[-18707|0xffffffffffffb6ed] <|@
d <@d|@=== Debug Properties ===
isDefaultStable: false
rawvalue: -18707
stableDimension: 0
stamp: i32 [-18707] ⇊00000000ffffb6ed ⇈00000000ffffb6ed
stampKind: i32
value: int[-18707|0xffffffffffffb6ed]
=== Inputs ===
=== Succesors ===
=== Usages ===
i105 
=== Predecessor ===
- >@ <|@
instruction <@Constant|@org.graalvm.compiler.nodes.ConstantNode>@  <|@  <|@
f <@*|@fixed>@ <|@
tid v112 <|@
d <@d|@=== Debug Properties ===
stamp: void
=== Inputs ===
=== Succesors ===
=== Usages ===
v101 
=== Predecessor ===
v91 >@ <|@
instruction <@EndNode|@org.graalvm.compiler.nodes.EndNode>@  <|@  <|@
    end_IR
    begin_IR
      LIR
      nr   -1  <|@ instruction [] = LABEL numbPhis: 0 align: false label: ? <|@ <|@
      nr   -1  <|@ instruction JUMP ~[int[-18707|0xffffffffffffb6ed]] destination: B7 -> B13 <|@ <|@
    end_IR
  end_block
  begin_block
    name "B8"
    from_bci -1
    to_bci -1
    predecessors "B6" 
    successors "B9" "B10" 
    xhandlers
    flags 
    probability 4607182418800017408
    begin_IR
      HIR
f <@#|@fixed with next>@ <|@
tid v89 <|@
d <@d|@=== Debug Properties ===
nodeSourcePosition: at java.nio.Buffer.position(Buffer.java:243) [bci: 5]
at java.nio.Buffer.<init>(Buffer.java:202) [bci: 61]
stamp: void
=== Inputs ===
=== Succesors ===
next: v96 
=== Usages ===
=== Predecessor ===
v92 >@ <|@
instruction <@Begin|@org.graalvm.compiler.nodes.BeginNode>@ #next: v96  <|@  <|@
f <@~|@floating>@ <|@
tid v46 <|@
d <@d|@=== Debug Properties ===
condition: LT
nodeSourcePosition: at java.nio.Buffer.position(Buffer.java:243) [bci: 9]
at java.nio.Buffer.<init>(Buffer.java:202) [bci: 61]
op: org.graalvm.compiler.nodes.calc.IntegerLessThanNode$LessThanOp@33a89f26
stamp: void
unorderedIsTrue: false
=== Inputs ===
x: i3 
y: i10 
=== Succesors ===
=== Usages ===
v96 
=== Predecessor ===
- >@ <|@
instruction <@<|@org.graalvm.compiler.nodes.calc.IntegerLessThanNode>@ x: i3 y: i10  <|@  <|@
f <@*|@fixed>@ <|@
tid v96 <|@
d <@d|@=== Debug Properties ===
nodeSourcePosition: at java.nio.Buffer.position(Buffer.java:243) [bci: 9]
at java.nio.Buffer.<init>(Buffer.java:202) [bci: 61]
stamp: void
trueSuccessorProbability: 0.0
=== Inputs ===
condition: v46 
=== Succesors ===
trueSuccessor: v95 
falseSuccessor: v93 
=== Usages ===
=== Predecessor ===
v89 >@ <|@
instruction <@If|@org.graalvm.compiler.nodes.IfNode>@ condition: v46 #trueSuccessor: v95 #falseSuccessor: v93  <|@  <|@
    end_IR
    begin_IR
      LIR
      nr   -1  <|@ instruction [] = LABEL numbPhis: 0 align: false label: ? <|@ <|@
      nr   -1  <|@ instruction TEST (x: v2|DWORD, y: v2|DWORD) size: DWORD <|@ <|@
      nr   -1  <|@ instruction BRANCH trueDestinationProbability: 0.0 condition: < trueDestination: B8 -> B9 falseDestination: B8 -> B10 <|@ <|@
    end_IR
  end_block
  begin_block
    name "B9"
    from_bci -1
    to_bci -1
    predecessors "B8" 
    successors "B13" 
    xhandlers
    flags 
    probability 2355382605114769408
    begin_IR
      HIR
f <@#|@fixed with next>@ <|@
tid v95 <|@
d <@d|@=== Debug Properties ===
nodeSourcePosition: at java.nio.Buffer.position(Buffer.java:243) [bci: 9]
at java.nio.Buffer.<init>(Buffer.java:202) [bci: 61]
stamp: void
=== Inputs ===
=== Succesors ===
next: v114 
=== Usages ===
=== Predecessor ===
v96 >@ <|@
instruction <@Begin|@org.graalvm.compiler.nodes.BeginNode>@ #next: v114  <|@  <|@
f <@~|@floating>@ <|@
tid i115 <|@
result int[-18963|0xffffffffffffb5ed] <|@
d <@d|@=== Debug Properties ===
isDefaultStable: false
rawvalue: -18963
stableDimension: 0
stamp: i32 [-18963] ⇊00000000ffffb5ed ⇈00000000ffffb5ed
stampKind: i32
value: int[-18963|0xffffffffffffb5ed]
=== Inputs ===
=== Succesors ===
=== Usages ===
i105 
=== Predecessor ===
- >@ <|@
instruction <@Constant|@org.graalvm.compiler.nodes.ConstantNode>@  <|@  <|@
f <@*|@fixed>@ <|@
tid v114 <|@
d <@d|@=== Debug Properties ===
stamp: void
=== Inputs ===
=== Succesors ===
=== Usages ===
v101 
=== Predecessor ===
v95 >@ <|@
instruction <@EndNode|@org.graalvm.compiler.nodes.EndNode>@  <|@  <|@
    end_IR
    begin_IR
      LIR
      nr   -1  <|@ instruction [] = LABEL numbPhis: 0 align: false label: ? <|@ <|@
      nr   -1  <|@ instruction JUMP ~[int[-18963|0xffffffffffffb5ed]] destination: B9 -> B13 <|@ <|@
    end_IR
  end_block
  begin_block
    name "B10"
    from_bci -1
    to_bci -1
    predecessors "B8" 
    successors "B11" "B12" 
    xhandlers
    flags 
    probability 4607182418800017408
    begin_IR
      HIR
f <@#|@fixed with next>@ <|@
tid v93 <|@
d <@d|@=== Debug Properties ===
nodeSourcePosition: at java.nio.Buffer.position(Buffer.java:243) [bci: 9]
at java.nio.Buffer.<init>(Buffer.java:202) [bci: 61]
stamp: void
=== Inputs ===
=== Succesors ===
next: v100 
=== Usages ===
=== Predecessor ===
v96 >@ <|@
instruction <@Begin|@org.graalvm.compiler.nodes.BeginNode>@ #next: v100  <|@  <|@
f <@~|@floating>@ <|@
tid v23 <|@
d <@d|@=== Debug Properties ===
condition: LT
nodeSourcePosition: at java.nio.Buffer.<init>(Buffer.java:203) [bci: 66]
op: org.graalvm.compiler.nodes.calc.IntegerLessThanNode$LessThanOp@33a89f26
stamp: void
unorderedIsTrue: false
=== Inputs ===
x: i2 
y: i10 
=== Succesors ===
=== Usages ===
v100 
=== Predecessor ===
- >@ <|@
instruction <@<|@org.graalvm.compiler.nodes.calc.IntegerLessThanNode>@ x: i2 y: i10  <|@  <|@
f <@*|@fixed>@ <|@
tid v100 <|@
d <@d|@=== Debug Properties ===
nodeSourcePosition: at java.nio.Buffer.<init>(Buffer.java:203) [bci: 66]
stamp: void
trueSuccessorProbability: 1.0
=== Inputs ===
condition: v23 
=== Succesors ===
trueSuccessor: v97 
falseSuccessor: v99 
=== Usages ===
=== Predecessor ===
v93 >@ <|@
instruction <@If|@org.graalvm.compiler.nodes.IfNode>@ condition: v23 #trueSuccessor: v97 #falseSuccessor: v99  <|@  <|@
    end_IR
    begin_IR
      LIR
      nr   -1  <|@ instruction [] = LABEL numbPhis: 0 align: false label: ? <|@ <|@
      nr   -1  <|@ instruction TEST (x: v1|DWORD, y: v1|DWORD) size: DWORD <|@ <|@
      nr   -1  <|@ instruction BRANCH trueDestinationProbability: 1.0 condition: < trueDestination: B10 -> B11 falseDestination: B10 -> B12 <|@ <|@
    end_IR
  end_block
  begin_block
    name "B11"
    from_bci -1
    to_bci -1
    predecessors "B10" 
    successors 
    xhandlers
    flags 
    probability 4607182418800017408
    begin_IR
      HIR
f <@#|@fixed with next>@ <|@
tid v97 <|@
d <@d|@=== Debug Properties ===
nodeSourcePosition: at java.nio.Buffer.<init>(Buffer.java:203) [bci: 66]
stamp: void
=== Inputs ===
=== Succesors ===
next: v60 
=== Usages ===
=== Predecessor ===
v100 >@ <|@
instruction <@Begin|@org.graalvm.compiler.nodes.BeginNode>@ #next: v60  <|@  <|@
f <@~|@floating>@ <|@
tid v118 <|@
result [v0|QWORD[.] + 12] <|@
d <@d|@=== Debug Properties ===
displacement: 12
scale: Times1
stamp: void*
=== Inputs ===
base: a1 
index: - 
=== Succesors ===
=== Usages ===
v60 
=== Predecessor ===
- >@ <|@
instruction <@AMD64Address|@org.graalvm.compiler.core.amd64.AMD64AddressNode>@ base: a1 index: -  <|@  <|@
f <@~|@floating>@ <|@
tid i7 <|@
result int[-1|0xffffffffffffffff] <|@
d <@d|@=== Debug Properties ===
isDefaultStable: false
nodeSourcePosition: at java.nio.Buffer.<init>(Buffer.java:185) [bci: 5]
rawvalue: -1
stableDimension: 0
stamp: i32 [-1] ⇊00000000ffffffff
stampKind: i32
value: int[-1|0xffffffffffffffff]
=== Inputs ===
=== Succesors ===
=== Usages ===
v60 
=== Predecessor ===
- >@ <|@
instruction <@Constant|@org.graalvm.compiler.nodes.ConstantNode>@  <|@  <|@
f <@#|@fixed with next>@ <|@
tid v60 <|@
d <@d|@=== Debug Properties ===
barrierType: NONE
location: Buffer.mark
nodeSourcePosition: at java.nio.Buffer.<init>(Buffer.java:185) [bci: 6]
nullCheck: false
stamp: void
=== Inputs ===
stateBefore: - 
guard: - 
address: v118 
value: i7 
stateAfter: - 
lastLocationAccess: - 
=== Succesors ===
next: v63 
=== Usages ===
=== Predecessor ===
v97 >@ <|@
instruction <@Write|@org.graalvm.compiler.nodes.memory.WriteNode>@ stateBefore: - guard: - address: v118 value: i7 stateAfter: - lastLocationAccess: - #next: v63  <|@  <|@
f <@~|@floating>@ <|@
tid v119 <|@
result [v0|QWORD[.] + 24] <|@
d <@d|@=== Debug Properties ===
displacement: 24
scale: Times1
stamp: void*
=== Inputs ===
base: a1 
index: - 
=== Succesors ===
=== Usages ===
v63 v75 
=== Predecessor ===
- >@ <|@
instruction <@AMD64Address|@org.graalvm.compiler.core.amd64.AMD64AddressNode>@ base: a1 index: -  <|@  <|@
f <@#|@fixed with next>@ <|@
tid v63 <|@
d <@d|@=== Debug Properties ===
barrierType: NONE
location: Buffer.position
nodeSourcePosition: at java.nio.Buffer.<init>(Buffer.java:186) [bci: 11]
nullCheck: false
stamp: void
=== Inputs ===
stateBefore: - 
guard: - 
address: v119 
value: i10 
stateAfter: - 
lastLocationAccess: - 
=== Succesors ===
next: v67 
=== Usages ===
=== Predecessor ===
v60 >@ <|@
instruction <@Write|@org.graalvm.compiler.nodes.memory.WriteNode>@ stateBefore: - guard: - address: v119 value: i10 stateAfter: - lastLocationAccess: - #next: v67  <|@  <|@
f <@~|@floating>@ <|@
tid v120 <|@
result [v0|QWORD[.] + 32] <|@
d <@d|@=== Debug Properties ===
displacement: 32
scale: Times1
stamp: void*
=== Inputs ===
base: a1 
index: - 
=== Succesors ===
=== Usages ===
v67 
=== Predecessor ===
- >@ <|@
instruction <@AMD64Address|@org.graalvm.compiler.core.amd64.AMD64AddressNode>@ base: a1 index: -  <|@  <|@
f <@#|@fixed with next>@ <|@
tid v67 <|@
d <@d|@=== Debug Properties ===
barrierType: NONE
location: Buffer.capacity
nodeSourcePosition: at java.nio.Buffer.<init>(Buffer.java:200) [bci: 50]
nullCheck: false
stamp: void
=== Inputs ===
stateBefore: - 
guard: - 
address: v120 
value: i5 
stateAfter: - 
lastLocationAccess: - 
=== Succesors ===
next: v72 
=== Usages ===
=== Predecessor ===
v63 >@ <|@
instruction <@Write|@org.graalvm.compiler.nodes.memory.WriteNode>@ stateBefore: - guard: - address: v120 value: i5 stateAfter: - lastLocationAccess: - #next: v72  <|@  <|@
f <@~|@floating>@ <|@
tid v121 <|@
result [v0|QWORD[.] + 28] <|@
d <@d|@=== Debug Properties ===
displacement: 28
scale: Times1
stamp: void*
=== Inputs ===
base: a1 
index: - 
=== Succesors ===
=== Usages ===
v72 
=== Predecessor ===
- >@ <|@
instruction <@AMD64Address|@org.graalvm.compiler.core.amd64.AMD64AddressNode>@ base: a1 index: -  <|@  <|@
f <@#|@fixed with next>@ <|@
tid v72 <|@
d <@d|@=== Debug Properties ===
barrierType: NONE
location: Buffer.limit
nodeSourcePosition: at java.nio.Buffer.limit(Buffer.java:276) [bci: 22]
at java.nio.Buffer.<init>(Buffer.java:201) [bci: 55]
nullCheck: false
stamp: void
=== Inputs ===
stateBefore: - 
guard: - 
address: v121 
value: i4 
stateAfter: - 
lastLocationAccess: - 
=== Succesors ===
next: v75 
=== Usages ===
=== Predecessor ===
v67 >@ <|@
instruction <@Write|@org.graalvm.compiler.nodes.memory.WriteNode>@ stateBefore: - guard: - address: v121 value: i4 stateAfter: - lastLocationAccess: - #next: v75  <|@  <|@
f <@#|@fixed with next>@ <|@
tid v75 <|@
d <@d|@=== Debug Properties ===
barrierType: NONE
location: Buffer.position
nodeSourcePosition: at java.nio.Buffer.position(Buffer.java:245) [bci: 22]
at java.nio.Buffer.<init>(Buffer.java:202) [bci: 61]
nullCheck: false
stamp: void
=== Inputs ===
stateBefore: - 
guard: - 
address: v119 
value: i3 
stateAfter: - 
lastLocationAccess: - 
=== Succesors ===
next: v25 
=== Usages ===
=== Predecessor ===
v72 >@ <|@
instruction <@Write|@org.graalvm.compiler.nodes.memory.WriteNode>@ stateBefore: - guard: - address: v119 value: i3 stateAfter: - lastLocationAccess: - #next: v25  <|@  <|@
f <@*|@fixed>@ <|@
tid v25 <|@
d <@d|@=== Debug Properties ===
nodeSourcePosition: at java.nio.Buffer.<init>(Buffer.java:209) [bci: 120]
stamp: void
=== Inputs ===
result: - 
memoryMap: - 
=== Succesors ===
=== Usages ===
=== Predecessor ===
v75 >@ <|@
instruction <@Return|@org.graalvm.compiler.nodes.ReturnNode>@ result: - memoryMap: -  <|@  <|@
    end_IR
    begin_IR
      LIR
      nr   -1  <|@ instruction [] = LABEL numbPhis: 0 align: false label: ? <|@ <|@
      nr   -1  <|@ instruction MOV [v0|QWORD[.] + 12] y: -1 size: DWORD <|@ <|@
      nr   -1  <|@ instruction MOV (x: [v0|QWORD[.] + 24], y: r12|ILLEGAL) size: DWORD <|@ <|@
      nr   -1  <|@ instruction MOV (x: [v0|QWORD[.] + 32], y: v4|DWORD) size: DWORD <|@ <|@
      nr   -1  <|@ instruction MOV (x: [v0|QWORD[.] + 28], y: v3|DWORD) size: DWORD <|@ <|@
      nr   -1  <|@ instruction MOV (x: [v0|QWORD[.] + 24], y: v2|DWORD) size: DWORD <|@ <|@
      nr   -1  <|@ instruction RETURN (savedRbp: stack:16|QWORD, value: -) isStub: false thread: r15 scratchForSafepointOnReturn: rcx config: org.graalvm.compiler.hotspot.GraalHotSpotVMConfig@69d7a7b <|@ <|@
    end_IR
  end_block
  begin_block
    name "B12"
    from_bci -1
    to_bci -1
    predecessors "B10" 
    successors "B13" 
    xhandlers
    flags 
    probability 2355382605114769408
    begin_IR
      HIR
f <@#|@fixed with next>@ <|@
tid v99 <|@
d <@d|@=== Debug Properties ===
nodeSourcePosition: at java.nio.Buffer.<init>(Buffer.java:203) [bci: 66]
stamp: void
=== Inputs ===
=== Succesors ===
next: v116 
=== Usages ===
=== Predecessor ===
v100 >@ <|@
instruction <@Begin|@org.graalvm.compiler.nodes.BeginNode>@ #next: v116  <|@  <|@
f <@~|@floating>@ <|@
tid i117 <|@
result int[-19475|0xffffffffffffb3ed] <|@
d <@d|@=== Debug Properties ===
isDefaultStable: false
rawvalue: -19475
stableDimension: 0
stamp: i32 [-19475] ⇊00000000ffffb3ed ⇈00000000ffffb3ed
stampKind: i32
value: int[-19475|0xffffffffffffb3ed]
=== Inputs ===
=== Succesors ===
=== Usages ===
i105 
=== Predecessor ===
- >@ <|@
instruction <@Constant|@org.graalvm.compiler.nodes.ConstantNode>@  <|@  <|@
f <@*|@fixed>@ <|@
tid v116 <|@
d <@d|@=== Debug Properties ===
stamp: void
=== Inputs ===
=== Succesors ===
=== Usages ===
v101 
=== Predecessor ===
v99 >@ <|@
instruction <@EndNode|@org.graalvm.compiler.nodes.EndNode>@  <|@  <|@
    end_IR
    begin_IR
      LIR
      nr   -1  <|@ instruction [] = LABEL numbPhis: 0 align: false label: ? <|@ <|@
      nr   -1  <|@ instruction JUMP ~[int[-19475|0xffffffffffffb3ed]] destination: B12 -> B13 <|@ <|@
    end_IR
  end_block
  begin_block
    name "B13"
    from_bci -1
    to_bci -1
    predecessors "B1" "B3" "B5" "B7" "B9" "B12" 
    successors 
    xhandlers
    flags 
    probability 2366641604183195648
    begin_IR
      HIR
f <@~|@floating>@ <|@
tid i105 <|@
result v5|DWORD <|@
d <@d|@=== Debug Properties ===
stamp: i32 [-19475 - -16403] ⇊00000000ffffb0ed ⇈00000000ffffbfed
valueDescription: i32
=== Inputs ===
merge: v101 
values: i103 i109 i111 i113 i115 i117 
=== Succesors ===
=== Usages ===
v107 
=== Predecessor ===
- >@ <|@
instruction <@ValuePhi|@org.graalvm.compiler.nodes.ValuePhiNode>@ merge: v101 values: i103 i109 i111 i113 i115 i117  <|@  <|@
f <@#|@fixed with next>@ <|@
tid v101 <|@
d <@d|@=== Debug Properties ===
stamp: void
=== Inputs ===
stateAfter: - 
ends: v102 v108 v110 v112 v114 v116 
=== Succesors ===
next: v107 
=== Usages ===
i105 
=== Predecessor ===
- >@ <|@
instruction <@Merge|@org.graalvm.compiler.nodes.MergeNode>@ stateAfter: - ends: v102 v108 v110 v112 v114 v116 #next: v107  <|@  <|@
f <@~|@floating>@ <|@
tid a104 <|@
result Object[null] <|@
d <@d|@=== Debug Properties ===
isDefaultStable: false
rawvalue: null
stableDimension: 0
stamp: a - NULL
stampKind: a -
value: Object[null]
=== Inputs ===
=== Succesors ===
=== Usages ===
v107 
=== Predecessor ===
- >@ <|@
instruction <@Constant|@org.graalvm.compiler.nodes.ConstantNode>@  <|@  <|@
tid ?6 <|@
d <@d|@=== Debug Properties ===
bci: 0
code: ResolvedJavaMethodBytecode<Buffer.<init>(int, int, int, int)>
duringCall: false
localsSize: 5
locksSize: 0
rethrowException: false
sourceFile: Buffer.java
sourceLine: 197
stackSize: 0
=== Inputs ===
outerFrameState: - 
values: a1 i2 i3 i4 i5 
=== Succesors ===
=== Usages ===
v107 
=== Predecessor ===
- >@ <|@
instruction <@FrameState|@org.graalvm.compiler.nodes.FrameState>@ outerFrameState: - values: a1 i2 i3 i4 i5  <|@  <|@
f <@*|@fixed>@ <|@
tid v107 <|@
d <@d|@=== Debug Properties ===
stamp: void
=== Inputs ===
stateBefore: ?6 
actionAndReason: i105 
speculation: a104 
=== Succesors ===
=== Usages ===
=== Predecessor ===
v101 >@ <|@
instruction <@DynamicDeoptimize|@org.graalvm.compiler.nodes.DynamicDeoptimizeNode>@ stateBefore: ?6 actionAndReason: i105 speculation: a104  <|@  <|@
    end_IR
    begin_IR
      LIR
      nr   -1  <|@ instruction [v5|DWORD] = LABEL numbPhis: 1 align: false label: ? <|@ <|@
      nr   -1  <|@ instruction MOV (x: [r15|QWORD + 668], y: v5|DWORD) size: DWORD <|@ <|@
      nr   -1  <|@ instruction MOV (x: [r15|QWORD + 680], y: r12|ILLEGAL) size: QWORD <|@ <|@
      nr   -1  <|@ st <@st|@java.nio.Buffer.<init>(Buffer.java:197) [bci: 0]
locals: v0|QWORD[.] v1|DWORD v2|DWORD v3|DWORD v4|DWORD 
>@ <|@ instruction DEOPT info [bci:0] <|@ <|@
    end_IR
  end_block
end_cfg
begin_cfg
  name "After PreAllocationOptimizationStage"
  begin_block
    name "B0"
    from_bci -1
    to_bci -1
    predecessors 
    successors "B1" "B2" 
    xhandlers
    flags 
    probability 4607182418800017408
    begin_IR
      LIR
      nr   -1  <|@ instruction [rsi|QWORD[.], rdx|DWORD, rcx|DWORD, r8|DWORD, r9|DWORD, rbp|QWORD] = LABEL numbPhis: 0 align: false label: ? <|@ <|@
      nr   -1  <|@ instruction stack:16|QWORD = MOVE rbp|QWORD moveKind: QWORD <|@ <|@
      nr   -1  <|@ instruction [] = HOTSPOTLOCKSTACK frameMapBuilder: org.graalvm.compiler.lir.amd64.AMD64FrameMapBuilder@69596961 slotKind: QWORD <|@ <|@
      nr   -1  <|@ instruction v0|QWORD[.] = MOVE rsi|QWORD[.] moveKind: QWORD <|@ <|@
      nr   -1  <|@ instruction v1|DWORD = MOVE rdx|DWORD moveKind: DWORD <|@ <|@
      nr   -1  <|@ instruction v2|DWORD = MOVE rcx|DWORD moveKind: DWORD <|@ <|@
      nr   -1  <|@ instruction v3|DWORD = MOVE r8|DWORD moveKind: DWORD <|@ <|@
      nr   -1  <|@ instruction v4|DWORD = MOVE r9|DWORD moveKind: DWORD <|@ <|@
      nr   -1  <|@ instruction TEST (x: v4|DWORD, y: v4|DWORD) size: DWORD <|@ <|@
      nr   -1  <|@ instruction BRANCH trueDestinationProbability: 0.0 condition: < trueDestination: B0 -> B1 falseDestination: B0 -> B2 <|@ <|@
    end_IR
  end_block
  begin_block
    name "B2"
    from_bci -1
    to_bci -1
    predecessors "B0" 
    successors "B3" "B4" 
    xhandlers
    flags 
    probability 4607182418800017408
    begin_IR
      LIR
      nr   -1  <|@ instruction [] = LABEL numbPhis: 0 align: false label: ? <|@ <|@
      nr   -1  <|@ instruction CMP (x: v3|DWORD, y: v4|DWORD) size: DWORD <|@ <|@
      nr   -1  <|@ instruction BRANCH trueDestinationProbability: 0.0 condition: > trueDestination: B2 -> B3 falseDestination: B2 -> B4 <|@ <|@
    end_IR
  end_block
  begin_block
    name "B4"
    from_bci -1
    to_bci -1
    predecessors "B2" 
    successors "B5" "B6" 
    xhandlers
    flags 
    probability 4607182418800017408
    begin_IR
      LIR
      nr   -1  <|@ instruction [] = LABEL numbPhis: 0 align: false label: ? <|@ <|@
      nr   -1  <|@ instruction TEST (x: v3|DWORD, y: v3|DWORD) size: DWORD <|@ <|@
      nr   -1  <|@ instruction BRANCH trueDestinationProbability: 0.0 condition: < trueDestination: B4 -> B5 falseDestination: B4 -> B6 <|@ <|@
    end_IR
  end_block
  begin_block
    name "B6"
    from_bci -1
    to_bci -1
    predecessors "B4" 
    successors "B7" "B8" 
    xhandlers
    flags 
    probability 4607182418800017408
    begin_IR
      LIR
      nr   -1  <|@ instruction [] = LABEL numbPhis: 0 align: false label: ? <|@ <|@
      nr   -1  <|@ instruction CMP (x: v2|DWORD, y: v3|DWORD) size: DWORD <|@ <|@
      nr   -1  <|@ instruction BRANCH trueDestinationProbability: 0.0 condition: > trueDestination: B6 -> B7 falseDestination: B6 -> B8 <|@ <|@
    end_IR
  end_block
  begin_block
    name "B8"
    from_bci -1
    to_bci -1
    predecessors "B6" 
    successors "B9" "B10" 
    xhandlers
    flags 
    probability 4607182418800017408
    begin_IR
      LIR
      nr   -1  <|@ instruction [] = LABEL numbPhis: 0 align: false label: ? <|@ <|@
      nr   -1  <|@ instruction TEST (x: v2|DWORD, y: v2|DWORD) size: DWORD <|@ <|@
      nr   -1  <|@ instruction BRANCH trueDestinationProbability: 0.0 condition: < trueDestination: B8 -> B9 falseDestination: B8 -> B10 <|@ <|@
    end_IR
  end_block
  begin_block
    name "B10"
    from_bci -1
    to_bci -1
    predecessors "B8" 
    successors "B11" "B12" 
    xhandlers
    flags 
    probability 4607182418800017408
    begin_IR
      LIR
      nr   -1  <|@ instruction [] = LABEL numbPhis: 0 align: false label: ? <|@ <|@
      nr   -1  <|@ instruction TEST (x: v1|DWORD, y: v1|DWORD) size: DWORD <|@ <|@
      nr   -1  <|@ instruction BRANCH trueDestinationProbability: 1.0 condition: < trueDestination: B10 -> B11 falseDestination: B10 -> B12 <|@ <|@
    end_IR
  end_block
  begin_block
    name "B11"
    from_bci -1
    to_bci -1
    predecessors "B10" 
    successors 
    xhandlers
    flags 
    probability 4607182418800017408
    begin_IR
      LIR
      nr   -1  <|@ instruction [] = LABEL numbPhis: 0 align: false label: ? <|@ <|@
      nr   -1  <|@ instruction MOV [v0|QWORD[.] + 12] y: -1 size: DWORD <|@ <|@
      nr   -1  <|@ instruction MOV (x: [v0|QWORD[.] + 24], y: r12|ILLEGAL) size: DWORD <|@ <|@
      nr   -1  <|@ instruction MOV (x: [v0|QWORD[.] + 32], y: v4|DWORD) size: DWORD <|@ <|@
      nr   -1  <|@ instruction MOV (x: [v0|QWORD[.] + 28], y: v3|DWORD) size: DWORD <|@ <|@
      nr   -1  <|@ instruction MOV (x: [v0|QWORD[.] + 24], y: v2|DWORD) size: DWORD <|@ <|@
      nr   -1  <|@ instruction RETURN (savedRbp: stack:16|QWORD, value: -) isStub: false thread: r15 scratchForSafepointOnReturn: rcx config: org.graalvm.compiler.hotspot.GraalHotSpotVMConfig@69d7a7b <|@ <|@
    end_IR
  end_block
  begin_block
    name "B1"
    from_bci -1
    to_bci -1
    predecessors "B0" 
    successors "B13" 
    xhandlers
    flags 
    probability 2355382605114769408
    begin_IR
      LIR
      nr   -1  <|@ instruction [] = LABEL numbPhis: 0 align: false label: ? <|@ <|@
      nr   -1  <|@ instruction JUMP ~[int[-16403|0xffffffffffffbfed]] destination: B1 -> B13 <|@ <|@
    end_IR
  end_block
  begin_block
    name "B13"
    from_bci -1
    to_bci -1
    predecessors "B1" "B3" "B5" "B7" "B9" "B12" 
    successors 
    xhandlers
    flags 
    probability 2366641604183195648
    begin_IR
      LIR
      nr   -1  <|@ instruction [v5|DWORD] = LABEL numbPhis: 1 align: false label: ? <|@ <|@
      nr   -1  <|@ instruction MOV (x: [r15|QWORD + 668], y: v5|DWORD) size: DWORD <|@ <|@
      nr   -1  <|@ instruction MOV (x: [r15|QWORD + 680], y: r12|ILLEGAL) size: QWORD <|@ <|@
      nr   -1  <|@ st <@st|@java.nio.Buffer.<init>(Buffer.java:197) [bci: 0]
locals: v0|QWORD[.] v1|DWORD v2|DWORD v3|DWORD v4|DWORD 
>@ <|@ instruction DEOPT info [bci:0] <|@ <|@
    end_IR
  end_block
  begin_block
    name "B5"
    from_bci -1
    to_bci -1
    predecessors "B4" 
    successors "B13" 
    xhandlers
    flags 
    probability 2355382605114769408
    begin_IR
      LIR
      nr   -1  <|@ instruction [] = LABEL numbPhis: 0 align: false label: ? <|@ <|@
      nr   -1  <|@ instruction JUMP ~[int[-17683|0xffffffffffffbaed]] destination: B5 -> B13 <|@ <|@
    end_IR
  end_block
  begin_block
    name "B12"
    from_bci -1
    to_bci -1
    predecessors "B10" 
    successors "B13" 
    xhandlers
    flags 
    probability 2355382605114769408
    begin_IR
      LIR
      nr   -1  <|@ instruction [] = LABEL numbPhis: 0 align: false label: ? <|@ <|@
      nr   -1  <|@ instruction JUMP ~[int[-19475|0xffffffffffffb3ed]] destination: B12 -> B13 <|@ <|@
    end_IR
  end_block
  begin_block
    name "B9"
    from_bci -1
    to_bci -1
    predecessors "B8" 
    successors "B13" 
    xhandlers
    flags 
    probability 2355382605114769408
    begin_IR
      LIR
      nr   -1  <|@ instruction [] = LABEL numbPhis: 0 align: false label: ? <|@ <|@
      nr   -1  <|@ instruction JUMP ~[int[-18963|0xffffffffffffb5ed]] destination: B9 -> B13 <|@ <|@
    end_IR
  end_block
  begin_block
    name "B3"
    from_bci -1
    to_bci -1
    predecessors "B2" 
    successors "B13" 
    xhandlers
    flags 
    probability 2355382605114769408
    begin_IR
      LIR
      nr   -1  <|@ instruction [] = LABEL numbPhis: 0 align: false label: ? <|@ <|@
      nr   -1  <|@ instruction JUMP ~[int[-17427|0xffffffffffffbbed]] destination: B3 -> B13 <|@ <|@
    end_IR
  end_block
  begin_block
    name "B7"
    from_bci -1
    to_bci -1
    predecessors "B6" 
    successors "B13" 
    xhandlers
    flags 
    probability 2355382605114769408
    begin_IR
      LIR
      nr   -1  <|@ instruction [] = LABEL numbPhis: 0 align: false label: ? <|@ <|@
      nr   -1  <|@ instruction JUMP ~[int[-18707|0xffffffffffffb6ed]] destination: B7 -> B13 <|@ <|@
    end_IR
  end_block
end_cfg
begin_bytecodes
     0: aload_0       
     1: invokespecial #0          // java.lang.Object.<init>:()void
     4: aload_0       
     5: iconst_m1     
     6: putfield      #1          // mark:int
     9: aload_0       
    10: iconst_0      
    11: putfield      #2          // position:int
    14: iload         4
    16: ifge          47
    19: new           #5          // java.lang.IllegalArgumentException
    22: dup           
    23: new           #6          // java.lang.StringBuilder
    26: dup           
    27: invokespecial #3          // java.lang.StringBuilder.<init>:()void
    30: ldc           #8          // "Negative capacity: "
    32: invokevirtual #4          // java.lang.StringBuilder.append:(java.lang.String)java.lang.StringBuilder
    35: iload         4
    37: invokevirtual #5          // java.lang.StringBuilder.append:(int)java.lang.StringBuilder
    40: invokevirtual #6          // java.lang.StringBuilder.toString:()java.lang.String
    43: invokespecial #7          // java.lang.IllegalArgumentException.<init>:(java.lang.String)void
    46: athrow        
    47: aload_0       
    48: iload         4
    50: putfield      #8          // capacity:int
    53: aload_0       
    54: iload_3       
    55: invokevirtual #9          // limit:(int)java.nio.Buffer
    58: pop           
    59: aload_0       
    60: iload_2       
    61: invokevirtual #10         // position:(int)java.nio.Buffer
    64: pop           
    65: iload_1       
    66: iflt          120
    69: iload_1       
    70: iload_2       
    71: if_icmple     115
    74: new           #5          // java.lang.IllegalArgumentException
    77: dup           
    78: new           #6          // java.lang.StringBuilder
    81: dup           
    82: invokespecial #3          // java.lang.StringBuilder.<init>:()void
    85: ldc           #16         // "mark > position: ("
    87: invokevirtual #4          // java.lang.StringBuilder.append:(java.lang.String)java.lang.StringBuilder
    90: iload_1       
    91: invokevirtual #5          // java.lang.StringBuilder.append:(int)java.lang.StringBuilder
    94: ldc           #17         // " > "
    96: invokevirtual #4          // java.lang.StringBuilder.append:(java.lang.String)java.lang.StringBuilder
    99: iload_2       
   100: invokevirtual #5          // java.lang.StringBuilder.append:(int)java.lang.StringBuilder
   103: ldc           #18         // ")"
   105: invokevirtual #4          // java.lang.StringBuilder.append:(java.lang.String)java.lang.StringBuilder
   108: invokevirtual #6          // java.lang.StringBuilder.toString:()java.lang.String
   111: invokespecial #7          // java.lang.IllegalArgumentException.<init>:(java.lang.String)void
   114: athrow        
   115: aload_0       
   116: iload_1       
   117: putfield      #1          // mark:int
   120: return        
   <|@
end_bytecodes
begin_cfg
  name "After AllocationStage"
  begin_block
    name "B0"
    from_bci -1
    to_bci -1
    predecessors 
    successors "B1" "B2" 
    xhandlers
    flags 
    probability 4607182418800017408
    begin_IR
      LIR
      nr    0  <|@ instruction [rsi|QWORD[.], rdx|DWORD, rcx|DWORD, r8|DWORD, r9|DWORD, rbp|QWORD] = LABEL numbPhis: 0 align: false label: ? <|@ <|@
      nr    2  <|@ instruction stack:16|QWORD = MOVE rbp|QWORD moveKind: QWORD <|@ <|@
      nr    4  <|@ instruction [] = HOTSPOTLOCKSTACK frameMapBuilder: org.graalvm.compiler.lir.amd64.AMD64FrameMapBuilder@69596961 slotKind: QWORD <|@ <|@
      nr   16  <|@ instruction TEST (x: r9|DWORD, y: r9|DWORD) size: DWORD <|@ <|@
      nr   18  <|@ instruction BRANCH trueDestinationProbability: 0.0 condition: < trueDestination: B0 -> B1 falseDestination: B0 -> B2 <|@ <|@
    end_IR
  end_block
  begin_block
    name "B2"
    from_bci -1
    to_bci -1
    predecessors "B0" 
    successors "B3" "B4" 
    xhandlers
    flags 
    probability 4607182418800017408
    begin_IR
      LIR
      nr   20  <|@ instruction [] = LABEL numbPhis: 0 align: false label: ? <|@ <|@
      nr   22  <|@ instruction CMP (x: r8|DWORD, y: r9|DWORD) size: DWORD <|@ <|@
      nr   24  <|@ instruction BRANCH trueDestinationProbability: 0.0 condition: > trueDestination: B2 -> B3 falseDestination: B2 -> B4 <|@ <|@
    end_IR
  end_block
  begin_block
    name "B4"
    from_bci -1
    to_bci -1
    predecessors "B2" 
    successors "B5" "B6" 
    xhandlers
    flags 
    probability 4607182418800017408
    begin_IR
      LIR
      nr   26  <|@ instruction [] = LABEL numbPhis: 0 align: false label: ? <|@ <|@
      nr   28  <|@ instruction TEST (x: r8|DWORD, y: r8|DWORD) size: DWORD <|@ <|@
      nr   30  <|@ instruction BRANCH trueDestinationProbability: 0.0 condition: < trueDestination: B4 -> B5 falseDestination: B4 -> B6 <|@ <|@
    end_IR
  end_block
  begin_block
    name "B6"
    from_bci -1
    to_bci -1
    predecessors "B4" 
    successors "B7" "B8" 
    xhandlers
    flags 
    probability 4607182418800017408
    begin_IR
      LIR
      nr   32  <|@ instruction [] = LABEL numbPhis: 0 align: false label: ? <|@ <|@
      nr   34  <|@ instruction CMP (x: rcx|DWORD, y: r8|DWORD) size: DWORD <|@ <|@
      nr   36  <|@ instruction BRANCH trueDestinationProbability: 0.0 condition: > trueDestination: B6 -> B7 falseDestination: B6 -> B8 <|@ <|@
    end_IR
  end_block
  begin_block
    name "B8"
    from_bci -1
    to_bci -1
    predecessors "B6" 
    successors "B9" "B10" 
    xhandlers
    flags 
    probability 4607182418800017408
    begin_IR
      LIR
      nr   38  <|@ instruction [] = LABEL numbPhis: 0 align: false label: ? <|@ <|@
      nr   40  <|@ instruction TEST (x: rcx|DWORD, y: rcx|DWORD) size: DWORD <|@ <|@
      nr   42  <|@ instruction BRANCH trueDestinationProbability: 0.0 condition: < trueDestination: B8 -> B9 falseDestination: B8 -> B10 <|@ <|@
    end_IR
  end_block
  begin_block
    name "B10"
    from_bci -1
    to_bci -1
    predecessors "B8" 
    successors "B11" "B12" 
    xhandlers
    flags 
    probability 4607182418800017408
    begin_IR
      LIR
      nr   44  <|@ instruction [] = LABEL numbPhis: 0 align: false label: ? <|@ <|@
      nr   46  <|@ instruction TEST (x: rdx|DWORD, y: rdx|DWORD) size: DWORD <|@ <|@
      nr   48  <|@ instruction BRANCH trueDestinationProbability: 1.0 condition: < trueDestination: B10 -> B11 falseDestination: B10 -> B12 <|@ <|@
    end_IR
  end_block
  begin_block
    name "B11"
    from_bci -1
    to_bci -1
    predecessors "B10" 
    successors 
    xhandlers
    flags 
    probability 4607182418800017408
    begin_IR
      LIR
      nr   50  <|@ instruction [] = LABEL numbPhis: 0 align: false label: ? <|@ <|@
      nr   52  <|@ instruction MOV [rsi|QWORD[.] + 12] y: -1 size: DWORD <|@ <|@
      nr   54  <|@ instruction MOV (x: [rsi|QWORD[.] + 24], y: r12|ILLEGAL) size: DWORD <|@ <|@
      nr   56  <|@ instruction MOV (x: [rsi|QWORD[.] + 32], y: r9|DWORD) size: DWORD <|@ <|@
      nr   58  <|@ instruction MOV (x: [rsi|QWORD[.] + 28], y: r8|DWORD) size: DWORD <|@ <|@
      nr   60  <|@ instruction MOV (x: [rsi|QWORD[.] + 24], y: rcx|DWORD) size: DWORD <|@ <|@
      nr   62  <|@ instruction RETURN (savedRbp: stack:16|QWORD, value: -) isStub: false thread: r15 scratchForSafepointOnReturn: rcx config: org.graalvm.compiler.hotspot.GraalHotSpotVMConfig@69d7a7b <|@ <|@
    end_IR
  end_block
  begin_block
    name "B1"
    from_bci -1
    to_bci -1
    predecessors "B0" 
    successors "B13" 
    xhandlers
    flags 
    probability 2355382605114769408
    begin_IR
      LIR
      nr   64  <|@ instruction [] = LABEL numbPhis: 0 align: false label: ? <|@ <|@
      nr   -1  <|@ instruction r10|DWORD = MOVE input: int[-16403|0xffffffffffffbfed] // MoveResolver resolve mapping <|@ <|@
      nr   66  <|@ instruction JUMP ~[] destination: B1 -> B13 <|@ <|@
    end_IR
  end_block
  begin_block
    name "B13"
    from_bci -1
    to_bci -1
    predecessors "B1" "B3" "B5" "B7" "B9" "B12" 
    successors 
    xhandlers
    flags 
    probability 2366641604183195648
    begin_IR
      LIR
      nr   88  <|@ instruction [] = LABEL numbPhis: 1 align: false label: ? <|@ <|@
      nr   90  <|@ instruction MOV (x: [r15|QWORD + 668], y: r10|DWORD) size: DWORD <|@ <|@
      nr   92  <|@ instruction MOV (x: [r15|QWORD + 680], y: r12|ILLEGAL) size: QWORD <|@ <|@
      nr   94  <|@ st <@st|@reference-map: [rsi:0]
live-base-pointers: []
java.nio.Buffer.<init>(Buffer.java:197) [bci: 0]
locals: rsi|QWORD[.] rdx|DWORD rcx|DWORD r8|DWORD r9|DWORD 
>@ <|@ instruction DEOPT info [bci:0] <|@ <|@
    end_IR
  end_block
  begin_block
    name "B5"
    from_bci -1
    to_bci -1
    predecessors "B4" 
    successors "B13" 
    xhandlers
    flags 
    probability 2355382605114769408
    begin_IR
      LIR
      nr   68  <|@ instruction [] = LABEL numbPhis: 0 align: false label: ? <|@ <|@
      nr   -1  <|@ instruction r10|DWORD = MOVE input: int[-17683|0xffffffffffffbaed] // MoveResolver resolve mapping <|@ <|@
      nr   70  <|@ instruction JUMP ~[] destination: B5 -> B13 <|@ <|@
    end_IR
  end_block
  begin_block
    name "B12"
    from_bci -1
    to_bci -1
    predecessors "B10" 
    successors "B13" 
    xhandlers
    flags 
    probability 2355382605114769408
    begin_IR
      LIR
      nr   72  <|@ instruction [] = LABEL numbPhis: 0 align: false label: ? <|@ <|@
      nr   -1  <|@ instruction r10|DWORD = MOVE input: int[-19475|0xffffffffffffb3ed] // MoveResolver resolve mapping <|@ <|@
      nr   74  <|@ instruction JUMP ~[] destination: B12 -> B13 <|@ <|@
    end_IR
  end_block
  begin_block
    name "B9"
    from_bci -1
    to_bci -1
    predecessors "B8" 
    successors "B13" 
    xhandlers
    flags 
    probability 2355382605114769408
    begin_IR
      LIR
      nr   76  <|@ instruction [] = LABEL numbPhis: 0 align: false label: ? <|@ <|@
      nr   -1  <|@ instruction r10|DWORD = MOVE input: int[-18963|0xffffffffffffb5ed] // MoveResolver resolve mapping <|@ <|@
      nr   78  <|@ instruction JUMP ~[] destination: B9 -> B13 <|@ <|@
    end_IR
  end_block
  begin_block
    name "B3"
    from_bci -1
    to_bci -1
    predecessors "B2" 
    successors "B13" 
    xhandlers
    flags 
    probability 2355382605114769408
    begin_IR
      LIR
      nr   80  <|@ instruction [] = LABEL numbPhis: 0 align: false label: ? <|@ <|@
      nr   -1  <|@ instruction r10|DWORD = MOVE input: int[-17427|0xffffffffffffbbed] // MoveResolver resolve mapping <|@ <|@
      nr   82  <|@ instruction JUMP ~[] destination: B3 -> B13 <|@ <|@
    end_IR
  end_block
  begin_block
    name "B7"
    from_bci -1
    to_bci -1
    predecessors "B6" 
    successors "B13" 
    xhandlers
    flags 
    probability 2355382605114769408
    begin_IR
      LIR
      nr   84  <|@ instruction [] = LABEL numbPhis: 0 align: false label: ? <|@ <|@
      nr   -1  <|@ instruction r10|DWORD = MOVE input: int[-18707|0xffffffffffffb6ed] // MoveResolver resolve mapping <|@ <|@
      nr   86  <|@ instruction JUMP ~[] destination: B7 -> B13 <|@ <|@
    end_IR
  end_block
end_cfg
begin_bytecodes
     0: aload_0       
     1: invokespecial #0          // java.lang.Object.<init>:()void
     4: aload_0       
     5: iconst_m1     
     6: putfield      #1          // mark:int
     9: aload_0       
    10: iconst_0      
    11: putfield      #2          // position:int
    14: iload         4
    16: ifge          47
    19: new           #5          // java.lang.IllegalArgumentException
    22: dup           
    23: new           #6          // java.lang.StringBuilder
    26: dup           
    27: invokespecial #3          // java.lang.StringBuilder.<init>:()void
    30: ldc           #8          // "Negative capacity: "
    32: invokevirtual #4          // java.lang.StringBuilder.append:(java.lang.String)java.lang.StringBuilder
    35: iload         4
    37: invokevirtual #5          // java.lang.StringBuilder.append:(int)java.lang.StringBuilder
    40: invokevirtual #6          // java.lang.StringBuilder.toString:()java.lang.String
    43: invokespecial #7          // java.lang.IllegalArgumentException.<init>:(java.lang.String)void
    46: athrow        
    47: aload_0       
    48: iload         4
    50: putfield      #8          // capacity:int
    53: aload_0       
    54: iload_3       
    55: invokevirtual #9          // limit:(int)java.nio.Buffer
    58: pop           
    59: aload_0       
    60: iload_2       
    61: invokevirtual #10         // position:(int)java.nio.Buffer
    64: pop           
    65: iload_1       
    66: iflt          120
    69: iload_1       
    70: iload_2       
    71: if_icmple     115
    74: new           #5          // java.lang.IllegalArgumentException
    77: dup           
    78: new           #6          // java.lang.StringBuilder
    81: dup           
    82: invokespecial #3          // java.lang.StringBuilder.<init>:()void
    85: ldc           #16         // "mark > position: ("
    87: invokevirtual #4          // java.lang.StringBuilder.append:(java.lang.String)java.lang.StringBuilder
    90: iload_1       
    91: invokevirtual #5          // java.lang.StringBuilder.append:(int)java.lang.StringBuilder
    94: ldc           #17         // " > "
    96: invokevirtual #4          // java.lang.StringBuilder.append:(java.lang.String)java.lang.StringBuilder
    99: iload_2       
   100: invokevirtual #5          // java.lang.StringBuilder.append:(int)java.lang.StringBuilder
   103: ldc           #18         // ")"
   105: invokevirtual #4          // java.lang.StringBuilder.append:(java.lang.String)java.lang.StringBuilder
   108: invokevirtual #6          // java.lang.StringBuilder.toString:()java.lang.String
   111: invokespecial #7          // java.lang.IllegalArgumentException.<init>:(java.lang.String)void
   114: athrow        
   115: aload_0       
   116: iload_1       
   117: putfield      #1          // mark:int
   120: return        
   <|@
end_bytecodes
begin_cfg
  name "After PostAllocationOptimizationStage"
  begin_block
    name "B0"
    from_bci -1
    to_bci -1
    predecessors 
    successors "B1" "B2" 
    xhandlers
    flags 
    probability 4607182418800017408
    begin_IR
      LIR
      nr    0  <|@ instruction [rsi|QWORD[.], rdx|DWORD, rcx|DWORD, r8|DWORD, r9|DWORD, rbp|QWORD] = LABEL numbPhis: 0 align: false label: ? <|@ <|@
      nr    2  <|@ instruction stack:16|QWORD = MOVE rbp|QWORD moveKind: QWORD <|@ <|@
      nr    4  <|@ instruction [] = HOTSPOTLOCKSTACK frameMapBuilder: org.graalvm.compiler.lir.amd64.AMD64FrameMapBuilder@69596961 slotKind: QWORD <|@ <|@
      nr   16  <|@ instruction TEST (x: r9|DWORD, y: r9|DWORD) size: DWORD <|@ <|@
      nr   18  <|@ instruction BRANCH trueDestinationProbability: 0.0 condition: < trueDestination: B0 -> B1 falseDestination: B0 -> B2 <|@ <|@
    end_IR
  end_block
  begin_block
    name "B2"
    from_bci -1
    to_bci -1
    predecessors "B0" 
    successors "B3" "B4" 
    xhandlers
    flags 
    probability 4607182418800017408
    begin_IR
      LIR
      nr   20  <|@ instruction [] = LABEL numbPhis: 0 align: false label: ? <|@ <|@
      nr   22  <|@ instruction CMP (x: r8|DWORD, y: r9|DWORD) size: DWORD <|@ <|@
      nr   24  <|@ instruction BRANCH trueDestinationProbability: 0.0 condition: > trueDestination: B2 -> B3 falseDestination: B2 -> B4 <|@ <|@
    end_IR
  end_block
  begin_block
    name "B4"
    from_bci -1
    to_bci -1
    predecessors "B2" 
    successors "B5" "B6" 
    xhandlers
    flags 
    probability 4607182418800017408
    begin_IR
      LIR
      nr   26  <|@ instruction [] = LABEL numbPhis: 0 align: false label: ? <|@ <|@
      nr   28  <|@ instruction TEST (x: r8|DWORD, y: r8|DWORD) size: DWORD <|@ <|@
      nr   30  <|@ instruction BRANCH trueDestinationProbability: 0.0 condition: < trueDestination: B4 -> B5 falseDestination: B4 -> B6 <|@ <|@
    end_IR
  end_block
  begin_block
    name "B6"
    from_bci -1
    to_bci -1
    predecessors "B4" 
    successors "B7" "B8" 
    xhandlers
    flags 
    probability 4607182418800017408
    begin_IR
      LIR
      nr   32  <|@ instruction [] = LABEL numbPhis: 0 align: false label: ? <|@ <|@
      nr   34  <|@ instruction CMP (x: rcx|DWORD, y: r8|DWORD) size: DWORD <|@ <|@
      nr   36  <|@ instruction BRANCH trueDestinationProbability: 0.0 condition: > trueDestination: B6 -> B7 falseDestination: B6 -> B8 <|@ <|@
    end_IR
  end_block
  begin_block
    name "B8"
    from_bci -1
    to_bci -1
    predecessors "B6" 
    successors "B9" "B10" 
    xhandlers
    flags 
    probability 4607182418800017408
    begin_IR
      LIR
      nr   38  <|@ instruction [] = LABEL numbPhis: 0 align: false label: ? <|@ <|@
      nr   40  <|@ instruction TEST (x: rcx|DWORD, y: rcx|DWORD) size: DWORD <|@ <|@
      nr   42  <|@ instruction BRANCH trueDestinationProbability: 0.0 condition: < trueDestination: B8 -> B9 falseDestination: B8 -> B10 <|@ <|@
    end_IR
  end_block
  begin_block
    name "B10"
    from_bci -1
    to_bci -1
    predecessors "B8" 
    successors "B11" "B12" 
    xhandlers
    flags 
    probability 4607182418800017408
    begin_IR
      LIR
      nr   44  <|@ instruction [] = LABEL numbPhis: 0 align: false label: ? <|@ <|@
      nr   46  <|@ instruction TEST (x: rdx|DWORD, y: rdx|DWORD) size: DWORD <|@ <|@
      nr   48  <|@ instruction BRANCH trueDestinationProbability: 1.0 condition: < trueDestination: B10 -> B11 falseDestination: B10 -> B12 <|@ <|@
    end_IR
  end_block
  begin_block
    name "B11"
    from_bci -1
    to_bci -1
    predecessors "B10" 
    successors 
    xhandlers
    flags 
    probability 4607182418800017408
    begin_IR
      LIR
      nr   50  <|@ instruction [] = LABEL numbPhis: 0 align: false label: ? <|@ <|@
      nr   52  <|@ instruction MOV [rsi|QWORD[.] + 12] y: -1 size: DWORD <|@ <|@
      nr   54  <|@ instruction MOV (x: [rsi|QWORD[.] + 24], y: r12|ILLEGAL) size: DWORD <|@ <|@
      nr   56  <|@ instruction MOV (x: [rsi|QWORD[.] + 32], y: r9|DWORD) size: DWORD <|@ <|@
      nr   58  <|@ instruction MOV (x: [rsi|QWORD[.] + 28], y: r8|DWORD) size: DWORD <|@ <|@
      nr   60  <|@ instruction MOV (x: [rsi|QWORD[.] + 24], y: rcx|DWORD) size: DWORD <|@ <|@
      nr   62  <|@ instruction RETURN (savedRbp: stack:16|QWORD, value: -) isStub: false thread: r15 scratchForSafepointOnReturn: rcx config: org.graalvm.compiler.hotspot.GraalHotSpotVMConfig@69d7a7b <|@ <|@
    end_IR
  end_block
  begin_block
    name "B1"
    from_bci -1
    to_bci -1
    predecessors "B0" 
    successors "B13" 
    xhandlers
    flags 
    probability 2355382605114769408
    begin_IR
      LIR
      nr   64  <|@ instruction [] = LABEL numbPhis: 0 align: false label: ? <|@ <|@
      nr   -1  <|@ instruction r10|DWORD = MOVE input: int[-16403|0xffffffffffffbfed] // MoveResolver resolve mapping <|@ <|@
      nr   66  <|@ instruction JUMP ~[] destination: B1 -> B13 <|@ <|@
    end_IR
  end_block
  begin_block
    name "B13"
    from_bci -1
    to_bci -1
    predecessors "B1" "B3" "B5" "B7" "B9" "B12" 
    successors 
    xhandlers
    flags 
    probability 2366641604183195648
    begin_IR
      LIR
      nr   88  <|@ instruction [] = LABEL numbPhis: 1 align: false label: ? <|@ <|@
      nr   90  <|@ instruction MOV (x: [r15|QWORD + 668], y: r10|DWORD) size: DWORD <|@ <|@
      nr   92  <|@ instruction MOV (x: [r15|QWORD + 680], y: r12|ILLEGAL) size: QWORD <|@ <|@
      nr   94  <|@ st <@st|@reference-map: [rsi:0]
live-base-pointers: []
java.nio.Buffer.<init>(Buffer.java:197) [bci: 0]
locals: rsi|QWORD[.] rdx|DWORD rcx|DWORD r8|DWORD r9|DWORD 
>@ <|@ instruction DEOPT info [bci:0] <|@ <|@
    end_IR
  end_block
  begin_block
    name "B5"
    from_bci -1
    to_bci -1
    predecessors "B4" 
    successors "B13" 
    xhandlers
    flags 
    probability 2355382605114769408
    begin_IR
      LIR
      nr   68  <|@ instruction [] = LABEL numbPhis: 0 align: false label: ? <|@ <|@
      nr   -1  <|@ instruction r10|DWORD = MOVE input: int[-17683|0xffffffffffffbaed] // MoveResolver resolve mapping <|@ <|@
      nr   70  <|@ instruction JUMP ~[] destination: B5 -> B13 <|@ <|@
    end_IR
  end_block
  begin_block
    name "B12"
    from_bci -1
    to_bci -1
    predecessors "B10" 
    successors "B13" 
    xhandlers
    flags 
    probability 2355382605114769408
    begin_IR
      LIR
      nr   72  <|@ instruction [] = LABEL numbPhis: 0 align: false label: ? <|@ <|@
      nr   -1  <|@ instruction r10|DWORD = MOVE input: int[-19475|0xffffffffffffb3ed] // MoveResolver resolve mapping <|@ <|@
      nr   74  <|@ instruction JUMP ~[] destination: B12 -> B13 <|@ <|@
    end_IR
  end_block
  begin_block
    name "B9"
    from_bci -1
    to_bci -1
    predecessors "B8" 
    successors "B13" 
    xhandlers
    flags 
    probability 2355382605114769408
    begin_IR
      LIR
      nr   76  <|@ instruction [] = LABEL numbPhis: 0 align: false label: ? <|@ <|@
      nr   -1  <|@ instruction r10|DWORD = MOVE input: int[-18963|0xffffffffffffb5ed] // MoveResolver resolve mapping <|@ <|@
      nr   78  <|@ instruction JUMP ~[] destination: B9 -> B13 <|@ <|@
    end_IR
  end_block
  begin_block
    name "B3"
    from_bci -1
    to_bci -1
    predecessors "B2" 
    successors "B13" 
    xhandlers
    flags 
    probability 2355382605114769408
    begin_IR
      LIR
      nr   80  <|@ instruction [] = LABEL numbPhis: 0 align: false label: ? <|@ <|@
      nr   -1  <|@ instruction r10|DWORD = MOVE input: int[-17427|0xffffffffffffbbed] // MoveResolver resolve mapping <|@ <|@
      nr   82  <|@ instruction JUMP ~[] destination: B3 -> B13 <|@ <|@
    end_IR
  end_block
  begin_block
    name "B7"
    from_bci -1
    to_bci -1
    predecessors "B6" 
    successors "B13" 
    xhandlers
    flags 
    probability 2355382605114769408
    begin_IR
      LIR
      nr   84  <|@ instruction [] = LABEL numbPhis: 0 align: false label: ? <|@ <|@
      nr   -1  <|@ instruction r10|DWORD = MOVE input: int[-18707|0xffffffffffffb6ed] // MoveResolver resolve mapping <|@ <|@
      nr   86  <|@ instruction JUMP ~[] destination: B7 -> B13 <|@ <|@
    end_IR
  end_block
end_cfg
begin_bytecodes
     0: aload_0       
     1: invokespecial #0          // java.lang.Object.<init>:()void
     4: aload_0       
     5: iconst_m1     
     6: putfield      #1          // mark:int
     9: aload_0       
    10: iconst_0      
    11: putfield      #2          // position:int
    14: iload         4
    16: ifge          47
    19: new           #5          // java.lang.IllegalArgumentException
    22: dup           
    23: new           #6          // java.lang.StringBuilder
    26: dup           
    27: invokespecial #3          // java.lang.StringBuilder.<init>:()void
    30: ldc           #8          // "Negative capacity: "
    32: invokevirtual #4          // java.lang.StringBuilder.append:(java.lang.String)java.lang.StringBuilder
    35: iload         4
    37: invokevirtual #5          // java.lang.StringBuilder.append:(int)java.lang.StringBuilder
    40: invokevirtual #6          // java.lang.StringBuilder.toString:()java.lang.String
    43: invokespecial #7          // java.lang.IllegalArgumentException.<init>:(java.lang.String)void
    46: athrow        
    47: aload_0       
    48: iload         4
    50: putfield      #8          // capacity:int
    53: aload_0       
    54: iload_3       
    55: invokevirtual #9          // limit:(int)java.nio.Buffer
    58: pop           
    59: aload_0       
    60: iload_2       
    61: invokevirtual #10         // position:(int)java.nio.Buffer
    64: pop           
    65: iload_1       
    66: iflt          120
    69: iload_1       
    70: iload_2       
    71: if_icmple     115
    74: new           #5          // java.lang.IllegalArgumentException
    77: dup           
    78: new           #6          // java.lang.StringBuilder
    81: dup           
    82: invokespecial #3          // java.lang.StringBuilder.<init>:()void
    85: ldc           #16         // "mark > position: ("
    87: invokevirtual #4          // java.lang.StringBuilder.append:(java.lang.String)java.lang.StringBuilder
    90: iload_1       
    91: invokevirtual #5          // java.lang.StringBuilder.append:(int)java.lang.StringBuilder
    94: ldc           #17         // " > "
    96: invokevirtual #4          // java.lang.StringBuilder.append:(java.lang.String)java.lang.StringBuilder
    99: iload_2       
   100: invokevirtual #5          // java.lang.StringBuilder.append:(int)java.lang.StringBuilder
   103: ldc           #18         // ")"
   105: invokevirtual #4          // java.lang.StringBuilder.append:(java.lang.String)java.lang.StringBuilder
   108: invokevirtual #6          // java.lang.StringBuilder.toString:()java.lang.String
   111: invokespecial #7          // java.lang.IllegalArgumentException.<init>:(java.lang.String)void
   114: athrow        
   115: aload_0       
   116: iload_1       
   117: putfield      #1          // mark:int
   120: return        
   <|@
end_bytecodes
begin_cfg
  name "After code generation"
end_cfg
begin_nmethod
  <<<HexCodeFile
  Platform AMD64 64  <||@
  HexCode 0 448b560849c1e203493bc20f85efffffff900f1f80000000000f1f800000000089842400c0feff4883ec1848896c24104585c90f8c54000000453bc10f8f7d0000004585c00f8c5c000000413bc80f8f7300000085c90f8c5b00000085d20f8d4b000000c7460cffffffff4489661844894e204489461c894e18488b6c24104883c418850500000000c5f877c341baedbfffff4589979c0200004d89a7a8020000e8000000009041baedbaffffebe441baedb3ffffebdc41baedb5ffffebd441baedbbffffebcc41baedb6ffffebc4e80000000090e80000000090  <||@
  Comment 0 2  <||@
  Comment 11 {Field[name=CompilerToVM::Data::SharedRuntime_ic_miss_stub, type=address, offset=0, address=0x10b0a1f78, value=0x118a04e60]:0x118a04e60}  <||@
  Comment 32 [stack overflow check]  <||@
  Comment 32 3  <||@
  Comment 32 1  <||@
  Comment 43 block B0 null  <||@
  Comment 43 0 [rsi|QWORD[.], rdx|DWORD, rcx|DWORD, r8|DWORD, r9|DWORD, rbp|QWORD] = LABEL numbPhis: 0 align: false label: ?  <||@
  Comment 43 2 stack:16|QWORD = MOVE rbp|QWORD moveKind: QWORD  <||@
  Comment 48 4 [] = HOTSPOTLOCKSTACK frameMapBuilder: org.graalvm.compiler.lir.amd64.AMD64FrameMapBuilder@69596961 slotKind: QWORD  <||@
  Comment 48 16 TEST (x: r9|DWORD, y: r9|DWORD) size: DWORD  <||@
  Comment 51 18 BRANCH trueDestinationProbability: 0.0 condition: < trueDestination: B0 -> B1 falseDestination: B0 -> B2  <||@
  Comment 57 block B2 null  <||@
  Comment 57 20 [] = LABEL numbPhis: 0 align: false label: ?  <||@
  Comment 57 22 CMP (x: r8|DWORD, y: r9|DWORD) size: DWORD  <||@
  Comment 60 24 BRANCH trueDestinationProbability: 0.0 condition: > trueDestination: B2 -> B3 falseDestination: B2 -> B4  <||@
  Comment 66 block B4 null  <||@
  Comment 66 26 [] = LABEL numbPhis: 0 align: false label: ?  <||@
  Comment 66 28 TEST (x: r8|DWORD, y: r8|DWORD) size: DWORD  <||@
  Comment 69 30 BRANCH trueDestinationProbability: 0.0 condition: < trueDestination: B4 -> B5 falseDestination: B4 -> B6  <||@
  Comment 75 block B6 null  <||@
  Comment 75 32 [] = LABEL numbPhis: 0 align: false label: ?  <||@
  Comment 75 34 CMP (x: rcx|DWORD, y: r8|DWORD) size: DWORD  <||@
  Comment 78 36 BRANCH trueDestinationProbability: 0.0 condition: > trueDestination: B6 -> B7 falseDestination: B6 -> B8  <||@
  Comment 84 block B8 null  <||@
  Comment 84 38 [] = LABEL numbPhis: 0 align: false label: ?  <||@
  Comment 84 40 TEST (x: rcx|DWORD, y: rcx|DWORD) size: DWORD  <||@
  Comment 86 42 BRANCH trueDestinationProbability: 0.0 condition: < trueDestination: B8 -> B9 falseDestination: B8 -> B10  <||@
  Comment 92 block B10 null  <||@
  Comment 92 44 [] = LABEL numbPhis: 0 align: false label: ?  <||@
  Comment 92 46 TEST (x: rdx|DWORD, y: rdx|DWORD) size: DWORD  <||@
  Comment 94 48 BRANCH trueDestinationProbability: 1.0 condition: < trueDestination: B10 -> B11 falseDestination: B10 -> B12  <||@
  Comment 100 block B11 null  <||@
  Comment 100 50 [] = LABEL numbPhis: 0 align: false label: ?  <||@
  Comment 100 52 MOV [rsi|QWORD[.] + 12] y: -1 size: DWORD  <||@
  Comment 107 54 MOV (x: [rsi|QWORD[.] + 24], y: r12|ILLEGAL) size: DWORD  <||@
  Comment 111 56 MOV (x: [rsi|QWORD[.] + 32], y: r9|DWORD) size: DWORD  <||@
  Comment 115 58 MOV (x: [rsi|QWORD[.] + 28], y: r8|DWORD) size: DWORD  <||@
  Comment 119 60 MOV (x: [rsi|QWORD[.] + 24], y: rcx|DWORD) size: DWORD  <||@
  Comment 122 62 RETURN (savedRbp: stack:16|QWORD, value: -) isStub: false thread: r15 scratchForSafepointOnReturn: rcx config: org.graalvm.compiler.hotspot.GraalHotSpotVMConfig@69d7a7b  <||@
  Comment 131 12  <||@
  Comment 141 block B1 null  <||@
  Comment 141 64 [] = LABEL numbPhis: 0 align: false label: ?  <||@
  Comment 141 -1 r10|DWORD = MOVE input: int[-16403|0xffffffffffffbfed]  <||@
  Comment 147 66 JUMP ~[] destination: B1 -> B13  <||@
  Comment 147 block B13 null  <||@
  Comment 147 88 [] = LABEL numbPhis: 1 align: false label: ?  <||@
  Comment 147 90 MOV (x: [r15|QWORD + 668], y: r10|DWORD) size: DWORD  <||@
  Comment 154 92 MOV (x: [r15|QWORD + 680], y: r12|ILLEGAL) size: QWORD  <||@
  Comment 161 94 DEOPT info [bci:0]  <||@
  Comment 161 {Field[name=CompilerToVM::Data::SharedRuntime_deopt_blob_uncommon_trap, type=address, offset=0, address=0x10b0a1f90, value=0x118a065fe]:0x118a065fe}  <||@
  Comment 166 [rsi:0]at java.nio.Buffer.<init>(Buffer.java:197) [bci: 0, duringCall: false, rethrow: false]
              |0             |1          |2          |3         |4        
     locals:  |rsi|QWORD[.]  |rdx|DWORD  |rcx|DWORD  |r8|DWORD  |r9|DWORD   <||@
  Comment 167 block B5 null  <||@
  Comment 167 68 [] = LABEL numbPhis: 0 align: false label: ?  <||@
  Comment 167 -1 r10|DWORD = MOVE input: int[-17683|0xffffffffffffbaed]  <||@
  Comment 173 70 JUMP ~[] destination: B5 -> B13  <||@
  Comment 175 block B12 null  <||@
  Comment 175 72 [] = LABEL numbPhis: 0 align: false label: ?  <||@
  Comment 175 -1 r10|DWORD = MOVE input: int[-19475|0xffffffffffffb3ed]  <||@
  Comment 181 74 JUMP ~[] destination: B12 -> B13  <||@
  Comment 183 block B9 null  <||@
  Comment 183 76 [] = LABEL numbPhis: 0 align: false label: ?  <||@
  Comment 183 -1 r10|DWORD = MOVE input: int[-18963|0xffffffffffffb5ed]  <||@
  Comment 189 78 JUMP ~[] destination: B9 -> B13  <||@
  Comment 191 block B3 null  <||@
  Comment 191 80 [] = LABEL numbPhis: 0 align: false label: ?  <||@
  Comment 191 -1 r10|DWORD = MOVE input: int[-17427|0xffffffffffffbbed]  <||@
  Comment 197 82 JUMP ~[] destination: B3 -> B13  <||@
  Comment 199 block B7 null  <||@
  Comment 199 84 [] = LABEL numbPhis: 0 align: false label: ?  <||@
  Comment 199 -1 r10|DWORD = MOVE input: int[-18707|0xffffffffffffb6ed]  <||@
  Comment 205 86 JUMP ~[] destination: B7 -> B13  <||@
  Comment 207 {Stub<ExceptionHandlerStub.exceptionHandler>@0x118dff7a0:CallingConvention[rax|QWORD[.], rdx|QWORD]:CallingConvention[rax|QWORD[.], rdx|QWORD]; temps=rdi|ILLEGAL,xmm0|ILLEGAL,xmm1|ILLEGAL,xmm2|ILLEGAL,xmm3|ILLEGAL,xmm4|ILLEGAL,xmm5|ILLEGAL,xmm6|ILLEGAL,xmm7|ILLEGAL,xmm8|ILLEGAL,xmm9|ILLEGAL,xmm10|ILLEGAL,xmm11|ILLEGAL,xmm12|ILLEGAL,xmm13|ILLEGAL,xmm14|ILLEGAL,xmm15|ILLEGAL,xmm16|ILLEGAL,xmm17|ILLEGAL,xmm18|ILLEGAL,xmm19|ILLEGAL,xmm20|ILLEGAL,xmm21|ILLEGAL,xmm22|ILLEGAL,xmm23|ILLEGAL,xmm24|ILLEGAL,xmm25|ILLEGAL,xmm26|ILLEGAL,xmm27|ILLEGAL,xmm28|ILLEGAL,xmm29|ILLEGAL,xmm30|ILLEGAL,xmm31|ILLEGAL,rax|ILLEGAL,rcx|ILLEGAL,rdx|ILLEGAL,rsi|ILLEGAL,r8|ILLEGAL,r9|ILLEGAL,r10|ILLEGAL,r11|ILLEGAL}  <||@
  Comment 207 4  <||@
  Comment 213 {Field[name=CompilerToVM::Data::SharedRuntime_deopt_blob_unpack, type=address, offset=0, address=0x10b0a1f88, value=0x118a06500]:0x118a06500}  <||@
  Comment 213 5  <||@
  HexCodeFile>>> <|@
end_nmethod
begin_compilation
  name " HotSpotCompilation-3553[java.nio.Buffer.<init>(int, int, int, int)]"
  method "HotSpotCompilation-3553[java.nio.Buffer.<init>(int, int, int, int)]"
  date 1526687584129
end_compilation
begin_cfg
  name "After code installation"
end_cfg
begin_nmethod
  <<<HexCodeFile
  Platform AMD64 64  <||@
  HexCode 1198e29e0 448b560849c1e203493bc20f856f2412ff900f1f80000000000f1f800000000089842400c0feff4883ec1848896c24104585c90f8c54000000453bc10f8f7d0000004585c00f8c5c000000413bc80f8f7300000085c90f8c5b00000085d20f8d4b000000c7460cffffffff4489661844894e204489461c894e18488b6c24104883c41885059d955ff0c5f877c341baedbfffff4589979c0200004d89a7a8020000e8783b12ff9041baedbaffffebe441baedb3ffffebdc41baedb5ffffebd441baedbbffffebcc41baedb6ffffebc4e8eccc51ff90e8463a12ff90f4f4f4f4f4  <||@
  Comment 0 2  <||@
  Comment 11 {Field[name=CompilerToVM::Data::SharedRuntime_ic_miss_stub, type=address, offset=0, address=0x10b0a1f78, value=0x118a04e60]:0x118a04e60}  <||@
  Comment 32 [stack overflow check]  <||@
  Comment 32 3  <||@
  Comment 32 1  <||@
  Comment 43 block B0 null  <||@
  Comment 43 0 [rsi|QWORD[.], rdx|DWORD, rcx|DWORD, r8|DWORD, r9|DWORD, rbp|QWORD] = LABEL numbPhis: 0 align: false label: ?  <||@
  Comment 43 2 stack:16|QWORD = MOVE rbp|QWORD moveKind: QWORD  <||@
  Comment 48 4 [] = HOTSPOTLOCKSTACK frameMapBuilder: org.graalvm.compiler.lir.amd64.AMD64FrameMapBuilder@69596961 slotKind: QWORD  <||@
  Comment 48 16 TEST (x: r9|DWORD, y: r9|DWORD) size: DWORD  <||@
  Comment 51 18 BRANCH trueDestinationProbability: 0.0 condition: < trueDestination: B0 -> B1 falseDestination: B0 -> B2  <||@
  Comment 57 block B2 null  <||@
  Comment 57 20 [] = LABEL numbPhis: 0 align: false label: ?  <||@
  Comment 57 22 CMP (x: r8|DWORD, y: r9|DWORD) size: DWORD  <||@
  Comment 60 24 BRANCH trueDestinationProbability: 0.0 condition: > trueDestination: B2 -> B3 falseDestination: B2 -> B4  <||@
  Comment 66 block B4 null  <||@
  Comment 66 26 [] = LABEL numbPhis: 0 align: false label: ?  <||@
  Comment 66 28 TEST (x: r8|DWORD, y: r8|DWORD) size: DWORD  <||@
  Comment 69 30 BRANCH trueDestinationProbability: 0.0 condition: < trueDestination: B4 -> B5 falseDestination: B4 -> B6  <||@
  Comment 75 block B6 null  <||@
  Comment 75 32 [] = LABEL numbPhis: 0 align: false label: ?  <||@
  Comment 75 34 CMP (x: rcx|DWORD, y: r8|DWORD) size: DWORD  <||@
  Comment 78 36 BRANCH trueDestinationProbability: 0.0 condition: > trueDestination: B6 -> B7 falseDestination: B6 -> B8  <||@
  Comment 84 block B8 null  <||@
  Comment 84 38 [] = LABEL numbPhis: 0 align: false label: ?  <||@
  Comment 84 40 TEST (x: rcx|DWORD, y: rcx|DWORD) size: DWORD  <||@
  Comment 86 42 BRANCH trueDestinationProbability: 0.0 condition: < trueDestination: B8 -> B9 falseDestination: B8 -> B10  <||@
  Comment 92 block B10 null  <||@
  Comment 92 44 [] = LABEL numbPhis: 0 align: false label: ?  <||@
  Comment 92 46 TEST (x: rdx|DWORD, y: rdx|DWORD) size: DWORD  <||@
  Comment 94 48 BRANCH trueDestinationProbability: 1.0 condition: < trueDestination: B10 -> B11 falseDestination: B10 -> B12  <||@
  Comment 100 block B11 null  <||@
  Comment 100 50 [] = LABEL numbPhis: 0 align: false label: ?  <||@
  Comment 100 52 MOV [rsi|QWORD[.] + 12] y: -1 size: DWORD  <||@
  Comment 107 54 MOV (x: [rsi|QWORD[.] + 24], y: r12|ILLEGAL) size: DWORD  <||@
  Comment 111 56 MOV (x: [rsi|QWORD[.] + 32], y: r9|DWORD) size: DWORD  <||@
  Comment 115 58 MOV (x: [rsi|QWORD[.] + 28], y: r8|DWORD) size: DWORD  <||@
  Comment 119 60 MOV (x: [rsi|QWORD[.] + 24], y: rcx|DWORD) size: DWORD  <||@
  Comment 122 62 RETURN (savedRbp: stack:16|QWORD, value: -) isStub: false thread: r15 scratchForSafepointOnReturn: rcx config: org.graalvm.compiler.hotspot.GraalHotSpotVMConfig@69d7a7b  <||@
  Comment 131 12  <||@
  Comment 141 block B1 null  <||@
  Comment 141 64 [] = LABEL numbPhis: 0 align: false label: ?  <||@
  Comment 141 -1 r10|DWORD = MOVE input: int[-16403|0xffffffffffffbfed]  <||@
  Comment 147 66 JUMP ~[] destination: B1 -> B13  <||@
  Comment 147 block B13 null  <||@
  Comment 147 88 [] = LABEL numbPhis: 1 align: false label: ?  <||@
  Comment 147 90 MOV (x: [r15|QWORD + 668], y: r10|DWORD) size: DWORD  <||@
  Comment 154 92 MOV (x: [r15|QWORD + 680], y: r12|ILLEGAL) size: QWORD  <||@
  Comment 161 94 DEOPT info [bci:0]  <||@
  Comment 161 {Field[name=CompilerToVM::Data::SharedRuntime_deopt_blob_uncommon_trap, type=address, offset=0, address=0x10b0a1f90, value=0x118a065fe]:0x118a065fe}  <||@
  Comment 166 [rsi:0]at java.nio.Buffer.<init>(Buffer.java:197) [bci: 0, duringCall: false, rethrow: false]
              |0             |1          |2          |3         |4        
     locals:  |rsi|QWORD[.]  |rdx|DWORD  |rcx|DWORD  |r8|DWORD  |r9|DWORD   <||@
  Comment 167 block B5 null  <||@
  Comment 167 68 [] = LABEL numbPhis: 0 align: false label: ?  <||@
  Comment 167 -1 r10|DWORD = MOVE input: int[-17683|0xffffffffffffbaed]  <||@
  Comment 173 70 JUMP ~[] destination: B5 -> B13  <||@
  Comment 175 block B12 null  <||@
  Comment 175 72 [] = LABEL numbPhis: 0 align: false label: ?  <||@
  Comment 175 -1 r10|DWORD = MOVE input: int[-19475|0xffffffffffffb3ed]  <||@
  Comment 181 74 JUMP ~[] destination: B12 -> B13  <||@
  Comment 183 block B9 null  <||@
  Comment 183 76 [] = LABEL numbPhis: 0 align: false label: ?  <||@
  Comment 183 -1 r10|DWORD = MOVE input: int[-18963|0xffffffffffffb5ed]  <||@
  Comment 189 78 JUMP ~[] destination: B9 -> B13  <||@
  Comment 191 block B3 null  <||@
  Comment 191 80 [] = LABEL numbPhis: 0 align: false label: ?  <||@
  Comment 191 -1 r10|DWORD = MOVE input: int[-17427|0xffffffffffffbbed]  <||@
  Comment 197 82 JUMP ~[] destination: B3 -> B13  <||@
  Comment 199 block B7 null  <||@
  Comment 199 84 [] = LABEL numbPhis: 0 align: false label: ?  <||@
  Comment 199 -1 r10|DWORD = MOVE input: int[-18707|0xffffffffffffb6ed]  <||@
  Comment 205 86 JUMP ~[] destination: B7 -> B13  <||@
  Comment 207 {Stub<ExceptionHandlerStub.exceptionHandler>@0x118dff7a0:CallingConvention[rax|QWORD[.], rdx|QWORD]:CallingConvention[rax|QWORD[.], rdx|QWORD]; temps=rdi|ILLEGAL,xmm0|ILLEGAL,xmm1|ILLEGAL,xmm2|ILLEGAL,xmm3|ILLEGAL,xmm4|ILLEGAL,xmm5|ILLEGAL,xmm6|ILLEGAL,xmm7|ILLEGAL,xmm8|ILLEGAL,xmm9|ILLEGAL,xmm10|ILLEGAL,xmm11|ILLEGAL,xmm12|ILLEGAL,xmm13|ILLEGAL,xmm14|ILLEGAL,xmm15|ILLEGAL,xmm16|ILLEGAL,xmm17|ILLEGAL,xmm18|ILLEGAL,xmm19|ILLEGAL,xmm20|ILLEGAL,xmm21|ILLEGAL,xmm22|ILLEGAL,xmm23|ILLEGAL,xmm24|ILLEGAL,xmm25|ILLEGAL,xmm26|ILLEGAL,xmm27|ILLEGAL,xmm28|ILLEGAL,xmm29|ILLEGAL,xmm30|ILLEGAL,xmm31|ILLEGAL,rax|ILLEGAL,rcx|ILLEGAL,rdx|ILLEGAL,rsi|ILLEGAL,r8|ILLEGAL,r9|ILLEGAL,r10|ILLEGAL,r11|ILLEGAL}  <||@
  Comment 207 4  <||@
  Comment 213 {Field[name=CompilerToVM::Data::SharedRuntime_deopt_blob_unpack, type=address, offset=0, address=0x10b0a1f88, value=0x118a06500]:0x118a06500}  <||@
  Comment 213 5  <||@
  HexCodeFile>>> <|@
end_nmethod
