begin_compilation
  name " HotSpotCompilation-7681[java.nio.Buffer.flip()]"
  method "HotSpotCompilation-7681[java.nio.Buffer.flip()]"
  date 1526687582819
end_compilation
begin_cfg
  name "Final HIR schedule"
  begin_block
    name "B0"
    from_bci -1
    to_bci -1
    predecessors 
    successors 
    xhandlers
    flags 
    probability 4607182418800017408
    begin_IR
      HIR
f <@#|@fixed with next>@ <|@
tid v0 <|@
d <@d|@=== Debug Properties ===
stamp: void
=== Inputs ===
stateAfter: - 
=== Succesors ===
next: i24 
=== Usages ===
=== Predecessor ===
- >@ <|@
instruction <@StartNode|@org.graalvm.compiler.nodes.StartNode>@ stateAfter: - #next: i24  <|@  <|@
f <@~|@floating>@ <|@
tid a1 <|@
d <@d|@=== Debug Properties ===
index: 0
stamp: a! Ljava/nio/Buffer;
uncheckedStamp: [null]
=== Inputs ===
=== Succesors ===
=== Usages ===
v12 v25 v26 v27 
=== Predecessor ===
- >@ <|@
instruction <@Parameter|@org.graalvm.compiler.nodes.ParameterNode>@  <|@  <|@
f <@~|@floating>@ <|@
tid v25 <|@
d <@d|@=== Debug Properties ===
displacement: 24
scale: Times1
stamp: void*
=== Inputs ===
base: a1 
index: - 
=== Succesors ===
=== Usages ===
i24 v19 
=== Predecessor ===
- >@ <|@
instruction <@AMD64Address|@org.graalvm.compiler.core.amd64.AMD64AddressNode>@ base: a1 index: -  <|@  <|@
f <@#|@fixed with next>@ <|@
tid i24 <|@
d <@d|@=== Debug Properties ===
barrierType: NONE
forceFixed: false
location: Buffer.position
nodeSourcePosition: at java.nio.Buffer.flip(Buffer.java:357) [bci: 2]
nullCheck: false
stamp: i32
=== Inputs ===
stateBefore: - 
guard: - 
address: v25 
=== Succesors ===
next: v18 
=== Usages ===
v18 
=== Predecessor ===
v0 >@ <|@
instruction <@Read|@org.graalvm.compiler.nodes.memory.ReadNode>@ stateBefore: - guard: - address: v25 #next: v18  <|@  <|@
f <@~|@floating>@ <|@
tid v26 <|@
d <@d|@=== Debug Properties ===
displacement: 28
scale: Times1
stamp: void*
=== Inputs ===
base: a1 
index: - 
=== Succesors ===
=== Usages ===
v18 
=== Predecessor ===
- >@ <|@
instruction <@AMD64Address|@org.graalvm.compiler.core.amd64.AMD64AddressNode>@ base: a1 index: -  <|@  <|@
f <@#|@fixed with next>@ <|@
tid v18 <|@
d <@d|@=== Debug Properties ===
barrierType: NONE
location: Buffer.limit
nodeSourcePosition: at java.nio.Buffer.flip(Buffer.java:357) [bci: 5]
nullCheck: false
stamp: void
=== Inputs ===
stateBefore: - 
guard: - 
address: v26 
value: i24 
stateAfter: - 
lastLocationAccess: - 
=== Succesors ===
next: v19 
=== Usages ===
=== Predecessor ===
i24 >@ <|@
instruction <@Write|@org.graalvm.compiler.nodes.memory.WriteNode>@ stateBefore: - guard: - address: v26 value: i24 stateAfter: - lastLocationAccess: - #next: v19  <|@  <|@
f <@~|@floating>@ <|@
tid i6 <|@
d <@d|@=== Debug Properties ===
isDefaultStable: false
nodeSourcePosition: at java.nio.Buffer.flip(Buffer.java:358) [bci: 9]
rawvalue: 0
stableDimension: 0
stamp: i32 [0] ⇈0000000000000000
stampKind: i32
value: int[0|0x0]
=== Inputs ===
=== Succesors ===
=== Usages ===
v19 
=== Predecessor ===
- >@ <|@
instruction <@Constant|@org.graalvm.compiler.nodes.ConstantNode>@  <|@  <|@
f <@#|@fixed with next>@ <|@
tid v19 <|@
d <@d|@=== Debug Properties ===
barrierType: NONE
location: Buffer.position
nodeSourcePosition: at java.nio.Buffer.flip(Buffer.java:358) [bci: 10]
nullCheck: false
stamp: void
=== Inputs ===
stateBefore: - 
guard: - 
address: v25 
value: i6 
stateAfter: - 
lastLocationAccess: - 
=== Succesors ===
next: v22 
=== Usages ===
=== Predecessor ===
v18 >@ <|@
instruction <@Write|@org.graalvm.compiler.nodes.memory.WriteNode>@ stateBefore: - guard: - address: v25 value: i6 stateAfter: - lastLocationAccess: - #next: v22  <|@  <|@
f <@~|@floating>@ <|@
tid v27 <|@
d <@d|@=== Debug Properties ===
displacement: 12
scale: Times1
stamp: void*
=== Inputs ===
base: a1 
index: - 
=== Succesors ===
=== Usages ===
v22 
=== Predecessor ===
- >@ <|@
instruction <@AMD64Address|@org.graalvm.compiler.core.amd64.AMD64AddressNode>@ base: a1 index: -  <|@  <|@
f <@~|@floating>@ <|@
tid i9 <|@
d <@d|@=== Debug Properties ===
isDefaultStable: false
nodeSourcePosition: at java.nio.Buffer.flip(Buffer.java:359) [bci: 14]
rawvalue: -1
stableDimension: 0
stamp: i32 [-1] ⇊00000000ffffffff
stampKind: i32
value: int[-1|0xffffffffffffffff]
=== Inputs ===
=== Succesors ===
=== Usages ===
v22 
=== Predecessor ===
- >@ <|@
instruction <@Constant|@org.graalvm.compiler.nodes.ConstantNode>@  <|@  <|@
f <@#|@fixed with next>@ <|@
tid v22 <|@
d <@d|@=== Debug Properties ===
barrierType: NONE
location: Buffer.mark
nodeSourcePosition: at java.nio.Buffer.flip(Buffer.java:359) [bci: 15]
nullCheck: false
stamp: void
=== Inputs ===
stateBefore: - 
guard: - 
address: v27 
value: i9 
stateAfter: - 
lastLocationAccess: - 
=== Succesors ===
next: v12 
=== Usages ===
=== Predecessor ===
v19 >@ <|@
instruction <@Write|@org.graalvm.compiler.nodes.memory.WriteNode>@ stateBefore: - guard: - address: v27 value: i9 stateAfter: - lastLocationAccess: - #next: v12  <|@  <|@
f <@*|@fixed>@ <|@
tid v12 <|@
d <@d|@=== Debug Properties ===
nodeSourcePosition: at java.nio.Buffer.flip(Buffer.java:360) [bci: 19]
stamp: void
=== Inputs ===
result: a1 
memoryMap: - 
=== Succesors ===
=== Usages ===
=== Predecessor ===
v22 >@ <|@
instruction <@Return|@org.graalvm.compiler.nodes.ReturnNode>@ result: a1 memoryMap: -  <|@  <|@
    end_IR
  end_block
end_cfg
begin_cfg
  name "After LIR generation"
  begin_block
    name "B0"
    from_bci -1
    to_bci -1
    predecessors 
    successors 
    xhandlers
    flags 
    probability 4607182418800017408
    begin_IR
      HIR
f <@#|@fixed with next>@ <|@
tid v0 <|@
d <@d|@=== Debug Properties ===
stamp: void
=== Inputs ===
stateAfter: - 
=== Succesors ===
next: i24 
=== Usages ===
=== Predecessor ===
- >@ <|@
instruction <@StartNode|@org.graalvm.compiler.nodes.StartNode>@ stateAfter: - #next: i24  <|@  <|@
f <@~|@floating>@ <|@
tid a1 <|@
result v0|QWORD[.] <|@
d <@d|@=== Debug Properties ===
index: 0
stamp: a! Ljava/nio/Buffer;
uncheckedStamp: [null]
=== Inputs ===
=== Succesors ===
=== Usages ===
v12 v25 v26 v27 
=== Predecessor ===
- >@ <|@
instruction <@Parameter|@org.graalvm.compiler.nodes.ParameterNode>@  <|@  <|@
f <@~|@floating>@ <|@
tid v25 <|@
result [v0|QWORD[.] + 24] <|@
d <@d|@=== Debug Properties ===
displacement: 24
scale: Times1
stamp: void*
=== Inputs ===
base: a1 
index: - 
=== Succesors ===
=== Usages ===
i24 v19 
=== Predecessor ===
- >@ <|@
instruction <@AMD64Address|@org.graalvm.compiler.core.amd64.AMD64AddressNode>@ base: a1 index: -  <|@  <|@
f <@#|@fixed with next>@ <|@
tid i24 <|@
result v1|DWORD <|@
d <@d|@=== Debug Properties ===
barrierType: NONE
forceFixed: false
location: Buffer.position
nodeSourcePosition: at java.nio.Buffer.flip(Buffer.java:357) [bci: 2]
nullCheck: false
stamp: i32
=== Inputs ===
stateBefore: - 
guard: - 
address: v25 
=== Succesors ===
next: v18 
=== Usages ===
v18 
=== Predecessor ===
v0 >@ <|@
instruction <@Read|@org.graalvm.compiler.nodes.memory.ReadNode>@ stateBefore: - guard: - address: v25 #next: v18  <|@  <|@
f <@~|@floating>@ <|@
tid v26 <|@
result [v0|QWORD[.] + 28] <|@
d <@d|@=== Debug Properties ===
displacement: 28
scale: Times1
stamp: void*
=== Inputs ===
base: a1 
index: - 
=== Succesors ===
=== Usages ===
v18 
=== Predecessor ===
- >@ <|@
instruction <@AMD64Address|@org.graalvm.compiler.core.amd64.AMD64AddressNode>@ base: a1 index: -  <|@  <|@
f <@#|@fixed with next>@ <|@
tid v18 <|@
d <@d|@=== Debug Properties ===
barrierType: NONE
location: Buffer.limit
nodeSourcePosition: at java.nio.Buffer.flip(Buffer.java:357) [bci: 5]
nullCheck: false
stamp: void
=== Inputs ===
stateBefore: - 
guard: - 
address: v26 
value: i24 
stateAfter: - 
lastLocationAccess: - 
=== Succesors ===
next: v19 
=== Usages ===
=== Predecessor ===
i24 >@ <|@
instruction <@Write|@org.graalvm.compiler.nodes.memory.WriteNode>@ stateBefore: - guard: - address: v26 value: i24 stateAfter: - lastLocationAccess: - #next: v19  <|@  <|@
f <@~|@floating>@ <|@
tid i6 <|@
result int[0|0x0] <|@
d <@d|@=== Debug Properties ===
isDefaultStable: false
nodeSourcePosition: at java.nio.Buffer.flip(Buffer.java:358) [bci: 9]
rawvalue: 0
stableDimension: 0
stamp: i32 [0] ⇈0000000000000000
stampKind: i32
value: int[0|0x0]
=== Inputs ===
=== Succesors ===
=== Usages ===
v19 
=== Predecessor ===
- >@ <|@
instruction <@Constant|@org.graalvm.compiler.nodes.ConstantNode>@  <|@  <|@
f <@#|@fixed with next>@ <|@
tid v19 <|@
d <@d|@=== Debug Properties ===
barrierType: NONE
location: Buffer.position
nodeSourcePosition: at java.nio.Buffer.flip(Buffer.java:358) [bci: 10]
nullCheck: false
stamp: void
=== Inputs ===
stateBefore: - 
guard: - 
address: v25 
value: i6 
stateAfter: - 
lastLocationAccess: - 
=== Succesors ===
next: v22 
=== Usages ===
=== Predecessor ===
v18 >@ <|@
instruction <@Write|@org.graalvm.compiler.nodes.memory.WriteNode>@ stateBefore: - guard: - address: v25 value: i6 stateAfter: - lastLocationAccess: - #next: v22  <|@  <|@
f <@~|@floating>@ <|@
tid v27 <|@
result [v0|QWORD[.] + 12] <|@
d <@d|@=== Debug Properties ===
displacement: 12
scale: Times1
stamp: void*
=== Inputs ===
base: a1 
index: - 
=== Succesors ===
=== Usages ===
v22 
=== Predecessor ===
- >@ <|@
instruction <@AMD64Address|@org.graalvm.compiler.core.amd64.AMD64AddressNode>@ base: a1 index: -  <|@  <|@
f <@~|@floating>@ <|@
tid i9 <|@
result int[-1|0xffffffffffffffff] <|@
d <@d|@=== Debug Properties ===
isDefaultStable: false
nodeSourcePosition: at java.nio.Buffer.flip(Buffer.java:359) [bci: 14]
rawvalue: -1
stableDimension: 0
stamp: i32 [-1] ⇊00000000ffffffff
stampKind: i32
value: int[-1|0xffffffffffffffff]
=== Inputs ===
=== Succesors ===
=== Usages ===
v22 
=== Predecessor ===
- >@ <|@
instruction <@Constant|@org.graalvm.compiler.nodes.ConstantNode>@  <|@  <|@
f <@#|@fixed with next>@ <|@
tid v22 <|@
d <@d|@=== Debug Properties ===
barrierType: NONE
location: Buffer.mark
nodeSourcePosition: at java.nio.Buffer.flip(Buffer.java:359) [bci: 15]
nullCheck: false
stamp: void
=== Inputs ===
stateBefore: - 
guard: - 
address: v27 
value: i9 
stateAfter: - 
lastLocationAccess: - 
=== Succesors ===
next: v12 
=== Usages ===
=== Predecessor ===
v19 >@ <|@
instruction <@Write|@org.graalvm.compiler.nodes.memory.WriteNode>@ stateBefore: - guard: - address: v27 value: i9 stateAfter: - lastLocationAccess: - #next: v12  <|@  <|@
f <@*|@fixed>@ <|@
tid v12 <|@
d <@d|@=== Debug Properties ===
nodeSourcePosition: at java.nio.Buffer.flip(Buffer.java:360) [bci: 19]
stamp: void
=== Inputs ===
result: a1 
memoryMap: - 
=== Succesors ===
=== Usages ===
=== Predecessor ===
v22 >@ <|@
instruction <@Return|@org.graalvm.compiler.nodes.ReturnNode>@ result: a1 memoryMap: -  <|@  <|@
    end_IR
    begin_IR
      LIR
      nr   -1  <|@ instruction [rsi|QWORD[.], rbp|QWORD] = LABEL numbPhis: 0 align: false label: ? <|@ <|@
      nr   -1  <|@ instruction v2|QWORD = MOVE rbp|QWORD moveKind: QWORD <|@ <|@
      nr   -1  <|@ instruction [] = HOTSPOTLOCKSTACK frameMapBuilder: org.graalvm.compiler.lir.amd64.AMD64FrameMapBuilder@5f405023 slotKind: QWORD <|@ <|@
      nr   -1  <|@ instruction v0|QWORD[.] = MOVE rsi|QWORD[.] moveKind: QWORD <|@ <|@
      nr   -1  <|@ instruction v1|DWORD = MOV [v0|QWORD[.] + 24] size: DWORD <|@ <|@
      nr   -1  <|@ instruction MOV (x: [v0|QWORD[.] + 28], y: v1|DWORD) size: DWORD <|@ <|@
      nr   -1  <|@ instruction MOV (x: [v0|QWORD[.] + 24], y: r12|ILLEGAL) size: DWORD <|@ <|@
      nr   -1  <|@ instruction MOV [v0|QWORD[.] + 12] y: -1 size: DWORD <|@ <|@
      nr   -1  <|@ instruction rax|QWORD[.] = MOVE v0|QWORD[.] moveKind: QWORD <|@ <|@
      nr   -1  <|@ instruction RETURN (savedRbp: v2|QWORD, value: rax|QWORD[.]) isStub: false thread: r15 scratchForSafepointOnReturn: rcx config: org.graalvm.compiler.hotspot.GraalHotSpotVMConfig@69d7a7b <|@ <|@
    end_IR
  end_block
end_cfg
begin_cfg
  name "After PreAllocationOptimizationStage"
  begin_block
    name "B0"
    from_bci -1
    to_bci -1
    predecessors 
    successors 
    xhandlers
    flags 
    probability 4607182418800017408
    begin_IR
      LIR
      nr   -1  <|@ instruction [rsi|QWORD[.], rbp|QWORD] = LABEL numbPhis: 0 align: false label: ? <|@ <|@
      nr   -1  <|@ instruction v2|QWORD = MOVE rbp|QWORD moveKind: QWORD <|@ <|@
      nr   -1  <|@ instruction [] = HOTSPOTLOCKSTACK frameMapBuilder: org.graalvm.compiler.lir.amd64.AMD64FrameMapBuilder@5f405023 slotKind: QWORD <|@ <|@
      nr   -1  <|@ instruction v0|QWORD[.] = MOVE rsi|QWORD[.] moveKind: QWORD <|@ <|@
      nr   -1  <|@ instruction v1|DWORD = MOV [v0|QWORD[.] + 24] size: DWORD <|@ <|@
      nr   -1  <|@ instruction MOV (x: [v0|QWORD[.] + 28], y: v1|DWORD) size: DWORD <|@ <|@
      nr   -1  <|@ instruction MOV (x: [v0|QWORD[.] + 24], y: r12|ILLEGAL) size: DWORD <|@ <|@
      nr   -1  <|@ instruction MOV [v0|QWORD[.] + 12] y: -1 size: DWORD <|@ <|@
      nr   -1  <|@ instruction rax|QWORD[.] = MOVE v0|QWORD[.] moveKind: QWORD <|@ <|@
      nr   -1  <|@ instruction RETURN (savedRbp: v2|QWORD, value: rax|QWORD[.]) isStub: false thread: r15 scratchForSafepointOnReturn: rcx config: org.graalvm.compiler.hotspot.GraalHotSpotVMConfig@69d7a7b <|@ <|@
    end_IR
  end_block
end_cfg
begin_bytecodes
     0: aload_0       
     1: aload_0       
     2: getfield      #2          // position:int
     5: putfield      #11         // limit:int
     8: aload_0       
     9: iconst_0      
    10: putfield      #2          // position:int
    13: aload_0       
    14: iconst_m1     
    15: putfield      #1          // mark:int
    18: aload_0       
    19: areturn       
   <|@
end_bytecodes
begin_cfg
  name "After AllocationStage"
  begin_block
    name "B0"
    from_bci -1
    to_bci -1
    predecessors 
    successors 
    xhandlers
    flags 
    probability 4607182418800017408
    begin_IR
      LIR
      nr    0  <|@ instruction [rsi|QWORD[.], rbp|QWORD] = LABEL numbPhis: 0 align: false label: ? <|@ <|@
      nr    4  <|@ instruction [] = HOTSPOTLOCKSTACK frameMapBuilder: org.graalvm.compiler.lir.amd64.AMD64FrameMapBuilder@5f405023 slotKind: QWORD <|@ <|@
      nr    8  <|@ instruction rax|DWORD = MOV [rsi|QWORD[.] + 24] size: DWORD <|@ <|@
      nr   10  <|@ instruction MOV (x: [rsi|QWORD[.] + 28], y: rax|DWORD) size: DWORD <|@ <|@
      nr   12  <|@ instruction MOV (x: [rsi|QWORD[.] + 24], y: r12|ILLEGAL) size: DWORD <|@ <|@
      nr   14  <|@ instruction MOV [rsi|QWORD[.] + 12] y: -1 size: DWORD <|@ <|@
      nr   16  <|@ instruction rax|QWORD[.] = MOVE rsi|QWORD[.] moveKind: QWORD <|@ <|@
      nr   18  <|@ instruction RETURN (savedRbp: rbp|QWORD, value: rax|QWORD[.]) isStub: false thread: r15 scratchForSafepointOnReturn: rcx config: org.graalvm.compiler.hotspot.GraalHotSpotVMConfig@69d7a7b <|@ <|@
    end_IR
  end_block
end_cfg
begin_bytecodes
     0: aload_0       
     1: aload_0       
     2: getfield      #2          // position:int
     5: putfield      #11         // limit:int
     8: aload_0       
     9: iconst_0      
    10: putfield      #2          // position:int
    13: aload_0       
    14: iconst_m1     
    15: putfield      #1          // mark:int
    18: aload_0       
    19: areturn       
   <|@
end_bytecodes
begin_cfg
  name "After PostAllocationOptimizationStage"
  begin_block
    name "B0"
    from_bci -1
    to_bci -1
    predecessors 
    successors 
    xhandlers
    flags 
    probability 4607182418800017408
    begin_IR
      LIR
      nr    0  <|@ instruction [rsi|QWORD[.], rbp|QWORD] = LABEL numbPhis: 0 align: false label: ? <|@ <|@
      nr    4  <|@ instruction [] = HOTSPOTLOCKSTACK frameMapBuilder: org.graalvm.compiler.lir.amd64.AMD64FrameMapBuilder@5f405023 slotKind: QWORD <|@ <|@
      nr    8  <|@ instruction rax|DWORD = MOV [rsi|QWORD[.] + 24] size: DWORD <|@ <|@
      nr   10  <|@ instruction MOV (x: [rsi|QWORD[.] + 28], y: rax|DWORD) size: DWORD <|@ <|@
      nr   12  <|@ instruction MOV (x: [rsi|QWORD[.] + 24], y: r12|ILLEGAL) size: DWORD <|@ <|@
      nr   14  <|@ instruction MOV [rsi|QWORD[.] + 12] y: -1 size: DWORD <|@ <|@
      nr   16  <|@ instruction rax|QWORD[.] = MOVE rsi|QWORD[.] moveKind: QWORD <|@ <|@
      nr   18  <|@ instruction RETURN (savedRbp: rbp|QWORD, value: rax|QWORD[.]) isStub: false thread: r15 scratchForSafepointOnReturn: rcx config: org.graalvm.compiler.hotspot.GraalHotSpotVMConfig@69d7a7b <|@ <|@
    end_IR
  end_block
end_cfg
begin_bytecodes
     0: aload_0       
     1: aload_0       
     2: getfield      #2          // position:int
     5: putfield      #11         // limit:int
     8: aload_0       
     9: iconst_0      
    10: putfield      #2          // position:int
    13: aload_0       
    14: iconst_m1     
    15: putfield      #1          // mark:int
    18: aload_0       
    19: areturn       
   <|@
end_bytecodes
begin_cfg
  name "After code generation"
end_cfg
begin_nmethod
  <<<HexCodeFile
  Platform AMD64 64  <||@
  HexCode 0 448b560849c1e203493bc20f85efffffff900f1f80000000000f1f80000000000f1f4400008b461889461c44896618c7460cffffffff488bc6850500000000c5f877c3e80000000090e80000000090  <||@
  Comment 0 2  <||@
  Comment 11 {Field[name=CompilerToVM::Data::SharedRuntime_ic_miss_stub, type=address, offset=0, address=0x10b0a1f78, value=0x118a04e60]:0x118a04e60}  <||@
  Comment 32 3  <||@
  Comment 32 1  <||@
  Comment 37 block B0 null  <||@
  Comment 37 0 [rsi|QWORD[.], rbp|QWORD] = LABEL numbPhis: 0 align: false label: ?  <||@
  Comment 37 4 [] = HOTSPOTLOCKSTACK frameMapBuilder: org.graalvm.compiler.lir.amd64.AMD64FrameMapBuilder@5f405023 slotKind: QWORD  <||@
  Comment 37 8 rax|DWORD = MOV [rsi|QWORD[.] + 24] size: DWORD  <||@
  Comment 40 10 MOV (x: [rsi|QWORD[.] + 28], y: rax|DWORD) size: DWORD  <||@
  Comment 43 12 MOV (x: [rsi|QWORD[.] + 24], y: r12|ILLEGAL) size: DWORD  <||@
  Comment 47 14 MOV [rsi|QWORD[.] + 12] y: -1 size: DWORD  <||@
  Comment 54 16 rax|QWORD[.] = MOVE rsi|QWORD[.] moveKind: QWORD  <||@
  Comment 57 18 RETURN (savedRbp: rbp|QWORD, value: rax|QWORD[.]) isStub: false thread: r15 scratchForSafepointOnReturn: rcx config: org.graalvm.compiler.hotspot.GraalHotSpotVMConfig@69d7a7b  <||@
  Comment 57 12  <||@
  Comment 67 {Stub<ExceptionHandlerStub.exceptionHandler>@0x118dff7a0:CallingConvention[rax|QWORD[.], rdx|QWORD]:CallingConvention[rax|QWORD[.], rdx|QWORD]; temps=rdi|ILLEGAL,xmm0|ILLEGAL,xmm1|ILLEGAL,xmm2|ILLEGAL,xmm3|ILLEGAL,xmm4|ILLEGAL,xmm5|ILLEGAL,xmm6|ILLEGAL,xmm7|ILLEGAL,xmm8|ILLEGAL,xmm9|ILLEGAL,xmm10|ILLEGAL,xmm11|ILLEGAL,xmm12|ILLEGAL,xmm13|ILLEGAL,xmm14|ILLEGAL,xmm15|ILLEGAL,xmm16|ILLEGAL,xmm17|ILLEGAL,xmm18|ILLEGAL,xmm19|ILLEGAL,xmm20|ILLEGAL,xmm21|ILLEGAL,xmm22|ILLEGAL,xmm23|ILLEGAL,xmm24|ILLEGAL,xmm25|ILLEGAL,xmm26|ILLEGAL,xmm27|ILLEGAL,xmm28|ILLEGAL,xmm29|ILLEGAL,xmm30|ILLEGAL,xmm31|ILLEGAL,rax|ILLEGAL,rcx|ILLEGAL,rdx|ILLEGAL,rsi|ILLEGAL,r8|ILLEGAL,r9|ILLEGAL,r10|ILLEGAL,r11|ILLEGAL}  <||@
  Comment 67 4  <||@
  Comment 73 {Field[name=CompilerToVM::Data::SharedRuntime_deopt_blob_unpack, type=address, offset=0, address=0x10b0a1f88, value=0x118a06500]:0x118a06500}  <||@
  Comment 73 5  <||@
  HexCodeFile>>> <|@
end_nmethod
begin_compilation
  name " HotSpotCompilation-7681[java.nio.Buffer.flip()]"
  method "HotSpotCompilation-7681[java.nio.Buffer.flip()]"
  date 1526687582832
end_compilation
begin_cfg
  name "After code installation"
end_cfg
begin_nmethod
  <<<HexCodeFile
  Platform AMD64 64  <||@
  HexCode 11939cee0 448b560849c1e203493bc20f856f7f66ff900f1f80000000000f1f80000000000f1f4400008b461889461c44896618c7460cffffffff488bc68505e7f0b3f0c5f877c3e87828a6ff90e8d29566ff90f4  <||@
  Comment 0 2  <||@
  Comment 11 {Field[name=CompilerToVM::Data::SharedRuntime_ic_miss_stub, type=address, offset=0, address=0x10b0a1f78, value=0x118a04e60]:0x118a04e60}  <||@
  Comment 32 3  <||@
  Comment 32 1  <||@
  Comment 37 block B0 null  <||@
  Comment 37 0 [rsi|QWORD[.], rbp|QWORD] = LABEL numbPhis: 0 align: false label: ?  <||@
  Comment 37 4 [] = HOTSPOTLOCKSTACK frameMapBuilder: org.graalvm.compiler.lir.amd64.AMD64FrameMapBuilder@5f405023 slotKind: QWORD  <||@
  Comment 37 8 rax|DWORD = MOV [rsi|QWORD[.] + 24] size: DWORD  <||@
  Comment 40 10 MOV (x: [rsi|QWORD[.] + 28], y: rax|DWORD) size: DWORD  <||@
  Comment 43 12 MOV (x: [rsi|QWORD[.] + 24], y: r12|ILLEGAL) size: DWORD  <||@
  Comment 47 14 MOV [rsi|QWORD[.] + 12] y: -1 size: DWORD  <||@
  Comment 54 16 rax|QWORD[.] = MOVE rsi|QWORD[.] moveKind: QWORD  <||@
  Comment 57 18 RETURN (savedRbp: rbp|QWORD, value: rax|QWORD[.]) isStub: false thread: r15 scratchForSafepointOnReturn: rcx config: org.graalvm.compiler.hotspot.GraalHotSpotVMConfig@69d7a7b  <||@
  Comment 57 12  <||@
  Comment 67 {Stub<ExceptionHandlerStub.exceptionHandler>@0x118dff7a0:CallingConvention[rax|QWORD[.], rdx|QWORD]:CallingConvention[rax|QWORD[.], rdx|QWORD]; temps=rdi|ILLEGAL,xmm0|ILLEGAL,xmm1|ILLEGAL,xmm2|ILLEGAL,xmm3|ILLEGAL,xmm4|ILLEGAL,xmm5|ILLEGAL,xmm6|ILLEGAL,xmm7|ILLEGAL,xmm8|ILLEGAL,xmm9|ILLEGAL,xmm10|ILLEGAL,xmm11|ILLEGAL,xmm12|ILLEGAL,xmm13|ILLEGAL,xmm14|ILLEGAL,xmm15|ILLEGAL,xmm16|ILLEGAL,xmm17|ILLEGAL,xmm18|ILLEGAL,xmm19|ILLEGAL,xmm20|ILLEGAL,xmm21|ILLEGAL,xmm22|ILLEGAL,xmm23|ILLEGAL,xmm24|ILLEGAL,xmm25|ILLEGAL,xmm26|ILLEGAL,xmm27|ILLEGAL,xmm28|ILLEGAL,xmm29|ILLEGAL,xmm30|ILLEGAL,xmm31|ILLEGAL,rax|ILLEGAL,rcx|ILLEGAL,rdx|ILLEGAL,rsi|ILLEGAL,r8|ILLEGAL,r9|ILLEGAL,r10|ILLEGAL,r11|ILLEGAL}  <||@
  Comment 67 4  <||@
  Comment 73 {Field[name=CompilerToVM::Data::SharedRuntime_deopt_blob_unpack, type=address, offset=0, address=0x10b0a1f88, value=0x118a06500]:0x118a06500}  <||@
  Comment 73 5  <||@
  HexCodeFile>>> <|@
end_nmethod
