begin_compilation
  name " HotSpotCompilation-5280[java.util.Formatter$FormatSpecifier.index(String)]"
  method "HotSpotCompilation-5280[java.util.Formatter$FormatSpecifier.index(String)]"
  date 1526687586415
end_compilation
begin_cfg
  name "Final HIR schedule"
  begin_block
    name "B0"
    from_bci -1
    to_bci -1
    predecessors 
    successors "B1" "B2" 
    xhandlers
    flags 
    probability 4607182418800017408
    begin_IR
      HIR
f <@#|@fixed with next>@ <|@
tid v0 <|@
d <@d|@=== Debug Properties ===
stamp: void
=== Inputs ===
stateAfter: - 
=== Succesors ===
next: v20 
=== Usages ===
=== Predecessor ===
- >@ <|@
instruction <@StartNode|@org.graalvm.compiler.nodes.StartNode>@ stateAfter: - #next: v20  <|@  <|@
f <@~|@floating>@ <|@
tid a1 <|@
d <@d|@=== Debug Properties ===
index: 0
stamp: a!# Ljava/util/Formatter$FormatSpecifier;
uncheckedStamp: [null]
=== Inputs ===
=== Succesors ===
=== Usages ===
?3 v21 
=== Predecessor ===
- >@ <|@
instruction <@Parameter|@org.graalvm.compiler.nodes.ParameterNode>@  <|@  <|@
f <@~|@floating>@ <|@
tid a2 <|@
d <@d|@=== Debug Properties ===
index: 1
stamp: a# Ljava/lang/String;
uncheckedStamp: [null]
=== Inputs ===
=== Succesors ===
=== Usages ===
?3 v5 
=== Predecessor ===
- >@ <|@
instruction <@Parameter|@org.graalvm.compiler.nodes.ParameterNode>@  <|@  <|@
f <@~|@floating>@ <|@
tid v5 <|@
d <@d|@=== Debug Properties ===
nodeSourcePosition: at java.util.Formatter$FormatSpecifier.index(Formatter.java:2623) [bci: 1]
stamp: void
=== Inputs ===
value: a2 
=== Succesors ===
=== Usages ===
v20 
=== Predecessor ===
- >@ <|@
instruction <@IsNull|@org.graalvm.compiler.nodes.calc.IsNullNode>@ value: a2  <|@  <|@
f <@*|@fixed>@ <|@
tid v20 <|@
d <@d|@=== Debug Properties ===
nodeSourcePosition: at java.util.Formatter$FormatSpecifier.index(Formatter.java:2623) [bci: 1]
stamp: void
trueSuccessorProbability: 1.0
=== Inputs ===
condition: v5 
=== Succesors ===
trueSuccessor: v17 
falseSuccessor: v19 
=== Usages ===
=== Predecessor ===
v0 >@ <|@
instruction <@If|@org.graalvm.compiler.nodes.IfNode>@ condition: v5 #trueSuccessor: v17 #falseSuccessor: v19  <|@  <|@
    end_IR
  end_block
  begin_block
    name "B1"
    from_bci -1
    to_bci -1
    predecessors "B0" 
    successors 
    xhandlers
    flags 
    probability 4607182418800017408
    begin_IR
      HIR
f <@#|@fixed with next>@ <|@
tid v17 <|@
d <@d|@=== Debug Properties ===
nodeSourcePosition: at java.util.Formatter$FormatSpecifier.index(Formatter.java:2623) [bci: 1]
stamp: void
=== Inputs ===
=== Succesors ===
next: v16 
=== Usages ===
=== Predecessor ===
v20 >@ <|@
instruction <@Begin|@org.graalvm.compiler.nodes.BeginNode>@ #next: v16  <|@  <|@
f <@~|@floating>@ <|@
tid v21 <|@
d <@d|@=== Debug Properties ===
displacement: 12
scale: Times1
stamp: void*
=== Inputs ===
base: a1 
index: - 
=== Succesors ===
=== Usages ===
v16 
=== Predecessor ===
- >@ <|@
instruction <@AMD64Address|@org.graalvm.compiler.core.amd64.AMD64AddressNode>@ base: a1 index: -  <|@  <|@
f <@~|@floating>@ <|@
tid i7 <|@
d <@d|@=== Debug Properties ===
isDefaultStable: false
nodeSourcePosition: at java.util.Formatter$FormatSpecifier.index(Formatter.java:2630) [bci: 44]
rawvalue: 0
stableDimension: 0
stamp: i32 [0] ⇈0000000000000000
stampKind: i32
value: int[0|0x0]
=== Inputs ===
=== Succesors ===
=== Usages ===
v16 v11 
=== Predecessor ===
- >@ <|@
instruction <@Constant|@org.graalvm.compiler.nodes.ConstantNode>@  <|@  <|@
f <@#|@fixed with next>@ <|@
tid v16 <|@
d <@d|@=== Debug Properties ===
barrierType: NONE
location: Formatter$FormatSpecifier.index
nodeSourcePosition: at java.util.Formatter$FormatSpecifier.index(Formatter.java:2630) [bci: 45]
nullCheck: false
stamp: void
=== Inputs ===
stateBefore: - 
guard: - 
address: v21 
value: i7 
stateAfter: - 
lastLocationAccess: - 
=== Succesors ===
next: v11 
=== Usages ===
=== Predecessor ===
v17 >@ <|@
instruction <@Write|@org.graalvm.compiler.nodes.memory.WriteNode>@ stateBefore: - guard: - address: v21 value: i7 stateAfter: - lastLocationAccess: - #next: v11  <|@  <|@
f <@*|@fixed>@ <|@
tid v11 <|@
d <@d|@=== Debug Properties ===
nodeSourcePosition: at java.util.Formatter$FormatSpecifier.index(Formatter.java:2632) [bci: 52]
stamp: void
=== Inputs ===
result: i7 
memoryMap: - 
=== Succesors ===
=== Usages ===
=== Predecessor ===
v16 >@ <|@
instruction <@Return|@org.graalvm.compiler.nodes.ReturnNode>@ result: i7 memoryMap: -  <|@  <|@
    end_IR
  end_block
  begin_block
    name "B2"
    from_bci -1
    to_bci -1
    predecessors "B0" 
    successors 
    xhandlers
    flags 
    probability 2355382605114769408
    begin_IR
      HIR
f <@#|@fixed with next>@ <|@
tid v19 <|@
d <@d|@=== Debug Properties ===
nodeSourcePosition: at java.util.Formatter$FormatSpecifier.index(Formatter.java:2623) [bci: 1]
stamp: void
=== Inputs ===
=== Succesors ===
next: v18 
=== Usages ===
=== Predecessor ===
v20 >@ <|@
instruction <@Begin|@org.graalvm.compiler.nodes.BeginNode>@ #next: v18  <|@  <|@
tid ?3 <|@
d <@d|@=== Debug Properties ===
bci: 0
code: ResolvedJavaMethodBytecode<Formatter$FormatSpecifier.index(String)>
duringCall: false
localsSize: 3
locksSize: 0
rethrowException: false
sourceFile: Formatter.java
sourceLine: 2623
stackSize: 0
=== Inputs ===
outerFrameState: - 
values: a1 a2 - 
=== Succesors ===
=== Usages ===
v18 
=== Predecessor ===
- >@ <|@
instruction <@FrameState|@org.graalvm.compiler.nodes.FrameState>@ outerFrameState: - values: a1 a2 -  <|@  <|@
f <@*|@fixed>@ <|@
tid v18 <|@
d <@d|@=== Debug Properties ===
action: InvalidateReprofile
debugId: 13
nodeSourcePosition: at java.util.Formatter$FormatSpecifier.index(Formatter.java:2623) [bci: 1]
reason: UnreachedCode
speculation: Object[null]
stamp: void
=== Inputs ===
stateBefore: ?3 
=== Succesors ===
=== Usages ===
=== Predecessor ===
v19 >@ <|@
instruction <@Deopt|@org.graalvm.compiler.nodes.DeoptimizeNode>@ stateBefore: ?3  <|@  <|@
    end_IR
  end_block
end_cfg
begin_cfg
  name "After LIR generation"
  begin_block
    name "B0"
    from_bci -1
    to_bci -1
    predecessors 
    successors "B1" "B2" 
    xhandlers
    flags 
    probability 4607182418800017408
    begin_IR
      HIR
f <@#|@fixed with next>@ <|@
tid v0 <|@
d <@d|@=== Debug Properties ===
stamp: void
=== Inputs ===
stateAfter: - 
=== Succesors ===
next: v20 
=== Usages ===
=== Predecessor ===
- >@ <|@
instruction <@StartNode|@org.graalvm.compiler.nodes.StartNode>@ stateAfter: - #next: v20  <|@  <|@
f <@~|@floating>@ <|@
tid a1 <|@
result v0|QWORD[.] <|@
d <@d|@=== Debug Properties ===
index: 0
stamp: a!# Ljava/util/Formatter$FormatSpecifier;
uncheckedStamp: [null]
=== Inputs ===
=== Succesors ===
=== Usages ===
?3 v21 
=== Predecessor ===
- >@ <|@
instruction <@Parameter|@org.graalvm.compiler.nodes.ParameterNode>@  <|@  <|@
f <@~|@floating>@ <|@
tid a2 <|@
result v1|QWORD[.] <|@
d <@d|@=== Debug Properties ===
index: 1
stamp: a# Ljava/lang/String;
uncheckedStamp: [null]
=== Inputs ===
=== Succesors ===
=== Usages ===
?3 v5 
=== Predecessor ===
- >@ <|@
instruction <@Parameter|@org.graalvm.compiler.nodes.ParameterNode>@  <|@  <|@
f <@~|@floating>@ <|@
tid v5 <|@
d <@d|@=== Debug Properties ===
nodeSourcePosition: at java.util.Formatter$FormatSpecifier.index(Formatter.java:2623) [bci: 1]
stamp: void
=== Inputs ===
value: a2 
=== Succesors ===
=== Usages ===
v20 
=== Predecessor ===
- >@ <|@
instruction <@IsNull|@org.graalvm.compiler.nodes.calc.IsNullNode>@ value: a2  <|@  <|@
f <@*|@fixed>@ <|@
tid v20 <|@
d <@d|@=== Debug Properties ===
nodeSourcePosition: at java.util.Formatter$FormatSpecifier.index(Formatter.java:2623) [bci: 1]
stamp: void
trueSuccessorProbability: 1.0
=== Inputs ===
condition: v5 
=== Succesors ===
trueSuccessor: v17 
falseSuccessor: v19 
=== Usages ===
=== Predecessor ===
v0 >@ <|@
instruction <@If|@org.graalvm.compiler.nodes.IfNode>@ condition: v5 #trueSuccessor: v17 #falseSuccessor: v19  <|@  <|@
    end_IR
    begin_IR
      LIR
      nr   -1  <|@ instruction [rsi|QWORD[.], rdx|QWORD[.], rbp|QWORD] = LABEL numbPhis: 0 align: false label: ? <|@ <|@
      nr   -1  <|@ instruction stack:16|QWORD = MOVE rbp|QWORD moveKind: QWORD <|@ <|@
      nr   -1  <|@ instruction [] = HOTSPOTLOCKSTACK frameMapBuilder: org.graalvm.compiler.lir.amd64.AMD64FrameMapBuilder@6312f0dc slotKind: QWORD <|@ <|@
      nr   -1  <|@ instruction v0|QWORD[.] = MOVE rsi|QWORD[.] moveKind: QWORD <|@ <|@
      nr   -1  <|@ instruction v1|QWORD[.] = MOVE rdx|QWORD[.] moveKind: QWORD <|@ <|@
      nr   -1  <|@ instruction TEST (x: v1|QWORD[.], y: v1|QWORD[.]) size: QWORD <|@ <|@
      nr   -1  <|@ instruction BRANCH trueDestinationProbability: 1.0 condition: = trueDestination: B0 -> B1 falseDestination: B0 -> B2 <|@ <|@
    end_IR
  end_block
  begin_block
    name "B1"
    from_bci -1
    to_bci -1
    predecessors "B0" 
    successors 
    xhandlers
    flags 
    probability 4607182418800017408
    begin_IR
      HIR
f <@#|@fixed with next>@ <|@
tid v17 <|@
d <@d|@=== Debug Properties ===
nodeSourcePosition: at java.util.Formatter$FormatSpecifier.index(Formatter.java:2623) [bci: 1]
stamp: void
=== Inputs ===
=== Succesors ===
next: v16 
=== Usages ===
=== Predecessor ===
v20 >@ <|@
instruction <@Begin|@org.graalvm.compiler.nodes.BeginNode>@ #next: v16  <|@  <|@
f <@~|@floating>@ <|@
tid v21 <|@
result [v0|QWORD[.] + 12] <|@
d <@d|@=== Debug Properties ===
displacement: 12
scale: Times1
stamp: void*
=== Inputs ===
base: a1 
index: - 
=== Succesors ===
=== Usages ===
v16 
=== Predecessor ===
- >@ <|@
instruction <@AMD64Address|@org.graalvm.compiler.core.amd64.AMD64AddressNode>@ base: a1 index: -  <|@  <|@
f <@~|@floating>@ <|@
tid i7 <|@
result int[0|0x0] <|@
d <@d|@=== Debug Properties ===
isDefaultStable: false
nodeSourcePosition: at java.util.Formatter$FormatSpecifier.index(Formatter.java:2630) [bci: 44]
rawvalue: 0
stableDimension: 0
stamp: i32 [0] ⇈0000000000000000
stampKind: i32
value: int[0|0x0]
=== Inputs ===
=== Succesors ===
=== Usages ===
v16 v11 
=== Predecessor ===
- >@ <|@
instruction <@Constant|@org.graalvm.compiler.nodes.ConstantNode>@  <|@  <|@
f <@#|@fixed with next>@ <|@
tid v16 <|@
d <@d|@=== Debug Properties ===
barrierType: NONE
location: Formatter$FormatSpecifier.index
nodeSourcePosition: at java.util.Formatter$FormatSpecifier.index(Formatter.java:2630) [bci: 45]
nullCheck: false
stamp: void
=== Inputs ===
stateBefore: - 
guard: - 
address: v21 
value: i7 
stateAfter: - 
lastLocationAccess: - 
=== Succesors ===
next: v11 
=== Usages ===
=== Predecessor ===
v17 >@ <|@
instruction <@Write|@org.graalvm.compiler.nodes.memory.WriteNode>@ stateBefore: - guard: - address: v21 value: i7 stateAfter: - lastLocationAccess: - #next: v11  <|@  <|@
f <@*|@fixed>@ <|@
tid v11 <|@
d <@d|@=== Debug Properties ===
nodeSourcePosition: at java.util.Formatter$FormatSpecifier.index(Formatter.java:2632) [bci: 52]
stamp: void
=== Inputs ===
result: i7 
memoryMap: - 
=== Succesors ===
=== Usages ===
=== Predecessor ===
v16 >@ <|@
instruction <@Return|@org.graalvm.compiler.nodes.ReturnNode>@ result: i7 memoryMap: -  <|@  <|@
    end_IR
    begin_IR
      LIR
      nr   -1  <|@ instruction [] = LABEL numbPhis: 0 align: false label: ? <|@ <|@
      nr   -1  <|@ instruction MOV (x: [v0|QWORD[.] + 12], y: r12|ILLEGAL) size: DWORD <|@ <|@
      nr   -1  <|@ instruction rax|DWORD = MOVE input: int[0|0x0] <|@ <|@
      nr   -1  <|@ instruction RETURN (savedRbp: stack:16|QWORD, value: rax|DWORD) isStub: false thread: r15 scratchForSafepointOnReturn: rcx config: org.graalvm.compiler.hotspot.GraalHotSpotVMConfig@69d7a7b <|@ <|@
    end_IR
  end_block
  begin_block
    name "B2"
    from_bci -1
    to_bci -1
    predecessors "B0" 
    successors 
    xhandlers
    flags 
    probability 2355382605114769408
    begin_IR
      HIR
f <@#|@fixed with next>@ <|@
tid v19 <|@
d <@d|@=== Debug Properties ===
nodeSourcePosition: at java.util.Formatter$FormatSpecifier.index(Formatter.java:2623) [bci: 1]
stamp: void
=== Inputs ===
=== Succesors ===
next: v18 
=== Usages ===
=== Predecessor ===
v20 >@ <|@
instruction <@Begin|@org.graalvm.compiler.nodes.BeginNode>@ #next: v18  <|@  <|@
tid ?3 <|@
d <@d|@=== Debug Properties ===
bci: 0
code: ResolvedJavaMethodBytecode<Formatter$FormatSpecifier.index(String)>
duringCall: false
localsSize: 3
locksSize: 0
rethrowException: false
sourceFile: Formatter.java
sourceLine: 2623
stackSize: 0
=== Inputs ===
outerFrameState: - 
values: a1 a2 - 
=== Succesors ===
=== Usages ===
v18 
=== Predecessor ===
- >@ <|@
instruction <@FrameState|@org.graalvm.compiler.nodes.FrameState>@ outerFrameState: - values: a1 a2 -  <|@  <|@
f <@*|@fixed>@ <|@
tid v18 <|@
d <@d|@=== Debug Properties ===
action: InvalidateReprofile
debugId: 13
nodeSourcePosition: at java.util.Formatter$FormatSpecifier.index(Formatter.java:2623) [bci: 1]
reason: UnreachedCode
speculation: Object[null]
stamp: void
=== Inputs ===
stateBefore: ?3 
=== Succesors ===
=== Usages ===
=== Predecessor ===
v19 >@ <|@
instruction <@Deopt|@org.graalvm.compiler.nodes.DeoptimizeNode>@ stateBefore: ?3  <|@  <|@
    end_IR
    begin_IR
      LIR
      nr   -1  <|@ instruction [] = LABEL numbPhis: 0 align: false label: ? <|@ <|@
      nr   -1  <|@ instruction MOV [r15|QWORD + 668] y: -3347 size: DWORD <|@ <|@
      nr   -1  <|@ instruction MOV (x: [r15|QWORD + 680], y: r12|ILLEGAL) size: QWORD <|@ <|@
      nr   -1  <|@ st <@st|@java.util.Formatter$FormatSpecifier.index(Formatter.java:2623) [bci: 0]
locals: v0|QWORD[.] v1|QWORD[.] - 
>@ <|@ instruction DEOPT info [bci:0] <|@ <|@
    end_IR
  end_block
end_cfg
begin_cfg
  name "After PreAllocationOptimizationStage"
  begin_block
    name "B0"
    from_bci -1
    to_bci -1
    predecessors 
    successors "B1" "B2" 
    xhandlers
    flags 
    probability 4607182418800017408
    begin_IR
      LIR
      nr   -1  <|@ instruction [rsi|QWORD[.], rdx|QWORD[.], rbp|QWORD] = LABEL numbPhis: 0 align: false label: ? <|@ <|@
      nr   -1  <|@ instruction stack:16|QWORD = MOVE rbp|QWORD moveKind: QWORD <|@ <|@
      nr   -1  <|@ instruction [] = HOTSPOTLOCKSTACK frameMapBuilder: org.graalvm.compiler.lir.amd64.AMD64FrameMapBuilder@6312f0dc slotKind: QWORD <|@ <|@
      nr   -1  <|@ instruction v0|QWORD[.] = MOVE rsi|QWORD[.] moveKind: QWORD <|@ <|@
      nr   -1  <|@ instruction v1|QWORD[.] = MOVE rdx|QWORD[.] moveKind: QWORD <|@ <|@
      nr   -1  <|@ instruction TEST (x: v1|QWORD[.], y: v1|QWORD[.]) size: QWORD <|@ <|@
      nr   -1  <|@ instruction BRANCH trueDestinationProbability: 1.0 condition: = trueDestination: B0 -> B1 falseDestination: B0 -> B2 <|@ <|@
    end_IR
  end_block
  begin_block
    name "B1"
    from_bci -1
    to_bci -1
    predecessors "B0" 
    successors 
    xhandlers
    flags 
    probability 4607182418800017408
    begin_IR
      LIR
      nr   -1  <|@ instruction [] = LABEL numbPhis: 0 align: false label: ? <|@ <|@
      nr   -1  <|@ instruction MOV (x: [v0|QWORD[.] + 12], y: r12|ILLEGAL) size: DWORD <|@ <|@
      nr   -1  <|@ instruction rax|DWORD = MOVE input: int[0|0x0] <|@ <|@
      nr   -1  <|@ instruction RETURN (savedRbp: stack:16|QWORD, value: rax|DWORD) isStub: false thread: r15 scratchForSafepointOnReturn: rcx config: org.graalvm.compiler.hotspot.GraalHotSpotVMConfig@69d7a7b <|@ <|@
    end_IR
  end_block
  begin_block
    name "B2"
    from_bci -1
    to_bci -1
    predecessors "B0" 
    successors 
    xhandlers
    flags 
    probability 2355382605114769408
    begin_IR
      LIR
      nr   -1  <|@ instruction [] = LABEL numbPhis: 0 align: false label: ? <|@ <|@
      nr   -1  <|@ instruction MOV [r15|QWORD + 668] y: -3347 size: DWORD <|@ <|@
      nr   -1  <|@ instruction MOV (x: [r15|QWORD + 680], y: r12|ILLEGAL) size: QWORD <|@ <|@
      nr   -1  <|@ st <@st|@java.util.Formatter$FormatSpecifier.index(Formatter.java:2623) [bci: 0]
locals: v0|QWORD[.] v1|QWORD[.] - 
>@ <|@ instruction DEOPT info [bci:0] <|@ <|@
    end_IR
  end_block
end_cfg
begin_bytecodes
     0: aload_1       
     1: ifnull        43
     4: aload_0       
     5: aload_1       
     6: iconst_0      
     7: aload_1       
     8: invokevirtual #0          // java.lang.String.length:()int
    11: iconst_1      
    12: isub          
    13: invokevirtual #1          // java.lang.String.substring:(int, int)java.lang.String
    16: invokestatic  #2          // java.lang.Integer.parseInt:(java.lang.String)int
    19: putfield      #3          // index:int
    22: goto          48
    25: astore_2      
    26: getstatic     #4          // $assertionsDisabled:boolean
    29: ifne          40
    32: new           #7          // java.lang.AssertionError
    35: dup           
    36: invokespecial #5          // java.lang.AssertionError.<init>:()void
    39: athrow        
    40: goto          48
    43: aload_0       
    44: iconst_0      
    45: putfield      #3          // index:int
    48: aload_0       
    49: getfield      #3          // index:int
    52: ireturn       
   <|@
end_bytecodes
begin_cfg
  name "After AllocationStage"
  begin_block
    name "B0"
    from_bci -1
    to_bci -1
    predecessors 
    successors "B1" "B2" 
    xhandlers
    flags 
    probability 4607182418800017408
    begin_IR
      LIR
      nr    0  <|@ instruction [rsi|QWORD[.], rdx|QWORD[.], rbp|QWORD] = LABEL numbPhis: 0 align: false label: ? <|@ <|@
      nr    2  <|@ instruction stack:16|QWORD = MOVE rbp|QWORD moveKind: QWORD <|@ <|@
      nr    4  <|@ instruction [] = HOTSPOTLOCKSTACK frameMapBuilder: org.graalvm.compiler.lir.amd64.AMD64FrameMapBuilder@6312f0dc slotKind: QWORD <|@ <|@
      nr   10  <|@ instruction TEST (x: rdx|QWORD[.], y: rdx|QWORD[.]) size: QWORD <|@ <|@
      nr   12  <|@ instruction BRANCH trueDestinationProbability: 1.0 condition: = trueDestination: B0 -> B1 falseDestination: B0 -> B2 <|@ <|@
    end_IR
  end_block
  begin_block
    name "B1"
    from_bci -1
    to_bci -1
    predecessors "B0" 
    successors 
    xhandlers
    flags 
    probability 4607182418800017408
    begin_IR
      LIR
      nr   14  <|@ instruction [] = LABEL numbPhis: 0 align: false label: ? <|@ <|@
      nr   16  <|@ instruction MOV (x: [rsi|QWORD[.] + 12], y: r12|ILLEGAL) size: DWORD <|@ <|@
      nr   18  <|@ instruction rax|DWORD = MOVE input: int[0|0x0] <|@ <|@
      nr   20  <|@ instruction RETURN (savedRbp: stack:16|QWORD, value: rax|DWORD) isStub: false thread: r15 scratchForSafepointOnReturn: rcx config: org.graalvm.compiler.hotspot.GraalHotSpotVMConfig@69d7a7b <|@ <|@
    end_IR
  end_block
  begin_block
    name "B2"
    from_bci -1
    to_bci -1
    predecessors "B0" 
    successors 
    xhandlers
    flags 
    probability 2355382605114769408
    begin_IR
      LIR
      nr   22  <|@ instruction [] = LABEL numbPhis: 0 align: false label: ? <|@ <|@
      nr   24  <|@ instruction MOV [r15|QWORD + 668] y: -3347 size: DWORD <|@ <|@
      nr   26  <|@ instruction MOV (x: [r15|QWORD + 680], y: r12|ILLEGAL) size: QWORD <|@ <|@
      nr   28  <|@ st <@st|@reference-map: [rdx:0, rsi:0]
live-base-pointers: []
java.util.Formatter$FormatSpecifier.index(Formatter.java:2623) [bci: 0]
locals: rsi|QWORD[.] rdx|QWORD[.] - 
>@ <|@ instruction DEOPT info [bci:0] <|@ <|@
    end_IR
  end_block
end_cfg
begin_bytecodes
     0: aload_1       
     1: ifnull        43
     4: aload_0       
     5: aload_1       
     6: iconst_0      
     7: aload_1       
     8: invokevirtual #0          // java.lang.String.length:()int
    11: iconst_1      
    12: isub          
    13: invokevirtual #1          // java.lang.String.substring:(int, int)java.lang.String
    16: invokestatic  #2          // java.lang.Integer.parseInt:(java.lang.String)int
    19: putfield      #3          // index:int
    22: goto          48
    25: astore_2      
    26: getstatic     #4          // $assertionsDisabled:boolean
    29: ifne          40
    32: new           #7          // java.lang.AssertionError
    35: dup           
    36: invokespecial #5          // java.lang.AssertionError.<init>:()void
    39: athrow        
    40: goto          48
    43: aload_0       
    44: iconst_0      
    45: putfield      #3          // index:int
    48: aload_0       
    49: getfield      #3          // index:int
    52: ireturn       
   <|@
end_bytecodes
begin_cfg
  name "After PostAllocationOptimizationStage"
  begin_block
    name "B0"
    from_bci -1
    to_bci -1
    predecessors 
    successors "B1" "B2" 
    xhandlers
    flags 
    probability 4607182418800017408
    begin_IR
      LIR
      nr    0  <|@ instruction [rsi|QWORD[.], rdx|QWORD[.], rbp|QWORD] = LABEL numbPhis: 0 align: false label: ? <|@ <|@
      nr    2  <|@ instruction stack:16|QWORD = MOVE rbp|QWORD moveKind: QWORD <|@ <|@
      nr    4  <|@ instruction [] = HOTSPOTLOCKSTACK frameMapBuilder: org.graalvm.compiler.lir.amd64.AMD64FrameMapBuilder@6312f0dc slotKind: QWORD <|@ <|@
      nr   10  <|@ instruction TEST (x: rdx|QWORD[.], y: rdx|QWORD[.]) size: QWORD <|@ <|@
      nr   12  <|@ instruction BRANCH trueDestinationProbability: 1.0 condition: = trueDestination: B0 -> B1 falseDestination: B0 -> B2 <|@ <|@
    end_IR
  end_block
  begin_block
    name "B1"
    from_bci -1
    to_bci -1
    predecessors "B0" 
    successors 
    xhandlers
    flags 
    probability 4607182418800017408
    begin_IR
      LIR
      nr   14  <|@ instruction [] = LABEL numbPhis: 0 align: false label: ? <|@ <|@
      nr   16  <|@ instruction MOV (x: [rsi|QWORD[.] + 12], y: r12|ILLEGAL) size: DWORD <|@ <|@
      nr   18  <|@ instruction rax|DWORD = MOVE input: int[0|0x0] <|@ <|@
      nr   20  <|@ instruction RETURN (savedRbp: stack:16|QWORD, value: rax|DWORD) isStub: false thread: r15 scratchForSafepointOnReturn: rcx config: org.graalvm.compiler.hotspot.GraalHotSpotVMConfig@69d7a7b <|@ <|@
    end_IR
  end_block
  begin_block
    name "B2"
    from_bci -1
    to_bci -1
    predecessors "B0" 
    successors 
    xhandlers
    flags 
    probability 2355382605114769408
    begin_IR
      LIR
      nr   22  <|@ instruction [] = LABEL numbPhis: 0 align: false label: ? <|@ <|@
      nr   24  <|@ instruction MOV [r15|QWORD + 668] y: -3347 size: DWORD <|@ <|@
      nr   26  <|@ instruction MOV (x: [r15|QWORD + 680], y: r12|ILLEGAL) size: QWORD <|@ <|@
      nr   28  <|@ st <@st|@reference-map: [rdx:0, rsi:0]
live-base-pointers: []
java.util.Formatter$FormatSpecifier.index(Formatter.java:2623) [bci: 0]
locals: rsi|QWORD[.] rdx|QWORD[.] - 
>@ <|@ instruction DEOPT info [bci:0] <|@ <|@
    end_IR
  end_block
end_cfg
begin_bytecodes
     0: aload_1       
     1: ifnull        43
     4: aload_0       
     5: aload_1       
     6: iconst_0      
     7: aload_1       
     8: invokevirtual #0          // java.lang.String.length:()int
    11: iconst_1      
    12: isub          
    13: invokevirtual #1          // java.lang.String.substring:(int, int)java.lang.String
    16: invokestatic  #2          // java.lang.Integer.parseInt:(java.lang.String)int
    19: putfield      #3          // index:int
    22: goto          48
    25: astore_2      
    26: getstatic     #4          // $assertionsDisabled:boolean
    29: ifne          40
    32: new           #7          // java.lang.AssertionError
    35: dup           
    36: invokespecial #5          // java.lang.AssertionError.<init>:()void
    39: athrow        
    40: goto          48
    43: aload_0       
    44: iconst_0      
    45: putfield      #3          // index:int
    48: aload_0       
    49: getfield      #3          // index:int
    52: ireturn       
   <|@
end_bytecodes
begin_cfg
  name "After code generation"
end_cfg
begin_nmethod
  <<<HexCodeFile
  Platform AMD64 64  <||@
  HexCode 0 448b560849c1e203493bc20f85efffffff900f1f80000000000f1f800000000089842400c0feff4883ec1848896c24104885d20f851c0000004489660cb800000000488b6c24104883c418850500000000c5f877c341c7879c020000edf2ffff4d89a7a8020000e80000000090e80000000090e80000000090  <||@
  Comment 0 2  <||@
  Comment 11 {Field[name=CompilerToVM::Data::SharedRuntime_ic_miss_stub, type=address, offset=0, address=0x10b0a1f78, value=0x118a04e60]:0x118a04e60}  <||@
  Comment 32 [stack overflow check]  <||@
  Comment 32 3  <||@
  Comment 32 1  <||@
  Comment 43 block B0 null  <||@
  Comment 43 0 [rsi|QWORD[.], rdx|QWORD[.], rbp|QWORD] = LABEL numbPhis: 0 align: false label: ?  <||@
  Comment 43 2 stack:16|QWORD = MOVE rbp|QWORD moveKind: QWORD  <||@
  Comment 48 4 [] = HOTSPOTLOCKSTACK frameMapBuilder: org.graalvm.compiler.lir.amd64.AMD64FrameMapBuilder@6312f0dc slotKind: QWORD  <||@
  Comment 48 10 TEST (x: rdx|QWORD[.], y: rdx|QWORD[.]) size: QWORD  <||@
  Comment 51 12 BRANCH trueDestinationProbability: 1.0 condition: = trueDestination: B0 -> B1 falseDestination: B0 -> B2  <||@
  Comment 57 block B1 null  <||@
  Comment 57 14 [] = LABEL numbPhis: 0 align: false label: ?  <||@
  Comment 57 16 MOV (x: [rsi|QWORD[.] + 12], y: r12|ILLEGAL) size: DWORD  <||@
  Comment 61 18 rax|DWORD = MOVE input: int[0|0x0]  <||@
  Comment 66 20 RETURN (savedRbp: stack:16|QWORD, value: rax|DWORD) isStub: false thread: r15 scratchForSafepointOnReturn: rcx config: org.graalvm.compiler.hotspot.GraalHotSpotVMConfig@69d7a7b  <||@
  Comment 75 12  <||@
  Comment 85 block B2 null  <||@
  Comment 85 22 [] = LABEL numbPhis: 0 align: false label: ?  <||@
  Comment 85 24 MOV [r15|QWORD + 668] y: -3347 size: DWORD  <||@
  Comment 96 26 MOV (x: [r15|QWORD + 680], y: r12|ILLEGAL) size: QWORD  <||@
  Comment 103 28 DEOPT info [bci:0]  <||@
  Comment 103 {Field[name=CompilerToVM::Data::SharedRuntime_deopt_blob_uncommon_trap, type=address, offset=0, address=0x10b0a1f90, value=0x118a065fe]:0x118a065fe}  <||@
  Comment 108 [rdx:0, rsi:0]at java.util.Formatter$FormatSpecifier.index(Formatter.java:2623) [bci: 0, duringCall: false, rethrow: false]
              |0             |1             |2 
     locals:  |rsi|QWORD[.]  |rdx|QWORD[.]  |-   <||@
  Comment 109 {Stub<ExceptionHandlerStub.exceptionHandler>@0x118dff7a0:CallingConvention[rax|QWORD[.], rdx|QWORD]:CallingConvention[rax|QWORD[.], rdx|QWORD]; temps=rdi|ILLEGAL,xmm0|ILLEGAL,xmm1|ILLEGAL,xmm2|ILLEGAL,xmm3|ILLEGAL,xmm4|ILLEGAL,xmm5|ILLEGAL,xmm6|ILLEGAL,xmm7|ILLEGAL,xmm8|ILLEGAL,xmm9|ILLEGAL,xmm10|ILLEGAL,xmm11|ILLEGAL,xmm12|ILLEGAL,xmm13|ILLEGAL,xmm14|ILLEGAL,xmm15|ILLEGAL,xmm16|ILLEGAL,xmm17|ILLEGAL,xmm18|ILLEGAL,xmm19|ILLEGAL,xmm20|ILLEGAL,xmm21|ILLEGAL,xmm22|ILLEGAL,xmm23|ILLEGAL,xmm24|ILLEGAL,xmm25|ILLEGAL,xmm26|ILLEGAL,xmm27|ILLEGAL,xmm28|ILLEGAL,xmm29|ILLEGAL,xmm30|ILLEGAL,xmm31|ILLEGAL,rax|ILLEGAL,rcx|ILLEGAL,rdx|ILLEGAL,rsi|ILLEGAL,r8|ILLEGAL,r9|ILLEGAL,r10|ILLEGAL,r11|ILLEGAL}  <||@
  Comment 109 4  <||@
  Comment 115 {Field[name=CompilerToVM::Data::SharedRuntime_deopt_blob_unpack, type=address, offset=0, address=0x10b0a1f88, value=0x118a06500]:0x118a06500}  <||@
  Comment 115 5  <||@
  HexCodeFile>>> <|@
end_nmethod
begin_compilation
  name " HotSpotCompilation-5280[java.util.Formatter$FormatSpecifier.index(String)]"
  method "HotSpotCompilation-5280[java.util.Formatter$FormatSpecifier.index(String)]"
  date 1526687586438
end_compilation
begin_cfg
  name "After code installation"
end_cfg
begin_nmethod
  <<<HexCodeFile
  Platform AMD64 64  <||@
  HexCode 11990ade0 448b560849c1e203493bc20f856fa00fff900f1f80000000000f1f800000000089842400c0feff4883ec1848896c24104885d20f851c0000004489660cb800000000488b6c24104883c4188505d5115df0c5f877c341c7879c020000edf2ffff4d89a7a8020000e8b2b70fff90e84e494fff90e8a8b60fff90f4f4f4f4f4f4f4  <||@
  Comment 0 2  <||@
  Comment 11 {Field[name=CompilerToVM::Data::SharedRuntime_ic_miss_stub, type=address, offset=0, address=0x10b0a1f78, value=0x118a04e60]:0x118a04e60}  <||@
  Comment 32 [stack overflow check]  <||@
  Comment 32 3  <||@
  Comment 32 1  <||@
  Comment 43 block B0 null  <||@
  Comment 43 0 [rsi|QWORD[.], rdx|QWORD[.], rbp|QWORD] = LABEL numbPhis: 0 align: false label: ?  <||@
  Comment 43 2 stack:16|QWORD = MOVE rbp|QWORD moveKind: QWORD  <||@
  Comment 48 4 [] = HOTSPOTLOCKSTACK frameMapBuilder: org.graalvm.compiler.lir.amd64.AMD64FrameMapBuilder@6312f0dc slotKind: QWORD  <||@
  Comment 48 10 TEST (x: rdx|QWORD[.], y: rdx|QWORD[.]) size: QWORD  <||@
  Comment 51 12 BRANCH trueDestinationProbability: 1.0 condition: = trueDestination: B0 -> B1 falseDestination: B0 -> B2  <||@
  Comment 57 block B1 null  <||@
  Comment 57 14 [] = LABEL numbPhis: 0 align: false label: ?  <||@
  Comment 57 16 MOV (x: [rsi|QWORD[.] + 12], y: r12|ILLEGAL) size: DWORD  <||@
  Comment 61 18 rax|DWORD = MOVE input: int[0|0x0]  <||@
  Comment 66 20 RETURN (savedRbp: stack:16|QWORD, value: rax|DWORD) isStub: false thread: r15 scratchForSafepointOnReturn: rcx config: org.graalvm.compiler.hotspot.GraalHotSpotVMConfig@69d7a7b  <||@
  Comment 75 12  <||@
  Comment 85 block B2 null  <||@
  Comment 85 22 [] = LABEL numbPhis: 0 align: false label: ?  <||@
  Comment 85 24 MOV [r15|QWORD + 668] y: -3347 size: DWORD  <||@
  Comment 96 26 MOV (x: [r15|QWORD + 680], y: r12|ILLEGAL) size: QWORD  <||@
  Comment 103 28 DEOPT info [bci:0]  <||@
  Comment 103 {Field[name=CompilerToVM::Data::SharedRuntime_deopt_blob_uncommon_trap, type=address, offset=0, address=0x10b0a1f90, value=0x118a065fe]:0x118a065fe}  <||@
  Comment 108 [rdx:0, rsi:0]at java.util.Formatter$FormatSpecifier.index(Formatter.java:2623) [bci: 0, duringCall: false, rethrow: false]
              |0             |1             |2 
     locals:  |rsi|QWORD[.]  |rdx|QWORD[.]  |-   <||@
  Comment 109 {Stub<ExceptionHandlerStub.exceptionHandler>@0x118dff7a0:CallingConvention[rax|QWORD[.], rdx|QWORD]:CallingConvention[rax|QWORD[.], rdx|QWORD]; temps=rdi|ILLEGAL,xmm0|ILLEGAL,xmm1|ILLEGAL,xmm2|ILLEGAL,xmm3|ILLEGAL,xmm4|ILLEGAL,xmm5|ILLEGAL,xmm6|ILLEGAL,xmm7|ILLEGAL,xmm8|ILLEGAL,xmm9|ILLEGAL,xmm10|ILLEGAL,xmm11|ILLEGAL,xmm12|ILLEGAL,xmm13|ILLEGAL,xmm14|ILLEGAL,xmm15|ILLEGAL,xmm16|ILLEGAL,xmm17|ILLEGAL,xmm18|ILLEGAL,xmm19|ILLEGAL,xmm20|ILLEGAL,xmm21|ILLEGAL,xmm22|ILLEGAL,xmm23|ILLEGAL,xmm24|ILLEGAL,xmm25|ILLEGAL,xmm26|ILLEGAL,xmm27|ILLEGAL,xmm28|ILLEGAL,xmm29|ILLEGAL,xmm30|ILLEGAL,xmm31|ILLEGAL,rax|ILLEGAL,rcx|ILLEGAL,rdx|ILLEGAL,rsi|ILLEGAL,r8|ILLEGAL,r9|ILLEGAL,r10|ILLEGAL,r11|ILLEGAL}  <||@
  Comment 109 4  <||@
  Comment 115 {Field[name=CompilerToVM::Data::SharedRuntime_deopt_blob_unpack, type=address, offset=0, address=0x10b0a1f88, value=0x118a06500]:0x118a06500}  <||@
  Comment 115 5  <||@
  HexCodeFile>>> <|@
end_nmethod
