begin_compilation
  name " HotSpotCompilation-9437[java.net.URI.appendAuthority(StringBuffer, String, String, String, int)]"
  method "HotSpotCompilation-9437[java.net.URI.appendAuthority(StringBuffer, String, String, String, int)]"
  date 1527005212691
end_compilation
begin_cfg
  name "Final HIR schedule"
  begin_block
    name "B0"
    from_bci -1
    to_bci -1
    predecessors 
    successors "B1" "B4" 
    xhandlers
    flags 
    probability 4607182418800017408
    begin_IR
      HIR
f <@#|@fixed with next>@ <|@
tid v0 <|@
d <@d|@=== Debug Properties ===
stamp: void
=== Inputs ===
stateAfter: - 
=== Succesors ===
next: v19 
=== Usages ===
=== Predecessor ===
- >@ <|@
instruction <@StartNode|@org.graalvm.compiler.nodes.StartNode>@ stateAfter: - #next: v19  <|@  <|@
f <@~|@floating>@ <|@
tid a3 <|@
d <@d|@=== Debug Properties ===
index: 2
stamp: a# Ljava/lang/String;
uncheckedStamp: [null]
=== Inputs ===
=== Succesors ===
=== Usages ===
?7 v11 
=== Predecessor ===
- >@ <|@
instruction <@Parameter|@org.graalvm.compiler.nodes.ParameterNode>@  <|@  <|@
f <@~|@floating>@ <|@
tid a5 <|@
d <@d|@=== Debug Properties ===
index: 4
stamp: a# Ljava/lang/String;
uncheckedStamp: [null]
=== Inputs ===
=== Succesors ===
=== Usages ===
?7 v9 
=== Predecessor ===
- >@ <|@
instruction <@Parameter|@org.graalvm.compiler.nodes.ParameterNode>@  <|@  <|@
f <@~|@floating>@ <|@
tid v9 <|@
d <@d|@=== Debug Properties ===
nodeSourcePosition: at java.net.URI.appendAuthority(URI.java:1834) [bci: 2]
stamp: void
=== Inputs ===
value: a5 
=== Succesors ===
=== Usages ===
v19 
=== Predecessor ===
- >@ <|@
instruction <@IsNull|@org.graalvm.compiler.nodes.calc.IsNullNode>@ value: a5  <|@  <|@
f <@*|@fixed>@ <|@
tid v19 <|@
d <@d|@=== Debug Properties ===
nodeSourcePosition: at java.net.URI.appendAuthority(URI.java:1834) [bci: 2]
stamp: void
trueSuccessorProbability: 1.0
=== Inputs ===
condition: v9 
=== Succesors ===
trueSuccessor: v16 
falseSuccessor: v18 
=== Usages ===
=== Predecessor ===
v0 >@ <|@
instruction <@If|@org.graalvm.compiler.nodes.IfNode>@ condition: v9 #trueSuccessor: v16 #falseSuccessor: v18  <|@  <|@
    end_IR
  end_block
  begin_block
    name "B1"
    from_bci -1
    to_bci -1
    predecessors "B0" 
    successors "B2" "B3" 
    xhandlers
    flags 
    probability 4607182418800017408
    begin_IR
      HIR
f <@#|@fixed with next>@ <|@
tid v16 <|@
d <@d|@=== Debug Properties ===
nodeSourcePosition: at java.net.URI.appendAuthority(URI.java:1834) [bci: 2]
stamp: void
=== Inputs ===
=== Succesors ===
next: v23 
=== Usages ===
=== Predecessor ===
v19 >@ <|@
instruction <@Begin|@org.graalvm.compiler.nodes.BeginNode>@ #next: v23  <|@  <|@
f <@~|@floating>@ <|@
tid v11 <|@
d <@d|@=== Debug Properties ===
nodeSourcePosition: at java.net.URI.appendAuthority(URI.java:1850) [bci: 130]
stamp: void
=== Inputs ===
value: a3 
=== Succesors ===
=== Usages ===
v23 
=== Predecessor ===
- >@ <|@
instruction <@IsNull|@org.graalvm.compiler.nodes.calc.IsNullNode>@ value: a3  <|@  <|@
f <@*|@fixed>@ <|@
tid v23 <|@
d <@d|@=== Debug Properties ===
nodeSourcePosition: at java.net.URI.appendAuthority(URI.java:1850) [bci: 130]
stamp: void
trueSuccessorProbability: 1.0
=== Inputs ===
condition: v11 
=== Succesors ===
trueSuccessor: v20 
falseSuccessor: v22 
=== Usages ===
=== Predecessor ===
v16 >@ <|@
instruction <@If|@org.graalvm.compiler.nodes.IfNode>@ condition: v11 #trueSuccessor: v20 #falseSuccessor: v22  <|@  <|@
    end_IR
  end_block
  begin_block
    name "B2"
    from_bci -1
    to_bci -1
    predecessors "B1" 
    successors 
    xhandlers
    flags 
    probability 4607182418800017408
    begin_IR
      HIR
f <@#|@fixed with next>@ <|@
tid v20 <|@
d <@d|@=== Debug Properties ===
nodeSourcePosition: at java.net.URI.appendAuthority(URI.java:1850) [bci: 130]
stamp: void
=== Inputs ===
=== Succesors ===
next: v13 
=== Usages ===
=== Predecessor ===
v23 >@ <|@
instruction <@Begin|@org.graalvm.compiler.nodes.BeginNode>@ #next: v13  <|@  <|@
f <@*|@fixed>@ <|@
tid v13 <|@
d <@d|@=== Debug Properties ===
nodeSourcePosition: at java.net.URI.appendAuthority(URI.java:1876) [bci: 277]
stamp: void
=== Inputs ===
result: - 
memoryMap: - 
=== Succesors ===
=== Usages ===
=== Predecessor ===
v20 >@ <|@
instruction <@Return|@org.graalvm.compiler.nodes.ReturnNode>@ result: - memoryMap: -  <|@  <|@
    end_IR
  end_block
  begin_block
    name "B3"
    from_bci -1
    to_bci -1
    predecessors "B1" 
    successors "B5" 
    xhandlers
    flags 
    probability 2355382605114769408
    begin_IR
      HIR
f <@#|@fixed with next>@ <|@
tid v22 <|@
d <@d|@=== Debug Properties ===
nodeSourcePosition: at java.net.URI.appendAuthority(URI.java:1850) [bci: 130]
stamp: void
=== Inputs ===
=== Succesors ===
next: v31 
=== Usages ===
=== Predecessor ===
v23 >@ <|@
instruction <@Begin|@org.graalvm.compiler.nodes.BeginNode>@ #next: v31  <|@  <|@
f <@~|@floating>@ <|@
tid i32 <|@
d <@d|@=== Debug Properties ===
isDefaultStable: false
rawvalue: -3859
stableDimension: 0
stamp: i32 [-3859] ⇊00000000fffff0ed ⇈00000000fffff0ed
stampKind: i32
value: int[-3859|0xfffffffffffff0ed]
=== Inputs ===
=== Succesors ===
=== Usages ===
i28 
=== Predecessor ===
- >@ <|@
instruction <@Constant|@org.graalvm.compiler.nodes.ConstantNode>@  <|@  <|@
f <@*|@fixed>@ <|@
tid v31 <|@
d <@d|@=== Debug Properties ===
stamp: void
=== Inputs ===
=== Succesors ===
=== Usages ===
v24 
=== Predecessor ===
v22 >@ <|@
instruction <@EndNode|@org.graalvm.compiler.nodes.EndNode>@  <|@  <|@
    end_IR
  end_block
  begin_block
    name "B4"
    from_bci -1
    to_bci -1
    predecessors "B0" 
    successors "B5" 
    xhandlers
    flags 
    probability 2355382605114769408
    begin_IR
      HIR
f <@#|@fixed with next>@ <|@
tid v18 <|@
d <@d|@=== Debug Properties ===
nodeSourcePosition: at java.net.URI.appendAuthority(URI.java:1834) [bci: 2]
stamp: void
=== Inputs ===
=== Succesors ===
next: v25 
=== Usages ===
=== Predecessor ===
v19 >@ <|@
instruction <@Begin|@org.graalvm.compiler.nodes.BeginNode>@ #next: v25  <|@  <|@
f <@~|@floating>@ <|@
tid i26 <|@
d <@d|@=== Debug Properties ===
isDefaultStable: false
rawvalue: -3603
stableDimension: 0
stamp: i32 [-3603] ⇊00000000fffff1ed ⇈00000000fffff1ed
stampKind: i32
value: int[-3603|0xfffffffffffff1ed]
=== Inputs ===
=== Succesors ===
=== Usages ===
i28 
=== Predecessor ===
- >@ <|@
instruction <@Constant|@org.graalvm.compiler.nodes.ConstantNode>@  <|@  <|@
f <@*|@fixed>@ <|@
tid v25 <|@
d <@d|@=== Debug Properties ===
stamp: void
=== Inputs ===
=== Succesors ===
=== Usages ===
v24 
=== Predecessor ===
v18 >@ <|@
instruction <@EndNode|@org.graalvm.compiler.nodes.EndNode>@  <|@  <|@
    end_IR
  end_block
  begin_block
    name "B5"
    from_bci -1
    to_bci -1
    predecessors "B4" "B3" 
    successors 
    xhandlers
    flags 
    probability 2359886204742139904
    begin_IR
      HIR
f <@~|@floating>@ <|@
tid i28 <|@
d <@d|@=== Debug Properties ===
stamp: i32 [-3859 - -3603] ⇊00000000fffff0ed ⇈00000000fffff1ed
valueDescription: i32
=== Inputs ===
merge: v24 
values: i26 i32 
=== Succesors ===
=== Usages ===
v30 
=== Predecessor ===
- >@ <|@
instruction <@ValuePhi|@org.graalvm.compiler.nodes.ValuePhiNode>@ merge: v24 values: i26 i32  <|@  <|@
f <@#|@fixed with next>@ <|@
tid v24 <|@
d <@d|@=== Debug Properties ===
stamp: void
=== Inputs ===
stateAfter: - 
ends: v25 v31 
=== Succesors ===
next: v30 
=== Usages ===
i28 
=== Predecessor ===
- >@ <|@
instruction <@Merge|@org.graalvm.compiler.nodes.MergeNode>@ stateAfter: - ends: v25 v31 #next: v30  <|@  <|@
f <@~|@floating>@ <|@
tid a27 <|@
d <@d|@=== Debug Properties ===
isDefaultStable: false
rawvalue: null
stableDimension: 0
stamp: a - NULL
stampKind: a -
value: Object[null]
=== Inputs ===
=== Succesors ===
=== Usages ===
v30 
=== Predecessor ===
- >@ <|@
instruction <@Constant|@org.graalvm.compiler.nodes.ConstantNode>@  <|@  <|@
f <@~|@floating>@ <|@
tid a2 <|@
d <@d|@=== Debug Properties ===
index: 1
stamp: a# Ljava/lang/StringBuffer;
uncheckedStamp: [null]
=== Inputs ===
=== Succesors ===
=== Usages ===
?7 
=== Predecessor ===
- >@ <|@
instruction <@Parameter|@org.graalvm.compiler.nodes.ParameterNode>@  <|@  <|@
f <@~|@floating>@ <|@
tid a4 <|@
d <@d|@=== Debug Properties ===
index: 3
stamp: a# Ljava/lang/String;
uncheckedStamp: [null]
=== Inputs ===
=== Succesors ===
=== Usages ===
?7 
=== Predecessor ===
- >@ <|@
instruction <@Parameter|@org.graalvm.compiler.nodes.ParameterNode>@  <|@  <|@
f <@~|@floating>@ <|@
tid i6 <|@
d <@d|@=== Debug Properties ===
index: 5
stamp: i32
uncheckedStamp: [null]
=== Inputs ===
=== Succesors ===
=== Usages ===
?7 
=== Predecessor ===
- >@ <|@
instruction <@Parameter|@org.graalvm.compiler.nodes.ParameterNode>@  <|@  <|@
tid ?7 <|@
d <@d|@=== Debug Properties ===
bci: 0
code: ResolvedJavaMethodBytecode<URI.appendAuthority(StringBuffer, String, String, String, int)>
duringCall: false
localsSize: 9
locksSize: 0
rethrowException: false
sourceFile: URI.java
sourceLine: 1834
stackSize: 0
=== Inputs ===
outerFrameState: - 
values: - a2 a3 a4 a5 i6 - - - 
=== Succesors ===
=== Usages ===
v30 
=== Predecessor ===
- >@ <|@
instruction <@FrameState|@org.graalvm.compiler.nodes.FrameState>@ outerFrameState: - values: - a2 a3 a4 a5 i6 - - -  <|@  <|@
f <@*|@fixed>@ <|@
tid v30 <|@
d <@d|@=== Debug Properties ===
stamp: void
=== Inputs ===
stateBefore: ?7 
actionAndReason: i28 
speculation: a27 
=== Succesors ===
=== Usages ===
=== Predecessor ===
v24 >@ <|@
instruction <@DynamicDeoptimize|@org.graalvm.compiler.nodes.DynamicDeoptimizeNode>@ stateBefore: ?7 actionAndReason: i28 speculation: a27  <|@  <|@
    end_IR
  end_block
end_cfg
begin_cfg
  name "After LIR generation"
  begin_block
    name "B0"
    from_bci -1
    to_bci -1
    predecessors 
    successors "B1" "B4" 
    xhandlers
    flags 
    probability 4607182418800017408
    begin_IR
      HIR
f <@#|@fixed with next>@ <|@
tid v0 <|@
d <@d|@=== Debug Properties ===
stamp: void
=== Inputs ===
stateAfter: - 
=== Succesors ===
next: v19 
=== Usages ===
=== Predecessor ===
- >@ <|@
instruction <@StartNode|@org.graalvm.compiler.nodes.StartNode>@ stateAfter: - #next: v19  <|@  <|@
f <@~|@floating>@ <|@
tid a3 <|@
result v1|QWORD[.] <|@
d <@d|@=== Debug Properties ===
index: 2
stamp: a# Ljava/lang/String;
uncheckedStamp: [null]
=== Inputs ===
=== Succesors ===
=== Usages ===
?7 v11 
=== Predecessor ===
- >@ <|@
instruction <@Parameter|@org.graalvm.compiler.nodes.ParameterNode>@  <|@  <|@
f <@~|@floating>@ <|@
tid a5 <|@
result v3|QWORD[.] <|@
d <@d|@=== Debug Properties ===
index: 4
stamp: a# Ljava/lang/String;
uncheckedStamp: [null]
=== Inputs ===
=== Succesors ===
=== Usages ===
?7 v9 
=== Predecessor ===
- >@ <|@
instruction <@Parameter|@org.graalvm.compiler.nodes.ParameterNode>@  <|@  <|@
f <@~|@floating>@ <|@
tid v9 <|@
d <@d|@=== Debug Properties ===
nodeSourcePosition: at java.net.URI.appendAuthority(URI.java:1834) [bci: 2]
stamp: void
=== Inputs ===
value: a5 
=== Succesors ===
=== Usages ===
v19 
=== Predecessor ===
- >@ <|@
instruction <@IsNull|@org.graalvm.compiler.nodes.calc.IsNullNode>@ value: a5  <|@  <|@
f <@*|@fixed>@ <|@
tid v19 <|@
d <@d|@=== Debug Properties ===
nodeSourcePosition: at java.net.URI.appendAuthority(URI.java:1834) [bci: 2]
stamp: void
trueSuccessorProbability: 1.0
=== Inputs ===
condition: v9 
=== Succesors ===
trueSuccessor: v16 
falseSuccessor: v18 
=== Usages ===
=== Predecessor ===
v0 >@ <|@
instruction <@If|@org.graalvm.compiler.nodes.IfNode>@ condition: v9 #trueSuccessor: v16 #falseSuccessor: v18  <|@  <|@
    end_IR
    begin_IR
      LIR
      nr   -1  <|@ instruction [rsi|QWORD[.], rdx|QWORD[.], rcx|QWORD[.], r8|QWORD[.], r9|QWORD[.], rdi|DWORD, rbp|QWORD] = LABEL numbPhis: 0 align: false label: ? <|@ <|@
      nr   -1  <|@ instruction stack:16|QWORD = MOVE rbp|QWORD moveKind: QWORD <|@ <|@
      nr   -1  <|@ instruction [] = HOTSPOTLOCKSTACK frameMapBuilder: org.graalvm.compiler.lir.amd64.AMD64FrameMapBuilder@2743c67e slotKind: QWORD <|@ <|@
      nr   -1  <|@ instruction v0|QWORD[.] = MOVE rdx|QWORD[.] moveKind: QWORD <|@ <|@
      nr   -1  <|@ instruction v1|QWORD[.] = MOVE rcx|QWORD[.] moveKind: QWORD <|@ <|@
      nr   -1  <|@ instruction v2|QWORD[.] = MOVE r8|QWORD[.] moveKind: QWORD <|@ <|@
      nr   -1  <|@ instruction v3|QWORD[.] = MOVE r9|QWORD[.] moveKind: QWORD <|@ <|@
      nr   -1  <|@ instruction v4|DWORD = MOVE rdi|DWORD moveKind: DWORD <|@ <|@
      nr   -1  <|@ instruction TEST (x: v3|QWORD[.], y: v3|QWORD[.]) size: QWORD <|@ <|@
      nr   -1  <|@ instruction BRANCH trueDestinationProbability: 1.0 condition: = trueDestination: B0 -> B1 falseDestination: B0 -> B4 <|@ <|@
    end_IR
  end_block
  begin_block
    name "B1"
    from_bci -1
    to_bci -1
    predecessors "B0" 
    successors "B2" "B3" 
    xhandlers
    flags 
    probability 4607182418800017408
    begin_IR
      HIR
f <@#|@fixed with next>@ <|@
tid v16 <|@
d <@d|@=== Debug Properties ===
nodeSourcePosition: at java.net.URI.appendAuthority(URI.java:1834) [bci: 2]
stamp: void
=== Inputs ===
=== Succesors ===
next: v23 
=== Usages ===
=== Predecessor ===
v19 >@ <|@
instruction <@Begin|@org.graalvm.compiler.nodes.BeginNode>@ #next: v23  <|@  <|@
f <@~|@floating>@ <|@
tid v11 <|@
d <@d|@=== Debug Properties ===
nodeSourcePosition: at java.net.URI.appendAuthority(URI.java:1850) [bci: 130]
stamp: void
=== Inputs ===
value: a3 
=== Succesors ===
=== Usages ===
v23 
=== Predecessor ===
- >@ <|@
instruction <@IsNull|@org.graalvm.compiler.nodes.calc.IsNullNode>@ value: a3  <|@  <|@
f <@*|@fixed>@ <|@
tid v23 <|@
d <@d|@=== Debug Properties ===
nodeSourcePosition: at java.net.URI.appendAuthority(URI.java:1850) [bci: 130]
stamp: void
trueSuccessorProbability: 1.0
=== Inputs ===
condition: v11 
=== Succesors ===
trueSuccessor: v20 
falseSuccessor: v22 
=== Usages ===
=== Predecessor ===
v16 >@ <|@
instruction <@If|@org.graalvm.compiler.nodes.IfNode>@ condition: v11 #trueSuccessor: v20 #falseSuccessor: v22  <|@  <|@
    end_IR
    begin_IR
      LIR
      nr   -1  <|@ instruction [] = LABEL numbPhis: 0 align: false label: ? <|@ <|@
      nr   -1  <|@ instruction TEST (x: v1|QWORD[.], y: v1|QWORD[.]) size: QWORD <|@ <|@
      nr   -1  <|@ instruction BRANCH trueDestinationProbability: 1.0 condition: = trueDestination: B1 -> B2 falseDestination: B1 -> B3 <|@ <|@
    end_IR
  end_block
  begin_block
    name "B2"
    from_bci -1
    to_bci -1
    predecessors "B1" 
    successors 
    xhandlers
    flags 
    probability 4607182418800017408
    begin_IR
      HIR
f <@#|@fixed with next>@ <|@
tid v20 <|@
d <@d|@=== Debug Properties ===
nodeSourcePosition: at java.net.URI.appendAuthority(URI.java:1850) [bci: 130]
stamp: void
=== Inputs ===
=== Succesors ===
next: v13 
=== Usages ===
=== Predecessor ===
v23 >@ <|@
instruction <@Begin|@org.graalvm.compiler.nodes.BeginNode>@ #next: v13  <|@  <|@
f <@*|@fixed>@ <|@
tid v13 <|@
d <@d|@=== Debug Properties ===
nodeSourcePosition: at java.net.URI.appendAuthority(URI.java:1876) [bci: 277]
stamp: void
=== Inputs ===
result: - 
memoryMap: - 
=== Succesors ===
=== Usages ===
=== Predecessor ===
v20 >@ <|@
instruction <@Return|@org.graalvm.compiler.nodes.ReturnNode>@ result: - memoryMap: -  <|@  <|@
    end_IR
    begin_IR
      LIR
      nr   -1  <|@ instruction [] = LABEL numbPhis: 0 align: false label: ? <|@ <|@
      nr   -1  <|@ instruction RETURN (savedRbp: stack:16|QWORD, value: -) isStub: false thread: r15 scratchForSafepointOnReturn: rcx config: org.graalvm.compiler.hotspot.GraalHotSpotVMConfig@7222fe45 <|@ <|@
    end_IR
  end_block
  begin_block
    name "B3"
    from_bci -1
    to_bci -1
    predecessors "B1" 
    successors "B5" 
    xhandlers
    flags 
    probability 2355382605114769408
    begin_IR
      HIR
f <@#|@fixed with next>@ <|@
tid v22 <|@
d <@d|@=== Debug Properties ===
nodeSourcePosition: at java.net.URI.appendAuthority(URI.java:1850) [bci: 130]
stamp: void
=== Inputs ===
=== Succesors ===
next: v31 
=== Usages ===
=== Predecessor ===
v23 >@ <|@
instruction <@Begin|@org.graalvm.compiler.nodes.BeginNode>@ #next: v31  <|@  <|@
f <@~|@floating>@ <|@
tid i32 <|@
result int[-3859|0xfffffffffffff0ed] <|@
d <@d|@=== Debug Properties ===
isDefaultStable: false
rawvalue: -3859
stableDimension: 0
stamp: i32 [-3859] ⇊00000000fffff0ed ⇈00000000fffff0ed
stampKind: i32
value: int[-3859|0xfffffffffffff0ed]
=== Inputs ===
=== Succesors ===
=== Usages ===
i28 
=== Predecessor ===
- >@ <|@
instruction <@Constant|@org.graalvm.compiler.nodes.ConstantNode>@  <|@  <|@
f <@*|@fixed>@ <|@
tid v31 <|@
d <@d|@=== Debug Properties ===
stamp: void
=== Inputs ===
=== Succesors ===
=== Usages ===
v24 
=== Predecessor ===
v22 >@ <|@
instruction <@EndNode|@org.graalvm.compiler.nodes.EndNode>@  <|@  <|@
    end_IR
    begin_IR
      LIR
      nr   -1  <|@ instruction [] = LABEL numbPhis: 0 align: false label: ? <|@ <|@
      nr   -1  <|@ instruction JUMP ~[int[-3859|0xfffffffffffff0ed]] destination: B3 -> B5 <|@ <|@
    end_IR
  end_block
  begin_block
    name "B4"
    from_bci -1
    to_bci -1
    predecessors "B0" 
    successors "B5" 
    xhandlers
    flags 
    probability 2355382605114769408
    begin_IR
      HIR
f <@#|@fixed with next>@ <|@
tid v18 <|@
d <@d|@=== Debug Properties ===
nodeSourcePosition: at java.net.URI.appendAuthority(URI.java:1834) [bci: 2]
stamp: void
=== Inputs ===
=== Succesors ===
next: v25 
=== Usages ===
=== Predecessor ===
v19 >@ <|@
instruction <@Begin|@org.graalvm.compiler.nodes.BeginNode>@ #next: v25  <|@  <|@
f <@~|@floating>@ <|@
tid i26 <|@
result int[-3603|0xfffffffffffff1ed] <|@
d <@d|@=== Debug Properties ===
isDefaultStable: false
rawvalue: -3603
stableDimension: 0
stamp: i32 [-3603] ⇊00000000fffff1ed ⇈00000000fffff1ed
stampKind: i32
value: int[-3603|0xfffffffffffff1ed]
=== Inputs ===
=== Succesors ===
=== Usages ===
i28 
=== Predecessor ===
- >@ <|@
instruction <@Constant|@org.graalvm.compiler.nodes.ConstantNode>@  <|@  <|@
f <@*|@fixed>@ <|@
tid v25 <|@
d <@d|@=== Debug Properties ===
stamp: void
=== Inputs ===
=== Succesors ===
=== Usages ===
v24 
=== Predecessor ===
v18 >@ <|@
instruction <@EndNode|@org.graalvm.compiler.nodes.EndNode>@  <|@  <|@
    end_IR
    begin_IR
      LIR
      nr   -1  <|@ instruction [] = LABEL numbPhis: 0 align: false label: ? <|@ <|@
      nr   -1  <|@ instruction JUMP ~[int[-3603|0xfffffffffffff1ed]] destination: B4 -> B5 <|@ <|@
    end_IR
  end_block
  begin_block
    name "B5"
    from_bci -1
    to_bci -1
    predecessors "B4" "B3" 
    successors 
    xhandlers
    flags 
    probability 2359886204742139904
    begin_IR
      HIR
f <@~|@floating>@ <|@
tid i28 <|@
result v5|DWORD <|@
d <@d|@=== Debug Properties ===
stamp: i32 [-3859 - -3603] ⇊00000000fffff0ed ⇈00000000fffff1ed
valueDescription: i32
=== Inputs ===
merge: v24 
values: i26 i32 
=== Succesors ===
=== Usages ===
v30 
=== Predecessor ===
- >@ <|@
instruction <@ValuePhi|@org.graalvm.compiler.nodes.ValuePhiNode>@ merge: v24 values: i26 i32  <|@  <|@
f <@#|@fixed with next>@ <|@
tid v24 <|@
d <@d|@=== Debug Properties ===
stamp: void
=== Inputs ===
stateAfter: - 
ends: v25 v31 
=== Succesors ===
next: v30 
=== Usages ===
i28 
=== Predecessor ===
- >@ <|@
instruction <@Merge|@org.graalvm.compiler.nodes.MergeNode>@ stateAfter: - ends: v25 v31 #next: v30  <|@  <|@
f <@~|@floating>@ <|@
tid a27 <|@
result Object[null] <|@
d <@d|@=== Debug Properties ===
isDefaultStable: false
rawvalue: null
stableDimension: 0
stamp: a - NULL
stampKind: a -
value: Object[null]
=== Inputs ===
=== Succesors ===
=== Usages ===
v30 
=== Predecessor ===
- >@ <|@
instruction <@Constant|@org.graalvm.compiler.nodes.ConstantNode>@  <|@  <|@
f <@~|@floating>@ <|@
tid a2 <|@
result v0|QWORD[.] <|@
d <@d|@=== Debug Properties ===
index: 1
stamp: a# Ljava/lang/StringBuffer;
uncheckedStamp: [null]
=== Inputs ===
=== Succesors ===
=== Usages ===
?7 
=== Predecessor ===
- >@ <|@
instruction <@Parameter|@org.graalvm.compiler.nodes.ParameterNode>@  <|@  <|@
f <@~|@floating>@ <|@
tid a4 <|@
result v2|QWORD[.] <|@
d <@d|@=== Debug Properties ===
index: 3
stamp: a# Ljava/lang/String;
uncheckedStamp: [null]
=== Inputs ===
=== Succesors ===
=== Usages ===
?7 
=== Predecessor ===
- >@ <|@
instruction <@Parameter|@org.graalvm.compiler.nodes.ParameterNode>@  <|@  <|@
f <@~|@floating>@ <|@
tid i6 <|@
result v4|DWORD <|@
d <@d|@=== Debug Properties ===
index: 5
stamp: i32
uncheckedStamp: [null]
=== Inputs ===
=== Succesors ===
=== Usages ===
?7 
=== Predecessor ===
- >@ <|@
instruction <@Parameter|@org.graalvm.compiler.nodes.ParameterNode>@  <|@  <|@
tid ?7 <|@
d <@d|@=== Debug Properties ===
bci: 0
code: ResolvedJavaMethodBytecode<URI.appendAuthority(StringBuffer, String, String, String, int)>
duringCall: false
localsSize: 9
locksSize: 0
rethrowException: false
sourceFile: URI.java
sourceLine: 1834
stackSize: 0
=== Inputs ===
outerFrameState: - 
values: - a2 a3 a4 a5 i6 - - - 
=== Succesors ===
=== Usages ===
v30 
=== Predecessor ===
- >@ <|@
instruction <@FrameState|@org.graalvm.compiler.nodes.FrameState>@ outerFrameState: - values: - a2 a3 a4 a5 i6 - - -  <|@  <|@
f <@*|@fixed>@ <|@
tid v30 <|@
d <@d|@=== Debug Properties ===
stamp: void
=== Inputs ===
stateBefore: ?7 
actionAndReason: i28 
speculation: a27 
=== Succesors ===
=== Usages ===
=== Predecessor ===
v24 >@ <|@
instruction <@DynamicDeoptimize|@org.graalvm.compiler.nodes.DynamicDeoptimizeNode>@ stateBefore: ?7 actionAndReason: i28 speculation: a27  <|@  <|@
    end_IR
    begin_IR
      LIR
      nr   -1  <|@ instruction [v5|DWORD] = LABEL numbPhis: 1 align: false label: ? <|@ <|@
      nr   -1  <|@ instruction MOV (x: [r15|QWORD + 668], y: v5|DWORD) size: DWORD <|@ <|@
      nr   -1  <|@ instruction MOV (x: [r15|QWORD + 680], y: r12|ILLEGAL) size: QWORD <|@ <|@
      nr   -1  <|@ st <@st|@java.net.URI.appendAuthority(URI.java:1834) [bci: 0]
locals: - v0|QWORD[.] v1|QWORD[.] v2|QWORD[.] v3|QWORD[.] v4|DWORD - - - 
>@ <|@ instruction DEOPT info [bci:0] <|@ <|@
    end_IR
  end_block
end_cfg
begin_cfg
  name "After PreAllocationOptimizationStage"
  begin_block
    name "B0"
    from_bci -1
    to_bci -1
    predecessors 
    successors "B1" "B4" 
    xhandlers
    flags 
    probability 4607182418800017408
    begin_IR
      LIR
      nr   -1  <|@ instruction [rsi|QWORD[.], rdx|QWORD[.], rcx|QWORD[.], r8|QWORD[.], r9|QWORD[.], rdi|DWORD, rbp|QWORD] = LABEL numbPhis: 0 align: false label: ? <|@ <|@
      nr   -1  <|@ instruction stack:16|QWORD = MOVE rbp|QWORD moveKind: QWORD <|@ <|@
      nr   -1  <|@ instruction [] = HOTSPOTLOCKSTACK frameMapBuilder: org.graalvm.compiler.lir.amd64.AMD64FrameMapBuilder@2743c67e slotKind: QWORD <|@ <|@
      nr   -1  <|@ instruction v0|QWORD[.] = MOVE rdx|QWORD[.] moveKind: QWORD <|@ <|@
      nr   -1  <|@ instruction v1|QWORD[.] = MOVE rcx|QWORD[.] moveKind: QWORD <|@ <|@
      nr   -1  <|@ instruction v2|QWORD[.] = MOVE r8|QWORD[.] moveKind: QWORD <|@ <|@
      nr   -1  <|@ instruction v3|QWORD[.] = MOVE r9|QWORD[.] moveKind: QWORD <|@ <|@
      nr   -1  <|@ instruction v4|DWORD = MOVE rdi|DWORD moveKind: DWORD <|@ <|@
      nr   -1  <|@ instruction TEST (x: v3|QWORD[.], y: v3|QWORD[.]) size: QWORD <|@ <|@
      nr   -1  <|@ instruction BRANCH trueDestinationProbability: 1.0 condition: = trueDestination: B0 -> B1 falseDestination: B0 -> B4 <|@ <|@
    end_IR
  end_block
  begin_block
    name "B1"
    from_bci -1
    to_bci -1
    predecessors "B0" 
    successors "B2" "B3" 
    xhandlers
    flags 
    probability 4607182418800017408
    begin_IR
      LIR
      nr   -1  <|@ instruction [] = LABEL numbPhis: 0 align: false label: ? <|@ <|@
      nr   -1  <|@ instruction TEST (x: v1|QWORD[.], y: v1|QWORD[.]) size: QWORD <|@ <|@
      nr   -1  <|@ instruction BRANCH trueDestinationProbability: 1.0 condition: = trueDestination: B1 -> B2 falseDestination: B1 -> B3 <|@ <|@
    end_IR
  end_block
  begin_block
    name "B2"
    from_bci -1
    to_bci -1
    predecessors "B1" 
    successors 
    xhandlers
    flags 
    probability 4607182418800017408
    begin_IR
      LIR
      nr   -1  <|@ instruction [] = LABEL numbPhis: 0 align: false label: ? <|@ <|@
      nr   -1  <|@ instruction RETURN (savedRbp: stack:16|QWORD, value: -) isStub: false thread: r15 scratchForSafepointOnReturn: rcx config: org.graalvm.compiler.hotspot.GraalHotSpotVMConfig@7222fe45 <|@ <|@
    end_IR
  end_block
  begin_block
    name "B4"
    from_bci -1
    to_bci -1
    predecessors "B0" 
    successors "B5" 
    xhandlers
    flags 
    probability 2355382605114769408
    begin_IR
      LIR
      nr   -1  <|@ instruction [] = LABEL numbPhis: 0 align: false label: ? <|@ <|@
      nr   -1  <|@ instruction JUMP ~[int[-3603|0xfffffffffffff1ed]] destination: B4 -> B5 <|@ <|@
    end_IR
  end_block
  begin_block
    name "B5"
    from_bci -1
    to_bci -1
    predecessors "B4" "B3" 
    successors 
    xhandlers
    flags 
    probability 2359886204742139904
    begin_IR
      LIR
      nr   -1  <|@ instruction [v5|DWORD] = LABEL numbPhis: 1 align: false label: ? <|@ <|@
      nr   -1  <|@ instruction MOV (x: [r15|QWORD + 668], y: v5|DWORD) size: DWORD <|@ <|@
      nr   -1  <|@ instruction MOV (x: [r15|QWORD + 680], y: r12|ILLEGAL) size: QWORD <|@ <|@
      nr   -1  <|@ st <@st|@java.net.URI.appendAuthority(URI.java:1834) [bci: 0]
locals: - v0|QWORD[.] v1|QWORD[.] v2|QWORD[.] v3|QWORD[.] v4|DWORD - - - 
>@ <|@ instruction DEOPT info [bci:0] <|@ <|@
    end_IR
  end_block
  begin_block
    name "B3"
    from_bci -1
    to_bci -1
    predecessors "B1" 
    successors "B5" 
    xhandlers
    flags 
    probability 2355382605114769408
    begin_IR
      LIR
      nr   -1  <|@ instruction [] = LABEL numbPhis: 0 align: false label: ? <|@ <|@
      nr   -1  <|@ instruction JUMP ~[int[-3859|0xfffffffffffff0ed]] destination: B3 -> B5 <|@ <|@
    end_IR
  end_block
end_cfg
begin_bytecodes
     0: aload         4
     2: ifnull        129
     5: aload_1       
     6: ldc           #96         // "//"
     8: invokevirtual #86         // java.lang.StringBuffer.append:(java.lang.String)java.lang.StringBuffer
    11: pop           
    12: aload_3       
    13: ifnull        38
    16: aload_1       
    17: aload_3       
    18: getstatic     #8          // L_USERINFO:long
    21: getstatic     #7          // H_USERINFO:long
    24: invokestatic  #87         // quote:(java.lang.String, long, long)java.lang.String
    27: invokevirtual #86         // java.lang.StringBuffer.append:(java.lang.String)java.lang.StringBuffer
    30: pop           
    31: aload_1       
    32: bipush        64
    34: invokevirtual #88         // java.lang.StringBuffer.append:(char)java.lang.StringBuffer
    37: pop           
    38: aload         4
    40: bipush        58
    42: invokevirtual #77         // java.lang.String.indexOf:(int)int
    45: iflt          72
    48: aload         4
    50: ldc           #100        // "["
    52: invokevirtual #89         // java.lang.String.startsWith:(java.lang.String)boolean
    55: ifne          72
    58: aload         4
    60: ldc           #102        // "]"
    62: invokevirtual #90         // java.lang.String.endsWith:(java.lang.String)boolean
    65: ifne          72
    68: iconst_1      
    69: goto          73
    72: iconst_0      
    73: istore        6
    75: iload         6
    77: ifeq          87
    80: aload_1       
    81: bipush        91
    83: invokevirtual #88         // java.lang.StringBuffer.append:(char)java.lang.StringBuffer
    86: pop           
    87: aload_1       
    88: aload         4
    90: invokevirtual #86         // java.lang.StringBuffer.append:(java.lang.String)java.lang.StringBuffer
    93: pop           
    94: iload         6
    96: ifeq          106
    99: aload_1       
   100: bipush        93
   102: invokevirtual #88         // java.lang.StringBuffer.append:(char)java.lang.StringBuffer
   105: pop           
   106: iload         5
   108: iconst_m1     
   109: if_icmpeq     126
   112: aload_1       
   113: bipush        58
   115: invokevirtual #88         // java.lang.StringBuffer.append:(char)java.lang.StringBuffer
   118: pop           
   119: aload_1       
   120: iload         5
   122: invokevirtual #91         // java.lang.StringBuffer.append:(int)java.lang.StringBuffer
   125: pop           
   126: goto          277
   129: aload_2       
   130: ifnull        277
   133: aload_1       
   134: ldc           #96         // "//"
   136: invokevirtual #86         // java.lang.StringBuffer.append:(java.lang.String)java.lang.StringBuffer
   139: pop           
   140: aload_2       
   141: ldc           #100        // "["
   143: invokevirtual #89         // java.lang.String.startsWith:(java.lang.String)boolean
   146: ifeq          254
   149: aload_2       
   150: ldc           #102        // "]"
   152: invokevirtual #92         // java.lang.String.indexOf:(java.lang.String)int
   155: istore        6
   157: aload_2       
   158: astore        7
   160: ldc           #106        // ""
   162: astore        8
   164: iload         6
   166: iconst_m1     
   167: if_icmpeq     220
   170: aload_2       
   171: ldc           #107        // ":"
   173: invokevirtual #92         // java.lang.String.indexOf:(java.lang.String)int
   176: iconst_m1     
   177: if_icmpeq     220
   180: iload         6
   182: aload_2       
   183: invokevirtual #76         // java.lang.String.length:()int
   186: if_icmpne     199
   189: aload_2       
   190: astore        8
   192: ldc           #106        // ""
   194: astore        7
   196: goto          220
   199: aload_2       
   200: iconst_0      
   201: iload         6
   203: iconst_1      
   204: iadd          
   205: invokevirtual #93         // java.lang.String.substring:(int, int)java.lang.String
   208: astore        8
   210: aload_2       
   211: iload         6
   213: iconst_1      
   214: iadd          
   215: invokevirtual #94         // java.lang.String.substring:(int)java.lang.String
   218: astore        7
   220: aload_1       
   221: aload         8
   223: invokevirtual #86         // java.lang.StringBuffer.append:(java.lang.String)java.lang.StringBuffer
   226: pop           
   227: aload_1       
   228: aload         7
   230: getstatic     #14         // L_REG_NAME:long
   233: getstatic     #16         // L_SERVER:long
   236: lor           
   237: getstatic     #13         // H_REG_NAME:long
   240: getstatic     #15         // H_SERVER:long
   243: lor           
   244: invokestatic  #87         // quote:(java.lang.String, long, long)java.lang.String
   247: invokevirtual #86         // java.lang.StringBuffer.append:(java.lang.String)java.lang.StringBuffer
   250: pop           
   251: goto          277
   254: aload_1       
   255: aload_2       
   256: getstatic     #14         // L_REG_NAME:long
   259: getstatic     #16         // L_SERVER:long
   262: lor           
   263: getstatic     #13         // H_REG_NAME:long
   266: getstatic     #15         // H_SERVER:long
   269: lor           
   270: invokestatic  #87         // quote:(java.lang.String, long, long)java.lang.String
   273: invokevirtual #86         // java.lang.StringBuffer.append:(java.lang.String)java.lang.StringBuffer
   276: pop           
   277: return        
   <|@
end_bytecodes
begin_cfg
  name "After AllocationStage"
  begin_block
    name "B0"
    from_bci -1
    to_bci -1
    predecessors 
    successors "B1" "B4" 
    xhandlers
    flags 
    probability 4607182418800017408
    begin_IR
      LIR
      nr    0  <|@ instruction [rsi|QWORD[.], rdx|QWORD[.], rcx|QWORD[.], r8|QWORD[.], r9|QWORD[.], rdi|DWORD, rbp|QWORD] = LABEL numbPhis: 0 align: false label: ? <|@ <|@
      nr    2  <|@ instruction stack:16|QWORD = MOVE rbp|QWORD moveKind: QWORD <|@ <|@
      nr    4  <|@ instruction [] = HOTSPOTLOCKSTACK frameMapBuilder: org.graalvm.compiler.lir.amd64.AMD64FrameMapBuilder@2743c67e slotKind: QWORD <|@ <|@
      nr   16  <|@ instruction TEST (x: r9|QWORD[.], y: r9|QWORD[.]) size: QWORD <|@ <|@
      nr   18  <|@ instruction BRANCH trueDestinationProbability: 1.0 condition: = trueDestination: B0 -> B1 falseDestination: B0 -> B4 <|@ <|@
    end_IR
  end_block
  begin_block
    name "B1"
    from_bci -1
    to_bci -1
    predecessors "B0" 
    successors "B2" "B3" 
    xhandlers
    flags 
    probability 4607182418800017408
    begin_IR
      LIR
      nr   20  <|@ instruction [] = LABEL numbPhis: 0 align: false label: ? <|@ <|@
      nr   22  <|@ instruction TEST (x: rcx|QWORD[.], y: rcx|QWORD[.]) size: QWORD <|@ <|@
      nr   24  <|@ instruction BRANCH trueDestinationProbability: 1.0 condition: = trueDestination: B1 -> B2 falseDestination: B1 -> B3 <|@ <|@
    end_IR
  end_block
  begin_block
    name "B2"
    from_bci -1
    to_bci -1
    predecessors "B1" 
    successors 
    xhandlers
    flags 
    probability 4607182418800017408
    begin_IR
      LIR
      nr   26  <|@ instruction [] = LABEL numbPhis: 0 align: false label: ? <|@ <|@
      nr   28  <|@ instruction RETURN (savedRbp: stack:16|QWORD, value: -) isStub: false thread: r15 scratchForSafepointOnReturn: rcx config: org.graalvm.compiler.hotspot.GraalHotSpotVMConfig@7222fe45 <|@ <|@
    end_IR
  end_block
  begin_block
    name "B4"
    from_bci -1
    to_bci -1
    predecessors "B0" 
    successors "B5" 
    xhandlers
    flags 
    probability 2355382605114769408
    begin_IR
      LIR
      nr   30  <|@ instruction [] = LABEL numbPhis: 0 align: false label: ? <|@ <|@
      nr   -1  <|@ instruction r10|DWORD = MOVE input: int[-3603|0xfffffffffffff1ed] // MoveResolver resolve mapping <|@ <|@
      nr   32  <|@ instruction JUMP ~[] destination: B4 -> B5 <|@ <|@
    end_IR
  end_block
  begin_block
    name "B5"
    from_bci -1
    to_bci -1
    predecessors "B4" "B3" 
    successors 
    xhandlers
    flags 
    probability 2359886204742139904
    begin_IR
      LIR
      nr   38  <|@ instruction [] = LABEL numbPhis: 1 align: false label: ? <|@ <|@
      nr   40  <|@ instruction MOV (x: [r15|QWORD + 668], y: r10|DWORD) size: DWORD <|@ <|@
      nr   42  <|@ instruction MOV (x: [r15|QWORD + 680], y: r12|ILLEGAL) size: QWORD <|@ <|@
      nr   44  <|@ st <@st|@reference-map: [rcx:0, rdx:0, r8:0, r9:0]
live-base-pointers: []
java.net.URI.appendAuthority(URI.java:1834) [bci: 0]
locals: - rdx|QWORD[.] rcx|QWORD[.] r8|QWORD[.] r9|QWORD[.] rdi|DWORD - - - 
>@ <|@ instruction DEOPT info [bci:0] <|@ <|@
    end_IR
  end_block
  begin_block
    name "B3"
    from_bci -1
    to_bci -1
    predecessors "B1" 
    successors "B5" 
    xhandlers
    flags 
    probability 2355382605114769408
    begin_IR
      LIR
      nr   34  <|@ instruction [] = LABEL numbPhis: 0 align: false label: ? <|@ <|@
      nr   -1  <|@ instruction r10|DWORD = MOVE input: int[-3859|0xfffffffffffff0ed] // MoveResolver resolve mapping <|@ <|@
      nr   36  <|@ instruction JUMP ~[] destination: B3 -> B5 <|@ <|@
    end_IR
  end_block
end_cfg
begin_bytecodes
     0: aload         4
     2: ifnull        129
     5: aload_1       
     6: ldc           #96         // "//"
     8: invokevirtual #86         // java.lang.StringBuffer.append:(java.lang.String)java.lang.StringBuffer
    11: pop           
    12: aload_3       
    13: ifnull        38
    16: aload_1       
    17: aload_3       
    18: getstatic     #8          // L_USERINFO:long
    21: getstatic     #7          // H_USERINFO:long
    24: invokestatic  #87         // quote:(java.lang.String, long, long)java.lang.String
    27: invokevirtual #86         // java.lang.StringBuffer.append:(java.lang.String)java.lang.StringBuffer
    30: pop           
    31: aload_1       
    32: bipush        64
    34: invokevirtual #88         // java.lang.StringBuffer.append:(char)java.lang.StringBuffer
    37: pop           
    38: aload         4
    40: bipush        58
    42: invokevirtual #77         // java.lang.String.indexOf:(int)int
    45: iflt          72
    48: aload         4
    50: ldc           #100        // "["
    52: invokevirtual #89         // java.lang.String.startsWith:(java.lang.String)boolean
    55: ifne          72
    58: aload         4
    60: ldc           #102        // "]"
    62: invokevirtual #90         // java.lang.String.endsWith:(java.lang.String)boolean
    65: ifne          72
    68: iconst_1      
    69: goto          73
    72: iconst_0      
    73: istore        6
    75: iload         6
    77: ifeq          87
    80: aload_1       
    81: bipush        91
    83: invokevirtual #88         // java.lang.StringBuffer.append:(char)java.lang.StringBuffer
    86: pop           
    87: aload_1       
    88: aload         4
    90: invokevirtual #86         // java.lang.StringBuffer.append:(java.lang.String)java.lang.StringBuffer
    93: pop           
    94: iload         6
    96: ifeq          106
    99: aload_1       
   100: bipush        93
   102: invokevirtual #88         // java.lang.StringBuffer.append:(char)java.lang.StringBuffer
   105: pop           
   106: iload         5
   108: iconst_m1     
   109: if_icmpeq     126
   112: aload_1       
   113: bipush        58
   115: invokevirtual #88         // java.lang.StringBuffer.append:(char)java.lang.StringBuffer
   118: pop           
   119: aload_1       
   120: iload         5
   122: invokevirtual #91         // java.lang.StringBuffer.append:(int)java.lang.StringBuffer
   125: pop           
   126: goto          277
   129: aload_2       
   130: ifnull        277
   133: aload_1       
   134: ldc           #96         // "//"
   136: invokevirtual #86         // java.lang.StringBuffer.append:(java.lang.String)java.lang.StringBuffer
   139: pop           
   140: aload_2       
   141: ldc           #100        // "["
   143: invokevirtual #89         // java.lang.String.startsWith:(java.lang.String)boolean
   146: ifeq          254
   149: aload_2       
   150: ldc           #102        // "]"
   152: invokevirtual #92         // java.lang.String.indexOf:(java.lang.String)int
   155: istore        6
   157: aload_2       
   158: astore        7
   160: ldc           #106        // ""
   162: astore        8
   164: iload         6
   166: iconst_m1     
   167: if_icmpeq     220
   170: aload_2       
   171: ldc           #107        // ":"
   173: invokevirtual #92         // java.lang.String.indexOf:(java.lang.String)int
   176: iconst_m1     
   177: if_icmpeq     220
   180: iload         6
   182: aload_2       
   183: invokevirtual #76         // java.lang.String.length:()int
   186: if_icmpne     199
   189: aload_2       
   190: astore        8
   192: ldc           #106        // ""
   194: astore        7
   196: goto          220
   199: aload_2       
   200: iconst_0      
   201: iload         6
   203: iconst_1      
   204: iadd          
   205: invokevirtual #93         // java.lang.String.substring:(int, int)java.lang.String
   208: astore        8
   210: aload_2       
   211: iload         6
   213: iconst_1      
   214: iadd          
   215: invokevirtual #94         // java.lang.String.substring:(int)java.lang.String
   218: astore        7
   220: aload_1       
   221: aload         8
   223: invokevirtual #86         // java.lang.StringBuffer.append:(java.lang.String)java.lang.StringBuffer
   226: pop           
   227: aload_1       
   228: aload         7
   230: getstatic     #14         // L_REG_NAME:long
   233: getstatic     #16         // L_SERVER:long
   236: lor           
   237: getstatic     #13         // H_REG_NAME:long
   240: getstatic     #15         // H_SERVER:long
   243: lor           
   244: invokestatic  #87         // quote:(java.lang.String, long, long)java.lang.String
   247: invokevirtual #86         // java.lang.StringBuffer.append:(java.lang.String)java.lang.StringBuffer
   250: pop           
   251: goto          277
   254: aload_1       
   255: aload_2       
   256: getstatic     #14         // L_REG_NAME:long
   259: getstatic     #16         // L_SERVER:long
   262: lor           
   263: getstatic     #13         // H_REG_NAME:long
   266: getstatic     #15         // H_SERVER:long
   269: lor           
   270: invokestatic  #87         // quote:(java.lang.String, long, long)java.lang.String
   273: invokevirtual #86         // java.lang.StringBuffer.append:(java.lang.String)java.lang.StringBuffer
   276: pop           
   277: return        
   <|@
end_bytecodes
begin_cfg
  name "After PostAllocationOptimizationStage"
  begin_block
    name "B0"
    from_bci -1
    to_bci -1
    predecessors 
    successors "B1" "B4" 
    xhandlers
    flags 
    probability 4607182418800017408
    begin_IR
      LIR
      nr    0  <|@ instruction [rsi|QWORD[.], rdx|QWORD[.], rcx|QWORD[.], r8|QWORD[.], r9|QWORD[.], rdi|DWORD, rbp|QWORD] = LABEL numbPhis: 0 align: false label: ? <|@ <|@
      nr    2  <|@ instruction stack:16|QWORD = MOVE rbp|QWORD moveKind: QWORD <|@ <|@
      nr    4  <|@ instruction [] = HOTSPOTLOCKSTACK frameMapBuilder: org.graalvm.compiler.lir.amd64.AMD64FrameMapBuilder@2743c67e slotKind: QWORD <|@ <|@
      nr   16  <|@ instruction TEST (x: r9|QWORD[.], y: r9|QWORD[.]) size: QWORD <|@ <|@
      nr   18  <|@ instruction BRANCH trueDestinationProbability: 1.0 condition: = trueDestination: B0 -> B1 falseDestination: B0 -> B4 <|@ <|@
    end_IR
  end_block
  begin_block
    name "B1"
    from_bci -1
    to_bci -1
    predecessors "B0" 
    successors "B2" "B3" 
    xhandlers
    flags 
    probability 4607182418800017408
    begin_IR
      LIR
      nr   20  <|@ instruction [] = LABEL numbPhis: 0 align: false label: ? <|@ <|@
      nr   22  <|@ instruction TEST (x: rcx|QWORD[.], y: rcx|QWORD[.]) size: QWORD <|@ <|@
      nr   24  <|@ instruction BRANCH trueDestinationProbability: 1.0 condition: = trueDestination: B1 -> B2 falseDestination: B1 -> B3 <|@ <|@
    end_IR
  end_block
  begin_block
    name "B2"
    from_bci -1
    to_bci -1
    predecessors "B1" 
    successors 
    xhandlers
    flags 
    probability 4607182418800017408
    begin_IR
      LIR
      nr   26  <|@ instruction [] = LABEL numbPhis: 0 align: false label: ? <|@ <|@
      nr   28  <|@ instruction RETURN (savedRbp: stack:16|QWORD, value: -) isStub: false thread: r15 scratchForSafepointOnReturn: rcx config: org.graalvm.compiler.hotspot.GraalHotSpotVMConfig@7222fe45 <|@ <|@
    end_IR
  end_block
  begin_block
    name "B4"
    from_bci -1
    to_bci -1
    predecessors "B0" 
    successors "B5" 
    xhandlers
    flags 
    probability 2355382605114769408
    begin_IR
      LIR
      nr   30  <|@ instruction [] = LABEL numbPhis: 0 align: false label: ? <|@ <|@
      nr   -1  <|@ instruction r10|DWORD = MOVE input: int[-3603|0xfffffffffffff1ed] // MoveResolver resolve mapping <|@ <|@
      nr   32  <|@ instruction JUMP ~[] destination: B4 -> B5 <|@ <|@
    end_IR
  end_block
  begin_block
    name "B5"
    from_bci -1
    to_bci -1
    predecessors "B4" "B3" 
    successors 
    xhandlers
    flags 
    probability 2359886204742139904
    begin_IR
      LIR
      nr   38  <|@ instruction [] = LABEL numbPhis: 1 align: false label: ? <|@ <|@
      nr   40  <|@ instruction MOV (x: [r15|QWORD + 668], y: r10|DWORD) size: DWORD <|@ <|@
      nr   42  <|@ instruction MOV (x: [r15|QWORD + 680], y: r12|ILLEGAL) size: QWORD <|@ <|@
      nr   44  <|@ st <@st|@reference-map: [rcx:0, rdx:0, r8:0, r9:0]
live-base-pointers: []
java.net.URI.appendAuthority(URI.java:1834) [bci: 0]
locals: - rdx|QWORD[.] rcx|QWORD[.] r8|QWORD[.] r9|QWORD[.] rdi|DWORD - - - 
>@ <|@ instruction DEOPT info [bci:0] <|@ <|@
    end_IR
  end_block
  begin_block
    name "B3"
    from_bci -1
    to_bci -1
    predecessors "B1" 
    successors "B5" 
    xhandlers
    flags 
    probability 2355382605114769408
    begin_IR
      LIR
      nr   34  <|@ instruction [] = LABEL numbPhis: 0 align: false label: ? <|@ <|@
      nr   -1  <|@ instruction r10|DWORD = MOVE input: int[-3859|0xfffffffffffff0ed] // MoveResolver resolve mapping <|@ <|@
      nr   36  <|@ instruction JUMP ~[] destination: B3 -> B5 <|@ <|@
    end_IR
  end_block
end_cfg
begin_bytecodes
     0: aload         4
     2: ifnull        129
     5: aload_1       
     6: ldc           #96         // "//"
     8: invokevirtual #86         // java.lang.StringBuffer.append:(java.lang.String)java.lang.StringBuffer
    11: pop           
    12: aload_3       
    13: ifnull        38
    16: aload_1       
    17: aload_3       
    18: getstatic     #8          // L_USERINFO:long
    21: getstatic     #7          // H_USERINFO:long
    24: invokestatic  #87         // quote:(java.lang.String, long, long)java.lang.String
    27: invokevirtual #86         // java.lang.StringBuffer.append:(java.lang.String)java.lang.StringBuffer
    30: pop           
    31: aload_1       
    32: bipush        64
    34: invokevirtual #88         // java.lang.StringBuffer.append:(char)java.lang.StringBuffer
    37: pop           
    38: aload         4
    40: bipush        58
    42: invokevirtual #77         // java.lang.String.indexOf:(int)int
    45: iflt          72
    48: aload         4
    50: ldc           #100        // "["
    52: invokevirtual #89         // java.lang.String.startsWith:(java.lang.String)boolean
    55: ifne          72
    58: aload         4
    60: ldc           #102        // "]"
    62: invokevirtual #90         // java.lang.String.endsWith:(java.lang.String)boolean
    65: ifne          72
    68: iconst_1      
    69: goto          73
    72: iconst_0      
    73: istore        6
    75: iload         6
    77: ifeq          87
    80: aload_1       
    81: bipush        91
    83: invokevirtual #88         // java.lang.StringBuffer.append:(char)java.lang.StringBuffer
    86: pop           
    87: aload_1       
    88: aload         4
    90: invokevirtual #86         // java.lang.StringBuffer.append:(java.lang.String)java.lang.StringBuffer
    93: pop           
    94: iload         6
    96: ifeq          106
    99: aload_1       
   100: bipush        93
   102: invokevirtual #88         // java.lang.StringBuffer.append:(char)java.lang.StringBuffer
   105: pop           
   106: iload         5
   108: iconst_m1     
   109: if_icmpeq     126
   112: aload_1       
   113: bipush        58
   115: invokevirtual #88         // java.lang.StringBuffer.append:(char)java.lang.StringBuffer
   118: pop           
   119: aload_1       
   120: iload         5
   122: invokevirtual #91         // java.lang.StringBuffer.append:(int)java.lang.StringBuffer
   125: pop           
   126: goto          277
   129: aload_2       
   130: ifnull        277
   133: aload_1       
   134: ldc           #96         // "//"
   136: invokevirtual #86         // java.lang.StringBuffer.append:(java.lang.String)java.lang.StringBuffer
   139: pop           
   140: aload_2       
   141: ldc           #100        // "["
   143: invokevirtual #89         // java.lang.String.startsWith:(java.lang.String)boolean
   146: ifeq          254
   149: aload_2       
   150: ldc           #102        // "]"
   152: invokevirtual #92         // java.lang.String.indexOf:(java.lang.String)int
   155: istore        6
   157: aload_2       
   158: astore        7
   160: ldc           #106        // ""
   162: astore        8
   164: iload         6
   166: iconst_m1     
   167: if_icmpeq     220
   170: aload_2       
   171: ldc           #107        // ":"
   173: invokevirtual #92         // java.lang.String.indexOf:(java.lang.String)int
   176: iconst_m1     
   177: if_icmpeq     220
   180: iload         6
   182: aload_2       
   183: invokevirtual #76         // java.lang.String.length:()int
   186: if_icmpne     199
   189: aload_2       
   190: astore        8
   192: ldc           #106        // ""
   194: astore        7
   196: goto          220
   199: aload_2       
   200: iconst_0      
   201: iload         6
   203: iconst_1      
   204: iadd          
   205: invokevirtual #93         // java.lang.String.substring:(int, int)java.lang.String
   208: astore        8
   210: aload_2       
   211: iload         6
   213: iconst_1      
   214: iadd          
   215: invokevirtual #94         // java.lang.String.substring:(int)java.lang.String
   218: astore        7
   220: aload_1       
   221: aload         8
   223: invokevirtual #86         // java.lang.StringBuffer.append:(java.lang.String)java.lang.StringBuffer
   226: pop           
   227: aload_1       
   228: aload         7
   230: getstatic     #14         // L_REG_NAME:long
   233: getstatic     #16         // L_SERVER:long
   236: lor           
   237: getstatic     #13         // H_REG_NAME:long
   240: getstatic     #15         // H_SERVER:long
   243: lor           
   244: invokestatic  #87         // quote:(java.lang.String, long, long)java.lang.String
   247: invokevirtual #86         // java.lang.StringBuffer.append:(java.lang.String)java.lang.StringBuffer
   250: pop           
   251: goto          277
   254: aload_1       
   255: aload_2       
   256: getstatic     #14         // L_REG_NAME:long
   259: getstatic     #16         // L_SERVER:long
   262: lor           
   263: getstatic     #13         // H_REG_NAME:long
   266: getstatic     #15         // H_SERVER:long
   269: lor           
   270: invokestatic  #87         // quote:(java.lang.String, long, long)java.lang.String
   273: invokevirtual #86         // java.lang.StringBuffer.append:(java.lang.String)java.lang.StringBuffer
   276: pop           
   277: return        
   <|@
end_bytecodes
begin_cfg
  name "After code generation"
end_cfg
begin_nmethod
  <<<HexCodeFile
  Platform AMD64 64  <||@
  HexCode 0 448b560849c1e203493bc20f85efffffff900f1f80000000000f1f800000000089842400c0feff4883ec1848896c24104d85c90f851c0000004885c90f852d000000488b6c24104883c418850500000000c5f877c341baedf1ffff4589979c0200004d89a7a8020000e8000000009041baedf0ffffebe4e80000000090e80000000090  <||@
  Comment 0 2  <||@
  Comment 11 {Field[name=CompilerToVM::Data::SharedRuntime_ic_miss_stub, type=address, offset=0, address=0x105aa1f78, value=0x106805e60]:0x106805e60}  <||@
  Comment 32 [stack overflow check]  <||@
  Comment 32 3  <||@
  Comment 32 1  <||@
  Comment 43 block B0 null  <||@
  Comment 43 0 [rsi|QWORD[.], rdx|QWORD[.], rcx|QWORD[.], r8|QWORD[.], r9|QWORD[.], rdi|DWORD, rbp|QWORD] = LABEL numbPhis: 0 align: false label: ?  <||@
  Comment 43 2 stack:16|QWORD = MOVE rbp|QWORD moveKind: QWORD  <||@
  Comment 48 4 [] = HOTSPOTLOCKSTACK frameMapBuilder: org.graalvm.compiler.lir.amd64.AMD64FrameMapBuilder@2743c67e slotKind: QWORD  <||@
  Comment 48 16 TEST (x: r9|QWORD[.], y: r9|QWORD[.]) size: QWORD  <||@
  Comment 51 18 BRANCH trueDestinationProbability: 1.0 condition: = trueDestination: B0 -> B1 falseDestination: B0 -> B4  <||@
  Comment 57 block B1 null  <||@
  Comment 57 20 [] = LABEL numbPhis: 0 align: false label: ?  <||@
  Comment 57 22 TEST (x: rcx|QWORD[.], y: rcx|QWORD[.]) size: QWORD  <||@
  Comment 60 24 BRANCH trueDestinationProbability: 1.0 condition: = trueDestination: B1 -> B2 falseDestination: B1 -> B3  <||@
  Comment 66 block B2 null  <||@
  Comment 66 26 [] = LABEL numbPhis: 0 align: false label: ?  <||@
  Comment 66 28 RETURN (savedRbp: stack:16|QWORD, value: -) isStub: false thread: r15 scratchForSafepointOnReturn: rcx config: org.graalvm.compiler.hotspot.GraalHotSpotVMConfig@7222fe45  <||@
  Comment 75 12  <||@
  Comment 85 block B4 null  <||@
  Comment 85 30 [] = LABEL numbPhis: 0 align: false label: ?  <||@
  Comment 85 -1 r10|DWORD = MOVE input: int[-3603|0xfffffffffffff1ed]  <||@
  Comment 91 32 JUMP ~[] destination: B4 -> B5  <||@
  Comment 91 block B5 null  <||@
  Comment 91 38 [] = LABEL numbPhis: 1 align: false label: ?  <||@
  Comment 91 40 MOV (x: [r15|QWORD + 668], y: r10|DWORD) size: DWORD  <||@
  Comment 98 42 MOV (x: [r15|QWORD + 680], y: r12|ILLEGAL) size: QWORD  <||@
  Comment 105 44 DEOPT info [bci:0]  <||@
  Comment 105 {Field[name=CompilerToVM::Data::SharedRuntime_deopt_blob_uncommon_trap, type=address, offset=0, address=0x105aa1f90, value=0x1068075fe]:0x1068075fe}  <||@
  Comment 110 [rcx:0, rdx:0, r8:0, r9:0]at java.net.URI.appendAuthority(URI.java:1834) [bci: 0, duringCall: false, rethrow: false]
              |0  |1             |2             |3            |4            |5          |6  |7  |8 
     locals:  |-  |rdx|QWORD[.]  |rcx|QWORD[.]  |r8|QWORD[.]  |r9|QWORD[.]  |rdi|DWORD  |-  |-  |-   <||@
  Comment 111 block B3 null  <||@
  Comment 111 34 [] = LABEL numbPhis: 0 align: false label: ?  <||@
  Comment 111 -1 r10|DWORD = MOVE input: int[-3859|0xfffffffffffff0ed]  <||@
  Comment 117 36 JUMP ~[] destination: B3 -> B5  <||@
  Comment 119 {Stub<ExceptionHandlerStub.exceptionHandler>@0x106c4a620:CallingConvention[rax|QWORD[.], rdx|QWORD]:CallingConvention[rax|QWORD[.], rdx|QWORD]; temps=rdi|ILLEGAL,xmm0|ILLEGAL,xmm1|ILLEGAL,xmm2|ILLEGAL,xmm3|ILLEGAL,xmm4|ILLEGAL,xmm5|ILLEGAL,xmm6|ILLEGAL,xmm7|ILLEGAL,xmm8|ILLEGAL,xmm9|ILLEGAL,xmm10|ILLEGAL,xmm11|ILLEGAL,xmm12|ILLEGAL,xmm13|ILLEGAL,xmm14|ILLEGAL,xmm15|ILLEGAL,xmm16|ILLEGAL,xmm17|ILLEGAL,xmm18|ILLEGAL,xmm19|ILLEGAL,xmm20|ILLEGAL,xmm21|ILLEGAL,xmm22|ILLEGAL,xmm23|ILLEGAL,xmm24|ILLEGAL,xmm25|ILLEGAL,xmm26|ILLEGAL,xmm27|ILLEGAL,xmm28|ILLEGAL,xmm29|ILLEGAL,xmm30|ILLEGAL,xmm31|ILLEGAL,rax|ILLEGAL,rcx|ILLEGAL,rdx|ILLEGAL,rsi|ILLEGAL,r8|ILLEGAL,r9|ILLEGAL,r10|ILLEGAL,r11|ILLEGAL}  <||@
  Comment 119 4  <||@
  Comment 125 {Field[name=CompilerToVM::Data::SharedRuntime_deopt_blob_unpack, type=address, offset=0, address=0x105aa1f88, value=0x106807500]:0x106807500}  <||@
  Comment 125 5  <||@
  HexCodeFile>>> <|@
end_nmethod
begin_compilation
  name " HotSpotCompilation-9437[java.net.URI.appendAuthority(StringBuffer, String, String, String, int)]"
  method "HotSpotCompilation-9437[java.net.URI.appendAuthority(StringBuffer, String, String, String, int)]"
  date 1527005212736
end_compilation
begin_cfg
  name "After code installation"
end_cfg
begin_nmethod
  <<<HexCodeFile
  Platform AMD64 64  <||@
  HexCode 106fc8ea0 448b560849c1e203493bc20f85afcf83ff900f1f80000000000f1f800000000089842400c0feff4883ec1848896c24104d85c90f851c0000004885c90f852d000000488b6c24104883c418850515618cfdc5f877c341baedf1ffff4589979c0200004d89a7a8020000e8f0e683ff9041baedf0ffffebe4e80417c8ff90e8dee583ff90f4f4f4f4f4  <||@
  Comment 0 2  <||@
  Comment 11 {Field[name=CompilerToVM::Data::SharedRuntime_ic_miss_stub, type=address, offset=0, address=0x105aa1f78, value=0x106805e60]:0x106805e60}  <||@
  Comment 32 [stack overflow check]  <||@
  Comment 32 3  <||@
  Comment 32 1  <||@
  Comment 43 block B0 null  <||@
  Comment 43 0 [rsi|QWORD[.], rdx|QWORD[.], rcx|QWORD[.], r8|QWORD[.], r9|QWORD[.], rdi|DWORD, rbp|QWORD] = LABEL numbPhis: 0 align: false label: ?  <||@
  Comment 43 2 stack:16|QWORD = MOVE rbp|QWORD moveKind: QWORD  <||@
  Comment 48 4 [] = HOTSPOTLOCKSTACK frameMapBuilder: org.graalvm.compiler.lir.amd64.AMD64FrameMapBuilder@2743c67e slotKind: QWORD  <||@
  Comment 48 16 TEST (x: r9|QWORD[.], y: r9|QWORD[.]) size: QWORD  <||@
  Comment 51 18 BRANCH trueDestinationProbability: 1.0 condition: = trueDestination: B0 -> B1 falseDestination: B0 -> B4  <||@
  Comment 57 block B1 null  <||@
  Comment 57 20 [] = LABEL numbPhis: 0 align: false label: ?  <||@
  Comment 57 22 TEST (x: rcx|QWORD[.], y: rcx|QWORD[.]) size: QWORD  <||@
  Comment 60 24 BRANCH trueDestinationProbability: 1.0 condition: = trueDestination: B1 -> B2 falseDestination: B1 -> B3  <||@
  Comment 66 block B2 null  <||@
  Comment 66 26 [] = LABEL numbPhis: 0 align: false label: ?  <||@
  Comment 66 28 RETURN (savedRbp: stack:16|QWORD, value: -) isStub: false thread: r15 scratchForSafepointOnReturn: rcx config: org.graalvm.compiler.hotspot.GraalHotSpotVMConfig@7222fe45  <||@
  Comment 75 12  <||@
  Comment 85 block B4 null  <||@
  Comment 85 30 [] = LABEL numbPhis: 0 align: false label: ?  <||@
  Comment 85 -1 r10|DWORD = MOVE input: int[-3603|0xfffffffffffff1ed]  <||@
  Comment 91 32 JUMP ~[] destination: B4 -> B5  <||@
  Comment 91 block B5 null  <||@
  Comment 91 38 [] = LABEL numbPhis: 1 align: false label: ?  <||@
  Comment 91 40 MOV (x: [r15|QWORD + 668], y: r10|DWORD) size: DWORD  <||@
  Comment 98 42 MOV (x: [r15|QWORD + 680], y: r12|ILLEGAL) size: QWORD  <||@
  Comment 105 44 DEOPT info [bci:0]  <||@
  Comment 105 {Field[name=CompilerToVM::Data::SharedRuntime_deopt_blob_uncommon_trap, type=address, offset=0, address=0x105aa1f90, value=0x1068075fe]:0x1068075fe}  <||@
  Comment 110 [rcx:0, rdx:0, r8:0, r9:0]at java.net.URI.appendAuthority(URI.java:1834) [bci: 0, duringCall: false, rethrow: false]
              |0  |1             |2             |3            |4            |5          |6  |7  |8 
     locals:  |-  |rdx|QWORD[.]  |rcx|QWORD[.]  |r8|QWORD[.]  |r9|QWORD[.]  |rdi|DWORD  |-  |-  |-   <||@
  Comment 111 block B3 null  <||@
  Comment 111 34 [] = LABEL numbPhis: 0 align: false label: ?  <||@
  Comment 111 -1 r10|DWORD = MOVE input: int[-3859|0xfffffffffffff0ed]  <||@
  Comment 117 36 JUMP ~[] destination: B3 -> B5  <||@
  Comment 119 {Stub<ExceptionHandlerStub.exceptionHandler>@0x106c4a620:CallingConvention[rax|QWORD[.], rdx|QWORD]:CallingConvention[rax|QWORD[.], rdx|QWORD]; temps=rdi|ILLEGAL,xmm0|ILLEGAL,xmm1|ILLEGAL,xmm2|ILLEGAL,xmm3|ILLEGAL,xmm4|ILLEGAL,xmm5|ILLEGAL,xmm6|ILLEGAL,xmm7|ILLEGAL,xmm8|ILLEGAL,xmm9|ILLEGAL,xmm10|ILLEGAL,xmm11|ILLEGAL,xmm12|ILLEGAL,xmm13|ILLEGAL,xmm14|ILLEGAL,xmm15|ILLEGAL,xmm16|ILLEGAL,xmm17|ILLEGAL,xmm18|ILLEGAL,xmm19|ILLEGAL,xmm20|ILLEGAL,xmm21|ILLEGAL,xmm22|ILLEGAL,xmm23|ILLEGAL,xmm24|ILLEGAL,xmm25|ILLEGAL,xmm26|ILLEGAL,xmm27|ILLEGAL,xmm28|ILLEGAL,xmm29|ILLEGAL,xmm30|ILLEGAL,xmm31|ILLEGAL,rax|ILLEGAL,rcx|ILLEGAL,rdx|ILLEGAL,rsi|ILLEGAL,r8|ILLEGAL,r9|ILLEGAL,r10|ILLEGAL,r11|ILLEGAL}  <||@
  Comment 119 4  <||@
  Comment 125 {Field[name=CompilerToVM::Data::SharedRuntime_deopt_blob_unpack, type=address, offset=0, address=0x105aa1f88, value=0x106807500]:0x106807500}  <||@
  Comment 125 5  <||@
  HexCodeFile>>> <|@
end_nmethod
