begin_compilation
  name " HotSpotCompilation-9373[java.util.Formatter$Flags.parse(char)]"
  method "HotSpotCompilation-9373[java.util.Formatter$Flags.parse(char)]"
  date 1527005205858
end_compilation
begin_cfg
  name "Final HIR schedule"
  begin_block
    name "B0"
    from_bci -1
    to_bci -1
    predecessors 
    successors "B1" "B2" "B3" 
    xhandlers
    flags 
    probability 4607182418800017408
    begin_IR
      HIR
f <@#|@fixed with next>@ <|@
tid v0 <|@
d <@d|@=== Debug Properties ===
stamp: void
=== Inputs ===
stateAfter: - 
=== Succesors ===
next: v12 
=== Usages ===
=== Predecessor ===
- >@ <|@
instruction <@StartNode|@org.graalvm.compiler.nodes.StartNode>@ stateAfter: - #next: v12  <|@  <|@
f <@~|@floating>@ <|@
tid i1 <|@
d <@d|@=== Debug Properties ===
index: 0
stamp: i32 [0 - 65535] ⇈000000000000ffff
uncheckedStamp: [null]
=== Inputs ===
=== Succesors ===
=== Usages ===
?2 v12 
=== Predecessor ===
- >@ <|@
instruction <@Parameter|@org.graalvm.compiler.nodes.ParameterNode>@  <|@  <|@
f <@*|@fixed>@ <|@
tid v12 <|@
d <@d|@=== Debug Properties ===
keyProbabilities: [D@11159b17
keySuccessors: [I@5877428d
keys: [I@135b84b3
nodeSourcePosition: at java.util.Formatter$Flags.parse(Formatter.java:4451) [bci: 1]
stamp: void
=== Inputs ===
value: i1 
=== Succesors ===
successors: v6 v7 v5 
=== Usages ===
=== Predecessor ===
v0 >@ <|@
instruction <@IntegerSwitch|@org.graalvm.compiler.nodes.extended.IntegerSwitchNode>@ value: i1 #successors: v6 v7 v5  <|@  <|@
    end_IR
  end_block
  begin_block
    name "B1"
    from_bci -1
    to_bci -1
    predecessors "B0" 
    successors 
    xhandlers
    flags 
    probability 4607123930493168441
    begin_IR
      HIR
f <@#|@fixed with next>@ <|@
tid v6 <|@
d <@d|@=== Debug Properties ===
nodeSourcePosition: at java.util.Formatter$Flags.parse(Formatter.java:4452) [bci: 132]
stamp: void
=== Inputs ===
=== Succesors ===
next: v11 
=== Usages ===
=== Predecessor ===
v12 >@ <|@
instruction <@Begin|@org.graalvm.compiler.nodes.BeginNode>@ #next: v11  <|@  <|@
f <@~|@floating>@ <|@
tid a10 <|@
d <@d|@=== Debug Properties ===
isDefaultStable: false
nodeSourcePosition: at java.util.Formatter$Flags.parse(Formatter.java:4452) [bci: 132]
rawvalue: Formatter.Flags@122446495
stableDimension: 0
stamp: a!# Ljava/util/Formatter$Flags;
stampKind: a -
value: Object[Formatter.Flags@122446495]
=== Inputs ===
=== Succesors ===
=== Usages ===
v11 
=== Predecessor ===
- >@ <|@
instruction <@Constant|@org.graalvm.compiler.nodes.ConstantNode>@  <|@  <|@
f <@*|@fixed>@ <|@
tid v11 <|@
d <@d|@=== Debug Properties ===
nodeSourcePosition: at java.util.Formatter$Flags.parse(Formatter.java:4452) [bci: 135]
stamp: void
=== Inputs ===
result: a10 
memoryMap: - 
=== Succesors ===
=== Usages ===
=== Predecessor ===
v6 >@ <|@
instruction <@Return|@org.graalvm.compiler.nodes.ReturnNode>@ result: a10 memoryMap: -  <|@  <|@
    end_IR
  end_block
  begin_block
    name "B2"
    from_bci -1
    to_bci -1
    predecessors "B0" 
    successors 
    xhandlers
    flags 
    probability 4574136525430350782
    begin_IR
      HIR
f <@#|@fixed with next>@ <|@
tid v7 <|@
d <@d|@=== Debug Properties ===
nodeSourcePosition: at java.util.Formatter$Flags.parse(Formatter.java:4456) [bci: 148]
stamp: void
=== Inputs ===
=== Succesors ===
next: v9 
=== Usages ===
=== Predecessor ===
v12 >@ <|@
instruction <@Begin|@org.graalvm.compiler.nodes.BeginNode>@ #next: v9  <|@  <|@
f <@~|@floating>@ <|@
tid a8 <|@
d <@d|@=== Debug Properties ===
isDefaultStable: false
nodeSourcePosition: at java.util.Formatter$Flags.parse(Formatter.java:4456) [bci: 148]
rawvalue: Formatter.Flags@271681927
stableDimension: 0
stamp: a!# Ljava/util/Formatter$Flags;
stampKind: a -
value: Object[Formatter.Flags@271681927]
=== Inputs ===
=== Succesors ===
=== Usages ===
v9 
=== Predecessor ===
- >@ <|@
instruction <@Constant|@org.graalvm.compiler.nodes.ConstantNode>@  <|@  <|@
f <@*|@fixed>@ <|@
tid v9 <|@
d <@d|@=== Debug Properties ===
nodeSourcePosition: at java.util.Formatter$Flags.parse(Formatter.java:4456) [bci: 151]
stamp: void
=== Inputs ===
result: a8 
memoryMap: - 
=== Succesors ===
=== Usages ===
=== Predecessor ===
v7 >@ <|@
instruction <@Return|@org.graalvm.compiler.nodes.ReturnNode>@ result: a8 memoryMap: -  <|@  <|@
    end_IR
  end_block
  begin_block
    name "B3"
    from_bci -1
    to_bci -1
    predecessors "B0" 
    successors 
    xhandlers
    flags 
    probability 2355382605114769408
    begin_IR
      HIR
f <@#|@fixed with next>@ <|@
tid v5 <|@
d <@d|@=== Debug Properties ===
nodeSourcePosition: at java.util.Formatter$Flags.parse(Formatter.java:4451) [bci: 1]
stamp: void
=== Inputs ===
=== Succesors ===
next: v4 
=== Usages ===
=== Predecessor ===
v12 >@ <|@
instruction <@Begin|@org.graalvm.compiler.nodes.BeginNode>@ #next: v4  <|@  <|@
tid ?2 <|@
d <@d|@=== Debug Properties ===
bci: 0
code: ResolvedJavaMethodBytecode<Formatter$Flags.parse(char)>
duringCall: false
localsSize: 1
locksSize: 0
rethrowException: false
sourceFile: Formatter.java
sourceLine: 4451
stackSize: 0
=== Inputs ===
outerFrameState: - 
values: i1 
=== Succesors ===
=== Usages ===
v4 
=== Predecessor ===
- >@ <|@
instruction <@FrameState|@org.graalvm.compiler.nodes.FrameState>@ outerFrameState: - values: i1  <|@  <|@
f <@*|@fixed>@ <|@
tid v4 <|@
d <@d|@=== Debug Properties ===
action: InvalidateReprofile
debugId: 0
nodeSourcePosition: at java.util.Formatter$Flags.parse(Formatter.java:4451) [bci: 1]
reason: UnreachedCode
speculation: Object[null]
stamp: void
=== Inputs ===
stateBefore: ?2 
=== Succesors ===
=== Usages ===
=== Predecessor ===
v5 >@ <|@
instruction <@Deopt|@org.graalvm.compiler.nodes.DeoptimizeNode>@ stateBefore: ?2  <|@  <|@
    end_IR
  end_block
end_cfg
begin_cfg
  name "After LIR generation"
  begin_block
    name "B0"
    from_bci -1
    to_bci -1
    predecessors 
    successors "B1" "B2" "B3" 
    xhandlers
    flags 
    probability 4607182418800017408
    begin_IR
      HIR
f <@#|@fixed with next>@ <|@
tid v0 <|@
d <@d|@=== Debug Properties ===
stamp: void
=== Inputs ===
stateAfter: - 
=== Succesors ===
next: v12 
=== Usages ===
=== Predecessor ===
- >@ <|@
instruction <@StartNode|@org.graalvm.compiler.nodes.StartNode>@ stateAfter: - #next: v12  <|@  <|@
f <@~|@floating>@ <|@
tid i1 <|@
result v0|DWORD <|@
d <@d|@=== Debug Properties ===
index: 0
stamp: i32 [0 - 65535] ⇈000000000000ffff
uncheckedStamp: [null]
=== Inputs ===
=== Succesors ===
=== Usages ===
?2 v12 
=== Predecessor ===
- >@ <|@
instruction <@Parameter|@org.graalvm.compiler.nodes.ParameterNode>@  <|@  <|@
f <@*|@fixed>@ <|@
tid v12 <|@
d <@d|@=== Debug Properties ===
keyProbabilities: [D@11159b17
keySuccessors: [I@5877428d
keys: [I@135b84b3
nodeSourcePosition: at java.util.Formatter$Flags.parse(Formatter.java:4451) [bci: 1]
stamp: void
=== Inputs ===
value: i1 
=== Succesors ===
successors: v6 v7 v5 
=== Usages ===
=== Predecessor ===
v0 >@ <|@
instruction <@IntegerSwitch|@org.graalvm.compiler.nodes.extended.IntegerSwitchNode>@ value: i1 #successors: v6 v7 v5  <|@  <|@
    end_IR
    begin_IR
      LIR
      nr   -1  <|@ instruction [rsi|DWORD, rbp|QWORD] = LABEL numbPhis: 0 align: false label: ? <|@ <|@
      nr   -1  <|@ instruction stack:16|QWORD = MOVE rbp|QWORD moveKind: QWORD <|@ <|@
      nr   -1  <|@ instruction [] = HOTSPOTLOCKSTACK frameMapBuilder: org.graalvm.compiler.lir.amd64.AMD64FrameMapBuilder@b067190 slotKind: QWORD <|@ <|@
      nr   -1  <|@ instruction v0|DWORD = MOVE rsi|DWORD moveKind: DWORD <|@ <|@
      nr   -1  <|@ instruction AMD64HOTSPOTSTRATEGYSWITCH ~v0|DWORD - keyConstants: [int[45|0x2d], int[48|0x30]] keyTargets: [B0 -> B1, B0 -> B2] defaultTarget: B0 -> B3 strategy: SequentialStrategy[avgEffort=1.0064935064935066] <|@ <|@
    end_IR
  end_block
  begin_block
    name "B1"
    from_bci -1
    to_bci -1
    predecessors "B0" 
    successors 
    xhandlers
    flags 
    probability 4607123930493168441
    begin_IR
      HIR
f <@#|@fixed with next>@ <|@
tid v6 <|@
d <@d|@=== Debug Properties ===
nodeSourcePosition: at java.util.Formatter$Flags.parse(Formatter.java:4452) [bci: 132]
stamp: void
=== Inputs ===
=== Succesors ===
next: v11 
=== Usages ===
=== Predecessor ===
v12 >@ <|@
instruction <@Begin|@org.graalvm.compiler.nodes.BeginNode>@ #next: v11  <|@  <|@
f <@~|@floating>@ <|@
tid a10 <|@
result v1|QWORD[.] <|@
d <@d|@=== Debug Properties ===
isDefaultStable: false
nodeSourcePosition: at java.util.Formatter$Flags.parse(Formatter.java:4452) [bci: 132]
rawvalue: Formatter.Flags@122446495
stableDimension: 0
stamp: a!# Ljava/util/Formatter$Flags;
stampKind: a -
value: Object[Formatter.Flags@122446495]
=== Inputs ===
=== Succesors ===
=== Usages ===
v11 
=== Predecessor ===
- >@ <|@
instruction <@Constant|@org.graalvm.compiler.nodes.ConstantNode>@  <|@  <|@
f <@*|@fixed>@ <|@
tid v11 <|@
d <@d|@=== Debug Properties ===
nodeSourcePosition: at java.util.Formatter$Flags.parse(Formatter.java:4452) [bci: 135]
stamp: void
=== Inputs ===
result: a10 
memoryMap: - 
=== Succesors ===
=== Usages ===
=== Predecessor ===
v6 >@ <|@
instruction <@Return|@org.graalvm.compiler.nodes.ReturnNode>@ result: a10 memoryMap: -  <|@  <|@
    end_IR
    begin_IR
      LIR
      nr   -1  <|@ instruction [] = LABEL numbPhis: 0 align: false label: ? <|@ <|@
      nr   -1  <|@ instruction v1|QWORD[.] = HOTSPOTLOADOBJECTCONSTANT input: Object[Formatter.Flags@122446495] <|@ <|@
      nr   -1  <|@ instruction rax|QWORD[.] = MOVE v1|QWORD[.] moveKind: QWORD <|@ <|@
      nr   -1  <|@ instruction RETURN (savedRbp: stack:16|QWORD, value: rax|QWORD[.]) isStub: false thread: r15 scratchForSafepointOnReturn: rcx config: org.graalvm.compiler.hotspot.GraalHotSpotVMConfig@7222fe45 <|@ <|@
    end_IR
  end_block
  begin_block
    name "B2"
    from_bci -1
    to_bci -1
    predecessors "B0" 
    successors 
    xhandlers
    flags 
    probability 4574136525430350782
    begin_IR
      HIR
f <@#|@fixed with next>@ <|@
tid v7 <|@
d <@d|@=== Debug Properties ===
nodeSourcePosition: at java.util.Formatter$Flags.parse(Formatter.java:4456) [bci: 148]
stamp: void
=== Inputs ===
=== Succesors ===
next: v9 
=== Usages ===
=== Predecessor ===
v12 >@ <|@
instruction <@Begin|@org.graalvm.compiler.nodes.BeginNode>@ #next: v9  <|@  <|@
f <@~|@floating>@ <|@
tid a8 <|@
result v2|QWORD[.] <|@
d <@d|@=== Debug Properties ===
isDefaultStable: false
nodeSourcePosition: at java.util.Formatter$Flags.parse(Formatter.java:4456) [bci: 148]
rawvalue: Formatter.Flags@271681927
stableDimension: 0
stamp: a!# Ljava/util/Formatter$Flags;
stampKind: a -
value: Object[Formatter.Flags@271681927]
=== Inputs ===
=== Succesors ===
=== Usages ===
v9 
=== Predecessor ===
- >@ <|@
instruction <@Constant|@org.graalvm.compiler.nodes.ConstantNode>@  <|@  <|@
f <@*|@fixed>@ <|@
tid v9 <|@
d <@d|@=== Debug Properties ===
nodeSourcePosition: at java.util.Formatter$Flags.parse(Formatter.java:4456) [bci: 151]
stamp: void
=== Inputs ===
result: a8 
memoryMap: - 
=== Succesors ===
=== Usages ===
=== Predecessor ===
v7 >@ <|@
instruction <@Return|@org.graalvm.compiler.nodes.ReturnNode>@ result: a8 memoryMap: -  <|@  <|@
    end_IR
    begin_IR
      LIR
      nr   -1  <|@ instruction [] = LABEL numbPhis: 0 align: false label: ? <|@ <|@
      nr   -1  <|@ instruction v2|QWORD[.] = HOTSPOTLOADOBJECTCONSTANT input: Object[Formatter.Flags@271681927] <|@ <|@
      nr   -1  <|@ instruction rax|QWORD[.] = MOVE v2|QWORD[.] moveKind: QWORD <|@ <|@
      nr   -1  <|@ instruction RETURN (savedRbp: stack:16|QWORD, value: rax|QWORD[.]) isStub: false thread: r15 scratchForSafepointOnReturn: rcx config: org.graalvm.compiler.hotspot.GraalHotSpotVMConfig@7222fe45 <|@ <|@
    end_IR
  end_block
  begin_block
    name "B3"
    from_bci -1
    to_bci -1
    predecessors "B0" 
    successors 
    xhandlers
    flags 
    probability 2355382605114769408
    begin_IR
      HIR
f <@#|@fixed with next>@ <|@
tid v5 <|@
d <@d|@=== Debug Properties ===
nodeSourcePosition: at java.util.Formatter$Flags.parse(Formatter.java:4451) [bci: 1]
stamp: void
=== Inputs ===
=== Succesors ===
next: v4 
=== Usages ===
=== Predecessor ===
v12 >@ <|@
instruction <@Begin|@org.graalvm.compiler.nodes.BeginNode>@ #next: v4  <|@  <|@
tid ?2 <|@
d <@d|@=== Debug Properties ===
bci: 0
code: ResolvedJavaMethodBytecode<Formatter$Flags.parse(char)>
duringCall: false
localsSize: 1
locksSize: 0
rethrowException: false
sourceFile: Formatter.java
sourceLine: 4451
stackSize: 0
=== Inputs ===
outerFrameState: - 
values: i1 
=== Succesors ===
=== Usages ===
v4 
=== Predecessor ===
- >@ <|@
instruction <@FrameState|@org.graalvm.compiler.nodes.FrameState>@ outerFrameState: - values: i1  <|@  <|@
f <@*|@fixed>@ <|@
tid v4 <|@
d <@d|@=== Debug Properties ===
action: InvalidateReprofile
debugId: 0
nodeSourcePosition: at java.util.Formatter$Flags.parse(Formatter.java:4451) [bci: 1]
reason: UnreachedCode
speculation: Object[null]
stamp: void
=== Inputs ===
stateBefore: ?2 
=== Succesors ===
=== Usages ===
=== Predecessor ===
v5 >@ <|@
instruction <@Deopt|@org.graalvm.compiler.nodes.DeoptimizeNode>@ stateBefore: ?2  <|@  <|@
    end_IR
    begin_IR
      LIR
      nr   -1  <|@ instruction [] = LABEL numbPhis: 0 align: false label: ? <|@ <|@
      nr   -1  <|@ instruction MOV [r15|QWORD + 668] y: -1043 size: DWORD <|@ <|@
      nr   -1  <|@ instruction MOV (x: [r15|QWORD + 680], y: r12|ILLEGAL) size: QWORD <|@ <|@
      nr   -1  <|@ st <@st|@java.util.Formatter$Flags.parse(Formatter.java:4451) [bci: 0]
locals: v0|DWORD 
>@ <|@ instruction DEOPT info [bci:0] <|@ <|@
    end_IR
  end_block
end_cfg
begin_cfg
  name "After PreAllocationOptimizationStage"
  begin_block
    name "B0"
    from_bci -1
    to_bci -1
    predecessors 
    successors "B1" "B2" "B3" 
    xhandlers
    flags 
    probability 4607182418800017408
    begin_IR
      LIR
      nr   -1  <|@ instruction [rsi|DWORD, rbp|QWORD] = LABEL numbPhis: 0 align: false label: ? <|@ <|@
      nr   -1  <|@ instruction stack:16|QWORD = MOVE rbp|QWORD moveKind: QWORD <|@ <|@
      nr   -1  <|@ instruction [] = HOTSPOTLOCKSTACK frameMapBuilder: org.graalvm.compiler.lir.amd64.AMD64FrameMapBuilder@b067190 slotKind: QWORD <|@ <|@
      nr   -1  <|@ instruction v0|DWORD = MOVE rsi|DWORD moveKind: DWORD <|@ <|@
      nr   -1  <|@ instruction AMD64HOTSPOTSTRATEGYSWITCH ~v0|DWORD - keyConstants: [int[45|0x2d], int[48|0x30]] keyTargets: [B0 -> B1, B0 -> B2] defaultTarget: B0 -> B3 strategy: SequentialStrategy[avgEffort=1.0064935064935066] <|@ <|@
    end_IR
  end_block
  begin_block
    name "B1"
    from_bci -1
    to_bci -1
    predecessors "B0" 
    successors 
    xhandlers
    flags 
    probability 4607123930493168441
    begin_IR
      LIR
      nr   -1  <|@ instruction [] = LABEL numbPhis: 0 align: false label: ? <|@ <|@
      nr   -1  <|@ instruction v1|QWORD[.] = HOTSPOTLOADOBJECTCONSTANT input: Object[Formatter.Flags@122446495] <|@ <|@
      nr   -1  <|@ instruction rax|QWORD[.] = MOVE v1|QWORD[.] moveKind: QWORD <|@ <|@
      nr   -1  <|@ instruction RETURN (savedRbp: stack:16|QWORD, value: rax|QWORD[.]) isStub: false thread: r15 scratchForSafepointOnReturn: rcx config: org.graalvm.compiler.hotspot.GraalHotSpotVMConfig@7222fe45 <|@ <|@
    end_IR
  end_block
  begin_block
    name "B2"
    from_bci -1
    to_bci -1
    predecessors "B0" 
    successors 
    xhandlers
    flags 
    probability 4574136525430350782
    begin_IR
      LIR
      nr   -1  <|@ instruction [] = LABEL numbPhis: 0 align: false label: ? <|@ <|@
      nr   -1  <|@ instruction v2|QWORD[.] = HOTSPOTLOADOBJECTCONSTANT input: Object[Formatter.Flags@271681927] <|@ <|@
      nr   -1  <|@ instruction rax|QWORD[.] = MOVE v2|QWORD[.] moveKind: QWORD <|@ <|@
      nr   -1  <|@ instruction RETURN (savedRbp: stack:16|QWORD, value: rax|QWORD[.]) isStub: false thread: r15 scratchForSafepointOnReturn: rcx config: org.graalvm.compiler.hotspot.GraalHotSpotVMConfig@7222fe45 <|@ <|@
    end_IR
  end_block
  begin_block
    name "B3"
    from_bci -1
    to_bci -1
    predecessors "B0" 
    successors 
    xhandlers
    flags 
    probability 2355382605114769408
    begin_IR
      LIR
      nr   -1  <|@ instruction [] = LABEL numbPhis: 0 align: false label: ? <|@ <|@
      nr   -1  <|@ instruction MOV [r15|QWORD + 668] y: -1043 size: DWORD <|@ <|@
      nr   -1  <|@ instruction MOV (x: [r15|QWORD + 680], y: r12|ILLEGAL) size: QWORD <|@ <|@
      nr   -1  <|@ st <@st|@java.util.Formatter$Flags.parse(Formatter.java:4451) [bci: 0]
locals: v0|DWORD 
>@ <|@ instruction DEOPT info [bci:0] <|@ <|@
    end_IR
  end_block
end_cfg
begin_bytecodes
     0: iload_0       
     1: tableswitch   [29] {32: 144, 33: 164, 34: 164, 35: 136, 36: 164, 37: 164, 38: 164, 39: 164, 40: 156, 41: 164, 42: 164, 43: 140, 44: 152, 45: 132, 46: 164, 47: 164, 48: 148, 49: 164, 50: 164, 51: 164, 52: 164, 53: 164, 54: 164, 55: 164, 56: 164, 57: 164, 58: 164, 59: 164, 60: 160} default: 164
   132: getstatic     #10         // LEFT_JUSTIFY:java.util.Formatter$Flags
   135: areturn       
   136: getstatic     #11         // ALTERNATE:java.util.Formatter$Flags
   139: areturn       
   140: getstatic     #12         // PLUS:java.util.Formatter$Flags
   143: areturn       
   144: getstatic     #13         // LEADING_SPACE:java.util.Formatter$Flags
   147: areturn       
   148: getstatic     #14         // ZERO_PAD:java.util.Formatter$Flags
   151: areturn       
   152: getstatic     #15         // GROUP:java.util.Formatter$Flags
   155: areturn       
   156: getstatic     #16         // PARENTHESES:java.util.Formatter$Flags
   159: areturn       
   160: getstatic     #17         // PREVIOUS:java.util.Formatter$Flags
   163: areturn       
   164: new           #21         // java.util.UnknownFormatFlagsException
   167: dup           
   168: iload_0       
   169: invokestatic  #18         // java.lang.String.valueOf:(char)java.lang.String
   172: invokespecial #19         // java.util.UnknownFormatFlagsException.<init>:(java.lang.String)void
   175: athrow        
   <|@
end_bytecodes
begin_cfg
  name "After AllocationStage"
  begin_block
    name "B0"
    from_bci -1
    to_bci -1
    predecessors 
    successors "B1" "B2" "B3" 
    xhandlers
    flags 
    probability 4607182418800017408
    begin_IR
      LIR
      nr    0  <|@ instruction [rsi|DWORD, rbp|QWORD] = LABEL numbPhis: 0 align: false label: ? <|@ <|@
      nr    2  <|@ instruction stack:16|QWORD = MOVE rbp|QWORD moveKind: QWORD <|@ <|@
      nr    4  <|@ instruction [] = HOTSPOTLOCKSTACK frameMapBuilder: org.graalvm.compiler.lir.amd64.AMD64FrameMapBuilder@b067190 slotKind: QWORD <|@ <|@
      nr    8  <|@ instruction AMD64HOTSPOTSTRATEGYSWITCH ~rsi|DWORD - keyConstants: [int[45|0x2d], int[48|0x30]] keyTargets: [B0 -> B1, B0 -> B2] defaultTarget: B0 -> B3 strategy: SequentialStrategy[avgEffort=1.0064935064935066] <|@ <|@
    end_IR
  end_block
  begin_block
    name "B1"
    from_bci -1
    to_bci -1
    predecessors "B0" 
    successors 
    xhandlers
    flags 
    probability 4607123930493168441
    begin_IR
      LIR
      nr   10  <|@ instruction [] = LABEL numbPhis: 0 align: false label: ? <|@ <|@
      nr   12  <|@ instruction rax|QWORD[.] = HOTSPOTLOADOBJECTCONSTANT input: Object[Formatter.Flags@122446495] <|@ <|@
      nr   16  <|@ instruction RETURN (savedRbp: stack:16|QWORD, value: rax|QWORD[.]) isStub: false thread: r15 scratchForSafepointOnReturn: rcx config: org.graalvm.compiler.hotspot.GraalHotSpotVMConfig@7222fe45 <|@ <|@
    end_IR
  end_block
  begin_block
    name "B2"
    from_bci -1
    to_bci -1
    predecessors "B0" 
    successors 
    xhandlers
    flags 
    probability 4574136525430350782
    begin_IR
      LIR
      nr   18  <|@ instruction [] = LABEL numbPhis: 0 align: false label: ? <|@ <|@
      nr   20  <|@ instruction rax|QWORD[.] = HOTSPOTLOADOBJECTCONSTANT input: Object[Formatter.Flags@271681927] <|@ <|@
      nr   24  <|@ instruction RETURN (savedRbp: stack:16|QWORD, value: rax|QWORD[.]) isStub: false thread: r15 scratchForSafepointOnReturn: rcx config: org.graalvm.compiler.hotspot.GraalHotSpotVMConfig@7222fe45 <|@ <|@
    end_IR
  end_block
  begin_block
    name "B3"
    from_bci -1
    to_bci -1
    predecessors "B0" 
    successors 
    xhandlers
    flags 
    probability 2355382605114769408
    begin_IR
      LIR
      nr   26  <|@ instruction [] = LABEL numbPhis: 0 align: false label: ? <|@ <|@
      nr   28  <|@ instruction MOV [r15|QWORD + 668] y: -1043 size: DWORD <|@ <|@
      nr   30  <|@ instruction MOV (x: [r15|QWORD + 680], y: r12|ILLEGAL) size: QWORD <|@ <|@
      nr   32  <|@ st <@st|@reference-map: []
live-base-pointers: []
java.util.Formatter$Flags.parse(Formatter.java:4451) [bci: 0]
locals: rsi|DWORD 
>@ <|@ instruction DEOPT info [bci:0] <|@ <|@
    end_IR
  end_block
end_cfg
begin_bytecodes
     0: iload_0       
     1: tableswitch   [29] {32: 144, 33: 164, 34: 164, 35: 136, 36: 164, 37: 164, 38: 164, 39: 164, 40: 156, 41: 164, 42: 164, 43: 140, 44: 152, 45: 132, 46: 164, 47: 164, 48: 148, 49: 164, 50: 164, 51: 164, 52: 164, 53: 164, 54: 164, 55: 164, 56: 164, 57: 164, 58: 164, 59: 164, 60: 160} default: 164
   132: getstatic     #10         // LEFT_JUSTIFY:java.util.Formatter$Flags
   135: areturn       
   136: getstatic     #11         // ALTERNATE:java.util.Formatter$Flags
   139: areturn       
   140: getstatic     #12         // PLUS:java.util.Formatter$Flags
   143: areturn       
   144: getstatic     #13         // LEADING_SPACE:java.util.Formatter$Flags
   147: areturn       
   148: getstatic     #14         // ZERO_PAD:java.util.Formatter$Flags
   151: areturn       
   152: getstatic     #15         // GROUP:java.util.Formatter$Flags
   155: areturn       
   156: getstatic     #16         // PARENTHESES:java.util.Formatter$Flags
   159: areturn       
   160: getstatic     #17         // PREVIOUS:java.util.Formatter$Flags
   163: areturn       
   164: new           #21         // java.util.UnknownFormatFlagsException
   167: dup           
   168: iload_0       
   169: invokestatic  #18         // java.lang.String.valueOf:(char)java.lang.String
   172: invokespecial #19         // java.util.UnknownFormatFlagsException.<init>:(java.lang.String)void
   175: athrow        
   <|@
end_bytecodes
begin_cfg
  name "After PostAllocationOptimizationStage"
  begin_block
    name "B0"
    from_bci -1
    to_bci -1
    predecessors 
    successors "B1" "B2" "B3" 
    xhandlers
    flags 
    probability 4607182418800017408
    begin_IR
      LIR
      nr    0  <|@ instruction [rsi|DWORD, rbp|QWORD] = LABEL numbPhis: 0 align: false label: ? <|@ <|@
      nr    2  <|@ instruction stack:16|QWORD = MOVE rbp|QWORD moveKind: QWORD <|@ <|@
      nr    4  <|@ instruction [] = HOTSPOTLOCKSTACK frameMapBuilder: org.graalvm.compiler.lir.amd64.AMD64FrameMapBuilder@b067190 slotKind: QWORD <|@ <|@
      nr    8  <|@ instruction AMD64HOTSPOTSTRATEGYSWITCH ~rsi|DWORD - keyConstants: [int[45|0x2d], int[48|0x30]] keyTargets: [B0 -> B1, B0 -> B2] defaultTarget: B0 -> B3 strategy: SequentialStrategy[avgEffort=1.0064935064935066] <|@ <|@
    end_IR
  end_block
  begin_block
    name "B1"
    from_bci -1
    to_bci -1
    predecessors "B0" 
    successors 
    xhandlers
    flags 
    probability 4607123930493168441
    begin_IR
      LIR
      nr   10  <|@ instruction [] = LABEL numbPhis: 0 align: false label: ? <|@ <|@
      nr   12  <|@ instruction rax|QWORD[.] = HOTSPOTLOADOBJECTCONSTANT input: Object[Formatter.Flags@122446495] <|@ <|@
      nr   16  <|@ instruction RETURN (savedRbp: stack:16|QWORD, value: rax|QWORD[.]) isStub: false thread: r15 scratchForSafepointOnReturn: rcx config: org.graalvm.compiler.hotspot.GraalHotSpotVMConfig@7222fe45 <|@ <|@
    end_IR
  end_block
  begin_block
    name "B2"
    from_bci -1
    to_bci -1
    predecessors "B0" 
    successors 
    xhandlers
    flags 
    probability 4574136525430350782
    begin_IR
      LIR
      nr   18  <|@ instruction [] = LABEL numbPhis: 0 align: false label: ? <|@ <|@
      nr   20  <|@ instruction rax|QWORD[.] = HOTSPOTLOADOBJECTCONSTANT input: Object[Formatter.Flags@271681927] <|@ <|@
      nr   24  <|@ instruction RETURN (savedRbp: stack:16|QWORD, value: rax|QWORD[.]) isStub: false thread: r15 scratchForSafepointOnReturn: rcx config: org.graalvm.compiler.hotspot.GraalHotSpotVMConfig@7222fe45 <|@ <|@
    end_IR
  end_block
  begin_block
    name "B3"
    from_bci -1
    to_bci -1
    predecessors "B0" 
    successors 
    xhandlers
    flags 
    probability 2355382605114769408
    begin_IR
      LIR
      nr   26  <|@ instruction [] = LABEL numbPhis: 0 align: false label: ? <|@ <|@
      nr   28  <|@ instruction MOV [r15|QWORD + 668] y: -1043 size: DWORD <|@ <|@
      nr   30  <|@ instruction MOV (x: [r15|QWORD + 680], y: r12|ILLEGAL) size: QWORD <|@ <|@
      nr   32  <|@ st <@st|@reference-map: []
live-base-pointers: []
java.util.Formatter$Flags.parse(Formatter.java:4451) [bci: 0]
locals: rsi|DWORD 
>@ <|@ instruction DEOPT info [bci:0] <|@ <|@
    end_IR
  end_block
end_cfg
begin_bytecodes
     0: iload_0       
     1: tableswitch   [29] {32: 144, 33: 164, 34: 164, 35: 136, 36: 164, 37: 164, 38: 164, 39: 164, 40: 156, 41: 164, 42: 164, 43: 140, 44: 152, 45: 132, 46: 164, 47: 164, 48: 148, 49: 164, 50: 164, 51: 164, 52: 164, 53: 164, 54: 164, 55: 164, 56: 164, 57: 164, 58: 164, 59: 164, 60: 160} default: 164
   132: getstatic     #10         // LEFT_JUSTIFY:java.util.Formatter$Flags
   135: areturn       
   136: getstatic     #11         // ALTERNATE:java.util.Formatter$Flags
   139: areturn       
   140: getstatic     #12         // PLUS:java.util.Formatter$Flags
   143: areturn       
   144: getstatic     #13         // LEADING_SPACE:java.util.Formatter$Flags
   147: areturn       
   148: getstatic     #14         // ZERO_PAD:java.util.Formatter$Flags
   151: areturn       
   152: getstatic     #15         // GROUP:java.util.Formatter$Flags
   155: areturn       
   156: getstatic     #16         // PARENTHESES:java.util.Formatter$Flags
   159: areturn       
   160: getstatic     #17         // PREVIOUS:java.util.Formatter$Flags
   163: areturn       
   164: new           #21         // java.util.UnknownFormatFlagsException
   167: dup           
   168: iload_0       
   169: invokestatic  #18         // java.lang.String.valueOf:(char)java.lang.String
   172: invokespecial #19         // java.util.UnknownFormatFlagsException.<init>:(java.lang.String)void
   175: athrow        
   <|@
end_bytecodes
begin_cfg
  name "After code generation"
end_cfg
begin_nmethod
  <<<HexCodeFile
  Platform AMD64 64  <||@
  HexCode 0 89842400c0feff4883ec1848896c241083fe2d0f840e00000083fe300f8422000000e93a00000048b8addeaddeaddeadde488b6c24104883c418850500000000c5f877c348b8addeaddeaddeadde488b6c24104883c418850500000000c5f877c341c7879c020000edfbffff4d89a7a8020000e80000000090e80000000090e80000000090  <||@
  Comment 0 [stack overflow check]  <||@
  Comment 0 3  <||@
  Comment 0 1  <||@
  Comment 11 block B0 null  <||@
  Comment 11 0 [rsi|DWORD, rbp|QWORD] = LABEL numbPhis: 0 align: false label: ?  <||@
  Comment 11 2 stack:16|QWORD = MOVE rbp|QWORD moveKind: QWORD  <||@
  Comment 16 4 [] = HOTSPOTLOCKSTACK frameMapBuilder: org.graalvm.compiler.lir.amd64.AMD64FrameMapBuilder@b067190 slotKind: QWORD  <||@
  Comment 16 8 AMD64HOTSPOTSTRATEGYSWITCH ~rsi|DWORD - keyConstants: [int[45|0x2d], int[48|0x30]] keyTargets: [B0 -> B1, B0 -> B2] defaultTarget: B0 -> B3 strategy: SequentialStrategy[avgEffort=1.0064935064935066]  <||@
  Comment 39 block B1 null  <||@
  Comment 39 10 [] = LABEL numbPhis: 0 align: false label: ?  <||@
  Comment 39 12 rax|QWORD[.] = HOTSPOTLOADOBJECTCONSTANT input: Object[Formatter.Flags@122446495]  <||@
  Comment 39 {Object[Formatter.Flags@122446495]}  <||@
  Comment 49 16 RETURN (savedRbp: stack:16|QWORD, value: rax|QWORD[.]) isStub: false thread: r15 scratchForSafepointOnReturn: rcx config: org.graalvm.compiler.hotspot.GraalHotSpotVMConfig@7222fe45  <||@
  Comment 58 12  <||@
  Comment 68 block B2 null  <||@
  Comment 68 18 [] = LABEL numbPhis: 0 align: false label: ?  <||@
  Comment 68 20 rax|QWORD[.] = HOTSPOTLOADOBJECTCONSTANT input: Object[Formatter.Flags@271681927]  <||@
  Comment 68 {Object[Formatter.Flags@271681927]}  <||@
  Comment 78 24 RETURN (savedRbp: stack:16|QWORD, value: rax|QWORD[.]) isStub: false thread: r15 scratchForSafepointOnReturn: rcx config: org.graalvm.compiler.hotspot.GraalHotSpotVMConfig@7222fe45  <||@
  Comment 87 12  <||@
  Comment 97 block B3 null  <||@
  Comment 97 26 [] = LABEL numbPhis: 0 align: false label: ?  <||@
  Comment 97 28 MOV [r15|QWORD + 668] y: -1043 size: DWORD  <||@
  Comment 108 30 MOV (x: [r15|QWORD + 680], y: r12|ILLEGAL) size: QWORD  <||@
  Comment 115 32 DEOPT info [bci:0]  <||@
  Comment 115 {Field[name=CompilerToVM::Data::SharedRuntime_deopt_blob_uncommon_trap, type=address, offset=0, address=0x105aa1f90, value=0x1068075fe]:0x1068075fe}  <||@
  Comment 120 []at java.util.Formatter$Flags.parse(Formatter.java:4451) [bci: 0, duringCall: false, rethrow: false]
              |0         
     locals:  |rsi|DWORD   <||@
  Comment 121 {Stub<ExceptionHandlerStub.exceptionHandler>@0x106c4a620:CallingConvention[rax|QWORD[.], rdx|QWORD]:CallingConvention[rax|QWORD[.], rdx|QWORD]; temps=rdi|ILLEGAL,xmm0|ILLEGAL,xmm1|ILLEGAL,xmm2|ILLEGAL,xmm3|ILLEGAL,xmm4|ILLEGAL,xmm5|ILLEGAL,xmm6|ILLEGAL,xmm7|ILLEGAL,xmm8|ILLEGAL,xmm9|ILLEGAL,xmm10|ILLEGAL,xmm11|ILLEGAL,xmm12|ILLEGAL,xmm13|ILLEGAL,xmm14|ILLEGAL,xmm15|ILLEGAL,xmm16|ILLEGAL,xmm17|ILLEGAL,xmm18|ILLEGAL,xmm19|ILLEGAL,xmm20|ILLEGAL,xmm21|ILLEGAL,xmm22|ILLEGAL,xmm23|ILLEGAL,xmm24|ILLEGAL,xmm25|ILLEGAL,xmm26|ILLEGAL,xmm27|ILLEGAL,xmm28|ILLEGAL,xmm29|ILLEGAL,xmm30|ILLEGAL,xmm31|ILLEGAL,rax|ILLEGAL,rcx|ILLEGAL,rdx|ILLEGAL,rsi|ILLEGAL,r8|ILLEGAL,r9|ILLEGAL,r10|ILLEGAL,r11|ILLEGAL}  <||@
  Comment 121 4  <||@
  Comment 127 {Field[name=CompilerToVM::Data::SharedRuntime_deopt_blob_unpack, type=address, offset=0, address=0x105aa1f88, value=0x106807500]:0x106807500}  <||@
  Comment 127 5  <||@
  HexCodeFile>>> <|@
end_nmethod
begin_compilation
  name " HotSpotCompilation-9373[java.util.Formatter$Flags.parse(char)]"
  method "HotSpotCompilation-9373[java.util.Formatter$Flags.parse(char)]"
  date 1527005205874
end_compilation
begin_cfg
  name "After code installation"
end_cfg
begin_nmethod
  <<<HexCodeFile
  Platform AMD64 64  <||@
  HexCode 107921560 89842400c0feff4883ec1848896c241083fe2d0f840e00000083fe300f8422000000e93a00000048b858711ac006000000488b6c24104883c418850566daf6fcc5f877c348b888711ac006000000488b6c24104883c418850549daf6fcc5f877c341c7879c020000edfbffff4d89a7a8020000e82660eefe90e8429032ff90e81c5feefe90f4f4f4  <||@
  Comment 0 [stack overflow check]  <||@
  Comment 0 3  <||@
  Comment 0 1  <||@
  Comment 11 block B0 null  <||@
  Comment 11 0 [rsi|DWORD, rbp|QWORD] = LABEL numbPhis: 0 align: false label: ?  <||@
  Comment 11 2 stack:16|QWORD = MOVE rbp|QWORD moveKind: QWORD  <||@
  Comment 16 4 [] = HOTSPOTLOCKSTACK frameMapBuilder: org.graalvm.compiler.lir.amd64.AMD64FrameMapBuilder@b067190 slotKind: QWORD  <||@
  Comment 16 8 AMD64HOTSPOTSTRATEGYSWITCH ~rsi|DWORD - keyConstants: [int[45|0x2d], int[48|0x30]] keyTargets: [B0 -> B1, B0 -> B2] defaultTarget: B0 -> B3 strategy: SequentialStrategy[avgEffort=1.0064935064935066]  <||@
  Comment 39 block B1 null  <||@
  Comment 39 10 [] = LABEL numbPhis: 0 align: false label: ?  <||@
  Comment 39 12 rax|QWORD[.] = HOTSPOTLOADOBJECTCONSTANT input: Object[Formatter.Flags@122446495]  <||@
  Comment 39 {Object[Formatter.Flags@122446495]}  <||@
  Comment 49 16 RETURN (savedRbp: stack:16|QWORD, value: rax|QWORD[.]) isStub: false thread: r15 scratchForSafepointOnReturn: rcx config: org.graalvm.compiler.hotspot.GraalHotSpotVMConfig@7222fe45  <||@
  Comment 58 12  <||@
  Comment 68 block B2 null  <||@
  Comment 68 18 [] = LABEL numbPhis: 0 align: false label: ?  <||@
  Comment 68 20 rax|QWORD[.] = HOTSPOTLOADOBJECTCONSTANT input: Object[Formatter.Flags@271681927]  <||@
  Comment 68 {Object[Formatter.Flags@271681927]}  <||@
  Comment 78 24 RETURN (savedRbp: stack:16|QWORD, value: rax|QWORD[.]) isStub: false thread: r15 scratchForSafepointOnReturn: rcx config: org.graalvm.compiler.hotspot.GraalHotSpotVMConfig@7222fe45  <||@
  Comment 87 12  <||@
  Comment 97 block B3 null  <||@
  Comment 97 26 [] = LABEL numbPhis: 0 align: false label: ?  <||@
  Comment 97 28 MOV [r15|QWORD + 668] y: -1043 size: DWORD  <||@
  Comment 108 30 MOV (x: [r15|QWORD + 680], y: r12|ILLEGAL) size: QWORD  <||@
  Comment 115 32 DEOPT info [bci:0]  <||@
  Comment 115 {Field[name=CompilerToVM::Data::SharedRuntime_deopt_blob_uncommon_trap, type=address, offset=0, address=0x105aa1f90, value=0x1068075fe]:0x1068075fe}  <||@
  Comment 120 []at java.util.Formatter$Flags.parse(Formatter.java:4451) [bci: 0, duringCall: false, rethrow: false]
              |0         
     locals:  |rsi|DWORD   <||@
  Comment 121 {Stub<ExceptionHandlerStub.exceptionHandler>@0x106c4a620:CallingConvention[rax|QWORD[.], rdx|QWORD]:CallingConvention[rax|QWORD[.], rdx|QWORD]; temps=rdi|ILLEGAL,xmm0|ILLEGAL,xmm1|ILLEGAL,xmm2|ILLEGAL,xmm3|ILLEGAL,xmm4|ILLEGAL,xmm5|ILLEGAL,xmm6|ILLEGAL,xmm7|ILLEGAL,xmm8|ILLEGAL,xmm9|ILLEGAL,xmm10|ILLEGAL,xmm11|ILLEGAL,xmm12|ILLEGAL,xmm13|ILLEGAL,xmm14|ILLEGAL,xmm15|ILLEGAL,xmm16|ILLEGAL,xmm17|ILLEGAL,xmm18|ILLEGAL,xmm19|ILLEGAL,xmm20|ILLEGAL,xmm21|ILLEGAL,xmm22|ILLEGAL,xmm23|ILLEGAL,xmm24|ILLEGAL,xmm25|ILLEGAL,xmm26|ILLEGAL,xmm27|ILLEGAL,xmm28|ILLEGAL,xmm29|ILLEGAL,xmm30|ILLEGAL,xmm31|ILLEGAL,rax|ILLEGAL,rcx|ILLEGAL,rdx|ILLEGAL,rsi|ILLEGAL,r8|ILLEGAL,r9|ILLEGAL,r10|ILLEGAL,r11|ILLEGAL}  <||@
  Comment 121 4  <||@
  Comment 127 {Field[name=CompilerToVM::Data::SharedRuntime_deopt_blob_unpack, type=address, offset=0, address=0x105aa1f88, value=0x106807500]:0x106807500}  <||@
  Comment 127 5  <||@
  HexCodeFile>>> <|@
end_nmethod
