begin_compilation
  name " HotSpotCompilation-9244[java.lang.StackTraceElement.<init>(String, String, String, int)]"
  method "HotSpotCompilation-9244[java.lang.StackTraceElement.<init>(String, String, String, int)]"
  date 1527005202557
end_compilation
begin_cfg
  name "Final HIR schedule"
  begin_block
    name "B0"
    from_bci -1
    to_bci -1
    predecessors 
    successors "B1" "B2" 
    xhandlers
    flags 
    probability 4607182418800017408
    begin_IR
      HIR
f <@#|@fixed with next>@ <|@
tid v0 <|@
d <@d|@=== Debug Properties ===
stamp: void
=== Inputs ===
stateAfter: - 
=== Succesors ===
next: v76 
=== Usages ===
=== Predecessor ===
- >@ <|@
instruction <@StartNode|@org.graalvm.compiler.nodes.StartNode>@ stateAfter: - #next: v76  <|@  <|@
f <@~|@floating>@ <|@
tid a1 <|@
d <@d|@=== Debug Properties ===
index: 0
stamp: a!# Ljava/lang/StackTraceElement;
uncheckedStamp: [null]
=== Inputs ===
=== Succesors ===
=== Usages ===
?6 v71 v73 v72 v74 j61 
=== Predecessor ===
- >@ <|@
instruction <@Parameter|@org.graalvm.compiler.nodes.ParameterNode>@  <|@  <|@
f <@~|@floating>@ <|@
tid a2 <|@
d <@d|@=== Debug Properties ===
index: 1
stamp: a# Ljava/lang/String;
uncheckedStamp: [null]
=== Inputs ===
=== Succesors ===
=== Usages ===
?6 v76 a25 
=== Predecessor ===
- >@ <|@
instruction <@Parameter|@org.graalvm.compiler.nodes.ParameterNode>@  <|@  <|@
f <@~|@floating>@ <|@
tid a3 <|@
d <@d|@=== Debug Properties ===
index: 2
stamp: a# Ljava/lang/String;
uncheckedStamp: [null]
=== Inputs ===
=== Succesors ===
=== Usages ===
?6 a30 v15 
=== Predecessor ===
- >@ <|@
instruction <@Parameter|@org.graalvm.compiler.nodes.ParameterNode>@  <|@  <|@
f <@~|@floating>@ <|@
tid a4 <|@
d <@d|@=== Debug Properties ===
index: 3
stamp: a# Ljava/lang/String;
uncheckedStamp: [null]
=== Inputs ===
=== Succesors ===
=== Usages ===
?6 a34 
=== Predecessor ===
- >@ <|@
instruction <@Parameter|@org.graalvm.compiler.nodes.ParameterNode>@  <|@  <|@
f <@~|@floating>@ <|@
tid i5 <|@
d <@d|@=== Debug Properties ===
index: 4
stamp: i32
uncheckedStamp: [null]
=== Inputs ===
=== Succesors ===
=== Usages ===
?6 v40 
=== Predecessor ===
- >@ <|@
instruction <@Parameter|@org.graalvm.compiler.nodes.ParameterNode>@  <|@  <|@
tid ?6 <|@
d <@d|@=== Debug Properties ===
bci: 0
code: ResolvedJavaMethodBytecode<StackTraceElement.<init>(String, String, String, int)>
duringCall: false
localsSize: 5
locksSize: 0
rethrowException: false
sourceFile: StackTraceElement.java
sourceLine: 70
stackSize: 0
=== Inputs ===
outerFrameState: - 
values: a1 a2 a3 a4 i5 
=== Succesors ===
=== Usages ===
v55 v76 
=== Predecessor ===
- >@ <|@
instruction <@FrameState|@org.graalvm.compiler.nodes.FrameState>@ outerFrameState: - values: a1 a2 a3 a4 i5  <|@  <|@
f <@#|@fixed with next>@ <|@
tid v76 <|@
d <@d|@=== Debug Properties ===
stamp: void
=== Inputs ===
stateBefore: ?6 
object: a2 
=== Succesors ===
next: v48 
=== Usages ===
=== Predecessor ===
v0 >@ <|@
instruction <@NullCheck|@org.graalvm.compiler.nodes.extended.NullCheckNode>@ stateBefore: ?6 object: a2 #next: v48  <|@  <|@
f <@~|@floating>@ <|@
tid v15 <|@
d <@d|@=== Debug Properties ===
nodeSourcePosition: at java.util.Objects.requireNonNull(Objects.java:227) [bci: 1]
at java.lang.StackTraceElement.<init>(StackTraceElement.java:72) [bci: 21]
stamp: void
=== Inputs ===
value: a3 
=== Succesors ===
=== Usages ===
v48 
=== Predecessor ===
- >@ <|@
instruction <@IsNull|@org.graalvm.compiler.nodes.calc.IsNullNode>@ value: a3  <|@  <|@
f <@*|@fixed>@ <|@
tid v48 <|@
d <@d|@=== Debug Properties ===
nodeSourcePosition: at java.util.Objects.requireNonNull(Objects.java:227) [bci: 1]
at java.lang.StackTraceElement.<init>(StackTraceElement.java:72) [bci: 21]
stamp: void
trueSuccessorProbability: 0.0
=== Inputs ===
condition: v15 
=== Succesors ===
trueSuccessor: v47 
falseSuccessor: v45 
=== Usages ===
=== Predecessor ===
v76 >@ <|@
instruction <@If|@org.graalvm.compiler.nodes.IfNode>@ condition: v15 #trueSuccessor: v47 #falseSuccessor: v45  <|@  <|@
    end_IR
  end_block
  begin_block
    name "B1"
    from_bci -1
    to_bci -1
    predecessors "B0" 
    successors 
    xhandlers
    flags 
    probability 2355382605114769408
    begin_IR
      HIR
f <@#|@fixed with next>@ <|@
tid v47 <|@
d <@d|@=== Debug Properties ===
nodeSourcePosition: at java.util.Objects.requireNonNull(Objects.java:227) [bci: 1]
at java.lang.StackTraceElement.<init>(StackTraceElement.java:72) [bci: 21]
stamp: void
=== Inputs ===
=== Succesors ===
next: v55 
=== Usages ===
=== Predecessor ===
v48 >@ <|@
instruction <@Begin|@org.graalvm.compiler.nodes.BeginNode>@ #next: v55  <|@  <|@
f <@~|@floating>@ <|@
tid a52 <|@
d <@d|@=== Debug Properties ===
isDefaultStable: false
rawvalue: null
stableDimension: 0
stamp: a - NULL
stampKind: a -
value: Object[null]
=== Inputs ===
=== Succesors ===
=== Usages ===
v55 
=== Predecessor ===
- >@ <|@
instruction <@Constant|@org.graalvm.compiler.nodes.ConstantNode>@  <|@  <|@
f <@~|@floating>@ <|@
tid i57 <|@
d <@d|@=== Debug Properties ===
isDefaultStable: false
rawvalue: -7443
stableDimension: 0
stamp: i32 [-7443] ⇊00000000ffffe2ed ⇈00000000ffffe2ed
stampKind: i32
value: int[-7443|0xffffffffffffe2ed]
=== Inputs ===
=== Succesors ===
=== Usages ===
v55 
=== Predecessor ===
- >@ <|@
instruction <@Constant|@org.graalvm.compiler.nodes.ConstantNode>@  <|@  <|@
f <@*|@fixed>@ <|@
tid v55 <|@
d <@d|@=== Debug Properties ===
stamp: void
=== Inputs ===
stateBefore: ?6 
actionAndReason: i57 
speculation: a52 
=== Succesors ===
=== Usages ===
=== Predecessor ===
v47 >@ <|@
instruction <@DynamicDeoptimize|@org.graalvm.compiler.nodes.DynamicDeoptimizeNode>@ stateBefore: ?6 actionAndReason: i57 speculation: a52  <|@  <|@
    end_IR
  end_block
  begin_block
    name "B2"
    from_bci -1
    to_bci -1
    predecessors "B0" 
    successors 
    xhandlers
    flags 
    probability 4607182418800017408
    begin_IR
      HIR
f <@#|@fixed with next>@ <|@
tid v45 <|@
d <@d|@=== Debug Properties ===
nodeSourcePosition: at java.util.Objects.requireNonNull(Objects.java:227) [bci: 1]
at java.lang.StackTraceElement.<init>(StackTraceElement.java:72) [bci: 21]
stamp: void
=== Inputs ===
=== Succesors ===
next: v28 
=== Usages ===
=== Predecessor ===
v48 >@ <|@
instruction <@Begin|@org.graalvm.compiler.nodes.BeginNode>@ #next: v28  <|@  <|@
f <@~|@floating>@ <|@
tid v71 <|@
d <@d|@=== Debug Properties ===
displacement: 12
scale: Times1
stamp: void*
=== Inputs ===
base: a1 
index: - 
=== Succesors ===
=== Usages ===
v28 
=== Predecessor ===
- >@ <|@
instruction <@AMD64Address|@org.graalvm.compiler.core.amd64.AMD64AddressNode>@ base: a1 index: -  <|@  <|@
f <@~|@floating>@ <|@
tid a25 <|@
d <@d|@=== Debug Properties ===
encoding: base: 0 shift: 3
nodeSourcePosition: at java.lang.StackTraceElement.<init>(StackTraceElement.java:71) [bci: 14]
op: Compress
stamp: n# Ljava/lang/String;
=== Inputs ===
value: a2 
=== Succesors ===
=== Usages ===
v28 
=== Predecessor ===
- >@ <|@
instruction <@HotSpotCompression|@org.graalvm.compiler.hotspot.nodes.HotSpotCompressionNode>@ value: a2  <|@  <|@
f <@#|@fixed with next>@ <|@
tid v28 <|@
d <@d|@=== Debug Properties ===
barrierType: IMPRECISE
location: StackTraceElement.declaringClass
nodeSourcePosition: at java.lang.StackTraceElement.<init>(StackTraceElement.java:71) [bci: 14]
nullCheck: false
stamp: void
=== Inputs ===
stateBefore: - 
guard: - 
address: v71 
value: a25 
stateAfter: - 
lastLocationAccess: - 
=== Succesors ===
next: j61 
=== Usages ===
=== Predecessor ===
v45 >@ <|@
instruction <@Write|@org.graalvm.compiler.nodes.memory.WriteNode>@ stateBefore: - guard: - address: v71 value: a25 stateAfter: - lastLocationAccess: - #next: j61  <|@  <|@
f <@#|@fixed with next>@ <|@
tid j61 <|@
d <@d|@=== Debug Properties ===
nodeSourcePosition: at org.graalvm.compiler.hotspot.replacements.WriteBarrierSnippets.serialImpreciseWriteBarrier(WriteBarrierSnippets.java:144) [bci: 1]
at java.lang.StackTraceElement.<init>(StackTraceElement.java:71) [bci: 14]
stamp: i64
trackedPointer: true
=== Inputs ===
input: a1 
=== Succesors ===
next: v67 
=== Usages ===
j63 
=== Predecessor ===
v28 >@ <|@
instruction <@WordCast|@org.graalvm.compiler.word.WordCastNode>@ input: a1 #next: v67  <|@  <|@
f <@~|@floating>@ <|@
tid i62 <|@
d <@d|@=== Debug Properties ===
isDefaultStable: false
nodeSourcePosition: at org.graalvm.compiler.hotspot.replacements.HotSpotReplacementsUtil.cardTableShift(GraalHotSpotVMConfig) [bci: -1]
at org.graalvm.compiler.hotspot.replacements.WriteBarrierSnippets.serialWriteBarrier(WriteBarrierSnippets.java:134) [bci: 15]
at org.graalvm.compiler.hotspot.replacements.WriteBarrierSnippets.serialImpreciseWriteBarrier(WriteBarrierSnippets.java:144) [bci: 5]
at java.lang.StackTraceElement.<init>(StackTraceElement.java:71) [bci: 14]
rawvalue: 9
stableDimension: 0
stamp: i32 [9] ⇊0000000000000009 ⇈0000000000000009
stampKind: i32
value: int[9|0x9]
=== Inputs ===
=== Succesors ===
=== Usages ===
j63 
=== Predecessor ===
- >@ <|@
instruction <@Constant|@org.graalvm.compiler.nodes.ConstantNode>@  <|@  <|@
f <@~|@floating>@ <|@
tid j63 <|@
d <@d|@=== Debug Properties ===
getOp: org.graalvm.compiler.nodes.calc.UnsignedRightShiftNode$$Lambda$68/774788493@3e7195e9
nodeSourcePosition: at org.graalvm.compiler.hotspot.replacements.WriteBarrierSnippets.serialWriteBarrier(WriteBarrierSnippets.java:134) [bci: 18]
at org.graalvm.compiler.hotspot.replacements.WriteBarrierSnippets.serialImpreciseWriteBarrier(WriteBarrierSnippets.java:144) [bci: 5]
at java.lang.StackTraceElement.<init>(StackTraceElement.java:71) [bci: 14]
stamp: i64 [0 - 36028797018963967] ⇈007fffffffffffff
=== Inputs ===
x: j61 
y: i62 
=== Succesors ===
=== Usages ===
v75 
=== Predecessor ===
- >@ <|@
instruction <@>>>|@org.graalvm.compiler.nodes.calc.UnsignedRightShiftNode>@ x: j61 y: i62  <|@  <|@
f <@~|@floating>@ <|@
tid j66 <|@
d <@d|@=== Debug Properties ===
isDefaultStable: false
nodeSourcePosition: at org.graalvm.compiler.hotspot.nodes.GraalHotSpotVMConfigNode.loadLongConfigValue(int) [bci: -1]
at org.graalvm.compiler.hotspot.nodes.GraalHotSpotVMConfigNode.cardTableAddress(GraalHotSpotVMConfigNode.java:114) [bci: 6]
at org.graalvm.compiler.hotspot.replacements.WriteBarrierSnippets.serialWriteBarrier(WriteBarrierSnippets.java:133) [bci: 7]
at org.graalvm.compiler.hotspot.replacements.WriteBarrierSnippets.serialImpreciseWriteBarrier(WriteBarrierSnippets.java:144) [bci: 5]
at java.lang.StackTraceElement.<init>(StackTraceElement.java:71) [bci: 14]
rawvalue: 4682670080
stableDimension: 0
stamp: i64 [4682670080] ⇊00000001171be000 ⇈00000001171be000
stampKind: i64
value: long[4682670080|0x1171be000]
=== Inputs ===
=== Succesors ===
=== Usages ===
v75 
=== Predecessor ===
- >@ <|@
instruction <@Constant|@org.graalvm.compiler.nodes.ConstantNode>@  <|@  <|@
f <@~|@floating>@ <|@
tid v75 <|@
d <@d|@=== Debug Properties ===
displacement: 0
scale: Times1
stamp: void*
=== Inputs ===
base: j63 
index: j66 
=== Succesors ===
=== Usages ===
v67 
=== Predecessor ===
- >@ <|@
instruction <@AMD64Address|@org.graalvm.compiler.core.amd64.AMD64AddressNode>@ base: j63 index: j66  <|@  <|@
f <@~|@floating>@ <|@
tid i68 <|@
d <@d|@=== Debug Properties ===
isDefaultStable: false
nodeSourcePosition: at org.graalvm.compiler.hotspot.replacements.WriteBarrierSnippets.serialWriteBarrier(WriteBarrierSnippets.java:138) [bci: 66]
at org.graalvm.compiler.hotspot.replacements.WriteBarrierSnippets.serialImpreciseWriteBarrier(WriteBarrierSnippets.java:144) [bci: 5]
at java.lang.StackTraceElement.<init>(StackTraceElement.java:71) [bci: 14]
rawvalue: 0
stableDimension: 0
stamp: i8 [0] ⇈0000000000000000
stampKind: i8
value: byte[0|0x0]
=== Inputs ===
=== Succesors ===
=== Usages ===
v67 
=== Predecessor ===
- >@ <|@
instruction <@Constant|@org.graalvm.compiler.nodes.ConstantNode>@  <|@  <|@
f <@#|@fixed with next>@ <|@
tid v67 <|@
d <@d|@=== Debug Properties ===
barrierType: NONE
location: GC-Card
nodeSourcePosition: at org.graalvm.compiler.hotspot.replacements.WriteBarrierSnippets.serialWriteBarrier(WriteBarrierSnippets.java:138) [bci: 66]
at org.graalvm.compiler.hotspot.replacements.WriteBarrierSnippets.serialImpreciseWriteBarrier(WriteBarrierSnippets.java:144) [bci: 5]
at java.lang.StackTraceElement.<init>(StackTraceElement.java:71) [bci: 14]
nullCheck: false
stamp: void
=== Inputs ===
stateBefore: - 
guard: - 
address: v75 
value: i68 
stateAfter: - 
lastLocationAccess: - 
=== Succesors ===
next: v33 
=== Usages ===
=== Predecessor ===
j61 >@ <|@
instruction <@Write|@org.graalvm.compiler.nodes.memory.WriteNode>@ stateBefore: - guard: - address: v75 value: i68 stateAfter: - lastLocationAccess: - #next: v33  <|@  <|@
f <@~|@floating>@ <|@
tid v72 <|@
d <@d|@=== Debug Properties ===
displacement: 16
scale: Times1
stamp: void*
=== Inputs ===
base: a1 
index: - 
=== Succesors ===
=== Usages ===
v33 
=== Predecessor ===
- >@ <|@
instruction <@AMD64Address|@org.graalvm.compiler.core.amd64.AMD64AddressNode>@ base: a1 index: -  <|@  <|@
f <@~|@floating>@ <|@
tid a30 <|@
d <@d|@=== Debug Properties ===
encoding: base: 0 shift: 3
nodeSourcePosition: at java.lang.StackTraceElement.<init>(StackTraceElement.java:72) [bci: 27]
op: Compress
stamp: n# Ljava/lang/String;
=== Inputs ===
value: a3 
=== Succesors ===
=== Usages ===
v33 
=== Predecessor ===
- >@ <|@
instruction <@HotSpotCompression|@org.graalvm.compiler.hotspot.nodes.HotSpotCompressionNode>@ value: a3  <|@  <|@
f <@#|@fixed with next>@ <|@
tid v33 <|@
d <@d|@=== Debug Properties ===
barrierType: IMPRECISE
location: StackTraceElement.methodName
nodeSourcePosition: at java.lang.StackTraceElement.<init>(StackTraceElement.java:72) [bci: 27]
nullCheck: false
stamp: void
=== Inputs ===
stateBefore: - 
guard: - 
address: v72 
value: a30 
stateAfter: - 
lastLocationAccess: - 
=== Succesors ===
next: v37 
=== Usages ===
=== Predecessor ===
v67 >@ <|@
instruction <@Write|@org.graalvm.compiler.nodes.memory.WriteNode>@ stateBefore: - guard: - address: v72 value: a30 stateAfter: - lastLocationAccess: - #next: v37  <|@  <|@
f <@~|@floating>@ <|@
tid v73 <|@
d <@d|@=== Debug Properties ===
displacement: 20
scale: Times1
stamp: void*
=== Inputs ===
base: a1 
index: - 
=== Succesors ===
=== Usages ===
v37 
=== Predecessor ===
- >@ <|@
instruction <@AMD64Address|@org.graalvm.compiler.core.amd64.AMD64AddressNode>@ base: a1 index: -  <|@  <|@
f <@~|@floating>@ <|@
tid a34 <|@
d <@d|@=== Debug Properties ===
encoding: base: 0 shift: 3
nodeSourcePosition: at java.lang.StackTraceElement.<init>(StackTraceElement.java:73) [bci: 32]
op: Compress
stamp: n# Ljava/lang/String;
=== Inputs ===
value: a4 
=== Succesors ===
=== Usages ===
v37 
=== Predecessor ===
- >@ <|@
instruction <@HotSpotCompression|@org.graalvm.compiler.hotspot.nodes.HotSpotCompressionNode>@ value: a4  <|@  <|@
f <@#|@fixed with next>@ <|@
tid v37 <|@
d <@d|@=== Debug Properties ===
barrierType: IMPRECISE
location: StackTraceElement.fileName
nodeSourcePosition: at java.lang.StackTraceElement.<init>(StackTraceElement.java:73) [bci: 32]
nullCheck: false
stamp: void
=== Inputs ===
stateBefore: - 
guard: - 
address: v73 
value: a34 
stateAfter: - 
lastLocationAccess: - 
=== Succesors ===
next: v40 
=== Usages ===
=== Predecessor ===
v33 >@ <|@
instruction <@Write|@org.graalvm.compiler.nodes.memory.WriteNode>@ stateBefore: - guard: - address: v73 value: a34 stateAfter: - lastLocationAccess: - #next: v40  <|@  <|@
f <@~|@floating>@ <|@
tid v74 <|@
d <@d|@=== Debug Properties ===
displacement: 24
scale: Times1
stamp: void*
=== Inputs ===
base: a1 
index: - 
=== Succesors ===
=== Usages ===
v40 
=== Predecessor ===
- >@ <|@
instruction <@AMD64Address|@org.graalvm.compiler.core.amd64.AMD64AddressNode>@ base: a1 index: -  <|@  <|@
f <@#|@fixed with next>@ <|@
tid v40 <|@
d <@d|@=== Debug Properties ===
barrierType: NONE
location: StackTraceElement.lineNumber
nodeSourcePosition: at java.lang.StackTraceElement.<init>(StackTraceElement.java:74) [bci: 38]
nullCheck: false
stamp: void
=== Inputs ===
stateBefore: - 
guard: - 
address: v74 
value: i5 
stateAfter: - 
lastLocationAccess: - 
=== Succesors ===
next: v23 
=== Usages ===
=== Predecessor ===
v37 >@ <|@
instruction <@Write|@org.graalvm.compiler.nodes.memory.WriteNode>@ stateBefore: - guard: - address: v74 value: i5 stateAfter: - lastLocationAccess: - #next: v23  <|@  <|@
f <@*|@fixed>@ <|@
tid v23 <|@
d <@d|@=== Debug Properties ===
nodeSourcePosition: at java.lang.StackTraceElement.<init>(StackTraceElement.java:75) [bci: 41]
stamp: void
=== Inputs ===
result: - 
memoryMap: - 
=== Succesors ===
=== Usages ===
=== Predecessor ===
v40 >@ <|@
instruction <@Return|@org.graalvm.compiler.nodes.ReturnNode>@ result: - memoryMap: -  <|@  <|@
    end_IR
  end_block
end_cfg
begin_cfg
  name "After LIR generation"
  begin_block
    name "B0"
    from_bci -1
    to_bci -1
    predecessors 
    successors "B1" "B2" 
    xhandlers
    flags 
    probability 4607182418800017408
    begin_IR
      HIR
f <@#|@fixed with next>@ <|@
tid v0 <|@
d <@d|@=== Debug Properties ===
stamp: void
=== Inputs ===
stateAfter: - 
=== Succesors ===
next: v76 
=== Usages ===
=== Predecessor ===
- >@ <|@
instruction <@StartNode|@org.graalvm.compiler.nodes.StartNode>@ stateAfter: - #next: v76  <|@  <|@
f <@~|@floating>@ <|@
tid a1 <|@
result v0|QWORD[.] <|@
d <@d|@=== Debug Properties ===
index: 0
stamp: a!# Ljava/lang/StackTraceElement;
uncheckedStamp: [null]
=== Inputs ===
=== Succesors ===
=== Usages ===
?6 v71 v73 v72 v74 j61 
=== Predecessor ===
- >@ <|@
instruction <@Parameter|@org.graalvm.compiler.nodes.ParameterNode>@  <|@  <|@
f <@~|@floating>@ <|@
tid a2 <|@
result v1|QWORD[.] <|@
d <@d|@=== Debug Properties ===
index: 1
stamp: a# Ljava/lang/String;
uncheckedStamp: [null]
=== Inputs ===
=== Succesors ===
=== Usages ===
?6 v76 a25 
=== Predecessor ===
- >@ <|@
instruction <@Parameter|@org.graalvm.compiler.nodes.ParameterNode>@  <|@  <|@
f <@~|@floating>@ <|@
tid a3 <|@
result v2|QWORD[.] <|@
d <@d|@=== Debug Properties ===
index: 2
stamp: a# Ljava/lang/String;
uncheckedStamp: [null]
=== Inputs ===
=== Succesors ===
=== Usages ===
?6 a30 v15 
=== Predecessor ===
- >@ <|@
instruction <@Parameter|@org.graalvm.compiler.nodes.ParameterNode>@  <|@  <|@
f <@~|@floating>@ <|@
tid a4 <|@
result v3|QWORD[.] <|@
d <@d|@=== Debug Properties ===
index: 3
stamp: a# Ljava/lang/String;
uncheckedStamp: [null]
=== Inputs ===
=== Succesors ===
=== Usages ===
?6 a34 
=== Predecessor ===
- >@ <|@
instruction <@Parameter|@org.graalvm.compiler.nodes.ParameterNode>@  <|@  <|@
f <@~|@floating>@ <|@
tid i5 <|@
result v4|DWORD <|@
d <@d|@=== Debug Properties ===
index: 4
stamp: i32
uncheckedStamp: [null]
=== Inputs ===
=== Succesors ===
=== Usages ===
?6 v40 
=== Predecessor ===
- >@ <|@
instruction <@Parameter|@org.graalvm.compiler.nodes.ParameterNode>@  <|@  <|@
tid ?6 <|@
d <@d|@=== Debug Properties ===
bci: 0
code: ResolvedJavaMethodBytecode<StackTraceElement.<init>(String, String, String, int)>
duringCall: false
localsSize: 5
locksSize: 0
rethrowException: false
sourceFile: StackTraceElement.java
sourceLine: 70
stackSize: 0
=== Inputs ===
outerFrameState: - 
values: a1 a2 a3 a4 i5 
=== Succesors ===
=== Usages ===
v55 v76 
=== Predecessor ===
- >@ <|@
instruction <@FrameState|@org.graalvm.compiler.nodes.FrameState>@ outerFrameState: - values: a1 a2 a3 a4 i5  <|@  <|@
f <@#|@fixed with next>@ <|@
tid v76 <|@
d <@d|@=== Debug Properties ===
stamp: void
=== Inputs ===
stateBefore: ?6 
object: a2 
=== Succesors ===
next: v48 
=== Usages ===
=== Predecessor ===
v0 >@ <|@
instruction <@NullCheck|@org.graalvm.compiler.nodes.extended.NullCheckNode>@ stateBefore: ?6 object: a2 #next: v48  <|@  <|@
f <@~|@floating>@ <|@
tid v15 <|@
d <@d|@=== Debug Properties ===
nodeSourcePosition: at java.util.Objects.requireNonNull(Objects.java:227) [bci: 1]
at java.lang.StackTraceElement.<init>(StackTraceElement.java:72) [bci: 21]
stamp: void
=== Inputs ===
value: a3 
=== Succesors ===
=== Usages ===
v48 
=== Predecessor ===
- >@ <|@
instruction <@IsNull|@org.graalvm.compiler.nodes.calc.IsNullNode>@ value: a3  <|@  <|@
f <@*|@fixed>@ <|@
tid v48 <|@
d <@d|@=== Debug Properties ===
nodeSourcePosition: at java.util.Objects.requireNonNull(Objects.java:227) [bci: 1]
at java.lang.StackTraceElement.<init>(StackTraceElement.java:72) [bci: 21]
stamp: void
trueSuccessorProbability: 0.0
=== Inputs ===
condition: v15 
=== Succesors ===
trueSuccessor: v47 
falseSuccessor: v45 
=== Usages ===
=== Predecessor ===
v76 >@ <|@
instruction <@If|@org.graalvm.compiler.nodes.IfNode>@ condition: v15 #trueSuccessor: v47 #falseSuccessor: v45  <|@  <|@
    end_IR
    begin_IR
      LIR
      nr   -1  <|@ instruction [rsi|QWORD[.], rdx|QWORD[.], rcx|QWORD[.], r8|QWORD[.], r9|DWORD, rbp|QWORD] = LABEL numbPhis: 0 align: false label: ? <|@ <|@
      nr   -1  <|@ instruction stack:16|QWORD = MOVE rbp|QWORD moveKind: QWORD <|@ <|@
      nr   -1  <|@ instruction [] = HOTSPOTLOCKSTACK frameMapBuilder: org.graalvm.compiler.lir.amd64.AMD64FrameMapBuilder@5101a515 slotKind: QWORD <|@ <|@
      nr   -1  <|@ instruction v0|QWORD[.] = MOVE rsi|QWORD[.] moveKind: QWORD <|@ <|@
      nr   -1  <|@ instruction v1|QWORD[.] = MOVE rdx|QWORD[.] moveKind: QWORD <|@ <|@
      nr   -1  <|@ instruction v2|QWORD[.] = MOVE rcx|QWORD[.] moveKind: QWORD <|@ <|@
      nr   -1  <|@ instruction v3|QWORD[.] = MOVE r8|QWORD[.] moveKind: QWORD <|@ <|@
      nr   -1  <|@ instruction v4|DWORD = MOVE r9|DWORD moveKind: DWORD <|@ <|@
      nr   -1  <|@ st <@st|@java.lang.StackTraceElement.<init>(StackTraceElement.java:70) [bci: 0]
locals: v0|QWORD[.] v1|QWORD[.] v2|QWORD[.] v3|QWORD[.] v4|DWORD 
>@ <|@ instruction NULLCHECK [v1|QWORD[.]] state [bci:0] <|@ <|@
      nr   -1  <|@ instruction TEST (x: v2|QWORD[.], y: v2|QWORD[.]) size: QWORD <|@ <|@
      nr   -1  <|@ instruction BRANCH trueDestinationProbability: 0.0 condition: = trueDestination: B0 -> B1 falseDestination: B0 -> B2 <|@ <|@
    end_IR
  end_block
  begin_block
    name "B1"
    from_bci -1
    to_bci -1
    predecessors "B0" 
    successors 
    xhandlers
    flags 
    probability 2355382605114769408
    begin_IR
      HIR
f <@#|@fixed with next>@ <|@
tid v47 <|@
d <@d|@=== Debug Properties ===
nodeSourcePosition: at java.util.Objects.requireNonNull(Objects.java:227) [bci: 1]
at java.lang.StackTraceElement.<init>(StackTraceElement.java:72) [bci: 21]
stamp: void
=== Inputs ===
=== Succesors ===
next: v55 
=== Usages ===
=== Predecessor ===
v48 >@ <|@
instruction <@Begin|@org.graalvm.compiler.nodes.BeginNode>@ #next: v55  <|@  <|@
f <@~|@floating>@ <|@
tid a52 <|@
result Object[null] <|@
d <@d|@=== Debug Properties ===
isDefaultStable: false
rawvalue: null
stableDimension: 0
stamp: a - NULL
stampKind: a -
value: Object[null]
=== Inputs ===
=== Succesors ===
=== Usages ===
v55 
=== Predecessor ===
- >@ <|@
instruction <@Constant|@org.graalvm.compiler.nodes.ConstantNode>@  <|@  <|@
f <@~|@floating>@ <|@
tid i57 <|@
result int[-7443|0xffffffffffffe2ed] <|@
d <@d|@=== Debug Properties ===
isDefaultStable: false
rawvalue: -7443
stableDimension: 0
stamp: i32 [-7443] ⇊00000000ffffe2ed ⇈00000000ffffe2ed
stampKind: i32
value: int[-7443|0xffffffffffffe2ed]
=== Inputs ===
=== Succesors ===
=== Usages ===
v55 
=== Predecessor ===
- >@ <|@
instruction <@Constant|@org.graalvm.compiler.nodes.ConstantNode>@  <|@  <|@
f <@*|@fixed>@ <|@
tid v55 <|@
d <@d|@=== Debug Properties ===
stamp: void
=== Inputs ===
stateBefore: ?6 
actionAndReason: i57 
speculation: a52 
=== Succesors ===
=== Usages ===
=== Predecessor ===
v47 >@ <|@
instruction <@DynamicDeoptimize|@org.graalvm.compiler.nodes.DynamicDeoptimizeNode>@ stateBefore: ?6 actionAndReason: i57 speculation: a52  <|@  <|@
    end_IR
    begin_IR
      LIR
      nr   -1  <|@ instruction [] = LABEL numbPhis: 0 align: false label: ? <|@ <|@
      nr   -1  <|@ instruction MOV [r15|QWORD + 668] y: -7443 size: DWORD <|@ <|@
      nr   -1  <|@ instruction MOV (x: [r15|QWORD + 680], y: r12|ILLEGAL) size: QWORD <|@ <|@
      nr   -1  <|@ st <@st|@java.lang.StackTraceElement.<init>(StackTraceElement.java:70) [bci: 0]
locals: v0|QWORD[.] v1|QWORD[.] v2|QWORD[.] v3|QWORD[.] v4|DWORD 
>@ <|@ instruction DEOPT info [bci:0] <|@ <|@
    end_IR
  end_block
  begin_block
    name "B2"
    from_bci -1
    to_bci -1
    predecessors "B0" 
    successors 
    xhandlers
    flags 
    probability 4607182418800017408
    begin_IR
      HIR
f <@#|@fixed with next>@ <|@
tid v45 <|@
d <@d|@=== Debug Properties ===
nodeSourcePosition: at java.util.Objects.requireNonNull(Objects.java:227) [bci: 1]
at java.lang.StackTraceElement.<init>(StackTraceElement.java:72) [bci: 21]
stamp: void
=== Inputs ===
=== Succesors ===
next: v28 
=== Usages ===
=== Predecessor ===
v48 >@ <|@
instruction <@Begin|@org.graalvm.compiler.nodes.BeginNode>@ #next: v28  <|@  <|@
f <@~|@floating>@ <|@
tid v71 <|@
result [v0|QWORD[.] + 12] <|@
d <@d|@=== Debug Properties ===
displacement: 12
scale: Times1
stamp: void*
=== Inputs ===
base: a1 
index: - 
=== Succesors ===
=== Usages ===
v28 
=== Predecessor ===
- >@ <|@
instruction <@AMD64Address|@org.graalvm.compiler.core.amd64.AMD64AddressNode>@ base: a1 index: -  <|@  <|@
f <@~|@floating>@ <|@
tid a25 <|@
result v5|DWORD[.] <|@
d <@d|@=== Debug Properties ===
encoding: base: 0 shift: 3
nodeSourcePosition: at java.lang.StackTraceElement.<init>(StackTraceElement.java:71) [bci: 14]
op: Compress
stamp: n# Ljava/lang/String;
=== Inputs ===
value: a2 
=== Succesors ===
=== Usages ===
v28 
=== Predecessor ===
- >@ <|@
instruction <@HotSpotCompression|@org.graalvm.compiler.hotspot.nodes.HotSpotCompressionNode>@ value: a2  <|@  <|@
f <@#|@fixed with next>@ <|@
tid v28 <|@
d <@d|@=== Debug Properties ===
barrierType: IMPRECISE
location: StackTraceElement.declaringClass
nodeSourcePosition: at java.lang.StackTraceElement.<init>(StackTraceElement.java:71) [bci: 14]
nullCheck: false
stamp: void
=== Inputs ===
stateBefore: - 
guard: - 
address: v71 
value: a25 
stateAfter: - 
lastLocationAccess: - 
=== Succesors ===
next: j61 
=== Usages ===
=== Predecessor ===
v45 >@ <|@
instruction <@Write|@org.graalvm.compiler.nodes.memory.WriteNode>@ stateBefore: - guard: - address: v71 value: a25 stateAfter: - lastLocationAccess: - #next: j61  <|@  <|@
f <@#|@fixed with next>@ <|@
tid j61 <|@
result v0|QWORD[.] <|@
d <@d|@=== Debug Properties ===
nodeSourcePosition: at org.graalvm.compiler.hotspot.replacements.WriteBarrierSnippets.serialImpreciseWriteBarrier(WriteBarrierSnippets.java:144) [bci: 1]
at java.lang.StackTraceElement.<init>(StackTraceElement.java:71) [bci: 14]
stamp: i64
trackedPointer: true
=== Inputs ===
input: a1 
=== Succesors ===
next: v67 
=== Usages ===
j63 
=== Predecessor ===
v28 >@ <|@
instruction <@WordCast|@org.graalvm.compiler.word.WordCastNode>@ input: a1 #next: v67  <|@  <|@
f <@~|@floating>@ <|@
tid i62 <|@
result int[9|0x9] <|@
d <@d|@=== Debug Properties ===
isDefaultStable: false
nodeSourcePosition: at org.graalvm.compiler.hotspot.replacements.HotSpotReplacementsUtil.cardTableShift(GraalHotSpotVMConfig) [bci: -1]
at org.graalvm.compiler.hotspot.replacements.WriteBarrierSnippets.serialWriteBarrier(WriteBarrierSnippets.java:134) [bci: 15]
at org.graalvm.compiler.hotspot.replacements.WriteBarrierSnippets.serialImpreciseWriteBarrier(WriteBarrierSnippets.java:144) [bci: 5]
at java.lang.StackTraceElement.<init>(StackTraceElement.java:71) [bci: 14]
rawvalue: 9
stableDimension: 0
stamp: i32 [9] ⇊0000000000000009 ⇈0000000000000009
stampKind: i32
value: int[9|0x9]
=== Inputs ===
=== Succesors ===
=== Usages ===
j63 
=== Predecessor ===
- >@ <|@
instruction <@Constant|@org.graalvm.compiler.nodes.ConstantNode>@  <|@  <|@
f <@~|@floating>@ <|@
tid j63 <|@
result v6|QWORD[*] <|@
d <@d|@=== Debug Properties ===
getOp: org.graalvm.compiler.nodes.calc.UnsignedRightShiftNode$$Lambda$68/774788493@3e7195e9
nodeSourcePosition: at org.graalvm.compiler.hotspot.replacements.WriteBarrierSnippets.serialWriteBarrier(WriteBarrierSnippets.java:134) [bci: 18]
at org.graalvm.compiler.hotspot.replacements.WriteBarrierSnippets.serialImpreciseWriteBarrier(WriteBarrierSnippets.java:144) [bci: 5]
at java.lang.StackTraceElement.<init>(StackTraceElement.java:71) [bci: 14]
stamp: i64 [0 - 36028797018963967] ⇈007fffffffffffff
=== Inputs ===
x: j61 
y: i62 
=== Succesors ===
=== Usages ===
v75 
=== Predecessor ===
- >@ <|@
instruction <@>>>|@org.graalvm.compiler.nodes.calc.UnsignedRightShiftNode>@ x: j61 y: i62  <|@  <|@
f <@~|@floating>@ <|@
tid j66 <|@
result v7|QWORD <|@
d <@d|@=== Debug Properties ===
isDefaultStable: false
nodeSourcePosition: at org.graalvm.compiler.hotspot.nodes.GraalHotSpotVMConfigNode.loadLongConfigValue(int) [bci: -1]
at org.graalvm.compiler.hotspot.nodes.GraalHotSpotVMConfigNode.cardTableAddress(GraalHotSpotVMConfigNode.java:114) [bci: 6]
at org.graalvm.compiler.hotspot.replacements.WriteBarrierSnippets.serialWriteBarrier(WriteBarrierSnippets.java:133) [bci: 7]
at org.graalvm.compiler.hotspot.replacements.WriteBarrierSnippets.serialImpreciseWriteBarrier(WriteBarrierSnippets.java:144) [bci: 5]
at java.lang.StackTraceElement.<init>(StackTraceElement.java:71) [bci: 14]
rawvalue: 4682670080
stableDimension: 0
stamp: i64 [4682670080] ⇊00000001171be000 ⇈00000001171be000
stampKind: i64
value: long[4682670080|0x1171be000]
=== Inputs ===
=== Succesors ===
=== Usages ===
v75 
=== Predecessor ===
- >@ <|@
instruction <@Constant|@org.graalvm.compiler.nodes.ConstantNode>@  <|@  <|@
f <@~|@floating>@ <|@
tid v75 <|@
result [v6|QWORD[*] + v7|QWORD * 1] <|@
d <@d|@=== Debug Properties ===
displacement: 0
scale: Times1
stamp: void*
=== Inputs ===
base: j63 
index: j66 
=== Succesors ===
=== Usages ===
v67 
=== Predecessor ===
- >@ <|@
instruction <@AMD64Address|@org.graalvm.compiler.core.amd64.AMD64AddressNode>@ base: j63 index: j66  <|@  <|@
f <@~|@floating>@ <|@
tid i68 <|@
result byte[0|0x0] <|@
d <@d|@=== Debug Properties ===
isDefaultStable: false
nodeSourcePosition: at org.graalvm.compiler.hotspot.replacements.WriteBarrierSnippets.serialWriteBarrier(WriteBarrierSnippets.java:138) [bci: 66]
at org.graalvm.compiler.hotspot.replacements.WriteBarrierSnippets.serialImpreciseWriteBarrier(WriteBarrierSnippets.java:144) [bci: 5]
at java.lang.StackTraceElement.<init>(StackTraceElement.java:71) [bci: 14]
rawvalue: 0
stableDimension: 0
stamp: i8 [0] ⇈0000000000000000
stampKind: i8
value: byte[0|0x0]
=== Inputs ===
=== Succesors ===
=== Usages ===
v67 
=== Predecessor ===
- >@ <|@
instruction <@Constant|@org.graalvm.compiler.nodes.ConstantNode>@  <|@  <|@
f <@#|@fixed with next>@ <|@
tid v67 <|@
d <@d|@=== Debug Properties ===
barrierType: NONE
location: GC-Card
nodeSourcePosition: at org.graalvm.compiler.hotspot.replacements.WriteBarrierSnippets.serialWriteBarrier(WriteBarrierSnippets.java:138) [bci: 66]
at org.graalvm.compiler.hotspot.replacements.WriteBarrierSnippets.serialImpreciseWriteBarrier(WriteBarrierSnippets.java:144) [bci: 5]
at java.lang.StackTraceElement.<init>(StackTraceElement.java:71) [bci: 14]
nullCheck: false
stamp: void
=== Inputs ===
stateBefore: - 
guard: - 
address: v75 
value: i68 
stateAfter: - 
lastLocationAccess: - 
=== Succesors ===
next: v33 
=== Usages ===
=== Predecessor ===
j61 >@ <|@
instruction <@Write|@org.graalvm.compiler.nodes.memory.WriteNode>@ stateBefore: - guard: - address: v75 value: i68 stateAfter: - lastLocationAccess: - #next: v33  <|@  <|@
f <@~|@floating>@ <|@
tid v72 <|@
result [v0|QWORD[.] + 16] <|@
d <@d|@=== Debug Properties ===
displacement: 16
scale: Times1
stamp: void*
=== Inputs ===
base: a1 
index: - 
=== Succesors ===
=== Usages ===
v33 
=== Predecessor ===
- >@ <|@
instruction <@AMD64Address|@org.graalvm.compiler.core.amd64.AMD64AddressNode>@ base: a1 index: -  <|@  <|@
f <@~|@floating>@ <|@
tid a30 <|@
result v8|DWORD[.] <|@
d <@d|@=== Debug Properties ===
encoding: base: 0 shift: 3
nodeSourcePosition: at java.lang.StackTraceElement.<init>(StackTraceElement.java:72) [bci: 27]
op: Compress
stamp: n# Ljava/lang/String;
=== Inputs ===
value: a3 
=== Succesors ===
=== Usages ===
v33 
=== Predecessor ===
- >@ <|@
instruction <@HotSpotCompression|@org.graalvm.compiler.hotspot.nodes.HotSpotCompressionNode>@ value: a3  <|@  <|@
f <@#|@fixed with next>@ <|@
tid v33 <|@
d <@d|@=== Debug Properties ===
barrierType: IMPRECISE
location: StackTraceElement.methodName
nodeSourcePosition: at java.lang.StackTraceElement.<init>(StackTraceElement.java:72) [bci: 27]
nullCheck: false
stamp: void
=== Inputs ===
stateBefore: - 
guard: - 
address: v72 
value: a30 
stateAfter: - 
lastLocationAccess: - 
=== Succesors ===
next: v37 
=== Usages ===
=== Predecessor ===
v67 >@ <|@
instruction <@Write|@org.graalvm.compiler.nodes.memory.WriteNode>@ stateBefore: - guard: - address: v72 value: a30 stateAfter: - lastLocationAccess: - #next: v37  <|@  <|@
f <@~|@floating>@ <|@
tid v73 <|@
result [v0|QWORD[.] + 20] <|@
d <@d|@=== Debug Properties ===
displacement: 20
scale: Times1
stamp: void*
=== Inputs ===
base: a1 
index: - 
=== Succesors ===
=== Usages ===
v37 
=== Predecessor ===
- >@ <|@
instruction <@AMD64Address|@org.graalvm.compiler.core.amd64.AMD64AddressNode>@ base: a1 index: -  <|@  <|@
f <@~|@floating>@ <|@
tid a34 <|@
result v9|DWORD[.] <|@
d <@d|@=== Debug Properties ===
encoding: base: 0 shift: 3
nodeSourcePosition: at java.lang.StackTraceElement.<init>(StackTraceElement.java:73) [bci: 32]
op: Compress
stamp: n# Ljava/lang/String;
=== Inputs ===
value: a4 
=== Succesors ===
=== Usages ===
v37 
=== Predecessor ===
- >@ <|@
instruction <@HotSpotCompression|@org.graalvm.compiler.hotspot.nodes.HotSpotCompressionNode>@ value: a4  <|@  <|@
f <@#|@fixed with next>@ <|@
tid v37 <|@
d <@d|@=== Debug Properties ===
barrierType: IMPRECISE
location: StackTraceElement.fileName
nodeSourcePosition: at java.lang.StackTraceElement.<init>(StackTraceElement.java:73) [bci: 32]
nullCheck: false
stamp: void
=== Inputs ===
stateBefore: - 
guard: - 
address: v73 
value: a34 
stateAfter: - 
lastLocationAccess: - 
=== Succesors ===
next: v40 
=== Usages ===
=== Predecessor ===
v33 >@ <|@
instruction <@Write|@org.graalvm.compiler.nodes.memory.WriteNode>@ stateBefore: - guard: - address: v73 value: a34 stateAfter: - lastLocationAccess: - #next: v40  <|@  <|@
f <@~|@floating>@ <|@
tid v74 <|@
result [v0|QWORD[.] + 24] <|@
d <@d|@=== Debug Properties ===
displacement: 24
scale: Times1
stamp: void*
=== Inputs ===
base: a1 
index: - 
=== Succesors ===
=== Usages ===
v40 
=== Predecessor ===
- >@ <|@
instruction <@AMD64Address|@org.graalvm.compiler.core.amd64.AMD64AddressNode>@ base: a1 index: -  <|@  <|@
f <@#|@fixed with next>@ <|@
tid v40 <|@
d <@d|@=== Debug Properties ===
barrierType: NONE
location: StackTraceElement.lineNumber
nodeSourcePosition: at java.lang.StackTraceElement.<init>(StackTraceElement.java:74) [bci: 38]
nullCheck: false
stamp: void
=== Inputs ===
stateBefore: - 
guard: - 
address: v74 
value: i5 
stateAfter: - 
lastLocationAccess: - 
=== Succesors ===
next: v23 
=== Usages ===
=== Predecessor ===
v37 >@ <|@
instruction <@Write|@org.graalvm.compiler.nodes.memory.WriteNode>@ stateBefore: - guard: - address: v74 value: i5 stateAfter: - lastLocationAccess: - #next: v23  <|@  <|@
f <@*|@fixed>@ <|@
tid v23 <|@
d <@d|@=== Debug Properties ===
nodeSourcePosition: at java.lang.StackTraceElement.<init>(StackTraceElement.java:75) [bci: 41]
stamp: void
=== Inputs ===
result: - 
memoryMap: - 
=== Succesors ===
=== Usages ===
=== Predecessor ===
v40 >@ <|@
instruction <@Return|@org.graalvm.compiler.nodes.ReturnNode>@ result: - memoryMap: -  <|@  <|@
    end_IR
    begin_IR
      LIR
      nr   -1  <|@ instruction [] = LABEL numbPhis: 0 align: false label: ? <|@ <|@
      nr   -1  <|@ instruction v5|DWORD[.] = COMPRESSPOINTER (input: v1|QWORD[.], ~baseRegister: r12|ILLEGAL) nonNull: false lirKindTool: com.oracle.graal.enterprise.z.a@7a7f5448 encoding: base: 0 shift: 3 <|@ <|@
      nr   -1  <|@ instruction MOV (x: [v0|QWORD[.] + 12], y: v5|DWORD[.]) size: DWORD <|@ <|@
      nr   -1  <|@ instruction v6|QWORD[*] = SHR v0|QWORD[.] y: 9 size: QWORD <|@ <|@
      nr   -1  <|@ instruction v7|QWORD = MOVE input: long[4682670080|0x1171be000] <|@ <|@
      nr   -1  <|@ instruction MOVB (x: [v6|QWORD[*] + v7|QWORD * 1], y: r12|ILLEGAL) size: BYTE <|@ <|@
      nr   -1  <|@ instruction v8|DWORD[.] = COMPRESSPOINTER (input: v2|QWORD[.], ~baseRegister: r12|ILLEGAL) nonNull: false lirKindTool: com.oracle.graal.enterprise.z.a@7a7f5448 encoding: base: 0 shift: 3 <|@ <|@
      nr   -1  <|@ instruction MOV (x: [v0|QWORD[.] + 16], y: v8|DWORD[.]) size: DWORD <|@ <|@
      nr   -1  <|@ instruction v9|DWORD[.] = COMPRESSPOINTER (input: v3|QWORD[.], ~baseRegister: r12|ILLEGAL) nonNull: false lirKindTool: com.oracle.graal.enterprise.z.a@7a7f5448 encoding: base: 0 shift: 3 <|@ <|@
      nr   -1  <|@ instruction MOV (x: [v0|QWORD[.] + 20], y: v9|DWORD[.]) size: DWORD <|@ <|@
      nr   -1  <|@ instruction MOV (x: [v0|QWORD[.] + 24], y: v4|DWORD) size: DWORD <|@ <|@
      nr   -1  <|@ instruction RETURN (savedRbp: stack:16|QWORD, value: -) isStub: false thread: r15 scratchForSafepointOnReturn: rcx config: org.graalvm.compiler.hotspot.GraalHotSpotVMConfig@7222fe45 <|@ <|@
    end_IR
  end_block
end_cfg
begin_cfg
  name "After PreAllocationOptimizationStage"
  begin_block
    name "B0"
    from_bci -1
    to_bci -1
    predecessors 
    successors "B1" "B2" 
    xhandlers
    flags 
    probability 4607182418800017408
    begin_IR
      LIR
      nr   -1  <|@ instruction [rsi|QWORD[.], rdx|QWORD[.], rcx|QWORD[.], r8|QWORD[.], r9|DWORD, rbp|QWORD] = LABEL numbPhis: 0 align: false label: ? <|@ <|@
      nr   -1  <|@ instruction stack:16|QWORD = MOVE rbp|QWORD moveKind: QWORD <|@ <|@
      nr   -1  <|@ instruction [] = HOTSPOTLOCKSTACK frameMapBuilder: org.graalvm.compiler.lir.amd64.AMD64FrameMapBuilder@5101a515 slotKind: QWORD <|@ <|@
      nr   -1  <|@ instruction v0|QWORD[.] = MOVE rsi|QWORD[.] moveKind: QWORD <|@ <|@
      nr   -1  <|@ instruction v1|QWORD[.] = MOVE rdx|QWORD[.] moveKind: QWORD <|@ <|@
      nr   -1  <|@ instruction v2|QWORD[.] = MOVE rcx|QWORD[.] moveKind: QWORD <|@ <|@
      nr   -1  <|@ instruction v3|QWORD[.] = MOVE r8|QWORD[.] moveKind: QWORD <|@ <|@
      nr   -1  <|@ instruction v4|DWORD = MOVE r9|DWORD moveKind: DWORD <|@ <|@
      nr   -1  <|@ st <@st|@java.lang.StackTraceElement.<init>(StackTraceElement.java:70) [bci: 0]
locals: v0|QWORD[.] v1|QWORD[.] v2|QWORD[.] v3|QWORD[.] v4|DWORD 
>@ <|@ instruction NULLCHECK [v1|QWORD[.]] state [bci:0] <|@ <|@
      nr   -1  <|@ instruction TEST (x: v2|QWORD[.], y: v2|QWORD[.]) size: QWORD <|@ <|@
      nr   -1  <|@ instruction BRANCH trueDestinationProbability: 0.0 condition: = trueDestination: B0 -> B1 falseDestination: B0 -> B2 <|@ <|@
    end_IR
  end_block
  begin_block
    name "B2"
    from_bci -1
    to_bci -1
    predecessors "B0" 
    successors 
    xhandlers
    flags 
    probability 4607182418800017408
    begin_IR
      LIR
      nr   -1  <|@ instruction [] = LABEL numbPhis: 0 align: false label: ? <|@ <|@
      nr   -1  <|@ instruction v5|DWORD[.] = COMPRESSPOINTER (input: v1|QWORD[.], ~baseRegister: r12|ILLEGAL) nonNull: false lirKindTool: com.oracle.graal.enterprise.z.a@7a7f5448 encoding: base: 0 shift: 3 <|@ <|@
      nr   -1  <|@ instruction MOV (x: [v0|QWORD[.] + 12], y: v5|DWORD[.]) size: DWORD <|@ <|@
      nr   -1  <|@ instruction v6|QWORD[*] = SHR v0|QWORD[.] y: 9 size: QWORD <|@ <|@
      nr   -1  <|@ instruction v7|QWORD = MOVE input: long[4682670080|0x1171be000] <|@ <|@
      nr   -1  <|@ instruction MOVB (x: [v6|QWORD[*] + v7|QWORD * 1], y: r12|ILLEGAL) size: BYTE <|@ <|@
      nr   -1  <|@ instruction v8|DWORD[.] = COMPRESSPOINTER (input: v2|QWORD[.], ~baseRegister: r12|ILLEGAL) nonNull: false lirKindTool: com.oracle.graal.enterprise.z.a@7a7f5448 encoding: base: 0 shift: 3 <|@ <|@
      nr   -1  <|@ instruction MOV (x: [v0|QWORD[.] + 16], y: v8|DWORD[.]) size: DWORD <|@ <|@
      nr   -1  <|@ instruction v9|DWORD[.] = COMPRESSPOINTER (input: v3|QWORD[.], ~baseRegister: r12|ILLEGAL) nonNull: false lirKindTool: com.oracle.graal.enterprise.z.a@7a7f5448 encoding: base: 0 shift: 3 <|@ <|@
      nr   -1  <|@ instruction MOV (x: [v0|QWORD[.] + 20], y: v9|DWORD[.]) size: DWORD <|@ <|@
      nr   -1  <|@ instruction MOV (x: [v0|QWORD[.] + 24], y: v4|DWORD) size: DWORD <|@ <|@
      nr   -1  <|@ instruction RETURN (savedRbp: stack:16|QWORD, value: -) isStub: false thread: r15 scratchForSafepointOnReturn: rcx config: org.graalvm.compiler.hotspot.GraalHotSpotVMConfig@7222fe45 <|@ <|@
    end_IR
  end_block
  begin_block
    name "B1"
    from_bci -1
    to_bci -1
    predecessors "B0" 
    successors 
    xhandlers
    flags 
    probability 2355382605114769408
    begin_IR
      LIR
      nr   -1  <|@ instruction [] = LABEL numbPhis: 0 align: false label: ? <|@ <|@
      nr   -1  <|@ instruction MOV [r15|QWORD + 668] y: -7443 size: DWORD <|@ <|@
      nr   -1  <|@ instruction MOV (x: [r15|QWORD + 680], y: r12|ILLEGAL) size: QWORD <|@ <|@
      nr   -1  <|@ st <@st|@java.lang.StackTraceElement.<init>(StackTraceElement.java:70) [bci: 0]
locals: v0|QWORD[.] v1|QWORD[.] v2|QWORD[.] v3|QWORD[.] v4|DWORD 
>@ <|@ instruction DEOPT info [bci:0] <|@ <|@
    end_IR
  end_block
end_cfg
begin_bytecodes
     0: aload_0       
     1: invokespecial #0          // java.lang.Object.<init>:()void
     4: aload_0       
     5: aload_1       
     6: ldc           #2          // "Declaring class is null"
     8: invokestatic  #1          // java.util.Objects.requireNonNull:(java.lang.Object, java.lang.String)java.lang.Object
    11: checkcast     #4          // java.lang.String
    14: putfield      #2          // declaringClass:java.lang.String
    17: aload_0       
    18: aload_2       
    19: ldc           #6          // "Method name is null"
    21: invokestatic  #1          // java.util.Objects.requireNonNull:(java.lang.Object, java.lang.String)java.lang.Object
    24: checkcast     #4          // java.lang.String
    27: putfield      #3          // methodName:java.lang.String
    30: aload_0       
    31: aload_3       
    32: putfield      #4          // fileName:java.lang.String
    35: aload_0       
    36: iload         4
    38: putfield      #5          // lineNumber:int
    41: return        
   <|@
end_bytecodes
begin_cfg
  name "After AllocationStage"
  begin_block
    name "B0"
    from_bci -1
    to_bci -1
    predecessors 
    successors "B1" "B2" 
    xhandlers
    flags 
    probability 4607182418800017408
    begin_IR
      LIR
      nr    0  <|@ instruction [rsi|QWORD[.], rdx|QWORD[.], rcx|QWORD[.], r8|QWORD[.], r9|DWORD, rbp|QWORD] = LABEL numbPhis: 0 align: false label: ? <|@ <|@
      nr    2  <|@ instruction stack:16|QWORD = MOVE rbp|QWORD moveKind: QWORD <|@ <|@
      nr    4  <|@ instruction [] = HOTSPOTLOCKSTACK frameMapBuilder: org.graalvm.compiler.lir.amd64.AMD64FrameMapBuilder@5101a515 slotKind: QWORD <|@ <|@
      nr   16  <|@ st <@st|@reference-map: [rcx:0, rdx:0, rsi:0, r8:0]
live-base-pointers: []
java.lang.StackTraceElement.<init>(StackTraceElement.java:70) [bci: 0]
locals: rsi|QWORD[.] rdx|QWORD[.] rcx|QWORD[.] r8|QWORD[.] r9|DWORD 
>@ <|@ instruction NULLCHECK [rdx|QWORD[.]] state [bci:0] <|@ <|@
      nr   18  <|@ instruction TEST (x: rcx|QWORD[.], y: rcx|QWORD[.]) size: QWORD <|@ <|@
      nr   20  <|@ instruction BRANCH trueDestinationProbability: 0.0 condition: = trueDestination: B0 -> B1 falseDestination: B0 -> B2 <|@ <|@
    end_IR
  end_block
  begin_block
    name "B2"
    from_bci -1
    to_bci -1
    predecessors "B0" 
    successors 
    xhandlers
    flags 
    probability 4607182418800017408
    begin_IR
      LIR
      nr   22  <|@ instruction [] = LABEL numbPhis: 0 align: false label: ? <|@ <|@
      nr   24  <|@ instruction rdx|DWORD[.] = COMPRESSPOINTER (input: rdx|QWORD[.], ~baseRegister: r12|ILLEGAL) nonNull: false lirKindTool: com.oracle.graal.enterprise.z.a@7a7f5448 encoding: base: 0 shift: 3 <|@ <|@
      nr   26  <|@ instruction MOV (x: [rsi|QWORD[.] + 12], y: rdx|DWORD[.]) size: DWORD <|@ <|@
      nr   28  <|@ instruction r10|QWORD[*] = SHR rsi|QWORD[.] y: 9 size: QWORD <|@ <|@
      nr   30  <|@ instruction r11|QWORD = MOVE input: long[4682670080|0x1171be000] <|@ <|@
      nr   32  <|@ instruction MOVB (x: [r10|QWORD[*] + r11|QWORD * 1], y: r12|ILLEGAL) size: BYTE <|@ <|@
      nr   34  <|@ instruction rcx|DWORD[.] = COMPRESSPOINTER (input: rcx|QWORD[.], ~baseRegister: r12|ILLEGAL) nonNull: false lirKindTool: com.oracle.graal.enterprise.z.a@7a7f5448 encoding: base: 0 shift: 3 <|@ <|@
      nr   36  <|@ instruction MOV (x: [rsi|QWORD[.] + 16], y: rcx|DWORD[.]) size: DWORD <|@ <|@
      nr   38  <|@ instruction r8|DWORD[.] = COMPRESSPOINTER (input: r8|QWORD[.], ~baseRegister: r12|ILLEGAL) nonNull: false lirKindTool: com.oracle.graal.enterprise.z.a@7a7f5448 encoding: base: 0 shift: 3 <|@ <|@
      nr   40  <|@ instruction MOV (x: [rsi|QWORD[.] + 20], y: r8|DWORD[.]) size: DWORD <|@ <|@
      nr   42  <|@ instruction MOV (x: [rsi|QWORD[.] + 24], y: r9|DWORD) size: DWORD <|@ <|@
      nr   44  <|@ instruction RETURN (savedRbp: stack:16|QWORD, value: -) isStub: false thread: r15 scratchForSafepointOnReturn: rcx config: org.graalvm.compiler.hotspot.GraalHotSpotVMConfig@7222fe45 <|@ <|@
    end_IR
  end_block
  begin_block
    name "B1"
    from_bci -1
    to_bci -1
    predecessors "B0" 
    successors 
    xhandlers
    flags 
    probability 2355382605114769408
    begin_IR
      LIR
      nr   46  <|@ instruction [] = LABEL numbPhis: 0 align: false label: ? <|@ <|@
      nr   48  <|@ instruction MOV [r15|QWORD + 668] y: -7443 size: DWORD <|@ <|@
      nr   50  <|@ instruction MOV (x: [r15|QWORD + 680], y: r12|ILLEGAL) size: QWORD <|@ <|@
      nr   52  <|@ st <@st|@reference-map: [rcx:0, rdx:0, rsi:0, r8:0]
live-base-pointers: []
java.lang.StackTraceElement.<init>(StackTraceElement.java:70) [bci: 0]
locals: rsi|QWORD[.] rdx|QWORD[.] rcx|QWORD[.] r8|QWORD[.] r9|DWORD 
>@ <|@ instruction DEOPT info [bci:0] <|@ <|@
    end_IR
  end_block
end_cfg
begin_bytecodes
     0: aload_0       
     1: invokespecial #0          // java.lang.Object.<init>:()void
     4: aload_0       
     5: aload_1       
     6: ldc           #2          // "Declaring class is null"
     8: invokestatic  #1          // java.util.Objects.requireNonNull:(java.lang.Object, java.lang.String)java.lang.Object
    11: checkcast     #4          // java.lang.String
    14: putfield      #2          // declaringClass:java.lang.String
    17: aload_0       
    18: aload_2       
    19: ldc           #6          // "Method name is null"
    21: invokestatic  #1          // java.util.Objects.requireNonNull:(java.lang.Object, java.lang.String)java.lang.Object
    24: checkcast     #4          // java.lang.String
    27: putfield      #3          // methodName:java.lang.String
    30: aload_0       
    31: aload_3       
    32: putfield      #4          // fileName:java.lang.String
    35: aload_0       
    36: iload         4
    38: putfield      #5          // lineNumber:int
    41: return        
   <|@
end_bytecodes
begin_cfg
  name "After PostAllocationOptimizationStage"
  begin_block
    name "B0"
    from_bci -1
    to_bci -1
    predecessors 
    successors "B1" "B2" 
    xhandlers
    flags 
    probability 4607182418800017408
    begin_IR
      LIR
      nr    0  <|@ instruction [rsi|QWORD[.], rdx|QWORD[.], rcx|QWORD[.], r8|QWORD[.], r9|DWORD, rbp|QWORD] = LABEL numbPhis: 0 align: false label: ? <|@ <|@
      nr    2  <|@ instruction stack:16|QWORD = MOVE rbp|QWORD moveKind: QWORD <|@ <|@
      nr    4  <|@ instruction [] = HOTSPOTLOCKSTACK frameMapBuilder: org.graalvm.compiler.lir.amd64.AMD64FrameMapBuilder@5101a515 slotKind: QWORD <|@ <|@
      nr   16  <|@ st <@st|@reference-map: [rcx:0, rdx:0, rsi:0, r8:0]
live-base-pointers: []
java.lang.StackTraceElement.<init>(StackTraceElement.java:70) [bci: 0]
locals: rsi|QWORD[.] rdx|QWORD[.] rcx|QWORD[.] r8|QWORD[.] r9|DWORD 
>@ <|@ instruction NULLCHECK [rdx|QWORD[.]] state [bci:0] <|@ <|@
      nr   18  <|@ instruction TEST (x: rcx|QWORD[.], y: rcx|QWORD[.]) size: QWORD <|@ <|@
      nr   20  <|@ instruction BRANCH trueDestinationProbability: 0.0 condition: = trueDestination: B0 -> B1 falseDestination: B0 -> B2 <|@ <|@
    end_IR
  end_block
  begin_block
    name "B2"
    from_bci -1
    to_bci -1
    predecessors "B0" 
    successors 
    xhandlers
    flags 
    probability 4607182418800017408
    begin_IR
      LIR
      nr   22  <|@ instruction [] = LABEL numbPhis: 0 align: false label: ? <|@ <|@
      nr   24  <|@ instruction rdx|DWORD[.] = COMPRESSPOINTER (input: rdx|QWORD[.], ~baseRegister: r12|ILLEGAL) nonNull: false lirKindTool: com.oracle.graal.enterprise.z.a@7a7f5448 encoding: base: 0 shift: 3 <|@ <|@
      nr   26  <|@ instruction MOV (x: [rsi|QWORD[.] + 12], y: rdx|DWORD[.]) size: DWORD <|@ <|@
      nr   28  <|@ instruction r10|QWORD[*] = SHR rsi|QWORD[.] y: 9 size: QWORD <|@ <|@
      nr   30  <|@ instruction r11|QWORD = MOVE input: long[4682670080|0x1171be000] <|@ <|@
      nr   32  <|@ instruction MOVB (x: [r10|QWORD[*] + r11|QWORD * 1], y: r12|ILLEGAL) size: BYTE <|@ <|@
      nr   34  <|@ instruction rcx|DWORD[.] = COMPRESSPOINTER (input: rcx|QWORD[.], ~baseRegister: r12|ILLEGAL) nonNull: false lirKindTool: com.oracle.graal.enterprise.z.a@7a7f5448 encoding: base: 0 shift: 3 <|@ <|@
      nr   36  <|@ instruction MOV (x: [rsi|QWORD[.] + 16], y: rcx|DWORD[.]) size: DWORD <|@ <|@
      nr   38  <|@ instruction r8|DWORD[.] = COMPRESSPOINTER (input: r8|QWORD[.], ~baseRegister: r12|ILLEGAL) nonNull: false lirKindTool: com.oracle.graal.enterprise.z.a@7a7f5448 encoding: base: 0 shift: 3 <|@ <|@
      nr   40  <|@ instruction MOV (x: [rsi|QWORD[.] + 20], y: r8|DWORD[.]) size: DWORD <|@ <|@
      nr   42  <|@ instruction MOV (x: [rsi|QWORD[.] + 24], y: r9|DWORD) size: DWORD <|@ <|@
      nr   44  <|@ instruction RETURN (savedRbp: stack:16|QWORD, value: -) isStub: false thread: r15 scratchForSafepointOnReturn: rcx config: org.graalvm.compiler.hotspot.GraalHotSpotVMConfig@7222fe45 <|@ <|@
    end_IR
  end_block
  begin_block
    name "B1"
    from_bci -1
    to_bci -1
    predecessors "B0" 
    successors 
    xhandlers
    flags 
    probability 2355382605114769408
    begin_IR
      LIR
      nr   46  <|@ instruction [] = LABEL numbPhis: 0 align: false label: ? <|@ <|@
      nr   48  <|@ instruction MOV [r15|QWORD + 668] y: -7443 size: DWORD <|@ <|@
      nr   50  <|@ instruction MOV (x: [r15|QWORD + 680], y: r12|ILLEGAL) size: QWORD <|@ <|@
      nr   52  <|@ st <@st|@reference-map: [rcx:0, rdx:0, rsi:0, r8:0]
live-base-pointers: []
java.lang.StackTraceElement.<init>(StackTraceElement.java:70) [bci: 0]
locals: rsi|QWORD[.] rdx|QWORD[.] rcx|QWORD[.] r8|QWORD[.] r9|DWORD 
>@ <|@ instruction DEOPT info [bci:0] <|@ <|@
    end_IR
  end_block
end_cfg
begin_bytecodes
     0: aload_0       
     1: invokespecial #0          // java.lang.Object.<init>:()void
     4: aload_0       
     5: aload_1       
     6: ldc           #2          // "Declaring class is null"
     8: invokestatic  #1          // java.util.Objects.requireNonNull:(java.lang.Object, java.lang.String)java.lang.Object
    11: checkcast     #4          // java.lang.String
    14: putfield      #2          // declaringClass:java.lang.String
    17: aload_0       
    18: aload_2       
    19: ldc           #6          // "Method name is null"
    21: invokestatic  #1          // java.util.Objects.requireNonNull:(java.lang.Object, java.lang.String)java.lang.Object
    24: checkcast     #4          // java.lang.String
    27: putfield      #3          // methodName:java.lang.String
    30: aload_0       
    31: aload_3       
    32: putfield      #4          // fileName:java.lang.String
    35: aload_0       
    36: iload         4
    38: putfield      #5          // lineNumber:int
    41: return        
   <|@
end_bytecodes
begin_cfg
  name "After code generation"
end_cfg
begin_nmethod
  <<<HexCodeFile
  Platform AMD64 64  <||@
  HexCode 0 448b560849c1e203493bc20f85efffffff900f1f80000000000f1f800000000089842400c0feff4883ec1848896c241085024885c90f844200000048c1ea0389560c4c8bd649c1ea0949bb00e01b17010000004788241a48c1e903894e1049c1e8034489461444894e18488b6c24104883c418850500000000c5f877c341c7879c020000ede2ffff4d89a7a8020000e80000000090e80000000090e80000000090  <||@
  Comment 0 2  <||@
  Comment 11 {Field[name=CompilerToVM::Data::SharedRuntime_ic_miss_stub, type=address, offset=0, address=0x105aa1f78, value=0x106805e60]:0x106805e60}  <||@
  Comment 32 [stack overflow check]  <||@
  Comment 32 3  <||@
  Comment 32 1  <||@
  Comment 43 block B0 null  <||@
  Comment 43 0 [rsi|QWORD[.], rdx|QWORD[.], rcx|QWORD[.], r8|QWORD[.], r9|DWORD, rbp|QWORD] = LABEL numbPhis: 0 align: false label: ?  <||@
  Comment 43 2 stack:16|QWORD = MOVE rbp|QWORD moveKind: QWORD  <||@
  Comment 48 4 [] = HOTSPOTLOCKSTACK frameMapBuilder: org.graalvm.compiler.lir.amd64.AMD64FrameMapBuilder@5101a515 slotKind: QWORD  <||@
  Comment 48 16 NULLCHECK [rdx|QWORD[.]] state [bci:0]  <||@
  Comment 48 [rcx:0, rdx:0, rsi:0, r8:0]at java.lang.StackTraceElement.<init>(StackTraceElement.java:70) [bci: 0, duringCall: false, rethrow: false]
              |0             |1             |2             |3            |4        
     locals:  |rsi|QWORD[.]  |rdx|QWORD[.]  |rcx|QWORD[.]  |r8|QWORD[.]  |r9|DWORD   <||@
  Comment 48 {infopoint: IMPLICIT_EXCEPTION}  <||@
  Comment 50 18 TEST (x: rcx|QWORD[.], y: rcx|QWORD[.]) size: QWORD  <||@
  Comment 53 20 BRANCH trueDestinationProbability: 0.0 condition: = trueDestination: B0 -> B1 falseDestination: B0 -> B2  <||@
  Comment 59 block B2 null  <||@
  Comment 59 22 [] = LABEL numbPhis: 0 align: false label: ?  <||@
  Comment 59 24 rdx|DWORD[.] = COMPRESSPOINTER (input: rdx|QWORD[.], ~baseRegister: r12|ILLEGAL) nonNull: false lirKindTool: com.oracle.graal.enterprise.z.a@7a7f5448 encoding: base: 0 shift: 3  <||@
  Comment 63 26 MOV (x: [rsi|QWORD[.] + 12], y: rdx|DWORD[.]) size: DWORD  <||@
  Comment 66 28 r10|QWORD[*] = SHR rsi|QWORD[.] y: 9 size: QWORD  <||@
  Comment 73 30 r11|QWORD = MOVE input: long[4682670080|0x1171be000]  <||@
  Comment 83 32 MOVB (x: [r10|QWORD[*] + r11|QWORD * 1], y: r12|ILLEGAL) size: BYTE  <||@
  Comment 87 34 rcx|DWORD[.] = COMPRESSPOINTER (input: rcx|QWORD[.], ~baseRegister: r12|ILLEGAL) nonNull: false lirKindTool: com.oracle.graal.enterprise.z.a@7a7f5448 encoding: base: 0 shift: 3  <||@
  Comment 91 36 MOV (x: [rsi|QWORD[.] + 16], y: rcx|DWORD[.]) size: DWORD  <||@
  Comment 94 38 r8|DWORD[.] = COMPRESSPOINTER (input: r8|QWORD[.], ~baseRegister: r12|ILLEGAL) nonNull: false lirKindTool: com.oracle.graal.enterprise.z.a@7a7f5448 encoding: base: 0 shift: 3  <||@
  Comment 98 40 MOV (x: [rsi|QWORD[.] + 20], y: r8|DWORD[.]) size: DWORD  <||@
  Comment 102 42 MOV (x: [rsi|QWORD[.] + 24], y: r9|DWORD) size: DWORD  <||@
  Comment 106 44 RETURN (savedRbp: stack:16|QWORD, value: -) isStub: false thread: r15 scratchForSafepointOnReturn: rcx config: org.graalvm.compiler.hotspot.GraalHotSpotVMConfig@7222fe45  <||@
  Comment 115 12  <||@
  Comment 125 block B1 null  <||@
  Comment 125 46 [] = LABEL numbPhis: 0 align: false label: ?  <||@
  Comment 125 48 MOV [r15|QWORD + 668] y: -7443 size: DWORD  <||@
  Comment 136 50 MOV (x: [r15|QWORD + 680], y: r12|ILLEGAL) size: QWORD  <||@
  Comment 143 52 DEOPT info [bci:0]  <||@
  Comment 143 {Field[name=CompilerToVM::Data::SharedRuntime_deopt_blob_uncommon_trap, type=address, offset=0, address=0x105aa1f90, value=0x1068075fe]:0x1068075fe}  <||@
  Comment 148 [rcx:0, rdx:0, rsi:0, r8:0]at java.lang.StackTraceElement.<init>(StackTraceElement.java:70) [bci: 0, duringCall: false, rethrow: false]
              |0             |1             |2             |3            |4        
     locals:  |rsi|QWORD[.]  |rdx|QWORD[.]  |rcx|QWORD[.]  |r8|QWORD[.]  |r9|DWORD   <||@
  Comment 149 {Stub<ExceptionHandlerStub.exceptionHandler>@0x106c4a620:CallingConvention[rax|QWORD[.], rdx|QWORD]:CallingConvention[rax|QWORD[.], rdx|QWORD]; temps=rdi|ILLEGAL,xmm0|ILLEGAL,xmm1|ILLEGAL,xmm2|ILLEGAL,xmm3|ILLEGAL,xmm4|ILLEGAL,xmm5|ILLEGAL,xmm6|ILLEGAL,xmm7|ILLEGAL,xmm8|ILLEGAL,xmm9|ILLEGAL,xmm10|ILLEGAL,xmm11|ILLEGAL,xmm12|ILLEGAL,xmm13|ILLEGAL,xmm14|ILLEGAL,xmm15|ILLEGAL,xmm16|ILLEGAL,xmm17|ILLEGAL,xmm18|ILLEGAL,xmm19|ILLEGAL,xmm20|ILLEGAL,xmm21|ILLEGAL,xmm22|ILLEGAL,xmm23|ILLEGAL,xmm24|ILLEGAL,xmm25|ILLEGAL,xmm26|ILLEGAL,xmm27|ILLEGAL,xmm28|ILLEGAL,xmm29|ILLEGAL,xmm30|ILLEGAL,xmm31|ILLEGAL,rax|ILLEGAL,rcx|ILLEGAL,rdx|ILLEGAL,rsi|ILLEGAL,r8|ILLEGAL,r9|ILLEGAL,r10|ILLEGAL,r11|ILLEGAL}  <||@
  Comment 149 4  <||@
  Comment 155 {Field[name=CompilerToVM::Data::SharedRuntime_deopt_blob_unpack, type=address, offset=0, address=0x105aa1f88, value=0x106807500]:0x106807500}  <||@
  Comment 155 5  <||@
  HexCodeFile>>> <|@
end_nmethod
begin_compilation
  name " HotSpotCompilation-9244[java.lang.StackTraceElement.<init>(String, String, String, int)]"
  method "HotSpotCompilation-9244[java.lang.StackTraceElement.<init>(String, String, String, int)]"
  date 1527005202599
end_compilation
begin_cfg
  name "After code installation"
end_cfg
begin_nmethod
  <<<HexCodeFile
  Platform AMD64 64  <||@
  HexCode 107b5be60 448b560849c1e203493bc20f85ef9fcafe900f1f80000000000f1f800000000089842400c0feff4883ec1848896c241085024885c90f844200000048c1ea0389560c4c8bd649c1ea0949bb00e01b17010000004788241a48c1e903894e1049c1e8034489461444894e18488b6c24104883c41885052d31d3fcc5f877c341c7879c020000ede2ffff4d89a7a8020000e80ab7cafe90e826e70eff90e800b6cafe90f4f4f4f4f4f4f4  <||@
  Comment 0 2  <||@
  Comment 11 {Field[name=CompilerToVM::Data::SharedRuntime_ic_miss_stub, type=address, offset=0, address=0x105aa1f78, value=0x106805e60]:0x106805e60}  <||@
  Comment 32 [stack overflow check]  <||@
  Comment 32 3  <||@
  Comment 32 1  <||@
  Comment 43 block B0 null  <||@
  Comment 43 0 [rsi|QWORD[.], rdx|QWORD[.], rcx|QWORD[.], r8|QWORD[.], r9|DWORD, rbp|QWORD] = LABEL numbPhis: 0 align: false label: ?  <||@
  Comment 43 2 stack:16|QWORD = MOVE rbp|QWORD moveKind: QWORD  <||@
  Comment 48 4 [] = HOTSPOTLOCKSTACK frameMapBuilder: org.graalvm.compiler.lir.amd64.AMD64FrameMapBuilder@5101a515 slotKind: QWORD  <||@
  Comment 48 16 NULLCHECK [rdx|QWORD[.]] state [bci:0]  <||@
  Comment 48 [rcx:0, rdx:0, rsi:0, r8:0]at java.lang.StackTraceElement.<init>(StackTraceElement.java:70) [bci: 0, duringCall: false, rethrow: false]
              |0             |1             |2             |3            |4        
     locals:  |rsi|QWORD[.]  |rdx|QWORD[.]  |rcx|QWORD[.]  |r8|QWORD[.]  |r9|DWORD   <||@
  Comment 48 {infopoint: IMPLICIT_EXCEPTION}  <||@
  Comment 50 18 TEST (x: rcx|QWORD[.], y: rcx|QWORD[.]) size: QWORD  <||@
  Comment 53 20 BRANCH trueDestinationProbability: 0.0 condition: = trueDestination: B0 -> B1 falseDestination: B0 -> B2  <||@
  Comment 59 block B2 null  <||@
  Comment 59 22 [] = LABEL numbPhis: 0 align: false label: ?  <||@
  Comment 59 24 rdx|DWORD[.] = COMPRESSPOINTER (input: rdx|QWORD[.], ~baseRegister: r12|ILLEGAL) nonNull: false lirKindTool: com.oracle.graal.enterprise.z.a@7a7f5448 encoding: base: 0 shift: 3  <||@
  Comment 63 26 MOV (x: [rsi|QWORD[.] + 12], y: rdx|DWORD[.]) size: DWORD  <||@
  Comment 66 28 r10|QWORD[*] = SHR rsi|QWORD[.] y: 9 size: QWORD  <||@
  Comment 73 30 r11|QWORD = MOVE input: long[4682670080|0x1171be000]  <||@
  Comment 83 32 MOVB (x: [r10|QWORD[*] + r11|QWORD * 1], y: r12|ILLEGAL) size: BYTE  <||@
  Comment 87 34 rcx|DWORD[.] = COMPRESSPOINTER (input: rcx|QWORD[.], ~baseRegister: r12|ILLEGAL) nonNull: false lirKindTool: com.oracle.graal.enterprise.z.a@7a7f5448 encoding: base: 0 shift: 3  <||@
  Comment 91 36 MOV (x: [rsi|QWORD[.] + 16], y: rcx|DWORD[.]) size: DWORD  <||@
  Comment 94 38 r8|DWORD[.] = COMPRESSPOINTER (input: r8|QWORD[.], ~baseRegister: r12|ILLEGAL) nonNull: false lirKindTool: com.oracle.graal.enterprise.z.a@7a7f5448 encoding: base: 0 shift: 3  <||@
  Comment 98 40 MOV (x: [rsi|QWORD[.] + 20], y: r8|DWORD[.]) size: DWORD  <||@
  Comment 102 42 MOV (x: [rsi|QWORD[.] + 24], y: r9|DWORD) size: DWORD  <||@
  Comment 106 44 RETURN (savedRbp: stack:16|QWORD, value: -) isStub: false thread: r15 scratchForSafepointOnReturn: rcx config: org.graalvm.compiler.hotspot.GraalHotSpotVMConfig@7222fe45  <||@
  Comment 115 12  <||@
  Comment 125 block B1 null  <||@
  Comment 125 46 [] = LABEL numbPhis: 0 align: false label: ?  <||@
  Comment 125 48 MOV [r15|QWORD + 668] y: -7443 size: DWORD  <||@
  Comment 136 50 MOV (x: [r15|QWORD + 680], y: r12|ILLEGAL) size: QWORD  <||@
  Comment 143 52 DEOPT info [bci:0]  <||@
  Comment 143 {Field[name=CompilerToVM::Data::SharedRuntime_deopt_blob_uncommon_trap, type=address, offset=0, address=0x105aa1f90, value=0x1068075fe]:0x1068075fe}  <||@
  Comment 148 [rcx:0, rdx:0, rsi:0, r8:0]at java.lang.StackTraceElement.<init>(StackTraceElement.java:70) [bci: 0, duringCall: false, rethrow: false]
              |0             |1             |2             |3            |4        
     locals:  |rsi|QWORD[.]  |rdx|QWORD[.]  |rcx|QWORD[.]  |r8|QWORD[.]  |r9|DWORD   <||@
  Comment 149 {Stub<ExceptionHandlerStub.exceptionHandler>@0x106c4a620:CallingConvention[rax|QWORD[.], rdx|QWORD]:CallingConvention[rax|QWORD[.], rdx|QWORD]; temps=rdi|ILLEGAL,xmm0|ILLEGAL,xmm1|ILLEGAL,xmm2|ILLEGAL,xmm3|ILLEGAL,xmm4|ILLEGAL,xmm5|ILLEGAL,xmm6|ILLEGAL,xmm7|ILLEGAL,xmm8|ILLEGAL,xmm9|ILLEGAL,xmm10|ILLEGAL,xmm11|ILLEGAL,xmm12|ILLEGAL,xmm13|ILLEGAL,xmm14|ILLEGAL,xmm15|ILLEGAL,xmm16|ILLEGAL,xmm17|ILLEGAL,xmm18|ILLEGAL,xmm19|ILLEGAL,xmm20|ILLEGAL,xmm21|ILLEGAL,xmm22|ILLEGAL,xmm23|ILLEGAL,xmm24|ILLEGAL,xmm25|ILLEGAL,xmm26|ILLEGAL,xmm27|ILLEGAL,xmm28|ILLEGAL,xmm29|ILLEGAL,xmm30|ILLEGAL,xmm31|ILLEGAL,rax|ILLEGAL,rcx|ILLEGAL,rdx|ILLEGAL,rsi|ILLEGAL,r8|ILLEGAL,r9|ILLEGAL,r10|ILLEGAL,r11|ILLEGAL}  <||@
  Comment 149 4  <||@
  Comment 155 {Field[name=CompilerToVM::Data::SharedRuntime_deopt_blob_unpack, type=address, offset=0, address=0x105aa1f88, value=0x106807500]:0x106807500}  <||@
  Comment 155 5  <||@
  HexCodeFile>>> <|@
end_nmethod
