begin_compilation
  name " HotSpotCompilation-5243[java.util.BitSet.checkInvariants()]"
  method "HotSpotCompilation-5243[java.util.BitSet.checkInvariants()]"
  date 1527005147716
end_compilation
begin_cfg
  name "Final HIR schedule"
  begin_block
    name "B0"
    from_bci -1
    to_bci -1
    predecessors 
    successors 
    xhandlers
    flags 
    probability 4607182418800017408
    begin_IR
      HIR
f <@#|@fixed with next>@ <|@
tid v0 <|@
d <@d|@=== Debug Properties ===
stamp: void
=== Inputs ===
stateAfter: - 
=== Succesors ===
next: v5 
=== Usages ===
=== Predecessor ===
- >@ <|@
instruction <@StartNode|@org.graalvm.compiler.nodes.StartNode>@ stateAfter: - #next: v5  <|@  <|@
f <@*|@fixed>@ <|@
tid v5 <|@
d <@d|@=== Debug Properties ===
nodeSourcePosition: at java.util.BitSet.checkInvariants(BitSet.java:122) [bci: 110]
stamp: void
=== Inputs ===
result: - 
memoryMap: - 
=== Succesors ===
=== Usages ===
=== Predecessor ===
v0 >@ <|@
instruction <@Return|@org.graalvm.compiler.nodes.ReturnNode>@ result: - memoryMap: -  <|@  <|@
    end_IR
  end_block
end_cfg
begin_cfg
  name "After LIR generation"
  begin_block
    name "B0"
    from_bci -1
    to_bci -1
    predecessors 
    successors 
    xhandlers
    flags 
    probability 4607182418800017408
    begin_IR
      HIR
f <@#|@fixed with next>@ <|@
tid v0 <|@
d <@d|@=== Debug Properties ===
stamp: void
=== Inputs ===
stateAfter: - 
=== Succesors ===
next: v5 
=== Usages ===
=== Predecessor ===
- >@ <|@
instruction <@StartNode|@org.graalvm.compiler.nodes.StartNode>@ stateAfter: - #next: v5  <|@  <|@
f <@*|@fixed>@ <|@
tid v5 <|@
d <@d|@=== Debug Properties ===
nodeSourcePosition: at java.util.BitSet.checkInvariants(BitSet.java:122) [bci: 110]
stamp: void
=== Inputs ===
result: - 
memoryMap: - 
=== Succesors ===
=== Usages ===
=== Predecessor ===
v0 >@ <|@
instruction <@Return|@org.graalvm.compiler.nodes.ReturnNode>@ result: - memoryMap: -  <|@  <|@
    end_IR
    begin_IR
      LIR
      nr   -1  <|@ instruction [rsi|QWORD[.], rbp|QWORD] = LABEL numbPhis: 0 align: false label: ? <|@ <|@
      nr   -1  <|@ instruction v0|QWORD = MOVE rbp|QWORD moveKind: QWORD <|@ <|@
      nr   -1  <|@ instruction [] = HOTSPOTLOCKSTACK frameMapBuilder: org.graalvm.compiler.lir.amd64.AMD64FrameMapBuilder@3117bf2b slotKind: QWORD <|@ <|@
      nr   -1  <|@ instruction RETURN (savedRbp: v0|QWORD, value: -) isStub: false thread: r15 scratchForSafepointOnReturn: rcx config: org.graalvm.compiler.hotspot.GraalHotSpotVMConfig@7222fe45 <|@ <|@
    end_IR
  end_block
end_cfg
begin_cfg
  name "After PreAllocationOptimizationStage"
  begin_block
    name "B0"
    from_bci -1
    to_bci -1
    predecessors 
    successors 
    xhandlers
    flags 
    probability 4607182418800017408
    begin_IR
      LIR
      nr   -1  <|@ instruction [rsi|QWORD[.], rbp|QWORD] = LABEL numbPhis: 0 align: false label: ? <|@ <|@
      nr   -1  <|@ instruction v0|QWORD = MOVE rbp|QWORD moveKind: QWORD <|@ <|@
      nr   -1  <|@ instruction [] = HOTSPOTLOCKSTACK frameMapBuilder: org.graalvm.compiler.lir.amd64.AMD64FrameMapBuilder@3117bf2b slotKind: QWORD <|@ <|@
      nr   -1  <|@ instruction RETURN (savedRbp: v0|QWORD, value: -) isStub: false thread: r15 scratchForSafepointOnReturn: rcx config: org.graalvm.compiler.hotspot.GraalHotSpotVMConfig@7222fe45 <|@ <|@
    end_IR
  end_block
end_cfg
begin_bytecodes
     0: getstatic     #0          // $assertionsDisabled:boolean
     3: ifne          37
     6: aload_0       
     7: getfield      #1          // wordsInUse:int
    10: ifeq          37
    13: aload_0       
    14: getfield      #2          // words:long[]
    17: aload_0       
    18: getfield      #1          // wordsInUse:int
    21: iconst_1      
    22: isub          
    23: laload        
    24: lconst_0      
    25: lcmp          
    26: ifne          37
    29: new           #5          // java.lang.AssertionError
    32: dup           
    33: invokespecial #3          // java.lang.AssertionError.<init>:()void
    36: athrow        
    37: getstatic     #0          // $assertionsDisabled:boolean
    40: ifne          70
    43: aload_0       
    44: getfield      #1          // wordsInUse:int
    47: iflt          62
    50: aload_0       
    51: getfield      #1          // wordsInUse:int
    54: aload_0       
    55: getfield      #2          // words:long[]
    58: arraylength   
    59: if_icmple     70
    62: new           #5          // java.lang.AssertionError
    65: dup           
    66: invokespecial #3          // java.lang.AssertionError.<init>:()void
    69: athrow        
    70: getstatic     #0          // $assertionsDisabled:boolean
    73: ifne          110
    76: aload_0       
    77: getfield      #1          // wordsInUse:int
    80: aload_0       
    81: getfield      #2          // words:long[]
    84: arraylength   
    85: if_icmpeq     110
    88: aload_0       
    89: getfield      #2          // words:long[]
    92: aload_0       
    93: getfield      #1          // wordsInUse:int
    96: laload        
    97: lconst_0      
    98: lcmp          
    99: ifeq          110
   102: new           #5          // java.lang.AssertionError
   105: dup           
   106: invokespecial #3          // java.lang.AssertionError.<init>:()void
   109: athrow        
   110: return        
   <|@
end_bytecodes
begin_cfg
  name "After AllocationStage"
  begin_block
    name "B0"
    from_bci -1
    to_bci -1
    predecessors 
    successors 
    xhandlers
    flags 
    probability 4607182418800017408
    begin_IR
      LIR
      nr    0  <|@ instruction [rsi|QWORD[.], rbp|QWORD] = LABEL numbPhis: 0 align: false label: ? <|@ <|@
      nr    4  <|@ instruction [] = HOTSPOTLOCKSTACK frameMapBuilder: org.graalvm.compiler.lir.amd64.AMD64FrameMapBuilder@3117bf2b slotKind: QWORD <|@ <|@
      nr    6  <|@ instruction RETURN (savedRbp: rbp|QWORD, value: -) isStub: false thread: r15 scratchForSafepointOnReturn: rcx config: org.graalvm.compiler.hotspot.GraalHotSpotVMConfig@7222fe45 <|@ <|@
    end_IR
  end_block
end_cfg
begin_bytecodes
     0: getstatic     #0          // $assertionsDisabled:boolean
     3: ifne          37
     6: aload_0       
     7: getfield      #1          // wordsInUse:int
    10: ifeq          37
    13: aload_0       
    14: getfield      #2          // words:long[]
    17: aload_0       
    18: getfield      #1          // wordsInUse:int
    21: iconst_1      
    22: isub          
    23: laload        
    24: lconst_0      
    25: lcmp          
    26: ifne          37
    29: new           #5          // java.lang.AssertionError
    32: dup           
    33: invokespecial #3          // java.lang.AssertionError.<init>:()void
    36: athrow        
    37: getstatic     #0          // $assertionsDisabled:boolean
    40: ifne          70
    43: aload_0       
    44: getfield      #1          // wordsInUse:int
    47: iflt          62
    50: aload_0       
    51: getfield      #1          // wordsInUse:int
    54: aload_0       
    55: getfield      #2          // words:long[]
    58: arraylength   
    59: if_icmple     70
    62: new           #5          // java.lang.AssertionError
    65: dup           
    66: invokespecial #3          // java.lang.AssertionError.<init>:()void
    69: athrow        
    70: getstatic     #0          // $assertionsDisabled:boolean
    73: ifne          110
    76: aload_0       
    77: getfield      #1          // wordsInUse:int
    80: aload_0       
    81: getfield      #2          // words:long[]
    84: arraylength   
    85: if_icmpeq     110
    88: aload_0       
    89: getfield      #2          // words:long[]
    92: aload_0       
    93: getfield      #1          // wordsInUse:int
    96: laload        
    97: lconst_0      
    98: lcmp          
    99: ifeq          110
   102: new           #5          // java.lang.AssertionError
   105: dup           
   106: invokespecial #3          // java.lang.AssertionError.<init>:()void
   109: athrow        
   110: return        
   <|@
end_bytecodes
begin_cfg
  name "After PostAllocationOptimizationStage"
  begin_block
    name "B0"
    from_bci -1
    to_bci -1
    predecessors 
    successors 
    xhandlers
    flags 
    probability 4607182418800017408
    begin_IR
      LIR
      nr    0  <|@ instruction [rsi|QWORD[.], rbp|QWORD] = LABEL numbPhis: 0 align: false label: ? <|@ <|@
      nr    4  <|@ instruction [] = HOTSPOTLOCKSTACK frameMapBuilder: org.graalvm.compiler.lir.amd64.AMD64FrameMapBuilder@3117bf2b slotKind: QWORD <|@ <|@
      nr    6  <|@ instruction RETURN (savedRbp: rbp|QWORD, value: -) isStub: false thread: r15 scratchForSafepointOnReturn: rcx config: org.graalvm.compiler.hotspot.GraalHotSpotVMConfig@7222fe45 <|@ <|@
    end_IR
  end_block
end_cfg
begin_bytecodes
     0: getstatic     #0          // $assertionsDisabled:boolean
     3: ifne          37
     6: aload_0       
     7: getfield      #1          // wordsInUse:int
    10: ifeq          37
    13: aload_0       
    14: getfield      #2          // words:long[]
    17: aload_0       
    18: getfield      #1          // wordsInUse:int
    21: iconst_1      
    22: isub          
    23: laload        
    24: lconst_0      
    25: lcmp          
    26: ifne          37
    29: new           #5          // java.lang.AssertionError
    32: dup           
    33: invokespecial #3          // java.lang.AssertionError.<init>:()void
    36: athrow        
    37: getstatic     #0          // $assertionsDisabled:boolean
    40: ifne          70
    43: aload_0       
    44: getfield      #1          // wordsInUse:int
    47: iflt          62
    50: aload_0       
    51: getfield      #1          // wordsInUse:int
    54: aload_0       
    55: getfield      #2          // words:long[]
    58: arraylength   
    59: if_icmple     70
    62: new           #5          // java.lang.AssertionError
    65: dup           
    66: invokespecial #3          // java.lang.AssertionError.<init>:()void
    69: athrow        
    70: getstatic     #0          // $assertionsDisabled:boolean
    73: ifne          110
    76: aload_0       
    77: getfield      #1          // wordsInUse:int
    80: aload_0       
    81: getfield      #2          // words:long[]
    84: arraylength   
    85: if_icmpeq     110
    88: aload_0       
    89: getfield      #2          // words:long[]
    92: aload_0       
    93: getfield      #1          // wordsInUse:int
    96: laload        
    97: lconst_0      
    98: lcmp          
    99: ifeq          110
   102: new           #5          // java.lang.AssertionError
   105: dup           
   106: invokespecial #3          // java.lang.AssertionError.<init>:()void
   109: athrow        
   110: return        
   <|@
end_bytecodes
begin_cfg
  name "After code generation"
end_cfg
begin_nmethod
  <<<HexCodeFile
  Platform AMD64 64  <||@
  HexCode 0 448b560849c1e203493bc20f85efffffff900f1f80000000000f1f80000000000f1f440000850500000000c5f877c3e80000000090e80000000090  <||@
  Comment 0 2  <||@
  Comment 11 {Field[name=CompilerToVM::Data::SharedRuntime_ic_miss_stub, type=address, offset=0, address=0x105aa1f78, value=0x106805e60]:0x106805e60}  <||@
  Comment 32 3  <||@
  Comment 32 1  <||@
  Comment 37 block B0 null  <||@
  Comment 37 0 [rsi|QWORD[.], rbp|QWORD] = LABEL numbPhis: 0 align: false label: ?  <||@
  Comment 37 4 [] = HOTSPOTLOCKSTACK frameMapBuilder: org.graalvm.compiler.lir.amd64.AMD64FrameMapBuilder@3117bf2b slotKind: QWORD  <||@
  Comment 37 6 RETURN (savedRbp: rbp|QWORD, value: -) isStub: false thread: r15 scratchForSafepointOnReturn: rcx config: org.graalvm.compiler.hotspot.GraalHotSpotVMConfig@7222fe45  <||@
  Comment 37 12  <||@
  Comment 47 {Stub<ExceptionHandlerStub.exceptionHandler>@0x106c4a620:CallingConvention[rax|QWORD[.], rdx|QWORD]:CallingConvention[rax|QWORD[.], rdx|QWORD]; temps=rdi|ILLEGAL,xmm0|ILLEGAL,xmm1|ILLEGAL,xmm2|ILLEGAL,xmm3|ILLEGAL,xmm4|ILLEGAL,xmm5|ILLEGAL,xmm6|ILLEGAL,xmm7|ILLEGAL,xmm8|ILLEGAL,xmm9|ILLEGAL,xmm10|ILLEGAL,xmm11|ILLEGAL,xmm12|ILLEGAL,xmm13|ILLEGAL,xmm14|ILLEGAL,xmm15|ILLEGAL,xmm16|ILLEGAL,xmm17|ILLEGAL,xmm18|ILLEGAL,xmm19|ILLEGAL,xmm20|ILLEGAL,xmm21|ILLEGAL,xmm22|ILLEGAL,xmm23|ILLEGAL,xmm24|ILLEGAL,xmm25|ILLEGAL,xmm26|ILLEGAL,xmm27|ILLEGAL,xmm28|ILLEGAL,xmm29|ILLEGAL,xmm30|ILLEGAL,xmm31|ILLEGAL,rax|ILLEGAL,rcx|ILLEGAL,rdx|ILLEGAL,rsi|ILLEGAL,r8|ILLEGAL,r9|ILLEGAL,r10|ILLEGAL,r11|ILLEGAL}  <||@
  Comment 47 4  <||@
  Comment 53 {Field[name=CompilerToVM::Data::SharedRuntime_deopt_blob_unpack, type=address, offset=0, address=0x105aa1f88, value=0x106807500]:0x106807500}  <||@
  Comment 53 5  <||@
  HexCodeFile>>> <|@
end_nmethod
begin_compilation
  name " HotSpotCompilation-5243[java.util.BitSet.checkInvariants()]"
  method "HotSpotCompilation-5243[java.util.BitSet.checkInvariants()]"
  date 1527005147736
end_compilation
begin_cfg
  name "After code installation"
end_cfg
begin_nmethod
  <<<HexCodeFile
  Platform AMD64 64  <||@
  HexCode 10785e2a0 448b560849c1e203493bc20f85af7bfafe900f1f80000000000f1f80000000000f1f44000085053b0d03fdc5f877c3e84cc33eff90e82692fafe90f4f4f4f4f4  <||@
  Comment 0 2  <||@
  Comment 11 {Field[name=CompilerToVM::Data::SharedRuntime_ic_miss_stub, type=address, offset=0, address=0x105aa1f78, value=0x106805e60]:0x106805e60}  <||@
  Comment 32 3  <||@
  Comment 32 1  <||@
  Comment 37 block B0 null  <||@
  Comment 37 0 [rsi|QWORD[.], rbp|QWORD] = LABEL numbPhis: 0 align: false label: ?  <||@
  Comment 37 4 [] = HOTSPOTLOCKSTACK frameMapBuilder: org.graalvm.compiler.lir.amd64.AMD64FrameMapBuilder@3117bf2b slotKind: QWORD  <||@
  Comment 37 6 RETURN (savedRbp: rbp|QWORD, value: -) isStub: false thread: r15 scratchForSafepointOnReturn: rcx config: org.graalvm.compiler.hotspot.GraalHotSpotVMConfig@7222fe45  <||@
  Comment 37 12  <||@
  Comment 47 {Stub<ExceptionHandlerStub.exceptionHandler>@0x106c4a620:CallingConvention[rax|QWORD[.], rdx|QWORD]:CallingConvention[rax|QWORD[.], rdx|QWORD]; temps=rdi|ILLEGAL,xmm0|ILLEGAL,xmm1|ILLEGAL,xmm2|ILLEGAL,xmm3|ILLEGAL,xmm4|ILLEGAL,xmm5|ILLEGAL,xmm6|ILLEGAL,xmm7|ILLEGAL,xmm8|ILLEGAL,xmm9|ILLEGAL,xmm10|ILLEGAL,xmm11|ILLEGAL,xmm12|ILLEGAL,xmm13|ILLEGAL,xmm14|ILLEGAL,xmm15|ILLEGAL,xmm16|ILLEGAL,xmm17|ILLEGAL,xmm18|ILLEGAL,xmm19|ILLEGAL,xmm20|ILLEGAL,xmm21|ILLEGAL,xmm22|ILLEGAL,xmm23|ILLEGAL,xmm24|ILLEGAL,xmm25|ILLEGAL,xmm26|ILLEGAL,xmm27|ILLEGAL,xmm28|ILLEGAL,xmm29|ILLEGAL,xmm30|ILLEGAL,xmm31|ILLEGAL,rax|ILLEGAL,rcx|ILLEGAL,rdx|ILLEGAL,rsi|ILLEGAL,r8|ILLEGAL,r9|ILLEGAL,r10|ILLEGAL,r11|ILLEGAL}  <||@
  Comment 47 4  <||@
  Comment 53 {Field[name=CompilerToVM::Data::SharedRuntime_deopt_blob_unpack, type=address, offset=0, address=0x105aa1f88, value=0x106807500]:0x106807500}  <||@
  Comment 53 5  <||@
  HexCodeFile>>> <|@
end_nmethod
