begin_compilation
  name " HotSpotCompilation-9450[java.util.ArrayList.contains(Object)]"
  method "HotSpotCompilation-9450[java.util.ArrayList.contains(Object)]"
  date 1527005213410
end_compilation
begin_cfg
  name "Final HIR schedule"
  begin_block
    name "B0"
    from_bci -1
    to_bci -1
    predecessors 
    successors 
    xhandlers
    flags 
    probability 4607182418800017408
    begin_IR
      HIR
f <@#|@fixed with next>@ <|@
tid v0 <|@
d <@d|@=== Debug Properties ===
stamp: void
=== Inputs ===
stateAfter: - 
=== Succesors ===
next: i5 
=== Usages ===
=== Predecessor ===
- >@ <|@
instruction <@StartNode|@org.graalvm.compiler.nodes.StartNode>@ stateAfter: - #next: i5  <|@  <|@
f <@~|@floating>@ <|@
tid a1 <|@
d <@d|@=== Debug Properties ===
index: 0
stamp: a!# Ljava/util/ArrayList;
uncheckedStamp: [null]
=== Inputs ===
=== Succesors ===
=== Usages ===
v12 
=== Predecessor ===
- >@ <|@
instruction <@Parameter|@org.graalvm.compiler.nodes.ParameterNode>@  <|@  <|@
f <@~|@floating>@ <|@
tid a2 <|@
d <@d|@=== Debug Properties ===
index: 1
stamp: a Ljava/lang/Object;
uncheckedStamp: [null]
=== Inputs ===
=== Succesors ===
=== Usages ===
v12 
=== Predecessor ===
- >@ <|@
instruction <@Parameter|@org.graalvm.compiler.nodes.ParameterNode>@  <|@  <|@
tid v12 <|@
d <@d|@=== Debug Properties ===
callType: JavaCall
invokeKind: Special
nodeSourcePosition: at java.util.ArrayList.contains(ArrayList.java:304) [bci: 2]
returnStamp: i32
signature: [Ljdk.vm.ci.meta.JavaType;@6093892f
stamp: void
targetMethod: HotSpotMethod<ArrayList.indexOf(Object)>
=== Inputs ===
arguments: a1 a2 
=== Succesors ===
=== Usages ===
i5 
=== Predecessor ===
- >@ <|@
instruction <@HotSpotDirectCallTarget|@org.graalvm.compiler.hotspot.nodes.HotSpotDirectCallTargetNode>@ arguments: a1 a2  <|@  <|@
tid ?13 <|@
d <@d|@=== Debug Properties ===
bci: 2
code: ResolvedJavaMethodBytecode<ArrayList.contains(Object)>
duringCall: true
localsSize: 2
locksSize: 0
rethrowException: false
sourceFile: ArrayList.java
sourceLine: 304
stackSize: 0
=== Inputs ===
outerFrameState: - 
values: - - 
=== Succesors ===
=== Usages ===
i5 
=== Predecessor ===
- >@ <|@
instruction <@FrameState|@org.graalvm.compiler.nodes.FrameState>@ outerFrameState: - values: - -  <|@  <|@
f <@#|@fixed with next>@ <|@
tid i5 <|@
d <@d|@=== Debug Properties ===
bci: 2
nodeSourcePosition: at java.util.ArrayList.contains(ArrayList.java:304) [bci: 2]
polymorphic: false
stamp: i32
targetMethod: Direct#ArrayList.indexOf
useForInlining: true
=== Inputs ===
stateAfter: - 
classInit: - 
callTarget: v12 
stateDuring: ?13 
=== Succesors ===
next: v11 
=== Usages ===
v8 
=== Predecessor ===
v0 >@ <|@
instruction <@Invoke|@org.graalvm.compiler.nodes.InvokeNode>@ stateAfter: - classInit: - callTarget: v12 stateDuring: ?13 #next: v11  <|@  <|@
f <@~|@floating>@ <|@
tid i7 <|@
d <@d|@=== Debug Properties ===
isDefaultStable: false
nodeSourcePosition: at java.util.ArrayList.contains(ArrayList.java:304) [bci: 5]
rawvalue: 0
stableDimension: 0
stamp: i32 [0] ⇈0000000000000000
stampKind: i32
value: int[0|0x0]
=== Inputs ===
=== Succesors ===
=== Usages ===
v8 i10 
=== Predecessor ===
- >@ <|@
instruction <@Constant|@org.graalvm.compiler.nodes.ConstantNode>@  <|@  <|@
f <@~|@floating>@ <|@
tid v8 <|@
d <@d|@=== Debug Properties ===
condition: LT
nodeSourcePosition: at java.util.ArrayList.contains(ArrayList.java:304) [bci: 5]
op: org.graalvm.compiler.nodes.calc.IntegerLessThanNode$LessThanOp@7cc8d043
stamp: void
unorderedIsTrue: false
=== Inputs ===
x: i5 
y: i7 
=== Succesors ===
=== Usages ===
i10 
=== Predecessor ===
- >@ <|@
instruction <@<|@org.graalvm.compiler.nodes.calc.IntegerLessThanNode>@ x: i5 y: i7  <|@  <|@
f <@~|@floating>@ <|@
tid i9 <|@
d <@d|@=== Debug Properties ===
isDefaultStable: false
nodeSourcePosition: at java.util.ArrayList.contains(ArrayList.java:304) [bci: 5]
rawvalue: 1
stableDimension: 0
stamp: i32 [1] ⇊0000000000000001 ⇈0000000000000001
stampKind: i32
value: int[1|0x1]
=== Inputs ===
=== Succesors ===
=== Usages ===
i10 
=== Predecessor ===
- >@ <|@
instruction <@Constant|@org.graalvm.compiler.nodes.ConstantNode>@  <|@  <|@
f <@~|@floating>@ <|@
tid i10 <|@
d <@d|@=== Debug Properties ===
nodeSourcePosition: at java.util.ArrayList.contains(ArrayList.java:304) [bci: 5]
stamp: i32 [0 - 1] ⇈0000000000000001
=== Inputs ===
condition: v8 
trueValue: i7 
falseValue: i9 
=== Succesors ===
=== Usages ===
v11 
=== Predecessor ===
- >@ <|@
instruction <@Conditional|@org.graalvm.compiler.nodes.calc.ConditionalNode>@ condition: v8 trueValue: i7 falseValue: i9  <|@  <|@
f <@*|@fixed>@ <|@
tid v11 <|@
d <@d|@=== Debug Properties ===
nodeSourcePosition: at java.util.ArrayList.contains(ArrayList.java:304) [bci: 13]
stamp: void
=== Inputs ===
result: i10 
memoryMap: - 
=== Succesors ===
=== Usages ===
=== Predecessor ===
i5 >@ <|@
instruction <@Return|@org.graalvm.compiler.nodes.ReturnNode>@ result: i10 memoryMap: -  <|@  <|@
    end_IR
  end_block
end_cfg
begin_cfg
  name "After LIR generation"
  begin_block
    name "B0"
    from_bci -1
    to_bci -1
    predecessors 
    successors 
    xhandlers
    flags 
    probability 4607182418800017408
    begin_IR
      HIR
f <@#|@fixed with next>@ <|@
tid v0 <|@
d <@d|@=== Debug Properties ===
stamp: void
=== Inputs ===
stateAfter: - 
=== Succesors ===
next: i5 
=== Usages ===
=== Predecessor ===
- >@ <|@
instruction <@StartNode|@org.graalvm.compiler.nodes.StartNode>@ stateAfter: - #next: i5  <|@  <|@
f <@~|@floating>@ <|@
tid a1 <|@
result v0|QWORD[.] <|@
d <@d|@=== Debug Properties ===
index: 0
stamp: a!# Ljava/util/ArrayList;
uncheckedStamp: [null]
=== Inputs ===
=== Succesors ===
=== Usages ===
v12 
=== Predecessor ===
- >@ <|@
instruction <@Parameter|@org.graalvm.compiler.nodes.ParameterNode>@  <|@  <|@
f <@~|@floating>@ <|@
tid a2 <|@
result v1|QWORD[.] <|@
d <@d|@=== Debug Properties ===
index: 1
stamp: a Ljava/lang/Object;
uncheckedStamp: [null]
=== Inputs ===
=== Succesors ===
=== Usages ===
v12 
=== Predecessor ===
- >@ <|@
instruction <@Parameter|@org.graalvm.compiler.nodes.ParameterNode>@  <|@  <|@
tid v12 <|@
d <@d|@=== Debug Properties ===
callType: JavaCall
invokeKind: Special
nodeSourcePosition: at java.util.ArrayList.contains(ArrayList.java:304) [bci: 2]
returnStamp: i32
signature: [Ljdk.vm.ci.meta.JavaType;@6093892f
stamp: void
targetMethod: HotSpotMethod<ArrayList.indexOf(Object)>
=== Inputs ===
arguments: a1 a2 
=== Succesors ===
=== Usages ===
i5 
=== Predecessor ===
- >@ <|@
instruction <@HotSpotDirectCallTarget|@org.graalvm.compiler.hotspot.nodes.HotSpotDirectCallTargetNode>@ arguments: a1 a2  <|@  <|@
tid ?13 <|@
d <@d|@=== Debug Properties ===
bci: 2
code: ResolvedJavaMethodBytecode<ArrayList.contains(Object)>
duringCall: true
localsSize: 2
locksSize: 0
rethrowException: false
sourceFile: ArrayList.java
sourceLine: 304
stackSize: 0
=== Inputs ===
outerFrameState: - 
values: - - 
=== Succesors ===
=== Usages ===
i5 
=== Predecessor ===
- >@ <|@
instruction <@FrameState|@org.graalvm.compiler.nodes.FrameState>@ outerFrameState: - values: - -  <|@  <|@
f <@#|@fixed with next>@ <|@
tid i5 <|@
result v2|DWORD <|@
d <@d|@=== Debug Properties ===
bci: 2
nodeSourcePosition: at java.util.ArrayList.contains(ArrayList.java:304) [bci: 2]
polymorphic: false
stamp: i32
targetMethod: Direct#ArrayList.indexOf
useForInlining: true
=== Inputs ===
stateAfter: - 
classInit: - 
callTarget: v12 
stateDuring: ?13 
=== Succesors ===
next: v11 
=== Usages ===
v8 
=== Predecessor ===
v0 >@ <|@
instruction <@Invoke|@org.graalvm.compiler.nodes.InvokeNode>@ stateAfter: - classInit: - callTarget: v12 stateDuring: ?13 #next: v11  <|@  <|@
f <@~|@floating>@ <|@
tid i7 <|@
result int[0|0x0] <|@
d <@d|@=== Debug Properties ===
isDefaultStable: false
nodeSourcePosition: at java.util.ArrayList.contains(ArrayList.java:304) [bci: 5]
rawvalue: 0
stableDimension: 0
stamp: i32 [0] ⇈0000000000000000
stampKind: i32
value: int[0|0x0]
=== Inputs ===
=== Succesors ===
=== Usages ===
v8 i10 
=== Predecessor ===
- >@ <|@
instruction <@Constant|@org.graalvm.compiler.nodes.ConstantNode>@  <|@  <|@
f <@~|@floating>@ <|@
tid v8 <|@
d <@d|@=== Debug Properties ===
condition: LT
nodeSourcePosition: at java.util.ArrayList.contains(ArrayList.java:304) [bci: 5]
op: org.graalvm.compiler.nodes.calc.IntegerLessThanNode$LessThanOp@7cc8d043
stamp: void
unorderedIsTrue: false
=== Inputs ===
x: i5 
y: i7 
=== Succesors ===
=== Usages ===
i10 
=== Predecessor ===
- >@ <|@
instruction <@<|@org.graalvm.compiler.nodes.calc.IntegerLessThanNode>@ x: i5 y: i7  <|@  <|@
f <@~|@floating>@ <|@
tid i9 <|@
result int[1|0x1] <|@
d <@d|@=== Debug Properties ===
isDefaultStable: false
nodeSourcePosition: at java.util.ArrayList.contains(ArrayList.java:304) [bci: 5]
rawvalue: 1
stableDimension: 0
stamp: i32 [1] ⇊0000000000000001 ⇈0000000000000001
stampKind: i32
value: int[1|0x1]
=== Inputs ===
=== Succesors ===
=== Usages ===
i10 
=== Predecessor ===
- >@ <|@
instruction <@Constant|@org.graalvm.compiler.nodes.ConstantNode>@  <|@  <|@
f <@~|@floating>@ <|@
tid i10 <|@
result v3|DWORD <|@
d <@d|@=== Debug Properties ===
nodeSourcePosition: at java.util.ArrayList.contains(ArrayList.java:304) [bci: 5]
stamp: i32 [0 - 1] ⇈0000000000000001
=== Inputs ===
condition: v8 
trueValue: i7 
falseValue: i9 
=== Succesors ===
=== Usages ===
v11 
=== Predecessor ===
- >@ <|@
instruction <@Conditional|@org.graalvm.compiler.nodes.calc.ConditionalNode>@ condition: v8 trueValue: i7 falseValue: i9  <|@  <|@
f <@*|@fixed>@ <|@
tid v11 <|@
d <@d|@=== Debug Properties ===
nodeSourcePosition: at java.util.ArrayList.contains(ArrayList.java:304) [bci: 13]
stamp: void
=== Inputs ===
result: i10 
memoryMap: - 
=== Succesors ===
=== Usages ===
=== Predecessor ===
i5 >@ <|@
instruction <@Return|@org.graalvm.compiler.nodes.ReturnNode>@ result: i10 memoryMap: -  <|@  <|@
    end_IR
    begin_IR
      LIR
      nr   -1  <|@ instruction [rsi|QWORD[.], rdx|QWORD[.], rbp|QWORD] = LABEL numbPhis: 0 align: false label: ? <|@ <|@
      nr   -1  <|@ instruction stack:16|QWORD = MOVE rbp|QWORD moveKind: QWORD <|@ <|@
      nr   -1  <|@ instruction [] = HOTSPOTLOCKSTACK frameMapBuilder: org.graalvm.compiler.lir.amd64.AMD64FrameMapBuilder@8ce87e9 slotKind: QWORD <|@ <|@
      nr   -1  <|@ instruction v0|QWORD[.] = MOVE rsi|QWORD[.] moveKind: QWORD <|@ <|@
      nr   -1  <|@ instruction v1|QWORD[.] = MOVE rdx|QWORD[.] moveKind: QWORD <|@ <|@
      nr   -1  <|@ instruction rsi|QWORD[.] = MOVE v0|QWORD[.] moveKind: QWORD <|@ <|@
      nr   -1  <|@ instruction rdx|QWORD[.] = MOVE v1|QWORD[.] moveKind: QWORD <|@ <|@
      nr   -1  <|@ st <@st|@java.util.ArrayList.contains(ArrayList.java:304) [bci: 2]
locals: - - 
>@ <|@ instruction rax|DWORD = CALL_DIRECT [rsi|QWORD[.], rdx|QWORD[.]] [] callTarget: HotSpotMethod<ArrayList.indexOf(Object)> invokeKind: Special config: org.graalvm.compiler.hotspot.GraalHotSpotVMConfig@7222fe45 state [bci:2] <|@ <|@
      nr   -1  <|@ instruction v2|DWORD = MOVE rax|DWORD moveKind: DWORD <|@ <|@
      nr   -1  <|@ instruction TEST (x: v2|DWORD, y: v2|DWORD) size: DWORD <|@ <|@
      nr   -1  <|@ instruction v3|DWORD = SETCC condition: >= <|@ <|@
      nr   -1  <|@ instruction rax|DWORD = MOVE v3|DWORD moveKind: DWORD <|@ <|@
      nr   -1  <|@ instruction RETURN (savedRbp: stack:16|QWORD, value: rax|DWORD) isStub: false thread: r15 scratchForSafepointOnReturn: rcx config: org.graalvm.compiler.hotspot.GraalHotSpotVMConfig@7222fe45 <|@ <|@
    end_IR
  end_block
end_cfg
begin_cfg
  name "After PreAllocationOptimizationStage"
  begin_block
    name "B0"
    from_bci -1
    to_bci -1
    predecessors 
    successors 
    xhandlers
    flags 
    probability 4607182418800017408
    begin_IR
      LIR
      nr   -1  <|@ instruction [rsi|QWORD[.], rdx|QWORD[.], rbp|QWORD] = LABEL numbPhis: 0 align: false label: ? <|@ <|@
      nr   -1  <|@ instruction stack:16|QWORD = MOVE rbp|QWORD moveKind: QWORD <|@ <|@
      nr   -1  <|@ instruction [] = HOTSPOTLOCKSTACK frameMapBuilder: org.graalvm.compiler.lir.amd64.AMD64FrameMapBuilder@8ce87e9 slotKind: QWORD <|@ <|@
      nr   -1  <|@ instruction v0|QWORD[.] = MOVE rsi|QWORD[.] moveKind: QWORD <|@ <|@
      nr   -1  <|@ instruction v1|QWORD[.] = MOVE rdx|QWORD[.] moveKind: QWORD <|@ <|@
      nr   -1  <|@ instruction rsi|QWORD[.] = MOVE v0|QWORD[.] moveKind: QWORD <|@ <|@
      nr   -1  <|@ instruction rdx|QWORD[.] = MOVE v1|QWORD[.] moveKind: QWORD <|@ <|@
      nr   -1  <|@ st <@st|@java.util.ArrayList.contains(ArrayList.java:304) [bci: 2]
locals: - - 
>@ <|@ instruction rax|DWORD = CALL_DIRECT [rsi|QWORD[.], rdx|QWORD[.]] [] callTarget: HotSpotMethod<ArrayList.indexOf(Object)> invokeKind: Special config: org.graalvm.compiler.hotspot.GraalHotSpotVMConfig@7222fe45 state [bci:2] <|@ <|@
      nr   -1  <|@ instruction v2|DWORD = MOVE rax|DWORD moveKind: DWORD <|@ <|@
      nr   -1  <|@ instruction TEST (x: v2|DWORD, y: v2|DWORD) size: DWORD <|@ <|@
      nr   -1  <|@ instruction v3|DWORD = SETCC condition: >= <|@ <|@
      nr   -1  <|@ instruction rax|DWORD = MOVE v3|DWORD moveKind: DWORD <|@ <|@
      nr   -1  <|@ instruction RETURN (savedRbp: stack:16|QWORD, value: rax|DWORD) isStub: false thread: r15 scratchForSafepointOnReturn: rcx config: org.graalvm.compiler.hotspot.GraalHotSpotVMConfig@7222fe45 <|@ <|@
    end_IR
  end_block
end_cfg
begin_bytecodes
     0: aload_0       
     1: aload_1       
     2: invokevirtual #21         // indexOf:(java.lang.Object)int
     5: iflt          12
     8: iconst_1      
     9: goto          13
    12: iconst_0      
    13: ireturn       
   <|@
end_bytecodes
begin_cfg
  name "After AllocationStage"
  begin_block
    name "B0"
    from_bci -1
    to_bci -1
    predecessors 
    successors 
    xhandlers
    flags 
    probability 4607182418800017408
    begin_IR
      LIR
      nr    0  <|@ instruction [rsi|QWORD[.], rdx|QWORD[.], rbp|QWORD] = LABEL numbPhis: 0 align: false label: ? <|@ <|@
      nr    2  <|@ instruction stack:16|QWORD = MOVE rbp|QWORD moveKind: QWORD <|@ <|@
      nr    4  <|@ instruction [] = HOTSPOTLOCKSTACK frameMapBuilder: org.graalvm.compiler.lir.amd64.AMD64FrameMapBuilder@8ce87e9 slotKind: QWORD <|@ <|@
      nr   14  <|@ st <@st|@reference-map: []
live-base-pointers: []
java.util.ArrayList.contains(ArrayList.java:304) [bci: 2]
locals: - - 
>@ <|@ instruction rax|DWORD = CALL_DIRECT [rsi|QWORD[.], rdx|QWORD[.]] [] callTarget: HotSpotMethod<ArrayList.indexOf(Object)> invokeKind: Special config: org.graalvm.compiler.hotspot.GraalHotSpotVMConfig@7222fe45 state [bci:2] <|@ <|@
      nr   18  <|@ instruction TEST (x: rax|DWORD, y: rax|DWORD) size: DWORD <|@ <|@
      nr   20  <|@ instruction rax|DWORD = SETCC condition: >= <|@ <|@
      nr   24  <|@ instruction RETURN (savedRbp: stack:16|QWORD, value: rax|DWORD) isStub: false thread: r15 scratchForSafepointOnReturn: rcx config: org.graalvm.compiler.hotspot.GraalHotSpotVMConfig@7222fe45 <|@ <|@
    end_IR
  end_block
end_cfg
begin_bytecodes
     0: aload_0       
     1: aload_1       
     2: invokevirtual #21         // indexOf:(java.lang.Object)int
     5: iflt          12
     8: iconst_1      
     9: goto          13
    12: iconst_0      
    13: ireturn       
   <|@
end_bytecodes
begin_cfg
  name "After PostAllocationOptimizationStage"
  begin_block
    name "B0"
    from_bci -1
    to_bci -1
    predecessors 
    successors 
    xhandlers
    flags 
    probability 4607182418800017408
    begin_IR
      LIR
      nr    0  <|@ instruction [rsi|QWORD[.], rdx|QWORD[.], rbp|QWORD] = LABEL numbPhis: 0 align: false label: ? <|@ <|@
      nr    2  <|@ instruction stack:16|QWORD = MOVE rbp|QWORD moveKind: QWORD <|@ <|@
      nr    4  <|@ instruction [] = HOTSPOTLOCKSTACK frameMapBuilder: org.graalvm.compiler.lir.amd64.AMD64FrameMapBuilder@8ce87e9 slotKind: QWORD <|@ <|@
      nr   14  <|@ st <@st|@reference-map: []
live-base-pointers: []
java.util.ArrayList.contains(ArrayList.java:304) [bci: 2]
locals: - - 
>@ <|@ instruction rax|DWORD = CALL_DIRECT [rsi|QWORD[.], rdx|QWORD[.]] [] callTarget: HotSpotMethod<ArrayList.indexOf(Object)> invokeKind: Special config: org.graalvm.compiler.hotspot.GraalHotSpotVMConfig@7222fe45 state [bci:2] <|@ <|@
      nr   18  <|@ instruction TEST (x: rax|DWORD, y: rax|DWORD) size: DWORD <|@ <|@
      nr   20  <|@ instruction rax|DWORD = SETCC condition: >= <|@ <|@
      nr   24  <|@ instruction RETURN (savedRbp: stack:16|QWORD, value: rax|DWORD) isStub: false thread: r15 scratchForSafepointOnReturn: rcx config: org.graalvm.compiler.hotspot.GraalHotSpotVMConfig@7222fe45 <|@ <|@
    end_IR
  end_block
end_cfg
begin_bytecodes
     0: aload_0       
     1: aload_1       
     2: invokevirtual #21         // indexOf:(java.lang.Object)int
     5: iflt          12
     8: iconst_1      
     9: goto          13
    12: iconst_0      
    13: ireturn       
   <|@
end_bytecodes
begin_cfg
  name "After code generation"
end_cfg
begin_nmethod
  <<<HexCodeFile
  Platform AMD64 64  <||@
  HexCode 0 448b560849c1e203493bc20f85efffffff900f1f80000000000f1f800000000089842400c0feff4883ec1848896c24100f1f8000000000e8000000009085c00f9dc00fb6c0488b6c24104883c418850500000000c5f877c3e80000000090e80000000090  <||@
  Comment 0 2  <||@
  Comment 11 {Field[name=CompilerToVM::Data::SharedRuntime_ic_miss_stub, type=address, offset=0, address=0x105aa1f78, value=0x106805e60]:0x106805e60}  <||@
  Comment 32 [stack overflow check]  <||@
  Comment 32 3  <||@
  Comment 32 1  <||@
  Comment 43 block B0 null  <||@
  Comment 43 0 [rsi|QWORD[.], rdx|QWORD[.], rbp|QWORD] = LABEL numbPhis: 0 align: false label: ?  <||@
  Comment 43 2 stack:16|QWORD = MOVE rbp|QWORD moveKind: QWORD  <||@
  Comment 48 4 [] = HOTSPOTLOCKSTACK frameMapBuilder: org.graalvm.compiler.lir.amd64.AMD64FrameMapBuilder@8ce87e9 slotKind: QWORD  <||@
  Comment 48 14 rax|DWORD = CALL_DIRECT [rsi|QWORD[.], rdx|QWORD[.]] [] callTarget: HotSpotMethod<ArrayList.indexOf(Object)> invokeKind: Special config: org.graalvm.compiler.hotspot.GraalHotSpotVMConfig@7222fe45 state [bci:2]  <||@
  Comment 48 9  <||@
  Comment 55 {HotSpotMethod<ArrayList.indexOf(Object)>}  <||@
  Comment 60 []at java.util.ArrayList.contains(ArrayList.java:304) [bci: 2, duringCall: true, rethrow: false]
              |0  |1 
     locals:  |-  |-   <||@
  Comment 61 18 TEST (x: rax|DWORD, y: rax|DWORD) size: DWORD  <||@
  Comment 63 20 rax|DWORD = SETCC condition: >=  <||@
  Comment 69 24 RETURN (savedRbp: stack:16|QWORD, value: rax|DWORD) isStub: false thread: r15 scratchForSafepointOnReturn: rcx config: org.graalvm.compiler.hotspot.GraalHotSpotVMConfig@7222fe45  <||@
  Comment 78 12  <||@
  Comment 88 {Stub<ExceptionHandlerStub.exceptionHandler>@0x106c4a620:CallingConvention[rax|QWORD[.], rdx|QWORD]:CallingConvention[rax|QWORD[.], rdx|QWORD]; temps=rdi|ILLEGAL,xmm0|ILLEGAL,xmm1|ILLEGAL,xmm2|ILLEGAL,xmm3|ILLEGAL,xmm4|ILLEGAL,xmm5|ILLEGAL,xmm6|ILLEGAL,xmm7|ILLEGAL,xmm8|ILLEGAL,xmm9|ILLEGAL,xmm10|ILLEGAL,xmm11|ILLEGAL,xmm12|ILLEGAL,xmm13|ILLEGAL,xmm14|ILLEGAL,xmm15|ILLEGAL,xmm16|ILLEGAL,xmm17|ILLEGAL,xmm18|ILLEGAL,xmm19|ILLEGAL,xmm20|ILLEGAL,xmm21|ILLEGAL,xmm22|ILLEGAL,xmm23|ILLEGAL,xmm24|ILLEGAL,xmm25|ILLEGAL,xmm26|ILLEGAL,xmm27|ILLEGAL,xmm28|ILLEGAL,xmm29|ILLEGAL,xmm30|ILLEGAL,xmm31|ILLEGAL,rax|ILLEGAL,rcx|ILLEGAL,rdx|ILLEGAL,rsi|ILLEGAL,r8|ILLEGAL,r9|ILLEGAL,r10|ILLEGAL,r11|ILLEGAL}  <||@
  Comment 88 4  <||@
  Comment 94 {Field[name=CompilerToVM::Data::SharedRuntime_deopt_blob_unpack, type=address, offset=0, address=0x105aa1f88, value=0x106807500]:0x106807500}  <||@
  Comment 94 5  <||@
  HexCodeFile>>> <|@
end_nmethod
begin_compilation
  name " HotSpotCompilation-9450[java.util.ArrayList.contains(Object)]"
  method "HotSpotCompilation-9450[java.util.ArrayList.contains(Object)]"
  date 1527005213421
end_compilation
begin_cfg
  name "After code installation"
end_cfg
begin_nmethod
  <<<HexCodeFile
  Platform AMD64 64  <||@
  HexCode 106c296a0 448b560849c1e203493bc20f85afc7bdff900f1f80000000000f1f800000000089842400c0feff4883ec1848896c24100f1f8000000000e8c4c9bdff9085c00f9dc00fb6c0488b6c24104883c41885051259c6fdc5f877c3e8230f020090e8fdddbdff90f4f4f4f4f4f4f4f4f4f4f4f4f4f4f4f4f4f4f4f4f4f4f4f4f4f4f4f448bb0000000000000000e9fbfffffff4  <||@
  Comment 0 2  <||@
  Comment 11 {Field[name=CompilerToVM::Data::SharedRuntime_ic_miss_stub, type=address, offset=0, address=0x105aa1f78, value=0x106805e60]:0x106805e60}  <||@
  Comment 32 [stack overflow check]  <||@
  Comment 32 3  <||@
  Comment 32 1  <||@
  Comment 43 block B0 null  <||@
  Comment 43 0 [rsi|QWORD[.], rdx|QWORD[.], rbp|QWORD] = LABEL numbPhis: 0 align: false label: ?  <||@
  Comment 43 2 stack:16|QWORD = MOVE rbp|QWORD moveKind: QWORD  <||@
  Comment 48 4 [] = HOTSPOTLOCKSTACK frameMapBuilder: org.graalvm.compiler.lir.amd64.AMD64FrameMapBuilder@8ce87e9 slotKind: QWORD  <||@
  Comment 48 14 rax|DWORD = CALL_DIRECT [rsi|QWORD[.], rdx|QWORD[.]] [] callTarget: HotSpotMethod<ArrayList.indexOf(Object)> invokeKind: Special config: org.graalvm.compiler.hotspot.GraalHotSpotVMConfig@7222fe45 state [bci:2]  <||@
  Comment 48 9  <||@
  Comment 55 {HotSpotMethod<ArrayList.indexOf(Object)>}  <||@
  Comment 60 []at java.util.ArrayList.contains(ArrayList.java:304) [bci: 2, duringCall: true, rethrow: false]
              |0  |1 
     locals:  |-  |-   <||@
  Comment 61 18 TEST (x: rax|DWORD, y: rax|DWORD) size: DWORD  <||@
  Comment 63 20 rax|DWORD = SETCC condition: >=  <||@
  Comment 69 24 RETURN (savedRbp: stack:16|QWORD, value: rax|DWORD) isStub: false thread: r15 scratchForSafepointOnReturn: rcx config: org.graalvm.compiler.hotspot.GraalHotSpotVMConfig@7222fe45  <||@
  Comment 78 12  <||@
  Comment 88 {Stub<ExceptionHandlerStub.exceptionHandler>@0x106c4a620:CallingConvention[rax|QWORD[.], rdx|QWORD]:CallingConvention[rax|QWORD[.], rdx|QWORD]; temps=rdi|ILLEGAL,xmm0|ILLEGAL,xmm1|ILLEGAL,xmm2|ILLEGAL,xmm3|ILLEGAL,xmm4|ILLEGAL,xmm5|ILLEGAL,xmm6|ILLEGAL,xmm7|ILLEGAL,xmm8|ILLEGAL,xmm9|ILLEGAL,xmm10|ILLEGAL,xmm11|ILLEGAL,xmm12|ILLEGAL,xmm13|ILLEGAL,xmm14|ILLEGAL,xmm15|ILLEGAL,xmm16|ILLEGAL,xmm17|ILLEGAL,xmm18|ILLEGAL,xmm19|ILLEGAL,xmm20|ILLEGAL,xmm21|ILLEGAL,xmm22|ILLEGAL,xmm23|ILLEGAL,xmm24|ILLEGAL,xmm25|ILLEGAL,xmm26|ILLEGAL,xmm27|ILLEGAL,xmm28|ILLEGAL,xmm29|ILLEGAL,xmm30|ILLEGAL,xmm31|ILLEGAL,rax|ILLEGAL,rcx|ILLEGAL,rdx|ILLEGAL,rsi|ILLEGAL,r8|ILLEGAL,r9|ILLEGAL,r10|ILLEGAL,r11|ILLEGAL}  <||@
  Comment 88 4  <||@
  Comment 94 {Field[name=CompilerToVM::Data::SharedRuntime_deopt_blob_unpack, type=address, offset=0, address=0x105aa1f88, value=0x106807500]:0x106807500}  <||@
  Comment 94 5  <||@
  HexCodeFile>>> <|@
end_nmethod
