begin_compilation
  name " HotSpotCompilation-8616[java.lang.String.lastIndexOf(char[], int, int, char[], int, int, int)]"
  method "HotSpotCompilation-8616[java.lang.String.lastIndexOf(char[], int, int, char[], int, int, int)]"
  date 1527005161314
end_compilation
begin_cfg
  name "Final HIR schedule"
  begin_block
    name "B0"
    from_bci -1
    to_bci -1
    predecessors 
    successors "B1" "B2" 
    xhandlers
    flags 
    probability 4607182418800017408
    begin_IR
      HIR
f <@#|@fixed with next>@ <|@
tid v0 <|@
d <@d|@=== Debug Properties ===
stamp: void
=== Inputs ===
stateAfter: - 
=== Succesors ===
next: v157 
=== Usages ===
=== Predecessor ===
- >@ <|@
instruction <@StartNode|@org.graalvm.compiler.nodes.StartNode>@ stateAfter: - #next: v157  <|@  <|@
f <@~|@floating>@ <|@
tid a1 <|@
d <@d|@=== Debug Properties ===
index: 0
stamp: a# [C
uncheckedStamp: [null]
=== Inputs ===
=== Succesors ===
=== Usages ===
?8 ?29 v241 v105 v240 
=== Predecessor ===
- >@ <|@
instruction <@Parameter|@org.graalvm.compiler.nodes.ParameterNode>@  <|@  <|@
f <@~|@floating>@ <|@
tid i2 <|@
d <@d|@=== Debug Properties ===
index: 1
stamp: i32
uncheckedStamp: [null]
=== Inputs ===
=== Succesors ===
=== Usages ===
?8 i22 ?29 i68 
=== Predecessor ===
- >@ <|@
instruction <@Parameter|@org.graalvm.compiler.nodes.ParameterNode>@  <|@  <|@
f <@~|@floating>@ <|@
tid i3 <|@
d <@d|@=== Debug Properties ===
index: 2
stamp: i32
uncheckedStamp: [null]
=== Inputs ===
=== Succesors ===
=== Usages ===
?8 i9 
=== Predecessor ===
- >@ <|@
instruction <@Parameter|@org.graalvm.compiler.nodes.ParameterNode>@  <|@  <|@
f <@~|@floating>@ <|@
tid a4 <|@
d <@d|@=== Debug Properties ===
index: 3
stamp: a# [C
uncheckedStamp: [null]
=== Inputs ===
=== Succesors ===
=== Usages ===
?8 v239 ?29 v238 
=== Predecessor ===
- >@ <|@
instruction <@Parameter|@org.graalvm.compiler.nodes.ParameterNode>@  <|@  <|@
f <@~|@floating>@ <|@
tid i5 <|@
d <@d|@=== Debug Properties ===
index: 4
stamp: i32
uncheckedStamp: [null]
=== Inputs ===
=== Succesors ===
=== Usages ===
?8 i17 
=== Predecessor ===
- >@ <|@
instruction <@Parameter|@org.graalvm.compiler.nodes.ParameterNode>@  <|@  <|@
f <@~|@floating>@ <|@
tid i6 <|@
d <@d|@=== Debug Properties ===
index: 5
stamp: i32
uncheckedStamp: [null]
=== Inputs ===
=== Succesors ===
=== Usages ===
?8 i9 v15 i17 i22 ?29 i50 
=== Predecessor ===
- >@ <|@
instruction <@Parameter|@org.graalvm.compiler.nodes.ParameterNode>@  <|@  <|@
f <@~|@floating>@ <|@
tid i7 <|@
d <@d|@=== Debug Properties ===
index: 6
stamp: i32
uncheckedStamp: [null]
=== Inputs ===
=== Succesors ===
=== Usages ===
?8 v11 v13 
=== Predecessor ===
- >@ <|@
instruction <@Parameter|@org.graalvm.compiler.nodes.ParameterNode>@  <|@  <|@
tid ?8 <|@
d <@d|@=== Debug Properties ===
bci: 0
code: ResolvedJavaMethodBytecode<String.lastIndexOf(char[], int, int, char[], int, int, int)>
duringCall: false
localsSize: 15
locksSize: 0
rethrowException: false
sourceFile: String.java
sourceLine: 1869
stackSize: 0
=== Inputs ===
outerFrameState: - 
values: a1 i2 i3 a4 i5 i6 i7 - - - - - - - - 
=== Succesors ===
=== Usages ===
v200 i234 
=== Predecessor ===
- >@ <|@
instruction <@FrameState|@org.graalvm.compiler.nodes.FrameState>@ outerFrameState: - values: a1 i2 i3 a4 i5 i6 i7 - - - - - - - -  <|@  <|@
f <@~|@floating>@ <|@
tid v105 <|@
d <@d|@=== Debug Properties ===
nodeSourcePosition: at java.lang.String.lastIndexOf(String.java:1888) [bci: 72]
stamp: void
=== Inputs ===
value: a1 
=== Succesors ===
=== Usages ===
v157 
=== Predecessor ===
- >@ <|@
instruction <@IsNull|@org.graalvm.compiler.nodes.calc.IsNullNode>@ value: a1  <|@  <|@
f <@*|@fixed>@ <|@
tid v157 <|@
d <@d|@=== Debug Properties ===
nodeSourcePosition: at java.lang.String.lastIndexOf(String.java:1888) [bci: 72]
stamp: void
trueSuccessorProbability: 0.0
=== Inputs ===
condition: v105 
=== Succesors ===
trueSuccessor: v156 
falseSuccessor: v154 
=== Usages ===
=== Predecessor ===
v0 >@ <|@
instruction <@If|@org.graalvm.compiler.nodes.IfNode>@ condition: v105 #trueSuccessor: v156 #falseSuccessor: v154  <|@  <|@
    end_IR
  end_block
  begin_block
    name "B1"
    from_bci -1
    to_bci -1
    predecessors "B0" 
    successors "B27" 
    xhandlers
    flags 
    probability 2355382605114769408
    begin_IR
      HIR
f <@#|@fixed with next>@ <|@
tid v156 <|@
d <@d|@=== Debug Properties ===
nodeSourcePosition: at java.lang.String.lastIndexOf(String.java:1888) [bci: 72]
stamp: void
=== Inputs ===
=== Succesors ===
next: v195 
=== Usages ===
=== Predecessor ===
v157 >@ <|@
instruction <@Begin|@org.graalvm.compiler.nodes.BeginNode>@ #next: v195  <|@  <|@
f <@~|@floating>@ <|@
tid a197 <|@
d <@d|@=== Debug Properties ===
isDefaultStable: false
rawvalue: d.a@506959935
stableDimension: 0
stamp: a!# Lcom/oracle/graal/enterprise/k/d$a;
stampKind: a -
value: Object[d.a@506959935]
=== Inputs ===
=== Succesors ===
=== Usages ===
a199 
=== Predecessor ===
- >@ <|@
instruction <@Constant|@org.graalvm.compiler.nodes.ConstantNode>@  <|@  <|@
f <@~|@floating>@ <|@
tid i196 <|@
d <@d|@=== Debug Properties ===
isDefaultStable: false
rawvalue: -27147
stableDimension: 0
stamp: i32 [-27147] ⇊00000000ffff95f5 ⇈00000000ffff95f5
stampKind: i32
value: int[-27147|0xffffffffffff95f5]
=== Inputs ===
=== Succesors ===
=== Usages ===
i198 
=== Predecessor ===
- >@ <|@
instruction <@Constant|@org.graalvm.compiler.nodes.ConstantNode>@  <|@  <|@
f <@*|@fixed>@ <|@
tid v195 <|@
d <@d|@=== Debug Properties ===
stamp: void
=== Inputs ===
=== Succesors ===
=== Usages ===
v194 
=== Predecessor ===
v156 >@ <|@
instruction <@EndNode|@org.graalvm.compiler.nodes.EndNode>@  <|@  <|@
    end_IR
  end_block
  begin_block
    name "B2"
    from_bci -1
    to_bci -1
    predecessors "B0" 
    successors "B3" "B4" 
    xhandlers
    flags 
    probability 4607182418800017408
    begin_IR
      HIR
f <@#|@fixed with next>@ <|@
tid v154 <|@
d <@d|@=== Debug Properties ===
nodeSourcePosition: at java.lang.String.lastIndexOf(String.java:1888) [bci: 72]
stamp: void
=== Inputs ===
=== Succesors ===
next: v161 
=== Usages ===
=== Predecessor ===
v157 >@ <|@
instruction <@Begin|@org.graalvm.compiler.nodes.BeginNode>@ #next: v161  <|@  <|@
f <@~|@floating>@ <|@
tid a203 <|@
d <@d|@=== Debug Properties ===
isDefaultStable: false
rawvalue: null
stableDimension: 0
stamp: a - NULL
stampKind: a -
value: Object[null]
=== Inputs ===
=== Succesors ===
=== Usages ===
a199 a199 a199 a199 a199 
=== Predecessor ===
- >@ <|@
instruction <@Constant|@org.graalvm.compiler.nodes.ConstantNode>@  <|@  <|@
f <@~|@floating>@ <|@
tid i22 <|@
d <@d|@=== Debug Properties ===
getOp: org.graalvm.compiler.nodes.calc.AddNode$$Lambda$15/1271304513@1406efde
nodeSourcePosition: at java.lang.String.lastIndexOf(String.java:1883) [bci: 50]
stamp: i32
=== Inputs ===
x: i2 
y: i6 
=== Succesors ===
=== Usages ===
i23 
=== Predecessor ===
- >@ <|@
instruction <@+|@org.graalvm.compiler.nodes.calc.AddNode>@ x: i2 y: i6  <|@  <|@
f <@~|@floating>@ <|@
tid i19 <|@
d <@d|@=== Debug Properties ===
isDefaultStable: false
nodeSourcePosition: at java.lang.String.lastIndexOf(String.java:1881) [bci: 38]
rawvalue: -1
stableDimension: 0
stamp: i32 [-1] ⇊00000000ffffffff
stampKind: i32
value: int[-1|0xffffffffffffffff]
=== Inputs ===
=== Succesors ===
=== Usages ===
i20 i23 i42 i50 v67 
=== Predecessor ===
- >@ <|@
instruction <@Constant|@org.graalvm.compiler.nodes.ConstantNode>@  <|@  <|@
f <@~|@floating>@ <|@
tid i23 <|@
d <@d|@=== Debug Properties ===
getOp: org.graalvm.compiler.nodes.calc.AddNode$$Lambda$15/1271304513@1406efde
nodeSourcePosition: at java.lang.String.lastIndexOf(String.java:1883) [bci: 52]
stamp: i32
=== Inputs ===
x: i22 
y: i19 
=== Succesors ===
=== Usages ===
i24 ?29 v30 v131 v148 
=== Predecessor ===
- >@ <|@
instruction <@+|@org.graalvm.compiler.nodes.calc.AddNode>@ x: i22 y: i19  <|@  <|@
f <@~|@floating>@ <|@
tid i130 <|@
d <@d|@=== Debug Properties ===
isDefaultStable: false
nodeSourcePosition: at java.lang.String.lastIndexOf(String.java:1888) [bci: 62]
rawvalue: -2147483645
stableDimension: 0
stamp: i32 [-2147483645] ⇊0000000080000003 ⇈0000000080000003
stampKind: i32
value: int[-2147483645|0xffffffff80000003]
=== Inputs ===
=== Succesors ===
=== Usages ===
v131 
=== Predecessor ===
- >@ <|@
instruction <@Constant|@org.graalvm.compiler.nodes.ConstantNode>@  <|@  <|@
f <@~|@floating>@ <|@
tid v131 <|@
d <@d|@=== Debug Properties ===
condition: LT
nodeSourcePosition: at java.lang.String.lastIndexOf(String.java:1888) [bci: 62]
op: org.graalvm.compiler.nodes.calc.IntegerLessThanNode$LessThanOp@7cc8d043
stamp: void
unorderedIsTrue: false
=== Inputs ===
x: i23 
y: i130 
=== Succesors ===
=== Usages ===
v161 
=== Predecessor ===
- >@ <|@
instruction <@<|@org.graalvm.compiler.nodes.calc.IntegerLessThanNode>@ x: i23 y: i130  <|@  <|@
f <@*|@fixed>@ <|@
tid v161 <|@
d <@d|@=== Debug Properties ===
nodeSourcePosition: at java.lang.String.lastIndexOf(String.java:1888) [bci: 62]
stamp: void
trueSuccessorProbability: 0.0
=== Inputs ===
condition: v131 
=== Succesors ===
trueSuccessor: v160 
falseSuccessor: v158 
=== Usages ===
=== Predecessor ===
v154 >@ <|@
instruction <@If|@org.graalvm.compiler.nodes.IfNode>@ condition: v131 #trueSuccessor: v160 #falseSuccessor: v158  <|@  <|@
    end_IR
  end_block
  begin_block
    name "B3"
    from_bci -1
    to_bci -1
    predecessors "B2" 
    successors "B27" 
    xhandlers
    flags 
    probability 2355382605114769408
    begin_IR
      HIR
f <@#|@fixed with next>@ <|@
tid v160 <|@
d <@d|@=== Debug Properties ===
nodeSourcePosition: at java.lang.String.lastIndexOf(String.java:1888) [bci: 62]
stamp: void
=== Inputs ===
=== Succesors ===
next: v201 
=== Usages ===
=== Predecessor ===
v161 >@ <|@
instruction <@Begin|@org.graalvm.compiler.nodes.BeginNode>@ #next: v201  <|@  <|@
f <@~|@floating>@ <|@
tid i202 <|@
d <@d|@=== Debug Properties ===
isDefaultStable: false
rawvalue: -33924
stableDimension: 0
stamp: i32 [-33924] ⇊00000000ffff7b7c ⇈00000000ffff7b7c
stampKind: i32
value: int[-33924|0xffffffffffff7b7c]
=== Inputs ===
=== Succesors ===
=== Usages ===
i198 
=== Predecessor ===
- >@ <|@
instruction <@Constant|@org.graalvm.compiler.nodes.ConstantNode>@  <|@  <|@
f <@*|@fixed>@ <|@
tid v201 <|@
d <@d|@=== Debug Properties ===
stamp: void
=== Inputs ===
=== Succesors ===
=== Usages ===
v194 
=== Predecessor ===
v160 >@ <|@
instruction <@EndNode|@org.graalvm.compiler.nodes.EndNode>@  <|@  <|@
    end_IR
  end_block
  begin_block
    name "B4"
    from_bci -1
    to_bci -1
    predecessors "B2" 
    successors "B5" "B6" 
    xhandlers
    flags 
    probability 4607182418800017408
    begin_IR
      HIR
f <@#|@fixed with next>@ <|@
tid v158 <|@
d <@d|@=== Debug Properties ===
nodeSourcePosition: at java.lang.String.lastIndexOf(String.java:1888) [bci: 62]
stamp: void
=== Inputs ===
=== Succesors ===
next: v224 
=== Usages ===
v27 j143 
=== Predecessor ===
v161 >@ <|@
instruction <@Begin|@org.graalvm.compiler.nodes.BeginNode>@ #next: v224  <|@  <|@
f <@~|@floating>@ <|@
tid i18 <|@
d <@d|@=== Debug Properties ===
isDefaultStable: false
nodeSourcePosition: at java.lang.String.lastIndexOf(String.java:1881) [bci: 37]
rawvalue: 1
stableDimension: 0
stamp: i32 [1] ⇊0000000000000001 ⇈0000000000000001
stampKind: i32
value: int[1|0x1]
=== Inputs ===
=== Succesors ===
=== Usages ===
i69 i137 
=== Predecessor ===
- >@ <|@
instruction <@Constant|@org.graalvm.compiler.nodes.ConstantNode>@  <|@  <|@
f <@~|@floating>@ <|@
tid i9 <|@
d <@d|@=== Debug Properties ===
getOp: org.graalvm.compiler.nodes.calc.SubNode$$Lambda$64/1952983589@24889bdf
nodeSourcePosition: at java.lang.String.lastIndexOf(String.java:1869) [bci: 3]
stamp: i32
=== Inputs ===
x: i3 
y: i6 
=== Succesors ===
=== Usages ===
v13 i24 i137 
=== Predecessor ===
- >@ <|@
instruction <@-|@org.graalvm.compiler.nodes.calc.SubNode>@ x: i3 y: i6  <|@  <|@
f <@~|@floating>@ <|@
tid i24 <|@
d <@d|@=== Debug Properties ===
getOp: org.graalvm.compiler.nodes.calc.AddNode$$Lambda$15/1271304513@1406efde
nodeSourcePosition: at java.lang.String.lastIndexOf(String.java:1884) [bci: 59]
stamp: i32
=== Inputs ===
x: i9 
y: i23 
=== Succesors ===
=== Usages ===
i28 j136 v145 v148 
=== Predecessor ===
- >@ <|@
instruction <@+|@org.graalvm.compiler.nodes.calc.AddNode>@ x: i9 y: i23  <|@  <|@
f <@~|@floating>@ <|@
tid v148 <|@
d <@d|@=== Debug Properties ===
condition: LT
op: org.graalvm.compiler.nodes.calc.IntegerLessThanNode$LessThanOp@7cc8d043
stamp: void
unorderedIsTrue: false
=== Inputs ===
x: i24 
y: i23 
=== Succesors ===
=== Usages ===
v224 
=== Predecessor ===
- >@ <|@
instruction <@<|@org.graalvm.compiler.nodes.calc.IntegerLessThanNode>@ x: i24 y: i23  <|@  <|@
f <@*|@fixed>@ <|@
tid v224 <|@
d <@d|@=== Debug Properties ===
nodeSourcePosition: at java.lang.String.lastIndexOf(String.java:1888) [bci: 72]
stamp: void
trueSuccessorProbability: 0.5
=== Inputs ===
condition: v148 
=== Succesors ===
trueSuccessor: v220 
falseSuccessor: v223 
=== Usages ===
=== Predecessor ===
v158 >@ <|@
instruction <@If|@org.graalvm.compiler.nodes.IfNode>@ condition: v148 #trueSuccessor: v220 #falseSuccessor: v223  <|@  <|@
    end_IR
  end_block
  begin_block
    name "B5"
    from_bci -1
    to_bci -1
    predecessors "B4" 
    successors "B9" 
    xhandlers
    flags 
    probability 4602678819172646912
    begin_IR
      HIR
f <@#|@fixed with next>@ <|@
tid v220 <|@
d <@d|@=== Debug Properties ===
nodeSourcePosition: at java.lang.String.lastIndexOf(String.java:1888) [bci: 72]
stamp: void
=== Inputs ===
=== Succesors ===
next: v218 
=== Usages ===
=== Predecessor ===
v224 >@ <|@
instruction <@Begin|@org.graalvm.compiler.nodes.BeginNode>@ #next: v218  <|@  <|@
f <@*|@fixed>@ <|@
tid v218 <|@
d <@d|@=== Debug Properties ===
nodeSourcePosition: at java.lang.String.lastIndexOf(String.java:1888) [bci: 72]
stamp: void
=== Inputs ===
=== Succesors ===
=== Usages ===
v217 
=== Predecessor ===
v220 >@ <|@
instruction <@EndNode|@org.graalvm.compiler.nodes.EndNode>@  <|@  <|@
    end_IR
  end_block
  begin_block
    name "B6"
    from_bci -1
    to_bci -1
    predecessors "B4" 
    successors "B7" "B26" 
    xhandlers
    flags 
    probability 4602678819172646912
    begin_IR
      HIR
f <@#|@fixed with next>@ <|@
tid v223 <|@
d <@d|@=== Debug Properties ===
nodeSourcePosition: at java.lang.String.lastIndexOf(String.java:1888) [bci: 72]
stamp: void
=== Inputs ===
=== Succesors ===
next: i233 
=== Usages ===
=== Predecessor ===
v224 >@ <|@
instruction <@Begin|@org.graalvm.compiler.nodes.BeginNode>@ #next: i233  <|@  <|@
f <@~|@floating>@ <|@
tid v240 <|@
d <@d|@=== Debug Properties ===
displacement: 12
scale: Times1
stamp: void*
=== Inputs ===
base: a1 
index: - 
=== Succesors ===
=== Usages ===
i233 
=== Predecessor ===
- >@ <|@
instruction <@AMD64Address|@org.graalvm.compiler.core.amd64.AMD64AddressNode>@ base: a1 index: -  <|@  <|@
f <@#|@fixed with next>@ <|@
tid i233 <|@
d <@d|@=== Debug Properties ===
barrierType: NONE
forceFixed: false
location: [].length:final
nodeSourcePosition: at java.lang.String.lastIndexOf(String.java:1888) [bci: 72]
nullCheck: false
stamp: i32 [0 - 2147483647] ⇈000000007fffffff
=== Inputs ===
stateBefore: - 
guard: - 
address: v240 
=== Succesors ===
next: v232 
=== Usages ===
v145 j134 
=== Predecessor ===
v223 >@ <|@
instruction <@Read|@org.graalvm.compiler.nodes.memory.ReadNode>@ stateBefore: - guard: - address: v240 #next: v232  <|@  <|@
f <@~|@floating>@ <|@
tid j136 <|@
d <@d|@=== Debug Properties ===
getOp: org.graalvm.compiler.nodes.calc.SignExtendNode$$Lambda$11/490840598@f525850
getReverseOp: org.graalvm.compiler.nodes.calc.SignExtendNode$$Lambda$12/742109885@1e2e35ef
inputBits: 32
resultBits: 64
stamp: i64 [-2147483648 - 2147483647]
=== Inputs ===
value: i24 
=== Succesors ===
=== Usages ===
j152 
=== Predecessor ===
- >@ <|@
instruction <@SignExtend|@org.graalvm.compiler.nodes.calc.SignExtendNode>@ value: i24  <|@  <|@
f <@~|@floating>@ <|@
tid i137 <|@
d <@d|@=== Debug Properties ===
getOp: org.graalvm.compiler.nodes.calc.AddNode$$Lambda$15/1271304513@1406efde
stamp: i32
=== Inputs ===
x: i9 
y: i18 
=== Succesors ===
=== Usages ===
j138 
=== Predecessor ===
- >@ <|@
instruction <@+|@org.graalvm.compiler.nodes.calc.AddNode>@ x: i9 y: i18  <|@  <|@
f <@~|@floating>@ <|@
tid j138 <|@
d <@d|@=== Debug Properties ===
getOp: org.graalvm.compiler.nodes.calc.SignExtendNode$$Lambda$11/490840598@f525850
getReverseOp: org.graalvm.compiler.nodes.calc.SignExtendNode$$Lambda$12/742109885@1e2e35ef
inputBits: 32
resultBits: 64
stamp: i64 [-2147483648 - 2147483647]
=== Inputs ===
value: i137 
=== Succesors ===
=== Usages ===
j140 
=== Predecessor ===
- >@ <|@
instruction <@SignExtend|@org.graalvm.compiler.nodes.calc.SignExtendNode>@ value: i137  <|@  <|@
f <@~|@floating>@ <|@
tid j135 <|@
d <@d|@=== Debug Properties ===
isDefaultStable: false
rawvalue: -1
stableDimension: 0
stamp: i64 [-1] ⇊ffffffffffffffff
stampKind: i64
value: long[-1|0xffffffffffffffff]
=== Inputs ===
=== Succesors ===
=== Usages ===
j140 
=== Predecessor ===
- >@ <|@
instruction <@Constant|@org.graalvm.compiler.nodes.ConstantNode>@  <|@  <|@
f <@~|@floating>@ <|@
tid j140 <|@
d <@d|@=== Debug Properties ===
getOp: org.graalvm.compiler.nodes.calc.AddNode$$Lambda$15/1271304513@1406efde
stamp: i64 [-2147483649 - 2147483646]
=== Inputs ===
x: j138 
y: j135 
=== Succesors ===
=== Usages ===
j152 
=== Predecessor ===
- >@ <|@
instruction <@+|@org.graalvm.compiler.nodes.calc.AddNode>@ x: j138 y: j135  <|@  <|@
f <@~|@floating>@ <|@
tid j152 <|@
d <@d|@=== Debug Properties ===
getOp: org.graalvm.compiler.nodes.calc.SubNode$$Lambda$64/1952983589@24889bdf
stamp: i64 [-4294967294 - 4294967296]
=== Inputs ===
x: j136 
y: j140 
=== Succesors ===
=== Usages ===
j143 
=== Predecessor ===
- >@ <|@
instruction <@-|@org.graalvm.compiler.nodes.calc.SubNode>@ x: j136 y: j140  <|@  <|@
f <@~|@floating>@ <|@
tid j143 <|@
d <@d|@=== Debug Properties ===
stamp: i64 [-4294967294 - 4294967296]
=== Inputs ===
guard: v158 
object: j152 
=== Succesors ===
=== Usages ===
v144 
=== Predecessor ===
- >@ <|@
instruction <@GuardedValue|@org.graalvm.compiler.nodes.GuardedValueNode>@ guard: v158 object: j152  <|@  <|@
f <@~|@floating>@ <|@
tid j134 <|@
d <@d|@=== Debug Properties ===
getOp: org.graalvm.compiler.nodes.calc.ZeroExtendNode$$Lambda$16/887152589@6b9fc47b
getReverseOp: org.graalvm.compiler.nodes.calc.ZeroExtendNode$$Lambda$17/1263733897@4844aec9
inputAlwaysPositive: true
inputBits: 32
resultBits: 64
stamp: i64 [0 - 2147483647] ⇈000000007fffffff
=== Inputs ===
value: i233 
=== Succesors ===
=== Usages ===
v144 
=== Predecessor ===
- >@ <|@
instruction <@ZeroExtend|@org.graalvm.compiler.nodes.calc.ZeroExtendNode>@ value: i233  <|@  <|@
f <@~|@floating>@ <|@
tid v144 <|@
d <@d|@=== Debug Properties ===
condition: BT
op: org.graalvm.compiler.nodes.calc.IntegerBelowNode$BelowOp@19d5dcf
stamp: void
unorderedIsTrue: false
=== Inputs ===
x: j143 
y: j134 
=== Succesors ===
=== Usages ===
v232 
=== Predecessor ===
- >@ <|@
instruction <@|<||@org.graalvm.compiler.nodes.calc.IntegerBelowNode>@ x: j143 y: j134  <|@  <|@
f <@~|@floating>@ <|@
tid a208 <|@
d <@d|@=== Debug Properties ===
isDefaultStable: false
rawvalue: d.a@800922110
stableDimension: 0
stamp: a!# Lcom/oracle/graal/enterprise/k/d$a;
stampKind: a -
value: Object[d.a@800922110]
=== Inputs ===
=== Succesors ===
=== Usages ===
a199 a199 
=== Predecessor ===
- >@ <|@
instruction <@Constant|@org.graalvm.compiler.nodes.ConstantNode>@  <|@  <|@
f <@~|@floating>@ <|@
tid i207 <|@
d <@d|@=== Debug Properties ===
isDefaultStable: false
rawvalue: -28443
stableDimension: 0
stamp: i32 [-28443] ⇊00000000ffff90e5 ⇈00000000ffff90e5
stampKind: i32
value: int[-28443|0xffffffffffff90e5]
=== Inputs ===
=== Succesors ===
=== Usages ===
i198 i198 
=== Predecessor ===
- >@ <|@
instruction <@Constant|@org.graalvm.compiler.nodes.ConstantNode>@  <|@  <|@
f <@*|@fixed>@ <|@
tid v232 <|@
d <@d|@=== Debug Properties ===
nodeSourcePosition: at java.lang.String.lastIndexOf(String.java:1888) [bci: 72]
stamp: void
trueSuccessorProbability: 1.0
=== Inputs ===
condition: v144 
=== Succesors ===
trueSuccessor: v231 
falseSuccessor: v228 
=== Usages ===
=== Predecessor ===
i233 >@ <|@
instruction <@If|@org.graalvm.compiler.nodes.IfNode>@ condition: v144 #trueSuccessor: v231 #falseSuccessor: v228  <|@  <|@
    end_IR
  end_block
  begin_block
    name "B7"
    from_bci -1
    to_bci -1
    predecessors "B6" 
    successors "B8" "B25" 
    xhandlers
    flags 
    probability 4602678819172646912
    begin_IR
      HIR
f <@#|@fixed with next>@ <|@
tid v231 <|@
d <@d|@=== Debug Properties ===
nodeSourcePosition: at java.lang.String.lastIndexOf(String.java:1888) [bci: 72]
stamp: void
=== Inputs ===
=== Succesors ===
next: v230 
=== Usages ===
=== Predecessor ===
v232 >@ <|@
instruction <@Begin|@org.graalvm.compiler.nodes.BeginNode>@ #next: v230  <|@  <|@
f <@~|@floating>@ <|@
tid v145 <|@
d <@d|@=== Debug Properties ===
condition: BT
op: org.graalvm.compiler.nodes.calc.IntegerBelowNode$BelowOp@19d5dcf
stamp: void
unorderedIsTrue: false
=== Inputs ===
x: i24 
y: i233 
=== Succesors ===
=== Usages ===
v230 
=== Predecessor ===
- >@ <|@
instruction <@|<||@org.graalvm.compiler.nodes.calc.IntegerBelowNode>@ x: i24 y: i233  <|@  <|@
f <@*|@fixed>@ <|@
tid v230 <|@
d <@d|@=== Debug Properties ===
nodeSourcePosition: at java.lang.String.lastIndexOf(String.java:1888) [bci: 72]
stamp: void
trueSuccessorProbability: 1.0
=== Inputs ===
condition: v145 
=== Succesors ===
trueSuccessor: v221 
falseSuccessor: v229 
=== Usages ===
=== Predecessor ===
v231 >@ <|@
instruction <@If|@org.graalvm.compiler.nodes.IfNode>@ condition: v145 #trueSuccessor: v221 #falseSuccessor: v229  <|@  <|@
    end_IR
  end_block
  begin_block
    name "B8"
    from_bci -1
    to_bci -1
    predecessors "B7" 
    successors "B9" 
    xhandlers
    flags 
    probability 4602678819172646912
    begin_IR
      HIR
f <@#|@fixed with next>@ <|@
tid v221 <|@
d <@d|@=== Debug Properties ===
nodeSourcePosition: at java.lang.String.lastIndexOf(String.java:1888) [bci: 72]
stamp: void
=== Inputs ===
=== Succesors ===
next: v219 
=== Usages ===
=== Predecessor ===
v230 >@ <|@
instruction <@Begin|@org.graalvm.compiler.nodes.BeginNode>@ #next: v219  <|@  <|@
f <@*|@fixed>@ <|@
tid v219 <|@
d <@d|@=== Debug Properties ===
nodeSourcePosition: at java.lang.String.lastIndexOf(String.java:1888) [bci: 72]
stamp: void
=== Inputs ===
=== Succesors ===
=== Usages ===
v217 
=== Predecessor ===
v221 >@ <|@
instruction <@EndNode|@org.graalvm.compiler.nodes.EndNode>@  <|@  <|@
    end_IR
  end_block
  begin_block
    name "B9"
    from_bci -1
    to_bci -1
    predecessors "B5" "B8" 
    successors "B10" "B11" 
    xhandlers
    flags 
    probability 4607182418800017408
    begin_IR
      HIR
f <@#|@fixed with next>@ <|@
tid v217 <|@
d <@d|@=== Debug Properties ===
nodeSourcePosition: at java.lang.String.lastIndexOf(String.java:1888) [bci: 72]
stamp: void
=== Inputs ===
stateAfter: - 
ends: v218 v219 
=== Succesors ===
next: v169 
=== Usages ===
v150 
=== Predecessor ===
- >@ <|@
instruction <@Merge|@org.graalvm.compiler.nodes.MergeNode>@ stateAfter: - ends: v218 v219 #next: v169  <|@  <|@
f <@~|@floating>@ <|@
tid i10 <|@
d <@d|@=== Debug Properties ===
isDefaultStable: false
nodeSourcePosition: at java.lang.String.lastIndexOf(String.java:1870) [bci: 8]
rawvalue: 0
stableDimension: 0
stamp: i32 [0] ⇈0000000000000000
stampKind: i32
value: int[0|0x0]
=== Inputs ===
=== Succesors ===
=== Usages ===
v11 v15 
=== Predecessor ===
- >@ <|@
instruction <@Constant|@org.graalvm.compiler.nodes.ConstantNode>@  <|@  <|@
f <@~|@floating>@ <|@
tid v11 <|@
d <@d|@=== Debug Properties ===
condition: LT
nodeSourcePosition: at java.lang.String.lastIndexOf(String.java:1870) [bci: 8]
op: org.graalvm.compiler.nodes.calc.IntegerLessThanNode$LessThanOp@7cc8d043
stamp: void
unorderedIsTrue: false
=== Inputs ===
x: i7 
y: i10 
=== Succesors ===
=== Usages ===
v169 
=== Predecessor ===
- >@ <|@
instruction <@<|@org.graalvm.compiler.nodes.calc.IntegerLessThanNode>@ x: i7 y: i10  <|@  <|@
f <@*|@fixed>@ <|@
tid v169 <|@
d <@d|@=== Debug Properties ===
nodeSourcePosition: at java.lang.String.lastIndexOf(String.java:1870) [bci: 8]
stamp: void
trueSuccessorProbability: 0.0
=== Inputs ===
condition: v11 
=== Succesors ===
trueSuccessor: v168 
falseSuccessor: v166 
=== Usages ===
=== Predecessor ===
v217 >@ <|@
instruction <@If|@org.graalvm.compiler.nodes.IfNode>@ condition: v11 #trueSuccessor: v168 #falseSuccessor: v166  <|@  <|@
    end_IR
  end_block
  begin_block
    name "B10"
    from_bci -1
    to_bci -1
    predecessors "B9" 
    successors "B27" 
    xhandlers
    flags 
    probability 2355382605114769408
    begin_IR
      HIR
f <@#|@fixed with next>@ <|@
tid v168 <|@
d <@d|@=== Debug Properties ===
nodeSourcePosition: at java.lang.String.lastIndexOf(String.java:1870) [bci: 8]
stamp: void
=== Inputs ===
=== Succesors ===
next: v204 
=== Usages ===
=== Predecessor ===
v169 >@ <|@
instruction <@Begin|@org.graalvm.compiler.nodes.BeginNode>@ #next: v204  <|@  <|@
f <@~|@floating>@ <|@
tid i205 <|@
d <@d|@=== Debug Properties ===
isDefaultStable: false
rawvalue: -22035
stableDimension: 0
stamp: i32 [-22035] ⇊00000000ffffa9ed ⇈00000000ffffa9ed
stampKind: i32
value: int[-22035|0xffffffffffffa9ed]
=== Inputs ===
=== Succesors ===
=== Usages ===
i198 
=== Predecessor ===
- >@ <|@
instruction <@Constant|@org.graalvm.compiler.nodes.ConstantNode>@  <|@  <|@
f <@*|@fixed>@ <|@
tid v204 <|@
d <@d|@=== Debug Properties ===
stamp: void
=== Inputs ===
=== Succesors ===
=== Usages ===
v194 
=== Predecessor ===
v168 >@ <|@
instruction <@EndNode|@org.graalvm.compiler.nodes.EndNode>@  <|@  <|@
    end_IR
  end_block
  begin_block
    name "B11"
    from_bci -1
    to_bci -1
    predecessors "B9" 
    successors "B12" "B24" 
    xhandlers
    flags 
    probability 4607182418800017408
    begin_IR
      HIR
f <@#|@fixed with next>@ <|@
tid v166 <|@
d <@d|@=== Debug Properties ===
nodeSourcePosition: at java.lang.String.lastIndexOf(String.java:1870) [bci: 8]
stamp: void
=== Inputs ===
=== Succesors ===
next: v173 
=== Usages ===
=== Predecessor ===
v169 >@ <|@
instruction <@Begin|@org.graalvm.compiler.nodes.BeginNode>@ #next: v173  <|@  <|@
f <@~|@floating>@ <|@
tid v13 <|@
d <@d|@=== Debug Properties ===
condition: LT
nodeSourcePosition: at java.lang.String.lastIndexOf(String.java:1873) [bci: 17]
op: org.graalvm.compiler.nodes.calc.IntegerLessThanNode$LessThanOp@7cc8d043
stamp: void
unorderedIsTrue: false
=== Inputs ===
x: i9 
y: i7 
=== Succesors ===
=== Usages ===
v173 
=== Predecessor ===
- >@ <|@
instruction <@<|@org.graalvm.compiler.nodes.calc.IntegerLessThanNode>@ x: i9 y: i7  <|@  <|@
f <@*|@fixed>@ <|@
tid v173 <|@
d <@d|@=== Debug Properties ===
nodeSourcePosition: at java.lang.String.lastIndexOf(String.java:1873) [bci: 17]
stamp: void
trueSuccessorProbability: 1.0
=== Inputs ===
condition: v13 
=== Succesors ===
trueSuccessor: v170 
falseSuccessor: v172 
=== Usages ===
=== Predecessor ===
v166 >@ <|@
instruction <@If|@org.graalvm.compiler.nodes.IfNode>@ condition: v13 #trueSuccessor: v170 #falseSuccessor: v172  <|@  <|@
    end_IR
  end_block
  begin_block
    name "B12"
    from_bci -1
    to_bci -1
    predecessors "B11" 
    successors "B13" "B14" 
    xhandlers
    flags 
    probability 4607182418800017408
    begin_IR
      HIR
f <@#|@fixed with next>@ <|@
tid v170 <|@
d <@d|@=== Debug Properties ===
nodeSourcePosition: at java.lang.String.lastIndexOf(String.java:1873) [bci: 17]
stamp: void
=== Inputs ===
=== Succesors ===
next: v177 
=== Usages ===
=== Predecessor ===
v173 >@ <|@
instruction <@Begin|@org.graalvm.compiler.nodes.BeginNode>@ #next: v177  <|@  <|@
f <@~|@floating>@ <|@
tid v15 <|@
d <@d|@=== Debug Properties ===
condition: EQ
nodeSourcePosition: at java.lang.String.lastIndexOf(String.java:1877) [bci: 26]
stamp: void
unorderedIsTrue: false
=== Inputs ===
x: i6 
y: i10 
=== Succesors ===
=== Usages ===
v177 
=== Predecessor ===
- >@ <|@
instruction <@==|@org.graalvm.compiler.nodes.calc.IntegerEqualsNode>@ x: i6 y: i10  <|@  <|@
f <@*|@fixed>@ <|@
tid v177 <|@
d <@d|@=== Debug Properties ===
nodeSourcePosition: at java.lang.String.lastIndexOf(String.java:1877) [bci: 26]
stamp: void
trueSuccessorProbability: 0.0
=== Inputs ===
condition: v15 
=== Succesors ===
trueSuccessor: v176 
falseSuccessor: v174 
=== Usages ===
=== Predecessor ===
v170 >@ <|@
instruction <@If|@org.graalvm.compiler.nodes.IfNode>@ condition: v15 #trueSuccessor: v176 #falseSuccessor: v174  <|@  <|@
    end_IR
  end_block
  begin_block
    name "B13"
    from_bci -1
    to_bci -1
    predecessors "B12" 
    successors "B27" 
    xhandlers
    flags 
    probability 2355382605114769408
    begin_IR
      HIR
f <@#|@fixed with next>@ <|@
tid v176 <|@
d <@d|@=== Debug Properties ===
nodeSourcePosition: at java.lang.String.lastIndexOf(String.java:1877) [bci: 26]
stamp: void
=== Inputs ===
=== Succesors ===
next: v209 
=== Usages ===
=== Predecessor ===
v177 >@ <|@
instruction <@Begin|@org.graalvm.compiler.nodes.BeginNode>@ #next: v209  <|@  <|@
f <@~|@floating>@ <|@
tid i210 <|@
d <@d|@=== Debug Properties ===
isDefaultStable: false
rawvalue: -22547
stableDimension: 0
stamp: i32 [-22547] ⇊00000000ffffa7ed ⇈00000000ffffa7ed
stampKind: i32
value: int[-22547|0xffffffffffffa7ed]
=== Inputs ===
=== Succesors ===
=== Usages ===
i198 
=== Predecessor ===
- >@ <|@
instruction <@Constant|@org.graalvm.compiler.nodes.ConstantNode>@  <|@  <|@
f <@*|@fixed>@ <|@
tid v209 <|@
d <@d|@=== Debug Properties ===
stamp: void
=== Inputs ===
=== Succesors ===
=== Usages ===
v194 
=== Predecessor ===
v176 >@ <|@
instruction <@EndNode|@org.graalvm.compiler.nodes.EndNode>@  <|@  <|@
    end_IR
  end_block
  begin_block
    name "B14"
    from_bci -1
    to_bci -1
    predecessors "B12" 
    successors "B15" "B23" 
    xhandlers
    flags 
    probability 4607182418800017408
    begin_IR
      HIR
f <@#|@fixed with next>@ <|@
tid v174 <|@
d <@d|@=== Debug Properties ===
nodeSourcePosition: at java.lang.String.lastIndexOf(String.java:1877) [bci: 26]
stamp: void
=== Inputs ===
=== Succesors ===
next: i234 
=== Usages ===
=== Predecessor ===
v177 >@ <|@
instruction <@Begin|@org.graalvm.compiler.nodes.BeginNode>@ #next: i234  <|@  <|@
f <@~|@floating>@ <|@
tid v238 <|@
d <@d|@=== Debug Properties ===
displacement: 12
scale: Times1
stamp: void*
=== Inputs ===
base: a4 
index: - 
=== Succesors ===
=== Usages ===
i234 
=== Predecessor ===
- >@ <|@
instruction <@AMD64Address|@org.graalvm.compiler.core.amd64.AMD64AddressNode>@ base: a4 index: -  <|@  <|@
f <@#|@fixed with next>@ <|@
tid i234 <|@
d <@d|@=== Debug Properties ===
barrierType: NONE
forceFixed: false
location: [].length:final
nodeSourcePosition: at java.lang.String.lastIndexOf(String.java:1882) [bci: 44]
nullCheck: true
stamp: i32 [0 - 2147483647] ⇈000000007fffffff
=== Inputs ===
stateBefore: ?8 
guard: - 
address: v238 
=== Succesors ===
next: v185 
=== Usages ===
v95 
=== Predecessor ===
v174 >@ <|@
instruction <@Read|@org.graalvm.compiler.nodes.memory.ReadNode>@ stateBefore: ?8 guard: - address: v238 #next: v185  <|@  <|@
f <@~|@floating>@ <|@
tid i17 <|@
d <@d|@=== Debug Properties ===
getOp: org.graalvm.compiler.nodes.calc.AddNode$$Lambda$15/1271304513@1406efde
nodeSourcePosition: at java.lang.String.lastIndexOf(String.java:1881) [bci: 36]
stamp: i32
=== Inputs ===
x: i5 
y: i6 
=== Succesors ===
=== Usages ===
i20 
=== Predecessor ===
- >@ <|@
instruction <@+|@org.graalvm.compiler.nodes.calc.AddNode>@ x: i5 y: i6  <|@  <|@
f <@~|@floating>@ <|@
tid i20 <|@
d <@d|@=== Debug Properties ===
getOp: org.graalvm.compiler.nodes.calc.AddNode$$Lambda$15/1271304513@1406efde
nodeSourcePosition: at java.lang.String.lastIndexOf(String.java:1881) [bci: 38]
stamp: i32
=== Inputs ===
x: i17 
y: i19 
=== Succesors ===
=== Usages ===
v239 ?29 v95 
=== Predecessor ===
- >@ <|@
instruction <@+|@org.graalvm.compiler.nodes.calc.AddNode>@ x: i17 y: i19  <|@  <|@
f <@~|@floating>@ <|@
tid v95 <|@
d <@d|@=== Debug Properties ===
condition: BT
nodeSourcePosition: at java.lang.String.lastIndexOf(String.java:1882) [bci: 44]
op: org.graalvm.compiler.nodes.calc.IntegerBelowNode$BelowOp@19d5dcf
stamp: void
unorderedIsTrue: false
=== Inputs ===
x: i20 
y: i234 
=== Succesors ===
=== Usages ===
v185 
=== Predecessor ===
- >@ <|@
instruction <@|<||@org.graalvm.compiler.nodes.calc.IntegerBelowNode>@ x: i20 y: i234  <|@  <|@
f <@*|@fixed>@ <|@
tid v185 <|@
d <@d|@=== Debug Properties ===
nodeSourcePosition: at java.lang.String.lastIndexOf(String.java:1882) [bci: 44]
stamp: void
trueSuccessorProbability: 1.0
=== Inputs ===
condition: v95 
=== Succesors ===
trueSuccessor: v182 
falseSuccessor: v184 
=== Usages ===
=== Predecessor ===
i234 >@ <|@
instruction <@If|@org.graalvm.compiler.nodes.IfNode>@ condition: v95 #trueSuccessor: v182 #falseSuccessor: v184  <|@  <|@
    end_IR
  end_block
  begin_block
    name "B15"
    from_bci -1
    to_bci -1
    predecessors "B14" 
    successors "B16" 
    xhandlers
    flags 
    probability 4607182418800017408
    begin_IR
      HIR
f <@#|@fixed with next>@ <|@
tid v182 <|@
d <@d|@=== Debug Properties ===
nodeSourcePosition: at java.lang.String.lastIndexOf(String.java:1882) [bci: 44]
stamp: void
=== Inputs ===
=== Succesors ===
next: i235 
=== Usages ===
i235 
=== Predecessor ===
v185 >@ <|@
instruction <@Begin|@org.graalvm.compiler.nodes.BeginNode>@ #next: i235  <|@  <|@
f <@~|@floating>@ <|@
tid v239 <|@
d <@d|@=== Debug Properties ===
displacement: 16
scale: Times2
stamp: void*
=== Inputs ===
base: a4 
index: i20 
=== Succesors ===
=== Usages ===
i235 
=== Predecessor ===
- >@ <|@
instruction <@AMD64Address|@org.graalvm.compiler.core.amd64.AMD64AddressNode>@ base: a4 index: i20  <|@  <|@
f <@#|@fixed with next>@ <|@
tid i235 <|@
d <@d|@=== Debug Properties ===
barrierType: NONE
forceFixed: false
location: Array: char
nodeSourcePosition: at java.lang.String.lastIndexOf(String.java:1882) [bci: 44]
nullCheck: false
stamp: i16
=== Inputs ===
stateBefore: - 
guard: v182 
address: v239 
=== Succesors ===
next: v26 
=== Usages ===
i104 
=== Predecessor ===
v182 >@ <|@
instruction <@Read|@org.graalvm.compiler.nodes.memory.ReadNode>@ stateBefore: - guard: v182 address: v239 #next: v26  <|@  <|@
f <@~|@floating>@ <|@
tid i104 <|@
d <@d|@=== Debug Properties ===
getOp: org.graalvm.compiler.nodes.calc.ZeroExtendNode$$Lambda$16/887152589@6b9fc47b
getReverseOp: org.graalvm.compiler.nodes.calc.ZeroExtendNode$$Lambda$17/1263733897@4844aec9
inputAlwaysPositive: false
inputBits: 16
nodeSourcePosition: at java.lang.String.lastIndexOf(String.java:1882) [bci: 44]
resultBits: 32
stamp: i32 [0 - 65535] ⇈000000000000ffff
=== Inputs ===
value: i235 
=== Succesors ===
=== Usages ===
?29 v35 
=== Predecessor ===
- >@ <|@
instruction <@ZeroExtend|@org.graalvm.compiler.nodes.calc.ZeroExtendNode>@ value: i235  <|@  <|@
f <@*|@fixed>@ <|@
tid v26 <|@
d <@d|@=== Debug Properties ===
nodeSourcePosition: at java.lang.String.lastIndexOf(String.java:1888) [bci: 62]
stamp: void
=== Inputs ===
=== Succesors ===
=== Usages ===
v27 
=== Predecessor ===
i235 >@ <|@
instruction <@EndNode|@org.graalvm.compiler.nodes.EndNode>@  <|@  <|@
    end_IR
  end_block
  begin_block
    name "B16"
    from_bci -1
    to_bci -1
    predecessors "B15" "B22" 
    successors "B17" "B18" 
    xhandlers
    flags "llh" 
    loop_index 0
    loop_depth 1
    probability 4623847342242986814
    begin_IR
      HIR
f <@~|@floating>@ <|@
tid i28 <|@
d <@d|@=== Debug Properties ===
stamp: i32
valueDescription: i32
=== Inputs ===
merge: v27 
values: i24 i42 
=== Succesors ===
=== Usages ===
?29 v30 v241 i42 
=== Predecessor ===
- >@ <|@
instruction <@ValuePhi|@org.graalvm.compiler.nodes.ValuePhiNode>@ merge: v27 values: i24 i42  <|@  <|@
f <@#|@fixed with next>@ <|@
tid v27 <|@
d <@d|@=== Debug Properties ===
canEndsSafepoint: false
inversionCount: 0
loopFrequency: 13.602850736000274
loopOrigFrequency: 1.0
loopType: SIMPLE_LOOP
nextEndIndex: 1
nodeSourcePosition: at java.lang.String.lastIndexOf(String.java:1888) [bci: 62]
splits: 0
stamp: void
unrollFactor: 1
unswitches: 0
=== Inputs ===
stateAfter: - 
overflowGuard: v158 
ends: v26 
=== Succesors ===
next: v33 
=== Usages ===
i28 v43 v46 v64 v189 
=== Predecessor ===
- >@ <|@
instruction <@LoopBegin|@org.graalvm.compiler.nodes.LoopBeginNode>@ stateAfter: - overflowGuard: v158 ends: v26 #next: v33  <|@  <|@
f <@~|@floating>@ <|@
tid v30 <|@
d <@d|@=== Debug Properties ===
condition: LT
nodeSourcePosition: at java.lang.String.lastIndexOf(String.java:1888) [bci: 66]
op: org.graalvm.compiler.nodes.calc.IntegerLessThanNode$LessThanOp@7cc8d043
stamp: void
unorderedIsTrue: false
=== Inputs ===
x: i28 
y: i23 
=== Succesors ===
=== Usages ===
v33 
=== Predecessor ===
- >@ <|@
instruction <@<|@org.graalvm.compiler.nodes.calc.IntegerLessThanNode>@ x: i28 y: i23  <|@  <|@
f <@*|@fixed>@ <|@
tid v33 <|@
d <@d|@=== Debug Properties ===
nodeSourcePosition: at java.lang.String.lastIndexOf(String.java:1888) [bci: 66]
stamp: void
trueSuccessorProbability: 0.014642233807685692
=== Inputs ===
condition: v30 
=== Succesors ===
trueSuccessor: v46 
falseSuccessor: v32 
=== Usages ===
=== Predecessor ===
v27 >@ <|@
instruction <@If|@org.graalvm.compiler.nodes.IfNode>@ condition: v30 #trueSuccessor: v46 #falseSuccessor: v32  <|@  <|@
    end_IR
  end_block
  begin_block
    name "B17"
    from_bci -1
    to_bci -1
    predecessors "B16" 
    successors 
    xhandlers
    flags 
    probability 4596344096322459299
    begin_IR
      HIR
f <@#|@fixed with next>@ <|@
tid v46 <|@
d <@d|@=== Debug Properties ===
nodeSourcePosition: at java.lang.String.lastIndexOf(String.java:1891) [bci: 84]
stamp: void
=== Inputs ===
stateAfter: - 
loopBegin: v27 
=== Succesors ===
next: v67 
=== Usages ===
=== Predecessor ===
v33 >@ <|@
instruction <@LoopExit|@org.graalvm.compiler.nodes.LoopExitNode>@ stateAfter: - loopBegin: v27 #next: v67  <|@  <|@
f <@*|@fixed>@ <|@
tid v67 <|@
d <@d|@=== Debug Properties ===
nodeSourcePosition: at java.lang.String.lastIndexOf(String.java:1892) [bci: 92]
stamp: void
=== Inputs ===
result: i19 
memoryMap: - 
=== Succesors ===
=== Usages ===
=== Predecessor ===
v46 >@ <|@
instruction <@Return|@org.graalvm.compiler.nodes.ReturnNode>@ result: i19 memoryMap: -  <|@  <|@
    end_IR
  end_block
  begin_block
    name "B18"
    from_bci -1
    to_bci -1
    predecessors "B16" 
    successors "B19" "B22" 
    xhandlers
    flags 
    loop_index 0
    loop_depth 1
    probability 4623735216054988003
    begin_IR
      HIR
f <@#|@fixed with next>@ <|@
tid v32 <|@
d <@d|@=== Debug Properties ===
nodeSourcePosition: at java.lang.String.lastIndexOf(String.java:1888) [bci: 69]
stamp: void
=== Inputs ===
=== Succesors ===
next: i236 
=== Usages ===
v150 
=== Predecessor ===
v33 >@ <|@
instruction <@Begin|@org.graalvm.compiler.nodes.BeginNode>@ #next: i236  <|@  <|@
f <@~|@floating>@ <|@
tid v150 <|@
d <@d|@=== Debug Properties ===
stamp: void
=== Inputs ===
kf: v217 v32 
=== Succesors ===
=== Usages ===
i236 
=== Predecessor ===
- >@ <|@
instruction <@c|@com.oracle.graal.enterprise.k.c>@ kf: v217 v32  <|@  <|@
f <@~|@floating>@ <|@
tid v241 <|@
d <@d|@=== Debug Properties ===
displacement: 16
scale: Times2
stamp: void*
=== Inputs ===
base: a1 
index: i28 
=== Succesors ===
=== Usages ===
i236 
=== Predecessor ===
- >@ <|@
instruction <@AMD64Address|@org.graalvm.compiler.core.amd64.AMD64AddressNode>@ base: a1 index: i28  <|@  <|@
f <@#|@fixed with next>@ <|@
tid i236 <|@
d <@d|@=== Debug Properties ===
barrierType: NONE
forceFixed: false
location: Array: char
nodeSourcePosition: at java.lang.String.lastIndexOf(String.java:1888) [bci: 72]
nullCheck: false
stamp: i16
=== Inputs ===
stateBefore: - 
guard: v150 
address: v241 
=== Succesors ===
next: v41 
=== Usages ===
i118 
=== Predecessor ===
v32 >@ <|@
instruction <@Read|@org.graalvm.compiler.nodes.memory.ReadNode>@ stateBefore: - guard: v150 address: v241 #next: v41  <|@  <|@
f <@~|@floating>@ <|@
tid i118 <|@
d <@d|@=== Debug Properties ===
getOp: org.graalvm.compiler.nodes.calc.ZeroExtendNode$$Lambda$16/887152589@6b9fc47b
getReverseOp: org.graalvm.compiler.nodes.calc.ZeroExtendNode$$Lambda$17/1263733897@4844aec9
inputAlwaysPositive: false
inputBits: 16
nodeSourcePosition: at java.lang.String.lastIndexOf(String.java:1888) [bci: 72]
resultBits: 32
stamp: i32 [0 - 65535] ⇈000000000000ffff
=== Inputs ===
value: i236 
=== Succesors ===
=== Usages ===
v35 
=== Predecessor ===
- >@ <|@
instruction <@ZeroExtend|@org.graalvm.compiler.nodes.calc.ZeroExtendNode>@ value: i236  <|@  <|@
f <@~|@floating>@ <|@
tid v35 <|@
d <@d|@=== Debug Properties ===
condition: EQ
nodeSourcePosition: at java.lang.String.lastIndexOf(String.java:1888) [bci: 75]
stamp: void
unorderedIsTrue: false
=== Inputs ===
x: i104 
y: i118 
=== Succesors ===
=== Usages ===
v41 
=== Predecessor ===
- >@ <|@
instruction <@==|@org.graalvm.compiler.nodes.calc.IntegerEqualsNode>@ x: i104 y: i118  <|@  <|@
f <@~|@floating>@ <|@
tid i42 <|@
d <@d|@=== Debug Properties ===
getOp: org.graalvm.compiler.nodes.calc.AddNode$$Lambda$15/1271304513@1406efde
nodeSourcePosition: at java.lang.String.lastIndexOf(String.java:1889) [bci: 78]
stamp: i32
=== Inputs ===
x: i28 
y: i19 
=== Succesors ===
=== Usages ===
i28 i51 v59 
=== Predecessor ===
- >@ <|@
instruction <@+|@org.graalvm.compiler.nodes.calc.AddNode>@ x: i28 y: i19  <|@  <|@
f <@*|@fixed>@ <|@
tid v41 <|@
d <@d|@=== Debug Properties ===
nodeSourcePosition: at java.lang.String.lastIndexOf(String.java:1888) [bci: 75]
stamp: void
trueSuccessorProbability: 0.059746592040655154
=== Inputs ===
condition: v35 
=== Succesors ===
trueSuccessor: v40 
falseSuccessor: v39 
=== Usages ===
=== Predecessor ===
i236 >@ <|@
instruction <@If|@org.graalvm.compiler.nodes.IfNode>@ condition: v35 #trueSuccessor: v40 #falseSuccessor: v39  <|@  <|@
    end_IR
  end_block
  begin_block
    name "B19"
    from_bci -1
    to_bci -1
    predecessors "B18" 
    successors "B20" "B21" 
    xhandlers
    flags 
    probability 4605388399792036439
    begin_IR
      HIR
f <@#|@fixed with next>@ <|@
tid v40 <|@
d <@d|@=== Debug Properties ===
nodeSourcePosition: at java.lang.String.lastIndexOf(String.java:1891) [bci: 84]
stamp: void
=== Inputs ===
=== Succesors ===
next: v190 
=== Usages ===
=== Predecessor ===
v41 >@ <|@
instruction <@Begin|@org.graalvm.compiler.nodes.BeginNode>@ #next: v190  <|@  <|@
f <@~|@floating>@ <|@
tid i50 <|@
d <@d|@=== Debug Properties ===
getOp: org.graalvm.compiler.nodes.calc.AddNode$$Lambda$15/1271304513@1406efde
nodeSourcePosition: at java.lang.String.lastIndexOf(String.java:1895) [bci: 104]
stamp: i32
=== Inputs ===
x: i6 
y: i19 
=== Succesors ===
=== Usages ===
i51 
=== Predecessor ===
- >@ <|@
instruction <@+|@org.graalvm.compiler.nodes.calc.AddNode>@ x: i6 y: i19  <|@  <|@
f <@~|@floating>@ <|@
tid i51 <|@
d <@d|@=== Debug Properties ===
getOp: org.graalvm.compiler.nodes.calc.SubNode$$Lambda$64/1952983589@24889bdf
nodeSourcePosition: at java.lang.String.lastIndexOf(String.java:1895) [bci: 105]
stamp: i32
=== Inputs ===
x: i42 
y: i50 
=== Succesors ===
=== Usages ===
i68 v59 
=== Predecessor ===
- >@ <|@
instruction <@-|@org.graalvm.compiler.nodes.calc.SubNode>@ x: i42 y: i50  <|@  <|@
f <@~|@floating>@ <|@
tid v59 <|@
d <@d|@=== Debug Properties ===
condition: LT
nodeSourcePosition: at java.lang.String.lastIndexOf(String.java:1898) [bci: 118]
op: org.graalvm.compiler.nodes.calc.IntegerLessThanNode$LessThanOp@7cc8d043
stamp: void
unorderedIsTrue: false
=== Inputs ===
x: i51 
y: i42 
=== Succesors ===
=== Usages ===
v190 
=== Predecessor ===
- >@ <|@
instruction <@<|@org.graalvm.compiler.nodes.calc.IntegerLessThanNode>@ x: i51 y: i42  <|@  <|@
f <@*|@fixed>@ <|@
tid v190 <|@
d <@d|@=== Debug Properties ===
nodeSourcePosition: at java.lang.String.lastIndexOf(String.java:1898) [bci: 118]
stamp: void
trueSuccessorProbability: 0.0
=== Inputs ===
condition: v59 
=== Succesors ===
trueSuccessor: v189 
falseSuccessor: v64 
=== Usages ===
=== Predecessor ===
v40 >@ <|@
instruction <@If|@org.graalvm.compiler.nodes.IfNode>@ condition: v59 #trueSuccessor: v189 #falseSuccessor: v64  <|@  <|@
    end_IR
  end_block
  begin_block
    name "B20"
    from_bci -1
    to_bci -1
    predecessors "B19" 
    successors 
    xhandlers
    flags 
    probability 2355382605114769408
    begin_IR
      HIR
f <@#|@fixed with next>@ <|@
tid v189 <|@
d <@d|@=== Debug Properties ===
nodeSourcePosition: at java.lang.String.lastIndexOf(String.java:1898) [bci: 118]
stamp: void
=== Inputs ===
stateAfter: - 
loopBegin: v27 
=== Succesors ===
next: v187 
=== Usages ===
=== Predecessor ===
v190 >@ <|@
instruction <@LoopExit|@org.graalvm.compiler.nodes.LoopExitNode>@ stateAfter: - loopBegin: v27 #next: v187  <|@  <|@
tid ?29 <|@
d <@d|@=== Debug Properties ===
bci: 62
code: ResolvedJavaMethodBytecode<String.lastIndexOf(char[], int, int, char[], int, int, int)>
duringCall: false
localsSize: 15
locksSize: 0
rethrowException: false
sourceFile: String.java
sourceLine: 1888
stackSize: 0
=== Inputs ===
outerFrameState: - 
values: a1 i2 - a4 - i6 - - i20 i104 i23 i28 - - - 
=== Succesors ===
=== Usages ===
v187 
=== Predecessor ===
- >@ <|@
instruction <@FrameState|@org.graalvm.compiler.nodes.FrameState>@ outerFrameState: - values: a1 i2 - a4 - i6 - - i20 i104 i23 i28 - - -  <|@  <|@
f <@*|@fixed>@ <|@
tid v187 <|@
d <@d|@=== Debug Properties ===
action: InvalidateReprofile
debugId: 119
nodeSourcePosition: at java.lang.String.lastIndexOf(String.java:1898) [bci: 118]
reason: UnreachedCode
speculation: Object[null]
stamp: void
=== Inputs ===
stateBefore: ?29 
=== Succesors ===
=== Usages ===
=== Predecessor ===
v189 >@ <|@
instruction <@Deopt|@org.graalvm.compiler.nodes.DeoptimizeNode>@ stateBefore: ?29  <|@  <|@
    end_IR
  end_block
  begin_block
    name "B21"
    from_bci -1
    to_bci -1
    predecessors "B19" 
    successors 
    xhandlers
    flags 
    probability 4605388399792036439
    begin_IR
      HIR
f <@#|@fixed with next>@ <|@
tid v64 <|@
d <@d|@=== Debug Properties ===
nodeSourcePosition: at java.lang.String.lastIndexOf(String.java:1898) [bci: 118]
stamp: void
=== Inputs ===
stateAfter: - 
loopBegin: v27 
=== Succesors ===
next: v70 
=== Usages ===
=== Predecessor ===
v190 >@ <|@
instruction <@LoopExit|@org.graalvm.compiler.nodes.LoopExitNode>@ stateAfter: - loopBegin: v27 #next: v70  <|@  <|@
f <@~|@floating>@ <|@
tid i68 <|@
d <@d|@=== Debug Properties ===
getOp: org.graalvm.compiler.nodes.calc.SubNode$$Lambda$64/1952983589@24889bdf
nodeSourcePosition: at java.lang.String.lastIndexOf(String.java:1904) [bci: 147]
stamp: i32
=== Inputs ===
x: i51 
y: i2 
=== Succesors ===
=== Usages ===
i69 
=== Predecessor ===
- >@ <|@
instruction <@-|@org.graalvm.compiler.nodes.calc.SubNode>@ x: i51 y: i2  <|@  <|@
f <@~|@floating>@ <|@
tid i69 <|@
d <@d|@=== Debug Properties ===
getOp: org.graalvm.compiler.nodes.calc.AddNode$$Lambda$15/1271304513@1406efde
nodeSourcePosition: at java.lang.String.lastIndexOf(String.java:1904) [bci: 149]
stamp: i32
=== Inputs ===
x: i68 
y: i18 
=== Succesors ===
=== Usages ===
v70 
=== Predecessor ===
- >@ <|@
instruction <@+|@org.graalvm.compiler.nodes.calc.AddNode>@ x: i68 y: i18  <|@  <|@
f <@*|@fixed>@ <|@
tid v70 <|@
d <@d|@=== Debug Properties ===
nodeSourcePosition: at java.lang.String.lastIndexOf(String.java:1904) [bci: 150]
stamp: void
=== Inputs ===
result: i69 
memoryMap: - 
=== Succesors ===
=== Usages ===
=== Predecessor ===
v64 >@ <|@
instruction <@Return|@org.graalvm.compiler.nodes.ReturnNode>@ result: i69 memoryMap: -  <|@  <|@
    end_IR
  end_block
  begin_block
    name "B22"
    from_bci -1
    to_bci -1
    predecessors "B18" 
    successors "B16" 
    xhandlers
    flags "lle" 
    loop_index 0
    loop_depth 1
    probability 4623284392289565502
    begin_IR
      HIR
f <@#|@fixed with next>@ <|@
tid v39 <|@
d <@d|@=== Debug Properties ===
nodeSourcePosition: at java.lang.String.lastIndexOf(String.java:1889) [bci: 78]
stamp: void
=== Inputs ===
=== Succesors ===
next: v43 
=== Usages ===
=== Predecessor ===
v41 >@ <|@
instruction <@Begin|@org.graalvm.compiler.nodes.BeginNode>@ #next: v43  <|@  <|@
f <@*|@fixed>@ <|@
tid v43 <|@
d <@d|@=== Debug Properties ===
canSafepoint: false
endIndex: 0
nodeSourcePosition: at java.lang.String.lastIndexOf(String.java:1888) [bci: 62]
stamp: void
=== Inputs ===
loopBegin: v27 
=== Succesors ===
=== Usages ===
=== Predecessor ===
v39 >@ <|@
instruction <@LoopEnd|@org.graalvm.compiler.nodes.LoopEndNode>@ loopBegin: v27  <|@  <|@
    end_IR
  end_block
  begin_block
    name "B23"
    from_bci -1
    to_bci -1
    predecessors "B14" 
    successors "B27" 
    xhandlers
    flags 
    probability 2355382605114769408
    begin_IR
      HIR
f <@#|@fixed with next>@ <|@
tid v184 <|@
d <@d|@=== Debug Properties ===
nodeSourcePosition: at java.lang.String.lastIndexOf(String.java:1882) [bci: 44]
stamp: void
=== Inputs ===
=== Succesors ===
next: v215 
=== Usages ===
=== Predecessor ===
v185 >@ <|@
instruction <@Begin|@org.graalvm.compiler.nodes.BeginNode>@ #next: v215  <|@  <|@
f <@~|@floating>@ <|@
tid i216 <|@
d <@d|@=== Debug Properties ===
isDefaultStable: false
rawvalue: -24603
stableDimension: 0
stamp: i32 [-24603] ⇊00000000ffff9fe5 ⇈00000000ffff9fe5
stampKind: i32
value: int[-24603|0xffffffffffff9fe5]
=== Inputs ===
=== Succesors ===
=== Usages ===
i198 
=== Predecessor ===
- >@ <|@
instruction <@Constant|@org.graalvm.compiler.nodes.ConstantNode>@  <|@  <|@
f <@*|@fixed>@ <|@
tid v215 <|@
d <@d|@=== Debug Properties ===
stamp: void
=== Inputs ===
=== Succesors ===
=== Usages ===
v194 
=== Predecessor ===
v184 >@ <|@
instruction <@EndNode|@org.graalvm.compiler.nodes.EndNode>@  <|@  <|@
    end_IR
  end_block
  begin_block
    name "B24"
    from_bci -1
    to_bci -1
    predecessors "B11" 
    successors "B27" 
    xhandlers
    flags 
    probability 2355382605114769408
    begin_IR
      HIR
f <@#|@fixed with next>@ <|@
tid v172 <|@
d <@d|@=== Debug Properties ===
nodeSourcePosition: at java.lang.String.lastIndexOf(String.java:1873) [bci: 17]
stamp: void
=== Inputs ===
=== Succesors ===
next: v211 
=== Usages ===
=== Predecessor ===
v173 >@ <|@
instruction <@Begin|@org.graalvm.compiler.nodes.BeginNode>@ #next: v211  <|@  <|@
f <@~|@floating>@ <|@
tid i212 <|@
d <@d|@=== Debug Properties ===
isDefaultStable: false
rawvalue: -22291
stableDimension: 0
stamp: i32 [-22291] ⇊00000000ffffa8ed ⇈00000000ffffa8ed
stampKind: i32
value: int[-22291|0xffffffffffffa8ed]
=== Inputs ===
=== Succesors ===
=== Usages ===
i198 
=== Predecessor ===
- >@ <|@
instruction <@Constant|@org.graalvm.compiler.nodes.ConstantNode>@  <|@  <|@
f <@*|@fixed>@ <|@
tid v211 <|@
d <@d|@=== Debug Properties ===
stamp: void
=== Inputs ===
=== Succesors ===
=== Usages ===
v194 
=== Predecessor ===
v172 >@ <|@
instruction <@EndNode|@org.graalvm.compiler.nodes.EndNode>@  <|@  <|@
    end_IR
  end_block
  begin_block
    name "B25"
    from_bci -1
    to_bci -1
    predecessors "B7" 
    successors "B27" 
    xhandlers
    flags 
    probability 2355382605114769408
    begin_IR
      HIR
f <@#|@fixed with next>@ <|@
tid v229 <|@
d <@d|@=== Debug Properties ===
nodeSourcePosition: at java.lang.String.lastIndexOf(String.java:1888) [bci: 72]
stamp: void
=== Inputs ===
=== Succesors ===
next: v242 
=== Usages ===
=== Predecessor ===
v230 >@ <|@
instruction <@Begin|@org.graalvm.compiler.nodes.BeginNode>@ #next: v242  <|@  <|@
f <@*|@fixed>@ <|@
tid v242 <|@
d <@d|@=== Debug Properties ===
nodeSourcePosition: at java.lang.String.lastIndexOf(String.java:1888) [bci: 72]
stamp: void
=== Inputs ===
=== Succesors ===
=== Usages ===
v194 
=== Predecessor ===
v229 >@ <|@
instruction <@EndNode|@org.graalvm.compiler.nodes.EndNode>@  <|@  <|@
    end_IR
  end_block
  begin_block
    name "B26"
    from_bci -1
    to_bci -1
    predecessors "B6" 
    successors "B27" 
    xhandlers
    flags 
    probability 2355382605114769408
    begin_IR
      HIR
f <@#|@fixed with next>@ <|@
tid v228 <|@
d <@d|@=== Debug Properties ===
nodeSourcePosition: at java.lang.String.lastIndexOf(String.java:1888) [bci: 72]
stamp: void
=== Inputs ===
=== Succesors ===
next: v206 
=== Usages ===
=== Predecessor ===
v232 >@ <|@
instruction <@Begin|@org.graalvm.compiler.nodes.BeginNode>@ #next: v206  <|@  <|@
f <@*|@fixed>@ <|@
tid v206 <|@
d <@d|@=== Debug Properties ===
stamp: void
=== Inputs ===
=== Succesors ===
=== Usages ===
v194 
=== Predecessor ===
v228 >@ <|@
instruction <@EndNode|@org.graalvm.compiler.nodes.EndNode>@  <|@  <|@
    end_IR
  end_block
  begin_block
    name "B27"
    from_bci -1
    to_bci -1
    predecessors "B1" "B3" "B10" "B26" "B13" "B24" "B23" "B25" 
    successors 
    xhandlers
    flags 
    probability 2368893403996880896
    begin_IR
      HIR
f <@~|@floating>@ <|@
tid i198 <|@
d <@d|@=== Debug Properties ===
stamp: i32 [-33924 - -22035] ⇊00000000ffff0064 ⇈00000000fffffffd
valueDescription: i32
=== Inputs ===
merge: v194 
values: i196 i202 i205 i207 i210 i212 i216 i207 
=== Succesors ===
=== Usages ===
v200 
=== Predecessor ===
- >@ <|@
instruction <@ValuePhi|@org.graalvm.compiler.nodes.ValuePhiNode>@ merge: v194 values: i196 i202 i205 i207 i210 i212 i216 i207  <|@  <|@
f <@~|@floating>@ <|@
tid a199 <|@
d <@d|@=== Debug Properties ===
stamp: a# Lcom/oracle/graal/enterprise/k/d$a;
valueDescription: a -
=== Inputs ===
merge: v194 
values: a197 a203 a203 a208 a203 a203 a203 a208 
=== Succesors ===
=== Usages ===
v200 
=== Predecessor ===
- >@ <|@
instruction <@ValuePhi|@org.graalvm.compiler.nodes.ValuePhiNode>@ merge: v194 values: a197 a203 a203 a208 a203 a203 a203 a208  <|@  <|@
f <@#|@fixed with next>@ <|@
tid v194 <|@
d <@d|@=== Debug Properties ===
stamp: void
=== Inputs ===
stateAfter: - 
ends: v195 v201 v204 v206 v209 v211 v215 v242 
=== Succesors ===
next: v200 
=== Usages ===
i198 a199 
=== Predecessor ===
- >@ <|@
instruction <@Merge|@org.graalvm.compiler.nodes.MergeNode>@ stateAfter: - ends: v195 v201 v204 v206 v209 v211 v215 v242 #next: v200  <|@  <|@
f <@*|@fixed>@ <|@
tid v200 <|@
d <@d|@=== Debug Properties ===
stamp: void
=== Inputs ===
stateBefore: ?8 
actionAndReason: i198 
speculation: a199 
=== Succesors ===
=== Usages ===
=== Predecessor ===
v194 >@ <|@
instruction <@DynamicDeoptimize|@org.graalvm.compiler.nodes.DynamicDeoptimizeNode>@ stateBefore: ?8 actionAndReason: i198 speculation: a199  <|@  <|@
    end_IR
  end_block
end_cfg
begin_cfg
  name "After LIR generation"
  begin_block
    name "B0"
    from_bci -1
    to_bci -1
    predecessors 
    successors "B1" "B2" 
    xhandlers
    flags 
    probability 4607182418800017408
    begin_IR
      HIR
f <@#|@fixed with next>@ <|@
tid v0 <|@
d <@d|@=== Debug Properties ===
stamp: void
=== Inputs ===
stateAfter: - 
=== Succesors ===
next: v157 
=== Usages ===
=== Predecessor ===
- >@ <|@
instruction <@StartNode|@org.graalvm.compiler.nodes.StartNode>@ stateAfter: - #next: v157  <|@  <|@
f <@~|@floating>@ <|@
tid a1 <|@
result v0|QWORD[.] <|@
d <@d|@=== Debug Properties ===
index: 0
stamp: a# [C
uncheckedStamp: [null]
=== Inputs ===
=== Succesors ===
=== Usages ===
?8 ?29 v241 v105 v240 
=== Predecessor ===
- >@ <|@
instruction <@Parameter|@org.graalvm.compiler.nodes.ParameterNode>@  <|@  <|@
f <@~|@floating>@ <|@
tid i2 <|@
result v1|DWORD <|@
d <@d|@=== Debug Properties ===
index: 1
stamp: i32
uncheckedStamp: [null]
=== Inputs ===
=== Succesors ===
=== Usages ===
?8 i22 ?29 i68 
=== Predecessor ===
- >@ <|@
instruction <@Parameter|@org.graalvm.compiler.nodes.ParameterNode>@  <|@  <|@
f <@~|@floating>@ <|@
tid i3 <|@
result v2|DWORD <|@
d <@d|@=== Debug Properties ===
index: 2
stamp: i32
uncheckedStamp: [null]
=== Inputs ===
=== Succesors ===
=== Usages ===
?8 i9 
=== Predecessor ===
- >@ <|@
instruction <@Parameter|@org.graalvm.compiler.nodes.ParameterNode>@  <|@  <|@
f <@~|@floating>@ <|@
tid a4 <|@
result v3|QWORD[.] <|@
d <@d|@=== Debug Properties ===
index: 3
stamp: a# [C
uncheckedStamp: [null]
=== Inputs ===
=== Succesors ===
=== Usages ===
?8 v239 ?29 v238 
=== Predecessor ===
- >@ <|@
instruction <@Parameter|@org.graalvm.compiler.nodes.ParameterNode>@  <|@  <|@
f <@~|@floating>@ <|@
tid i5 <|@
result v4|DWORD <|@
d <@d|@=== Debug Properties ===
index: 4
stamp: i32
uncheckedStamp: [null]
=== Inputs ===
=== Succesors ===
=== Usages ===
?8 i17 
=== Predecessor ===
- >@ <|@
instruction <@Parameter|@org.graalvm.compiler.nodes.ParameterNode>@  <|@  <|@
f <@~|@floating>@ <|@
tid i6 <|@
result v5|DWORD <|@
d <@d|@=== Debug Properties ===
index: 5
stamp: i32
uncheckedStamp: [null]
=== Inputs ===
=== Succesors ===
=== Usages ===
?8 i9 v15 i17 i22 ?29 i50 
=== Predecessor ===
- >@ <|@
instruction <@Parameter|@org.graalvm.compiler.nodes.ParameterNode>@  <|@  <|@
f <@~|@floating>@ <|@
tid i7 <|@
result v6|DWORD <|@
d <@d|@=== Debug Properties ===
index: 6
stamp: i32
uncheckedStamp: [null]
=== Inputs ===
=== Succesors ===
=== Usages ===
?8 v11 v13 
=== Predecessor ===
- >@ <|@
instruction <@Parameter|@org.graalvm.compiler.nodes.ParameterNode>@  <|@  <|@
tid ?8 <|@
d <@d|@=== Debug Properties ===
bci: 0
code: ResolvedJavaMethodBytecode<String.lastIndexOf(char[], int, int, char[], int, int, int)>
duringCall: false
localsSize: 15
locksSize: 0
rethrowException: false
sourceFile: String.java
sourceLine: 1869
stackSize: 0
=== Inputs ===
outerFrameState: - 
values: a1 i2 i3 a4 i5 i6 i7 - - - - - - - - 
=== Succesors ===
=== Usages ===
v200 i234 
=== Predecessor ===
- >@ <|@
instruction <@FrameState|@org.graalvm.compiler.nodes.FrameState>@ outerFrameState: - values: a1 i2 i3 a4 i5 i6 i7 - - - - - - - -  <|@  <|@
f <@~|@floating>@ <|@
tid v105 <|@
d <@d|@=== Debug Properties ===
nodeSourcePosition: at java.lang.String.lastIndexOf(String.java:1888) [bci: 72]
stamp: void
=== Inputs ===
value: a1 
=== Succesors ===
=== Usages ===
v157 
=== Predecessor ===
- >@ <|@
instruction <@IsNull|@org.graalvm.compiler.nodes.calc.IsNullNode>@ value: a1  <|@  <|@
f <@*|@fixed>@ <|@
tid v157 <|@
d <@d|@=== Debug Properties ===
nodeSourcePosition: at java.lang.String.lastIndexOf(String.java:1888) [bci: 72]
stamp: void
trueSuccessorProbability: 0.0
=== Inputs ===
condition: v105 
=== Succesors ===
trueSuccessor: v156 
falseSuccessor: v154 
=== Usages ===
=== Predecessor ===
v0 >@ <|@
instruction <@If|@org.graalvm.compiler.nodes.IfNode>@ condition: v105 #trueSuccessor: v156 #falseSuccessor: v154  <|@  <|@
    end_IR
    begin_IR
      LIR
      nr   -1  <|@ instruction [rsi|QWORD[.], rdx|DWORD, rcx|DWORD, r8|QWORD[.], r9|DWORD, rdi|DWORD, in:0|DWORD, rbp|QWORD] = LABEL numbPhis: 0 align: false label: ? <|@ <|@
      nr   -1  <|@ instruction stack:16|QWORD = MOVE rbp|QWORD moveKind: QWORD <|@ <|@
      nr   -1  <|@ instruction [] = HOTSPOTLOCKSTACK frameMapBuilder: org.graalvm.compiler.lir.amd64.AMD64FrameMapBuilder@6dfa0585 slotKind: QWORD <|@ <|@
      nr   -1  <|@ instruction v0|QWORD[.] = MOVE rsi|QWORD[.] moveKind: QWORD <|@ <|@
      nr   -1  <|@ instruction v1|DWORD = MOVE rdx|DWORD moveKind: DWORD <|@ <|@
      nr   -1  <|@ instruction v2|DWORD = MOVE rcx|DWORD moveKind: DWORD <|@ <|@
      nr   -1  <|@ instruction v3|QWORD[.] = MOVE r8|QWORD[.] moveKind: QWORD <|@ <|@
      nr   -1  <|@ instruction v4|DWORD = MOVE r9|DWORD moveKind: DWORD <|@ <|@
      nr   -1  <|@ instruction v5|DWORD = MOVE rdi|DWORD moveKind: DWORD <|@ <|@
      nr   -1  <|@ instruction v6|DWORD = MOVE in:0|DWORD moveKind: DWORD <|@ <|@
      nr   -1  <|@ instruction TEST (x: v0|QWORD[.], y: v0|QWORD[.]) size: QWORD <|@ <|@
      nr   -1  <|@ instruction BRANCH trueDestinationProbability: 0.0 condition: = trueDestination: B0 -> B1 falseDestination: B0 -> B2 <|@ <|@
    end_IR
  end_block
  begin_block
    name "B1"
    from_bci -1
    to_bci -1
    predecessors "B0" 
    successors "B27" 
    xhandlers
    flags 
    probability 2355382605114769408
    begin_IR
      HIR
f <@#|@fixed with next>@ <|@
tid v156 <|@
d <@d|@=== Debug Properties ===
nodeSourcePosition: at java.lang.String.lastIndexOf(String.java:1888) [bci: 72]
stamp: void
=== Inputs ===
=== Succesors ===
next: v195 
=== Usages ===
=== Predecessor ===
v157 >@ <|@
instruction <@Begin|@org.graalvm.compiler.nodes.BeginNode>@ #next: v195  <|@  <|@
f <@~|@floating>@ <|@
tid a197 <|@
result v7|QWORD[.] <|@
d <@d|@=== Debug Properties ===
isDefaultStable: false
rawvalue: d.a@506959935
stableDimension: 0
stamp: a!# Lcom/oracle/graal/enterprise/k/d$a;
stampKind: a -
value: Object[d.a@506959935]
=== Inputs ===
=== Succesors ===
=== Usages ===
a199 
=== Predecessor ===
- >@ <|@
instruction <@Constant|@org.graalvm.compiler.nodes.ConstantNode>@  <|@  <|@
f <@~|@floating>@ <|@
tid i196 <|@
result int[-27147|0xffffffffffff95f5] <|@
d <@d|@=== Debug Properties ===
isDefaultStable: false
rawvalue: -27147
stableDimension: 0
stamp: i32 [-27147] ⇊00000000ffff95f5 ⇈00000000ffff95f5
stampKind: i32
value: int[-27147|0xffffffffffff95f5]
=== Inputs ===
=== Succesors ===
=== Usages ===
i198 
=== Predecessor ===
- >@ <|@
instruction <@Constant|@org.graalvm.compiler.nodes.ConstantNode>@  <|@  <|@
f <@*|@fixed>@ <|@
tid v195 <|@
d <@d|@=== Debug Properties ===
stamp: void
=== Inputs ===
=== Succesors ===
=== Usages ===
v194 
=== Predecessor ===
v156 >@ <|@
instruction <@EndNode|@org.graalvm.compiler.nodes.EndNode>@  <|@  <|@
    end_IR
    begin_IR
      LIR
      nr   -1  <|@ instruction [] = LABEL numbPhis: 0 align: false label: ? <|@ <|@
      nr   -1  <|@ instruction v7|QWORD[.] = HOTSPOTLOADOBJECTCONSTANT input: Object[d.a@506959935] <|@ <|@
      nr   -1  <|@ instruction JUMP ~[int[-27147|0xffffffffffff95f5], v7|QWORD[.]] destination: B1 -> B27 <|@ <|@
    end_IR
  end_block
  begin_block
    name "B2"
    from_bci -1
    to_bci -1
    predecessors "B0" 
    successors "B3" "B4" 
    xhandlers
    flags 
    probability 4607182418800017408
    begin_IR
      HIR
f <@#|@fixed with next>@ <|@
tid v154 <|@
d <@d|@=== Debug Properties ===
nodeSourcePosition: at java.lang.String.lastIndexOf(String.java:1888) [bci: 72]
stamp: void
=== Inputs ===
=== Succesors ===
next: v161 
=== Usages ===
=== Predecessor ===
v157 >@ <|@
instruction <@Begin|@org.graalvm.compiler.nodes.BeginNode>@ #next: v161  <|@  <|@
f <@~|@floating>@ <|@
tid a203 <|@
result Object[null] <|@
d <@d|@=== Debug Properties ===
isDefaultStable: false
rawvalue: null
stableDimension: 0
stamp: a - NULL
stampKind: a -
value: Object[null]
=== Inputs ===
=== Succesors ===
=== Usages ===
a199 a199 a199 a199 a199 
=== Predecessor ===
- >@ <|@
instruction <@Constant|@org.graalvm.compiler.nodes.ConstantNode>@  <|@  <|@
f <@~|@floating>@ <|@
tid i22 <|@
result v8|DWORD <|@
d <@d|@=== Debug Properties ===
getOp: org.graalvm.compiler.nodes.calc.AddNode$$Lambda$15/1271304513@1406efde
nodeSourcePosition: at java.lang.String.lastIndexOf(String.java:1883) [bci: 50]
stamp: i32
=== Inputs ===
x: i2 
y: i6 
=== Succesors ===
=== Usages ===
i23 
=== Predecessor ===
- >@ <|@
instruction <@+|@org.graalvm.compiler.nodes.calc.AddNode>@ x: i2 y: i6  <|@  <|@
f <@~|@floating>@ <|@
tid i19 <|@
result int[-1|0xffffffffffffffff] <|@
d <@d|@=== Debug Properties ===
isDefaultStable: false
nodeSourcePosition: at java.lang.String.lastIndexOf(String.java:1881) [bci: 38]
rawvalue: -1
stableDimension: 0
stamp: i32 [-1] ⇊00000000ffffffff
stampKind: i32
value: int[-1|0xffffffffffffffff]
=== Inputs ===
=== Succesors ===
=== Usages ===
i20 i23 i42 i50 v67 
=== Predecessor ===
- >@ <|@
instruction <@Constant|@org.graalvm.compiler.nodes.ConstantNode>@  <|@  <|@
f <@~|@floating>@ <|@
tid i23 <|@
result v9|DWORD <|@
d <@d|@=== Debug Properties ===
getOp: org.graalvm.compiler.nodes.calc.AddNode$$Lambda$15/1271304513@1406efde
nodeSourcePosition: at java.lang.String.lastIndexOf(String.java:1883) [bci: 52]
stamp: i32
=== Inputs ===
x: i22 
y: i19 
=== Succesors ===
=== Usages ===
i24 ?29 v30 v131 v148 
=== Predecessor ===
- >@ <|@
instruction <@+|@org.graalvm.compiler.nodes.calc.AddNode>@ x: i22 y: i19  <|@  <|@
f <@~|@floating>@ <|@
tid i130 <|@
result int[-2147483645|0xffffffff80000003] <|@
d <@d|@=== Debug Properties ===
isDefaultStable: false
nodeSourcePosition: at java.lang.String.lastIndexOf(String.java:1888) [bci: 62]
rawvalue: -2147483645
stableDimension: 0
stamp: i32 [-2147483645] ⇊0000000080000003 ⇈0000000080000003
stampKind: i32
value: int[-2147483645|0xffffffff80000003]
=== Inputs ===
=== Succesors ===
=== Usages ===
v131 
=== Predecessor ===
- >@ <|@
instruction <@Constant|@org.graalvm.compiler.nodes.ConstantNode>@  <|@  <|@
f <@~|@floating>@ <|@
tid v131 <|@
d <@d|@=== Debug Properties ===
condition: LT
nodeSourcePosition: at java.lang.String.lastIndexOf(String.java:1888) [bci: 62]
op: org.graalvm.compiler.nodes.calc.IntegerLessThanNode$LessThanOp@7cc8d043
stamp: void
unorderedIsTrue: false
=== Inputs ===
x: i23 
y: i130 
=== Succesors ===
=== Usages ===
v161 
=== Predecessor ===
- >@ <|@
instruction <@<|@org.graalvm.compiler.nodes.calc.IntegerLessThanNode>@ x: i23 y: i130  <|@  <|@
f <@*|@fixed>@ <|@
tid v161 <|@
d <@d|@=== Debug Properties ===
nodeSourcePosition: at java.lang.String.lastIndexOf(String.java:1888) [bci: 62]
stamp: void
trueSuccessorProbability: 0.0
=== Inputs ===
condition: v131 
=== Succesors ===
trueSuccessor: v160 
falseSuccessor: v158 
=== Usages ===
=== Predecessor ===
v154 >@ <|@
instruction <@If|@org.graalvm.compiler.nodes.IfNode>@ condition: v131 #trueSuccessor: v160 #falseSuccessor: v158  <|@  <|@
    end_IR
    begin_IR
      LIR
      nr   -1  <|@ instruction [] = LABEL numbPhis: 0 align: false label: ? <|@ <|@
      nr   -1  <|@ instruction v8|DWORD = ADD (x: v1|DWORD, y: v5|DWORD) size: DWORD <|@ <|@
      nr   -1  <|@ instruction v9|DWORD = DEC v8|DWORD size: DWORD <|@ <|@
      nr   -1  <|@ instruction CMP v9|DWORD y: -2147483645 size: DWORD <|@ <|@
      nr   -1  <|@ instruction BRANCH trueDestinationProbability: 0.0 condition: < trueDestination: B2 -> B3 falseDestination: B2 -> B4 <|@ <|@
    end_IR
  end_block
  begin_block
    name "B3"
    from_bci -1
    to_bci -1
    predecessors "B2" 
    successors "B27" 
    xhandlers
    flags 
    probability 2355382605114769408
    begin_IR
      HIR
f <@#|@fixed with next>@ <|@
tid v160 <|@
d <@d|@=== Debug Properties ===
nodeSourcePosition: at java.lang.String.lastIndexOf(String.java:1888) [bci: 62]
stamp: void
=== Inputs ===
=== Succesors ===
next: v201 
=== Usages ===
=== Predecessor ===
v161 >@ <|@
instruction <@Begin|@org.graalvm.compiler.nodes.BeginNode>@ #next: v201  <|@  <|@
f <@~|@floating>@ <|@
tid i202 <|@
result int[-33924|0xffffffffffff7b7c] <|@
d <@d|@=== Debug Properties ===
isDefaultStable: false
rawvalue: -33924
stableDimension: 0
stamp: i32 [-33924] ⇊00000000ffff7b7c ⇈00000000ffff7b7c
stampKind: i32
value: int[-33924|0xffffffffffff7b7c]
=== Inputs ===
=== Succesors ===
=== Usages ===
i198 
=== Predecessor ===
- >@ <|@
instruction <@Constant|@org.graalvm.compiler.nodes.ConstantNode>@  <|@  <|@
f <@*|@fixed>@ <|@
tid v201 <|@
d <@d|@=== Debug Properties ===
stamp: void
=== Inputs ===
=== Succesors ===
=== Usages ===
v194 
=== Predecessor ===
v160 >@ <|@
instruction <@EndNode|@org.graalvm.compiler.nodes.EndNode>@  <|@  <|@
    end_IR
    begin_IR
      LIR
      nr   -1  <|@ instruction [] = LABEL numbPhis: 0 align: false label: ? <|@ <|@
      nr   -1  <|@ instruction JUMP ~[int[-33924|0xffffffffffff7b7c], Object[null]] destination: B3 -> B27 <|@ <|@
    end_IR
  end_block
  begin_block
    name "B4"
    from_bci -1
    to_bci -1
    predecessors "B2" 
    successors "B5" "B6" 
    xhandlers
    flags 
    probability 4607182418800017408
    begin_IR
      HIR
f <@#|@fixed with next>@ <|@
tid v158 <|@
d <@d|@=== Debug Properties ===
nodeSourcePosition: at java.lang.String.lastIndexOf(String.java:1888) [bci: 62]
stamp: void
=== Inputs ===
=== Succesors ===
next: v224 
=== Usages ===
v27 j143 
=== Predecessor ===
v161 >@ <|@
instruction <@Begin|@org.graalvm.compiler.nodes.BeginNode>@ #next: v224  <|@  <|@
f <@~|@floating>@ <|@
tid i18 <|@
result int[1|0x1] <|@
d <@d|@=== Debug Properties ===
isDefaultStable: false
nodeSourcePosition: at java.lang.String.lastIndexOf(String.java:1881) [bci: 37]
rawvalue: 1
stableDimension: 0
stamp: i32 [1] ⇊0000000000000001 ⇈0000000000000001
stampKind: i32
value: int[1|0x1]
=== Inputs ===
=== Succesors ===
=== Usages ===
i69 i137 
=== Predecessor ===
- >@ <|@
instruction <@Constant|@org.graalvm.compiler.nodes.ConstantNode>@  <|@  <|@
f <@~|@floating>@ <|@
tid i9 <|@
result v10|DWORD <|@
d <@d|@=== Debug Properties ===
getOp: org.graalvm.compiler.nodes.calc.SubNode$$Lambda$64/1952983589@24889bdf
nodeSourcePosition: at java.lang.String.lastIndexOf(String.java:1869) [bci: 3]
stamp: i32
=== Inputs ===
x: i3 
y: i6 
=== Succesors ===
=== Usages ===
v13 i24 i137 
=== Predecessor ===
- >@ <|@
instruction <@-|@org.graalvm.compiler.nodes.calc.SubNode>@ x: i3 y: i6  <|@  <|@
f <@~|@floating>@ <|@
tid i24 <|@
result v11|DWORD <|@
d <@d|@=== Debug Properties ===
getOp: org.graalvm.compiler.nodes.calc.AddNode$$Lambda$15/1271304513@1406efde
nodeSourcePosition: at java.lang.String.lastIndexOf(String.java:1884) [bci: 59]
stamp: i32
=== Inputs ===
x: i9 
y: i23 
=== Succesors ===
=== Usages ===
i28 j136 v145 v148 
=== Predecessor ===
- >@ <|@
instruction <@+|@org.graalvm.compiler.nodes.calc.AddNode>@ x: i9 y: i23  <|@  <|@
f <@~|@floating>@ <|@
tid v148 <|@
d <@d|@=== Debug Properties ===
condition: LT
op: org.graalvm.compiler.nodes.calc.IntegerLessThanNode$LessThanOp@7cc8d043
stamp: void
unorderedIsTrue: false
=== Inputs ===
x: i24 
y: i23 
=== Succesors ===
=== Usages ===
v224 
=== Predecessor ===
- >@ <|@
instruction <@<|@org.graalvm.compiler.nodes.calc.IntegerLessThanNode>@ x: i24 y: i23  <|@  <|@
f <@*|@fixed>@ <|@
tid v224 <|@
d <@d|@=== Debug Properties ===
nodeSourcePosition: at java.lang.String.lastIndexOf(String.java:1888) [bci: 72]
stamp: void
trueSuccessorProbability: 0.5
=== Inputs ===
condition: v148 
=== Succesors ===
trueSuccessor: v220 
falseSuccessor: v223 
=== Usages ===
=== Predecessor ===
v158 >@ <|@
instruction <@If|@org.graalvm.compiler.nodes.IfNode>@ condition: v148 #trueSuccessor: v220 #falseSuccessor: v223  <|@  <|@
    end_IR
    begin_IR
      LIR
      nr   -1  <|@ instruction [] = LABEL numbPhis: 0 align: false label: ? <|@ <|@
      nr   -1  <|@ instruction v10|DWORD = SUB (x: v2|DWORD, ~y: v5|DWORD) size: DWORD <|@ <|@
      nr   -1  <|@ instruction v11|DWORD = ADD (x: v10|DWORD, y: v9|DWORD) size: DWORD <|@ <|@
      nr   -1  <|@ instruction CMP (x: v9|DWORD, y: v11|DWORD) size: DWORD <|@ <|@
      nr   -1  <|@ instruction BRANCH trueDestinationProbability: 0.5 condition: > trueDestination: B4 -> B5 falseDestination: B4 -> B6 <|@ <|@
    end_IR
  end_block
  begin_block
    name "B5"
    from_bci -1
    to_bci -1
    predecessors "B4" 
    successors "B9" 
    xhandlers
    flags 
    probability 4602678819172646912
    begin_IR
      HIR
f <@#|@fixed with next>@ <|@
tid v220 <|@
d <@d|@=== Debug Properties ===
nodeSourcePosition: at java.lang.String.lastIndexOf(String.java:1888) [bci: 72]
stamp: void
=== Inputs ===
=== Succesors ===
next: v218 
=== Usages ===
=== Predecessor ===
v224 >@ <|@
instruction <@Begin|@org.graalvm.compiler.nodes.BeginNode>@ #next: v218  <|@  <|@
f <@*|@fixed>@ <|@
tid v218 <|@
d <@d|@=== Debug Properties ===
nodeSourcePosition: at java.lang.String.lastIndexOf(String.java:1888) [bci: 72]
stamp: void
=== Inputs ===
=== Succesors ===
=== Usages ===
v217 
=== Predecessor ===
v220 >@ <|@
instruction <@EndNode|@org.graalvm.compiler.nodes.EndNode>@  <|@  <|@
    end_IR
    begin_IR
      LIR
      nr   -1  <|@ instruction [] = LABEL numbPhis: 0 align: false label: ? <|@ <|@
      nr   -1  <|@ instruction JUMP ~[] destination: B5 -> B9 <|@ <|@
    end_IR
  end_block
  begin_block
    name "B6"
    from_bci -1
    to_bci -1
    predecessors "B4" 
    successors "B7" "B26" 
    xhandlers
    flags 
    probability 4602678819172646912
    begin_IR
      HIR
f <@#|@fixed with next>@ <|@
tid v223 <|@
d <@d|@=== Debug Properties ===
nodeSourcePosition: at java.lang.String.lastIndexOf(String.java:1888) [bci: 72]
stamp: void
=== Inputs ===
=== Succesors ===
next: i233 
=== Usages ===
=== Predecessor ===
v224 >@ <|@
instruction <@Begin|@org.graalvm.compiler.nodes.BeginNode>@ #next: i233  <|@  <|@
f <@~|@floating>@ <|@
tid v240 <|@
result [v0|QWORD[.] + 12] <|@
d <@d|@=== Debug Properties ===
displacement: 12
scale: Times1
stamp: void*
=== Inputs ===
base: a1 
index: - 
=== Succesors ===
=== Usages ===
i233 
=== Predecessor ===
- >@ <|@
instruction <@AMD64Address|@org.graalvm.compiler.core.amd64.AMD64AddressNode>@ base: a1 index: -  <|@  <|@
f <@#|@fixed with next>@ <|@
tid i233 <|@
result v12|DWORD <|@
d <@d|@=== Debug Properties ===
barrierType: NONE
forceFixed: false
location: [].length:final
nodeSourcePosition: at java.lang.String.lastIndexOf(String.java:1888) [bci: 72]
nullCheck: false
stamp: i32 [0 - 2147483647] ⇈000000007fffffff
=== Inputs ===
stateBefore: - 
guard: - 
address: v240 
=== Succesors ===
next: v232 
=== Usages ===
v145 j134 
=== Predecessor ===
v223 >@ <|@
instruction <@Read|@org.graalvm.compiler.nodes.memory.ReadNode>@ stateBefore: - guard: - address: v240 #next: v232  <|@  <|@
f <@~|@floating>@ <|@
tid j136 <|@
result v13|QWORD <|@
d <@d|@=== Debug Properties ===
getOp: org.graalvm.compiler.nodes.calc.SignExtendNode$$Lambda$11/490840598@f525850
getReverseOp: org.graalvm.compiler.nodes.calc.SignExtendNode$$Lambda$12/742109885@1e2e35ef
inputBits: 32
resultBits: 64
stamp: i64 [-2147483648 - 2147483647]
=== Inputs ===
value: i24 
=== Succesors ===
=== Usages ===
j152 
=== Predecessor ===
- >@ <|@
instruction <@SignExtend|@org.graalvm.compiler.nodes.calc.SignExtendNode>@ value: i24  <|@  <|@
f <@~|@floating>@ <|@
tid i137 <|@
result v14|DWORD <|@
d <@d|@=== Debug Properties ===
getOp: org.graalvm.compiler.nodes.calc.AddNode$$Lambda$15/1271304513@1406efde
stamp: i32
=== Inputs ===
x: i9 
y: i18 
=== Succesors ===
=== Usages ===
j138 
=== Predecessor ===
- >@ <|@
instruction <@+|@org.graalvm.compiler.nodes.calc.AddNode>@ x: i9 y: i18  <|@  <|@
f <@~|@floating>@ <|@
tid j138 <|@
result v15|QWORD <|@
d <@d|@=== Debug Properties ===
getOp: org.graalvm.compiler.nodes.calc.SignExtendNode$$Lambda$11/490840598@f525850
getReverseOp: org.graalvm.compiler.nodes.calc.SignExtendNode$$Lambda$12/742109885@1e2e35ef
inputBits: 32
resultBits: 64
stamp: i64 [-2147483648 - 2147483647]
=== Inputs ===
value: i137 
=== Succesors ===
=== Usages ===
j140 
=== Predecessor ===
- >@ <|@
instruction <@SignExtend|@org.graalvm.compiler.nodes.calc.SignExtendNode>@ value: i137  <|@  <|@
f <@~|@floating>@ <|@
tid j135 <|@
result long[-1|0xffffffffffffffff] <|@
d <@d|@=== Debug Properties ===
isDefaultStable: false
rawvalue: -1
stableDimension: 0
stamp: i64 [-1] ⇊ffffffffffffffff
stampKind: i64
value: long[-1|0xffffffffffffffff]
=== Inputs ===
=== Succesors ===
=== Usages ===
j140 
=== Predecessor ===
- >@ <|@
instruction <@Constant|@org.graalvm.compiler.nodes.ConstantNode>@  <|@  <|@
f <@~|@floating>@ <|@
tid j140 <|@
result v16|QWORD <|@
d <@d|@=== Debug Properties ===
getOp: org.graalvm.compiler.nodes.calc.AddNode$$Lambda$15/1271304513@1406efde
stamp: i64 [-2147483649 - 2147483646]
=== Inputs ===
x: j138 
y: j135 
=== Succesors ===
=== Usages ===
j152 
=== Predecessor ===
- >@ <|@
instruction <@+|@org.graalvm.compiler.nodes.calc.AddNode>@ x: j138 y: j135  <|@  <|@
f <@~|@floating>@ <|@
tid j152 <|@
result v17|QWORD <|@
d <@d|@=== Debug Properties ===
getOp: org.graalvm.compiler.nodes.calc.SubNode$$Lambda$64/1952983589@24889bdf
stamp: i64 [-4294967294 - 4294967296]
=== Inputs ===
x: j136 
y: j140 
=== Succesors ===
=== Usages ===
j143 
=== Predecessor ===
- >@ <|@
instruction <@-|@org.graalvm.compiler.nodes.calc.SubNode>@ x: j136 y: j140  <|@  <|@
f <@~|@floating>@ <|@
tid j143 <|@
result v17|QWORD <|@
d <@d|@=== Debug Properties ===
stamp: i64 [-4294967294 - 4294967296]
=== Inputs ===
guard: v158 
object: j152 
=== Succesors ===
=== Usages ===
v144 
=== Predecessor ===
- >@ <|@
instruction <@GuardedValue|@org.graalvm.compiler.nodes.GuardedValueNode>@ guard: v158 object: j152  <|@  <|@
f <@~|@floating>@ <|@
tid j134 <|@
result v18|QWORD <|@
d <@d|@=== Debug Properties ===
getOp: org.graalvm.compiler.nodes.calc.ZeroExtendNode$$Lambda$16/887152589@6b9fc47b
getReverseOp: org.graalvm.compiler.nodes.calc.ZeroExtendNode$$Lambda$17/1263733897@4844aec9
inputAlwaysPositive: true
inputBits: 32
resultBits: 64
stamp: i64 [0 - 2147483647] ⇈000000007fffffff
=== Inputs ===
value: i233 
=== Succesors ===
=== Usages ===
v144 
=== Predecessor ===
- >@ <|@
instruction <@ZeroExtend|@org.graalvm.compiler.nodes.calc.ZeroExtendNode>@ value: i233  <|@  <|@
f <@~|@floating>@ <|@
tid v144 <|@
d <@d|@=== Debug Properties ===
condition: BT
op: org.graalvm.compiler.nodes.calc.IntegerBelowNode$BelowOp@19d5dcf
stamp: void
unorderedIsTrue: false
=== Inputs ===
x: j143 
y: j134 
=== Succesors ===
=== Usages ===
v232 
=== Predecessor ===
- >@ <|@
instruction <@|<||@org.graalvm.compiler.nodes.calc.IntegerBelowNode>@ x: j143 y: j134  <|@  <|@
f <@~|@floating>@ <|@
tid a208 <|@
result v19|QWORD[.] <|@
d <@d|@=== Debug Properties ===
isDefaultStable: false
rawvalue: d.a@800922110
stableDimension: 0
stamp: a!# Lcom/oracle/graal/enterprise/k/d$a;
stampKind: a -
value: Object[d.a@800922110]
=== Inputs ===
=== Succesors ===
=== Usages ===
a199 a199 
=== Predecessor ===
- >@ <|@
instruction <@Constant|@org.graalvm.compiler.nodes.ConstantNode>@  <|@  <|@
f <@~|@floating>@ <|@
tid i207 <|@
result int[-28443|0xffffffffffff90e5] <|@
d <@d|@=== Debug Properties ===
isDefaultStable: false
rawvalue: -28443
stableDimension: 0
stamp: i32 [-28443] ⇊00000000ffff90e5 ⇈00000000ffff90e5
stampKind: i32
value: int[-28443|0xffffffffffff90e5]
=== Inputs ===
=== Succesors ===
=== Usages ===
i198 i198 
=== Predecessor ===
- >@ <|@
instruction <@Constant|@org.graalvm.compiler.nodes.ConstantNode>@  <|@  <|@
f <@*|@fixed>@ <|@
tid v232 <|@
d <@d|@=== Debug Properties ===
nodeSourcePosition: at java.lang.String.lastIndexOf(String.java:1888) [bci: 72]
stamp: void
trueSuccessorProbability: 1.0
=== Inputs ===
condition: v144 
=== Succesors ===
trueSuccessor: v231 
falseSuccessor: v228 
=== Usages ===
=== Predecessor ===
i233 >@ <|@
instruction <@If|@org.graalvm.compiler.nodes.IfNode>@ condition: v144 #trueSuccessor: v231 #falseSuccessor: v228  <|@  <|@
    end_IR
    begin_IR
      LIR
      nr   -1  <|@ instruction [] = LABEL numbPhis: 0 align: false label: ? <|@ <|@
      nr   -1  <|@ instruction v12|DWORD = MOV [v0|QWORD[.] + 12] size: DWORD <|@ <|@
      nr   -1  <|@ instruction v13|QWORD = MOVSXD v11|DWORD size: QWORD <|@ <|@
      nr   -1  <|@ instruction v14|DWORD = INC v10|DWORD size: DWORD <|@ <|@
      nr   -1  <|@ instruction v15|QWORD = MOVSXD v14|DWORD size: QWORD <|@ <|@
      nr   -1  <|@ instruction v16|QWORD = DEC v15|QWORD size: QWORD <|@ <|@
      nr   -1  <|@ instruction v17|QWORD = SUB (x: v13|QWORD, ~y: v16|QWORD) size: QWORD <|@ <|@
      nr   -1  <|@ instruction v18|QWORD = MOV v12|DWORD size: DWORD <|@ <|@
      nr   -1  <|@ instruction v19|QWORD[.] = HOTSPOTLOADOBJECTCONSTANT input: Object[d.a@800922110] <|@ <|@
      nr   -1  <|@ instruction CMP (x: v18|QWORD, y: v17|QWORD) size: QWORD <|@ <|@
      nr   -1  <|@ instruction BRANCH trueDestinationProbability: 1.0 condition: |>| trueDestination: B6 -> B7 falseDestination: B6 -> B26 <|@ <|@
    end_IR
  end_block
  begin_block
    name "B7"
    from_bci -1
    to_bci -1
    predecessors "B6" 
    successors "B8" "B25" 
    xhandlers
    flags 
    probability 4602678819172646912
    begin_IR
      HIR
f <@#|@fixed with next>@ <|@
tid v231 <|@
d <@d|@=== Debug Properties ===
nodeSourcePosition: at java.lang.String.lastIndexOf(String.java:1888) [bci: 72]
stamp: void
=== Inputs ===
=== Succesors ===
next: v230 
=== Usages ===
=== Predecessor ===
v232 >@ <|@
instruction <@Begin|@org.graalvm.compiler.nodes.BeginNode>@ #next: v230  <|@  <|@
f <@~|@floating>@ <|@
tid v145 <|@
d <@d|@=== Debug Properties ===
condition: BT
op: org.graalvm.compiler.nodes.calc.IntegerBelowNode$BelowOp@19d5dcf
stamp: void
unorderedIsTrue: false
=== Inputs ===
x: i24 
y: i233 
=== Succesors ===
=== Usages ===
v230 
=== Predecessor ===
- >@ <|@
instruction <@|<||@org.graalvm.compiler.nodes.calc.IntegerBelowNode>@ x: i24 y: i233  <|@  <|@
f <@*|@fixed>@ <|@
tid v230 <|@
d <@d|@=== Debug Properties ===
nodeSourcePosition: at java.lang.String.lastIndexOf(String.java:1888) [bci: 72]
stamp: void
trueSuccessorProbability: 1.0
=== Inputs ===
condition: v145 
=== Succesors ===
trueSuccessor: v221 
falseSuccessor: v229 
=== Usages ===
=== Predecessor ===
v231 >@ <|@
instruction <@If|@org.graalvm.compiler.nodes.IfNode>@ condition: v145 #trueSuccessor: v221 #falseSuccessor: v229  <|@  <|@
    end_IR
    begin_IR
      LIR
      nr   -1  <|@ instruction [] = LABEL numbPhis: 0 align: false label: ? <|@ <|@
      nr   -1  <|@ instruction CMP (x: v12|DWORD, y: v11|DWORD) size: DWORD <|@ <|@
      nr   -1  <|@ instruction BRANCH trueDestinationProbability: 1.0 condition: |>| trueDestination: B7 -> B8 falseDestination: B7 -> B25 <|@ <|@
    end_IR
  end_block
  begin_block
    name "B8"
    from_bci -1
    to_bci -1
    predecessors "B7" 
    successors "B9" 
    xhandlers
    flags 
    probability 4602678819172646912
    begin_IR
      HIR
f <@#|@fixed with next>@ <|@
tid v221 <|@
d <@d|@=== Debug Properties ===
nodeSourcePosition: at java.lang.String.lastIndexOf(String.java:1888) [bci: 72]
stamp: void
=== Inputs ===
=== Succesors ===
next: v219 
=== Usages ===
=== Predecessor ===
v230 >@ <|@
instruction <@Begin|@org.graalvm.compiler.nodes.BeginNode>@ #next: v219  <|@  <|@
f <@*|@fixed>@ <|@
tid v219 <|@
d <@d|@=== Debug Properties ===
nodeSourcePosition: at java.lang.String.lastIndexOf(String.java:1888) [bci: 72]
stamp: void
=== Inputs ===
=== Succesors ===
=== Usages ===
v217 
=== Predecessor ===
v221 >@ <|@
instruction <@EndNode|@org.graalvm.compiler.nodes.EndNode>@  <|@  <|@
    end_IR
    begin_IR
      LIR
      nr   -1  <|@ instruction [] = LABEL numbPhis: 0 align: false label: ? <|@ <|@
      nr   -1  <|@ instruction JUMP ~[] destination: B8 -> B9 <|@ <|@
    end_IR
  end_block
  begin_block
    name "B9"
    from_bci -1
    to_bci -1
    predecessors "B5" "B8" 
    successors "B10" "B11" 
    xhandlers
    flags 
    probability 4607182418800017408
    begin_IR
      HIR
f <@#|@fixed with next>@ <|@
tid v217 <|@
d <@d|@=== Debug Properties ===
nodeSourcePosition: at java.lang.String.lastIndexOf(String.java:1888) [bci: 72]
stamp: void
=== Inputs ===
stateAfter: - 
ends: v218 v219 
=== Succesors ===
next: v169 
=== Usages ===
v150 
=== Predecessor ===
- >@ <|@
instruction <@Merge|@org.graalvm.compiler.nodes.MergeNode>@ stateAfter: - ends: v218 v219 #next: v169  <|@  <|@
f <@~|@floating>@ <|@
tid i10 <|@
result int[0|0x0] <|@
d <@d|@=== Debug Properties ===
isDefaultStable: false
nodeSourcePosition: at java.lang.String.lastIndexOf(String.java:1870) [bci: 8]
rawvalue: 0
stableDimension: 0
stamp: i32 [0] ⇈0000000000000000
stampKind: i32
value: int[0|0x0]
=== Inputs ===
=== Succesors ===
=== Usages ===
v11 v15 
=== Predecessor ===
- >@ <|@
instruction <@Constant|@org.graalvm.compiler.nodes.ConstantNode>@  <|@  <|@
f <@~|@floating>@ <|@
tid v11 <|@
d <@d|@=== Debug Properties ===
condition: LT
nodeSourcePosition: at java.lang.String.lastIndexOf(String.java:1870) [bci: 8]
op: org.graalvm.compiler.nodes.calc.IntegerLessThanNode$LessThanOp@7cc8d043
stamp: void
unorderedIsTrue: false
=== Inputs ===
x: i7 
y: i10 
=== Succesors ===
=== Usages ===
v169 
=== Predecessor ===
- >@ <|@
instruction <@<|@org.graalvm.compiler.nodes.calc.IntegerLessThanNode>@ x: i7 y: i10  <|@  <|@
f <@*|@fixed>@ <|@
tid v169 <|@
d <@d|@=== Debug Properties ===
nodeSourcePosition: at java.lang.String.lastIndexOf(String.java:1870) [bci: 8]
stamp: void
trueSuccessorProbability: 0.0
=== Inputs ===
condition: v11 
=== Succesors ===
trueSuccessor: v168 
falseSuccessor: v166 
=== Usages ===
=== Predecessor ===
v217 >@ <|@
instruction <@If|@org.graalvm.compiler.nodes.IfNode>@ condition: v11 #trueSuccessor: v168 #falseSuccessor: v166  <|@  <|@
    end_IR
    begin_IR
      LIR
      nr   -1  <|@ instruction [] = LABEL numbPhis: 0 align: false label: ? <|@ <|@
      nr   -1  <|@ instruction TEST (x: v6|DWORD, y: v6|DWORD) size: DWORD <|@ <|@
      nr   -1  <|@ instruction BRANCH trueDestinationProbability: 0.0 condition: < trueDestination: B9 -> B10 falseDestination: B9 -> B11 <|@ <|@
    end_IR
  end_block
  begin_block
    name "B10"
    from_bci -1
    to_bci -1
    predecessors "B9" 
    successors "B27" 
    xhandlers
    flags 
    probability 2355382605114769408
    begin_IR
      HIR
f <@#|@fixed with next>@ <|@
tid v168 <|@
d <@d|@=== Debug Properties ===
nodeSourcePosition: at java.lang.String.lastIndexOf(String.java:1870) [bci: 8]
stamp: void
=== Inputs ===
=== Succesors ===
next: v204 
=== Usages ===
=== Predecessor ===
v169 >@ <|@
instruction <@Begin|@org.graalvm.compiler.nodes.BeginNode>@ #next: v204  <|@  <|@
f <@~|@floating>@ <|@
tid i205 <|@
result int[-22035|0xffffffffffffa9ed] <|@
d <@d|@=== Debug Properties ===
isDefaultStable: false
rawvalue: -22035
stableDimension: 0
stamp: i32 [-22035] ⇊00000000ffffa9ed ⇈00000000ffffa9ed
stampKind: i32
value: int[-22035|0xffffffffffffa9ed]
=== Inputs ===
=== Succesors ===
=== Usages ===
i198 
=== Predecessor ===
- >@ <|@
instruction <@Constant|@org.graalvm.compiler.nodes.ConstantNode>@  <|@  <|@
f <@*|@fixed>@ <|@
tid v204 <|@
d <@d|@=== Debug Properties ===
stamp: void
=== Inputs ===
=== Succesors ===
=== Usages ===
v194 
=== Predecessor ===
v168 >@ <|@
instruction <@EndNode|@org.graalvm.compiler.nodes.EndNode>@  <|@  <|@
    end_IR
    begin_IR
      LIR
      nr   -1  <|@ instruction [] = LABEL numbPhis: 0 align: false label: ? <|@ <|@
      nr   -1  <|@ instruction JUMP ~[int[-22035|0xffffffffffffa9ed], Object[null]] destination: B10 -> B27 <|@ <|@
    end_IR
  end_block
  begin_block
    name "B11"
    from_bci -1
    to_bci -1
    predecessors "B9" 
    successors "B12" "B24" 
    xhandlers
    flags 
    probability 4607182418800017408
    begin_IR
      HIR
f <@#|@fixed with next>@ <|@
tid v166 <|@
d <@d|@=== Debug Properties ===
nodeSourcePosition: at java.lang.String.lastIndexOf(String.java:1870) [bci: 8]
stamp: void
=== Inputs ===
=== Succesors ===
next: v173 
=== Usages ===
=== Predecessor ===
v169 >@ <|@
instruction <@Begin|@org.graalvm.compiler.nodes.BeginNode>@ #next: v173  <|@  <|@
f <@~|@floating>@ <|@
tid v13 <|@
d <@d|@=== Debug Properties ===
condition: LT
nodeSourcePosition: at java.lang.String.lastIndexOf(String.java:1873) [bci: 17]
op: org.graalvm.compiler.nodes.calc.IntegerLessThanNode$LessThanOp@7cc8d043
stamp: void
unorderedIsTrue: false
=== Inputs ===
x: i9 
y: i7 
=== Succesors ===
=== Usages ===
v173 
=== Predecessor ===
- >@ <|@
instruction <@<|@org.graalvm.compiler.nodes.calc.IntegerLessThanNode>@ x: i9 y: i7  <|@  <|@
f <@*|@fixed>@ <|@
tid v173 <|@
d <@d|@=== Debug Properties ===
nodeSourcePosition: at java.lang.String.lastIndexOf(String.java:1873) [bci: 17]
stamp: void
trueSuccessorProbability: 1.0
=== Inputs ===
condition: v13 
=== Succesors ===
trueSuccessor: v170 
falseSuccessor: v172 
=== Usages ===
=== Predecessor ===
v166 >@ <|@
instruction <@If|@org.graalvm.compiler.nodes.IfNode>@ condition: v13 #trueSuccessor: v170 #falseSuccessor: v172  <|@  <|@
    end_IR
    begin_IR
      LIR
      nr   -1  <|@ instruction [] = LABEL numbPhis: 0 align: false label: ? <|@ <|@
      nr   -1  <|@ instruction CMP (x: v6|DWORD, y: v10|DWORD) size: DWORD <|@ <|@
      nr   -1  <|@ instruction BRANCH trueDestinationProbability: 1.0 condition: > trueDestination: B11 -> B12 falseDestination: B11 -> B24 <|@ <|@
    end_IR
  end_block
  begin_block
    name "B12"
    from_bci -1
    to_bci -1
    predecessors "B11" 
    successors "B13" "B14" 
    xhandlers
    flags 
    probability 4607182418800017408
    begin_IR
      HIR
f <@#|@fixed with next>@ <|@
tid v170 <|@
d <@d|@=== Debug Properties ===
nodeSourcePosition: at java.lang.String.lastIndexOf(String.java:1873) [bci: 17]
stamp: void
=== Inputs ===
=== Succesors ===
next: v177 
=== Usages ===
=== Predecessor ===
v173 >@ <|@
instruction <@Begin|@org.graalvm.compiler.nodes.BeginNode>@ #next: v177  <|@  <|@
f <@~|@floating>@ <|@
tid v15 <|@
d <@d|@=== Debug Properties ===
condition: EQ
nodeSourcePosition: at java.lang.String.lastIndexOf(String.java:1877) [bci: 26]
stamp: void
unorderedIsTrue: false
=== Inputs ===
x: i6 
y: i10 
=== Succesors ===
=== Usages ===
v177 
=== Predecessor ===
- >@ <|@
instruction <@==|@org.graalvm.compiler.nodes.calc.IntegerEqualsNode>@ x: i6 y: i10  <|@  <|@
f <@*|@fixed>@ <|@
tid v177 <|@
d <@d|@=== Debug Properties ===
nodeSourcePosition: at java.lang.String.lastIndexOf(String.java:1877) [bci: 26]
stamp: void
trueSuccessorProbability: 0.0
=== Inputs ===
condition: v15 
=== Succesors ===
trueSuccessor: v176 
falseSuccessor: v174 
=== Usages ===
=== Predecessor ===
v170 >@ <|@
instruction <@If|@org.graalvm.compiler.nodes.IfNode>@ condition: v15 #trueSuccessor: v176 #falseSuccessor: v174  <|@  <|@
    end_IR
    begin_IR
      LIR
      nr   -1  <|@ instruction [] = LABEL numbPhis: 0 align: false label: ? <|@ <|@
      nr   -1  <|@ instruction TEST (x: v5|DWORD, y: v5|DWORD) size: DWORD <|@ <|@
      nr   -1  <|@ instruction BRANCH trueDestinationProbability: 0.0 condition: = trueDestination: B12 -> B13 falseDestination: B12 -> B14 <|@ <|@
    end_IR
  end_block
  begin_block
    name "B13"
    from_bci -1
    to_bci -1
    predecessors "B12" 
    successors "B27" 
    xhandlers
    flags 
    probability 2355382605114769408
    begin_IR
      HIR
f <@#|@fixed with next>@ <|@
tid v176 <|@
d <@d|@=== Debug Properties ===
nodeSourcePosition: at java.lang.String.lastIndexOf(String.java:1877) [bci: 26]
stamp: void
=== Inputs ===
=== Succesors ===
next: v209 
=== Usages ===
=== Predecessor ===
v177 >@ <|@
instruction <@Begin|@org.graalvm.compiler.nodes.BeginNode>@ #next: v209  <|@  <|@
f <@~|@floating>@ <|@
tid i210 <|@
result int[-22547|0xffffffffffffa7ed] <|@
d <@d|@=== Debug Properties ===
isDefaultStable: false
rawvalue: -22547
stableDimension: 0
stamp: i32 [-22547] ⇊00000000ffffa7ed ⇈00000000ffffa7ed
stampKind: i32
value: int[-22547|0xffffffffffffa7ed]
=== Inputs ===
=== Succesors ===
=== Usages ===
i198 
=== Predecessor ===
- >@ <|@
instruction <@Constant|@org.graalvm.compiler.nodes.ConstantNode>@  <|@  <|@
f <@*|@fixed>@ <|@
tid v209 <|@
d <@d|@=== Debug Properties ===
stamp: void
=== Inputs ===
=== Succesors ===
=== Usages ===
v194 
=== Predecessor ===
v176 >@ <|@
instruction <@EndNode|@org.graalvm.compiler.nodes.EndNode>@  <|@  <|@
    end_IR
    begin_IR
      LIR
      nr   -1  <|@ instruction [] = LABEL numbPhis: 0 align: false label: ? <|@ <|@
      nr   -1  <|@ instruction JUMP ~[int[-22547|0xffffffffffffa7ed], Object[null]] destination: B13 -> B27 <|@ <|@
    end_IR
  end_block
  begin_block
    name "B14"
    from_bci -1
    to_bci -1
    predecessors "B12" 
    successors "B15" "B23" 
    xhandlers
    flags 
    probability 4607182418800017408
    begin_IR
      HIR
f <@#|@fixed with next>@ <|@
tid v174 <|@
d <@d|@=== Debug Properties ===
nodeSourcePosition: at java.lang.String.lastIndexOf(String.java:1877) [bci: 26]
stamp: void
=== Inputs ===
=== Succesors ===
next: i234 
=== Usages ===
=== Predecessor ===
v177 >@ <|@
instruction <@Begin|@org.graalvm.compiler.nodes.BeginNode>@ #next: i234  <|@  <|@
f <@~|@floating>@ <|@
tid v238 <|@
result [v3|QWORD[.] + 12] <|@
d <@d|@=== Debug Properties ===
displacement: 12
scale: Times1
stamp: void*
=== Inputs ===
base: a4 
index: - 
=== Succesors ===
=== Usages ===
i234 
=== Predecessor ===
- >@ <|@
instruction <@AMD64Address|@org.graalvm.compiler.core.amd64.AMD64AddressNode>@ base: a4 index: -  <|@  <|@
f <@#|@fixed with next>@ <|@
tid i234 <|@
result INTERIOR_MATCH <|@
d <@d|@=== Debug Properties ===
barrierType: NONE
forceFixed: false
location: [].length:final
nodeSourcePosition: at java.lang.String.lastIndexOf(String.java:1882) [bci: 44]
nullCheck: true
stamp: i32 [0 - 2147483647] ⇈000000007fffffff
=== Inputs ===
stateBefore: ?8 
guard: - 
address: v238 
=== Succesors ===
next: v185 
=== Usages ===
v95 
=== Predecessor ===
v174 >@ <|@
instruction <@Read|@org.graalvm.compiler.nodes.memory.ReadNode>@ stateBefore: ?8 guard: - address: v238 #next: v185  <|@  <|@
f <@~|@floating>@ <|@
tid i17 <|@
result v20|DWORD <|@
d <@d|@=== Debug Properties ===
getOp: org.graalvm.compiler.nodes.calc.AddNode$$Lambda$15/1271304513@1406efde
nodeSourcePosition: at java.lang.String.lastIndexOf(String.java:1881) [bci: 36]
stamp: i32
=== Inputs ===
x: i5 
y: i6 
=== Succesors ===
=== Usages ===
i20 
=== Predecessor ===
- >@ <|@
instruction <@+|@org.graalvm.compiler.nodes.calc.AddNode>@ x: i5 y: i6  <|@  <|@
f <@~|@floating>@ <|@
tid i20 <|@
result v21|DWORD <|@
d <@d|@=== Debug Properties ===
getOp: org.graalvm.compiler.nodes.calc.AddNode$$Lambda$15/1271304513@1406efde
nodeSourcePosition: at java.lang.String.lastIndexOf(String.java:1881) [bci: 38]
stamp: i32
=== Inputs ===
x: i17 
y: i19 
=== Succesors ===
=== Usages ===
v239 ?29 v95 
=== Predecessor ===
- >@ <|@
instruction <@+|@org.graalvm.compiler.nodes.calc.AddNode>@ x: i17 y: i19  <|@  <|@
f <@~|@floating>@ <|@
tid v95 <|@
result INTERIOR_MATCH <|@
d <@d|@=== Debug Properties ===
condition: BT
nodeSourcePosition: at java.lang.String.lastIndexOf(String.java:1882) [bci: 44]
op: org.graalvm.compiler.nodes.calc.IntegerBelowNode$BelowOp@19d5dcf
stamp: void
unorderedIsTrue: false
=== Inputs ===
x: i20 
y: i234 
=== Succesors ===
=== Usages ===
v185 
=== Predecessor ===
- >@ <|@
instruction <@|<||@org.graalvm.compiler.nodes.calc.IntegerBelowNode>@ x: i20 y: i234  <|@  <|@
f <@*|@fixed>@ <|@
tid v185 <|@
result org.graalvm.compiler.core.match.ComplexMatchValue@d98b27eb <|@
d <@d|@=== Debug Properties ===
nodeSourcePosition: at java.lang.String.lastIndexOf(String.java:1882) [bci: 44]
stamp: void
trueSuccessorProbability: 1.0
=== Inputs ===
condition: v95 
=== Succesors ===
trueSuccessor: v182 
falseSuccessor: v184 
=== Usages ===
=== Predecessor ===
i234 >@ <|@
instruction <@If|@org.graalvm.compiler.nodes.IfNode>@ condition: v95 #trueSuccessor: v182 #falseSuccessor: v184  <|@  <|@
    end_IR
    begin_IR
      LIR
      nr   -1  <|@ instruction [] = LABEL numbPhis: 0 align: false label: ? <|@ <|@
      nr   -1  <|@ instruction v20|DWORD = ADD (x: v4|DWORD, y: v5|DWORD) size: DWORD <|@ <|@
      nr   -1  <|@ instruction v21|DWORD = DEC v20|DWORD size: DWORD <|@ <|@
      nr   -1  <|@ st <@st|@java.lang.String.lastIndexOf(String.java:1869) [bci: 0]
locals: v0|QWORD[.] v1|DWORD v2|DWORD v3|QWORD[.] v4|DWORD v5|DWORD v6|DWORD - - - - - - - - 
>@ <|@ instruction CMP (x: v21|DWORD, y: [v3|QWORD[.] + 12]) size: DWORD state [bci:0] <|@ <|@
      nr   -1  <|@ instruction BRANCH trueDestinationProbability: 1.0 condition: |<| trueDestination: B14 -> B15 falseDestination: B14 -> B23 <|@ <|@
    end_IR
  end_block
  begin_block
    name "B15"
    from_bci -1
    to_bci -1
    predecessors "B14" 
    successors "B16" 
    xhandlers
    flags 
    probability 4607182418800017408
    begin_IR
      HIR
f <@#|@fixed with next>@ <|@
tid v182 <|@
d <@d|@=== Debug Properties ===
nodeSourcePosition: at java.lang.String.lastIndexOf(String.java:1882) [bci: 44]
stamp: void
=== Inputs ===
=== Succesors ===
next: i235 
=== Usages ===
i235 
=== Predecessor ===
v185 >@ <|@
instruction <@Begin|@org.graalvm.compiler.nodes.BeginNode>@ #next: i235  <|@  <|@
f <@~|@floating>@ <|@
tid v239 <|@
result [v3|QWORD[.] + v21|DWORD * 2 + 16] <|@
d <@d|@=== Debug Properties ===
displacement: 16
scale: Times2
stamp: void*
=== Inputs ===
base: a4 
index: i20 
=== Succesors ===
=== Usages ===
i235 
=== Predecessor ===
- >@ <|@
instruction <@AMD64Address|@org.graalvm.compiler.core.amd64.AMD64AddressNode>@ base: a4 index: i20  <|@  <|@
f <@#|@fixed with next>@ <|@
tid i235 <|@
result INTERIOR_MATCH <|@
d <@d|@=== Debug Properties ===
barrierType: NONE
forceFixed: false
location: Array: char
nodeSourcePosition: at java.lang.String.lastIndexOf(String.java:1882) [bci: 44]
nullCheck: false
stamp: i16
=== Inputs ===
stateBefore: - 
guard: v182 
address: v239 
=== Succesors ===
next: v26 
=== Usages ===
i104 
=== Predecessor ===
v182 >@ <|@
instruction <@Read|@org.graalvm.compiler.nodes.memory.ReadNode>@ stateBefore: - guard: v182 address: v239 #next: v26  <|@  <|@
f <@~|@floating>@ <|@
tid i104 <|@
result v22|DWORD <|@
d <@d|@=== Debug Properties ===
getOp: org.graalvm.compiler.nodes.calc.ZeroExtendNode$$Lambda$16/887152589@6b9fc47b
getReverseOp: org.graalvm.compiler.nodes.calc.ZeroExtendNode$$Lambda$17/1263733897@4844aec9
inputAlwaysPositive: false
inputBits: 16
nodeSourcePosition: at java.lang.String.lastIndexOf(String.java:1882) [bci: 44]
resultBits: 32
stamp: i32 [0 - 65535] ⇈000000000000ffff
=== Inputs ===
value: i235 
=== Succesors ===
=== Usages ===
?29 v35 
=== Predecessor ===
- >@ <|@
instruction <@ZeroExtend|@org.graalvm.compiler.nodes.calc.ZeroExtendNode>@ value: i235  <|@  <|@
f <@*|@fixed>@ <|@
tid v26 <|@
d <@d|@=== Debug Properties ===
nodeSourcePosition: at java.lang.String.lastIndexOf(String.java:1888) [bci: 62]
stamp: void
=== Inputs ===
=== Succesors ===
=== Usages ===
v27 
=== Predecessor ===
i235 >@ <|@
instruction <@EndNode|@org.graalvm.compiler.nodes.EndNode>@  <|@  <|@
    end_IR
    begin_IR
      LIR
      nr   -1  <|@ instruction [] = LABEL numbPhis: 0 align: false label: ? <|@ <|@
      nr   -1  <|@ instruction v22|DWORD = MOVZX [v3|QWORD[.] + v21|DWORD * 2 + 16] size: DWORD <|@ <|@
      nr   -1  <|@ instruction JUMP ~[v11|DWORD] destination: B15 -> B16 <|@ <|@
    end_IR
  end_block
  begin_block
    name "B16"
    from_bci -1
    to_bci -1
    predecessors "B15" "B22" 
    successors "B17" "B18" 
    xhandlers
    flags "llh" 
    loop_index 0
    loop_depth 1
    probability 4623847342242986814
    begin_IR
      HIR
f <@~|@floating>@ <|@
tid i28 <|@
result v23|DWORD <|@
d <@d|@=== Debug Properties ===
stamp: i32
valueDescription: i32
=== Inputs ===
merge: v27 
values: i24 i42 
=== Succesors ===
=== Usages ===
?29 v30 v241 i42 
=== Predecessor ===
- >@ <|@
instruction <@ValuePhi|@org.graalvm.compiler.nodes.ValuePhiNode>@ merge: v27 values: i24 i42  <|@  <|@
f <@#|@fixed with next>@ <|@
tid v27 <|@
d <@d|@=== Debug Properties ===
canEndsSafepoint: false
inversionCount: 0
loopFrequency: 13.602850736000274
loopOrigFrequency: 1.0
loopType: SIMPLE_LOOP
nextEndIndex: 1
nodeSourcePosition: at java.lang.String.lastIndexOf(String.java:1888) [bci: 62]
splits: 0
stamp: void
unrollFactor: 1
unswitches: 0
=== Inputs ===
stateAfter: - 
overflowGuard: v158 
ends: v26 
=== Succesors ===
next: v33 
=== Usages ===
i28 v43 v46 v64 v189 
=== Predecessor ===
- >@ <|@
instruction <@LoopBegin|@org.graalvm.compiler.nodes.LoopBeginNode>@ stateAfter: - overflowGuard: v158 ends: v26 #next: v33  <|@  <|@
f <@~|@floating>@ <|@
tid v30 <|@
d <@d|@=== Debug Properties ===
condition: LT
nodeSourcePosition: at java.lang.String.lastIndexOf(String.java:1888) [bci: 66]
op: org.graalvm.compiler.nodes.calc.IntegerLessThanNode$LessThanOp@7cc8d043
stamp: void
unorderedIsTrue: false
=== Inputs ===
x: i28 
y: i23 
=== Succesors ===
=== Usages ===
v33 
=== Predecessor ===
- >@ <|@
instruction <@<|@org.graalvm.compiler.nodes.calc.IntegerLessThanNode>@ x: i28 y: i23  <|@  <|@
f <@*|@fixed>@ <|@
tid v33 <|@
d <@d|@=== Debug Properties ===
nodeSourcePosition: at java.lang.String.lastIndexOf(String.java:1888) [bci: 66]
stamp: void
trueSuccessorProbability: 0.014642233807685692
=== Inputs ===
condition: v30 
=== Succesors ===
trueSuccessor: v46 
falseSuccessor: v32 
=== Usages ===
=== Predecessor ===
v27 >@ <|@
instruction <@If|@org.graalvm.compiler.nodes.IfNode>@ condition: v30 #trueSuccessor: v46 #falseSuccessor: v32  <|@  <|@
    end_IR
    begin_IR
      LIR
      nr   -1  <|@ instruction [v23|DWORD] = LABEL numbPhis: 1 align: false label: ? <|@ <|@
      nr   -1  <|@ instruction CMP (x: v9|DWORD, y: v23|DWORD) size: DWORD <|@ <|@
      nr   -1  <|@ instruction BRANCH trueDestinationProbability: 0.014642233807685692 condition: > trueDestination: B16 -> B17 falseDestination: B16 -> B18 <|@ <|@
    end_IR
  end_block
  begin_block
    name "B17"
    from_bci -1
    to_bci -1
    predecessors "B16" 
    successors 
    xhandlers
    flags 
    probability 4596344096322459299
    begin_IR
      HIR
f <@#|@fixed with next>@ <|@
tid v46 <|@
d <@d|@=== Debug Properties ===
nodeSourcePosition: at java.lang.String.lastIndexOf(String.java:1891) [bci: 84]
stamp: void
=== Inputs ===
stateAfter: - 
loopBegin: v27 
=== Succesors ===
next: v67 
=== Usages ===
=== Predecessor ===
v33 >@ <|@
instruction <@LoopExit|@org.graalvm.compiler.nodes.LoopExitNode>@ stateAfter: - loopBegin: v27 #next: v67  <|@  <|@
f <@*|@fixed>@ <|@
tid v67 <|@
d <@d|@=== Debug Properties ===
nodeSourcePosition: at java.lang.String.lastIndexOf(String.java:1892) [bci: 92]
stamp: void
=== Inputs ===
result: i19 
memoryMap: - 
=== Succesors ===
=== Usages ===
=== Predecessor ===
v46 >@ <|@
instruction <@Return|@org.graalvm.compiler.nodes.ReturnNode>@ result: i19 memoryMap: -  <|@  <|@
    end_IR
    begin_IR
      LIR
      nr   -1  <|@ instruction [] = LABEL numbPhis: 0 align: false label: ? <|@ <|@
      nr   -1  <|@ instruction rax|DWORD = MOVE input: int[-1|0xffffffffffffffff] <|@ <|@
      nr   -1  <|@ instruction RETURN (savedRbp: stack:16|QWORD, value: rax|DWORD) isStub: false thread: r15 scratchForSafepointOnReturn: rcx config: org.graalvm.compiler.hotspot.GraalHotSpotVMConfig@7222fe45 <|@ <|@
    end_IR
  end_block
  begin_block
    name "B18"
    from_bci -1
    to_bci -1
    predecessors "B16" 
    successors "B19" "B22" 
    xhandlers
    flags 
    loop_index 0
    loop_depth 1
    probability 4623735216054988003
    begin_IR
      HIR
f <@#|@fixed with next>@ <|@
tid v32 <|@
d <@d|@=== Debug Properties ===
nodeSourcePosition: at java.lang.String.lastIndexOf(String.java:1888) [bci: 69]
stamp: void
=== Inputs ===
=== Succesors ===
next: i236 
=== Usages ===
v150 
=== Predecessor ===
v33 >@ <|@
instruction <@Begin|@org.graalvm.compiler.nodes.BeginNode>@ #next: i236  <|@  <|@
f <@~|@floating>@ <|@
tid v150 <|@
d <@d|@=== Debug Properties ===
stamp: void
=== Inputs ===
kf: v217 v32 
=== Succesors ===
=== Usages ===
i236 
=== Predecessor ===
- >@ <|@
instruction <@c|@com.oracle.graal.enterprise.k.c>@ kf: v217 v32  <|@  <|@
f <@~|@floating>@ <|@
tid v241 <|@
result [v0|QWORD[.] + v23|DWORD * 2 + 16] <|@
d <@d|@=== Debug Properties ===
displacement: 16
scale: Times2
stamp: void*
=== Inputs ===
base: a1 
index: i28 
=== Succesors ===
=== Usages ===
i236 
=== Predecessor ===
- >@ <|@
instruction <@AMD64Address|@org.graalvm.compiler.core.amd64.AMD64AddressNode>@ base: a1 index: i28  <|@  <|@
f <@#|@fixed with next>@ <|@
tid i236 <|@
result INTERIOR_MATCH <|@
d <@d|@=== Debug Properties ===
barrierType: NONE
forceFixed: false
location: Array: char
nodeSourcePosition: at java.lang.String.lastIndexOf(String.java:1888) [bci: 72]
nullCheck: false
stamp: i16
=== Inputs ===
stateBefore: - 
guard: v150 
address: v241 
=== Succesors ===
next: v41 
=== Usages ===
i118 
=== Predecessor ===
v32 >@ <|@
instruction <@Read|@org.graalvm.compiler.nodes.memory.ReadNode>@ stateBefore: - guard: v150 address: v241 #next: v41  <|@  <|@
f <@~|@floating>@ <|@
tid i118 <|@
result v24|DWORD <|@
d <@d|@=== Debug Properties ===
getOp: org.graalvm.compiler.nodes.calc.ZeroExtendNode$$Lambda$16/887152589@6b9fc47b
getReverseOp: org.graalvm.compiler.nodes.calc.ZeroExtendNode$$Lambda$17/1263733897@4844aec9
inputAlwaysPositive: false
inputBits: 16
nodeSourcePosition: at java.lang.String.lastIndexOf(String.java:1888) [bci: 72]
resultBits: 32
stamp: i32 [0 - 65535] ⇈000000000000ffff
=== Inputs ===
value: i236 
=== Succesors ===
=== Usages ===
v35 
=== Predecessor ===
- >@ <|@
instruction <@ZeroExtend|@org.graalvm.compiler.nodes.calc.ZeroExtendNode>@ value: i236  <|@  <|@
f <@~|@floating>@ <|@
tid v35 <|@
d <@d|@=== Debug Properties ===
condition: EQ
nodeSourcePosition: at java.lang.String.lastIndexOf(String.java:1888) [bci: 75]
stamp: void
unorderedIsTrue: false
=== Inputs ===
x: i104 
y: i118 
=== Succesors ===
=== Usages ===
v41 
=== Predecessor ===
- >@ <|@
instruction <@==|@org.graalvm.compiler.nodes.calc.IntegerEqualsNode>@ x: i104 y: i118  <|@  <|@
f <@~|@floating>@ <|@
tid i42 <|@
result v25|DWORD <|@
d <@d|@=== Debug Properties ===
getOp: org.graalvm.compiler.nodes.calc.AddNode$$Lambda$15/1271304513@1406efde
nodeSourcePosition: at java.lang.String.lastIndexOf(String.java:1889) [bci: 78]
stamp: i32
=== Inputs ===
x: i28 
y: i19 
=== Succesors ===
=== Usages ===
i28 i51 v59 
=== Predecessor ===
- >@ <|@
instruction <@+|@org.graalvm.compiler.nodes.calc.AddNode>@ x: i28 y: i19  <|@  <|@
f <@*|@fixed>@ <|@
tid v41 <|@
d <@d|@=== Debug Properties ===
nodeSourcePosition: at java.lang.String.lastIndexOf(String.java:1888) [bci: 75]
stamp: void
trueSuccessorProbability: 0.059746592040655154
=== Inputs ===
condition: v35 
=== Succesors ===
trueSuccessor: v40 
falseSuccessor: v39 
=== Usages ===
=== Predecessor ===
i236 >@ <|@
instruction <@If|@org.graalvm.compiler.nodes.IfNode>@ condition: v35 #trueSuccessor: v40 #falseSuccessor: v39  <|@  <|@
    end_IR
    begin_IR
      LIR
      nr   -1  <|@ instruction [] = LABEL numbPhis: 0 align: true label: ? <|@ <|@
      nr   -1  <|@ instruction v24|DWORD = MOVZX [v0|QWORD[.] + v23|DWORD * 2 + 16] size: DWORD <|@ <|@
      nr   -1  <|@ instruction v25|DWORD = DEC v23|DWORD size: DWORD <|@ <|@
      nr   -1  <|@ instruction CMP (x: v24|DWORD, y: v22|DWORD) size: DWORD <|@ <|@
      nr   -1  <|@ instruction BRANCH trueDestinationProbability: 0.059746592040655154 condition: = trueDestination: B18 -> B19 falseDestination: B18 -> B22 <|@ <|@
    end_IR
  end_block
  begin_block
    name "B19"
    from_bci -1
    to_bci -1
    predecessors "B18" 
    successors "B20" "B21" 
    xhandlers
    flags 
    probability 4605388399792036439
    begin_IR
      HIR
f <@#|@fixed with next>@ <|@
tid v40 <|@
d <@d|@=== Debug Properties ===
nodeSourcePosition: at java.lang.String.lastIndexOf(String.java:1891) [bci: 84]
stamp: void
=== Inputs ===
=== Succesors ===
next: v190 
=== Usages ===
=== Predecessor ===
v41 >@ <|@
instruction <@Begin|@org.graalvm.compiler.nodes.BeginNode>@ #next: v190  <|@  <|@
f <@~|@floating>@ <|@
tid i50 <|@
result v26|DWORD <|@
d <@d|@=== Debug Properties ===
getOp: org.graalvm.compiler.nodes.calc.AddNode$$Lambda$15/1271304513@1406efde
nodeSourcePosition: at java.lang.String.lastIndexOf(String.java:1895) [bci: 104]
stamp: i32
=== Inputs ===
x: i6 
y: i19 
=== Succesors ===
=== Usages ===
i51 
=== Predecessor ===
- >@ <|@
instruction <@+|@org.graalvm.compiler.nodes.calc.AddNode>@ x: i6 y: i19  <|@  <|@
f <@~|@floating>@ <|@
tid i51 <|@
result v27|DWORD <|@
d <@d|@=== Debug Properties ===
getOp: org.graalvm.compiler.nodes.calc.SubNode$$Lambda$64/1952983589@24889bdf
nodeSourcePosition: at java.lang.String.lastIndexOf(String.java:1895) [bci: 105]
stamp: i32
=== Inputs ===
x: i42 
y: i50 
=== Succesors ===
=== Usages ===
i68 v59 
=== Predecessor ===
- >@ <|@
instruction <@-|@org.graalvm.compiler.nodes.calc.SubNode>@ x: i42 y: i50  <|@  <|@
f <@~|@floating>@ <|@
tid v59 <|@
d <@d|@=== Debug Properties ===
condition: LT
nodeSourcePosition: at java.lang.String.lastIndexOf(String.java:1898) [bci: 118]
op: org.graalvm.compiler.nodes.calc.IntegerLessThanNode$LessThanOp@7cc8d043
stamp: void
unorderedIsTrue: false
=== Inputs ===
x: i51 
y: i42 
=== Succesors ===
=== Usages ===
v190 
=== Predecessor ===
- >@ <|@
instruction <@<|@org.graalvm.compiler.nodes.calc.IntegerLessThanNode>@ x: i51 y: i42  <|@  <|@
f <@*|@fixed>@ <|@
tid v190 <|@
d <@d|@=== Debug Properties ===
nodeSourcePosition: at java.lang.String.lastIndexOf(String.java:1898) [bci: 118]
stamp: void
trueSuccessorProbability: 0.0
=== Inputs ===
condition: v59 
=== Succesors ===
trueSuccessor: v189 
falseSuccessor: v64 
=== Usages ===
=== Predecessor ===
v40 >@ <|@
instruction <@If|@org.graalvm.compiler.nodes.IfNode>@ condition: v59 #trueSuccessor: v189 #falseSuccessor: v64  <|@  <|@
    end_IR
    begin_IR
      LIR
      nr   -1  <|@ instruction [] = LABEL numbPhis: 0 align: false label: ? <|@ <|@
      nr   -1  <|@ instruction v26|DWORD = DEC v5|DWORD size: DWORD <|@ <|@
      nr   -1  <|@ instruction v27|DWORD = SUB (x: v25|DWORD, ~y: v26|DWORD) size: DWORD <|@ <|@
      nr   -1  <|@ instruction CMP (x: v25|DWORD, y: v27|DWORD) size: DWORD <|@ <|@
      nr   -1  <|@ instruction BRANCH trueDestinationProbability: 0.0 condition: > trueDestination: B19 -> B20 falseDestination: B19 -> B21 <|@ <|@
    end_IR
  end_block
  begin_block
    name "B20"
    from_bci -1
    to_bci -1
    predecessors "B19" 
    successors 
    xhandlers
    flags 
    probability 2355382605114769408
    begin_IR
      HIR
f <@#|@fixed with next>@ <|@
tid v189 <|@
d <@d|@=== Debug Properties ===
nodeSourcePosition: at java.lang.String.lastIndexOf(String.java:1898) [bci: 118]
stamp: void
=== Inputs ===
stateAfter: - 
loopBegin: v27 
=== Succesors ===
next: v187 
=== Usages ===
=== Predecessor ===
v190 >@ <|@
instruction <@LoopExit|@org.graalvm.compiler.nodes.LoopExitNode>@ stateAfter: - loopBegin: v27 #next: v187  <|@  <|@
tid ?29 <|@
d <@d|@=== Debug Properties ===
bci: 62
code: ResolvedJavaMethodBytecode<String.lastIndexOf(char[], int, int, char[], int, int, int)>
duringCall: false
localsSize: 15
locksSize: 0
rethrowException: false
sourceFile: String.java
sourceLine: 1888
stackSize: 0
=== Inputs ===
outerFrameState: - 
values: a1 i2 - a4 - i6 - - i20 i104 i23 i28 - - - 
=== Succesors ===
=== Usages ===
v187 
=== Predecessor ===
- >@ <|@
instruction <@FrameState|@org.graalvm.compiler.nodes.FrameState>@ outerFrameState: - values: a1 i2 - a4 - i6 - - i20 i104 i23 i28 - - -  <|@  <|@
f <@*|@fixed>@ <|@
tid v187 <|@
d <@d|@=== Debug Properties ===
action: InvalidateReprofile
debugId: 119
nodeSourcePosition: at java.lang.String.lastIndexOf(String.java:1898) [bci: 118]
reason: UnreachedCode
speculation: Object[null]
stamp: void
=== Inputs ===
stateBefore: ?29 
=== Succesors ===
=== Usages ===
=== Predecessor ===
v189 >@ <|@
instruction <@Deopt|@org.graalvm.compiler.nodes.DeoptimizeNode>@ stateBefore: ?29  <|@  <|@
    end_IR
    begin_IR
      LIR
      nr   -1  <|@ instruction [] = LABEL numbPhis: 0 align: false label: ? <|@ <|@
      nr   -1  <|@ instruction MOV [r15|QWORD + 668] y: -30483 size: DWORD <|@ <|@
      nr   -1  <|@ instruction MOV (x: [r15|QWORD + 680], y: r12|ILLEGAL) size: QWORD <|@ <|@
      nr   -1  <|@ st <@st|@java.lang.String.lastIndexOf(String.java:1888) [bci: 62]
locals: v0|QWORD[.] v1|DWORD - v3|QWORD[.] - v5|DWORD - - v21|DWORD v22|DWORD v9|DWORD v23|DWORD - - - 
>@ <|@ instruction DEOPT info [bci:62] <|@ <|@
    end_IR
  end_block
  begin_block
    name "B21"
    from_bci -1
    to_bci -1
    predecessors "B19" 
    successors 
    xhandlers
    flags 
    probability 4605388399792036439
    begin_IR
      HIR
f <@#|@fixed with next>@ <|@
tid v64 <|@
d <@d|@=== Debug Properties ===
nodeSourcePosition: at java.lang.String.lastIndexOf(String.java:1898) [bci: 118]
stamp: void
=== Inputs ===
stateAfter: - 
loopBegin: v27 
=== Succesors ===
next: v70 
=== Usages ===
=== Predecessor ===
v190 >@ <|@
instruction <@LoopExit|@org.graalvm.compiler.nodes.LoopExitNode>@ stateAfter: - loopBegin: v27 #next: v70  <|@  <|@
f <@~|@floating>@ <|@
tid i68 <|@
result v28|DWORD <|@
d <@d|@=== Debug Properties ===
getOp: org.graalvm.compiler.nodes.calc.SubNode$$Lambda$64/1952983589@24889bdf
nodeSourcePosition: at java.lang.String.lastIndexOf(String.java:1904) [bci: 147]
stamp: i32
=== Inputs ===
x: i51 
y: i2 
=== Succesors ===
=== Usages ===
i69 
=== Predecessor ===
- >@ <|@
instruction <@-|@org.graalvm.compiler.nodes.calc.SubNode>@ x: i51 y: i2  <|@  <|@
f <@~|@floating>@ <|@
tid i69 <|@
result v29|DWORD <|@
d <@d|@=== Debug Properties ===
getOp: org.graalvm.compiler.nodes.calc.AddNode$$Lambda$15/1271304513@1406efde
nodeSourcePosition: at java.lang.String.lastIndexOf(String.java:1904) [bci: 149]
stamp: i32
=== Inputs ===
x: i68 
y: i18 
=== Succesors ===
=== Usages ===
v70 
=== Predecessor ===
- >@ <|@
instruction <@+|@org.graalvm.compiler.nodes.calc.AddNode>@ x: i68 y: i18  <|@  <|@
f <@*|@fixed>@ <|@
tid v70 <|@
d <@d|@=== Debug Properties ===
nodeSourcePosition: at java.lang.String.lastIndexOf(String.java:1904) [bci: 150]
stamp: void
=== Inputs ===
result: i69 
memoryMap: - 
=== Succesors ===
=== Usages ===
=== Predecessor ===
v64 >@ <|@
instruction <@Return|@org.graalvm.compiler.nodes.ReturnNode>@ result: i69 memoryMap: -  <|@  <|@
    end_IR
    begin_IR
      LIR
      nr   -1  <|@ instruction [] = LABEL numbPhis: 0 align: false label: ? <|@ <|@
      nr   -1  <|@ instruction v28|DWORD = SUB (x: v27|DWORD, ~y: v1|DWORD) size: DWORD <|@ <|@
      nr   -1  <|@ instruction v29|DWORD = INC v28|DWORD size: DWORD <|@ <|@
      nr   -1  <|@ instruction rax|DWORD = MOVE v29|DWORD moveKind: DWORD <|@ <|@
      nr   -1  <|@ instruction RETURN (savedRbp: stack:16|QWORD, value: rax|DWORD) isStub: false thread: r15 scratchForSafepointOnReturn: rcx config: org.graalvm.compiler.hotspot.GraalHotSpotVMConfig@7222fe45 <|@ <|@
    end_IR
  end_block
  begin_block
    name "B22"
    from_bci -1
    to_bci -1
    predecessors "B18" 
    successors "B16" 
    xhandlers
    flags "lle" 
    loop_index 0
    loop_depth 1
    probability 4623284392289565502
    begin_IR
      HIR
f <@#|@fixed with next>@ <|@
tid v39 <|@
d <@d|@=== Debug Properties ===
nodeSourcePosition: at java.lang.String.lastIndexOf(String.java:1889) [bci: 78]
stamp: void
=== Inputs ===
=== Succesors ===
next: v43 
=== Usages ===
=== Predecessor ===
v41 >@ <|@
instruction <@Begin|@org.graalvm.compiler.nodes.BeginNode>@ #next: v43  <|@  <|@
f <@*|@fixed>@ <|@
tid v43 <|@
d <@d|@=== Debug Properties ===
canSafepoint: false
endIndex: 0
nodeSourcePosition: at java.lang.String.lastIndexOf(String.java:1888) [bci: 62]
stamp: void
=== Inputs ===
loopBegin: v27 
=== Succesors ===
=== Usages ===
=== Predecessor ===
v39 >@ <|@
instruction <@LoopEnd|@org.graalvm.compiler.nodes.LoopEndNode>@ loopBegin: v27  <|@  <|@
    end_IR
    begin_IR
      LIR
      nr   -1  <|@ instruction [] = LABEL numbPhis: 0 align: false label: ? <|@ <|@
      nr   -1  <|@ instruction JUMP ~[v25|DWORD] destination: B22 -> B16 <|@ <|@
    end_IR
  end_block
  begin_block
    name "B23"
    from_bci -1
    to_bci -1
    predecessors "B14" 
    successors "B27" 
    xhandlers
    flags 
    probability 2355382605114769408
    begin_IR
      HIR
f <@#|@fixed with next>@ <|@
tid v184 <|@
d <@d|@=== Debug Properties ===
nodeSourcePosition: at java.lang.String.lastIndexOf(String.java:1882) [bci: 44]
stamp: void
=== Inputs ===
=== Succesors ===
next: v215 
=== Usages ===
=== Predecessor ===
v185 >@ <|@
instruction <@Begin|@org.graalvm.compiler.nodes.BeginNode>@ #next: v215  <|@  <|@
f <@~|@floating>@ <|@
tid i216 <|@
result int[-24603|0xffffffffffff9fe5] <|@
d <@d|@=== Debug Properties ===
isDefaultStable: false
rawvalue: -24603
stableDimension: 0
stamp: i32 [-24603] ⇊00000000ffff9fe5 ⇈00000000ffff9fe5
stampKind: i32
value: int[-24603|0xffffffffffff9fe5]
=== Inputs ===
=== Succesors ===
=== Usages ===
i198 
=== Predecessor ===
- >@ <|@
instruction <@Constant|@org.graalvm.compiler.nodes.ConstantNode>@  <|@  <|@
f <@*|@fixed>@ <|@
tid v215 <|@
d <@d|@=== Debug Properties ===
stamp: void
=== Inputs ===
=== Succesors ===
=== Usages ===
v194 
=== Predecessor ===
v184 >@ <|@
instruction <@EndNode|@org.graalvm.compiler.nodes.EndNode>@  <|@  <|@
    end_IR
    begin_IR
      LIR
      nr   -1  <|@ instruction [] = LABEL numbPhis: 0 align: false label: ? <|@ <|@
      nr   -1  <|@ instruction JUMP ~[int[-24603|0xffffffffffff9fe5], Object[null]] destination: B23 -> B27 <|@ <|@
    end_IR
  end_block
  begin_block
    name "B24"
    from_bci -1
    to_bci -1
    predecessors "B11" 
    successors "B27" 
    xhandlers
    flags 
    probability 2355382605114769408
    begin_IR
      HIR
f <@#|@fixed with next>@ <|@
tid v172 <|@
d <@d|@=== Debug Properties ===
nodeSourcePosition: at java.lang.String.lastIndexOf(String.java:1873) [bci: 17]
stamp: void
=== Inputs ===
=== Succesors ===
next: v211 
=== Usages ===
=== Predecessor ===
v173 >@ <|@
instruction <@Begin|@org.graalvm.compiler.nodes.BeginNode>@ #next: v211  <|@  <|@
f <@~|@floating>@ <|@
tid i212 <|@
result int[-22291|0xffffffffffffa8ed] <|@
d <@d|@=== Debug Properties ===
isDefaultStable: false
rawvalue: -22291
stableDimension: 0
stamp: i32 [-22291] ⇊00000000ffffa8ed ⇈00000000ffffa8ed
stampKind: i32
value: int[-22291|0xffffffffffffa8ed]
=== Inputs ===
=== Succesors ===
=== Usages ===
i198 
=== Predecessor ===
- >@ <|@
instruction <@Constant|@org.graalvm.compiler.nodes.ConstantNode>@  <|@  <|@
f <@*|@fixed>@ <|@
tid v211 <|@
d <@d|@=== Debug Properties ===
stamp: void
=== Inputs ===
=== Succesors ===
=== Usages ===
v194 
=== Predecessor ===
v172 >@ <|@
instruction <@EndNode|@org.graalvm.compiler.nodes.EndNode>@  <|@  <|@
    end_IR
    begin_IR
      LIR
      nr   -1  <|@ instruction [] = LABEL numbPhis: 0 align: false label: ? <|@ <|@
      nr   -1  <|@ instruction JUMP ~[int[-22291|0xffffffffffffa8ed], Object[null]] destination: B24 -> B27 <|@ <|@
    end_IR
  end_block
  begin_block
    name "B25"
    from_bci -1
    to_bci -1
    predecessors "B7" 
    successors "B27" 
    xhandlers
    flags 
    probability 2355382605114769408
    begin_IR
      HIR
f <@#|@fixed with next>@ <|@
tid v229 <|@
d <@d|@=== Debug Properties ===
nodeSourcePosition: at java.lang.String.lastIndexOf(String.java:1888) [bci: 72]
stamp: void
=== Inputs ===
=== Succesors ===
next: v242 
=== Usages ===
=== Predecessor ===
v230 >@ <|@
instruction <@Begin|@org.graalvm.compiler.nodes.BeginNode>@ #next: v242  <|@  <|@
f <@*|@fixed>@ <|@
tid v242 <|@
d <@d|@=== Debug Properties ===
nodeSourcePosition: at java.lang.String.lastIndexOf(String.java:1888) [bci: 72]
stamp: void
=== Inputs ===
=== Succesors ===
=== Usages ===
v194 
=== Predecessor ===
v229 >@ <|@
instruction <@EndNode|@org.graalvm.compiler.nodes.EndNode>@  <|@  <|@
    end_IR
    begin_IR
      LIR
      nr   -1  <|@ instruction [] = LABEL numbPhis: 0 align: false label: ? <|@ <|@
      nr   -1  <|@ instruction JUMP ~[int[-28443|0xffffffffffff90e5], v19|QWORD[.]] destination: B25 -> B27 <|@ <|@
    end_IR
  end_block
  begin_block
    name "B26"
    from_bci -1
    to_bci -1
    predecessors "B6" 
    successors "B27" 
    xhandlers
    flags 
    probability 2355382605114769408
    begin_IR
      HIR
f <@#|@fixed with next>@ <|@
tid v228 <|@
d <@d|@=== Debug Properties ===
nodeSourcePosition: at java.lang.String.lastIndexOf(String.java:1888) [bci: 72]
stamp: void
=== Inputs ===
=== Succesors ===
next: v206 
=== Usages ===
=== Predecessor ===
v232 >@ <|@
instruction <@Begin|@org.graalvm.compiler.nodes.BeginNode>@ #next: v206  <|@  <|@
f <@*|@fixed>@ <|@
tid v206 <|@
d <@d|@=== Debug Properties ===
stamp: void
=== Inputs ===
=== Succesors ===
=== Usages ===
v194 
=== Predecessor ===
v228 >@ <|@
instruction <@EndNode|@org.graalvm.compiler.nodes.EndNode>@  <|@  <|@
    end_IR
    begin_IR
      LIR
      nr   -1  <|@ instruction [] = LABEL numbPhis: 0 align: false label: ? <|@ <|@
      nr   -1  <|@ instruction JUMP ~[int[-28443|0xffffffffffff90e5], v19|QWORD[.]] destination: B26 -> B27 <|@ <|@
    end_IR
  end_block
  begin_block
    name "B27"
    from_bci -1
    to_bci -1
    predecessors "B1" "B3" "B10" "B26" "B13" "B24" "B23" "B25" 
    successors 
    xhandlers
    flags 
    probability 2368893403996880896
    begin_IR
      HIR
f <@~|@floating>@ <|@
tid i198 <|@
result v30|DWORD <|@
d <@d|@=== Debug Properties ===
stamp: i32 [-33924 - -22035] ⇊00000000ffff0064 ⇈00000000fffffffd
valueDescription: i32
=== Inputs ===
merge: v194 
values: i196 i202 i205 i207 i210 i212 i216 i207 
=== Succesors ===
=== Usages ===
v200 
=== Predecessor ===
- >@ <|@
instruction <@ValuePhi|@org.graalvm.compiler.nodes.ValuePhiNode>@ merge: v194 values: i196 i202 i205 i207 i210 i212 i216 i207  <|@  <|@
f <@~|@floating>@ <|@
tid a199 <|@
result v31|QWORD[.] <|@
d <@d|@=== Debug Properties ===
stamp: a# Lcom/oracle/graal/enterprise/k/d$a;
valueDescription: a -
=== Inputs ===
merge: v194 
values: a197 a203 a203 a208 a203 a203 a203 a208 
=== Succesors ===
=== Usages ===
v200 
=== Predecessor ===
- >@ <|@
instruction <@ValuePhi|@org.graalvm.compiler.nodes.ValuePhiNode>@ merge: v194 values: a197 a203 a203 a208 a203 a203 a203 a208  <|@  <|@
f <@#|@fixed with next>@ <|@
tid v194 <|@
d <@d|@=== Debug Properties ===
stamp: void
=== Inputs ===
stateAfter: - 
ends: v195 v201 v204 v206 v209 v211 v215 v242 
=== Succesors ===
next: v200 
=== Usages ===
i198 a199 
=== Predecessor ===
- >@ <|@
instruction <@Merge|@org.graalvm.compiler.nodes.MergeNode>@ stateAfter: - ends: v195 v201 v204 v206 v209 v211 v215 v242 #next: v200  <|@  <|@
f <@*|@fixed>@ <|@
tid v200 <|@
d <@d|@=== Debug Properties ===
stamp: void
=== Inputs ===
stateBefore: ?8 
actionAndReason: i198 
speculation: a199 
=== Succesors ===
=== Usages ===
=== Predecessor ===
v194 >@ <|@
instruction <@DynamicDeoptimize|@org.graalvm.compiler.nodes.DynamicDeoptimizeNode>@ stateBefore: ?8 actionAndReason: i198 speculation: a199  <|@  <|@
    end_IR
    begin_IR
      LIR
      nr   -1  <|@ instruction [v30|DWORD, v31|QWORD[.]] = LABEL numbPhis: 2 align: false label: ? <|@ <|@
      nr   -1  <|@ instruction MOV (x: [r15|QWORD + 668], y: v30|DWORD) size: DWORD <|@ <|@
      nr   -1  <|@ instruction MOV (x: [r15|QWORD + 680], y: v31|QWORD[.]) size: QWORD <|@ <|@
      nr   -1  <|@ st <@st|@java.lang.String.lastIndexOf(String.java:1869) [bci: 0]
locals: v0|QWORD[.] v1|DWORD v2|DWORD v3|QWORD[.] v4|DWORD v5|DWORD v6|DWORD - - - - - - - - 
>@ <|@ instruction DEOPT info [bci:0] <|@ <|@
    end_IR
  end_block
end_cfg
begin_cfg
  name "After PreAllocationOptimizationStage"
  begin_block
    name "B0"
    from_bci -1
    to_bci -1
    predecessors 
    successors "B1" "B2" 
    xhandlers
    flags 
    probability 4607182418800017408
    begin_IR
      LIR
      nr   -1  <|@ instruction [rsi|QWORD[.], rdx|DWORD, rcx|DWORD, r8|QWORD[.], r9|DWORD, rdi|DWORD, in:0|DWORD, rbp|QWORD] = LABEL numbPhis: 0 align: false label: ? <|@ <|@
      nr   -1  <|@ instruction stack:16|QWORD = MOVE rbp|QWORD moveKind: QWORD <|@ <|@
      nr   -1  <|@ instruction [] = HOTSPOTLOCKSTACK frameMapBuilder: org.graalvm.compiler.lir.amd64.AMD64FrameMapBuilder@6dfa0585 slotKind: QWORD <|@ <|@
      nr   -1  <|@ instruction v0|QWORD[.] = MOVE rsi|QWORD[.] moveKind: QWORD <|@ <|@
      nr   -1  <|@ instruction v1|DWORD = MOVE rdx|DWORD moveKind: DWORD <|@ <|@
      nr   -1  <|@ instruction v2|DWORD = MOVE rcx|DWORD moveKind: DWORD <|@ <|@
      nr   -1  <|@ instruction v3|QWORD[.] = MOVE r8|QWORD[.] moveKind: QWORD <|@ <|@
      nr   -1  <|@ instruction v4|DWORD = MOVE r9|DWORD moveKind: DWORD <|@ <|@
      nr   -1  <|@ instruction v5|DWORD = MOVE rdi|DWORD moveKind: DWORD <|@ <|@
      nr   -1  <|@ instruction v6|DWORD = MOVE in:0|DWORD moveKind: DWORD <|@ <|@
      nr   -1  <|@ instruction TEST (x: v0|QWORD[.], y: v0|QWORD[.]) size: QWORD <|@ <|@
      nr   -1  <|@ instruction BRANCH trueDestinationProbability: 0.0 condition: = trueDestination: B0 -> B1 falseDestination: B0 -> B2 <|@ <|@
    end_IR
  end_block
  begin_block
    name "B2"
    from_bci -1
    to_bci -1
    predecessors "B0" 
    successors "B3" "B4" 
    xhandlers
    flags 
    probability 4607182418800017408
    begin_IR
      LIR
      nr   -1  <|@ instruction [] = LABEL numbPhis: 0 align: false label: ? <|@ <|@
      nr   -1  <|@ instruction v8|DWORD = ADD (x: v1|DWORD, y: v5|DWORD) size: DWORD <|@ <|@
      nr   -1  <|@ instruction v9|DWORD = DEC v8|DWORD size: DWORD <|@ <|@
      nr   -1  <|@ instruction CMP v9|DWORD y: -2147483645 size: DWORD <|@ <|@
      nr   -1  <|@ instruction BRANCH trueDestinationProbability: 0.0 condition: < trueDestination: B2 -> B3 falseDestination: B2 -> B4 <|@ <|@
    end_IR
  end_block
  begin_block
    name "B4"
    from_bci -1
    to_bci -1
    predecessors "B2" 
    successors "B5" "B6" 
    xhandlers
    flags 
    probability 4607182418800017408
    begin_IR
      LIR
      nr   -1  <|@ instruction [] = LABEL numbPhis: 0 align: false label: ? <|@ <|@
      nr   -1  <|@ instruction v10|DWORD = SUB (x: v2|DWORD, ~y: v5|DWORD) size: DWORD <|@ <|@
      nr   -1  <|@ instruction v11|DWORD = ADD (x: v10|DWORD, y: v9|DWORD) size: DWORD <|@ <|@
      nr   -1  <|@ instruction CMP (x: v9|DWORD, y: v11|DWORD) size: DWORD <|@ <|@
      nr   -1  <|@ instruction BRANCH trueDestinationProbability: 0.5 condition: > trueDestination: B4 -> B5 falseDestination: B4 -> B6 <|@ <|@
    end_IR
  end_block
  begin_block
    name "B6"
    from_bci -1
    to_bci -1
    predecessors "B4" 
    successors "B7" "B26" 
    xhandlers
    flags 
    probability 4602678819172646912
    begin_IR
      LIR
      nr   -1  <|@ instruction [] = LABEL numbPhis: 0 align: false label: ? <|@ <|@
      nr   -1  <|@ instruction v12|DWORD = MOV [v0|QWORD[.] + 12] size: DWORD <|@ <|@
      nr   -1  <|@ instruction v13|QWORD = MOVSXD v11|DWORD size: QWORD <|@ <|@
      nr   -1  <|@ instruction v14|DWORD = INC v10|DWORD size: DWORD <|@ <|@
      nr   -1  <|@ instruction v15|QWORD = MOVSXD v14|DWORD size: QWORD <|@ <|@
      nr   -1  <|@ instruction v16|QWORD = DEC v15|QWORD size: QWORD <|@ <|@
      nr   -1  <|@ instruction v17|QWORD = SUB (x: v13|QWORD, ~y: v16|QWORD) size: QWORD <|@ <|@
      nr   -1  <|@ instruction v18|QWORD = MOV v12|DWORD size: DWORD <|@ <|@
      nr   -1  <|@ instruction CMP (x: v18|QWORD, y: v17|QWORD) size: QWORD <|@ <|@
      nr   -1  <|@ instruction BRANCH trueDestinationProbability: 1.0 condition: |>| trueDestination: B6 -> B7 falseDestination: B6 -> B26 <|@ <|@
    end_IR
  end_block
  begin_block
    name "B7"
    from_bci -1
    to_bci -1
    predecessors "B6" 
    successors "B8" "B25" 
    xhandlers
    flags 
    probability 4602678819172646912
    begin_IR
      LIR
      nr   -1  <|@ instruction [] = LABEL numbPhis: 0 align: false label: ? <|@ <|@
      nr   -1  <|@ instruction CMP (x: v12|DWORD, y: v11|DWORD) size: DWORD <|@ <|@
      nr   -1  <|@ instruction BRANCH trueDestinationProbability: 1.0 condition: |>| trueDestination: B7 -> B8 falseDestination: B7 -> B25 <|@ <|@
    end_IR
  end_block
  begin_block
    name "B8"
    from_bci -1
    to_bci -1
    predecessors "B7" 
    successors "B9" 
    xhandlers
    flags 
    probability 4602678819172646912
    begin_IR
      LIR
      nr   -1  <|@ instruction [] = LABEL numbPhis: 0 align: false label: ? <|@ <|@
      nr   -1  <|@ instruction JUMP ~[] destination: B8 -> B9 <|@ <|@
    end_IR
  end_block
  begin_block
    name "B9"
    from_bci -1
    to_bci -1
    predecessors "B5" "B8" 
    successors "B10" "B11" 
    xhandlers
    flags 
    probability 4607182418800017408
    begin_IR
      LIR
      nr   -1  <|@ instruction [] = LABEL numbPhis: 0 align: false label: ? <|@ <|@
      nr   -1  <|@ instruction TEST (x: v6|DWORD, y: v6|DWORD) size: DWORD <|@ <|@
      nr   -1  <|@ instruction BRANCH trueDestinationProbability: 0.0 condition: < trueDestination: B9 -> B10 falseDestination: B9 -> B11 <|@ <|@
    end_IR
  end_block
  begin_block
    name "B11"
    from_bci -1
    to_bci -1
    predecessors "B9" 
    successors "B12" "B24" 
    xhandlers
    flags 
    probability 4607182418800017408
    begin_IR
      LIR
      nr   -1  <|@ instruction [] = LABEL numbPhis: 0 align: false label: ? <|@ <|@
      nr   -1  <|@ instruction CMP (x: v6|DWORD, y: v10|DWORD) size: DWORD <|@ <|@
      nr   -1  <|@ instruction BRANCH trueDestinationProbability: 1.0 condition: > trueDestination: B11 -> B12 falseDestination: B11 -> B24 <|@ <|@
    end_IR
  end_block
  begin_block
    name "B12"
    from_bci -1
    to_bci -1
    predecessors "B11" 
    successors "B13" "B14" 
    xhandlers
    flags 
    probability 4607182418800017408
    begin_IR
      LIR
      nr   -1  <|@ instruction [] = LABEL numbPhis: 0 align: false label: ? <|@ <|@
      nr   -1  <|@ instruction TEST (x: v5|DWORD, y: v5|DWORD) size: DWORD <|@ <|@
      nr   -1  <|@ instruction BRANCH trueDestinationProbability: 0.0 condition: = trueDestination: B12 -> B13 falseDestination: B12 -> B14 <|@ <|@
    end_IR
  end_block
  begin_block
    name "B14"
    from_bci -1
    to_bci -1
    predecessors "B12" 
    successors "B15" "B23" 
    xhandlers
    flags 
    probability 4607182418800017408
    begin_IR
      LIR
      nr   -1  <|@ instruction [] = LABEL numbPhis: 0 align: false label: ? <|@ <|@
      nr   -1  <|@ instruction v20|DWORD = ADD (x: v4|DWORD, y: v5|DWORD) size: DWORD <|@ <|@
      nr   -1  <|@ instruction v21|DWORD = DEC v20|DWORD size: DWORD <|@ <|@
      nr   -1  <|@ st <@st|@java.lang.String.lastIndexOf(String.java:1869) [bci: 0]
locals: v0|QWORD[.] v1|DWORD v2|DWORD v3|QWORD[.] v4|DWORD v5|DWORD v6|DWORD - - - - - - - - 
>@ <|@ instruction CMP (x: v21|DWORD, y: [v3|QWORD[.] + 12]) size: DWORD state [bci:0] <|@ <|@
      nr   -1  <|@ instruction BRANCH trueDestinationProbability: 1.0 condition: |<| trueDestination: B14 -> B15 falseDestination: B14 -> B23 <|@ <|@
    end_IR
  end_block
  begin_block
    name "B15"
    from_bci -1
    to_bci -1
    predecessors "B14" 
    successors "B16" 
    xhandlers
    flags 
    probability 4607182418800017408
    begin_IR
      LIR
      nr   -1  <|@ instruction [] = LABEL numbPhis: 0 align: false label: ? <|@ <|@
      nr   -1  <|@ instruction v22|DWORD = MOVZX [v3|QWORD[.] + v21|DWORD * 2 + 16] size: DWORD <|@ <|@
      nr   -1  <|@ instruction JUMP ~[v11|DWORD] destination: B15 -> B16 <|@ <|@
    end_IR
  end_block
  begin_block
    name "B18"
    from_bci -1
    to_bci -1
    predecessors "B16" 
    successors "B19" "B22" 
    xhandlers
    flags 
    loop_index 0
    loop_depth 1
    probability 4623735216054988003
    begin_IR
      LIR
      nr   -1  <|@ instruction [] = LABEL numbPhis: 0 align: true label: ? <|@ <|@
      nr   -1  <|@ instruction v24|DWORD = MOVZX [v0|QWORD[.] + v23|DWORD * 2 + 16] size: DWORD <|@ <|@
      nr   -1  <|@ instruction v25|DWORD = DEC v23|DWORD size: DWORD <|@ <|@
      nr   -1  <|@ instruction CMP (x: v24|DWORD, y: v22|DWORD) size: DWORD <|@ <|@
      nr   -1  <|@ instruction BRANCH trueDestinationProbability: 0.059746592040655154 condition: = trueDestination: B18 -> B19 falseDestination: B18 -> B22 <|@ <|@
    end_IR
  end_block
  begin_block
    name "B22"
    from_bci -1
    to_bci -1
    predecessors "B18" 
    successors "B16" 
    xhandlers
    flags "lle" 
    loop_index 0
    loop_depth 1
    probability 4623284392289565502
    begin_IR
      LIR
      nr   -1  <|@ instruction [] = LABEL numbPhis: 0 align: false label: ? <|@ <|@
      nr   -1  <|@ instruction JUMP ~[v25|DWORD] destination: B22 -> B16 <|@ <|@
    end_IR
  end_block
  begin_block
    name "B16"
    from_bci -1
    to_bci -1
    predecessors "B15" "B22" 
    successors "B17" "B18" 
    xhandlers
    flags "llh" 
    loop_index 0
    loop_depth 1
    probability 4623847342242986814
    begin_IR
      LIR
      nr   -1  <|@ instruction [v23|DWORD] = LABEL numbPhis: 1 align: false label: ? <|@ <|@
      nr   -1  <|@ instruction CMP (x: v9|DWORD, y: v23|DWORD) size: DWORD <|@ <|@
      nr   -1  <|@ instruction BRANCH trueDestinationProbability: 0.014642233807685692 condition: > trueDestination: B16 -> B17 falseDestination: B16 -> B18 <|@ <|@
    end_IR
  end_block
  begin_block
    name "B19"
    from_bci -1
    to_bci -1
    predecessors "B18" 
    successors "B20" "B21" 
    xhandlers
    flags 
    probability 4605388399792036439
    begin_IR
      LIR
      nr   -1  <|@ instruction [] = LABEL numbPhis: 0 align: false label: ? <|@ <|@
      nr   -1  <|@ instruction v26|DWORD = DEC v5|DWORD size: DWORD <|@ <|@
      nr   -1  <|@ instruction v27|DWORD = SUB (x: v25|DWORD, ~y: v26|DWORD) size: DWORD <|@ <|@
      nr   -1  <|@ instruction CMP (x: v25|DWORD, y: v27|DWORD) size: DWORD <|@ <|@
      nr   -1  <|@ instruction BRANCH trueDestinationProbability: 0.0 condition: > trueDestination: B19 -> B20 falseDestination: B19 -> B21 <|@ <|@
    end_IR
  end_block
  begin_block
    name "B21"
    from_bci -1
    to_bci -1
    predecessors "B19" 
    successors 
    xhandlers
    flags 
    probability 4605388399792036439
    begin_IR
      LIR
      nr   -1  <|@ instruction [] = LABEL numbPhis: 0 align: false label: ? <|@ <|@
      nr   -1  <|@ instruction v28|DWORD = SUB (x: v27|DWORD, ~y: v1|DWORD) size: DWORD <|@ <|@
      nr   -1  <|@ instruction v29|DWORD = INC v28|DWORD size: DWORD <|@ <|@
      nr   -1  <|@ instruction rax|DWORD = MOVE v29|DWORD moveKind: DWORD <|@ <|@
      nr   -1  <|@ instruction RETURN (savedRbp: stack:16|QWORD, value: rax|DWORD) isStub: false thread: r15 scratchForSafepointOnReturn: rcx config: org.graalvm.compiler.hotspot.GraalHotSpotVMConfig@7222fe45 <|@ <|@
    end_IR
  end_block
  begin_block
    name "B5"
    from_bci -1
    to_bci -1
    predecessors "B4" 
    successors "B9" 
    xhandlers
    flags 
    probability 4602678819172646912
    begin_IR
      LIR
      nr   -1  <|@ instruction [] = LABEL numbPhis: 0 align: false label: ? <|@ <|@
      nr   -1  <|@ instruction JUMP ~[] destination: B5 -> B9 <|@ <|@
    end_IR
  end_block
  begin_block
    name "B17"
    from_bci -1
    to_bci -1
    predecessors "B16" 
    successors 
    xhandlers
    flags 
    probability 4596344096322459299
    begin_IR
      LIR
      nr   -1  <|@ instruction [] = LABEL numbPhis: 0 align: false label: ? <|@ <|@
      nr   -1  <|@ instruction rax|DWORD = MOVE input: int[-1|0xffffffffffffffff] <|@ <|@
      nr   -1  <|@ instruction RETURN (savedRbp: stack:16|QWORD, value: rax|DWORD) isStub: false thread: r15 scratchForSafepointOnReturn: rcx config: org.graalvm.compiler.hotspot.GraalHotSpotVMConfig@7222fe45 <|@ <|@
    end_IR
  end_block
  begin_block
    name "B1"
    from_bci -1
    to_bci -1
    predecessors "B0" 
    successors "B27" 
    xhandlers
    flags 
    probability 2355382605114769408
    begin_IR
      LIR
      nr   -1  <|@ instruction [] = LABEL numbPhis: 0 align: false label: ? <|@ <|@
      nr   -1  <|@ instruction v7|QWORD[.] = HOTSPOTLOADOBJECTCONSTANT input: Object[d.a@506959935] <|@ <|@
      nr   -1  <|@ instruction JUMP ~[int[-27147|0xffffffffffff95f5], v7|QWORD[.]] destination: B1 -> B27 <|@ <|@
    end_IR
  end_block
  begin_block
    name "B27"
    from_bci -1
    to_bci -1
    predecessors "B1" "B3" "B10" "B26" "B13" "B24" "B23" "B25" 
    successors 
    xhandlers
    flags 
    probability 2368893403996880896
    begin_IR
      LIR
      nr   -1  <|@ instruction [v30|DWORD, v31|QWORD[.]] = LABEL numbPhis: 2 align: false label: ? <|@ <|@
      nr   -1  <|@ instruction MOV (x: [r15|QWORD + 668], y: v30|DWORD) size: DWORD <|@ <|@
      nr   -1  <|@ instruction MOV (x: [r15|QWORD + 680], y: v31|QWORD[.]) size: QWORD <|@ <|@
      nr   -1  <|@ st <@st|@java.lang.String.lastIndexOf(String.java:1869) [bci: 0]
locals: v0|QWORD[.] v1|DWORD v2|DWORD v3|QWORD[.] v4|DWORD v5|DWORD v6|DWORD - - - - - - - - 
>@ <|@ instruction DEOPT info [bci:0] <|@ <|@
    end_IR
  end_block
  begin_block
    name "B24"
    from_bci -1
    to_bci -1
    predecessors "B11" 
    successors "B27" 
    xhandlers
    flags 
    probability 2355382605114769408
    begin_IR
      LIR
      nr   -1  <|@ instruction [] = LABEL numbPhis: 0 align: false label: ? <|@ <|@
      nr   -1  <|@ instruction JUMP ~[int[-22291|0xffffffffffffa8ed], Object[null]] destination: B24 -> B27 <|@ <|@
    end_IR
  end_block
  begin_block
    name "B20"
    from_bci -1
    to_bci -1
    predecessors "B19" 
    successors 
    xhandlers
    flags 
    probability 2355382605114769408
    begin_IR
      LIR
      nr   -1  <|@ instruction [] = LABEL numbPhis: 0 align: false label: ? <|@ <|@
      nr   -1  <|@ instruction MOV [r15|QWORD + 668] y: -30483 size: DWORD <|@ <|@
      nr   -1  <|@ instruction MOV (x: [r15|QWORD + 680], y: r12|ILLEGAL) size: QWORD <|@ <|@
      nr   -1  <|@ st <@st|@java.lang.String.lastIndexOf(String.java:1888) [bci: 62]
locals: v0|QWORD[.] v1|DWORD - v3|QWORD[.] - v5|DWORD - - v21|DWORD v22|DWORD v9|DWORD v23|DWORD - - - 
>@ <|@ instruction DEOPT info [bci:62] <|@ <|@
    end_IR
  end_block
  begin_block
    name "B23"
    from_bci -1
    to_bci -1
    predecessors "B14" 
    successors "B27" 
    xhandlers
    flags 
    probability 2355382605114769408
    begin_IR
      LIR
      nr   -1  <|@ instruction [] = LABEL numbPhis: 0 align: false label: ? <|@ <|@
      nr   -1  <|@ instruction JUMP ~[int[-24603|0xffffffffffff9fe5], Object[null]] destination: B23 -> B27 <|@ <|@
    end_IR
  end_block
  begin_block
    name "B10"
    from_bci -1
    to_bci -1
    predecessors "B9" 
    successors "B27" 
    xhandlers
    flags 
    probability 2355382605114769408
    begin_IR
      LIR
      nr   -1  <|@ instruction [] = LABEL numbPhis: 0 align: false label: ? <|@ <|@
      nr   -1  <|@ instruction JUMP ~[int[-22035|0xffffffffffffa9ed], Object[null]] destination: B10 -> B27 <|@ <|@
    end_IR
  end_block
  begin_block
    name "B13"
    from_bci -1
    to_bci -1
    predecessors "B12" 
    successors "B27" 
    xhandlers
    flags 
    probability 2355382605114769408
    begin_IR
      LIR
      nr   -1  <|@ instruction [] = LABEL numbPhis: 0 align: false label: ? <|@ <|@
      nr   -1  <|@ instruction JUMP ~[int[-22547|0xffffffffffffa7ed], Object[null]] destination: B13 -> B27 <|@ <|@
    end_IR
  end_block
  begin_block
    name "B3"
    from_bci -1
    to_bci -1
    predecessors "B2" 
    successors "B27" 
    xhandlers
    flags 
    probability 2355382605114769408
    begin_IR
      LIR
      nr   -1  <|@ instruction [] = LABEL numbPhis: 0 align: false label: ? <|@ <|@
      nr   -1  <|@ instruction JUMP ~[int[-33924|0xffffffffffff7b7c], Object[null]] destination: B3 -> B27 <|@ <|@
    end_IR
  end_block
  begin_block
    name "B25"
    from_bci -1
    to_bci -1
    predecessors "B7" 
    successors "B27" 
    xhandlers
    flags 
    probability 2355382605114769408
    begin_IR
      LIR
      nr   -1  <|@ instruction [] = LABEL numbPhis: 0 align: false label: ? <|@ <|@
      nr   -1  <|@ instruction v33|QWORD[.] = HOTSPOTLOADOBJECTCONSTANT input: Object[d.a@800922110] <|@ <|@
      nr   -1  <|@ instruction JUMP ~[int[-28443|0xffffffffffff90e5], v33|QWORD[.]] destination: B25 -> B27 <|@ <|@
    end_IR
  end_block
  begin_block
    name "B26"
    from_bci -1
    to_bci -1
    predecessors "B6" 
    successors "B27" 
    xhandlers
    flags 
    probability 2355382605114769408
    begin_IR
      LIR
      nr   -1  <|@ instruction [] = LABEL numbPhis: 0 align: false label: ? <|@ <|@
      nr   -1  <|@ instruction v32|QWORD[.] = HOTSPOTLOADOBJECTCONSTANT input: Object[d.a@800922110] <|@ <|@
      nr   -1  <|@ instruction JUMP ~[int[-28443|0xffffffffffff90e5], v32|QWORD[.]] destination: B26 -> B27 <|@ <|@
    end_IR
  end_block
end_cfg
begin_bytecodes
     0: iload_2       
     1: iload         5
     3: isub          
     4: istore        7
     6: iload         6
     8: ifge          13
    11: iconst_m1     
    12: ireturn       
    13: iload         6
    15: iload         7
    17: if_icmple     24
    20: iload         7
    22: istore        6
    24: iload         5
    26: ifne          32
    29: iload         6
    31: ireturn       
    32: iload         4
    34: iload         5
    36: iadd          
    37: iconst_1      
    38: isub          
    39: istore        8
    41: aload_3       
    42: iload         8
    44: caload        
    45: istore        9
    47: iload_1       
    48: iload         5
    50: iadd          
    51: iconst_1      
    52: isub          
    53: istore        10
    55: iload         10
    57: iload         6
    59: iadd          
    60: istore        11
    62: iload         11
    64: iload         10
    66: if_icmplt     84
    69: aload_0       
    70: iload         11
    72: caload        
    73: iload         9
    75: if_icmpeq     84
    78: iinc          
    81: goto          62
    84: iload         11
    86: iload         10
    88: if_icmpge     93
    91: iconst_m1     
    92: ireturn       
    93: iload         11
    95: iconst_1      
    96: isub          
    97: istore        12
    99: iload         12
   101: iload         5
   103: iconst_1      
   104: isub          
   105: isub          
   106: istore        13
   108: iload         8
   110: iconst_1      
   111: isub          
   112: istore        14
   114: iload         12
   116: iload         13
   118: if_icmple     144
   121: aload_0       
   122: iload         12
   124: iinc          
   127: caload        
   128: aload_3       
   129: iload         14
   131: iinc          
   134: caload        
   135: if_icmpeq     114
   138: iinc          
   141: goto          62
   144: iload         13
   146: iload_1       
   147: isub          
   148: iconst_1      
   149: iadd          
   150: ireturn       
   <|@
end_bytecodes
begin_cfg
  name "After AllocationStage"
  begin_block
    name "B0"
    from_bci -1
    to_bci -1
    predecessors 
    successors "B1" "B2" 
    xhandlers
    flags 
    probability 4607182418800017408
    begin_IR
      LIR
      nr    0  <|@ instruction [rsi|QWORD[.], rdx|DWORD, rcx|DWORD, r8|QWORD[.], r9|DWORD, rdi|DWORD, in:0|DWORD, rbp|QWORD] = LABEL numbPhis: 0 align: false label: ? <|@ <|@
      nr    2  <|@ instruction stack:16|QWORD = MOVE rbp|QWORD moveKind: QWORD <|@ <|@
      nr    4  <|@ instruction [] = HOTSPOTLOCKSTACK frameMapBuilder: org.graalvm.compiler.lir.amd64.AMD64FrameMapBuilder@6dfa0585 slotKind: QWORD <|@ <|@
      nr   20  <|@ instruction TEST (x: rsi|QWORD[.], y: rsi|QWORD[.]) size: QWORD <|@ <|@
      nr   22  <|@ instruction BRANCH trueDestinationProbability: 0.0 condition: = trueDestination: B0 -> B1 falseDestination: B0 -> B2 <|@ <|@
    end_IR
  end_block
  begin_block
    name "B2"
    from_bci -1
    to_bci -1
    predecessors "B0" 
    successors "B3" "B4" 
    xhandlers
    flags 
    probability 4607182418800017408
    begin_IR
      LIR
      nr   24  <|@ instruction [] = LABEL numbPhis: 0 align: false label: ? <|@ <|@
      nr   26  <|@ instruction rax|DWORD = ADD (x: rdx|DWORD, y: rdi|DWORD) size: DWORD <|@ <|@
      nr   28  <|@ instruction rax|DWORD = DEC rax|DWORD size: DWORD <|@ <|@
      nr   30  <|@ instruction CMP rax|DWORD y: -2147483645 size: DWORD <|@ <|@
      nr   32  <|@ instruction BRANCH trueDestinationProbability: 0.0 condition: < trueDestination: B2 -> B3 falseDestination: B2 -> B4 <|@ <|@
    end_IR
  end_block
  begin_block
    name "B4"
    from_bci -1
    to_bci -1
    predecessors "B2" 
    successors "B5" "B6" 
    xhandlers
    flags 
    probability 4607182418800017408
    begin_IR
      LIR
      nr   34  <|@ instruction [] = LABEL numbPhis: 0 align: false label: ? <|@ <|@
      nr   36  <|@ instruction r10|DWORD = SUB (x: rcx|DWORD, ~y: rdi|DWORD) size: DWORD <|@ <|@
      nr   38  <|@ instruction r11|DWORD = ADD (x: r10|DWORD, y: rax|DWORD) size: DWORD <|@ <|@
      nr   40  <|@ instruction CMP (x: rax|DWORD, y: r11|DWORD) size: DWORD <|@ <|@
      nr   42  <|@ instruction BRANCH trueDestinationProbability: 0.5 condition: > trueDestination: B4 -> B5 falseDestination: B4 -> B6 <|@ <|@
    end_IR
  end_block
  begin_block
    name "B6"
    from_bci -1
    to_bci -1
    predecessors "B4" 
    successors "B7" "B26" 
    xhandlers
    flags 
    probability 4602678819172646912
    begin_IR
      LIR
      nr   44  <|@ instruction [] = LABEL numbPhis: 0 align: false label: ? <|@ <|@
      nr   46  <|@ instruction rbx|DWORD = MOV [rsi|QWORD[.] + 12] size: DWORD <|@ <|@
      nr   48  <|@ instruction rbp|QWORD = MOVSXD r11|DWORD size: QWORD <|@ <|@
      nr   50  <|@ instruction r13|DWORD = INC r10|DWORD size: DWORD <|@ <|@
      nr   52  <|@ instruction r13|QWORD = MOVSXD r13|DWORD size: QWORD <|@ <|@
      nr   54  <|@ instruction r13|QWORD = DEC r13|QWORD size: QWORD <|@ <|@
      nr   56  <|@ instruction rbp|QWORD = SUB (x: rbp|QWORD, ~y: r13|QWORD) size: QWORD <|@ <|@
      nr   58  <|@ instruction r13|QWORD = MOV rbx|DWORD size: DWORD <|@ <|@
      nr   60  <|@ instruction CMP (x: r13|QWORD, y: rbp|QWORD) size: QWORD <|@ <|@
      nr   62  <|@ instruction BRANCH trueDestinationProbability: 1.0 condition: |>| trueDestination: B6 -> B7 falseDestination: B6 -> B26 <|@ <|@
    end_IR
  end_block
  begin_block
    name "B7"
    from_bci -1
    to_bci -1
    predecessors "B6" 
    successors "B8" "B25" 
    xhandlers
    flags 
    probability 4602678819172646912
    begin_IR
      LIR
      nr   64  <|@ instruction [] = LABEL numbPhis: 0 align: false label: ? <|@ <|@
      nr   66  <|@ instruction CMP (x: rbx|DWORD, y: r11|DWORD) size: DWORD <|@ <|@
      nr   68  <|@ instruction BRANCH trueDestinationProbability: 1.0 condition: |>| trueDestination: B7 -> B8 falseDestination: B7 -> B25 <|@ <|@
    end_IR
  end_block
  begin_block
    name "B8"
    from_bci -1
    to_bci -1
    predecessors "B7" 
    successors "B9" 
    xhandlers
    flags 
    probability 4602678819172646912
    begin_IR
      LIR
      nr   70  <|@ instruction [] = LABEL numbPhis: 0 align: false label: ? <|@ <|@
      nr   -1  <|@ instruction rbx|DWORD = MOVE in:0|DWORD moveKind: DWORD // MoveResolver resolve mapping <|@ <|@
      nr   72  <|@ instruction JUMP ~[] destination: B8 -> B9 <|@ <|@
    end_IR
  end_block
  begin_block
    name "B9"
    from_bci -1
    to_bci -1
    predecessors "B5" "B8" 
    successors "B10" "B11" 
    xhandlers
    flags 
    probability 4607182418800017408
    begin_IR
      LIR
      nr   78  <|@ instruction [] = LABEL numbPhis: 0 align: false label: ? <|@ <|@
      nr   80  <|@ instruction TEST (x: rbx|DWORD, y: rbx|DWORD) size: DWORD <|@ <|@
      nr   82  <|@ instruction BRANCH trueDestinationProbability: 0.0 condition: < trueDestination: B9 -> B10 falseDestination: B9 -> B11 <|@ <|@
    end_IR
  end_block
  begin_block
    name "B11"
    from_bci -1
    to_bci -1
    predecessors "B9" 
    successors "B12" "B24" 
    xhandlers
    flags 
    probability 4607182418800017408
    begin_IR
      LIR
      nr   84  <|@ instruction [] = LABEL numbPhis: 0 align: false label: ? <|@ <|@
      nr   86  <|@ instruction CMP (x: rbx|DWORD, y: r10|DWORD) size: DWORD <|@ <|@
      nr   88  <|@ instruction BRANCH trueDestinationProbability: 1.0 condition: > trueDestination: B11 -> B12 falseDestination: B11 -> B24 <|@ <|@
    end_IR
  end_block
  begin_block
    name "B12"
    from_bci -1
    to_bci -1
    predecessors "B11" 
    successors "B13" "B14" 
    xhandlers
    flags 
    probability 4607182418800017408
    begin_IR
      LIR
      nr   90  <|@ instruction [] = LABEL numbPhis: 0 align: false label: ? <|@ <|@
      nr   92  <|@ instruction TEST (x: rdi|DWORD, y: rdi|DWORD) size: DWORD <|@ <|@
      nr   94  <|@ instruction BRANCH trueDestinationProbability: 0.0 condition: = trueDestination: B12 -> B13 falseDestination: B12 -> B14 <|@ <|@
    end_IR
  end_block
  begin_block
    name "B14"
    from_bci -1
    to_bci -1
    predecessors "B12" 
    successors "B15" "B23" 
    xhandlers
    flags 
    probability 4607182418800017408
    begin_IR
      LIR
      nr   96  <|@ instruction [] = LABEL numbPhis: 0 align: false label: ? <|@ <|@
      nr   98  <|@ instruction r10|DWORD = ADD (x: r9|DWORD, y: rdi|DWORD) size: DWORD <|@ <|@
      nr  100  <|@ instruction r10|DWORD = DEC r10|DWORD size: DWORD <|@ <|@
      nr  102  <|@ st <@st|@reference-map: [rsi:0, r8:0]
live-base-pointers: []
java.lang.String.lastIndexOf(String.java:1869) [bci: 0]
locals: rsi|QWORD[.] rdx|DWORD rcx|DWORD r8|QWORD[.] r9|DWORD rdi|DWORD rbx|DWORD - - - - - - - - 
>@ <|@ instruction CMP (x: r10|DWORD, y: [r8|QWORD[.] + 12]) size: DWORD state [bci:0] <|@ <|@
      nr  104  <|@ instruction BRANCH trueDestinationProbability: 1.0 condition: |<| trueDestination: B14 -> B15 falseDestination: B14 -> B23 <|@ <|@
    end_IR
  end_block
  begin_block
    name "B15"
    from_bci -1
    to_bci -1
    predecessors "B14" 
    successors "B16" 
    xhandlers
    flags 
    probability 4607182418800017408
    begin_IR
      LIR
      nr  106  <|@ instruction [] = LABEL numbPhis: 0 align: false label: ? <|@ <|@
      nr  108  <|@ instruction r9|DWORD = MOVZX [r8|QWORD[.] + r10|DWORD * 2 + 16] size: DWORD <|@ <|@
      nr  110  <|@ instruction JUMP ~[] destination: B15 -> B16 <|@ <|@
    end_IR
  end_block
  begin_block
    name "B18"
    from_bci -1
    to_bci -1
    predecessors "B16" 
    successors "B19" "B22" 
    xhandlers
    flags 
    loop_index 0
    loop_depth 1
    probability 4623735216054988003
    begin_IR
      LIR
      nr  118  <|@ instruction [] = LABEL numbPhis: 0 align: true label: ? <|@ <|@
      nr  120  <|@ instruction rcx|DWORD = MOVZX [rsi|QWORD[.] + r11|DWORD * 2 + 16] size: DWORD <|@ <|@
      nr  122  <|@ instruction rbx|DWORD = DEC r11|DWORD size: DWORD <|@ <|@
      nr  124  <|@ instruction CMP (x: rcx|DWORD, y: r9|DWORD) size: DWORD <|@ <|@
      nr  126  <|@ instruction BRANCH trueDestinationProbability: 0.059746592040655154 condition: = trueDestination: B18 -> B19 falseDestination: B18 -> B22 <|@ <|@
    end_IR
  end_block
  begin_block
    name "B22"
    from_bci -1
    to_bci -1
    predecessors "B18" 
    successors "B16" 
    xhandlers
    flags "lle" 
    loop_index 0
    loop_depth 1
    probability 4623284392289565502
    begin_IR
      LIR
      nr  128  <|@ instruction [] = LABEL numbPhis: 0 align: false label: ? <|@ <|@
      nr   -1  <|@ instruction r11|DWORD = MOVE rbx|DWORD moveKind: DWORD // MoveResolver resolve mapping <|@ <|@
      nr  130  <|@ instruction JUMP ~[] destination: B22 -> B16 <|@ <|@
    end_IR
  end_block
  begin_block
    name "B16"
    from_bci -1
    to_bci -1
    predecessors "B15" "B22" 
    successors "B17" "B18" 
    xhandlers
    flags "llh" 
    loop_index 0
    loop_depth 1
    probability 4623847342242986814
    begin_IR
      LIR
      nr  112  <|@ instruction [] = LABEL numbPhis: 1 align: false label: ? <|@ <|@
      nr  114  <|@ instruction CMP (x: rax|DWORD, y: r11|DWORD) size: DWORD <|@ <|@
      nr  116  <|@ instruction BRANCH trueDestinationProbability: 0.014642233807685692 condition: > trueDestination: B16 -> B17 falseDestination: B16 -> B18 <|@ <|@
    end_IR
  end_block
  begin_block
    name "B19"
    from_bci -1
    to_bci -1
    predecessors "B18" 
    successors "B20" "B21" 
    xhandlers
    flags 
    probability 4605388399792036439
    begin_IR
      LIR
      nr  132  <|@ instruction [] = LABEL numbPhis: 0 align: false label: ? <|@ <|@
      nr  134  <|@ instruction rcx|DWORD = DEC rdi|DWORD size: DWORD <|@ <|@
      nr  136  <|@ instruction rbp|DWORD = SUB (x: rbx|DWORD, ~y: rcx|DWORD) size: DWORD <|@ <|@
      nr  138  <|@ instruction CMP (x: rbx|DWORD, y: rbp|DWORD) size: DWORD <|@ <|@
      nr  140  <|@ instruction BRANCH trueDestinationProbability: 0.0 condition: > trueDestination: B19 -> B20 falseDestination: B19 -> B21 <|@ <|@
    end_IR
  end_block
  begin_block
    name "B21"
    from_bci -1
    to_bci -1
    predecessors "B19" 
    successors 
    xhandlers
    flags 
    probability 4605388399792036439
    begin_IR
      LIR
      nr  142  <|@ instruction [] = LABEL numbPhis: 0 align: false label: ? <|@ <|@
      nr  144  <|@ instruction rbp|DWORD = SUB (x: rbp|DWORD, ~y: rdx|DWORD) size: DWORD <|@ <|@
      nr  146  <|@ instruction rbp|DWORD = INC rbp|DWORD size: DWORD <|@ <|@
      nr  148  <|@ instruction rax|DWORD = MOVE rbp|DWORD moveKind: DWORD <|@ <|@
      nr  150  <|@ instruction RETURN (savedRbp: stack:16|QWORD, value: rax|DWORD) isStub: false thread: r15 scratchForSafepointOnReturn: rcx config: org.graalvm.compiler.hotspot.GraalHotSpotVMConfig@7222fe45 <|@ <|@
    end_IR
  end_block
  begin_block
    name "B5"
    from_bci -1
    to_bci -1
    predecessors "B4" 
    successors "B9" 
    xhandlers
    flags 
    probability 4602678819172646912
    begin_IR
      LIR
      nr   74  <|@ instruction [] = LABEL numbPhis: 0 align: false label: ? <|@ <|@
      nr   -1  <|@ instruction rbx|DWORD = MOVE in:0|DWORD moveKind: DWORD // MoveResolver resolve mapping <|@ <|@
      nr   76  <|@ instruction JUMP ~[] destination: B5 -> B9 <|@ <|@
    end_IR
  end_block
  begin_block
    name "B17"
    from_bci -1
    to_bci -1
    predecessors "B16" 
    successors 
    xhandlers
    flags 
    probability 4596344096322459299
    begin_IR
      LIR
      nr  152  <|@ instruction [] = LABEL numbPhis: 0 align: false label: ? <|@ <|@
      nr  154  <|@ instruction rax|DWORD = MOVE input: int[-1|0xffffffffffffffff] <|@ <|@
      nr  156  <|@ instruction RETURN (savedRbp: stack:16|QWORD, value: rax|DWORD) isStub: false thread: r15 scratchForSafepointOnReturn: rcx config: org.graalvm.compiler.hotspot.GraalHotSpotVMConfig@7222fe45 <|@ <|@
    end_IR
  end_block
  begin_block
    name "B1"
    from_bci -1
    to_bci -1
    predecessors "B0" 
    successors "B27" 
    xhandlers
    flags 
    probability 2355382605114769408
    begin_IR
      LIR
      nr  194  <|@ instruction [] = LABEL numbPhis: 0 align: false label: ? <|@ <|@
      nr   -1  <|@ instruction rbx|DWORD = MOVE in:0|DWORD moveKind: DWORD // MoveResolver resolve mapping <|@ <|@
      nr  196  <|@ instruction r10|QWORD[.] = HOTSPOTLOADOBJECTCONSTANT input: Object[d.a@506959935] <|@ <|@
      nr   -1  <|@ instruction r11|QWORD[.] = MOVE r10|QWORD[.] moveKind: QWORD // MoveResolver resolve mapping <|@ <|@
      nr   -1  <|@ instruction r10|DWORD = MOVE input: int[-27147|0xffffffffffff95f5] // MoveResolver resolve mapping <|@ <|@
      nr  198  <|@ instruction JUMP ~[] destination: B1 -> B27 <|@ <|@
    end_IR
  end_block
  begin_block
    name "B27"
    from_bci -1
    to_bci -1
    predecessors "B1" "B3" "B10" "B26" "B13" "B24" "B23" "B25" 
    successors 
    xhandlers
    flags 
    probability 2368893403996880896
    begin_IR
      LIR
      nr  204  <|@ instruction [] = LABEL numbPhis: 2 align: false label: ? <|@ <|@
      nr  206  <|@ instruction MOV (x: [r15|QWORD + 668], y: r10|DWORD) size: DWORD <|@ <|@
      nr  208  <|@ instruction MOV (x: [r15|QWORD + 680], y: r11|QWORD[.]) size: QWORD <|@ <|@
      nr  210  <|@ st <@st|@reference-map: [rsi:0, r8:0]
live-base-pointers: []
java.lang.String.lastIndexOf(String.java:1869) [bci: 0]
locals: rsi|QWORD[.] rdx|DWORD rcx|DWORD r8|QWORD[.] r9|DWORD rdi|DWORD rbx|DWORD - - - - - - - - 
>@ <|@ instruction DEOPT info [bci:0] <|@ <|@
    end_IR
  end_block
  begin_block
    name "B24"
    from_bci -1
    to_bci -1
    predecessors "B11" 
    successors "B27" 
    xhandlers
    flags 
    probability 2355382605114769408
    begin_IR
      LIR
      nr  182  <|@ instruction [] = LABEL numbPhis: 0 align: false label: ? <|@ <|@
      nr   -1  <|@ instruction r11|QWORD[.] = MOVE input: Object[null] // MoveResolver resolve mapping <|@ <|@
      nr   -1  <|@ instruction r10|DWORD = MOVE input: int[-22291|0xffffffffffffa8ed] // MoveResolver resolve mapping <|@ <|@
      nr  184  <|@ instruction JUMP ~[] destination: B24 -> B27 <|@ <|@
    end_IR
  end_block
  begin_block
    name "B20"
    from_bci -1
    to_bci -1
    predecessors "B19" 
    successors 
    xhandlers
    flags 
    probability 2355382605114769408
    begin_IR
      LIR
      nr  168  <|@ instruction [] = LABEL numbPhis: 0 align: false label: ? <|@ <|@
      nr  170  <|@ instruction MOV [r15|QWORD + 668] y: -30483 size: DWORD <|@ <|@
      nr  172  <|@ instruction MOV (x: [r15|QWORD + 680], y: r12|ILLEGAL) size: QWORD <|@ <|@
      nr  174  <|@ st <@st|@reference-map: [rsi:0, r8:0]
live-base-pointers: []
java.lang.String.lastIndexOf(String.java:1888) [bci: 62]
locals: rsi|QWORD[.] rdx|DWORD - r8|QWORD[.] - rdi|DWORD - - r10|DWORD r9|DWORD rax|DWORD r11|DWORD - - - 
>@ <|@ instruction DEOPT info [bci:62] <|@ <|@
    end_IR
  end_block
  begin_block
    name "B23"
    from_bci -1
    to_bci -1
    predecessors "B14" 
    successors "B27" 
    xhandlers
    flags 
    probability 2355382605114769408
    begin_IR
      LIR
      nr  186  <|@ instruction [] = LABEL numbPhis: 0 align: false label: ? <|@ <|@
      nr   -1  <|@ instruction r11|QWORD[.] = MOVE input: Object[null] // MoveResolver resolve mapping <|@ <|@
      nr   -1  <|@ instruction r10|DWORD = MOVE input: int[-24603|0xffffffffffff9fe5] // MoveResolver resolve mapping <|@ <|@
      nr  188  <|@ instruction JUMP ~[] destination: B23 -> B27 <|@ <|@
    end_IR
  end_block
  begin_block
    name "B10"
    from_bci -1
    to_bci -1
    predecessors "B9" 
    successors "B27" 
    xhandlers
    flags 
    probability 2355382605114769408
    begin_IR
      LIR
      nr  190  <|@ instruction [] = LABEL numbPhis: 0 align: false label: ? <|@ <|@
      nr   -1  <|@ instruction r11|QWORD[.] = MOVE input: Object[null] // MoveResolver resolve mapping <|@ <|@
      nr   -1  <|@ instruction r10|DWORD = MOVE input: int[-22035|0xffffffffffffa9ed] // MoveResolver resolve mapping <|@ <|@
      nr  192  <|@ instruction JUMP ~[] destination: B10 -> B27 <|@ <|@
    end_IR
  end_block
  begin_block
    name "B13"
    from_bci -1
    to_bci -1
    predecessors "B12" 
    successors "B27" 
    xhandlers
    flags 
    probability 2355382605114769408
    begin_IR
      LIR
      nr  164  <|@ instruction [] = LABEL numbPhis: 0 align: false label: ? <|@ <|@
      nr   -1  <|@ instruction r11|QWORD[.] = MOVE input: Object[null] // MoveResolver resolve mapping <|@ <|@
      nr   -1  <|@ instruction r10|DWORD = MOVE input: int[-22547|0xffffffffffffa7ed] // MoveResolver resolve mapping <|@ <|@
      nr  166  <|@ instruction JUMP ~[] destination: B13 -> B27 <|@ <|@
    end_IR
  end_block
  begin_block
    name "B3"
    from_bci -1
    to_bci -1
    predecessors "B2" 
    successors "B27" 
    xhandlers
    flags 
    probability 2355382605114769408
    begin_IR
      LIR
      nr  200  <|@ instruction [] = LABEL numbPhis: 0 align: false label: ? <|@ <|@
      nr   -1  <|@ instruction r11|QWORD[.] = MOVE input: Object[null] // MoveResolver resolve mapping <|@ <|@
      nr   -1  <|@ instruction r10|DWORD = MOVE input: int[-33924|0xffffffffffff7b7c] // MoveResolver resolve mapping <|@ <|@
      nr   -1  <|@ instruction rbx|DWORD = MOVE in:0|DWORD moveKind: DWORD // MoveResolver resolve mapping <|@ <|@
      nr  202  <|@ instruction JUMP ~[] destination: B3 -> B27 <|@ <|@
    end_IR
  end_block
  begin_block
    name "B25"
    from_bci -1
    to_bci -1
    predecessors "B7" 
    successors "B27" 
    xhandlers
    flags 
    probability 2355382605114769408
    begin_IR
      LIR
      nr  158  <|@ instruction [] = LABEL numbPhis: 0 align: false label: ? <|@ <|@
      nr   -1  <|@ instruction rbx|DWORD = MOVE in:0|DWORD moveKind: DWORD // MoveResolver resolve mapping <|@ <|@
      nr  160  <|@ instruction r10|QWORD[.] = HOTSPOTLOADOBJECTCONSTANT input: Object[d.a@800922110] <|@ <|@
      nr   -1  <|@ instruction r11|QWORD[.] = MOVE r10|QWORD[.] moveKind: QWORD // MoveResolver resolve mapping <|@ <|@
      nr   -1  <|@ instruction r10|DWORD = MOVE input: int[-28443|0xffffffffffff90e5] // MoveResolver resolve mapping <|@ <|@
      nr  162  <|@ instruction JUMP ~[] destination: B25 -> B27 <|@ <|@
    end_IR
  end_block
  begin_block
    name "B26"
    from_bci -1
    to_bci -1
    predecessors "B6" 
    successors "B27" 
    xhandlers
    flags 
    probability 2355382605114769408
    begin_IR
      LIR
      nr  176  <|@ instruction [] = LABEL numbPhis: 0 align: false label: ? <|@ <|@
      nr   -1  <|@ instruction rbx|DWORD = MOVE in:0|DWORD moveKind: DWORD // MoveResolver resolve mapping <|@ <|@
      nr  178  <|@ instruction r10|QWORD[.] = HOTSPOTLOADOBJECTCONSTANT input: Object[d.a@800922110] <|@ <|@
      nr   -1  <|@ instruction r11|QWORD[.] = MOVE r10|QWORD[.] moveKind: QWORD // MoveResolver resolve mapping <|@ <|@
      nr   -1  <|@ instruction r10|DWORD = MOVE input: int[-28443|0xffffffffffff90e5] // MoveResolver resolve mapping <|@ <|@
      nr  180  <|@ instruction JUMP ~[] destination: B26 -> B27 <|@ <|@
    end_IR
  end_block
end_cfg
begin_bytecodes
     0: iload_2       
     1: iload         5
     3: isub          
     4: istore        7
     6: iload         6
     8: ifge          13
    11: iconst_m1     
    12: ireturn       
    13: iload         6
    15: iload         7
    17: if_icmple     24
    20: iload         7
    22: istore        6
    24: iload         5
    26: ifne          32
    29: iload         6
    31: ireturn       
    32: iload         4
    34: iload         5
    36: iadd          
    37: iconst_1      
    38: isub          
    39: istore        8
    41: aload_3       
    42: iload         8
    44: caload        
    45: istore        9
    47: iload_1       
    48: iload         5
    50: iadd          
    51: iconst_1      
    52: isub          
    53: istore        10
    55: iload         10
    57: iload         6
    59: iadd          
    60: istore        11
    62: iload         11
    64: iload         10
    66: if_icmplt     84
    69: aload_0       
    70: iload         11
    72: caload        
    73: iload         9
    75: if_icmpeq     84
    78: iinc          
    81: goto          62
    84: iload         11
    86: iload         10
    88: if_icmpge     93
    91: iconst_m1     
    92: ireturn       
    93: iload         11
    95: iconst_1      
    96: isub          
    97: istore        12
    99: iload         12
   101: iload         5
   103: iconst_1      
   104: isub          
   105: isub          
   106: istore        13
   108: iload         8
   110: iconst_1      
   111: isub          
   112: istore        14
   114: iload         12
   116: iload         13
   118: if_icmple     144
   121: aload_0       
   122: iload         12
   124: iinc          
   127: caload        
   128: aload_3       
   129: iload         14
   131: iinc          
   134: caload        
   135: if_icmpeq     114
   138: iinc          
   141: goto          62
   144: iload         13
   146: iload_1       
   147: isub          
   148: iconst_1      
   149: iadd          
   150: ireturn       
   <|@
end_bytecodes
begin_cfg
  name "After PostAllocationOptimizationStage"
  begin_block
    name "B0"
    from_bci -1
    to_bci -1
    predecessors 
    successors "B1" "B2" 
    xhandlers
    flags 
    probability 4607182418800017408
    begin_IR
      LIR
      nr    0  <|@ instruction [rsi|QWORD[.], rdx|DWORD, rcx|DWORD, r8|QWORD[.], r9|DWORD, rdi|DWORD, in:0|DWORD, rbp|QWORD] = LABEL numbPhis: 0 align: false label: ? <|@ <|@
      nr    2  <|@ instruction stack:16|QWORD = MOVE rbp|QWORD moveKind: QWORD <|@ <|@
      nr    4  <|@ instruction [] = HOTSPOTLOCKSTACK frameMapBuilder: org.graalvm.compiler.lir.amd64.AMD64FrameMapBuilder@6dfa0585 slotKind: QWORD <|@ <|@
      nr   20  <|@ instruction TEST (x: rsi|QWORD[.], y: rsi|QWORD[.]) size: QWORD <|@ <|@
      nr   22  <|@ instruction BRANCH trueDestinationProbability: 0.0 condition: = trueDestination: B0 -> B1 falseDestination: B0 -> B2 <|@ <|@
    end_IR
  end_block
  begin_block
    name "B2"
    from_bci -1
    to_bci -1
    predecessors "B0" 
    successors "B3" "B4" 
    xhandlers
    flags 
    probability 4607182418800017408
    begin_IR
      LIR
      nr   24  <|@ instruction [] = LABEL numbPhis: 0 align: false label: ? <|@ <|@
      nr   26  <|@ instruction rax|DWORD = ADD (x: rdx|DWORD, y: rdi|DWORD) size: DWORD <|@ <|@
      nr   28  <|@ instruction rax|DWORD = DEC rax|DWORD size: DWORD <|@ <|@
      nr   30  <|@ instruction CMP rax|DWORD y: -2147483645 size: DWORD <|@ <|@
      nr   32  <|@ instruction BRANCH trueDestinationProbability: 0.0 condition: < trueDestination: B2 -> B3 falseDestination: B2 -> B4 <|@ <|@
    end_IR
  end_block
  begin_block
    name "B4"
    from_bci -1
    to_bci -1
    predecessors "B2" 
    successors "B9" "B6" 
    xhandlers
    flags 
    probability 4607182418800017408
    begin_IR
      LIR
      nr   34  <|@ instruction [] = LABEL numbPhis: 0 align: false label: ? <|@ <|@
      nr   36  <|@ instruction r10|DWORD = SUB (x: rcx|DWORD, ~y: rdi|DWORD) size: DWORD <|@ <|@
      nr   38  <|@ instruction r11|DWORD = ADD (x: r10|DWORD, y: rax|DWORD) size: DWORD <|@ <|@
      nr   40  <|@ instruction CMP (x: rax|DWORD, y: r11|DWORD) size: DWORD <|@ <|@
      nr   42  <|@ instruction BRANCH trueDestinationProbability: 0.5 condition: > trueDestination: B4 -> B9 falseDestination: B4 -> B6 <|@ <|@
    end_IR
  end_block
  begin_block
    name "B6"
    from_bci -1
    to_bci -1
    predecessors "B4" 
    successors "B7" "B26" 
    xhandlers
    flags 
    probability 4602678819172646912
    begin_IR
      LIR
      nr   44  <|@ instruction [] = LABEL numbPhis: 0 align: false label: ? <|@ <|@
      nr   46  <|@ instruction rbx|DWORD = MOV [rsi|QWORD[.] + 12] size: DWORD <|@ <|@
      nr   48  <|@ instruction rbp|QWORD = MOVSXD r11|DWORD size: QWORD <|@ <|@
      nr   50  <|@ instruction r13|DWORD = INC r10|DWORD size: DWORD <|@ <|@
      nr   52  <|@ instruction r13|QWORD = MOVSXD r13|DWORD size: QWORD <|@ <|@
      nr   54  <|@ instruction r13|QWORD = DEC r13|QWORD size: QWORD <|@ <|@
      nr   56  <|@ instruction rbp|QWORD = SUB (x: rbp|QWORD, ~y: r13|QWORD) size: QWORD <|@ <|@
      nr   58  <|@ instruction r13|QWORD = MOV rbx|DWORD size: DWORD <|@ <|@
      nr   60  <|@ instruction CMP (x: r13|QWORD, y: rbp|QWORD) size: QWORD <|@ <|@
      nr   62  <|@ instruction BRANCH trueDestinationProbability: 1.0 condition: |>| trueDestination: B6 -> B7 falseDestination: B6 -> B26 <|@ <|@
    end_IR
  end_block
  begin_block
    name "B7"
    from_bci -1
    to_bci -1
    predecessors "B6" 
    successors "B9" "B25" 
    xhandlers
    flags 
    probability 4602678819172646912
    begin_IR
      LIR
      nr   64  <|@ instruction [] = LABEL numbPhis: 0 align: false label: ? <|@ <|@
      nr   66  <|@ instruction CMP (x: rbx|DWORD, y: r11|DWORD) size: DWORD <|@ <|@
      nr   68  <|@ instruction BRANCH trueDestinationProbability: 1.0 condition: |>| trueDestination: B7 -> B9 falseDestination: B7 -> B25 <|@ <|@
    end_IR
  end_block
  begin_block
    name "B9"
    from_bci -1
    to_bci -1
    predecessors "B4" "B7" 
    successors "B10" "B11" 
    xhandlers
    flags 
    probability 4607182418800017408
    begin_IR
      LIR
      nr   78  <|@ instruction [] = LABEL numbPhis: 0 align: false label: ? <|@ <|@
      nr   -1  <|@ instruction rbx|DWORD = MOVE in:0|DWORD moveKind: DWORD // MoveResolver resolve mapping <|@ <|@
      nr   80  <|@ instruction TEST (x: rbx|DWORD, y: rbx|DWORD) size: DWORD <|@ <|@
      nr   82  <|@ instruction BRANCH trueDestinationProbability: 0.0 condition: < trueDestination: B9 -> B10 falseDestination: B9 -> B11 <|@ <|@
    end_IR
  end_block
  begin_block
    name "B11"
    from_bci -1
    to_bci -1
    predecessors "B9" 
    successors "B12" "B24" 
    xhandlers
    flags 
    probability 4607182418800017408
    begin_IR
      LIR
      nr   84  <|@ instruction [] = LABEL numbPhis: 0 align: false label: ? <|@ <|@
      nr   86  <|@ instruction CMP (x: rbx|DWORD, y: r10|DWORD) size: DWORD <|@ <|@
      nr   88  <|@ instruction BRANCH trueDestinationProbability: 1.0 condition: > trueDestination: B11 -> B12 falseDestination: B11 -> B24 <|@ <|@
    end_IR
  end_block
  begin_block
    name "B12"
    from_bci -1
    to_bci -1
    predecessors "B11" 
    successors "B13" "B14" 
    xhandlers
    flags 
    probability 4607182418800017408
    begin_IR
      LIR
      nr   90  <|@ instruction [] = LABEL numbPhis: 0 align: false label: ? <|@ <|@
      nr   92  <|@ instruction TEST (x: rdi|DWORD, y: rdi|DWORD) size: DWORD <|@ <|@
      nr   94  <|@ instruction BRANCH trueDestinationProbability: 0.0 condition: = trueDestination: B12 -> B13 falseDestination: B12 -> B14 <|@ <|@
    end_IR
  end_block
  begin_block
    name "B14"
    from_bci -1
    to_bci -1
    predecessors "B12" 
    successors "B15" "B23" 
    xhandlers
    flags 
    probability 4607182418800017408
    begin_IR
      LIR
      nr   96  <|@ instruction [] = LABEL numbPhis: 0 align: false label: ? <|@ <|@
      nr   98  <|@ instruction r10|DWORD = ADD (x: r9|DWORD, y: rdi|DWORD) size: DWORD <|@ <|@
      nr  100  <|@ instruction r10|DWORD = DEC r10|DWORD size: DWORD <|@ <|@
      nr  102  <|@ st <@st|@reference-map: [rsi:0, r8:0]
live-base-pointers: []
java.lang.String.lastIndexOf(String.java:1869) [bci: 0]
locals: rsi|QWORD[.] rdx|DWORD rcx|DWORD r8|QWORD[.] r9|DWORD rdi|DWORD rbx|DWORD - - - - - - - - 
>@ <|@ instruction CMP (x: r10|DWORD, y: [r8|QWORD[.] + 12]) size: DWORD state [bci:0] <|@ <|@
      nr  104  <|@ instruction BRANCH trueDestinationProbability: 1.0 condition: |<| trueDestination: B14 -> B15 falseDestination: B14 -> B23 <|@ <|@
    end_IR
  end_block
  begin_block
    name "B15"
    from_bci -1
    to_bci -1
    predecessors "B14" 
    successors "B16" 
    xhandlers
    flags 
    probability 4607182418800017408
    begin_IR
      LIR
      nr  106  <|@ instruction [] = LABEL numbPhis: 0 align: false label: ? <|@ <|@
      nr  108  <|@ instruction r9|DWORD = MOVZX [r8|QWORD[.] + r10|DWORD * 2 + 16] size: DWORD <|@ <|@
      nr  110  <|@ instruction JUMP ~[] destination: B15 -> B16 <|@ <|@
    end_IR
  end_block
  begin_block
    name "B18"
    from_bci -1
    to_bci -1
    predecessors "B16" 
    successors "B19" "B22" 
    xhandlers
    flags 
    loop_index 0
    loop_depth 1
    probability 4623735216054988003
    begin_IR
      LIR
      nr  118  <|@ instruction [] = LABEL numbPhis: 0 align: true label: ? <|@ <|@
      nr  120  <|@ instruction rcx|DWORD = MOVZX [rsi|QWORD[.] + r11|DWORD * 2 + 16] size: DWORD <|@ <|@
      nr  122  <|@ instruction rbx|DWORD = DEC r11|DWORD size: DWORD <|@ <|@
      nr  124  <|@ instruction CMP (x: rcx|DWORD, y: r9|DWORD) size: DWORD <|@ <|@
      nr  126  <|@ instruction BRANCH trueDestinationProbability: 0.059746592040655154 condition: = trueDestination: B18 -> B19 falseDestination: B18 -> B22 <|@ <|@
    end_IR
  end_block
  begin_block
    name "B22"
    from_bci -1
    to_bci -1
    predecessors "B18" 
    successors "B16" 
    xhandlers
    flags "lle" 
    loop_index 0
    loop_depth 1
    probability 4623284392289565502
    begin_IR
      LIR
      nr  128  <|@ instruction [] = LABEL numbPhis: 0 align: false label: ? <|@ <|@
      nr   -1  <|@ instruction r11|DWORD = MOVE rbx|DWORD moveKind: DWORD // MoveResolver resolve mapping <|@ <|@
      nr  130  <|@ instruction JUMP ~[] destination: B22 -> B16 <|@ <|@
    end_IR
  end_block
  begin_block
    name "B16"
    from_bci -1
    to_bci -1
    predecessors "B15" "B22" 
    successors "B17" "B18" 
    xhandlers
    flags "llh" 
    loop_index 0
    loop_depth 1
    probability 4623847342242986814
    begin_IR
      LIR
      nr  112  <|@ instruction [] = LABEL numbPhis: 1 align: false label: ? <|@ <|@
      nr  114  <|@ instruction CMP (x: rax|DWORD, y: r11|DWORD) size: DWORD <|@ <|@
      nr  116  <|@ instruction BRANCH trueDestinationProbability: 0.014642233807685692 condition: > trueDestination: B16 -> B17 falseDestination: B16 -> B18 <|@ <|@
    end_IR
  end_block
  begin_block
    name "B19"
    from_bci -1
    to_bci -1
    predecessors "B18" 
    successors "B20" "B21" 
    xhandlers
    flags 
    probability 4605388399792036439
    begin_IR
      LIR
      nr  132  <|@ instruction [] = LABEL numbPhis: 0 align: false label: ? <|@ <|@
      nr  134  <|@ instruction rcx|DWORD = DEC rdi|DWORD size: DWORD <|@ <|@
      nr  136  <|@ instruction rbp|DWORD = SUB (x: rbx|DWORD, ~y: rcx|DWORD) size: DWORD <|@ <|@
      nr  138  <|@ instruction CMP (x: rbx|DWORD, y: rbp|DWORD) size: DWORD <|@ <|@
      nr  140  <|@ instruction BRANCH trueDestinationProbability: 0.0 condition: > trueDestination: B19 -> B20 falseDestination: B19 -> B21 <|@ <|@
    end_IR
  end_block
  begin_block
    name "B21"
    from_bci -1
    to_bci -1
    predecessors "B19" 
    successors 
    xhandlers
    flags 
    probability 4605388399792036439
    begin_IR
      LIR
      nr  142  <|@ instruction [] = LABEL numbPhis: 0 align: false label: ? <|@ <|@
      nr  144  <|@ instruction rbp|DWORD = SUB (x: rbp|DWORD, ~y: rdx|DWORD) size: DWORD <|@ <|@
      nr  146  <|@ instruction rbp|DWORD = INC rbp|DWORD size: DWORD <|@ <|@
      nr  148  <|@ instruction rax|DWORD = MOVE rbp|DWORD moveKind: DWORD <|@ <|@
      nr  150  <|@ instruction RETURN (savedRbp: stack:16|QWORD, value: rax|DWORD) isStub: false thread: r15 scratchForSafepointOnReturn: rcx config: org.graalvm.compiler.hotspot.GraalHotSpotVMConfig@7222fe45 <|@ <|@
    end_IR
  end_block
  begin_block
    name "B17"
    from_bci -1
    to_bci -1
    predecessors "B16" 
    successors 
    xhandlers
    flags 
    probability 4596344096322459299
    begin_IR
      LIR
      nr  152  <|@ instruction [] = LABEL numbPhis: 0 align: false label: ? <|@ <|@
      nr  154  <|@ instruction rax|DWORD = MOVE input: int[-1|0xffffffffffffffff] <|@ <|@
      nr  156  <|@ instruction RETURN (savedRbp: stack:16|QWORD, value: rax|DWORD) isStub: false thread: r15 scratchForSafepointOnReturn: rcx config: org.graalvm.compiler.hotspot.GraalHotSpotVMConfig@7222fe45 <|@ <|@
    end_IR
  end_block
  begin_block
    name "B1"
    from_bci -1
    to_bci -1
    predecessors "B0" 
    successors "B27" 
    xhandlers
    flags 
    probability 2355382605114769408
    begin_IR
      LIR
      nr  194  <|@ instruction [] = LABEL numbPhis: 0 align: false label: ? <|@ <|@
      nr   -1  <|@ instruction rbx|DWORD = MOVE in:0|DWORD moveKind: DWORD // MoveResolver resolve mapping <|@ <|@
      nr  196  <|@ instruction r10|QWORD[.] = HOTSPOTLOADOBJECTCONSTANT input: Object[d.a@506959935] <|@ <|@
      nr   -1  <|@ instruction r11|QWORD[.] = MOVE r10|QWORD[.] moveKind: QWORD // MoveResolver resolve mapping <|@ <|@
      nr   -1  <|@ instruction r10|DWORD = MOVE input: int[-27147|0xffffffffffff95f5] // MoveResolver resolve mapping <|@ <|@
      nr  198  <|@ instruction JUMP ~[] destination: B1 -> B27 <|@ <|@
    end_IR
  end_block
  begin_block
    name "B27"
    from_bci -1
    to_bci -1
    predecessors "B1" "B3" "B10" "B26" "B13" "B24" "B23" "B25" 
    successors 
    xhandlers
    flags 
    probability 2368893403996880896
    begin_IR
      LIR
      nr  204  <|@ instruction [] = LABEL numbPhis: 2 align: false label: ? <|@ <|@
      nr  206  <|@ instruction MOV (x: [r15|QWORD + 668], y: r10|DWORD) size: DWORD <|@ <|@
      nr  208  <|@ instruction MOV (x: [r15|QWORD + 680], y: r11|QWORD[.]) size: QWORD <|@ <|@
      nr  210  <|@ st <@st|@reference-map: [rsi:0, r8:0]
live-base-pointers: []
java.lang.String.lastIndexOf(String.java:1869) [bci: 0]
locals: rsi|QWORD[.] rdx|DWORD rcx|DWORD r8|QWORD[.] r9|DWORD rdi|DWORD rbx|DWORD - - - - - - - - 
>@ <|@ instruction DEOPT info [bci:0] <|@ <|@
    end_IR
  end_block
  begin_block
    name "B24"
    from_bci -1
    to_bci -1
    predecessors "B11" 
    successors "B27" 
    xhandlers
    flags 
    probability 2355382605114769408
    begin_IR
      LIR
      nr  182  <|@ instruction [] = LABEL numbPhis: 0 align: false label: ? <|@ <|@
      nr   -1  <|@ instruction r11|QWORD[.] = MOVE input: Object[null] // MoveResolver resolve mapping <|@ <|@
      nr   -1  <|@ instruction r10|DWORD = MOVE input: int[-22291|0xffffffffffffa8ed] // MoveResolver resolve mapping <|@ <|@
      nr  184  <|@ instruction JUMP ~[] destination: B24 -> B27 <|@ <|@
    end_IR
  end_block
  begin_block
    name "B20"
    from_bci -1
    to_bci -1
    predecessors "B19" 
    successors 
    xhandlers
    flags 
    probability 2355382605114769408
    begin_IR
      LIR
      nr  168  <|@ instruction [] = LABEL numbPhis: 0 align: false label: ? <|@ <|@
      nr  170  <|@ instruction MOV [r15|QWORD + 668] y: -30483 size: DWORD <|@ <|@
      nr  172  <|@ instruction MOV (x: [r15|QWORD + 680], y: r12|ILLEGAL) size: QWORD <|@ <|@
      nr  174  <|@ st <@st|@reference-map: [rsi:0, r8:0]
live-base-pointers: []
java.lang.String.lastIndexOf(String.java:1888) [bci: 62]
locals: rsi|QWORD[.] rdx|DWORD - r8|QWORD[.] - rdi|DWORD - - r10|DWORD r9|DWORD rax|DWORD r11|DWORD - - - 
>@ <|@ instruction DEOPT info [bci:62] <|@ <|@
    end_IR
  end_block
  begin_block
    name "B23"
    from_bci -1
    to_bci -1
    predecessors "B14" 
    successors "B27" 
    xhandlers
    flags 
    probability 2355382605114769408
    begin_IR
      LIR
      nr  186  <|@ instruction [] = LABEL numbPhis: 0 align: false label: ? <|@ <|@
      nr   -1  <|@ instruction r11|QWORD[.] = MOVE input: Object[null] // MoveResolver resolve mapping <|@ <|@
      nr   -1  <|@ instruction r10|DWORD = MOVE input: int[-24603|0xffffffffffff9fe5] // MoveResolver resolve mapping <|@ <|@
      nr  188  <|@ instruction JUMP ~[] destination: B23 -> B27 <|@ <|@
    end_IR
  end_block
  begin_block
    name "B10"
    from_bci -1
    to_bci -1
    predecessors "B9" 
    successors "B27" 
    xhandlers
    flags 
    probability 2355382605114769408
    begin_IR
      LIR
      nr  190  <|@ instruction [] = LABEL numbPhis: 0 align: false label: ? <|@ <|@
      nr   -1  <|@ instruction r11|QWORD[.] = MOVE input: Object[null] // MoveResolver resolve mapping <|@ <|@
      nr   -1  <|@ instruction r10|DWORD = MOVE input: int[-22035|0xffffffffffffa9ed] // MoveResolver resolve mapping <|@ <|@
      nr  192  <|@ instruction JUMP ~[] destination: B10 -> B27 <|@ <|@
    end_IR
  end_block
  begin_block
    name "B13"
    from_bci -1
    to_bci -1
    predecessors "B12" 
    successors "B27" 
    xhandlers
    flags 
    probability 2355382605114769408
    begin_IR
      LIR
      nr  164  <|@ instruction [] = LABEL numbPhis: 0 align: false label: ? <|@ <|@
      nr   -1  <|@ instruction r11|QWORD[.] = MOVE input: Object[null] // MoveResolver resolve mapping <|@ <|@
      nr   -1  <|@ instruction r10|DWORD = MOVE input: int[-22547|0xffffffffffffa7ed] // MoveResolver resolve mapping <|@ <|@
      nr  166  <|@ instruction JUMP ~[] destination: B13 -> B27 <|@ <|@
    end_IR
  end_block
  begin_block
    name "B3"
    from_bci -1
    to_bci -1
    predecessors "B2" 
    successors "B27" 
    xhandlers
    flags 
    probability 2355382605114769408
    begin_IR
      LIR
      nr  200  <|@ instruction [] = LABEL numbPhis: 0 align: false label: ? <|@ <|@
      nr   -1  <|@ instruction r11|QWORD[.] = MOVE input: Object[null] // MoveResolver resolve mapping <|@ <|@
      nr   -1  <|@ instruction r10|DWORD = MOVE input: int[-33924|0xffffffffffff7b7c] // MoveResolver resolve mapping <|@ <|@
      nr   -1  <|@ instruction rbx|DWORD = MOVE in:0|DWORD moveKind: DWORD // MoveResolver resolve mapping <|@ <|@
      nr  202  <|@ instruction JUMP ~[] destination: B3 -> B27 <|@ <|@
    end_IR
  end_block
  begin_block
    name "B25"
    from_bci -1
    to_bci -1
    predecessors "B7" 
    successors "B27" 
    xhandlers
    flags 
    probability 2355382605114769408
    begin_IR
      LIR
      nr  158  <|@ instruction [] = LABEL numbPhis: 0 align: false label: ? <|@ <|@
      nr   -1  <|@ instruction rbx|DWORD = MOVE in:0|DWORD moveKind: DWORD // MoveResolver resolve mapping <|@ <|@
      nr  160  <|@ instruction r10|QWORD[.] = HOTSPOTLOADOBJECTCONSTANT input: Object[d.a@800922110] <|@ <|@
      nr   -1  <|@ instruction r11|QWORD[.] = MOVE r10|QWORD[.] moveKind: QWORD // MoveResolver resolve mapping <|@ <|@
      nr   -1  <|@ instruction r10|DWORD = MOVE input: int[-28443|0xffffffffffff90e5] // MoveResolver resolve mapping <|@ <|@
      nr  162  <|@ instruction JUMP ~[] destination: B25 -> B27 <|@ <|@
    end_IR
  end_block
  begin_block
    name "B26"
    from_bci -1
    to_bci -1
    predecessors "B6" 
    successors "B27" 
    xhandlers
    flags 
    probability 2355382605114769408
    begin_IR
      LIR
      nr  176  <|@ instruction [] = LABEL numbPhis: 0 align: false label: ? <|@ <|@
      nr   -1  <|@ instruction rbx|DWORD = MOVE in:0|DWORD moveKind: DWORD // MoveResolver resolve mapping <|@ <|@
      nr  178  <|@ instruction r10|QWORD[.] = HOTSPOTLOADOBJECTCONSTANT input: Object[d.a@800922110] <|@ <|@
      nr   -1  <|@ instruction r11|QWORD[.] = MOVE r10|QWORD[.] moveKind: QWORD // MoveResolver resolve mapping <|@ <|@
      nr   -1  <|@ instruction r10|DWORD = MOVE input: int[-28443|0xffffffffffff90e5] // MoveResolver resolve mapping <|@ <|@
      nr  180  <|@ instruction JUMP ~[] destination: B26 -> B27 <|@ <|@
    end_IR
  end_block
end_cfg
begin_bytecodes
     0: iload_2       
     1: iload         5
     3: isub          
     4: istore        7
     6: iload         6
     8: ifge          13
    11: iconst_m1     
    12: ireturn       
    13: iload         6
    15: iload         7
    17: if_icmple     24
    20: iload         7
    22: istore        6
    24: iload         5
    26: ifne          32
    29: iload         6
    31: ireturn       
    32: iload         4
    34: iload         5
    36: iadd          
    37: iconst_1      
    38: isub          
    39: istore        8
    41: aload_3       
    42: iload         8
    44: caload        
    45: istore        9
    47: iload_1       
    48: iload         5
    50: iadd          
    51: iconst_1      
    52: isub          
    53: istore        10
    55: iload         10
    57: iload         6
    59: iadd          
    60: istore        11
    62: iload         11
    64: iload         10
    66: if_icmplt     84
    69: aload_0       
    70: iload         11
    72: caload        
    73: iload         9
    75: if_icmpeq     84
    78: iinc          
    81: goto          62
    84: iload         11
    86: iload         10
    88: if_icmpge     93
    91: iconst_m1     
    92: ireturn       
    93: iload         11
    95: iconst_1      
    96: isub          
    97: istore        12
    99: iload         12
   101: iload         5
   103: iconst_1      
   104: isub          
   105: isub          
   106: istore        13
   108: iload         8
   110: iconst_1      
   111: isub          
   112: istore        14
   114: iload         12
   116: iload         13
   118: if_icmple     144
   121: aload_0       
   122: iload         12
   124: iinc          
   127: caload        
   128: aload_3       
   129: iload         14
   131: iinc          
   134: caload        
   135: if_icmpeq     114
   138: iinc          
   141: goto          62
   144: iload         13
   146: iload_1       
   147: isub          
   148: iconst_1      
   149: iadd          
   150: ireturn       
   <|@
end_bytecodes
begin_cfg
  name "After code generation"
end_cfg
begin_nmethod
  <<<HexCodeFile
  Platform AMD64 64  <||@
  HexCode 0 89842400c0feff4883ec1848896c24104885f60f84f90000008bc203c7ffc881f8030000800f8c72010000448bd1442bd7458bda4403d8413bc30f8f2a0000008b5e0c4963eb458bea41ffc54d63ed49ffcd492bed448beb4c3bed0f8671010000413bdb0f864c0100008b5c242085db0f8c03010000413bda0f8ebe00000085ff0f8404010000458bd14403d741ffca453b500c0f83cd000000470fb74c5010e9220000006666660f1f840000000000420fb74c5e10418bdbffcb413bc90f840d000000448bdb413bc37ee4e9290000008bcfffc98beb2be93bdd0f8f6e0000002beaffc58bc5488b6c24104883c418850500000000c5f877c3b8ffffffff488b6c24104883c418850500000000c5f877c38b5c242049baaddeaddeaddeadde4d8bda41baf595ffff4589979c0200004d899fa8020000e8000000009049bb000000000000000041baeda8ffffebda41c7879c020000ed88ffff4d89a7a8020000e8000000009049bb000000000000000041bae59fffffebb049bb000000000000000041baeda9ffffeb9e49bb000000000000000041baeda7ffffeb8c49bb000000000000000041ba7c7bffff8b5c2420e973ffffff8b5c242049baaddeaddeaddeadde4d8bda41bae590ffffe957ffffff8b5c242049baaddeaddeaddeadde4d8bda41bae590ffffe93bffffffe80000000090e80000000090  <||@
  Comment 0 [stack overflow check]  <||@
  Comment 0 3  <||@
  Comment 0 1  <||@
  Comment 11 block B0 null  <||@
  Comment 11 0 [rsi|QWORD[.], rdx|DWORD, rcx|DWORD, r8|QWORD[.], r9|DWORD, rdi|DWORD, in:0|DWORD, rbp|QWORD] = LABEL numbPhis: 0 align: false label: ?  <||@
  Comment 11 2 stack:16|QWORD = MOVE rbp|QWORD moveKind: QWORD  <||@
  Comment 16 4 [] = HOTSPOTLOCKSTACK frameMapBuilder: org.graalvm.compiler.lir.amd64.AMD64FrameMapBuilder@6dfa0585 slotKind: QWORD  <||@
  Comment 16 20 TEST (x: rsi|QWORD[.], y: rsi|QWORD[.]) size: QWORD  <||@
  Comment 19 22 BRANCH trueDestinationProbability: 0.0 condition: = trueDestination: B0 -> B1 falseDestination: B0 -> B2  <||@
  Comment 25 block B2 null  <||@
  Comment 25 24 [] = LABEL numbPhis: 0 align: false label: ?  <||@
  Comment 25 26 rax|DWORD = ADD (x: rdx|DWORD, y: rdi|DWORD) size: DWORD  <||@
  Comment 29 28 rax|DWORD = DEC rax|DWORD size: DWORD  <||@
  Comment 31 30 CMP rax|DWORD y: -2147483645 size: DWORD  <||@
  Comment 37 32 BRANCH trueDestinationProbability: 0.0 condition: < trueDestination: B2 -> B3 falseDestination: B2 -> B4  <||@
  Comment 43 block B4 null  <||@
  Comment 43 34 [] = LABEL numbPhis: 0 align: false label: ?  <||@
  Comment 43 36 r10|DWORD = SUB (x: rcx|DWORD, ~y: rdi|DWORD) size: DWORD  <||@
  Comment 49 38 r11|DWORD = ADD (x: r10|DWORD, y: rax|DWORD) size: DWORD  <||@
  Comment 55 40 CMP (x: rax|DWORD, y: r11|DWORD) size: DWORD  <||@
  Comment 58 42 BRANCH trueDestinationProbability: 0.5 condition: > trueDestination: B4 -> B9 falseDestination: B4 -> B6  <||@
  Comment 64 block B6 null  <||@
  Comment 64 44 [] = LABEL numbPhis: 0 align: false label: ?  <||@
  Comment 64 46 rbx|DWORD = MOV [rsi|QWORD[.] + 12] size: DWORD  <||@
  Comment 67 48 rbp|QWORD = MOVSXD r11|DWORD size: QWORD  <||@
  Comment 70 50 r13|DWORD = INC r10|DWORD size: DWORD  <||@
  Comment 76 52 r13|QWORD = MOVSXD r13|DWORD size: QWORD  <||@
  Comment 79 54 r13|QWORD = DEC r13|QWORD size: QWORD  <||@
  Comment 82 56 rbp|QWORD = SUB (x: rbp|QWORD, ~y: r13|QWORD) size: QWORD  <||@
  Comment 85 58 r13|QWORD = MOV rbx|DWORD size: DWORD  <||@
  Comment 88 60 CMP (x: r13|QWORD, y: rbp|QWORD) size: QWORD  <||@
  Comment 91 62 BRANCH trueDestinationProbability: 1.0 condition: |>| trueDestination: B6 -> B7 falseDestination: B6 -> B26  <||@
  Comment 97 block B7 null  <||@
  Comment 97 64 [] = LABEL numbPhis: 0 align: false label: ?  <||@
  Comment 97 66 CMP (x: rbx|DWORD, y: r11|DWORD) size: DWORD  <||@
  Comment 100 68 BRANCH trueDestinationProbability: 1.0 condition: |>| trueDestination: B7 -> B9 falseDestination: B7 -> B25  <||@
  Comment 106 block B9 null  <||@
  Comment 106 78 [] = LABEL numbPhis: 0 align: false label: ?  <||@
  Comment 106 -1 rbx|DWORD = MOVE in:0|DWORD moveKind: DWORD  <||@
  Comment 110 80 TEST (x: rbx|DWORD, y: rbx|DWORD) size: DWORD  <||@
  Comment 112 82 BRANCH trueDestinationProbability: 0.0 condition: < trueDestination: B9 -> B10 falseDestination: B9 -> B11  <||@
  Comment 118 block B11 null  <||@
  Comment 118 84 [] = LABEL numbPhis: 0 align: false label: ?  <||@
  Comment 118 86 CMP (x: rbx|DWORD, y: r10|DWORD) size: DWORD  <||@
  Comment 121 88 BRANCH trueDestinationProbability: 1.0 condition: > trueDestination: B11 -> B12 falseDestination: B11 -> B24  <||@
  Comment 127 block B12 null  <||@
  Comment 127 90 [] = LABEL numbPhis: 0 align: false label: ?  <||@
  Comment 127 92 TEST (x: rdi|DWORD, y: rdi|DWORD) size: DWORD  <||@
  Comment 129 94 BRANCH trueDestinationProbability: 0.0 condition: = trueDestination: B12 -> B13 falseDestination: B12 -> B14  <||@
  Comment 135 block B14 null  <||@
  Comment 135 96 [] = LABEL numbPhis: 0 align: false label: ?  <||@
  Comment 135 98 r10|DWORD = ADD (x: r9|DWORD, y: rdi|DWORD) size: DWORD  <||@
  Comment 141 100 r10|DWORD = DEC r10|DWORD size: DWORD  <||@
  Comment 144 102 CMP (x: r10|DWORD, y: [r8|QWORD[.] + 12]) size: DWORD state [bci:0]  <||@
  Comment 144 [rsi:0, r8:0]at java.lang.String.lastIndexOf(String.java:1869) [bci: 0, duringCall: false, rethrow: false]
              |0             |1          |2          |3            |4         |5          |6          |7  |8  |9  |10  |11  |12  |13  |14 
     locals:  |rsi|QWORD[.]  |rdx|DWORD  |rcx|DWORD  |r8|QWORD[.]  |r9|DWORD  |rdi|DWORD  |rbx|DWORD  |-  |-  |-  |-   |-   |-   |-   |-    <||@
  Comment 144 {infopoint: IMPLICIT_EXCEPTION}  <||@
  Comment 148 104 BRANCH trueDestinationProbability: 1.0 condition: |<| trueDestination: B14 -> B15 falseDestination: B14 -> B23  <||@
  Comment 154 block B15 null  <||@
  Comment 154 106 [] = LABEL numbPhis: 0 align: false label: ?  <||@
  Comment 154 108 r9|DWORD = MOVZX [r8|QWORD[.] + r10|DWORD * 2 + 16] size: DWORD  <||@
  Comment 160 110 JUMP ~[] destination: B15 -> B16  <||@
  Comment 165 block B18 loop 0 depth 1 header:27|LoopBegin  <||@
  Comment 165 118 [] = LABEL numbPhis: 0 align: true label: ?  <||@
  Comment 176 120 rcx|DWORD = MOVZX [rsi|QWORD[.] + r11|DWORD * 2 + 16] size: DWORD  <||@
  Comment 182 122 rbx|DWORD = DEC r11|DWORD size: DWORD  <||@
  Comment 187 124 CMP (x: rcx|DWORD, y: r9|DWORD) size: DWORD  <||@
  Comment 190 126 BRANCH trueDestinationProbability: 0.059746592040655154 condition: = trueDestination: B18 -> B19 falseDestination: B18 -> B22  <||@
  Comment 196 block B22 loop 0 depth 1 header:27|LoopBegin  <||@
  Comment 196 128 [] = LABEL numbPhis: 0 align: false label: ?  <||@
  Comment 196 -1 r11|DWORD = MOVE rbx|DWORD moveKind: DWORD  <||@
  Comment 199 130 JUMP ~[] destination: B22 -> B16  <||@
  Comment 199 block B16 loop 0 depth 1 header:27|LoopBegin  <||@
  Comment 199 112 [] = LABEL numbPhis: 1 align: false label: ?  <||@
  Comment 199 114 CMP (x: rax|DWORD, y: r11|DWORD) size: DWORD  <||@
  Comment 202 116 BRANCH trueDestinationProbability: 0.014642233807685692 condition: > trueDestination: B16 -> B17 falseDestination: B16 -> B18  <||@
  Comment 209 block B19 null  <||@
  Comment 209 132 [] = LABEL numbPhis: 0 align: false label: ?  <||@
  Comment 209 134 rcx|DWORD = DEC rdi|DWORD size: DWORD  <||@
  Comment 213 136 rbp|DWORD = SUB (x: rbx|DWORD, ~y: rcx|DWORD) size: DWORD  <||@
  Comment 217 138 CMP (x: rbx|DWORD, y: rbp|DWORD) size: DWORD  <||@
  Comment 219 140 BRANCH trueDestinationProbability: 0.0 condition: > trueDestination: B19 -> B20 falseDestination: B19 -> B21  <||@
  Comment 225 block B21 null  <||@
  Comment 225 142 [] = LABEL numbPhis: 0 align: false label: ?  <||@
  Comment 225 144 rbp|DWORD = SUB (x: rbp|DWORD, ~y: rdx|DWORD) size: DWORD  <||@
  Comment 227 146 rbp|DWORD = INC rbp|DWORD size: DWORD  <||@
  Comment 229 148 rax|DWORD = MOVE rbp|DWORD moveKind: DWORD  <||@
  Comment 231 150 RETURN (savedRbp: stack:16|QWORD, value: rax|DWORD) isStub: false thread: r15 scratchForSafepointOnReturn: rcx config: org.graalvm.compiler.hotspot.GraalHotSpotVMConfig@7222fe45  <||@
  Comment 240 12  <||@
  Comment 250 block B17 null  <||@
  Comment 250 152 [] = LABEL numbPhis: 0 align: false label: ?  <||@
  Comment 250 154 rax|DWORD = MOVE input: int[-1|0xffffffffffffffff]  <||@
  Comment 255 156 RETURN (savedRbp: stack:16|QWORD, value: rax|DWORD) isStub: false thread: r15 scratchForSafepointOnReturn: rcx config: org.graalvm.compiler.hotspot.GraalHotSpotVMConfig@7222fe45  <||@
  Comment 264 12  <||@
  Comment 274 block B1 null  <||@
  Comment 274 194 [] = LABEL numbPhis: 0 align: false label: ?  <||@
  Comment 274 -1 rbx|DWORD = MOVE in:0|DWORD moveKind: DWORD  <||@
  Comment 278 196 r10|QWORD[.] = HOTSPOTLOADOBJECTCONSTANT input: Object[d.a@506959935]  <||@
  Comment 278 {Object[d.a@506959935]}  <||@
  Comment 288 -1 r11|QWORD[.] = MOVE r10|QWORD[.] moveKind: QWORD  <||@
  Comment 291 -1 r10|DWORD = MOVE input: int[-27147|0xffffffffffff95f5]  <||@
  Comment 297 198 JUMP ~[] destination: B1 -> B27  <||@
  Comment 297 block B27 null  <||@
  Comment 297 204 [] = LABEL numbPhis: 2 align: false label: ?  <||@
  Comment 297 206 MOV (x: [r15|QWORD + 668], y: r10|DWORD) size: DWORD  <||@
  Comment 304 208 MOV (x: [r15|QWORD + 680], y: r11|QWORD[.]) size: QWORD  <||@
  Comment 311 210 DEOPT info [bci:0]  <||@
  Comment 311 {Field[name=CompilerToVM::Data::SharedRuntime_deopt_blob_uncommon_trap, type=address, offset=0, address=0x105aa1f90, value=0x1068075fe]:0x1068075fe}  <||@
  Comment 316 [rsi:0, r8:0]at java.lang.String.lastIndexOf(String.java:1869) [bci: 0, duringCall: false, rethrow: false]
              |0             |1          |2          |3            |4         |5          |6          |7  |8  |9  |10  |11  |12  |13  |14 
     locals:  |rsi|QWORD[.]  |rdx|DWORD  |rcx|DWORD  |r8|QWORD[.]  |r9|DWORD  |rdi|DWORD  |rbx|DWORD  |-  |-  |-  |-   |-   |-   |-   |-    <||@
  Comment 317 block B24 null  <||@
  Comment 317 182 [] = LABEL numbPhis: 0 align: false label: ?  <||@
  Comment 317 -1 r11|QWORD[.] = MOVE input: Object[null]  <||@
  Comment 327 -1 r10|DWORD = MOVE input: int[-22291|0xffffffffffffa8ed]  <||@
  Comment 333 184 JUMP ~[] destination: B24 -> B27  <||@
  Comment 335 block B20 null  <||@
  Comment 335 168 [] = LABEL numbPhis: 0 align: false label: ?  <||@
  Comment 335 170 MOV [r15|QWORD + 668] y: -30483 size: DWORD  <||@
  Comment 346 172 MOV (x: [r15|QWORD + 680], y: r12|ILLEGAL) size: QWORD  <||@
  Comment 353 174 DEOPT info [bci:62]  <||@
  Comment 353 {Field[name=CompilerToVM::Data::SharedRuntime_deopt_blob_uncommon_trap, type=address, offset=0, address=0x105aa1f90, value=0x1068075fe]:0x1068075fe}  <||@
  Comment 358 [rsi:0, r8:0]at java.lang.String.lastIndexOf(String.java:1888) [bci: 62, duringCall: false, rethrow: false]
              |0             |1          |2  |3            |4  |5          |6  |7  |8          |9         |10         |11         |12  |13  |14 
     locals:  |rsi|QWORD[.]  |rdx|DWORD  |-  |r8|QWORD[.]  |-  |rdi|DWORD  |-  |-  |r10|DWORD  |r9|DWORD  |rax|DWORD  |r11|DWORD  |-   |-   |-    <||@
  Comment 359 block B23 null  <||@
  Comment 359 186 [] = LABEL numbPhis: 0 align: false label: ?  <||@
  Comment 359 -1 r11|QWORD[.] = MOVE input: Object[null]  <||@
  Comment 369 -1 r10|DWORD = MOVE input: int[-24603|0xffffffffffff9fe5]  <||@
  Comment 375 188 JUMP ~[] destination: B23 -> B27  <||@
  Comment 377 block B10 null  <||@
  Comment 377 190 [] = LABEL numbPhis: 0 align: false label: ?  <||@
  Comment 377 -1 r11|QWORD[.] = MOVE input: Object[null]  <||@
  Comment 387 -1 r10|DWORD = MOVE input: int[-22035|0xffffffffffffa9ed]  <||@
  Comment 393 192 JUMP ~[] destination: B10 -> B27  <||@
  Comment 395 block B13 null  <||@
  Comment 395 164 [] = LABEL numbPhis: 0 align: false label: ?  <||@
  Comment 395 -1 r11|QWORD[.] = MOVE input: Object[null]  <||@
  Comment 405 -1 r10|DWORD = MOVE input: int[-22547|0xffffffffffffa7ed]  <||@
  Comment 411 166 JUMP ~[] destination: B13 -> B27  <||@
  Comment 413 block B3 null  <||@
  Comment 413 200 [] = LABEL numbPhis: 0 align: false label: ?  <||@
  Comment 413 -1 r11|QWORD[.] = MOVE input: Object[null]  <||@
  Comment 423 -1 r10|DWORD = MOVE input: int[-33924|0xffffffffffff7b7c]  <||@
  Comment 429 -1 rbx|DWORD = MOVE in:0|DWORD moveKind: DWORD  <||@
  Comment 433 202 JUMP ~[] destination: B3 -> B27  <||@
  Comment 438 block B25 null  <||@
  Comment 438 158 [] = LABEL numbPhis: 0 align: false label: ?  <||@
  Comment 438 -1 rbx|DWORD = MOVE in:0|DWORD moveKind: DWORD  <||@
  Comment 442 160 r10|QWORD[.] = HOTSPOTLOADOBJECTCONSTANT input: Object[d.a@800922110]  <||@
  Comment 442 {Object[d.a@800922110]}  <||@
  Comment 452 -1 r11|QWORD[.] = MOVE r10|QWORD[.] moveKind: QWORD  <||@
  Comment 455 -1 r10|DWORD = MOVE input: int[-28443|0xffffffffffff90e5]  <||@
  Comment 461 162 JUMP ~[] destination: B25 -> B27  <||@
  Comment 466 block B26 null  <||@
  Comment 466 176 [] = LABEL numbPhis: 0 align: false label: ?  <||@
  Comment 466 -1 rbx|DWORD = MOVE in:0|DWORD moveKind: DWORD  <||@
  Comment 470 178 r10|QWORD[.] = HOTSPOTLOADOBJECTCONSTANT input: Object[d.a@800922110]  <||@
  Comment 470 {Object[d.a@800922110]}  <||@
  Comment 480 -1 r11|QWORD[.] = MOVE r10|QWORD[.] moveKind: QWORD  <||@
  Comment 483 -1 r10|DWORD = MOVE input: int[-28443|0xffffffffffff90e5]  <||@
  Comment 489 180 JUMP ~[] destination: B26 -> B27  <||@
  Comment 494 {Stub<ExceptionHandlerStub.exceptionHandler>@0x106c4a620:CallingConvention[rax|QWORD[.], rdx|QWORD]:CallingConvention[rax|QWORD[.], rdx|QWORD]; temps=rdi|ILLEGAL,xmm0|ILLEGAL,xmm1|ILLEGAL,xmm2|ILLEGAL,xmm3|ILLEGAL,xmm4|ILLEGAL,xmm5|ILLEGAL,xmm6|ILLEGAL,xmm7|ILLEGAL,xmm8|ILLEGAL,xmm9|ILLEGAL,xmm10|ILLEGAL,xmm11|ILLEGAL,xmm12|ILLEGAL,xmm13|ILLEGAL,xmm14|ILLEGAL,xmm15|ILLEGAL,xmm16|ILLEGAL,xmm17|ILLEGAL,xmm18|ILLEGAL,xmm19|ILLEGAL,xmm20|ILLEGAL,xmm21|ILLEGAL,xmm22|ILLEGAL,xmm23|ILLEGAL,xmm24|ILLEGAL,xmm25|ILLEGAL,xmm26|ILLEGAL,xmm27|ILLEGAL,xmm28|ILLEGAL,xmm29|ILLEGAL,xmm30|ILLEGAL,xmm31|ILLEGAL,rax|ILLEGAL,rcx|ILLEGAL,rdx|ILLEGAL,rsi|ILLEGAL,r8|ILLEGAL,r9|ILLEGAL,r10|ILLEGAL,r11|ILLEGAL}  <||@
  Comment 494 4  <||@
  Comment 500 {Field[name=CompilerToVM::Data::SharedRuntime_deopt_blob_unpack, type=address, offset=0, address=0x105aa1f88, value=0x106807500]:0x106807500}  <||@
  Comment 500 5  <||@
  HexCodeFile>>> <|@
end_nmethod
begin_compilation
  name " HotSpotCompilation-8616[java.lang.String.lastIndexOf(char[], int, int, char[], int, int, int)]"
  method "HotSpotCompilation-8616[java.lang.String.lastIndexOf(char[], int, int, char[], int, int, int)]"
  date 1527005161525
end_compilation
begin_cfg
  name "After code installation"
end_cfg
begin_nmethod
  <<<HexCodeFile
  Platform AMD64 64  <||@
  HexCode 107995060 89842400c0feff4883ec1848896c24104885f60f84f90000008bc203c7ffc881f8030000800f8c72010000448bd1442bd7458bda4403d8413bc30f8f2a0000008b5e0c4963eb458bea41ffc54d63ed49ffcd492bed448beb4c3bed0f8671010000413bdb0f864c0100008b5c242085db0f8c03010000413bda0f8ebe00000085ff0f8404010000458bd14403d741ffca453b500c0f83cd000000470fb74c5010e9220000006666660f1f840000000000420fb74c5e10418bdbffcb413bc90f840d000000448bdb413bc37ee4e9290000008bcfffc98beb2be93bdd0f8f6e0000002beaffc58bc5488b6c24104883c4188505b09eeffcc5f877c3b8ffffffff488b6c24104883c4188505989eeffcc5f877c38b5c242049ba2054f390070000004d8bda41baf595ffff4589979c0200004d899fa8020000e86224e7fe9049bb000000000000000041baeda8ffffebda41c7879c020000ed88ffff4d89a7a8020000e83824e7fe9049bb000000000000000041bae59fffffebb049bb000000000000000041baeda9ffffeb9e49bb000000000000000041baeda7ffffeb8c49bb000000000000000041ba7c7bffff8b5c2420e973ffffff8b5c242049ba9055f390070000004d8bda41bae590ffffe957ffffff8b5c242049ba9055f390070000004d8bda41bae590ffffe93bffffffe8cd532bff90e8a722e7fe90f4f4f4f4f4f4  <||@
  Comment 0 [stack overflow check]  <||@
  Comment 0 3  <||@
  Comment 0 1  <||@
  Comment 11 block B0 null  <||@
  Comment 11 0 [rsi|QWORD[.], rdx|DWORD, rcx|DWORD, r8|QWORD[.], r9|DWORD, rdi|DWORD, in:0|DWORD, rbp|QWORD] = LABEL numbPhis: 0 align: false label: ?  <||@
  Comment 11 2 stack:16|QWORD = MOVE rbp|QWORD moveKind: QWORD  <||@
  Comment 16 4 [] = HOTSPOTLOCKSTACK frameMapBuilder: org.graalvm.compiler.lir.amd64.AMD64FrameMapBuilder@6dfa0585 slotKind: QWORD  <||@
  Comment 16 20 TEST (x: rsi|QWORD[.], y: rsi|QWORD[.]) size: QWORD  <||@
  Comment 19 22 BRANCH trueDestinationProbability: 0.0 condition: = trueDestination: B0 -> B1 falseDestination: B0 -> B2  <||@
  Comment 25 block B2 null  <||@
  Comment 25 24 [] = LABEL numbPhis: 0 align: false label: ?  <||@
  Comment 25 26 rax|DWORD = ADD (x: rdx|DWORD, y: rdi|DWORD) size: DWORD  <||@
  Comment 29 28 rax|DWORD = DEC rax|DWORD size: DWORD  <||@
  Comment 31 30 CMP rax|DWORD y: -2147483645 size: DWORD  <||@
  Comment 37 32 BRANCH trueDestinationProbability: 0.0 condition: < trueDestination: B2 -> B3 falseDestination: B2 -> B4  <||@
  Comment 43 block B4 null  <||@
  Comment 43 34 [] = LABEL numbPhis: 0 align: false label: ?  <||@
  Comment 43 36 r10|DWORD = SUB (x: rcx|DWORD, ~y: rdi|DWORD) size: DWORD  <||@
  Comment 49 38 r11|DWORD = ADD (x: r10|DWORD, y: rax|DWORD) size: DWORD  <||@
  Comment 55 40 CMP (x: rax|DWORD, y: r11|DWORD) size: DWORD  <||@
  Comment 58 42 BRANCH trueDestinationProbability: 0.5 condition: > trueDestination: B4 -> B9 falseDestination: B4 -> B6  <||@
  Comment 64 block B6 null  <||@
  Comment 64 44 [] = LABEL numbPhis: 0 align: false label: ?  <||@
  Comment 64 46 rbx|DWORD = MOV [rsi|QWORD[.] + 12] size: DWORD  <||@
  Comment 67 48 rbp|QWORD = MOVSXD r11|DWORD size: QWORD  <||@
  Comment 70 50 r13|DWORD = INC r10|DWORD size: DWORD  <||@
  Comment 76 52 r13|QWORD = MOVSXD r13|DWORD size: QWORD  <||@
  Comment 79 54 r13|QWORD = DEC r13|QWORD size: QWORD  <||@
  Comment 82 56 rbp|QWORD = SUB (x: rbp|QWORD, ~y: r13|QWORD) size: QWORD  <||@
  Comment 85 58 r13|QWORD = MOV rbx|DWORD size: DWORD  <||@
  Comment 88 60 CMP (x: r13|QWORD, y: rbp|QWORD) size: QWORD  <||@
  Comment 91 62 BRANCH trueDestinationProbability: 1.0 condition: |>| trueDestination: B6 -> B7 falseDestination: B6 -> B26  <||@
  Comment 97 block B7 null  <||@
  Comment 97 64 [] = LABEL numbPhis: 0 align: false label: ?  <||@
  Comment 97 66 CMP (x: rbx|DWORD, y: r11|DWORD) size: DWORD  <||@
  Comment 100 68 BRANCH trueDestinationProbability: 1.0 condition: |>| trueDestination: B7 -> B9 falseDestination: B7 -> B25  <||@
  Comment 106 block B9 null  <||@
  Comment 106 78 [] = LABEL numbPhis: 0 align: false label: ?  <||@
  Comment 106 -1 rbx|DWORD = MOVE in:0|DWORD moveKind: DWORD  <||@
  Comment 110 80 TEST (x: rbx|DWORD, y: rbx|DWORD) size: DWORD  <||@
  Comment 112 82 BRANCH trueDestinationProbability: 0.0 condition: < trueDestination: B9 -> B10 falseDestination: B9 -> B11  <||@
  Comment 118 block B11 null  <||@
  Comment 118 84 [] = LABEL numbPhis: 0 align: false label: ?  <||@
  Comment 118 86 CMP (x: rbx|DWORD, y: r10|DWORD) size: DWORD  <||@
  Comment 121 88 BRANCH trueDestinationProbability: 1.0 condition: > trueDestination: B11 -> B12 falseDestination: B11 -> B24  <||@
  Comment 127 block B12 null  <||@
  Comment 127 90 [] = LABEL numbPhis: 0 align: false label: ?  <||@
  Comment 127 92 TEST (x: rdi|DWORD, y: rdi|DWORD) size: DWORD  <||@
  Comment 129 94 BRANCH trueDestinationProbability: 0.0 condition: = trueDestination: B12 -> B13 falseDestination: B12 -> B14  <||@
  Comment 135 block B14 null  <||@
  Comment 135 96 [] = LABEL numbPhis: 0 align: false label: ?  <||@
  Comment 135 98 r10|DWORD = ADD (x: r9|DWORD, y: rdi|DWORD) size: DWORD  <||@
  Comment 141 100 r10|DWORD = DEC r10|DWORD size: DWORD  <||@
  Comment 144 102 CMP (x: r10|DWORD, y: [r8|QWORD[.] + 12]) size: DWORD state [bci:0]  <||@
  Comment 144 [rsi:0, r8:0]at java.lang.String.lastIndexOf(String.java:1869) [bci: 0, duringCall: false, rethrow: false]
              |0             |1          |2          |3            |4         |5          |6          |7  |8  |9  |10  |11  |12  |13  |14 
     locals:  |rsi|QWORD[.]  |rdx|DWORD  |rcx|DWORD  |r8|QWORD[.]  |r9|DWORD  |rdi|DWORD  |rbx|DWORD  |-  |-  |-  |-   |-   |-   |-   |-    <||@
  Comment 144 {infopoint: IMPLICIT_EXCEPTION}  <||@
  Comment 148 104 BRANCH trueDestinationProbability: 1.0 condition: |<| trueDestination: B14 -> B15 falseDestination: B14 -> B23  <||@
  Comment 154 block B15 null  <||@
  Comment 154 106 [] = LABEL numbPhis: 0 align: false label: ?  <||@
  Comment 154 108 r9|DWORD = MOVZX [r8|QWORD[.] + r10|DWORD * 2 + 16] size: DWORD  <||@
  Comment 160 110 JUMP ~[] destination: B15 -> B16  <||@
  Comment 165 block B18 loop 0 depth 1 header:27|LoopBegin  <||@
  Comment 165 118 [] = LABEL numbPhis: 0 align: true label: ?  <||@
  Comment 176 120 rcx|DWORD = MOVZX [rsi|QWORD[.] + r11|DWORD * 2 + 16] size: DWORD  <||@
  Comment 182 122 rbx|DWORD = DEC r11|DWORD size: DWORD  <||@
  Comment 187 124 CMP (x: rcx|DWORD, y: r9|DWORD) size: DWORD  <||@
  Comment 190 126 BRANCH trueDestinationProbability: 0.059746592040655154 condition: = trueDestination: B18 -> B19 falseDestination: B18 -> B22  <||@
  Comment 196 block B22 loop 0 depth 1 header:27|LoopBegin  <||@
  Comment 196 128 [] = LABEL numbPhis: 0 align: false label: ?  <||@
  Comment 196 -1 r11|DWORD = MOVE rbx|DWORD moveKind: DWORD  <||@
  Comment 199 130 JUMP ~[] destination: B22 -> B16  <||@
  Comment 199 block B16 loop 0 depth 1 header:27|LoopBegin  <||@
  Comment 199 112 [] = LABEL numbPhis: 1 align: false label: ?  <||@
  Comment 199 114 CMP (x: rax|DWORD, y: r11|DWORD) size: DWORD  <||@
  Comment 202 116 BRANCH trueDestinationProbability: 0.014642233807685692 condition: > trueDestination: B16 -> B17 falseDestination: B16 -> B18  <||@
  Comment 209 block B19 null  <||@
  Comment 209 132 [] = LABEL numbPhis: 0 align: false label: ?  <||@
  Comment 209 134 rcx|DWORD = DEC rdi|DWORD size: DWORD  <||@
  Comment 213 136 rbp|DWORD = SUB (x: rbx|DWORD, ~y: rcx|DWORD) size: DWORD  <||@
  Comment 217 138 CMP (x: rbx|DWORD, y: rbp|DWORD) size: DWORD  <||@
  Comment 219 140 BRANCH trueDestinationProbability: 0.0 condition: > trueDestination: B19 -> B20 falseDestination: B19 -> B21  <||@
  Comment 225 block B21 null  <||@
  Comment 225 142 [] = LABEL numbPhis: 0 align: false label: ?  <||@
  Comment 225 144 rbp|DWORD = SUB (x: rbp|DWORD, ~y: rdx|DWORD) size: DWORD  <||@
  Comment 227 146 rbp|DWORD = INC rbp|DWORD size: DWORD  <||@
  Comment 229 148 rax|DWORD = MOVE rbp|DWORD moveKind: DWORD  <||@
  Comment 231 150 RETURN (savedRbp: stack:16|QWORD, value: rax|DWORD) isStub: false thread: r15 scratchForSafepointOnReturn: rcx config: org.graalvm.compiler.hotspot.GraalHotSpotVMConfig@7222fe45  <||@
  Comment 240 12  <||@
  Comment 250 block B17 null  <||@
  Comment 250 152 [] = LABEL numbPhis: 0 align: false label: ?  <||@
  Comment 250 154 rax|DWORD = MOVE input: int[-1|0xffffffffffffffff]  <||@
  Comment 255 156 RETURN (savedRbp: stack:16|QWORD, value: rax|DWORD) isStub: false thread: r15 scratchForSafepointOnReturn: rcx config: org.graalvm.compiler.hotspot.GraalHotSpotVMConfig@7222fe45  <||@
  Comment 264 12  <||@
  Comment 274 block B1 null  <||@
  Comment 274 194 [] = LABEL numbPhis: 0 align: false label: ?  <||@
  Comment 274 -1 rbx|DWORD = MOVE in:0|DWORD moveKind: DWORD  <||@
  Comment 278 196 r10|QWORD[.] = HOTSPOTLOADOBJECTCONSTANT input: Object[d.a@506959935]  <||@
  Comment 278 {Object[d.a@506959935]}  <||@
  Comment 288 -1 r11|QWORD[.] = MOVE r10|QWORD[.] moveKind: QWORD  <||@
  Comment 291 -1 r10|DWORD = MOVE input: int[-27147|0xffffffffffff95f5]  <||@
  Comment 297 198 JUMP ~[] destination: B1 -> B27  <||@
  Comment 297 block B27 null  <||@
  Comment 297 204 [] = LABEL numbPhis: 2 align: false label: ?  <||@
  Comment 297 206 MOV (x: [r15|QWORD + 668], y: r10|DWORD) size: DWORD  <||@
  Comment 304 208 MOV (x: [r15|QWORD + 680], y: r11|QWORD[.]) size: QWORD  <||@
  Comment 311 210 DEOPT info [bci:0]  <||@
  Comment 311 {Field[name=CompilerToVM::Data::SharedRuntime_deopt_blob_uncommon_trap, type=address, offset=0, address=0x105aa1f90, value=0x1068075fe]:0x1068075fe}  <||@
  Comment 316 [rsi:0, r8:0]at java.lang.String.lastIndexOf(String.java:1869) [bci: 0, duringCall: false, rethrow: false]
              |0             |1          |2          |3            |4         |5          |6          |7  |8  |9  |10  |11  |12  |13  |14 
     locals:  |rsi|QWORD[.]  |rdx|DWORD  |rcx|DWORD  |r8|QWORD[.]  |r9|DWORD  |rdi|DWORD  |rbx|DWORD  |-  |-  |-  |-   |-   |-   |-   |-    <||@
  Comment 317 block B24 null  <||@
  Comment 317 182 [] = LABEL numbPhis: 0 align: false label: ?  <||@
  Comment 317 -1 r11|QWORD[.] = MOVE input: Object[null]  <||@
  Comment 327 -1 r10|DWORD = MOVE input: int[-22291|0xffffffffffffa8ed]  <||@
  Comment 333 184 JUMP ~[] destination: B24 -> B27  <||@
  Comment 335 block B20 null  <||@
  Comment 335 168 [] = LABEL numbPhis: 0 align: false label: ?  <||@
  Comment 335 170 MOV [r15|QWORD + 668] y: -30483 size: DWORD  <||@
  Comment 346 172 MOV (x: [r15|QWORD + 680], y: r12|ILLEGAL) size: QWORD  <||@
  Comment 353 174 DEOPT info [bci:62]  <||@
  Comment 353 {Field[name=CompilerToVM::Data::SharedRuntime_deopt_blob_uncommon_trap, type=address, offset=0, address=0x105aa1f90, value=0x1068075fe]:0x1068075fe}  <||@
  Comment 358 [rsi:0, r8:0]at java.lang.String.lastIndexOf(String.java:1888) [bci: 62, duringCall: false, rethrow: false]
              |0             |1          |2  |3            |4  |5          |6  |7  |8          |9         |10         |11         |12  |13  |14 
     locals:  |rsi|QWORD[.]  |rdx|DWORD  |-  |r8|QWORD[.]  |-  |rdi|DWORD  |-  |-  |r10|DWORD  |r9|DWORD  |rax|DWORD  |r11|DWORD  |-   |-   |-    <||@
  Comment 359 block B23 null  <||@
  Comment 359 186 [] = LABEL numbPhis: 0 align: false label: ?  <||@
  Comment 359 -1 r11|QWORD[.] = MOVE input: Object[null]  <||@
  Comment 369 -1 r10|DWORD = MOVE input: int[-24603|0xffffffffffff9fe5]  <||@
  Comment 375 188 JUMP ~[] destination: B23 -> B27  <||@
  Comment 377 block B10 null  <||@
  Comment 377 190 [] = LABEL numbPhis: 0 align: false label: ?  <||@
  Comment 377 -1 r11|QWORD[.] = MOVE input: Object[null]  <||@
  Comment 387 -1 r10|DWORD = MOVE input: int[-22035|0xffffffffffffa9ed]  <||@
  Comment 393 192 JUMP ~[] destination: B10 -> B27  <||@
  Comment 395 block B13 null  <||@
  Comment 395 164 [] = LABEL numbPhis: 0 align: false label: ?  <||@
  Comment 395 -1 r11|QWORD[.] = MOVE input: Object[null]  <||@
  Comment 405 -1 r10|DWORD = MOVE input: int[-22547|0xffffffffffffa7ed]  <||@
  Comment 411 166 JUMP ~[] destination: B13 -> B27  <||@
  Comment 413 block B3 null  <||@
  Comment 413 200 [] = LABEL numbPhis: 0 align: false label: ?  <||@
  Comment 413 -1 r11|QWORD[.] = MOVE input: Object[null]  <||@
  Comment 423 -1 r10|DWORD = MOVE input: int[-33924|0xffffffffffff7b7c]  <||@
  Comment 429 -1 rbx|DWORD = MOVE in:0|DWORD moveKind: DWORD  <||@
  Comment 433 202 JUMP ~[] destination: B3 -> B27  <||@
  Comment 438 block B25 null  <||@
  Comment 438 158 [] = LABEL numbPhis: 0 align: false label: ?  <||@
  Comment 438 -1 rbx|DWORD = MOVE in:0|DWORD moveKind: DWORD  <||@
  Comment 442 160 r10|QWORD[.] = HOTSPOTLOADOBJECTCONSTANT input: Object[d.a@800922110]  <||@
  Comment 442 {Object[d.a@800922110]}  <||@
  Comment 452 -1 r11|QWORD[.] = MOVE r10|QWORD[.] moveKind: QWORD  <||@
  Comment 455 -1 r10|DWORD = MOVE input: int[-28443|0xffffffffffff90e5]  <||@
  Comment 461 162 JUMP ~[] destination: B25 -> B27  <||@
  Comment 466 block B26 null  <||@
  Comment 466 176 [] = LABEL numbPhis: 0 align: false label: ?  <||@
  Comment 466 -1 rbx|DWORD = MOVE in:0|DWORD moveKind: DWORD  <||@
  Comment 470 178 r10|QWORD[.] = HOTSPOTLOADOBJECTCONSTANT input: Object[d.a@800922110]  <||@
  Comment 470 {Object[d.a@800922110]}  <||@
  Comment 480 -1 r11|QWORD[.] = MOVE r10|QWORD[.] moveKind: QWORD  <||@
  Comment 483 -1 r10|DWORD = MOVE input: int[-28443|0xffffffffffff90e5]  <||@
  Comment 489 180 JUMP ~[] destination: B26 -> B27  <||@
  Comment 494 {Stub<ExceptionHandlerStub.exceptionHandler>@0x106c4a620:CallingConvention[rax|QWORD[.], rdx|QWORD]:CallingConvention[rax|QWORD[.], rdx|QWORD]; temps=rdi|ILLEGAL,xmm0|ILLEGAL,xmm1|ILLEGAL,xmm2|ILLEGAL,xmm3|ILLEGAL,xmm4|ILLEGAL,xmm5|ILLEGAL,xmm6|ILLEGAL,xmm7|ILLEGAL,xmm8|ILLEGAL,xmm9|ILLEGAL,xmm10|ILLEGAL,xmm11|ILLEGAL,xmm12|ILLEGAL,xmm13|ILLEGAL,xmm14|ILLEGAL,xmm15|ILLEGAL,xmm16|ILLEGAL,xmm17|ILLEGAL,xmm18|ILLEGAL,xmm19|ILLEGAL,xmm20|ILLEGAL,xmm21|ILLEGAL,xmm22|ILLEGAL,xmm23|ILLEGAL,xmm24|ILLEGAL,xmm25|ILLEGAL,xmm26|ILLEGAL,xmm27|ILLEGAL,xmm28|ILLEGAL,xmm29|ILLEGAL,xmm30|ILLEGAL,xmm31|ILLEGAL,rax|ILLEGAL,rcx|ILLEGAL,rdx|ILLEGAL,rsi|ILLEGAL,r8|ILLEGAL,r9|ILLEGAL,r10|ILLEGAL,r11|ILLEGAL}  <||@
  Comment 494 4  <||@
  Comment 500 {Field[name=CompilerToVM::Data::SharedRuntime_deopt_blob_unpack, type=address, offset=0, address=0x105aa1f88, value=0x106807500]:0x106807500}  <||@
  Comment 500 5  <||@
  HexCodeFile>>> <|@
end_nmethod
