begin_compilation
  name " HotSpotCompilation-9529[java.util.SubList.<init>(AbstractList, int, int)]"
  method "HotSpotCompilation-9529[java.util.SubList.<init>(AbstractList, int, int)]"
  date 1527005205345
end_compilation
begin_cfg
  name "Final HIR schedule"
  begin_block
    name "B0"
    from_bci -1
    to_bci -1
    predecessors 
    successors "B1" "B2" 
    xhandlers
    flags 
    probability 4607182418800017408
    begin_IR
      HIR
f <@#|@fixed with next>@ <|@
tid v0 <|@
d <@d|@=== Debug Properties ===
stamp: void
=== Inputs ===
stateAfter: - 
=== Succesors ===
next: v131 
=== Usages ===
=== Predecessor ===
- >@ <|@
instruction <@StartNode|@org.graalvm.compiler.nodes.StartNode>@ stateAfter: - #next: v131  <|@  <|@
f <@~|@floating>@ <|@
tid a199 <|@
d <@d|@=== Debug Properties ===
isDefaultStable: false
rawvalue: null
stableDimension: 0
stamp: a - NULL
stampKind: a -
value: Object[null]
=== Inputs ===
=== Succesors ===
=== Usages ===
v202 v212 
=== Predecessor ===
- >@ <|@
instruction <@Constant|@org.graalvm.compiler.nodes.ConstantNode>@  <|@  <|@
f <@~|@floating>@ <|@
tid a1 <|@
d <@d|@=== Debug Properties ===
index: 0
stamp: a! Ljava/util/SubList;
uncheckedStamp: [null]
=== Inputs ===
=== Succesors ===
=== Usages ===
?5 v243 ?8 ?9 v247 v246 v248 j224 
=== Predecessor ===
- >@ <|@
instruction <@Parameter|@org.graalvm.compiler.nodes.ParameterNode>@  <|@  <|@
f <@~|@floating>@ <|@
tid a2 <|@
d <@d|@=== Debug Properties ===
index: 1
stamp: a Ljava/util/AbstractList;
uncheckedStamp: [null]
=== Inputs ===
=== Succesors ===
=== Usages ===
?5 ?8 v244 v252 a96 v249 v250 
=== Predecessor ===
- >@ <|@
instruction <@Parameter|@org.graalvm.compiler.nodes.ParameterNode>@  <|@  <|@
f <@~|@floating>@ <|@
tid i3 <|@
d <@d|@=== Debug Properties ===
index: 2
stamp: i32
uncheckedStamp: [null]
=== Inputs ===
=== Succesors ===
=== Usages ===
?5 ?8 v10 v115 v17 i23 
=== Predecessor ===
- >@ <|@
instruction <@Parameter|@org.graalvm.compiler.nodes.ParameterNode>@  <|@  <|@
f <@~|@floating>@ <|@
tid i4 <|@
d <@d|@=== Debug Properties ===
index: 3
stamp: i32
uncheckedStamp: [null]
=== Inputs ===
=== Succesors ===
=== Usages ===
?5 ?8 i23 v69 v15 v17 
=== Predecessor ===
- >@ <|@
instruction <@Parameter|@org.graalvm.compiler.nodes.ParameterNode>@  <|@  <|@
tid ?5 <|@
d <@d|@=== Debug Properties ===
bci: 0
code: ResolvedJavaMethodBytecode<SubList.<init>(AbstractList, int, int)>
duringCall: false
localsSize: 4
locksSize: 0
rethrowException: false
sourceFile: AbstractList.java
sourceLine: 618
stackSize: 0
=== Inputs ===
outerFrameState: - 
values: a1 a2 i3 i4 
=== Succesors ===
=== Usages ===
v202 v252 
=== Predecessor ===
- >@ <|@
instruction <@FrameState|@org.graalvm.compiler.nodes.FrameState>@ outerFrameState: - values: a1 a2 i3 i4  <|@  <|@
f <@~|@floating>@ <|@
tid i6 <|@
d <@d|@=== Debug Properties ===
isDefaultStable: false
nodeSourcePosition: at java.util.AbstractList.<init>(AbstractList.java:601) [bci: 5]
at java.util.SubList.<init>(AbstractList.java:618) [bci: 1]
rawvalue: 0
stableDimension: 0
stamp: i32 [0] ⇈0000000000000000
stampKind: i32
value: int[0|0x0]
=== Inputs ===
=== Succesors ===
=== Usages ===
v81 v10 
=== Predecessor ===
- >@ <|@
instruction <@Constant|@org.graalvm.compiler.nodes.ConstantNode>@  <|@  <|@
f <@~|@floating>@ <|@
tid v10 <|@
d <@d|@=== Debug Properties ===
condition: LT
nodeSourcePosition: at java.util.SubList.<init>(AbstractList.java:619) [bci: 5]
op: org.graalvm.compiler.nodes.calc.IntegerLessThanNode$LessThanOp@7cc8d043
stamp: void
unorderedIsTrue: false
=== Inputs ===
x: i3 
y: i6 
=== Succesors ===
=== Usages ===
v131 
=== Predecessor ===
- >@ <|@
instruction <@<|@org.graalvm.compiler.nodes.calc.IntegerLessThanNode>@ x: i3 y: i6  <|@  <|@
f <@*|@fixed>@ <|@
tid v131 <|@
d <@d|@=== Debug Properties ===
nodeSourcePosition: at java.util.SubList.<init>(AbstractList.java:619) [bci: 5]
stamp: void
trueSuccessorProbability: 0.0
=== Inputs ===
condition: v10 
=== Succesors ===
trueSuccessor: v130 
falseSuccessor: v128 
=== Usages ===
=== Predecessor ===
v0 >@ <|@
instruction <@If|@org.graalvm.compiler.nodes.IfNode>@ condition: v10 #trueSuccessor: v130 #falseSuccessor: v128  <|@  <|@
    end_IR
  end_block
  begin_block
    name "B1"
    from_bci -1
    to_bci -1
    predecessors "B0" 
    successors "B4" 
    xhandlers
    flags 
    probability 2355382605114769408
    begin_IR
      HIR
f <@#|@fixed with next>@ <|@
tid v130 <|@
d <@d|@=== Debug Properties ===
nodeSourcePosition: at java.util.SubList.<init>(AbstractList.java:619) [bci: 5]
stamp: void
=== Inputs ===
=== Succesors ===
next: v197 
=== Usages ===
=== Predecessor ===
v131 >@ <|@
instruction <@Begin|@org.graalvm.compiler.nodes.BeginNode>@ #next: v197  <|@  <|@
f <@~|@floating>@ <|@
tid i198 <|@
d <@d|@=== Debug Properties ===
isDefaultStable: false
rawvalue: -21011
stableDimension: 0
stamp: i32 [-21011] ⇊00000000ffffaded ⇈00000000ffffaded
stampKind: i32
value: int[-21011|0xffffffffffffaded]
=== Inputs ===
=== Succesors ===
=== Usages ===
i200 
=== Predecessor ===
- >@ <|@
instruction <@Constant|@org.graalvm.compiler.nodes.ConstantNode>@  <|@  <|@
f <@*|@fixed>@ <|@
tid v197 <|@
d <@d|@=== Debug Properties ===
stamp: void
=== Inputs ===
=== Succesors ===
=== Usages ===
v196 
=== Predecessor ===
v130 >@ <|@
instruction <@EndNode|@org.graalvm.compiler.nodes.EndNode>@  <|@  <|@
    end_IR
  end_block
  begin_block
    name "B2"
    from_bci -1
    to_bci -1
    predecessors "B0" 
    successors "B3" "B5" 
    xhandlers
    flags 
    probability 4607182418800017408
    begin_IR
      HIR
f <@#|@fixed with next>@ <|@
tid v128 <|@
d <@d|@=== Debug Properties ===
nodeSourcePosition: at java.util.SubList.<init>(AbstractList.java:619) [bci: 5]
stamp: void
=== Inputs ===
=== Succesors ===
next: v252 
=== Usages ===
=== Predecessor ===
v131 >@ <|@
instruction <@Begin|@org.graalvm.compiler.nodes.BeginNode>@ #next: v252  <|@  <|@
f <@#|@fixed with next>@ <|@
tid v252 <|@
d <@d|@=== Debug Properties ===
stamp: void
=== Inputs ===
stateBefore: ?5 
object: a2 
=== Succesors ===
next: v139 
=== Usages ===
=== Predecessor ===
v128 >@ <|@
instruction <@NullCheck|@org.graalvm.compiler.nodes.extended.NullCheckNode>@ stateBefore: ?5 object: a2 #next: v139  <|@  <|@
f <@~|@floating>@ <|@
tid v17 <|@
d <@d|@=== Debug Properties ===
condition: LT
nodeSourcePosition: at java.util.SubList.<init>(AbstractList.java:623) [bci: 72]
op: org.graalvm.compiler.nodes.calc.IntegerLessThanNode$LessThanOp@7cc8d043
stamp: void
unorderedIsTrue: false
=== Inputs ===
x: i4 
y: i3 
=== Succesors ===
=== Usages ===
v139 
=== Predecessor ===
- >@ <|@
instruction <@<|@org.graalvm.compiler.nodes.calc.IntegerLessThanNode>@ x: i4 y: i3  <|@  <|@
f <@*|@fixed>@ <|@
tid v139 <|@
d <@d|@=== Debug Properties ===
nodeSourcePosition: at java.util.SubList.<init>(AbstractList.java:623) [bci: 72]
stamp: void
trueSuccessorProbability: 0.0
=== Inputs ===
condition: v17 
=== Succesors ===
trueSuccessor: v138 
falseSuccessor: v136 
=== Usages ===
=== Predecessor ===
v252 >@ <|@
instruction <@If|@org.graalvm.compiler.nodes.IfNode>@ condition: v17 #trueSuccessor: v138 #falseSuccessor: v136  <|@  <|@
    end_IR
  end_block
  begin_block
    name "B3"
    from_bci -1
    to_bci -1
    predecessors "B2" 
    successors "B4" 
    xhandlers
    flags 
    probability 2355382605114769408
    begin_IR
      HIR
f <@#|@fixed with next>@ <|@
tid v138 <|@
d <@d|@=== Debug Properties ===
nodeSourcePosition: at java.util.SubList.<init>(AbstractList.java:623) [bci: 72]
stamp: void
=== Inputs ===
=== Succesors ===
next: v205 
=== Usages ===
=== Predecessor ===
v139 >@ <|@
instruction <@Begin|@org.graalvm.compiler.nodes.BeginNode>@ #next: v205  <|@  <|@
f <@~|@floating>@ <|@
tid i206 <|@
d <@d|@=== Debug Properties ===
isDefaultStable: false
rawvalue: -32531
stableDimension: 0
stamp: i32 [-32531] ⇊00000000ffff80ed ⇈00000000ffff80ed
stampKind: i32
value: int[-32531|0xffffffffffff80ed]
=== Inputs ===
=== Succesors ===
=== Usages ===
i200 
=== Predecessor ===
- >@ <|@
instruction <@Constant|@org.graalvm.compiler.nodes.ConstantNode>@  <|@  <|@
f <@*|@fixed>@ <|@
tid v205 <|@
d <@d|@=== Debug Properties ===
stamp: void
=== Inputs ===
=== Succesors ===
=== Usages ===
v196 
=== Predecessor ===
v138 >@ <|@
instruction <@EndNode|@org.graalvm.compiler.nodes.EndNode>@  <|@  <|@
    end_IR
  end_block
  begin_block
    name "B4"
    from_bci -1
    to_bci -1
    predecessors "B1" "B3" 
    successors 
    xhandlers
    flags 
    probability 2359886204742139904
    begin_IR
      HIR
f <@~|@floating>@ <|@
tid i200 <|@
d <@d|@=== Debug Properties ===
stamp: i32 [-32531 - -21011] ⇊00000000ffff80e5 ⇈00000000ffffadfd
valueDescription: i32
=== Inputs ===
merge: v196 
values: i198 i206 
=== Succesors ===
=== Usages ===
v202 
=== Predecessor ===
- >@ <|@
instruction <@ValuePhi|@org.graalvm.compiler.nodes.ValuePhiNode>@ merge: v196 values: i198 i206  <|@  <|@
f <@#|@fixed with next>@ <|@
tid v196 <|@
d <@d|@=== Debug Properties ===
stamp: void
=== Inputs ===
stateAfter: - 
ends: v197 v205 
=== Succesors ===
next: v202 
=== Usages ===
i200 
=== Predecessor ===
- >@ <|@
instruction <@Merge|@org.graalvm.compiler.nodes.MergeNode>@ stateAfter: - ends: v197 v205 #next: v202  <|@  <|@
f <@*|@fixed>@ <|@
tid v202 <|@
d <@d|@=== Debug Properties ===
stamp: void
=== Inputs ===
stateBefore: ?5 
actionAndReason: i200 
speculation: a199 
=== Succesors ===
=== Usages ===
=== Predecessor ===
v196 >@ <|@
instruction <@DynamicDeoptimize|@org.graalvm.compiler.nodes.DynamicDeoptimizeNode>@ stateBefore: ?5 actionAndReason: i200 speculation: a199  <|@  <|@
    end_IR
  end_block
  begin_block
    name "B5"
    from_bci -1
    to_bci -1
    predecessors "B2" 
    successors "B6" "B9" 
    xhandlers
    flags 
    probability 4607182418800017408
    begin_IR
      HIR
f <@#|@fixed with next>@ <|@
tid v136 <|@
d <@d|@=== Debug Properties ===
nodeSourcePosition: at java.util.SubList.<init>(AbstractList.java:623) [bci: 72]
stamp: void
=== Inputs ===
=== Succesors ===
next: v81 
=== Usages ===
=== Predecessor ===
v139 >@ <|@
instruction <@Begin|@org.graalvm.compiler.nodes.BeginNode>@ #next: v81  <|@  <|@
f <@~|@floating>@ <|@
tid v243 <|@
d <@d|@=== Debug Properties ===
displacement: 12
scale: Times1
stamp: void*
=== Inputs ===
base: a1 
index: - 
=== Succesors ===
=== Usages ===
v81 v118 
=== Predecessor ===
- >@ <|@
instruction <@AMD64Address|@org.graalvm.compiler.core.amd64.AMD64AddressNode>@ base: a1 index: -  <|@  <|@
f <@#|@fixed with next>@ <|@
tid v81 <|@
d <@d|@=== Debug Properties ===
barrierType: NONE
location: AbstractList.modCount
nodeSourcePosition: at java.util.AbstractList.<init>(AbstractList.java:601) [bci: 6]
at java.util.SubList.<init>(AbstractList.java:618) [bci: 1]
nullCheck: false
stamp: void
=== Inputs ===
stateBefore: - 
guard: - 
address: v243 
value: i6 
stateAfter: - 
lastLocationAccess: - 
=== Succesors ===
next: v238 
=== Usages ===
=== Predecessor ===
v136 >@ <|@
instruction <@Write|@org.graalvm.compiler.nodes.memory.WriteNode>@ stateBefore: - guard: - address: v243 value: i6 stateAfter: - lastLocationAccess: - #next: v238  <|@  <|@
f <@~|@floating>@ <|@
tid v250 <|@
d <@d|@=== Debug Properties ===
displacement: 8
scale: Times1
stamp: void*
=== Inputs ===
base: a2 
index: - 
=== Succesors ===
=== Usages ===
v238 
=== Predecessor ===
- >@ <|@
instruction <@AMD64Address|@org.graalvm.compiler.core.amd64.AMD64AddressNode>@ base: a2 index: -  <|@  <|@
f <@#|@fixed with next>@ <|@
tid v238 <|@
d <@d|@=== Debug Properties ===
barrierType: NONE
forceFixed: false
location: CompressedHub:final
nodeSourcePosition: at org.graalvm.compiler.hotspot.replacements.HotSpotReplacementsUtil.loadHubIntrinsic(Object) [bci: -1]
at org.graalvm.compiler.hotspot.replacements.InstanceOfSnippets.instanceofExact(InstanceOfSnippets.java:142) [bci: 39]
at java.util.SubList.<init>(AbstractList.java:621) [bci: 37]
nullCheck: false
stamp: Klass*!(compressed base: 0 shift: 3)
=== Inputs ===
stateBefore: - 
guard: - 
address: v250 
=== Succesors ===
next: v46 
=== Usages ===
v237 v235 
=== Predecessor ===
v81 >@ <|@
instruction <@Read|@org.graalvm.compiler.nodes.memory.ReadNode>@ stateBefore: - guard: - address: v250 #next: v46  <|@  <|@
f <@~|@floating>@ <|@
tid v234 <|@
d <@d|@=== Debug Properties ===
isDefaultStable: false
nodeSourcePosition: at org.graalvm.compiler.hotspot.replacements.InstanceOfSnippets.instanceofExact(InstanceOfSnippets.java:143) [bci: 50]
at java.util.SubList.<init>(AbstractList.java:621) [bci: 37]
rawvalue: meta{HotSpotType<Ljava/util/Arrays$ArrayList;, resolved>;compressed}
stableDimension: 0
stamp: Klass*!(compressed base: 0 shift: 3)
stampKind: Klass*(compressed base: 0 shift: 3)
value: meta{HotSpotType<Ljava/util/Arrays$ArrayList;, resolved>;compressed}
=== Inputs ===
=== Succesors ===
=== Usages ===
v235 
=== Predecessor ===
- >@ <|@
instruction <@Constant|@org.graalvm.compiler.nodes.ConstantNode>@  <|@  <|@
f <@~|@floating>@ <|@
tid v235 <|@
d <@d|@=== Debug Properties ===
condition: EQ
nodeSourcePosition: at org.graalvm.compiler.hotspot.replacements.InstanceOfSnippets.instanceofExact(InstanceOfSnippets.java:143) [bci: 50]
at java.util.SubList.<init>(AbstractList.java:621) [bci: 37]
stamp: void
unorderedIsTrue: false
=== Inputs ===
x: v238 
y: v234 
=== Succesors ===
=== Usages ===
v46 
=== Predecessor ===
- >@ <|@
instruction <@==|@org.graalvm.compiler.nodes.calc.PointerEqualsNode>@ x: v238 y: v234  <|@  <|@
tid ?8 <|@
d <@d|@=== Debug Properties ===
bci: 1
code: ResolvedJavaMethodBytecode<SubList.<init>(AbstractList, int, int)>
duringCall: true
localsSize: 4
locksSize: 0
nodeSourcePosition: at java.util.AbstractList.<init>(AbstractList.java:601) [bci: 6]
at java.util.SubList.<init>(AbstractList.java:618) [bci: 1]
rethrowException: false
sourceFile: AbstractList.java
sourceLine: 618
stackSize: 0
=== Inputs ===
outerFrameState: - 
values: a1 a2 i3 i4 
=== Succesors ===
=== Usages ===
?9 
=== Predecessor ===
- >@ <|@
instruction <@FrameState|@org.graalvm.compiler.nodes.FrameState>@ outerFrameState: - values: a1 a2 i3 i4  <|@  <|@
tid ?9 <|@
d <@d|@=== Debug Properties ===
bci: 9
code: ResolvedJavaMethodBytecode<AbstractList.<init>()>
duringCall: false
localsSize: 1
locksSize: 0
nodeSourcePosition: at java.util.AbstractList.<init>(AbstractList.java:601) [bci: 6]
at java.util.SubList.<init>(AbstractList.java:618) [bci: 1]
rethrowException: false
sourceFile: AbstractList.java
sourceLine: 77
stackSize: 0
=== Inputs ===
outerFrameState: ?8 
values: a1 
=== Succesors ===
=== Usages ===
v212 i240 
=== Predecessor ===
- >@ <|@
instruction <@FrameState|@org.graalvm.compiler.nodes.FrameState>@ outerFrameState: ?8 values: a1  <|@  <|@
f <@~|@floating>@ <|@
tid v244 <|@
d <@d|@=== Debug Properties ===
displacement: 16
scale: Times1
stamp: void*
=== Inputs ===
base: a2 
index: - 
=== Succesors ===
=== Usages ===
a239 i241 
=== Predecessor ===
- >@ <|@
instruction <@AMD64Address|@org.graalvm.compiler.core.amd64.AMD64AddressNode>@ base: a2 index: -  <|@  <|@
f <@*|@fixed>@ <|@
tid v46 <|@
d <@d|@=== Debug Properties ===
nodeSourcePosition: dispatchedType=Ljava/util/Arrays$ArrayList; target_method=size target_method_class=Ljava/util/Arrays$ArrayList; position=at java.util.SubList.<init>(AbstractList.java:621) [bci: 37]
stamp: void
trueSuccessorProbability: 0.7936731773025761
=== Inputs ===
condition: v235 
=== Succesors ===
trueSuccessor: v39 
falseSuccessor: v45 
=== Usages ===
=== Predecessor ===
v238 >@ <|@
instruction <@If|@org.graalvm.compiler.nodes.IfNode>@ condition: v235 #trueSuccessor: v39 #falseSuccessor: v45  <|@  <|@
    end_IR
  end_block
  begin_block
    name "B6"
    from_bci -1
    to_bci -1
    predecessors "B5" 
    successors "B7" "B8" 
    xhandlers
    flags 
    probability 4605323991996384095
    begin_IR
      HIR
f <@#|@fixed with next>@ <|@
tid v39 <|@
d <@d|@=== Debug Properties ===
nodeSourcePosition: dispatchedType=Ljava/util/Arrays$ArrayList; target_method=size target_method_class=Ljava/util/Arrays$ArrayList; position=at java.util.SubList.<init>(AbstractList.java:621) [bci: 37]
stamp: void
=== Inputs ===
=== Succesors ===
next: a239 
=== Usages ===
=== Predecessor ===
v46 >@ <|@
instruction <@Begin|@org.graalvm.compiler.nodes.BeginNode>@ #next: a239  <|@  <|@
f <@#|@fixed with next>@ <|@
tid a239 <|@
d <@d|@=== Debug Properties ===
barrierType: NONE
forceFixed: false
location: Arrays$ArrayList.a
nodeSourcePosition: at java.util.Arrays$ArrayList.size(Arrays.java:3818) [bci: 1]
at java.util.SubList.<init>(AbstractList.java:621) [bci: 37]
nullCheck: false
stamp: n [Ljava/lang/Object;
=== Inputs ===
stateBefore: - 
guard: - 
address: v244 
=== Succesors ===
next: i240 
=== Usages ===
v245 
=== Predecessor ===
v39 >@ <|@
instruction <@Read|@org.graalvm.compiler.nodes.memory.ReadNode>@ stateBefore: - guard: - address: v244 #next: i240  <|@  <|@
f <@~|@floating>@ <|@
tid v245 <|@
d <@d|@=== Debug Properties ===
displacement: 12
scale: Times8
stamp: void*
=== Inputs ===
base: - 
index: a239 
=== Succesors ===
=== Usages ===
i240 
=== Predecessor ===
- >@ <|@
instruction <@AMD64Address|@org.graalvm.compiler.core.amd64.AMD64AddressNode>@ base: - index: a239  <|@  <|@
f <@#|@fixed with next>@ <|@
tid i240 <|@
d <@d|@=== Debug Properties ===
barrierType: NONE
forceFixed: false
location: [].length:final
nodeSourcePosition: at java.util.Arrays$ArrayList.size(Arrays.java:3818) [bci: 4]
at java.util.SubList.<init>(AbstractList.java:621) [bci: 37]
nullCheck: true
stamp: i32 [0 - 2147483647] ⇈000000007fffffff
=== Inputs ===
stateBefore: ?9 
guard: - 
address: v245 
=== Succesors ===
next: v147 
=== Usages ===
v69 
=== Predecessor ===
a239 >@ <|@
instruction <@Read|@org.graalvm.compiler.nodes.memory.ReadNode>@ stateBefore: ?9 guard: - address: v245 #next: v147  <|@  <|@
f <@~|@floating>@ <|@
tid v69 <|@
d <@d|@=== Debug Properties ===
condition: LT
nodeSourcePosition: at java.util.SubList.<init>(AbstractList.java:621) [bci: 40]
op: org.graalvm.compiler.nodes.calc.IntegerLessThanNode$LessThanOp@7cc8d043
stamp: void
unorderedIsTrue: false
=== Inputs ===
x: i240 
y: i4 
=== Succesors ===
=== Usages ===
v147 
=== Predecessor ===
- >@ <|@
instruction <@<|@org.graalvm.compiler.nodes.calc.IntegerLessThanNode>@ x: i240 y: i4  <|@  <|@
f <@*|@fixed>@ <|@
tid v147 <|@
d <@d|@=== Debug Properties ===
nodeSourcePosition: at java.util.SubList.<init>(AbstractList.java:621) [bci: 40]
stamp: void
trueSuccessorProbability: 0.0
=== Inputs ===
condition: v69 
=== Succesors ===
trueSuccessor: v146 
falseSuccessor: v144 
=== Usages ===
=== Predecessor ===
i240 >@ <|@
instruction <@If|@org.graalvm.compiler.nodes.IfNode>@ condition: v69 #trueSuccessor: v146 #falseSuccessor: v144  <|@  <|@
    end_IR
  end_block
  begin_block
    name "B7"
    from_bci -1
    to_bci -1
    predecessors "B6" 
    successors "B15" 
    xhandlers
    flags 
    probability 2355382605114769408
    begin_IR
      HIR
f <@#|@fixed with next>@ <|@
tid v146 <|@
d <@d|@=== Debug Properties ===
nodeSourcePosition: at java.util.SubList.<init>(AbstractList.java:621) [bci: 40]
stamp: void
=== Inputs ===
=== Succesors ===
next: v215 
=== Usages ===
=== Predecessor ===
v147 >@ <|@
instruction <@Begin|@org.graalvm.compiler.nodes.BeginNode>@ #next: v215  <|@  <|@
f <@~|@floating>@ <|@
tid i216 <|@
d <@d|@=== Debug Properties ===
isDefaultStable: false
rawvalue: -24083
stableDimension: 0
stamp: i32 [-24083] ⇊00000000ffffa1ed ⇈00000000ffffa1ed
stampKind: i32
value: int[-24083|0xffffffffffffa1ed]
=== Inputs ===
=== Succesors ===
=== Usages ===
i210 
=== Predecessor ===
- >@ <|@
instruction <@Constant|@org.graalvm.compiler.nodes.ConstantNode>@  <|@  <|@
f <@*|@fixed>@ <|@
tid v215 <|@
d <@d|@=== Debug Properties ===
stamp: void
=== Inputs ===
=== Succesors ===
=== Usages ===
v207 
=== Predecessor ===
v146 >@ <|@
instruction <@EndNode|@org.graalvm.compiler.nodes.EndNode>@  <|@  <|@
    end_IR
  end_block
  begin_block
    name "B8"
    from_bci -1
    to_bci -1
    predecessors "B6" 
    successors "B13" 
    xhandlers
    flags 
    probability 4605323991996384095
    begin_IR
      HIR
f <@#|@fixed with next>@ <|@
tid v144 <|@
d <@d|@=== Debug Properties ===
nodeSourcePosition: at java.util.SubList.<init>(AbstractList.java:621) [bci: 40]
stamp: void
=== Inputs ===
=== Succesors ===
next: v67 
=== Usages ===
=== Predecessor ===
v147 >@ <|@
instruction <@Begin|@org.graalvm.compiler.nodes.BeginNode>@ #next: v67  <|@  <|@
f <@*|@fixed>@ <|@
tid v67 <|@
d <@d|@=== Debug Properties ===
stamp: void
=== Inputs ===
=== Succesors ===
=== Usages ===
v65 
=== Predecessor ===
v144 >@ <|@
instruction <@EndNode|@org.graalvm.compiler.nodes.EndNode>@  <|@  <|@
    end_IR
  end_block
  begin_block
    name "B9"
    from_bci -1
    to_bci -1
    predecessors "B5" 
    successors "B10" "B14" 
    xhandlers
    flags 
    probability 4596601727505068676
    begin_IR
      HIR
f <@#|@fixed with next>@ <|@
tid v45 <|@
d <@d|@=== Debug Properties ===
nodeSourcePosition: at java.util.SubList.<init>(AbstractList.java:621) [bci: 37]
stamp: void
=== Inputs ===
=== Succesors ===
next: v151 
=== Usages ===
=== Predecessor ===
v46 >@ <|@
instruction <@Begin|@org.graalvm.compiler.nodes.BeginNode>@ #next: v151  <|@  <|@
f <@~|@floating>@ <|@
tid v236 <|@
d <@d|@=== Debug Properties ===
isDefaultStable: false
nodeSourcePosition: at org.graalvm.compiler.hotspot.replacements.InstanceOfSnippets.instanceofExact(InstanceOfSnippets.java:143) [bci: 50]
at java.util.SubList.<init>(AbstractList.java:621) [bci: 37]
rawvalue: meta{HotSpotType<Lorg/graalvm/compiler/graph/NodeInputList;, resolved>;compressed}
stableDimension: 0
stamp: Klass*!(compressed base: 0 shift: 3)
stampKind: Klass*(compressed base: 0 shift: 3)
value: meta{HotSpotType<Lorg/graalvm/compiler/graph/NodeInputList;, resolved>;compressed}
=== Inputs ===
=== Succesors ===
=== Usages ===
v237 
=== Predecessor ===
- >@ <|@
instruction <@Constant|@org.graalvm.compiler.nodes.ConstantNode>@  <|@  <|@
f <@~|@floating>@ <|@
tid v237 <|@
d <@d|@=== Debug Properties ===
condition: EQ
nodeSourcePosition: at org.graalvm.compiler.hotspot.replacements.InstanceOfSnippets.instanceofExact(InstanceOfSnippets.java:143) [bci: 50]
at java.util.SubList.<init>(AbstractList.java:621) [bci: 37]
stamp: void
unorderedIsTrue: false
=== Inputs ===
x: v238 
y: v236 
=== Succesors ===
=== Usages ===
v151 
=== Predecessor ===
- >@ <|@
instruction <@==|@org.graalvm.compiler.nodes.calc.PointerEqualsNode>@ x: v238 y: v236  <|@  <|@
f <@*|@fixed>@ <|@
tid v151 <|@
d <@d|@=== Debug Properties ===
nodeSourcePosition: dispatchedType=Lorg/graalvm/compiler/graph/NodeInputList; target_method=size target_method_class=Lorg/graalvm/compiler/graph/NodeList; position=at java.util.SubList.<init>(AbstractList.java:621) [bci: 37]
stamp: void
trueSuccessorProbability: 1.0
=== Inputs ===
condition: v237 
=== Succesors ===
trueSuccessor: v148 
falseSuccessor: v150 
=== Usages ===
=== Predecessor ===
v45 >@ <|@
instruction <@If|@org.graalvm.compiler.nodes.IfNode>@ condition: v237 #trueSuccessor: v148 #falseSuccessor: v150  <|@  <|@
    end_IR
  end_block
  begin_block
    name "B10"
    from_bci -1
    to_bci -1
    predecessors "B9" 
    successors "B11" "B12" 
    xhandlers
    flags 
    probability 4596601727505068676
    begin_IR
      HIR
f <@#|@fixed with next>@ <|@
tid v148 <|@
d <@d|@=== Debug Properties ===
nodeSourcePosition: dispatchedType=Lorg/graalvm/compiler/graph/NodeInputList; target_method=size target_method_class=Lorg/graalvm/compiler/graph/NodeList; position=at java.util.SubList.<init>(AbstractList.java:621) [bci: 37]
stamp: void
=== Inputs ===
=== Succesors ===
next: i241 
=== Usages ===
=== Predecessor ===
v151 >@ <|@
instruction <@Begin|@org.graalvm.compiler.nodes.BeginNode>@ #next: i241  <|@  <|@
f <@#|@fixed with next>@ <|@
tid i241 <|@
d <@d|@=== Debug Properties ===
barrierType: NONE
forceFixed: false
location: NodeList.size
nodeSourcePosition: at org.graalvm.compiler.graph.NodeList.size(NodeList.java:119) [bci: 1]
at java.util.SubList.<init>(AbstractList.java:621) [bci: 37]
nullCheck: false
stamp: i32
=== Inputs ===
stateBefore: - 
guard: - 
address: v244 
=== Succesors ===
next: v155 
=== Usages ===
v15 
=== Predecessor ===
v148 >@ <|@
instruction <@Read|@org.graalvm.compiler.nodes.memory.ReadNode>@ stateBefore: - guard: - address: v244 #next: v155  <|@  <|@
f <@~|@floating>@ <|@
tid v15 <|@
d <@d|@=== Debug Properties ===
condition: LT
nodeSourcePosition: at java.util.SubList.<init>(AbstractList.java:621) [bci: 40]
op: org.graalvm.compiler.nodes.calc.IntegerLessThanNode$LessThanOp@7cc8d043
stamp: void
unorderedIsTrue: false
=== Inputs ===
x: i241 
y: i4 
=== Succesors ===
=== Usages ===
v155 
=== Predecessor ===
- >@ <|@
instruction <@<|@org.graalvm.compiler.nodes.calc.IntegerLessThanNode>@ x: i241 y: i4  <|@  <|@
f <@*|@fixed>@ <|@
tid v155 <|@
d <@d|@=== Debug Properties ===
nodeSourcePosition: at java.util.SubList.<init>(AbstractList.java:621) [bci: 40]
stamp: void
trueSuccessorProbability: 0.0
=== Inputs ===
condition: v15 
=== Succesors ===
trueSuccessor: v154 
falseSuccessor: v152 
=== Usages ===
=== Predecessor ===
i241 >@ <|@
instruction <@If|@org.graalvm.compiler.nodes.IfNode>@ condition: v15 #trueSuccessor: v154 #falseSuccessor: v152  <|@  <|@
    end_IR
  end_block
  begin_block
    name "B11"
    from_bci -1
    to_bci -1
    predecessors "B10" 
    successors "B15" 
    xhandlers
    flags 
    probability 2355382605114769408
    begin_IR
      HIR
f <@#|@fixed with next>@ <|@
tid v154 <|@
d <@d|@=== Debug Properties ===
nodeSourcePosition: at java.util.SubList.<init>(AbstractList.java:621) [bci: 40]
stamp: void
=== Inputs ===
=== Succesors ===
next: v213 
=== Usages ===
=== Predecessor ===
v155 >@ <|@
instruction <@Begin|@org.graalvm.compiler.nodes.BeginNode>@ #next: v213  <|@  <|@
f <@~|@floating>@ <|@
tid i214 <|@
d <@d|@=== Debug Properties ===
isDefaultStable: false
rawvalue: -28691
stableDimension: 0
stamp: i32 [-28691] ⇊00000000ffff8fed ⇈00000000ffff8fed
stampKind: i32
value: int[-28691|0xffffffffffff8fed]
=== Inputs ===
=== Succesors ===
=== Usages ===
i210 
=== Predecessor ===
- >@ <|@
instruction <@Constant|@org.graalvm.compiler.nodes.ConstantNode>@  <|@  <|@
f <@*|@fixed>@ <|@
tid v213 <|@
d <@d|@=== Debug Properties ===
stamp: void
=== Inputs ===
=== Succesors ===
=== Usages ===
v207 
=== Predecessor ===
v154 >@ <|@
instruction <@EndNode|@org.graalvm.compiler.nodes.EndNode>@  <|@  <|@
    end_IR
  end_block
  begin_block
    name "B12"
    from_bci -1
    to_bci -1
    predecessors "B10" 
    successors "B13" 
    xhandlers
    flags 
    probability 4596601727505068676
    begin_IR
      HIR
f <@#|@fixed with next>@ <|@
tid v152 <|@
d <@d|@=== Debug Properties ===
nodeSourcePosition: at java.util.SubList.<init>(AbstractList.java:621) [bci: 40]
stamp: void
=== Inputs ===
=== Succesors ===
next: v64 
=== Usages ===
=== Predecessor ===
v155 >@ <|@
instruction <@Begin|@org.graalvm.compiler.nodes.BeginNode>@ #next: v64  <|@  <|@
f <@*|@fixed>@ <|@
tid v64 <|@
d <@d|@=== Debug Properties ===
stamp: void
=== Inputs ===
=== Succesors ===
=== Usages ===
v65 
=== Predecessor ===
v152 >@ <|@
instruction <@EndNode|@org.graalvm.compiler.nodes.EndNode>@  <|@  <|@
    end_IR
  end_block
  begin_block
    name "B13"
    from_bci -1
    to_bci -1
    predecessors "B12" "B8" 
    successors 
    xhandlers
    flags 
    probability 4607182418800017408
    begin_IR
      HIR
f <@#|@fixed with next>@ <|@
tid v65 <|@
d <@d|@=== Debug Properties ===
stamp: void
=== Inputs ===
stateAfter: - 
ends: v64 v67 
=== Succesors ===
next: v114 
=== Usages ===
=== Predecessor ===
- >@ <|@
instruction <@Merge|@org.graalvm.compiler.nodes.MergeNode>@ stateAfter: - ends: v64 v67 #next: v114  <|@  <|@
f <@~|@floating>@ <|@
tid v246 <|@
d <@d|@=== Debug Properties ===
displacement: 24
scale: Times1
stamp: void*
=== Inputs ===
base: a1 
index: - 
=== Succesors ===
=== Usages ===
v114 
=== Predecessor ===
- >@ <|@
instruction <@AMD64Address|@org.graalvm.compiler.core.amd64.AMD64AddressNode>@ base: a1 index: -  <|@  <|@
f <@~|@floating>@ <|@
tid a96 <|@
d <@d|@=== Debug Properties ===
encoding: base: 0 shift: 3
nodeSourcePosition: at java.util.SubList.<init>(AbstractList.java:626) [bci: 118]
op: Compress
stamp: n Ljava/util/AbstractList;
=== Inputs ===
value: a2 
=== Succesors ===
=== Usages ===
v114 
=== Predecessor ===
- >@ <|@
instruction <@HotSpotCompression|@org.graalvm.compiler.hotspot.nodes.HotSpotCompressionNode>@ value: a2  <|@  <|@
f <@#|@fixed with next>@ <|@
tid v114 <|@
d <@d|@=== Debug Properties ===
barrierType: IMPRECISE
location: SubList.l
nodeSourcePosition: at java.util.SubList.<init>(AbstractList.java:626) [bci: 118]
nullCheck: false
stamp: void
=== Inputs ===
stateBefore: - 
guard: - 
address: v246 
value: a96 
stateAfter: - 
lastLocationAccess: - 
=== Succesors ===
next: j224 
=== Usages ===
=== Predecessor ===
v65 >@ <|@
instruction <@Write|@org.graalvm.compiler.nodes.memory.WriteNode>@ stateBefore: - guard: - address: v246 value: a96 stateAfter: - lastLocationAccess: - #next: j224  <|@  <|@
f <@#|@fixed with next>@ <|@
tid j224 <|@
d <@d|@=== Debug Properties ===
nodeSourcePosition: at org.graalvm.compiler.hotspot.replacements.WriteBarrierSnippets.serialImpreciseWriteBarrier(WriteBarrierSnippets.java:144) [bci: 1]
at java.util.SubList.<init>(AbstractList.java:626) [bci: 118]
stamp: i64
trackedPointer: true
=== Inputs ===
input: a1 
=== Succesors ===
next: v230 
=== Usages ===
j226 
=== Predecessor ===
v114 >@ <|@
instruction <@WordCast|@org.graalvm.compiler.word.WordCastNode>@ input: a1 #next: v230  <|@  <|@
f <@~|@floating>@ <|@
tid i225 <|@
d <@d|@=== Debug Properties ===
isDefaultStable: false
nodeSourcePosition: at org.graalvm.compiler.hotspot.replacements.HotSpotReplacementsUtil.cardTableShift(GraalHotSpotVMConfig) [bci: -1]
at org.graalvm.compiler.hotspot.replacements.WriteBarrierSnippets.serialWriteBarrier(WriteBarrierSnippets.java:134) [bci: 15]
at org.graalvm.compiler.hotspot.replacements.WriteBarrierSnippets.serialImpreciseWriteBarrier(WriteBarrierSnippets.java:144) [bci: 5]
at java.util.SubList.<init>(AbstractList.java:626) [bci: 118]
rawvalue: 9
stableDimension: 0
stamp: i32 [9] ⇊0000000000000009 ⇈0000000000000009
stampKind: i32
value: int[9|0x9]
=== Inputs ===
=== Succesors ===
=== Usages ===
j226 
=== Predecessor ===
- >@ <|@
instruction <@Constant|@org.graalvm.compiler.nodes.ConstantNode>@  <|@  <|@
f <@~|@floating>@ <|@
tid j226 <|@
d <@d|@=== Debug Properties ===
getOp: org.graalvm.compiler.nodes.calc.UnsignedRightShiftNode$$Lambda$68/774788493@3e7195e9
nodeSourcePosition: at org.graalvm.compiler.hotspot.replacements.WriteBarrierSnippets.serialWriteBarrier(WriteBarrierSnippets.java:134) [bci: 18]
at org.graalvm.compiler.hotspot.replacements.WriteBarrierSnippets.serialImpreciseWriteBarrier(WriteBarrierSnippets.java:144) [bci: 5]
at java.util.SubList.<init>(AbstractList.java:626) [bci: 118]
stamp: i64 [0 - 36028797018963967] ⇈007fffffffffffff
=== Inputs ===
x: j224 
y: i225 
=== Succesors ===
=== Usages ===
v251 
=== Predecessor ===
- >@ <|@
instruction <@>>>|@org.graalvm.compiler.nodes.calc.UnsignedRightShiftNode>@ x: j224 y: i225  <|@  <|@
f <@~|@floating>@ <|@
tid j229 <|@
d <@d|@=== Debug Properties ===
isDefaultStable: false
nodeSourcePosition: at org.graalvm.compiler.hotspot.nodes.GraalHotSpotVMConfigNode.loadLongConfigValue(int) [bci: -1]
at org.graalvm.compiler.hotspot.nodes.GraalHotSpotVMConfigNode.cardTableAddress(GraalHotSpotVMConfigNode.java:114) [bci: 6]
at org.graalvm.compiler.hotspot.replacements.WriteBarrierSnippets.serialWriteBarrier(WriteBarrierSnippets.java:133) [bci: 7]
at org.graalvm.compiler.hotspot.replacements.WriteBarrierSnippets.serialImpreciseWriteBarrier(WriteBarrierSnippets.java:144) [bci: 5]
at java.util.SubList.<init>(AbstractList.java:626) [bci: 118]
rawvalue: 4682670080
stableDimension: 0
stamp: i64 [4682670080] ⇊00000001171be000 ⇈00000001171be000
stampKind: i64
value: long[4682670080|0x1171be000]
=== Inputs ===
=== Succesors ===
=== Usages ===
v251 
=== Predecessor ===
- >@ <|@
instruction <@Constant|@org.graalvm.compiler.nodes.ConstantNode>@  <|@  <|@
f <@~|@floating>@ <|@
tid v251 <|@
d <@d|@=== Debug Properties ===
displacement: 0
scale: Times1
stamp: void*
=== Inputs ===
base: j226 
index: j229 
=== Succesors ===
=== Usages ===
v230 
=== Predecessor ===
- >@ <|@
instruction <@AMD64Address|@org.graalvm.compiler.core.amd64.AMD64AddressNode>@ base: j226 index: j229  <|@  <|@
f <@~|@floating>@ <|@
tid i231 <|@
d <@d|@=== Debug Properties ===
isDefaultStable: false
nodeSourcePosition: at org.graalvm.compiler.hotspot.replacements.WriteBarrierSnippets.serialWriteBarrier(WriteBarrierSnippets.java:138) [bci: 66]
at org.graalvm.compiler.hotspot.replacements.WriteBarrierSnippets.serialImpreciseWriteBarrier(WriteBarrierSnippets.java:144) [bci: 5]
at java.util.SubList.<init>(AbstractList.java:626) [bci: 118]
rawvalue: 0
stableDimension: 0
stamp: i8 [0] ⇈0000000000000000
stampKind: i8
value: byte[0|0x0]
=== Inputs ===
=== Succesors ===
=== Usages ===
v230 
=== Predecessor ===
- >@ <|@
instruction <@Constant|@org.graalvm.compiler.nodes.ConstantNode>@  <|@  <|@
f <@#|@fixed with next>@ <|@
tid v230 <|@
d <@d|@=== Debug Properties ===
barrierType: NONE
location: GC-Card
nodeSourcePosition: at org.graalvm.compiler.hotspot.replacements.WriteBarrierSnippets.serialWriteBarrier(WriteBarrierSnippets.java:138) [bci: 66]
at org.graalvm.compiler.hotspot.replacements.WriteBarrierSnippets.serialImpreciseWriteBarrier(WriteBarrierSnippets.java:144) [bci: 5]
at java.util.SubList.<init>(AbstractList.java:626) [bci: 118]
nullCheck: false
stamp: void
=== Inputs ===
stateBefore: - 
guard: - 
address: v251 
value: i231 
stateAfter: - 
lastLocationAccess: - 
=== Succesors ===
next: v115 
=== Usages ===
=== Predecessor ===
j224 >@ <|@
instruction <@Write|@org.graalvm.compiler.nodes.memory.WriteNode>@ stateBefore: - guard: - address: v251 value: i231 stateAfter: - lastLocationAccess: - #next: v115  <|@  <|@
f <@~|@floating>@ <|@
tid v247 <|@
d <@d|@=== Debug Properties ===
displacement: 16
scale: Times1
stamp: void*
=== Inputs ===
base: a1 
index: - 
=== Succesors ===
=== Usages ===
v115 
=== Predecessor ===
- >@ <|@
instruction <@AMD64Address|@org.graalvm.compiler.core.amd64.AMD64AddressNode>@ base: a1 index: -  <|@  <|@
f <@#|@fixed with next>@ <|@
tid v115 <|@
d <@d|@=== Debug Properties ===
barrierType: NONE
location: SubList.offset
nodeSourcePosition: at java.util.SubList.<init>(AbstractList.java:627) [bci: 123]
nullCheck: false
stamp: void
=== Inputs ===
stateBefore: - 
guard: - 
address: v247 
value: i3 
stateAfter: - 
lastLocationAccess: - 
=== Succesors ===
next: v116 
=== Usages ===
=== Predecessor ===
v230 >@ <|@
instruction <@Write|@org.graalvm.compiler.nodes.memory.WriteNode>@ stateBefore: - guard: - address: v247 value: i3 stateAfter: - lastLocationAccess: - #next: v116  <|@  <|@
f <@~|@floating>@ <|@
tid v248 <|@
d <@d|@=== Debug Properties ===
displacement: 20
scale: Times1
stamp: void*
=== Inputs ===
base: a1 
index: - 
=== Succesors ===
=== Usages ===
v116 
=== Predecessor ===
- >@ <|@
instruction <@AMD64Address|@org.graalvm.compiler.core.amd64.AMD64AddressNode>@ base: a1 index: -  <|@  <|@
f <@~|@floating>@ <|@
tid i23 <|@
d <@d|@=== Debug Properties ===
getOp: org.graalvm.compiler.nodes.calc.SubNode$$Lambda$64/1952983589@24889bdf
nodeSourcePosition: at java.util.SubList.<init>(AbstractList.java:628) [bci: 129]
stamp: i32
=== Inputs ===
x: i4 
y: i3 
=== Succesors ===
=== Usages ===
v116 
=== Predecessor ===
- >@ <|@
instruction <@-|@org.graalvm.compiler.nodes.calc.SubNode>@ x: i4 y: i3  <|@  <|@
f <@#|@fixed with next>@ <|@
tid v116 <|@
d <@d|@=== Debug Properties ===
barrierType: NONE
location: SubList.size
nodeSourcePosition: at java.util.SubList.<init>(AbstractList.java:628) [bci: 130]
nullCheck: false
stamp: void
=== Inputs ===
stateBefore: - 
guard: - 
address: v248 
value: i23 
stateAfter: - 
lastLocationAccess: - 
=== Succesors ===
next: i242 
=== Usages ===
=== Predecessor ===
v115 >@ <|@
instruction <@Write|@org.graalvm.compiler.nodes.memory.WriteNode>@ stateBefore: - guard: - address: v248 value: i23 stateAfter: - lastLocationAccess: - #next: i242  <|@  <|@
f <@~|@floating>@ <|@
tid v249 <|@
d <@d|@=== Debug Properties ===
displacement: 12
scale: Times1
stamp: void*
=== Inputs ===
base: a2 
index: - 
=== Succesors ===
=== Usages ===
i242 
=== Predecessor ===
- >@ <|@
instruction <@AMD64Address|@org.graalvm.compiler.core.amd64.AMD64AddressNode>@ base: a2 index: -  <|@  <|@
f <@#|@fixed with next>@ <|@
tid i242 <|@
d <@d|@=== Debug Properties ===
barrierType: NONE
forceFixed: false
location: AbstractList.modCount
nodeSourcePosition: at java.util.SubList.<init>(AbstractList.java:629) [bci: 138]
nullCheck: false
stamp: i32
=== Inputs ===
stateBefore: - 
guard: - 
address: v249 
=== Succesors ===
next: v118 
=== Usages ===
v118 
=== Predecessor ===
v116 >@ <|@
instruction <@Read|@org.graalvm.compiler.nodes.memory.ReadNode>@ stateBefore: - guard: - address: v249 #next: v118  <|@  <|@
f <@#|@fixed with next>@ <|@
tid v118 <|@
d <@d|@=== Debug Properties ===
barrierType: NONE
location: AbstractList.modCount
nodeSourcePosition: at java.util.SubList.<init>(AbstractList.java:629) [bci: 141]
nullCheck: false
stamp: void
=== Inputs ===
stateBefore: - 
guard: - 
address: v243 
value: i242 
stateAfter: - 
lastLocationAccess: - 
=== Succesors ===
next: v84 
=== Usages ===
=== Predecessor ===
i242 >@ <|@
instruction <@Write|@org.graalvm.compiler.nodes.memory.WriteNode>@ stateBefore: - guard: - address: v243 value: i242 stateAfter: - lastLocationAccess: - #next: v84  <|@  <|@
f <@#|@fixed with next>@ <|@
tid v84 <|@
d <@d|@=== Debug Properties ===
barriers: 10
location: ANY_LOCATION
nodeSourcePosition: at java.util.SubList.<init>(AbstractList.java:630) [bci: 144]
stamp: void
=== Inputs ===
=== Succesors ===
next: v31 
=== Usages ===
=== Predecessor ===
v118 >@ <|@
instruction <@Membar|@org.graalvm.compiler.nodes.extended.MembarNode>@ #next: v31  <|@  <|@
f <@*|@fixed>@ <|@
tid v31 <|@
d <@d|@=== Debug Properties ===
nodeSourcePosition: at java.util.SubList.<init>(AbstractList.java:630) [bci: 144]
stamp: void
=== Inputs ===
result: - 
memoryMap: - 
=== Succesors ===
=== Usages ===
=== Predecessor ===
v84 >@ <|@
instruction <@Return|@org.graalvm.compiler.nodes.ReturnNode>@ result: - memoryMap: -  <|@  <|@
    end_IR
  end_block
  begin_block
    name "B14"
    from_bci -1
    to_bci -1
    predecessors "B9" 
    successors "B15" 
    xhandlers
    flags 
    probability 2355382605114769408
    begin_IR
      HIR
f <@#|@fixed with next>@ <|@
tid v150 <|@
d <@d|@=== Debug Properties ===
nodeSourcePosition: dispatchedType=Lorg/graalvm/compiler/graph/NodeInputList; target_method=size target_method_class=Lorg/graalvm/compiler/graph/NodeList; position=at java.util.SubList.<init>(AbstractList.java:621) [bci: 37]
stamp: void
=== Inputs ===
=== Succesors ===
next: v217 
=== Usages ===
=== Predecessor ===
v151 >@ <|@
instruction <@Begin|@org.graalvm.compiler.nodes.BeginNode>@ #next: v217  <|@  <|@
f <@~|@floating>@ <|@
tid i218 <|@
d <@d|@=== Debug Properties ===
isDefaultStable: false
rawvalue: -27955
stableDimension: 0
stamp: i32 [-27955] ⇊00000000ffff92cd ⇈00000000ffff92cd
stampKind: i32
value: int[-27955|0xffffffffffff92cd]
=== Inputs ===
=== Succesors ===
=== Usages ===
i210 
=== Predecessor ===
- >@ <|@
instruction <@Constant|@org.graalvm.compiler.nodes.ConstantNode>@  <|@  <|@
f <@*|@fixed>@ <|@
tid v217 <|@
d <@d|@=== Debug Properties ===
stamp: void
=== Inputs ===
=== Succesors ===
=== Usages ===
v207 
=== Predecessor ===
v150 >@ <|@
instruction <@EndNode|@org.graalvm.compiler.nodes.EndNode>@  <|@  <|@
    end_IR
  end_block
  begin_block
    name "B15"
    from_bci -1
    to_bci -1
    predecessors "B11" "B7" "B14" 
    successors 
    xhandlers
    flags 
    probability 2362138004555825152
    begin_IR
      HIR
f <@~|@floating>@ <|@
tid i210 <|@
d <@d|@=== Debug Properties ===
stamp: i32 [-28691 - -23051] ⇊00000000ffff80c5 ⇈00000000ffffbffd
valueDescription: i32
=== Inputs ===
merge: v207 
values: i214 i216 i218 
=== Succesors ===
=== Usages ===
v212 
=== Predecessor ===
- >@ <|@
instruction <@ValuePhi|@org.graalvm.compiler.nodes.ValuePhiNode>@ merge: v207 values: i214 i216 i218  <|@  <|@
f <@#|@fixed with next>@ <|@
tid v207 <|@
d <@d|@=== Debug Properties ===
stamp: void
=== Inputs ===
stateAfter: - 
ends: v213 v215 v217 
=== Succesors ===
next: v212 
=== Usages ===
i210 
=== Predecessor ===
- >@ <|@
instruction <@Merge|@org.graalvm.compiler.nodes.MergeNode>@ stateAfter: - ends: v213 v215 v217 #next: v212  <|@  <|@
f <@*|@fixed>@ <|@
tid v212 <|@
d <@d|@=== Debug Properties ===
stamp: void
=== Inputs ===
stateBefore: ?9 
actionAndReason: i210 
speculation: a199 
=== Succesors ===
=== Usages ===
=== Predecessor ===
v207 >@ <|@
instruction <@DynamicDeoptimize|@org.graalvm.compiler.nodes.DynamicDeoptimizeNode>@ stateBefore: ?9 actionAndReason: i210 speculation: a199  <|@  <|@
    end_IR
  end_block
end_cfg
begin_cfg
  name "After LIR generation"
  begin_block
    name "B0"
    from_bci -1
    to_bci -1
    predecessors 
    successors "B1" "B2" 
    xhandlers
    flags 
    probability 4607182418800017408
    begin_IR
      HIR
f <@#|@fixed with next>@ <|@
tid v0 <|@
d <@d|@=== Debug Properties ===
stamp: void
=== Inputs ===
stateAfter: - 
=== Succesors ===
next: v131 
=== Usages ===
=== Predecessor ===
- >@ <|@
instruction <@StartNode|@org.graalvm.compiler.nodes.StartNode>@ stateAfter: - #next: v131  <|@  <|@
f <@~|@floating>@ <|@
tid a199 <|@
result Object[null] <|@
d <@d|@=== Debug Properties ===
isDefaultStable: false
rawvalue: null
stableDimension: 0
stamp: a - NULL
stampKind: a -
value: Object[null]
=== Inputs ===
=== Succesors ===
=== Usages ===
v202 v212 
=== Predecessor ===
- >@ <|@
instruction <@Constant|@org.graalvm.compiler.nodes.ConstantNode>@  <|@  <|@
f <@~|@floating>@ <|@
tid a1 <|@
result v0|QWORD[.] <|@
d <@d|@=== Debug Properties ===
index: 0
stamp: a! Ljava/util/SubList;
uncheckedStamp: [null]
=== Inputs ===
=== Succesors ===
=== Usages ===
?5 v243 ?8 ?9 v247 v246 v248 j224 
=== Predecessor ===
- >@ <|@
instruction <@Parameter|@org.graalvm.compiler.nodes.ParameterNode>@  <|@  <|@
f <@~|@floating>@ <|@
tid a2 <|@
result v1|QWORD[.] <|@
d <@d|@=== Debug Properties ===
index: 1
stamp: a Ljava/util/AbstractList;
uncheckedStamp: [null]
=== Inputs ===
=== Succesors ===
=== Usages ===
?5 ?8 v244 v252 a96 v249 v250 
=== Predecessor ===
- >@ <|@
instruction <@Parameter|@org.graalvm.compiler.nodes.ParameterNode>@  <|@  <|@
f <@~|@floating>@ <|@
tid i3 <|@
result v2|DWORD <|@
d <@d|@=== Debug Properties ===
index: 2
stamp: i32
uncheckedStamp: [null]
=== Inputs ===
=== Succesors ===
=== Usages ===
?5 ?8 v10 v115 v17 i23 
=== Predecessor ===
- >@ <|@
instruction <@Parameter|@org.graalvm.compiler.nodes.ParameterNode>@  <|@  <|@
f <@~|@floating>@ <|@
tid i4 <|@
result v3|DWORD <|@
d <@d|@=== Debug Properties ===
index: 3
stamp: i32
uncheckedStamp: [null]
=== Inputs ===
=== Succesors ===
=== Usages ===
?5 ?8 i23 v69 v15 v17 
=== Predecessor ===
- >@ <|@
instruction <@Parameter|@org.graalvm.compiler.nodes.ParameterNode>@  <|@  <|@
tid ?5 <|@
d <@d|@=== Debug Properties ===
bci: 0
code: ResolvedJavaMethodBytecode<SubList.<init>(AbstractList, int, int)>
duringCall: false
localsSize: 4
locksSize: 0
rethrowException: false
sourceFile: AbstractList.java
sourceLine: 618
stackSize: 0
=== Inputs ===
outerFrameState: - 
values: a1 a2 i3 i4 
=== Succesors ===
=== Usages ===
v202 v252 
=== Predecessor ===
- >@ <|@
instruction <@FrameState|@org.graalvm.compiler.nodes.FrameState>@ outerFrameState: - values: a1 a2 i3 i4  <|@  <|@
f <@~|@floating>@ <|@
tid i6 <|@
result int[0|0x0] <|@
d <@d|@=== Debug Properties ===
isDefaultStable: false
nodeSourcePosition: at java.util.AbstractList.<init>(AbstractList.java:601) [bci: 5]
at java.util.SubList.<init>(AbstractList.java:618) [bci: 1]
rawvalue: 0
stableDimension: 0
stamp: i32 [0] ⇈0000000000000000
stampKind: i32
value: int[0|0x0]
=== Inputs ===
=== Succesors ===
=== Usages ===
v81 v10 
=== Predecessor ===
- >@ <|@
instruction <@Constant|@org.graalvm.compiler.nodes.ConstantNode>@  <|@  <|@
f <@~|@floating>@ <|@
tid v10 <|@
d <@d|@=== Debug Properties ===
condition: LT
nodeSourcePosition: at java.util.SubList.<init>(AbstractList.java:619) [bci: 5]
op: org.graalvm.compiler.nodes.calc.IntegerLessThanNode$LessThanOp@7cc8d043
stamp: void
unorderedIsTrue: false
=== Inputs ===
x: i3 
y: i6 
=== Succesors ===
=== Usages ===
v131 
=== Predecessor ===
- >@ <|@
instruction <@<|@org.graalvm.compiler.nodes.calc.IntegerLessThanNode>@ x: i3 y: i6  <|@  <|@
f <@*|@fixed>@ <|@
tid v131 <|@
d <@d|@=== Debug Properties ===
nodeSourcePosition: at java.util.SubList.<init>(AbstractList.java:619) [bci: 5]
stamp: void
trueSuccessorProbability: 0.0
=== Inputs ===
condition: v10 
=== Succesors ===
trueSuccessor: v130 
falseSuccessor: v128 
=== Usages ===
=== Predecessor ===
v0 >@ <|@
instruction <@If|@org.graalvm.compiler.nodes.IfNode>@ condition: v10 #trueSuccessor: v130 #falseSuccessor: v128  <|@  <|@
    end_IR
    begin_IR
      LIR
      nr   -1  <|@ instruction [rsi|QWORD[.], rdx|QWORD[.], rcx|DWORD, r8|DWORD, rbp|QWORD] = LABEL numbPhis: 0 align: false label: ? <|@ <|@
      nr   -1  <|@ instruction stack:16|QWORD = MOVE rbp|QWORD moveKind: QWORD <|@ <|@
      nr   -1  <|@ instruction [] = HOTSPOTLOCKSTACK frameMapBuilder: org.graalvm.compiler.lir.amd64.AMD64FrameMapBuilder@3c736a5f slotKind: QWORD <|@ <|@
      nr   -1  <|@ instruction v0|QWORD[.] = MOVE rsi|QWORD[.] moveKind: QWORD <|@ <|@
      nr   -1  <|@ instruction v1|QWORD[.] = MOVE rdx|QWORD[.] moveKind: QWORD <|@ <|@
      nr   -1  <|@ instruction v2|DWORD = MOVE rcx|DWORD moveKind: DWORD <|@ <|@
      nr   -1  <|@ instruction v3|DWORD = MOVE r8|DWORD moveKind: DWORD <|@ <|@
      nr   -1  <|@ instruction TEST (x: v2|DWORD, y: v2|DWORD) size: DWORD <|@ <|@
      nr   -1  <|@ instruction BRANCH trueDestinationProbability: 0.0 condition: < trueDestination: B0 -> B1 falseDestination: B0 -> B2 <|@ <|@
    end_IR
  end_block
  begin_block
    name "B1"
    from_bci -1
    to_bci -1
    predecessors "B0" 
    successors "B4" 
    xhandlers
    flags 
    probability 2355382605114769408
    begin_IR
      HIR
f <@#|@fixed with next>@ <|@
tid v130 <|@
d <@d|@=== Debug Properties ===
nodeSourcePosition: at java.util.SubList.<init>(AbstractList.java:619) [bci: 5]
stamp: void
=== Inputs ===
=== Succesors ===
next: v197 
=== Usages ===
=== Predecessor ===
v131 >@ <|@
instruction <@Begin|@org.graalvm.compiler.nodes.BeginNode>@ #next: v197  <|@  <|@
f <@~|@floating>@ <|@
tid i198 <|@
result int[-21011|0xffffffffffffaded] <|@
d <@d|@=== Debug Properties ===
isDefaultStable: false
rawvalue: -21011
stableDimension: 0
stamp: i32 [-21011] ⇊00000000ffffaded ⇈00000000ffffaded
stampKind: i32
value: int[-21011|0xffffffffffffaded]
=== Inputs ===
=== Succesors ===
=== Usages ===
i200 
=== Predecessor ===
- >@ <|@
instruction <@Constant|@org.graalvm.compiler.nodes.ConstantNode>@  <|@  <|@
f <@*|@fixed>@ <|@
tid v197 <|@
d <@d|@=== Debug Properties ===
stamp: void
=== Inputs ===
=== Succesors ===
=== Usages ===
v196 
=== Predecessor ===
v130 >@ <|@
instruction <@EndNode|@org.graalvm.compiler.nodes.EndNode>@  <|@  <|@
    end_IR
    begin_IR
      LIR
      nr   -1  <|@ instruction [] = LABEL numbPhis: 0 align: false label: ? <|@ <|@
      nr   -1  <|@ instruction JUMP ~[int[-21011|0xffffffffffffaded]] destination: B1 -> B4 <|@ <|@
    end_IR
  end_block
  begin_block
    name "B2"
    from_bci -1
    to_bci -1
    predecessors "B0" 
    successors "B3" "B5" 
    xhandlers
    flags 
    probability 4607182418800017408
    begin_IR
      HIR
f <@#|@fixed with next>@ <|@
tid v128 <|@
d <@d|@=== Debug Properties ===
nodeSourcePosition: at java.util.SubList.<init>(AbstractList.java:619) [bci: 5]
stamp: void
=== Inputs ===
=== Succesors ===
next: v252 
=== Usages ===
=== Predecessor ===
v131 >@ <|@
instruction <@Begin|@org.graalvm.compiler.nodes.BeginNode>@ #next: v252  <|@  <|@
f <@#|@fixed with next>@ <|@
tid v252 <|@
d <@d|@=== Debug Properties ===
stamp: void
=== Inputs ===
stateBefore: ?5 
object: a2 
=== Succesors ===
next: v139 
=== Usages ===
=== Predecessor ===
v128 >@ <|@
instruction <@NullCheck|@org.graalvm.compiler.nodes.extended.NullCheckNode>@ stateBefore: ?5 object: a2 #next: v139  <|@  <|@
f <@~|@floating>@ <|@
tid v17 <|@
d <@d|@=== Debug Properties ===
condition: LT
nodeSourcePosition: at java.util.SubList.<init>(AbstractList.java:623) [bci: 72]
op: org.graalvm.compiler.nodes.calc.IntegerLessThanNode$LessThanOp@7cc8d043
stamp: void
unorderedIsTrue: false
=== Inputs ===
x: i4 
y: i3 
=== Succesors ===
=== Usages ===
v139 
=== Predecessor ===
- >@ <|@
instruction <@<|@org.graalvm.compiler.nodes.calc.IntegerLessThanNode>@ x: i4 y: i3  <|@  <|@
f <@*|@fixed>@ <|@
tid v139 <|@
d <@d|@=== Debug Properties ===
nodeSourcePosition: at java.util.SubList.<init>(AbstractList.java:623) [bci: 72]
stamp: void
trueSuccessorProbability: 0.0
=== Inputs ===
condition: v17 
=== Succesors ===
trueSuccessor: v138 
falseSuccessor: v136 
=== Usages ===
=== Predecessor ===
v252 >@ <|@
instruction <@If|@org.graalvm.compiler.nodes.IfNode>@ condition: v17 #trueSuccessor: v138 #falseSuccessor: v136  <|@  <|@
    end_IR
    begin_IR
      LIR
      nr   -1  <|@ instruction [] = LABEL numbPhis: 0 align: false label: ? <|@ <|@
      nr   -1  <|@ st <@st|@java.util.SubList.<init>(AbstractList.java:618) [bci: 0]
locals: v0|QWORD[.] v1|QWORD[.] v2|DWORD v3|DWORD 
>@ <|@ instruction NULLCHECK [v1|QWORD[.]] state [bci:0] <|@ <|@
      nr   -1  <|@ instruction CMP (x: v2|DWORD, y: v3|DWORD) size: DWORD <|@ <|@
      nr   -1  <|@ instruction BRANCH trueDestinationProbability: 0.0 condition: > trueDestination: B2 -> B3 falseDestination: B2 -> B5 <|@ <|@
    end_IR
  end_block
  begin_block
    name "B3"
    from_bci -1
    to_bci -1
    predecessors "B2" 
    successors "B4" 
    xhandlers
    flags 
    probability 2355382605114769408
    begin_IR
      HIR
f <@#|@fixed with next>@ <|@
tid v138 <|@
d <@d|@=== Debug Properties ===
nodeSourcePosition: at java.util.SubList.<init>(AbstractList.java:623) [bci: 72]
stamp: void
=== Inputs ===
=== Succesors ===
next: v205 
=== Usages ===
=== Predecessor ===
v139 >@ <|@
instruction <@Begin|@org.graalvm.compiler.nodes.BeginNode>@ #next: v205  <|@  <|@
f <@~|@floating>@ <|@
tid i206 <|@
result int[-32531|0xffffffffffff80ed] <|@
d <@d|@=== Debug Properties ===
isDefaultStable: false
rawvalue: -32531
stableDimension: 0
stamp: i32 [-32531] ⇊00000000ffff80ed ⇈00000000ffff80ed
stampKind: i32
value: int[-32531|0xffffffffffff80ed]
=== Inputs ===
=== Succesors ===
=== Usages ===
i200 
=== Predecessor ===
- >@ <|@
instruction <@Constant|@org.graalvm.compiler.nodes.ConstantNode>@  <|@  <|@
f <@*|@fixed>@ <|@
tid v205 <|@
d <@d|@=== Debug Properties ===
stamp: void
=== Inputs ===
=== Succesors ===
=== Usages ===
v196 
=== Predecessor ===
v138 >@ <|@
instruction <@EndNode|@org.graalvm.compiler.nodes.EndNode>@  <|@  <|@
    end_IR
    begin_IR
      LIR
      nr   -1  <|@ instruction [] = LABEL numbPhis: 0 align: false label: ? <|@ <|@
      nr   -1  <|@ instruction JUMP ~[int[-32531|0xffffffffffff80ed]] destination: B3 -> B4 <|@ <|@
    end_IR
  end_block
  begin_block
    name "B4"
    from_bci -1
    to_bci -1
    predecessors "B1" "B3" 
    successors 
    xhandlers
    flags 
    probability 2359886204742139904
    begin_IR
      HIR
f <@~|@floating>@ <|@
tid i200 <|@
result v4|DWORD <|@
d <@d|@=== Debug Properties ===
stamp: i32 [-32531 - -21011] ⇊00000000ffff80e5 ⇈00000000ffffadfd
valueDescription: i32
=== Inputs ===
merge: v196 
values: i198 i206 
=== Succesors ===
=== Usages ===
v202 
=== Predecessor ===
- >@ <|@
instruction <@ValuePhi|@org.graalvm.compiler.nodes.ValuePhiNode>@ merge: v196 values: i198 i206  <|@  <|@
f <@#|@fixed with next>@ <|@
tid v196 <|@
d <@d|@=== Debug Properties ===
stamp: void
=== Inputs ===
stateAfter: - 
ends: v197 v205 
=== Succesors ===
next: v202 
=== Usages ===
i200 
=== Predecessor ===
- >@ <|@
instruction <@Merge|@org.graalvm.compiler.nodes.MergeNode>@ stateAfter: - ends: v197 v205 #next: v202  <|@  <|@
f <@*|@fixed>@ <|@
tid v202 <|@
d <@d|@=== Debug Properties ===
stamp: void
=== Inputs ===
stateBefore: ?5 
actionAndReason: i200 
speculation: a199 
=== Succesors ===
=== Usages ===
=== Predecessor ===
v196 >@ <|@
instruction <@DynamicDeoptimize|@org.graalvm.compiler.nodes.DynamicDeoptimizeNode>@ stateBefore: ?5 actionAndReason: i200 speculation: a199  <|@  <|@
    end_IR
    begin_IR
      LIR
      nr   -1  <|@ instruction [v4|DWORD] = LABEL numbPhis: 1 align: false label: ? <|@ <|@
      nr   -1  <|@ instruction MOV (x: [r15|QWORD + 668], y: v4|DWORD) size: DWORD <|@ <|@
      nr   -1  <|@ instruction MOV (x: [r15|QWORD + 680], y: r12|ILLEGAL) size: QWORD <|@ <|@
      nr   -1  <|@ st <@st|@java.util.SubList.<init>(AbstractList.java:618) [bci: 0]
locals: v0|QWORD[.] v1|QWORD[.] v2|DWORD v3|DWORD 
>@ <|@ instruction DEOPT info [bci:0] <|@ <|@
    end_IR
  end_block
  begin_block
    name "B5"
    from_bci -1
    to_bci -1
    predecessors "B2" 
    successors "B6" "B9" 
    xhandlers
    flags 
    probability 4607182418800017408
    begin_IR
      HIR
f <@#|@fixed with next>@ <|@
tid v136 <|@
d <@d|@=== Debug Properties ===
nodeSourcePosition: at java.util.SubList.<init>(AbstractList.java:623) [bci: 72]
stamp: void
=== Inputs ===
=== Succesors ===
next: v81 
=== Usages ===
=== Predecessor ===
v139 >@ <|@
instruction <@Begin|@org.graalvm.compiler.nodes.BeginNode>@ #next: v81  <|@  <|@
f <@~|@floating>@ <|@
tid v243 <|@
result [v0|QWORD[.] + 12] <|@
d <@d|@=== Debug Properties ===
displacement: 12
scale: Times1
stamp: void*
=== Inputs ===
base: a1 
index: - 
=== Succesors ===
=== Usages ===
v81 v118 
=== Predecessor ===
- >@ <|@
instruction <@AMD64Address|@org.graalvm.compiler.core.amd64.AMD64AddressNode>@ base: a1 index: -  <|@  <|@
f <@#|@fixed with next>@ <|@
tid v81 <|@
d <@d|@=== Debug Properties ===
barrierType: NONE
location: AbstractList.modCount
nodeSourcePosition: at java.util.AbstractList.<init>(AbstractList.java:601) [bci: 6]
at java.util.SubList.<init>(AbstractList.java:618) [bci: 1]
nullCheck: false
stamp: void
=== Inputs ===
stateBefore: - 
guard: - 
address: v243 
value: i6 
stateAfter: - 
lastLocationAccess: - 
=== Succesors ===
next: v238 
=== Usages ===
=== Predecessor ===
v136 >@ <|@
instruction <@Write|@org.graalvm.compiler.nodes.memory.WriteNode>@ stateBefore: - guard: - address: v243 value: i6 stateAfter: - lastLocationAccess: - #next: v238  <|@  <|@
f <@~|@floating>@ <|@
tid v250 <|@
result [v1|QWORD[.] + 8] <|@
d <@d|@=== Debug Properties ===
displacement: 8
scale: Times1
stamp: void*
=== Inputs ===
base: a2 
index: - 
=== Succesors ===
=== Usages ===
v238 
=== Predecessor ===
- >@ <|@
instruction <@AMD64Address|@org.graalvm.compiler.core.amd64.AMD64AddressNode>@ base: a2 index: -  <|@  <|@
f <@#|@fixed with next>@ <|@
tid v238 <|@
result v5|DWORD <|@
d <@d|@=== Debug Properties ===
barrierType: NONE
forceFixed: false
location: CompressedHub:final
nodeSourcePosition: at org.graalvm.compiler.hotspot.replacements.HotSpotReplacementsUtil.loadHubIntrinsic(Object) [bci: -1]
at org.graalvm.compiler.hotspot.replacements.InstanceOfSnippets.instanceofExact(InstanceOfSnippets.java:142) [bci: 39]
at java.util.SubList.<init>(AbstractList.java:621) [bci: 37]
nullCheck: false
stamp: Klass*!(compressed base: 0 shift: 3)
=== Inputs ===
stateBefore: - 
guard: - 
address: v250 
=== Succesors ===
next: v46 
=== Usages ===
v237 v235 
=== Predecessor ===
v81 >@ <|@
instruction <@Read|@org.graalvm.compiler.nodes.memory.ReadNode>@ stateBefore: - guard: - address: v250 #next: v46  <|@  <|@
f <@~|@floating>@ <|@
tid v234 <|@
result meta{HotSpotType<Ljava/util/Arrays$ArrayList;, resolved>;compressed} <|@
d <@d|@=== Debug Properties ===
isDefaultStable: false
nodeSourcePosition: at org.graalvm.compiler.hotspot.replacements.InstanceOfSnippets.instanceofExact(InstanceOfSnippets.java:143) [bci: 50]
at java.util.SubList.<init>(AbstractList.java:621) [bci: 37]
rawvalue: meta{HotSpotType<Ljava/util/Arrays$ArrayList;, resolved>;compressed}
stableDimension: 0
stamp: Klass*!(compressed base: 0 shift: 3)
stampKind: Klass*(compressed base: 0 shift: 3)
value: meta{HotSpotType<Ljava/util/Arrays$ArrayList;, resolved>;compressed}
=== Inputs ===
=== Succesors ===
=== Usages ===
v235 
=== Predecessor ===
- >@ <|@
instruction <@Constant|@org.graalvm.compiler.nodes.ConstantNode>@  <|@  <|@
f <@~|@floating>@ <|@
tid v235 <|@
d <@d|@=== Debug Properties ===
condition: EQ
nodeSourcePosition: at org.graalvm.compiler.hotspot.replacements.InstanceOfSnippets.instanceofExact(InstanceOfSnippets.java:143) [bci: 50]
at java.util.SubList.<init>(AbstractList.java:621) [bci: 37]
stamp: void
unorderedIsTrue: false
=== Inputs ===
x: v238 
y: v234 
=== Succesors ===
=== Usages ===
v46 
=== Predecessor ===
- >@ <|@
instruction <@==|@org.graalvm.compiler.nodes.calc.PointerEqualsNode>@ x: v238 y: v234  <|@  <|@
tid ?8 <|@
d <@d|@=== Debug Properties ===
bci: 1
code: ResolvedJavaMethodBytecode<SubList.<init>(AbstractList, int, int)>
duringCall: true
localsSize: 4
locksSize: 0
nodeSourcePosition: at java.util.AbstractList.<init>(AbstractList.java:601) [bci: 6]
at java.util.SubList.<init>(AbstractList.java:618) [bci: 1]
rethrowException: false
sourceFile: AbstractList.java
sourceLine: 618
stackSize: 0
=== Inputs ===
outerFrameState: - 
values: a1 a2 i3 i4 
=== Succesors ===
=== Usages ===
?9 
=== Predecessor ===
- >@ <|@
instruction <@FrameState|@org.graalvm.compiler.nodes.FrameState>@ outerFrameState: - values: a1 a2 i3 i4  <|@  <|@
tid ?9 <|@
d <@d|@=== Debug Properties ===
bci: 9
code: ResolvedJavaMethodBytecode<AbstractList.<init>()>
duringCall: false
localsSize: 1
locksSize: 0
nodeSourcePosition: at java.util.AbstractList.<init>(AbstractList.java:601) [bci: 6]
at java.util.SubList.<init>(AbstractList.java:618) [bci: 1]
rethrowException: false
sourceFile: AbstractList.java
sourceLine: 77
stackSize: 0
=== Inputs ===
outerFrameState: ?8 
values: a1 
=== Succesors ===
=== Usages ===
v212 i240 
=== Predecessor ===
- >@ <|@
instruction <@FrameState|@org.graalvm.compiler.nodes.FrameState>@ outerFrameState: ?8 values: a1  <|@  <|@
f <@~|@floating>@ <|@
tid v244 <|@
result [v1|QWORD[.] + 16] <|@
d <@d|@=== Debug Properties ===
displacement: 16
scale: Times1
stamp: void*
=== Inputs ===
base: a2 
index: - 
=== Succesors ===
=== Usages ===
a239 i241 
=== Predecessor ===
- >@ <|@
instruction <@AMD64Address|@org.graalvm.compiler.core.amd64.AMD64AddressNode>@ base: a2 index: -  <|@  <|@
f <@*|@fixed>@ <|@
tid v46 <|@
d <@d|@=== Debug Properties ===
nodeSourcePosition: dispatchedType=Ljava/util/Arrays$ArrayList; target_method=size target_method_class=Ljava/util/Arrays$ArrayList; position=at java.util.SubList.<init>(AbstractList.java:621) [bci: 37]
stamp: void
trueSuccessorProbability: 0.7936731773025761
=== Inputs ===
condition: v235 
=== Succesors ===
trueSuccessor: v39 
falseSuccessor: v45 
=== Usages ===
=== Predecessor ===
v238 >@ <|@
instruction <@If|@org.graalvm.compiler.nodes.IfNode>@ condition: v235 #trueSuccessor: v39 #falseSuccessor: v45  <|@  <|@
    end_IR
    begin_IR
      LIR
      nr   -1  <|@ instruction [] = LABEL numbPhis: 0 align: false label: ? <|@ <|@
      nr   -1  <|@ instruction MOV (x: [v0|QWORD[.] + 12], y: r12|ILLEGAL) size: DWORD <|@ <|@
      nr   -1  <|@ instruction v5|DWORD = MOV [v1|QWORD[.] + 8] size: DWORD <|@ <|@
      nr   -1  <|@ instruction CMP v5|DWORD y: -559030611 size: DWORD c: meta{HotSpotType<Ljava/util/Arrays$ArrayList;, resolved>;compressed} <|@ <|@
      nr   -1  <|@ instruction BRANCH trueDestinationProbability: 0.7936731773025761 condition: = trueDestination: B5 -> B6 falseDestination: B5 -> B9 <|@ <|@
    end_IR
  end_block
  begin_block
    name "B6"
    from_bci -1
    to_bci -1
    predecessors "B5" 
    successors "B7" "B8" 
    xhandlers
    flags 
    probability 4605323991996384095
    begin_IR
      HIR
f <@#|@fixed with next>@ <|@
tid v39 <|@
d <@d|@=== Debug Properties ===
nodeSourcePosition: dispatchedType=Ljava/util/Arrays$ArrayList; target_method=size target_method_class=Ljava/util/Arrays$ArrayList; position=at java.util.SubList.<init>(AbstractList.java:621) [bci: 37]
stamp: void
=== Inputs ===
=== Succesors ===
next: a239 
=== Usages ===
=== Predecessor ===
v46 >@ <|@
instruction <@Begin|@org.graalvm.compiler.nodes.BeginNode>@ #next: a239  <|@  <|@
f <@#|@fixed with next>@ <|@
tid a239 <|@
result v6|DWORD[.] <|@
d <@d|@=== Debug Properties ===
barrierType: NONE
forceFixed: false
location: Arrays$ArrayList.a
nodeSourcePosition: at java.util.Arrays$ArrayList.size(Arrays.java:3818) [bci: 1]
at java.util.SubList.<init>(AbstractList.java:621) [bci: 37]
nullCheck: false
stamp: n [Ljava/lang/Object;
=== Inputs ===
stateBefore: - 
guard: - 
address: v244 
=== Succesors ===
next: i240 
=== Usages ===
v245 
=== Predecessor ===
v39 >@ <|@
instruction <@Read|@org.graalvm.compiler.nodes.memory.ReadNode>@ stateBefore: - guard: - address: v244 #next: i240  <|@  <|@
f <@~|@floating>@ <|@
tid v245 <|@
result [v6|DWORD[.] * 8 + 12] <|@
d <@d|@=== Debug Properties ===
displacement: 12
scale: Times8
stamp: void*
=== Inputs ===
base: - 
index: a239 
=== Succesors ===
=== Usages ===
i240 
=== Predecessor ===
- >@ <|@
instruction <@AMD64Address|@org.graalvm.compiler.core.amd64.AMD64AddressNode>@ base: - index: a239  <|@  <|@
f <@#|@fixed with next>@ <|@
tid i240 <|@
result INTERIOR_MATCH <|@
d <@d|@=== Debug Properties ===
barrierType: NONE
forceFixed: false
location: [].length:final
nodeSourcePosition: at java.util.Arrays$ArrayList.size(Arrays.java:3818) [bci: 4]
at java.util.SubList.<init>(AbstractList.java:621) [bci: 37]
nullCheck: true
stamp: i32 [0 - 2147483647] ⇈000000007fffffff
=== Inputs ===
stateBefore: ?9 
guard: - 
address: v245 
=== Succesors ===
next: v147 
=== Usages ===
v69 
=== Predecessor ===
a239 >@ <|@
instruction <@Read|@org.graalvm.compiler.nodes.memory.ReadNode>@ stateBefore: ?9 guard: - address: v245 #next: v147  <|@  <|@
f <@~|@floating>@ <|@
tid v69 <|@
result INTERIOR_MATCH <|@
d <@d|@=== Debug Properties ===
condition: LT
nodeSourcePosition: at java.util.SubList.<init>(AbstractList.java:621) [bci: 40]
op: org.graalvm.compiler.nodes.calc.IntegerLessThanNode$LessThanOp@7cc8d043
stamp: void
unorderedIsTrue: false
=== Inputs ===
x: i240 
y: i4 
=== Succesors ===
=== Usages ===
v147 
=== Predecessor ===
- >@ <|@
instruction <@<|@org.graalvm.compiler.nodes.calc.IntegerLessThanNode>@ x: i240 y: i4  <|@  <|@
f <@*|@fixed>@ <|@
tid v147 <|@
result org.graalvm.compiler.core.match.ComplexMatchValue@d98b27eb <|@
d <@d|@=== Debug Properties ===
nodeSourcePosition: at java.util.SubList.<init>(AbstractList.java:621) [bci: 40]
stamp: void
trueSuccessorProbability: 0.0
=== Inputs ===
condition: v69 
=== Succesors ===
trueSuccessor: v146 
falseSuccessor: v144 
=== Usages ===
=== Predecessor ===
i240 >@ <|@
instruction <@If|@org.graalvm.compiler.nodes.IfNode>@ condition: v69 #trueSuccessor: v146 #falseSuccessor: v144  <|@  <|@
    end_IR
    begin_IR
      LIR
      nr   -1  <|@ instruction [] = LABEL numbPhis: 0 align: false label: ? <|@ <|@
      nr   -1  <|@ instruction v6|DWORD[.] = MOV [v1|QWORD[.] + 16] size: DWORD <|@ <|@
      nr   -1  <|@ st <@st|@java.util.AbstractList.<init>(AbstractList.java:77) [bci: 9]
locals: v0|QWORD[.] 
java.util.SubList.<init>(AbstractList.java:618) [bci: 1]
locals: v0|QWORD[.] v1|QWORD[.] v2|DWORD v3|DWORD 
>@ <|@ instruction CMP (x: v3|DWORD, y: [v6|DWORD[.] * 8 + 12]) size: DWORD state [bci:9, 1] <|@ <|@
      nr   -1  <|@ instruction BRANCH trueDestinationProbability: 0.0 condition: > trueDestination: B6 -> B7 falseDestination: B6 -> B8 <|@ <|@
    end_IR
  end_block
  begin_block
    name "B7"
    from_bci -1
    to_bci -1
    predecessors "B6" 
    successors "B15" 
    xhandlers
    flags 
    probability 2355382605114769408
    begin_IR
      HIR
f <@#|@fixed with next>@ <|@
tid v146 <|@
d <@d|@=== Debug Properties ===
nodeSourcePosition: at java.util.SubList.<init>(AbstractList.java:621) [bci: 40]
stamp: void
=== Inputs ===
=== Succesors ===
next: v215 
=== Usages ===
=== Predecessor ===
v147 >@ <|@
instruction <@Begin|@org.graalvm.compiler.nodes.BeginNode>@ #next: v215  <|@  <|@
f <@~|@floating>@ <|@
tid i216 <|@
result int[-24083|0xffffffffffffa1ed] <|@
d <@d|@=== Debug Properties ===
isDefaultStable: false
rawvalue: -24083
stableDimension: 0
stamp: i32 [-24083] ⇊00000000ffffa1ed ⇈00000000ffffa1ed
stampKind: i32
value: int[-24083|0xffffffffffffa1ed]
=== Inputs ===
=== Succesors ===
=== Usages ===
i210 
=== Predecessor ===
- >@ <|@
instruction <@Constant|@org.graalvm.compiler.nodes.ConstantNode>@  <|@  <|@
f <@*|@fixed>@ <|@
tid v215 <|@
d <@d|@=== Debug Properties ===
stamp: void
=== Inputs ===
=== Succesors ===
=== Usages ===
v207 
=== Predecessor ===
v146 >@ <|@
instruction <@EndNode|@org.graalvm.compiler.nodes.EndNode>@  <|@  <|@
    end_IR
    begin_IR
      LIR
      nr   -1  <|@ instruction [] = LABEL numbPhis: 0 align: false label: ? <|@ <|@
      nr   -1  <|@ instruction JUMP ~[int[-24083|0xffffffffffffa1ed]] destination: B7 -> B15 <|@ <|@
    end_IR
  end_block
  begin_block
    name "B8"
    from_bci -1
    to_bci -1
    predecessors "B6" 
    successors "B13" 
    xhandlers
    flags 
    probability 4605323991996384095
    begin_IR
      HIR
f <@#|@fixed with next>@ <|@
tid v144 <|@
d <@d|@=== Debug Properties ===
nodeSourcePosition: at java.util.SubList.<init>(AbstractList.java:621) [bci: 40]
stamp: void
=== Inputs ===
=== Succesors ===
next: v67 
=== Usages ===
=== Predecessor ===
v147 >@ <|@
instruction <@Begin|@org.graalvm.compiler.nodes.BeginNode>@ #next: v67  <|@  <|@
f <@*|@fixed>@ <|@
tid v67 <|@
d <@d|@=== Debug Properties ===
stamp: void
=== Inputs ===
=== Succesors ===
=== Usages ===
v65 
=== Predecessor ===
v144 >@ <|@
instruction <@EndNode|@org.graalvm.compiler.nodes.EndNode>@  <|@  <|@
    end_IR
    begin_IR
      LIR
      nr   -1  <|@ instruction [] = LABEL numbPhis: 0 align: false label: ? <|@ <|@
      nr   -1  <|@ instruction JUMP ~[] destination: B8 -> B13 <|@ <|@
    end_IR
  end_block
  begin_block
    name "B9"
    from_bci -1
    to_bci -1
    predecessors "B5" 
    successors "B10" "B14" 
    xhandlers
    flags 
    probability 4596601727505068676
    begin_IR
      HIR
f <@#|@fixed with next>@ <|@
tid v45 <|@
d <@d|@=== Debug Properties ===
nodeSourcePosition: at java.util.SubList.<init>(AbstractList.java:621) [bci: 37]
stamp: void
=== Inputs ===
=== Succesors ===
next: v151 
=== Usages ===
=== Predecessor ===
v46 >@ <|@
instruction <@Begin|@org.graalvm.compiler.nodes.BeginNode>@ #next: v151  <|@  <|@
f <@~|@floating>@ <|@
tid v236 <|@
result meta{HotSpotType<Lorg/graalvm/compiler/graph/NodeInputList;, resolved>;compressed} <|@
d <@d|@=== Debug Properties ===
isDefaultStable: false
nodeSourcePosition: at org.graalvm.compiler.hotspot.replacements.InstanceOfSnippets.instanceofExact(InstanceOfSnippets.java:143) [bci: 50]
at java.util.SubList.<init>(AbstractList.java:621) [bci: 37]
rawvalue: meta{HotSpotType<Lorg/graalvm/compiler/graph/NodeInputList;, resolved>;compressed}
stableDimension: 0
stamp: Klass*!(compressed base: 0 shift: 3)
stampKind: Klass*(compressed base: 0 shift: 3)
value: meta{HotSpotType<Lorg/graalvm/compiler/graph/NodeInputList;, resolved>;compressed}
=== Inputs ===
=== Succesors ===
=== Usages ===
v237 
=== Predecessor ===
- >@ <|@
instruction <@Constant|@org.graalvm.compiler.nodes.ConstantNode>@  <|@  <|@
f <@~|@floating>@ <|@
tid v237 <|@
d <@d|@=== Debug Properties ===
condition: EQ
nodeSourcePosition: at org.graalvm.compiler.hotspot.replacements.InstanceOfSnippets.instanceofExact(InstanceOfSnippets.java:143) [bci: 50]
at java.util.SubList.<init>(AbstractList.java:621) [bci: 37]
stamp: void
unorderedIsTrue: false
=== Inputs ===
x: v238 
y: v236 
=== Succesors ===
=== Usages ===
v151 
=== Predecessor ===
- >@ <|@
instruction <@==|@org.graalvm.compiler.nodes.calc.PointerEqualsNode>@ x: v238 y: v236  <|@  <|@
f <@*|@fixed>@ <|@
tid v151 <|@
d <@d|@=== Debug Properties ===
nodeSourcePosition: dispatchedType=Lorg/graalvm/compiler/graph/NodeInputList; target_method=size target_method_class=Lorg/graalvm/compiler/graph/NodeList; position=at java.util.SubList.<init>(AbstractList.java:621) [bci: 37]
stamp: void
trueSuccessorProbability: 1.0
=== Inputs ===
condition: v237 
=== Succesors ===
trueSuccessor: v148 
falseSuccessor: v150 
=== Usages ===
=== Predecessor ===
v45 >@ <|@
instruction <@If|@org.graalvm.compiler.nodes.IfNode>@ condition: v237 #trueSuccessor: v148 #falseSuccessor: v150  <|@  <|@
    end_IR
    begin_IR
      LIR
      nr   -1  <|@ instruction [] = LABEL numbPhis: 0 align: false label: ? <|@ <|@
      nr   -1  <|@ instruction CMP v5|DWORD y: -559030611 size: DWORD c: meta{HotSpotType<Lorg/graalvm/compiler/graph/NodeInputList;, resolved>;compressed} <|@ <|@
      nr   -1  <|@ instruction BRANCH trueDestinationProbability: 1.0 condition: = trueDestination: B9 -> B10 falseDestination: B9 -> B14 <|@ <|@
    end_IR
  end_block
  begin_block
    name "B10"
    from_bci -1
    to_bci -1
    predecessors "B9" 
    successors "B11" "B12" 
    xhandlers
    flags 
    probability 4596601727505068676
    begin_IR
      HIR
f <@#|@fixed with next>@ <|@
tid v148 <|@
d <@d|@=== Debug Properties ===
nodeSourcePosition: dispatchedType=Lorg/graalvm/compiler/graph/NodeInputList; target_method=size target_method_class=Lorg/graalvm/compiler/graph/NodeList; position=at java.util.SubList.<init>(AbstractList.java:621) [bci: 37]
stamp: void
=== Inputs ===
=== Succesors ===
next: i241 
=== Usages ===
=== Predecessor ===
v151 >@ <|@
instruction <@Begin|@org.graalvm.compiler.nodes.BeginNode>@ #next: i241  <|@  <|@
f <@#|@fixed with next>@ <|@
tid i241 <|@
result INTERIOR_MATCH <|@
d <@d|@=== Debug Properties ===
barrierType: NONE
forceFixed: false
location: NodeList.size
nodeSourcePosition: at org.graalvm.compiler.graph.NodeList.size(NodeList.java:119) [bci: 1]
at java.util.SubList.<init>(AbstractList.java:621) [bci: 37]
nullCheck: false
stamp: i32
=== Inputs ===
stateBefore: - 
guard: - 
address: v244 
=== Succesors ===
next: v155 
=== Usages ===
v15 
=== Predecessor ===
v148 >@ <|@
instruction <@Read|@org.graalvm.compiler.nodes.memory.ReadNode>@ stateBefore: - guard: - address: v244 #next: v155  <|@  <|@
f <@~|@floating>@ <|@
tid v15 <|@
result INTERIOR_MATCH <|@
d <@d|@=== Debug Properties ===
condition: LT
nodeSourcePosition: at java.util.SubList.<init>(AbstractList.java:621) [bci: 40]
op: org.graalvm.compiler.nodes.calc.IntegerLessThanNode$LessThanOp@7cc8d043
stamp: void
unorderedIsTrue: false
=== Inputs ===
x: i241 
y: i4 
=== Succesors ===
=== Usages ===
v155 
=== Predecessor ===
- >@ <|@
instruction <@<|@org.graalvm.compiler.nodes.calc.IntegerLessThanNode>@ x: i241 y: i4  <|@  <|@
f <@*|@fixed>@ <|@
tid v155 <|@
result org.graalvm.compiler.core.match.ComplexMatchValue@d98b27eb <|@
d <@d|@=== Debug Properties ===
nodeSourcePosition: at java.util.SubList.<init>(AbstractList.java:621) [bci: 40]
stamp: void
trueSuccessorProbability: 0.0
=== Inputs ===
condition: v15 
=== Succesors ===
trueSuccessor: v154 
falseSuccessor: v152 
=== Usages ===
=== Predecessor ===
i241 >@ <|@
instruction <@If|@org.graalvm.compiler.nodes.IfNode>@ condition: v15 #trueSuccessor: v154 #falseSuccessor: v152  <|@  <|@
    end_IR
    begin_IR
      LIR
      nr   -1  <|@ instruction [] = LABEL numbPhis: 0 align: false label: ? <|@ <|@
      nr   -1  <|@ instruction CMP (x: v3|DWORD, y: [v1|QWORD[.] + 16]) size: DWORD <|@ <|@
      nr   -1  <|@ instruction BRANCH trueDestinationProbability: 0.0 condition: > trueDestination: B10 -> B11 falseDestination: B10 -> B12 <|@ <|@
    end_IR
  end_block
  begin_block
    name "B11"
    from_bci -1
    to_bci -1
    predecessors "B10" 
    successors "B15" 
    xhandlers
    flags 
    probability 2355382605114769408
    begin_IR
      HIR
f <@#|@fixed with next>@ <|@
tid v154 <|@
d <@d|@=== Debug Properties ===
nodeSourcePosition: at java.util.SubList.<init>(AbstractList.java:621) [bci: 40]
stamp: void
=== Inputs ===
=== Succesors ===
next: v213 
=== Usages ===
=== Predecessor ===
v155 >@ <|@
instruction <@Begin|@org.graalvm.compiler.nodes.BeginNode>@ #next: v213  <|@  <|@
f <@~|@floating>@ <|@
tid i214 <|@
result int[-28691|0xffffffffffff8fed] <|@
d <@d|@=== Debug Properties ===
isDefaultStable: false
rawvalue: -28691
stableDimension: 0
stamp: i32 [-28691] ⇊00000000ffff8fed ⇈00000000ffff8fed
stampKind: i32
value: int[-28691|0xffffffffffff8fed]
=== Inputs ===
=== Succesors ===
=== Usages ===
i210 
=== Predecessor ===
- >@ <|@
instruction <@Constant|@org.graalvm.compiler.nodes.ConstantNode>@  <|@  <|@
f <@*|@fixed>@ <|@
tid v213 <|@
d <@d|@=== Debug Properties ===
stamp: void
=== Inputs ===
=== Succesors ===
=== Usages ===
v207 
=== Predecessor ===
v154 >@ <|@
instruction <@EndNode|@org.graalvm.compiler.nodes.EndNode>@  <|@  <|@
    end_IR
    begin_IR
      LIR
      nr   -1  <|@ instruction [] = LABEL numbPhis: 0 align: false label: ? <|@ <|@
      nr   -1  <|@ instruction JUMP ~[int[-28691|0xffffffffffff8fed]] destination: B11 -> B15 <|@ <|@
    end_IR
  end_block
  begin_block
    name "B12"
    from_bci -1
    to_bci -1
    predecessors "B10" 
    successors "B13" 
    xhandlers
    flags 
    probability 4596601727505068676
    begin_IR
      HIR
f <@#|@fixed with next>@ <|@
tid v152 <|@
d <@d|@=== Debug Properties ===
nodeSourcePosition: at java.util.SubList.<init>(AbstractList.java:621) [bci: 40]
stamp: void
=== Inputs ===
=== Succesors ===
next: v64 
=== Usages ===
=== Predecessor ===
v155 >@ <|@
instruction <@Begin|@org.graalvm.compiler.nodes.BeginNode>@ #next: v64  <|@  <|@
f <@*|@fixed>@ <|@
tid v64 <|@
d <@d|@=== Debug Properties ===
stamp: void
=== Inputs ===
=== Succesors ===
=== Usages ===
v65 
=== Predecessor ===
v152 >@ <|@
instruction <@EndNode|@org.graalvm.compiler.nodes.EndNode>@  <|@  <|@
    end_IR
    begin_IR
      LIR
      nr   -1  <|@ instruction [] = LABEL numbPhis: 0 align: false label: ? <|@ <|@
      nr   -1  <|@ instruction JUMP ~[] destination: B12 -> B13 <|@ <|@
    end_IR
  end_block
  begin_block
    name "B13"
    from_bci -1
    to_bci -1
    predecessors "B12" "B8" 
    successors 
    xhandlers
    flags 
    probability 4607182418800017408
    begin_IR
      HIR
f <@#|@fixed with next>@ <|@
tid v65 <|@
d <@d|@=== Debug Properties ===
stamp: void
=== Inputs ===
stateAfter: - 
ends: v64 v67 
=== Succesors ===
next: v114 
=== Usages ===
=== Predecessor ===
- >@ <|@
instruction <@Merge|@org.graalvm.compiler.nodes.MergeNode>@ stateAfter: - ends: v64 v67 #next: v114  <|@  <|@
f <@~|@floating>@ <|@
tid v246 <|@
result [v0|QWORD[.] + 24] <|@
d <@d|@=== Debug Properties ===
displacement: 24
scale: Times1
stamp: void*
=== Inputs ===
base: a1 
index: - 
=== Succesors ===
=== Usages ===
v114 
=== Predecessor ===
- >@ <|@
instruction <@AMD64Address|@org.graalvm.compiler.core.amd64.AMD64AddressNode>@ base: a1 index: -  <|@  <|@
f <@~|@floating>@ <|@
tid a96 <|@
result v7|DWORD[.] <|@
d <@d|@=== Debug Properties ===
encoding: base: 0 shift: 3
nodeSourcePosition: at java.util.SubList.<init>(AbstractList.java:626) [bci: 118]
op: Compress
stamp: n Ljava/util/AbstractList;
=== Inputs ===
value: a2 
=== Succesors ===
=== Usages ===
v114 
=== Predecessor ===
- >@ <|@
instruction <@HotSpotCompression|@org.graalvm.compiler.hotspot.nodes.HotSpotCompressionNode>@ value: a2  <|@  <|@
f <@#|@fixed with next>@ <|@
tid v114 <|@
d <@d|@=== Debug Properties ===
barrierType: IMPRECISE
location: SubList.l
nodeSourcePosition: at java.util.SubList.<init>(AbstractList.java:626) [bci: 118]
nullCheck: false
stamp: void
=== Inputs ===
stateBefore: - 
guard: - 
address: v246 
value: a96 
stateAfter: - 
lastLocationAccess: - 
=== Succesors ===
next: j224 
=== Usages ===
=== Predecessor ===
v65 >@ <|@
instruction <@Write|@org.graalvm.compiler.nodes.memory.WriteNode>@ stateBefore: - guard: - address: v246 value: a96 stateAfter: - lastLocationAccess: - #next: j224  <|@  <|@
f <@#|@fixed with next>@ <|@
tid j224 <|@
result v0|QWORD[.] <|@
d <@d|@=== Debug Properties ===
nodeSourcePosition: at org.graalvm.compiler.hotspot.replacements.WriteBarrierSnippets.serialImpreciseWriteBarrier(WriteBarrierSnippets.java:144) [bci: 1]
at java.util.SubList.<init>(AbstractList.java:626) [bci: 118]
stamp: i64
trackedPointer: true
=== Inputs ===
input: a1 
=== Succesors ===
next: v230 
=== Usages ===
j226 
=== Predecessor ===
v114 >@ <|@
instruction <@WordCast|@org.graalvm.compiler.word.WordCastNode>@ input: a1 #next: v230  <|@  <|@
f <@~|@floating>@ <|@
tid i225 <|@
result int[9|0x9] <|@
d <@d|@=== Debug Properties ===
isDefaultStable: false
nodeSourcePosition: at org.graalvm.compiler.hotspot.replacements.HotSpotReplacementsUtil.cardTableShift(GraalHotSpotVMConfig) [bci: -1]
at org.graalvm.compiler.hotspot.replacements.WriteBarrierSnippets.serialWriteBarrier(WriteBarrierSnippets.java:134) [bci: 15]
at org.graalvm.compiler.hotspot.replacements.WriteBarrierSnippets.serialImpreciseWriteBarrier(WriteBarrierSnippets.java:144) [bci: 5]
at java.util.SubList.<init>(AbstractList.java:626) [bci: 118]
rawvalue: 9
stableDimension: 0
stamp: i32 [9] ⇊0000000000000009 ⇈0000000000000009
stampKind: i32
value: int[9|0x9]
=== Inputs ===
=== Succesors ===
=== Usages ===
j226 
=== Predecessor ===
- >@ <|@
instruction <@Constant|@org.graalvm.compiler.nodes.ConstantNode>@  <|@  <|@
f <@~|@floating>@ <|@
tid j226 <|@
result v8|QWORD[*] <|@
d <@d|@=== Debug Properties ===
getOp: org.graalvm.compiler.nodes.calc.UnsignedRightShiftNode$$Lambda$68/774788493@3e7195e9
nodeSourcePosition: at org.graalvm.compiler.hotspot.replacements.WriteBarrierSnippets.serialWriteBarrier(WriteBarrierSnippets.java:134) [bci: 18]
at org.graalvm.compiler.hotspot.replacements.WriteBarrierSnippets.serialImpreciseWriteBarrier(WriteBarrierSnippets.java:144) [bci: 5]
at java.util.SubList.<init>(AbstractList.java:626) [bci: 118]
stamp: i64 [0 - 36028797018963967] ⇈007fffffffffffff
=== Inputs ===
x: j224 
y: i225 
=== Succesors ===
=== Usages ===
v251 
=== Predecessor ===
- >@ <|@
instruction <@>>>|@org.graalvm.compiler.nodes.calc.UnsignedRightShiftNode>@ x: j224 y: i225  <|@  <|@
f <@~|@floating>@ <|@
tid j229 <|@
result v9|QWORD <|@
d <@d|@=== Debug Properties ===
isDefaultStable: false
nodeSourcePosition: at org.graalvm.compiler.hotspot.nodes.GraalHotSpotVMConfigNode.loadLongConfigValue(int) [bci: -1]
at org.graalvm.compiler.hotspot.nodes.GraalHotSpotVMConfigNode.cardTableAddress(GraalHotSpotVMConfigNode.java:114) [bci: 6]
at org.graalvm.compiler.hotspot.replacements.WriteBarrierSnippets.serialWriteBarrier(WriteBarrierSnippets.java:133) [bci: 7]
at org.graalvm.compiler.hotspot.replacements.WriteBarrierSnippets.serialImpreciseWriteBarrier(WriteBarrierSnippets.java:144) [bci: 5]
at java.util.SubList.<init>(AbstractList.java:626) [bci: 118]
rawvalue: 4682670080
stableDimension: 0
stamp: i64 [4682670080] ⇊00000001171be000 ⇈00000001171be000
stampKind: i64
value: long[4682670080|0x1171be000]
=== Inputs ===
=== Succesors ===
=== Usages ===
v251 
=== Predecessor ===
- >@ <|@
instruction <@Constant|@org.graalvm.compiler.nodes.ConstantNode>@  <|@  <|@
f <@~|@floating>@ <|@
tid v251 <|@
result [v8|QWORD[*] + v9|QWORD * 1] <|@
d <@d|@=== Debug Properties ===
displacement: 0
scale: Times1
stamp: void*
=== Inputs ===
base: j226 
index: j229 
=== Succesors ===
=== Usages ===
v230 
=== Predecessor ===
- >@ <|@
instruction <@AMD64Address|@org.graalvm.compiler.core.amd64.AMD64AddressNode>@ base: j226 index: j229  <|@  <|@
f <@~|@floating>@ <|@
tid i231 <|@
result byte[0|0x0] <|@
d <@d|@=== Debug Properties ===
isDefaultStable: false
nodeSourcePosition: at org.graalvm.compiler.hotspot.replacements.WriteBarrierSnippets.serialWriteBarrier(WriteBarrierSnippets.java:138) [bci: 66]
at org.graalvm.compiler.hotspot.replacements.WriteBarrierSnippets.serialImpreciseWriteBarrier(WriteBarrierSnippets.java:144) [bci: 5]
at java.util.SubList.<init>(AbstractList.java:626) [bci: 118]
rawvalue: 0
stableDimension: 0
stamp: i8 [0] ⇈0000000000000000
stampKind: i8
value: byte[0|0x0]
=== Inputs ===
=== Succesors ===
=== Usages ===
v230 
=== Predecessor ===
- >@ <|@
instruction <@Constant|@org.graalvm.compiler.nodes.ConstantNode>@  <|@  <|@
f <@#|@fixed with next>@ <|@
tid v230 <|@
d <@d|@=== Debug Properties ===
barrierType: NONE
location: GC-Card
nodeSourcePosition: at org.graalvm.compiler.hotspot.replacements.WriteBarrierSnippets.serialWriteBarrier(WriteBarrierSnippets.java:138) [bci: 66]
at org.graalvm.compiler.hotspot.replacements.WriteBarrierSnippets.serialImpreciseWriteBarrier(WriteBarrierSnippets.java:144) [bci: 5]
at java.util.SubList.<init>(AbstractList.java:626) [bci: 118]
nullCheck: false
stamp: void
=== Inputs ===
stateBefore: - 
guard: - 
address: v251 
value: i231 
stateAfter: - 
lastLocationAccess: - 
=== Succesors ===
next: v115 
=== Usages ===
=== Predecessor ===
j224 >@ <|@
instruction <@Write|@org.graalvm.compiler.nodes.memory.WriteNode>@ stateBefore: - guard: - address: v251 value: i231 stateAfter: - lastLocationAccess: - #next: v115  <|@  <|@
f <@~|@floating>@ <|@
tid v247 <|@
result [v0|QWORD[.] + 16] <|@
d <@d|@=== Debug Properties ===
displacement: 16
scale: Times1
stamp: void*
=== Inputs ===
base: a1 
index: - 
=== Succesors ===
=== Usages ===
v115 
=== Predecessor ===
- >@ <|@
instruction <@AMD64Address|@org.graalvm.compiler.core.amd64.AMD64AddressNode>@ base: a1 index: -  <|@  <|@
f <@#|@fixed with next>@ <|@
tid v115 <|@
d <@d|@=== Debug Properties ===
barrierType: NONE
location: SubList.offset
nodeSourcePosition: at java.util.SubList.<init>(AbstractList.java:627) [bci: 123]
nullCheck: false
stamp: void
=== Inputs ===
stateBefore: - 
guard: - 
address: v247 
value: i3 
stateAfter: - 
lastLocationAccess: - 
=== Succesors ===
next: v116 
=== Usages ===
=== Predecessor ===
v230 >@ <|@
instruction <@Write|@org.graalvm.compiler.nodes.memory.WriteNode>@ stateBefore: - guard: - address: v247 value: i3 stateAfter: - lastLocationAccess: - #next: v116  <|@  <|@
f <@~|@floating>@ <|@
tid v248 <|@
result [v0|QWORD[.] + 20] <|@
d <@d|@=== Debug Properties ===
displacement: 20
scale: Times1
stamp: void*
=== Inputs ===
base: a1 
index: - 
=== Succesors ===
=== Usages ===
v116 
=== Predecessor ===
- >@ <|@
instruction <@AMD64Address|@org.graalvm.compiler.core.amd64.AMD64AddressNode>@ base: a1 index: -  <|@  <|@
f <@~|@floating>@ <|@
tid i23 <|@
result v10|DWORD <|@
d <@d|@=== Debug Properties ===
getOp: org.graalvm.compiler.nodes.calc.SubNode$$Lambda$64/1952983589@24889bdf
nodeSourcePosition: at java.util.SubList.<init>(AbstractList.java:628) [bci: 129]
stamp: i32
=== Inputs ===
x: i4 
y: i3 
=== Succesors ===
=== Usages ===
v116 
=== Predecessor ===
- >@ <|@
instruction <@-|@org.graalvm.compiler.nodes.calc.SubNode>@ x: i4 y: i3  <|@  <|@
f <@#|@fixed with next>@ <|@
tid v116 <|@
d <@d|@=== Debug Properties ===
barrierType: NONE
location: SubList.size
nodeSourcePosition: at java.util.SubList.<init>(AbstractList.java:628) [bci: 130]
nullCheck: false
stamp: void
=== Inputs ===
stateBefore: - 
guard: - 
address: v248 
value: i23 
stateAfter: - 
lastLocationAccess: - 
=== Succesors ===
next: i242 
=== Usages ===
=== Predecessor ===
v115 >@ <|@
instruction <@Write|@org.graalvm.compiler.nodes.memory.WriteNode>@ stateBefore: - guard: - address: v248 value: i23 stateAfter: - lastLocationAccess: - #next: i242  <|@  <|@
f <@~|@floating>@ <|@
tid v249 <|@
result [v1|QWORD[.] + 12] <|@
d <@d|@=== Debug Properties ===
displacement: 12
scale: Times1
stamp: void*
=== Inputs ===
base: a2 
index: - 
=== Succesors ===
=== Usages ===
i242 
=== Predecessor ===
- >@ <|@
instruction <@AMD64Address|@org.graalvm.compiler.core.amd64.AMD64AddressNode>@ base: a2 index: -  <|@  <|@
f <@#|@fixed with next>@ <|@
tid i242 <|@
result v11|DWORD <|@
d <@d|@=== Debug Properties ===
barrierType: NONE
forceFixed: false
location: AbstractList.modCount
nodeSourcePosition: at java.util.SubList.<init>(AbstractList.java:629) [bci: 138]
nullCheck: false
stamp: i32
=== Inputs ===
stateBefore: - 
guard: - 
address: v249 
=== Succesors ===
next: v118 
=== Usages ===
v118 
=== Predecessor ===
v116 >@ <|@
instruction <@Read|@org.graalvm.compiler.nodes.memory.ReadNode>@ stateBefore: - guard: - address: v249 #next: v118  <|@  <|@
f <@#|@fixed with next>@ <|@
tid v118 <|@
d <@d|@=== Debug Properties ===
barrierType: NONE
location: AbstractList.modCount
nodeSourcePosition: at java.util.SubList.<init>(AbstractList.java:629) [bci: 141]
nullCheck: false
stamp: void
=== Inputs ===
stateBefore: - 
guard: - 
address: v243 
value: i242 
stateAfter: - 
lastLocationAccess: - 
=== Succesors ===
next: v84 
=== Usages ===
=== Predecessor ===
i242 >@ <|@
instruction <@Write|@org.graalvm.compiler.nodes.memory.WriteNode>@ stateBefore: - guard: - address: v243 value: i242 stateAfter: - lastLocationAccess: - #next: v84  <|@  <|@
f <@#|@fixed with next>@ <|@
tid v84 <|@
d <@d|@=== Debug Properties ===
barriers: 10
location: ANY_LOCATION
nodeSourcePosition: at java.util.SubList.<init>(AbstractList.java:630) [bci: 144]
stamp: void
=== Inputs ===
=== Succesors ===
next: v31 
=== Usages ===
=== Predecessor ===
v118 >@ <|@
instruction <@Membar|@org.graalvm.compiler.nodes.extended.MembarNode>@ #next: v31  <|@  <|@
f <@*|@fixed>@ <|@
tid v31 <|@
d <@d|@=== Debug Properties ===
nodeSourcePosition: at java.util.SubList.<init>(AbstractList.java:630) [bci: 144]
stamp: void
=== Inputs ===
result: - 
memoryMap: - 
=== Succesors ===
=== Usages ===
=== Predecessor ===
v84 >@ <|@
instruction <@Return|@org.graalvm.compiler.nodes.ReturnNode>@ result: - memoryMap: -  <|@  <|@
    end_IR
    begin_IR
      LIR
      nr   -1  <|@ instruction [] = LABEL numbPhis: 0 align: false label: ? <|@ <|@
      nr   -1  <|@ instruction v7|DWORD[.] = COMPRESSPOINTER (input: v1|QWORD[.], ~baseRegister: r12|ILLEGAL) nonNull: false lirKindTool: com.oracle.graal.enterprise.z.a@2c336164 encoding: base: 0 shift: 3 <|@ <|@
      nr   -1  <|@ instruction MOV (x: [v0|QWORD[.] + 24], y: v7|DWORD[.]) size: DWORD <|@ <|@
      nr   -1  <|@ instruction v8|QWORD[*] = SHR v0|QWORD[.] y: 9 size: QWORD <|@ <|@
      nr   -1  <|@ instruction v9|QWORD = MOVE input: long[4682670080|0x1171be000] <|@ <|@
      nr   -1  <|@ instruction MOVB (x: [v8|QWORD[*] + v9|QWORD * 1], y: r12|ILLEGAL) size: BYTE <|@ <|@
      nr   -1  <|@ instruction MOV (x: [v0|QWORD[.] + 16], y: v2|DWORD) size: DWORD <|@ <|@
      nr   -1  <|@ instruction v10|DWORD = SUB (x: v3|DWORD, ~y: v2|DWORD) size: DWORD <|@ <|@
      nr   -1  <|@ instruction MOV (x: [v0|QWORD[.] + 20], y: v10|DWORD) size: DWORD <|@ <|@
      nr   -1  <|@ instruction v11|DWORD = MOV [v1|QWORD[.] + 12] size: DWORD <|@ <|@
      nr   -1  <|@ instruction MOV (x: [v0|QWORD[.] + 12], y: v11|DWORD) size: DWORD <|@ <|@
      nr   -1  <|@ instruction RETURN (savedRbp: stack:16|QWORD, value: -) isStub: false thread: r15 scratchForSafepointOnReturn: rcx config: org.graalvm.compiler.hotspot.GraalHotSpotVMConfig@7222fe45 <|@ <|@
    end_IR
  end_block
  begin_block
    name "B14"
    from_bci -1
    to_bci -1
    predecessors "B9" 
    successors "B15" 
    xhandlers
    flags 
    probability 2355382605114769408
    begin_IR
      HIR
f <@#|@fixed with next>@ <|@
tid v150 <|@
d <@d|@=== Debug Properties ===
nodeSourcePosition: dispatchedType=Lorg/graalvm/compiler/graph/NodeInputList; target_method=size target_method_class=Lorg/graalvm/compiler/graph/NodeList; position=at java.util.SubList.<init>(AbstractList.java:621) [bci: 37]
stamp: void
=== Inputs ===
=== Succesors ===
next: v217 
=== Usages ===
=== Predecessor ===
v151 >@ <|@
instruction <@Begin|@org.graalvm.compiler.nodes.BeginNode>@ #next: v217  <|@  <|@
f <@~|@floating>@ <|@
tid i218 <|@
result int[-27955|0xffffffffffff92cd] <|@
d <@d|@=== Debug Properties ===
isDefaultStable: false
rawvalue: -27955
stableDimension: 0
stamp: i32 [-27955] ⇊00000000ffff92cd ⇈00000000ffff92cd
stampKind: i32
value: int[-27955|0xffffffffffff92cd]
=== Inputs ===
=== Succesors ===
=== Usages ===
i210 
=== Predecessor ===
- >@ <|@
instruction <@Constant|@org.graalvm.compiler.nodes.ConstantNode>@  <|@  <|@
f <@*|@fixed>@ <|@
tid v217 <|@
d <@d|@=== Debug Properties ===
stamp: void
=== Inputs ===
=== Succesors ===
=== Usages ===
v207 
=== Predecessor ===
v150 >@ <|@
instruction <@EndNode|@org.graalvm.compiler.nodes.EndNode>@  <|@  <|@
    end_IR
    begin_IR
      LIR
      nr   -1  <|@ instruction [] = LABEL numbPhis: 0 align: false label: ? <|@ <|@
      nr   -1  <|@ instruction JUMP ~[int[-27955|0xffffffffffff92cd]] destination: B14 -> B15 <|@ <|@
    end_IR
  end_block
  begin_block
    name "B15"
    from_bci -1
    to_bci -1
    predecessors "B11" "B7" "B14" 
    successors 
    xhandlers
    flags 
    probability 2362138004555825152
    begin_IR
      HIR
f <@~|@floating>@ <|@
tid i210 <|@
result v12|DWORD <|@
d <@d|@=== Debug Properties ===
stamp: i32 [-28691 - -23051] ⇊00000000ffff80c5 ⇈00000000ffffbffd
valueDescription: i32
=== Inputs ===
merge: v207 
values: i214 i216 i218 
=== Succesors ===
=== Usages ===
v212 
=== Predecessor ===
- >@ <|@
instruction <@ValuePhi|@org.graalvm.compiler.nodes.ValuePhiNode>@ merge: v207 values: i214 i216 i218  <|@  <|@
f <@#|@fixed with next>@ <|@
tid v207 <|@
d <@d|@=== Debug Properties ===
stamp: void
=== Inputs ===
stateAfter: - 
ends: v213 v215 v217 
=== Succesors ===
next: v212 
=== Usages ===
i210 
=== Predecessor ===
- >@ <|@
instruction <@Merge|@org.graalvm.compiler.nodes.MergeNode>@ stateAfter: - ends: v213 v215 v217 #next: v212  <|@  <|@
f <@*|@fixed>@ <|@
tid v212 <|@
d <@d|@=== Debug Properties ===
stamp: void
=== Inputs ===
stateBefore: ?9 
actionAndReason: i210 
speculation: a199 
=== Succesors ===
=== Usages ===
=== Predecessor ===
v207 >@ <|@
instruction <@DynamicDeoptimize|@org.graalvm.compiler.nodes.DynamicDeoptimizeNode>@ stateBefore: ?9 actionAndReason: i210 speculation: a199  <|@  <|@
    end_IR
    begin_IR
      LIR
      nr   -1  <|@ instruction [v12|DWORD] = LABEL numbPhis: 1 align: false label: ? <|@ <|@
      nr   -1  <|@ instruction MOV (x: [r15|QWORD + 668], y: v12|DWORD) size: DWORD <|@ <|@
      nr   -1  <|@ instruction MOV (x: [r15|QWORD + 680], y: r12|ILLEGAL) size: QWORD <|@ <|@
      nr   -1  <|@ st <@st|@java.util.AbstractList.<init>(AbstractList.java:77) [bci: 9]
locals: v0|QWORD[.] 
java.util.SubList.<init>(AbstractList.java:618) [bci: 1]
locals: v0|QWORD[.] v1|QWORD[.] v2|DWORD v3|DWORD 
>@ <|@ instruction DEOPT info [bci:9, 1] <|@ <|@
    end_IR
  end_block
end_cfg
begin_cfg
  name "After PreAllocationOptimizationStage"
  begin_block
    name "B0"
    from_bci -1
    to_bci -1
    predecessors 
    successors "B1" "B2" 
    xhandlers
    flags 
    probability 4607182418800017408
    begin_IR
      LIR
      nr   -1  <|@ instruction [rsi|QWORD[.], rdx|QWORD[.], rcx|DWORD, r8|DWORD, rbp|QWORD] = LABEL numbPhis: 0 align: false label: ? <|@ <|@
      nr   -1  <|@ instruction stack:16|QWORD = MOVE rbp|QWORD moveKind: QWORD <|@ <|@
      nr   -1  <|@ instruction [] = HOTSPOTLOCKSTACK frameMapBuilder: org.graalvm.compiler.lir.amd64.AMD64FrameMapBuilder@3c736a5f slotKind: QWORD <|@ <|@
      nr   -1  <|@ instruction v0|QWORD[.] = MOVE rsi|QWORD[.] moveKind: QWORD <|@ <|@
      nr   -1  <|@ instruction v1|QWORD[.] = MOVE rdx|QWORD[.] moveKind: QWORD <|@ <|@
      nr   -1  <|@ instruction v2|DWORD = MOVE rcx|DWORD moveKind: DWORD <|@ <|@
      nr   -1  <|@ instruction v3|DWORD = MOVE r8|DWORD moveKind: DWORD <|@ <|@
      nr   -1  <|@ instruction TEST (x: v2|DWORD, y: v2|DWORD) size: DWORD <|@ <|@
      nr   -1  <|@ instruction BRANCH trueDestinationProbability: 0.0 condition: < trueDestination: B0 -> B1 falseDestination: B0 -> B2 <|@ <|@
    end_IR
  end_block
  begin_block
    name "B2"
    from_bci -1
    to_bci -1
    predecessors "B0" 
    successors "B3" "B5" 
    xhandlers
    flags 
    probability 4607182418800017408
    begin_IR
      LIR
      nr   -1  <|@ instruction [] = LABEL numbPhis: 0 align: false label: ? <|@ <|@
      nr   -1  <|@ st <@st|@java.util.SubList.<init>(AbstractList.java:618) [bci: 0]
locals: v0|QWORD[.] v1|QWORD[.] v2|DWORD v3|DWORD 
>@ <|@ instruction NULLCHECK [v1|QWORD[.]] state [bci:0] <|@ <|@
      nr   -1  <|@ instruction CMP (x: v2|DWORD, y: v3|DWORD) size: DWORD <|@ <|@
      nr   -1  <|@ instruction BRANCH trueDestinationProbability: 0.0 condition: > trueDestination: B2 -> B3 falseDestination: B2 -> B5 <|@ <|@
    end_IR
  end_block
  begin_block
    name "B5"
    from_bci -1
    to_bci -1
    predecessors "B2" 
    successors "B6" "B9" 
    xhandlers
    flags 
    probability 4607182418800017408
    begin_IR
      LIR
      nr   -1  <|@ instruction [] = LABEL numbPhis: 0 align: false label: ? <|@ <|@
      nr   -1  <|@ instruction MOV (x: [v0|QWORD[.] + 12], y: r12|ILLEGAL) size: DWORD <|@ <|@
      nr   -1  <|@ instruction v5|DWORD = MOV [v1|QWORD[.] + 8] size: DWORD <|@ <|@
      nr   -1  <|@ instruction CMP v5|DWORD y: -559030611 size: DWORD c: meta{HotSpotType<Ljava/util/Arrays$ArrayList;, resolved>;compressed} <|@ <|@
      nr   -1  <|@ instruction BRANCH trueDestinationProbability: 0.7936731773025761 condition: = trueDestination: B5 -> B6 falseDestination: B5 -> B9 <|@ <|@
    end_IR
  end_block
  begin_block
    name "B6"
    from_bci -1
    to_bci -1
    predecessors "B5" 
    successors "B7" "B8" 
    xhandlers
    flags 
    probability 4605323991996384095
    begin_IR
      LIR
      nr   -1  <|@ instruction [] = LABEL numbPhis: 0 align: false label: ? <|@ <|@
      nr   -1  <|@ instruction v6|DWORD[.] = MOV [v1|QWORD[.] + 16] size: DWORD <|@ <|@
      nr   -1  <|@ st <@st|@java.util.AbstractList.<init>(AbstractList.java:77) [bci: 9]
locals: v0|QWORD[.] 
java.util.SubList.<init>(AbstractList.java:618) [bci: 1]
locals: v0|QWORD[.] v1|QWORD[.] v2|DWORD v3|DWORD 
>@ <|@ instruction CMP (x: v3|DWORD, y: [v6|DWORD[.] * 8 + 12]) size: DWORD state [bci:9, 1] <|@ <|@
      nr   -1  <|@ instruction BRANCH trueDestinationProbability: 0.0 condition: > trueDestination: B6 -> B7 falseDestination: B6 -> B8 <|@ <|@
    end_IR
  end_block
  begin_block
    name "B8"
    from_bci -1
    to_bci -1
    predecessors "B6" 
    successors "B13" 
    xhandlers
    flags 
    probability 4605323991996384095
    begin_IR
      LIR
      nr   -1  <|@ instruction [] = LABEL numbPhis: 0 align: false label: ? <|@ <|@
      nr   -1  <|@ instruction JUMP ~[] destination: B8 -> B13 <|@ <|@
    end_IR
  end_block
  begin_block
    name "B13"
    from_bci -1
    to_bci -1
    predecessors "B12" "B8" 
    successors 
    xhandlers
    flags 
    probability 4607182418800017408
    begin_IR
      LIR
      nr   -1  <|@ instruction [] = LABEL numbPhis: 0 align: false label: ? <|@ <|@
      nr   -1  <|@ instruction v7|DWORD[.] = COMPRESSPOINTER (input: v1|QWORD[.], ~baseRegister: r12|ILLEGAL) nonNull: false lirKindTool: com.oracle.graal.enterprise.z.a@2c336164 encoding: base: 0 shift: 3 <|@ <|@
      nr   -1  <|@ instruction MOV (x: [v0|QWORD[.] + 24], y: v7|DWORD[.]) size: DWORD <|@ <|@
      nr   -1  <|@ instruction v8|QWORD[*] = SHR v0|QWORD[.] y: 9 size: QWORD <|@ <|@
      nr   -1  <|@ instruction v9|QWORD = MOVE input: long[4682670080|0x1171be000] <|@ <|@
      nr   -1  <|@ instruction MOVB (x: [v8|QWORD[*] + v9|QWORD * 1], y: r12|ILLEGAL) size: BYTE <|@ <|@
      nr   -1  <|@ instruction MOV (x: [v0|QWORD[.] + 16], y: v2|DWORD) size: DWORD <|@ <|@
      nr   -1  <|@ instruction v10|DWORD = SUB (x: v3|DWORD, ~y: v2|DWORD) size: DWORD <|@ <|@
      nr   -1  <|@ instruction MOV (x: [v0|QWORD[.] + 20], y: v10|DWORD) size: DWORD <|@ <|@
      nr   -1  <|@ instruction v11|DWORD = MOV [v1|QWORD[.] + 12] size: DWORD <|@ <|@
      nr   -1  <|@ instruction MOV (x: [v0|QWORD[.] + 12], y: v11|DWORD) size: DWORD <|@ <|@
      nr   -1  <|@ instruction RETURN (savedRbp: stack:16|QWORD, value: -) isStub: false thread: r15 scratchForSafepointOnReturn: rcx config: org.graalvm.compiler.hotspot.GraalHotSpotVMConfig@7222fe45 <|@ <|@
    end_IR
  end_block
  begin_block
    name "B9"
    from_bci -1
    to_bci -1
    predecessors "B5" 
    successors "B10" "B14" 
    xhandlers
    flags 
    probability 4596601727505068676
    begin_IR
      LIR
      nr   -1  <|@ instruction [] = LABEL numbPhis: 0 align: false label: ? <|@ <|@
      nr   -1  <|@ instruction CMP v5|DWORD y: -559030611 size: DWORD c: meta{HotSpotType<Lorg/graalvm/compiler/graph/NodeInputList;, resolved>;compressed} <|@ <|@
      nr   -1  <|@ instruction BRANCH trueDestinationProbability: 1.0 condition: = trueDestination: B9 -> B10 falseDestination: B9 -> B14 <|@ <|@
    end_IR
  end_block
  begin_block
    name "B10"
    from_bci -1
    to_bci -1
    predecessors "B9" 
    successors "B11" "B12" 
    xhandlers
    flags 
    probability 4596601727505068676
    begin_IR
      LIR
      nr   -1  <|@ instruction [] = LABEL numbPhis: 0 align: false label: ? <|@ <|@
      nr   -1  <|@ instruction CMP (x: v3|DWORD, y: [v1|QWORD[.] + 16]) size: DWORD <|@ <|@
      nr   -1  <|@ instruction BRANCH trueDestinationProbability: 0.0 condition: > trueDestination: B10 -> B11 falseDestination: B10 -> B12 <|@ <|@
    end_IR
  end_block
  begin_block
    name "B12"
    from_bci -1
    to_bci -1
    predecessors "B10" 
    successors "B13" 
    xhandlers
    flags 
    probability 4596601727505068676
    begin_IR
      LIR
      nr   -1  <|@ instruction [] = LABEL numbPhis: 0 align: false label: ? <|@ <|@
      nr   -1  <|@ instruction JUMP ~[] destination: B12 -> B13 <|@ <|@
    end_IR
  end_block
  begin_block
    name "B1"
    from_bci -1
    to_bci -1
    predecessors "B0" 
    successors "B4" 
    xhandlers
    flags 
    probability 2355382605114769408
    begin_IR
      LIR
      nr   -1  <|@ instruction [] = LABEL numbPhis: 0 align: false label: ? <|@ <|@
      nr   -1  <|@ instruction JUMP ~[int[-21011|0xffffffffffffaded]] destination: B1 -> B4 <|@ <|@
    end_IR
  end_block
  begin_block
    name "B4"
    from_bci -1
    to_bci -1
    predecessors "B1" "B3" 
    successors 
    xhandlers
    flags 
    probability 2359886204742139904
    begin_IR
      LIR
      nr   -1  <|@ instruction [v4|DWORD] = LABEL numbPhis: 1 align: false label: ? <|@ <|@
      nr   -1  <|@ instruction MOV (x: [r15|QWORD + 668], y: v4|DWORD) size: DWORD <|@ <|@
      nr   -1  <|@ instruction MOV (x: [r15|QWORD + 680], y: r12|ILLEGAL) size: QWORD <|@ <|@
      nr   -1  <|@ st <@st|@java.util.SubList.<init>(AbstractList.java:618) [bci: 0]
locals: v0|QWORD[.] v1|QWORD[.] v2|DWORD v3|DWORD 
>@ <|@ instruction DEOPT info [bci:0] <|@ <|@
    end_IR
  end_block
  begin_block
    name "B7"
    from_bci -1
    to_bci -1
    predecessors "B6" 
    successors "B15" 
    xhandlers
    flags 
    probability 2355382605114769408
    begin_IR
      LIR
      nr   -1  <|@ instruction [] = LABEL numbPhis: 0 align: false label: ? <|@ <|@
      nr   -1  <|@ instruction JUMP ~[int[-24083|0xffffffffffffa1ed]] destination: B7 -> B15 <|@ <|@
    end_IR
  end_block
  begin_block
    name "B15"
    from_bci -1
    to_bci -1
    predecessors "B11" "B7" "B14" 
    successors 
    xhandlers
    flags 
    probability 2362138004555825152
    begin_IR
      LIR
      nr   -1  <|@ instruction [v12|DWORD] = LABEL numbPhis: 1 align: false label: ? <|@ <|@
      nr   -1  <|@ instruction MOV (x: [r15|QWORD + 668], y: v12|DWORD) size: DWORD <|@ <|@
      nr   -1  <|@ instruction MOV (x: [r15|QWORD + 680], y: r12|ILLEGAL) size: QWORD <|@ <|@
      nr   -1  <|@ st <@st|@java.util.AbstractList.<init>(AbstractList.java:77) [bci: 9]
locals: v0|QWORD[.] 
java.util.SubList.<init>(AbstractList.java:618) [bci: 1]
locals: v0|QWORD[.] v1|QWORD[.] v2|DWORD v3|DWORD 
>@ <|@ instruction DEOPT info [bci:9, 1] <|@ <|@
    end_IR
  end_block
  begin_block
    name "B11"
    from_bci -1
    to_bci -1
    predecessors "B10" 
    successors "B15" 
    xhandlers
    flags 
    probability 2355382605114769408
    begin_IR
      LIR
      nr   -1  <|@ instruction [] = LABEL numbPhis: 0 align: false label: ? <|@ <|@
      nr   -1  <|@ instruction JUMP ~[int[-28691|0xffffffffffff8fed]] destination: B11 -> B15 <|@ <|@
    end_IR
  end_block
  begin_block
    name "B3"
    from_bci -1
    to_bci -1
    predecessors "B2" 
    successors "B4" 
    xhandlers
    flags 
    probability 2355382605114769408
    begin_IR
      LIR
      nr   -1  <|@ instruction [] = LABEL numbPhis: 0 align: false label: ? <|@ <|@
      nr   -1  <|@ instruction JUMP ~[int[-32531|0xffffffffffff80ed]] destination: B3 -> B4 <|@ <|@
    end_IR
  end_block
  begin_block
    name "B14"
    from_bci -1
    to_bci -1
    predecessors "B9" 
    successors "B15" 
    xhandlers
    flags 
    probability 2355382605114769408
    begin_IR
      LIR
      nr   -1  <|@ instruction [] = LABEL numbPhis: 0 align: false label: ? <|@ <|@
      nr   -1  <|@ instruction JUMP ~[int[-27955|0xffffffffffff92cd]] destination: B14 -> B15 <|@ <|@
    end_IR
  end_block
end_cfg
begin_bytecodes
     0: aload_0       
     1: invokespecial #3          // java.util.AbstractList.<init>:()void
     4: iload_2       
     5: ifge          35
     8: new           #5          // java.lang.IndexOutOfBoundsException
    11: dup           
    12: new           #6          // java.lang.StringBuilder
    15: dup           
    16: invokespecial #4          // java.lang.StringBuilder.<init>:()void
    19: ldc           #8          // "fromIndex = "
    21: invokevirtual #5          // java.lang.StringBuilder.append:(java.lang.String)java.lang.StringBuilder
    24: iload_2       
    25: invokevirtual #6          // java.lang.StringBuilder.append:(int)java.lang.StringBuilder
    28: invokevirtual #7          // java.lang.StringBuilder.toString:()java.lang.String
    31: invokespecial #8          // java.lang.IndexOutOfBoundsException.<init>:(java.lang.String)void
    34: athrow        
    35: iload_3       
    36: aload_1       
    37: invokevirtual #9          // java.util.AbstractCollection.size:()int
    40: if_icmple     70
    43: new           #5          // java.lang.IndexOutOfBoundsException
    46: dup           
    47: new           #6          // java.lang.StringBuilder
    50: dup           
    51: invokespecial #4          // java.lang.StringBuilder.<init>:()void
    54: ldc           #14         // "toIndex = "
    56: invokevirtual #5          // java.lang.StringBuilder.append:(java.lang.String)java.lang.StringBuilder
    59: iload_3       
    60: invokevirtual #6          // java.lang.StringBuilder.append:(int)java.lang.StringBuilder
    63: invokevirtual #7          // java.lang.StringBuilder.toString:()java.lang.String
    66: invokespecial #8          // java.lang.IndexOutOfBoundsException.<init>:(java.lang.String)void
    69: athrow        
    70: iload_2       
    71: iload_3       
    72: if_icmple     116
    75: new           #15         // java.lang.IllegalArgumentException
    78: dup           
    79: new           #6          // java.lang.StringBuilder
    82: dup           
    83: invokespecial #4          // java.lang.StringBuilder.<init>:()void
    86: ldc           #16         // "fromIndex("
    88: invokevirtual #5          // java.lang.StringBuilder.append:(java.lang.String)java.lang.StringBuilder
    91: iload_2       
    92: invokevirtual #6          // java.lang.StringBuilder.append:(int)java.lang.StringBuilder
    95: ldc           #17         // ") > toIndex("
    97: invokevirtual #5          // java.lang.StringBuilder.append:(java.lang.String)java.lang.StringBuilder
   100: iload_3       
   101: invokevirtual #6          // java.lang.StringBuilder.append:(int)java.lang.StringBuilder
   104: ldc           #18         // ")"
   106: invokevirtual #5          // java.lang.StringBuilder.append:(java.lang.String)java.lang.StringBuilder
   109: invokevirtual #7          // java.lang.StringBuilder.toString:()java.lang.String
   112: invokespecial #10         // java.lang.IllegalArgumentException.<init>:(java.lang.String)void
   115: athrow        
   116: aload_0       
   117: aload_1       
   118: putfield      #1          // l:java.util.AbstractList
   121: aload_0       
   122: iload_2       
   123: putfield      #2          // offset:int
   126: aload_0       
   127: iload_3       
   128: iload_2       
   129: isub          
   130: putfield      #0          // size:int
   133: aload_0       
   134: aload_0       
   135: getfield      #1          // l:java.util.AbstractList
   138: getfield      #11         // java.util.AbstractList.modCount:int
   141: putfield      #12         // java.util.AbstractList.modCount:int
   144: return        
   <|@
end_bytecodes
begin_cfg
  name "After AllocationStage"
  begin_block
    name "B0"
    from_bci -1
    to_bci -1
    predecessors 
    successors "B1" "B2" 
    xhandlers
    flags 
    probability 4607182418800017408
    begin_IR
      LIR
      nr    0  <|@ instruction [rsi|QWORD[.], rdx|QWORD[.], rcx|DWORD, r8|DWORD, rbp|QWORD] = LABEL numbPhis: 0 align: false label: ? <|@ <|@
      nr    2  <|@ instruction stack:16|QWORD = MOVE rbp|QWORD moveKind: QWORD <|@ <|@
      nr    4  <|@ instruction [] = HOTSPOTLOCKSTACK frameMapBuilder: org.graalvm.compiler.lir.amd64.AMD64FrameMapBuilder@3c736a5f slotKind: QWORD <|@ <|@
      nr   14  <|@ instruction TEST (x: rcx|DWORD, y: rcx|DWORD) size: DWORD <|@ <|@
      nr   16  <|@ instruction BRANCH trueDestinationProbability: 0.0 condition: < trueDestination: B0 -> B1 falseDestination: B0 -> B2 <|@ <|@
    end_IR
  end_block
  begin_block
    name "B2"
    from_bci -1
    to_bci -1
    predecessors "B0" 
    successors "B3" "B5" 
    xhandlers
    flags 
    probability 4607182418800017408
    begin_IR
      LIR
      nr   18  <|@ instruction [] = LABEL numbPhis: 0 align: false label: ? <|@ <|@
      nr   20  <|@ st <@st|@reference-map: [rdx:0, rsi:0]
live-base-pointers: []
java.util.SubList.<init>(AbstractList.java:618) [bci: 0]
locals: rsi|QWORD[.] rdx|QWORD[.] rcx|DWORD r8|DWORD 
>@ <|@ instruction NULLCHECK [rdx|QWORD[.]] state [bci:0] <|@ <|@
      nr   22  <|@ instruction CMP (x: rcx|DWORD, y: r8|DWORD) size: DWORD <|@ <|@
      nr   24  <|@ instruction BRANCH trueDestinationProbability: 0.0 condition: > trueDestination: B2 -> B3 falseDestination: B2 -> B5 <|@ <|@
    end_IR
  end_block
  begin_block
    name "B5"
    from_bci -1
    to_bci -1
    predecessors "B2" 
    successors "B6" "B9" 
    xhandlers
    flags 
    probability 4607182418800017408
    begin_IR
      LIR
      nr   26  <|@ instruction [] = LABEL numbPhis: 0 align: false label: ? <|@ <|@
      nr   28  <|@ instruction MOV (x: [rsi|QWORD[.] + 12], y: r12|ILLEGAL) size: DWORD <|@ <|@
      nr   30  <|@ instruction r10|DWORD = MOV [rdx|QWORD[.] + 8] size: DWORD <|@ <|@
      nr   32  <|@ instruction CMP r10|DWORD y: -559030611 size: DWORD c: meta{HotSpotType<Ljava/util/Arrays$ArrayList;, resolved>;compressed} <|@ <|@
      nr   34  <|@ instruction BRANCH trueDestinationProbability: 0.7936731773025761 condition: = trueDestination: B5 -> B6 falseDestination: B5 -> B9 <|@ <|@
    end_IR
  end_block
  begin_block
    name "B6"
    from_bci -1
    to_bci -1
    predecessors "B5" 
    successors "B7" "B8" 
    xhandlers
    flags 
    probability 4605323991996384095
    begin_IR
      LIR
      nr   36  <|@ instruction [] = LABEL numbPhis: 0 align: false label: ? <|@ <|@
      nr   38  <|@ instruction r10|DWORD[.] = MOV [rdx|QWORD[.] + 16] size: DWORD <|@ <|@
      nr   40  <|@ st <@st|@reference-map: [rdx:0, rsi:0]
live-base-pointers: []
java.util.AbstractList.<init>(AbstractList.java:77) [bci: 9]
locals: rsi|QWORD[.] 
java.util.SubList.<init>(AbstractList.java:618) [bci: 1]
locals: rsi|QWORD[.] rdx|QWORD[.] rcx|DWORD r8|DWORD 
>@ <|@ instruction CMP (x: r8|DWORD, y: [r10|DWORD[.] * 8 + 12]) size: DWORD state [bci:9, 1] <|@ <|@
      nr   42  <|@ instruction BRANCH trueDestinationProbability: 0.0 condition: > trueDestination: B6 -> B7 falseDestination: B6 -> B8 <|@ <|@
    end_IR
  end_block
  begin_block
    name "B8"
    from_bci -1
    to_bci -1
    predecessors "B6" 
    successors "B13" 
    xhandlers
    flags 
    probability 4605323991996384095
    begin_IR
      LIR
      nr   44  <|@ instruction [] = LABEL numbPhis: 0 align: false label: ? <|@ <|@
      nr   46  <|@ instruction JUMP ~[] destination: B8 -> B13 <|@ <|@
    end_IR
  end_block
  begin_block
    name "B13"
    from_bci -1
    to_bci -1
    predecessors "B12" "B8" 
    successors 
    xhandlers
    flags 
    probability 4607182418800017408
    begin_IR
      LIR
      nr   64  <|@ instruction [] = LABEL numbPhis: 0 align: false label: ? <|@ <|@
      nr   66  <|@ instruction r10|DWORD[.] = COMPRESSPOINTER (input: rdx|QWORD[.], ~baseRegister: r12|ILLEGAL) nonNull: false lirKindTool: com.oracle.graal.enterprise.z.a@2c336164 encoding: base: 0 shift: 3 <|@ <|@
      nr   68  <|@ instruction MOV (x: [rsi|QWORD[.] + 24], y: r10|DWORD[.]) size: DWORD <|@ <|@
      nr   70  <|@ instruction r10|QWORD[*] = SHR rsi|QWORD[.] y: 9 size: QWORD <|@ <|@
      nr   72  <|@ instruction r11|QWORD = MOVE input: long[4682670080|0x1171be000] <|@ <|@
      nr   74  <|@ instruction MOVB (x: [r10|QWORD[*] + r11|QWORD * 1], y: r12|ILLEGAL) size: BYTE <|@ <|@
      nr   76  <|@ instruction MOV (x: [rsi|QWORD[.] + 16], y: rcx|DWORD) size: DWORD <|@ <|@
      nr   78  <|@ instruction r8|DWORD = SUB (x: r8|DWORD, ~y: rcx|DWORD) size: DWORD <|@ <|@
      nr   80  <|@ instruction MOV (x: [rsi|QWORD[.] + 20], y: r8|DWORD) size: DWORD <|@ <|@
      nr   82  <|@ instruction r10|DWORD = MOV [rdx|QWORD[.] + 12] size: DWORD <|@ <|@
      nr   84  <|@ instruction MOV (x: [rsi|QWORD[.] + 12], y: r10|DWORD) size: DWORD <|@ <|@
      nr   86  <|@ instruction RETURN (savedRbp: stack:16|QWORD, value: -) isStub: false thread: r15 scratchForSafepointOnReturn: rcx config: org.graalvm.compiler.hotspot.GraalHotSpotVMConfig@7222fe45 <|@ <|@
    end_IR
  end_block
  begin_block
    name "B9"
    from_bci -1
    to_bci -1
    predecessors "B5" 
    successors "B10" "B14" 
    xhandlers
    flags 
    probability 4596601727505068676
    begin_IR
      LIR
      nr   48  <|@ instruction [] = LABEL numbPhis: 0 align: false label: ? <|@ <|@
      nr   50  <|@ instruction CMP r10|DWORD y: -559030611 size: DWORD c: meta{HotSpotType<Lorg/graalvm/compiler/graph/NodeInputList;, resolved>;compressed} <|@ <|@
      nr   52  <|@ instruction BRANCH trueDestinationProbability: 1.0 condition: = trueDestination: B9 -> B10 falseDestination: B9 -> B14 <|@ <|@
    end_IR
  end_block
  begin_block
    name "B10"
    from_bci -1
    to_bci -1
    predecessors "B9" 
    successors "B11" "B12" 
    xhandlers
    flags 
    probability 4596601727505068676
    begin_IR
      LIR
      nr   54  <|@ instruction [] = LABEL numbPhis: 0 align: false label: ? <|@ <|@
      nr   56  <|@ instruction CMP (x: r8|DWORD, y: [rdx|QWORD[.] + 16]) size: DWORD <|@ <|@
      nr   58  <|@ instruction BRANCH trueDestinationProbability: 0.0 condition: > trueDestination: B10 -> B11 falseDestination: B10 -> B12 <|@ <|@
    end_IR
  end_block
  begin_block
    name "B12"
    from_bci -1
    to_bci -1
    predecessors "B10" 
    successors "B13" 
    xhandlers
    flags 
    probability 4596601727505068676
    begin_IR
      LIR
      nr   60  <|@ instruction [] = LABEL numbPhis: 0 align: false label: ? <|@ <|@
      nr   62  <|@ instruction JUMP ~[] destination: B12 -> B13 <|@ <|@
    end_IR
  end_block
  begin_block
    name "B1"
    from_bci -1
    to_bci -1
    predecessors "B0" 
    successors "B4" 
    xhandlers
    flags 
    probability 2355382605114769408
    begin_IR
      LIR
      nr   88  <|@ instruction [] = LABEL numbPhis: 0 align: false label: ? <|@ <|@
      nr   -1  <|@ instruction r10|DWORD = MOVE input: int[-21011|0xffffffffffffaded] // MoveResolver resolve mapping <|@ <|@
      nr   90  <|@ instruction JUMP ~[] destination: B1 -> B4 <|@ <|@
    end_IR
  end_block
  begin_block
    name "B4"
    from_bci -1
    to_bci -1
    predecessors "B1" "B3" 
    successors 
    xhandlers
    flags 
    probability 2359886204742139904
    begin_IR
      LIR
      nr  104  <|@ instruction [] = LABEL numbPhis: 1 align: false label: ? <|@ <|@
      nr  106  <|@ instruction MOV (x: [r15|QWORD + 668], y: r10|DWORD) size: DWORD <|@ <|@
      nr  108  <|@ instruction MOV (x: [r15|QWORD + 680], y: r12|ILLEGAL) size: QWORD <|@ <|@
      nr  110  <|@ st <@st|@reference-map: [rdx:0, rsi:0]
live-base-pointers: []
java.util.SubList.<init>(AbstractList.java:618) [bci: 0]
locals: rsi|QWORD[.] rdx|QWORD[.] rcx|DWORD r8|DWORD 
>@ <|@ instruction DEOPT info [bci:0] <|@ <|@
    end_IR
  end_block
  begin_block
    name "B7"
    from_bci -1
    to_bci -1
    predecessors "B6" 
    successors "B15" 
    xhandlers
    flags 
    probability 2355382605114769408
    begin_IR
      LIR
      nr   92  <|@ instruction [] = LABEL numbPhis: 0 align: false label: ? <|@ <|@
      nr   -1  <|@ instruction r10|DWORD = MOVE input: int[-24083|0xffffffffffffa1ed] // MoveResolver resolve mapping <|@ <|@
      nr   94  <|@ instruction JUMP ~[] destination: B7 -> B15 <|@ <|@
    end_IR
  end_block
  begin_block
    name "B15"
    from_bci -1
    to_bci -1
    predecessors "B11" "B7" "B14" 
    successors 
    xhandlers
    flags 
    probability 2362138004555825152
    begin_IR
      LIR
      nr  116  <|@ instruction [] = LABEL numbPhis: 1 align: false label: ? <|@ <|@
      nr  118  <|@ instruction MOV (x: [r15|QWORD + 668], y: r10|DWORD) size: DWORD <|@ <|@
      nr  120  <|@ instruction MOV (x: [r15|QWORD + 680], y: r12|ILLEGAL) size: QWORD <|@ <|@
      nr  122  <|@ st <@st|@reference-map: [rdx:0, rsi:0]
live-base-pointers: []
java.util.AbstractList.<init>(AbstractList.java:77) [bci: 9]
locals: rsi|QWORD[.] 
java.util.SubList.<init>(AbstractList.java:618) [bci: 1]
locals: rsi|QWORD[.] rdx|QWORD[.] rcx|DWORD r8|DWORD 
>@ <|@ instruction DEOPT info [bci:9, 1] <|@ <|@
    end_IR
  end_block
  begin_block
    name "B11"
    from_bci -1
    to_bci -1
    predecessors "B10" 
    successors "B15" 
    xhandlers
    flags 
    probability 2355382605114769408
    begin_IR
      LIR
      nr   96  <|@ instruction [] = LABEL numbPhis: 0 align: false label: ? <|@ <|@
      nr   -1  <|@ instruction r10|DWORD = MOVE input: int[-28691|0xffffffffffff8fed] // MoveResolver resolve mapping <|@ <|@
      nr   98  <|@ instruction JUMP ~[] destination: B11 -> B15 <|@ <|@
    end_IR
  end_block
  begin_block
    name "B3"
    from_bci -1
    to_bci -1
    predecessors "B2" 
    successors "B4" 
    xhandlers
    flags 
    probability 2355382605114769408
    begin_IR
      LIR
      nr  100  <|@ instruction [] = LABEL numbPhis: 0 align: false label: ? <|@ <|@
      nr   -1  <|@ instruction r10|DWORD = MOVE input: int[-32531|0xffffffffffff80ed] // MoveResolver resolve mapping <|@ <|@
      nr  102  <|@ instruction JUMP ~[] destination: B3 -> B4 <|@ <|@
    end_IR
  end_block
  begin_block
    name "B14"
    from_bci -1
    to_bci -1
    predecessors "B9" 
    successors "B15" 
    xhandlers
    flags 
    probability 2355382605114769408
    begin_IR
      LIR
      nr  112  <|@ instruction [] = LABEL numbPhis: 0 align: false label: ? <|@ <|@
      nr   -1  <|@ instruction r10|DWORD = MOVE input: int[-27955|0xffffffffffff92cd] // MoveResolver resolve mapping <|@ <|@
      nr  114  <|@ instruction JUMP ~[] destination: B14 -> B15 <|@ <|@
    end_IR
  end_block
end_cfg
begin_bytecodes
     0: aload_0       
     1: invokespecial #3          // java.util.AbstractList.<init>:()void
     4: iload_2       
     5: ifge          35
     8: new           #5          // java.lang.IndexOutOfBoundsException
    11: dup           
    12: new           #6          // java.lang.StringBuilder
    15: dup           
    16: invokespecial #4          // java.lang.StringBuilder.<init>:()void
    19: ldc           #8          // "fromIndex = "
    21: invokevirtual #5          // java.lang.StringBuilder.append:(java.lang.String)java.lang.StringBuilder
    24: iload_2       
    25: invokevirtual #6          // java.lang.StringBuilder.append:(int)java.lang.StringBuilder
    28: invokevirtual #7          // java.lang.StringBuilder.toString:()java.lang.String
    31: invokespecial #8          // java.lang.IndexOutOfBoundsException.<init>:(java.lang.String)void
    34: athrow        
    35: iload_3       
    36: aload_1       
    37: invokevirtual #9          // java.util.AbstractCollection.size:()int
    40: if_icmple     70
    43: new           #5          // java.lang.IndexOutOfBoundsException
    46: dup           
    47: new           #6          // java.lang.StringBuilder
    50: dup           
    51: invokespecial #4          // java.lang.StringBuilder.<init>:()void
    54: ldc           #14         // "toIndex = "
    56: invokevirtual #5          // java.lang.StringBuilder.append:(java.lang.String)java.lang.StringBuilder
    59: iload_3       
    60: invokevirtual #6          // java.lang.StringBuilder.append:(int)java.lang.StringBuilder
    63: invokevirtual #7          // java.lang.StringBuilder.toString:()java.lang.String
    66: invokespecial #8          // java.lang.IndexOutOfBoundsException.<init>:(java.lang.String)void
    69: athrow        
    70: iload_2       
    71: iload_3       
    72: if_icmple     116
    75: new           #15         // java.lang.IllegalArgumentException
    78: dup           
    79: new           #6          // java.lang.StringBuilder
    82: dup           
    83: invokespecial #4          // java.lang.StringBuilder.<init>:()void
    86: ldc           #16         // "fromIndex("
    88: invokevirtual #5          // java.lang.StringBuilder.append:(java.lang.String)java.lang.StringBuilder
    91: iload_2       
    92: invokevirtual #6          // java.lang.StringBuilder.append:(int)java.lang.StringBuilder
    95: ldc           #17         // ") > toIndex("
    97: invokevirtual #5          // java.lang.StringBuilder.append:(java.lang.String)java.lang.StringBuilder
   100: iload_3       
   101: invokevirtual #6          // java.lang.StringBuilder.append:(int)java.lang.StringBuilder
   104: ldc           #18         // ")"
   106: invokevirtual #5          // java.lang.StringBuilder.append:(java.lang.String)java.lang.StringBuilder
   109: invokevirtual #7          // java.lang.StringBuilder.toString:()java.lang.String
   112: invokespecial #10         // java.lang.IllegalArgumentException.<init>:(java.lang.String)void
   115: athrow        
   116: aload_0       
   117: aload_1       
   118: putfield      #1          // l:java.util.AbstractList
   121: aload_0       
   122: iload_2       
   123: putfield      #2          // offset:int
   126: aload_0       
   127: iload_3       
   128: iload_2       
   129: isub          
   130: putfield      #0          // size:int
   133: aload_0       
   134: aload_0       
   135: getfield      #1          // l:java.util.AbstractList
   138: getfield      #11         // java.util.AbstractList.modCount:int
   141: putfield      #12         // java.util.AbstractList.modCount:int
   144: return        
   <|@
end_bytecodes
begin_cfg
  name "After PostAllocationOptimizationStage"
  begin_block
    name "B0"
    from_bci -1
    to_bci -1
    predecessors 
    successors "B1" "B2" 
    xhandlers
    flags 
    probability 4607182418800017408
    begin_IR
      LIR
      nr    0  <|@ instruction [rsi|QWORD[.], rdx|QWORD[.], rcx|DWORD, r8|DWORD, rbp|QWORD] = LABEL numbPhis: 0 align: false label: ? <|@ <|@
      nr    2  <|@ instruction stack:16|QWORD = MOVE rbp|QWORD moveKind: QWORD <|@ <|@
      nr    4  <|@ instruction [] = HOTSPOTLOCKSTACK frameMapBuilder: org.graalvm.compiler.lir.amd64.AMD64FrameMapBuilder@3c736a5f slotKind: QWORD <|@ <|@
      nr   14  <|@ instruction TEST (x: rcx|DWORD, y: rcx|DWORD) size: DWORD <|@ <|@
      nr   16  <|@ instruction BRANCH trueDestinationProbability: 0.0 condition: < trueDestination: B0 -> B1 falseDestination: B0 -> B2 <|@ <|@
    end_IR
  end_block
  begin_block
    name "B2"
    from_bci -1
    to_bci -1
    predecessors "B0" 
    successors "B3" "B5" 
    xhandlers
    flags 
    probability 4607182418800017408
    begin_IR
      LIR
      nr   18  <|@ instruction [] = LABEL numbPhis: 0 align: false label: ? <|@ <|@
      nr   20  <|@ st <@st|@reference-map: [rdx:0, rsi:0]
live-base-pointers: []
java.util.SubList.<init>(AbstractList.java:618) [bci: 0]
locals: rsi|QWORD[.] rdx|QWORD[.] rcx|DWORD r8|DWORD 
>@ <|@ instruction NULLCHECK [rdx|QWORD[.]] state [bci:0] <|@ <|@
      nr   22  <|@ instruction CMP (x: rcx|DWORD, y: r8|DWORD) size: DWORD <|@ <|@
      nr   24  <|@ instruction BRANCH trueDestinationProbability: 0.0 condition: > trueDestination: B2 -> B3 falseDestination: B2 -> B5 <|@ <|@
    end_IR
  end_block
  begin_block
    name "B5"
    from_bci -1
    to_bci -1
    predecessors "B2" 
    successors "B6" "B9" 
    xhandlers
    flags 
    probability 4607182418800017408
    begin_IR
      LIR
      nr   26  <|@ instruction [] = LABEL numbPhis: 0 align: false label: ? <|@ <|@
      nr   28  <|@ instruction MOV (x: [rsi|QWORD[.] + 12], y: r12|ILLEGAL) size: DWORD <|@ <|@
      nr   30  <|@ instruction r10|DWORD = MOV [rdx|QWORD[.] + 8] size: DWORD <|@ <|@
      nr   32  <|@ instruction CMP r10|DWORD y: -559030611 size: DWORD c: meta{HotSpotType<Ljava/util/Arrays$ArrayList;, resolved>;compressed} <|@ <|@
      nr   34  <|@ instruction BRANCH trueDestinationProbability: 0.7936731773025761 condition: = trueDestination: B5 -> B6 falseDestination: B5 -> B9 <|@ <|@
    end_IR
  end_block
  begin_block
    name "B6"
    from_bci -1
    to_bci -1
    predecessors "B5" 
    successors "B7" "B13" 
    xhandlers
    flags 
    probability 4605323991996384095
    begin_IR
      LIR
      nr   36  <|@ instruction [] = LABEL numbPhis: 0 align: false label: ? <|@ <|@
      nr   38  <|@ instruction r10|DWORD[.] = MOV [rdx|QWORD[.] + 16] size: DWORD <|@ <|@
      nr   40  <|@ st <@st|@reference-map: [rdx:0, rsi:0]
live-base-pointers: []
java.util.AbstractList.<init>(AbstractList.java:77) [bci: 9]
locals: rsi|QWORD[.] 
java.util.SubList.<init>(AbstractList.java:618) [bci: 1]
locals: rsi|QWORD[.] rdx|QWORD[.] rcx|DWORD r8|DWORD 
>@ <|@ instruction CMP (x: r8|DWORD, y: [r10|DWORD[.] * 8 + 12]) size: DWORD state [bci:9, 1] <|@ <|@
      nr   42  <|@ instruction BRANCH trueDestinationProbability: 0.0 condition: > trueDestination: B6 -> B7 falseDestination: B6 -> B13 <|@ <|@
    end_IR
  end_block
  begin_block
    name "B13"
    from_bci -1
    to_bci -1
    predecessors "B10" "B6" 
    successors 
    xhandlers
    flags 
    probability 4607182418800017408
    begin_IR
      LIR
      nr   64  <|@ instruction [] = LABEL numbPhis: 0 align: false label: ? <|@ <|@
      nr   66  <|@ instruction r10|DWORD[.] = COMPRESSPOINTER (input: rdx|QWORD[.], ~baseRegister: r12|ILLEGAL) nonNull: false lirKindTool: com.oracle.graal.enterprise.z.a@2c336164 encoding: base: 0 shift: 3 <|@ <|@
      nr   68  <|@ instruction MOV (x: [rsi|QWORD[.] + 24], y: r10|DWORD[.]) size: DWORD <|@ <|@
      nr   70  <|@ instruction r10|QWORD[*] = SHR rsi|QWORD[.] y: 9 size: QWORD <|@ <|@
      nr   72  <|@ instruction r11|QWORD = MOVE input: long[4682670080|0x1171be000] <|@ <|@
      nr   74  <|@ instruction MOVB (x: [r10|QWORD[*] + r11|QWORD * 1], y: r12|ILLEGAL) size: BYTE <|@ <|@
      nr   76  <|@ instruction MOV (x: [rsi|QWORD[.] + 16], y: rcx|DWORD) size: DWORD <|@ <|@
      nr   78  <|@ instruction r8|DWORD = SUB (x: r8|DWORD, ~y: rcx|DWORD) size: DWORD <|@ <|@
      nr   80  <|@ instruction MOV (x: [rsi|QWORD[.] + 20], y: r8|DWORD) size: DWORD <|@ <|@
      nr   82  <|@ instruction r10|DWORD = MOV [rdx|QWORD[.] + 12] size: DWORD <|@ <|@
      nr   84  <|@ instruction MOV (x: [rsi|QWORD[.] + 12], y: r10|DWORD) size: DWORD <|@ <|@
      nr   86  <|@ instruction RETURN (savedRbp: stack:16|QWORD, value: -) isStub: false thread: r15 scratchForSafepointOnReturn: rcx config: org.graalvm.compiler.hotspot.GraalHotSpotVMConfig@7222fe45 <|@ <|@
    end_IR
  end_block
  begin_block
    name "B9"
    from_bci -1
    to_bci -1
    predecessors "B5" 
    successors "B10" "B14" 
    xhandlers
    flags 
    probability 4596601727505068676
    begin_IR
      LIR
      nr   48  <|@ instruction [] = LABEL numbPhis: 0 align: false label: ? <|@ <|@
      nr   50  <|@ instruction CMP r10|DWORD y: -559030611 size: DWORD c: meta{HotSpotType<Lorg/graalvm/compiler/graph/NodeInputList;, resolved>;compressed} <|@ <|@
      nr   52  <|@ instruction BRANCH trueDestinationProbability: 1.0 condition: = trueDestination: B9 -> B10 falseDestination: B9 -> B14 <|@ <|@
    end_IR
  end_block
  begin_block
    name "B10"
    from_bci -1
    to_bci -1
    predecessors "B9" 
    successors "B11" "B13" 
    xhandlers
    flags 
    probability 4596601727505068676
    begin_IR
      LIR
      nr   54  <|@ instruction [] = LABEL numbPhis: 0 align: false label: ? <|@ <|@
      nr   56  <|@ instruction CMP (x: r8|DWORD, y: [rdx|QWORD[.] + 16]) size: DWORD <|@ <|@
      nr   58  <|@ instruction BRANCH trueDestinationProbability: 0.0 condition: > trueDestination: B10 -> B11 falseDestination: B10 -> B13 <|@ <|@
    end_IR
  end_block
  begin_block
    name "B1"
    from_bci -1
    to_bci -1
    predecessors "B0" 
    successors "B4" 
    xhandlers
    flags 
    probability 2355382605114769408
    begin_IR
      LIR
      nr   88  <|@ instruction [] = LABEL numbPhis: 0 align: false label: ? <|@ <|@
      nr   -1  <|@ instruction r10|DWORD = MOVE input: int[-21011|0xffffffffffffaded] // MoveResolver resolve mapping <|@ <|@
      nr   90  <|@ instruction JUMP ~[] destination: B1 -> B4 <|@ <|@
    end_IR
  end_block
  begin_block
    name "B4"
    from_bci -1
    to_bci -1
    predecessors "B1" "B3" 
    successors 
    xhandlers
    flags 
    probability 2359886204742139904
    begin_IR
      LIR
      nr  104  <|@ instruction [] = LABEL numbPhis: 1 align: false label: ? <|@ <|@
      nr  106  <|@ instruction MOV (x: [r15|QWORD + 668], y: r10|DWORD) size: DWORD <|@ <|@
      nr  108  <|@ instruction MOV (x: [r15|QWORD + 680], y: r12|ILLEGAL) size: QWORD <|@ <|@
      nr  110  <|@ st <@st|@reference-map: [rdx:0, rsi:0]
live-base-pointers: []
java.util.SubList.<init>(AbstractList.java:618) [bci: 0]
locals: rsi|QWORD[.] rdx|QWORD[.] rcx|DWORD r8|DWORD 
>@ <|@ instruction DEOPT info [bci:0] <|@ <|@
    end_IR
  end_block
  begin_block
    name "B7"
    from_bci -1
    to_bci -1
    predecessors "B6" 
    successors "B15" 
    xhandlers
    flags 
    probability 2355382605114769408
    begin_IR
      LIR
      nr   92  <|@ instruction [] = LABEL numbPhis: 0 align: false label: ? <|@ <|@
      nr   -1  <|@ instruction r10|DWORD = MOVE input: int[-24083|0xffffffffffffa1ed] // MoveResolver resolve mapping <|@ <|@
      nr   94  <|@ instruction JUMP ~[] destination: B7 -> B15 <|@ <|@
    end_IR
  end_block
  begin_block
    name "B15"
    from_bci -1
    to_bci -1
    predecessors "B11" "B7" "B14" 
    successors 
    xhandlers
    flags 
    probability 2362138004555825152
    begin_IR
      LIR
      nr  116  <|@ instruction [] = LABEL numbPhis: 1 align: false label: ? <|@ <|@
      nr  118  <|@ instruction MOV (x: [r15|QWORD + 668], y: r10|DWORD) size: DWORD <|@ <|@
      nr  120  <|@ instruction MOV (x: [r15|QWORD + 680], y: r12|ILLEGAL) size: QWORD <|@ <|@
      nr  122  <|@ st <@st|@reference-map: [rdx:0, rsi:0]
live-base-pointers: []
java.util.AbstractList.<init>(AbstractList.java:77) [bci: 9]
locals: rsi|QWORD[.] 
java.util.SubList.<init>(AbstractList.java:618) [bci: 1]
locals: rsi|QWORD[.] rdx|QWORD[.] rcx|DWORD r8|DWORD 
>@ <|@ instruction DEOPT info [bci:9, 1] <|@ <|@
    end_IR
  end_block
  begin_block
    name "B11"
    from_bci -1
    to_bci -1
    predecessors "B10" 
    successors "B15" 
    xhandlers
    flags 
    probability 2355382605114769408
    begin_IR
      LIR
      nr   96  <|@ instruction [] = LABEL numbPhis: 0 align: false label: ? <|@ <|@
      nr   -1  <|@ instruction r10|DWORD = MOVE input: int[-28691|0xffffffffffff8fed] // MoveResolver resolve mapping <|@ <|@
      nr   98  <|@ instruction JUMP ~[] destination: B11 -> B15 <|@ <|@
    end_IR
  end_block
  begin_block
    name "B3"
    from_bci -1
    to_bci -1
    predecessors "B2" 
    successors "B4" 
    xhandlers
    flags 
    probability 2355382605114769408
    begin_IR
      LIR
      nr  100  <|@ instruction [] = LABEL numbPhis: 0 align: false label: ? <|@ <|@
      nr   -1  <|@ instruction r10|DWORD = MOVE input: int[-32531|0xffffffffffff80ed] // MoveResolver resolve mapping <|@ <|@
      nr  102  <|@ instruction JUMP ~[] destination: B3 -> B4 <|@ <|@
    end_IR
  end_block
  begin_block
    name "B14"
    from_bci -1
    to_bci -1
    predecessors "B9" 
    successors "B15" 
    xhandlers
    flags 
    probability 2355382605114769408
    begin_IR
      LIR
      nr  112  <|@ instruction [] = LABEL numbPhis: 0 align: false label: ? <|@ <|@
      nr   -1  <|@ instruction r10|DWORD = MOVE input: int[-27955|0xffffffffffff92cd] // MoveResolver resolve mapping <|@ <|@
      nr  114  <|@ instruction JUMP ~[] destination: B14 -> B15 <|@ <|@
    end_IR
  end_block
end_cfg
begin_bytecodes
     0: aload_0       
     1: invokespecial #3          // java.util.AbstractList.<init>:()void
     4: iload_2       
     5: ifge          35
     8: new           #5          // java.lang.IndexOutOfBoundsException
    11: dup           
    12: new           #6          // java.lang.StringBuilder
    15: dup           
    16: invokespecial #4          // java.lang.StringBuilder.<init>:()void
    19: ldc           #8          // "fromIndex = "
    21: invokevirtual #5          // java.lang.StringBuilder.append:(java.lang.String)java.lang.StringBuilder
    24: iload_2       
    25: invokevirtual #6          // java.lang.StringBuilder.append:(int)java.lang.StringBuilder
    28: invokevirtual #7          // java.lang.StringBuilder.toString:()java.lang.String
    31: invokespecial #8          // java.lang.IndexOutOfBoundsException.<init>:(java.lang.String)void
    34: athrow        
    35: iload_3       
    36: aload_1       
    37: invokevirtual #9          // java.util.AbstractCollection.size:()int
    40: if_icmple     70
    43: new           #5          // java.lang.IndexOutOfBoundsException
    46: dup           
    47: new           #6          // java.lang.StringBuilder
    50: dup           
    51: invokespecial #4          // java.lang.StringBuilder.<init>:()void
    54: ldc           #14         // "toIndex = "
    56: invokevirtual #5          // java.lang.StringBuilder.append:(java.lang.String)java.lang.StringBuilder
    59: iload_3       
    60: invokevirtual #6          // java.lang.StringBuilder.append:(int)java.lang.StringBuilder
    63: invokevirtual #7          // java.lang.StringBuilder.toString:()java.lang.String
    66: invokespecial #8          // java.lang.IndexOutOfBoundsException.<init>:(java.lang.String)void
    69: athrow        
    70: iload_2       
    71: iload_3       
    72: if_icmple     116
    75: new           #15         // java.lang.IllegalArgumentException
    78: dup           
    79: new           #6          // java.lang.StringBuilder
    82: dup           
    83: invokespecial #4          // java.lang.StringBuilder.<init>:()void
    86: ldc           #16         // "fromIndex("
    88: invokevirtual #5          // java.lang.StringBuilder.append:(java.lang.String)java.lang.StringBuilder
    91: iload_2       
    92: invokevirtual #6          // java.lang.StringBuilder.append:(int)java.lang.StringBuilder
    95: ldc           #17         // ") > toIndex("
    97: invokevirtual #5          // java.lang.StringBuilder.append:(java.lang.String)java.lang.StringBuilder
   100: iload_3       
   101: invokevirtual #6          // java.lang.StringBuilder.append:(int)java.lang.StringBuilder
   104: ldc           #18         // ")"
   106: invokevirtual #5          // java.lang.StringBuilder.append:(java.lang.String)java.lang.StringBuilder
   109: invokevirtual #7          // java.lang.StringBuilder.toString:()java.lang.String
   112: invokespecial #10         // java.lang.IllegalArgumentException.<init>:(java.lang.String)void
   115: athrow        
   116: aload_0       
   117: aload_1       
   118: putfield      #1          // l:java.util.AbstractList
   121: aload_0       
   122: iload_2       
   123: putfield      #2          // offset:int
   126: aload_0       
   127: iload_3       
   128: iload_2       
   129: isub          
   130: putfield      #0          // size:int
   133: aload_0       
   134: aload_0       
   135: getfield      #1          // l:java.util.AbstractList
   138: getfield      #11         // java.util.AbstractList.modCount:int
   141: putfield      #12         // java.util.AbstractList.modCount:int
   144: return        
   <|@
end_bytecodes
begin_cfg
  name "After code generation"
end_cfg
begin_nmethod
  <<<HexCodeFile
  Platform AMD64 64  <||@
  HexCode 0 448b560849c1e203493bc20f85efffffff900f1f80000000000f1f800000000089842400c0feff4883ec1848896c241085c90f8c8f0000008502413bc80f8fc00000004489660c448b52084181faaddeadde0f8557000000448b5210463b04d50c0000000f8f770000004c8bd249c1ea03448956184c8bd649c1ea0949bb00e01b17010000004788241a894e10442bc144894614448b520c4489560c488b6c24104883c418850500000000c5f877c34181faaddeadde0f854f000000443b42107ea8e93400000041baedadffff4589979c0200004d89a7a8020000e8000000009041baeda1ffff4589979c0200004d89a7a8020000e8000000009041baed8fffffebe441baed80ffffebc241bacd92ffffebd4e80000000090e80000000090  <||@
  Comment 0 2  <||@
  Comment 11 {Field[name=CompilerToVM::Data::SharedRuntime_ic_miss_stub, type=address, offset=0, address=0x105aa1f78, value=0x106805e60]:0x106805e60}  <||@
  Comment 32 [stack overflow check]  <||@
  Comment 32 3  <||@
  Comment 32 1  <||@
  Comment 43 block B0 null  <||@
  Comment 43 0 [rsi|QWORD[.], rdx|QWORD[.], rcx|DWORD, r8|DWORD, rbp|QWORD] = LABEL numbPhis: 0 align: false label: ?  <||@
  Comment 43 2 stack:16|QWORD = MOVE rbp|QWORD moveKind: QWORD  <||@
  Comment 48 4 [] = HOTSPOTLOCKSTACK frameMapBuilder: org.graalvm.compiler.lir.amd64.AMD64FrameMapBuilder@3c736a5f slotKind: QWORD  <||@
  Comment 48 14 TEST (x: rcx|DWORD, y: rcx|DWORD) size: DWORD  <||@
  Comment 50 16 BRANCH trueDestinationProbability: 0.0 condition: < trueDestination: B0 -> B1 falseDestination: B0 -> B2  <||@
  Comment 56 block B2 null  <||@
  Comment 56 18 [] = LABEL numbPhis: 0 align: false label: ?  <||@
  Comment 56 20 NULLCHECK [rdx|QWORD[.]] state [bci:0]  <||@
  Comment 56 [rdx:0, rsi:0]at java.util.SubList.<init>(AbstractList.java:618) [bci: 0, duringCall: false, rethrow: false]
              |0             |1             |2          |3        
     locals:  |rsi|QWORD[.]  |rdx|QWORD[.]  |rcx|DWORD  |r8|DWORD   <||@
  Comment 56 {infopoint: IMPLICIT_EXCEPTION}  <||@
  Comment 58 22 CMP (x: rcx|DWORD, y: r8|DWORD) size: DWORD  <||@
  Comment 61 24 BRANCH trueDestinationProbability: 0.0 condition: > trueDestination: B2 -> B3 falseDestination: B2 -> B5  <||@
  Comment 67 block B5 null  <||@
  Comment 67 26 [] = LABEL numbPhis: 0 align: false label: ?  <||@
  Comment 67 28 MOV (x: [rsi|QWORD[.] + 12], y: r12|ILLEGAL) size: DWORD  <||@
  Comment 71 30 r10|DWORD = MOV [rdx|QWORD[.] + 8] size: DWORD  <||@
  Comment 75 32 CMP r10|DWORD y: -559030611 size: DWORD c: meta{HotSpotType<Ljava/util/Arrays$ArrayList;, resolved>;compressed}  <||@
  Comment 75 {meta{HotSpotType<Ljava/util/Arrays$ArrayList;, resolved>;compressed}}  <||@
  Comment 82 34 BRANCH trueDestinationProbability: 0.7936731773025761 condition: = trueDestination: B5 -> B6 falseDestination: B5 -> B9  <||@
  Comment 88 block B6 null  <||@
  Comment 88 36 [] = LABEL numbPhis: 0 align: false label: ?  <||@
  Comment 88 38 r10|DWORD[.] = MOV [rdx|QWORD[.] + 16] size: DWORD  <||@
  Comment 92 40 CMP (x: r8|DWORD, y: [r10|DWORD[.] * 8 + 12]) size: DWORD state [bci:9, 1]  <||@
  Comment 92 [rdx:0, rsi:0]at java.util.AbstractList.<init>(AbstractList.java:77) [bci: 9, duringCall: false, rethrow: false]
              |0            
     locals:  |rsi|QWORD[.] 
  at java.util.SubList.<init>(AbstractList.java:618) [bci: 1, duringCall: true, rethrow: false]
              |0             |1             |2          |3        
     locals:  |rsi|QWORD[.]  |rdx|QWORD[.]  |rcx|DWORD  |r8|DWORD   <||@
  Comment 92 {infopoint: IMPLICIT_EXCEPTION}  <||@
  Comment 100 42 BRANCH trueDestinationProbability: 0.0 condition: > trueDestination: B6 -> B7 falseDestination: B6 -> B13  <||@
  Comment 106 block B13 null  <||@
  Comment 106 64 [] = LABEL numbPhis: 0 align: false label: ?  <||@
  Comment 106 66 r10|DWORD[.] = COMPRESSPOINTER (input: rdx|QWORD[.], ~baseRegister: r12|ILLEGAL) nonNull: false lirKindTool: com.oracle.graal.enterprise.z.a@2c336164 encoding: base: 0 shift: 3  <||@
  Comment 113 68 MOV (x: [rsi|QWORD[.] + 24], y: r10|DWORD[.]) size: DWORD  <||@
  Comment 117 70 r10|QWORD[*] = SHR rsi|QWORD[.] y: 9 size: QWORD  <||@
  Comment 124 72 r11|QWORD = MOVE input: long[4682670080|0x1171be000]  <||@
  Comment 134 74 MOVB (x: [r10|QWORD[*] + r11|QWORD * 1], y: r12|ILLEGAL) size: BYTE  <||@
  Comment 138 76 MOV (x: [rsi|QWORD[.] + 16], y: rcx|DWORD) size: DWORD  <||@
  Comment 141 78 r8|DWORD = SUB (x: r8|DWORD, ~y: rcx|DWORD) size: DWORD  <||@
  Comment 144 80 MOV (x: [rsi|QWORD[.] + 20], y: r8|DWORD) size: DWORD  <||@
  Comment 148 82 r10|DWORD = MOV [rdx|QWORD[.] + 12] size: DWORD  <||@
  Comment 152 84 MOV (x: [rsi|QWORD[.] + 12], y: r10|DWORD) size: DWORD  <||@
  Comment 156 86 RETURN (savedRbp: stack:16|QWORD, value: -) isStub: false thread: r15 scratchForSafepointOnReturn: rcx config: org.graalvm.compiler.hotspot.GraalHotSpotVMConfig@7222fe45  <||@
  Comment 165 12  <||@
  Comment 175 block B9 null  <||@
  Comment 175 48 [] = LABEL numbPhis: 0 align: false label: ?  <||@
  Comment 175 50 CMP r10|DWORD y: -559030611 size: DWORD c: meta{HotSpotType<Lorg/graalvm/compiler/graph/NodeInputList;, resolved>;compressed}  <||@
  Comment 175 {meta{HotSpotType<Lorg/graalvm/compiler/graph/NodeInputList;, resolved>;compressed}}  <||@
  Comment 182 52 BRANCH trueDestinationProbability: 1.0 condition: = trueDestination: B9 -> B10 falseDestination: B9 -> B14  <||@
  Comment 188 block B10 null  <||@
  Comment 188 54 [] = LABEL numbPhis: 0 align: false label: ?  <||@
  Comment 188 56 CMP (x: r8|DWORD, y: [rdx|QWORD[.] + 16]) size: DWORD  <||@
  Comment 192 58 BRANCH trueDestinationProbability: 0.0 condition: > trueDestination: B10 -> B11 falseDestination: B10 -> B13  <||@
  Comment 199 block B1 null  <||@
  Comment 199 88 [] = LABEL numbPhis: 0 align: false label: ?  <||@
  Comment 199 -1 r10|DWORD = MOVE input: int[-21011|0xffffffffffffaded]  <||@
  Comment 205 90 JUMP ~[] destination: B1 -> B4  <||@
  Comment 205 block B4 null  <||@
  Comment 205 104 [] = LABEL numbPhis: 1 align: false label: ?  <||@
  Comment 205 106 MOV (x: [r15|QWORD + 668], y: r10|DWORD) size: DWORD  <||@
  Comment 212 108 MOV (x: [r15|QWORD + 680], y: r12|ILLEGAL) size: QWORD  <||@
  Comment 219 110 DEOPT info [bci:0]  <||@
  Comment 219 {Field[name=CompilerToVM::Data::SharedRuntime_deopt_blob_uncommon_trap, type=address, offset=0, address=0x105aa1f90, value=0x1068075fe]:0x1068075fe}  <||@
  Comment 224 [rdx:0, rsi:0]at java.util.SubList.<init>(AbstractList.java:618) [bci: 0, duringCall: false, rethrow: false]
              |0             |1             |2          |3        
     locals:  |rsi|QWORD[.]  |rdx|QWORD[.]  |rcx|DWORD  |r8|DWORD   <||@
  Comment 225 block B7 null  <||@
  Comment 225 92 [] = LABEL numbPhis: 0 align: false label: ?  <||@
  Comment 225 -1 r10|DWORD = MOVE input: int[-24083|0xffffffffffffa1ed]  <||@
  Comment 231 94 JUMP ~[] destination: B7 -> B15  <||@
  Comment 231 block B15 null  <||@
  Comment 231 116 [] = LABEL numbPhis: 1 align: false label: ?  <||@
  Comment 231 118 MOV (x: [r15|QWORD + 668], y: r10|DWORD) size: DWORD  <||@
  Comment 238 120 MOV (x: [r15|QWORD + 680], y: r12|ILLEGAL) size: QWORD  <||@
  Comment 245 122 DEOPT info [bci:9, 1]  <||@
  Comment 245 {Field[name=CompilerToVM::Data::SharedRuntime_deopt_blob_uncommon_trap, type=address, offset=0, address=0x105aa1f90, value=0x1068075fe]:0x1068075fe}  <||@
  Comment 250 [rdx:0, rsi:0]at java.util.AbstractList.<init>(AbstractList.java:77) [bci: 9, duringCall: false, rethrow: false]
              |0            
     locals:  |rsi|QWORD[.] 
  at java.util.SubList.<init>(AbstractList.java:618) [bci: 1, duringCall: true, rethrow: false]
              |0             |1             |2          |3        
     locals:  |rsi|QWORD[.]  |rdx|QWORD[.]  |rcx|DWORD  |r8|DWORD   <||@
  Comment 251 block B11 null  <||@
  Comment 251 96 [] = LABEL numbPhis: 0 align: false label: ?  <||@
  Comment 251 -1 r10|DWORD = MOVE input: int[-28691|0xffffffffffff8fed]  <||@
  Comment 257 98 JUMP ~[] destination: B11 -> B15  <||@
  Comment 259 block B3 null  <||@
  Comment 259 100 [] = LABEL numbPhis: 0 align: false label: ?  <||@
  Comment 259 -1 r10|DWORD = MOVE input: int[-32531|0xffffffffffff80ed]  <||@
  Comment 265 102 JUMP ~[] destination: B3 -> B4  <||@
  Comment 267 block B14 null  <||@
  Comment 267 112 [] = LABEL numbPhis: 0 align: false label: ?  <||@
  Comment 267 -1 r10|DWORD = MOVE input: int[-27955|0xffffffffffff92cd]  <||@
  Comment 273 114 JUMP ~[] destination: B14 -> B15  <||@
  Comment 275 {Stub<ExceptionHandlerStub.exceptionHandler>@0x106c4a620:CallingConvention[rax|QWORD[.], rdx|QWORD]:CallingConvention[rax|QWORD[.], rdx|QWORD]; temps=rdi|ILLEGAL,xmm0|ILLEGAL,xmm1|ILLEGAL,xmm2|ILLEGAL,xmm3|ILLEGAL,xmm4|ILLEGAL,xmm5|ILLEGAL,xmm6|ILLEGAL,xmm7|ILLEGAL,xmm8|ILLEGAL,xmm9|ILLEGAL,xmm10|ILLEGAL,xmm11|ILLEGAL,xmm12|ILLEGAL,xmm13|ILLEGAL,xmm14|ILLEGAL,xmm15|ILLEGAL,xmm16|ILLEGAL,xmm17|ILLEGAL,xmm18|ILLEGAL,xmm19|ILLEGAL,xmm20|ILLEGAL,xmm21|ILLEGAL,xmm22|ILLEGAL,xmm23|ILLEGAL,xmm24|ILLEGAL,xmm25|ILLEGAL,xmm26|ILLEGAL,xmm27|ILLEGAL,xmm28|ILLEGAL,xmm29|ILLEGAL,xmm30|ILLEGAL,xmm31|ILLEGAL,rax|ILLEGAL,rcx|ILLEGAL,rdx|ILLEGAL,rsi|ILLEGAL,r8|ILLEGAL,r9|ILLEGAL,r10|ILLEGAL,r11|ILLEGAL}  <||@
  Comment 275 4  <||@
  Comment 281 {Field[name=CompilerToVM::Data::SharedRuntime_deopt_blob_unpack, type=address, offset=0, address=0x105aa1f88, value=0x106807500]:0x106807500}  <||@
  Comment 281 5  <||@
  HexCodeFile>>> <|@
end_nmethod
begin_compilation
  name " HotSpotCompilation-9529[java.util.SubList.<init>(AbstractList, int, int)]"
  method "HotSpotCompilation-9529[java.util.SubList.<init>(AbstractList, int, int)]"
  date 1527005205430
end_compilation
begin_cfg
  name "After code installation"
end_cfg
begin_nmethod
  <<<HexCodeFile
  Platform AMD64 64  <||@
  HexCode 107b82ea0 448b560849c1e203493bc20f85af2fc8fe900f1f80000000000f1f800000000089842400c0feff4883ec1848896c241085c90f8c8f0000008502413bc80f8fc00000004489660c448b52084181fa8faf00f80f8557000000448b5210463b04d50c0000000f8f770000004c8bd249c1ea03448956184c8bd649c1ea0949bb00e01b17010000004788241a894e10442bc144894614448b520c4489560c488b6c24104883c4188505bbc0d0fcc5f877c34181fac8b101f80f854f000000443b42107ea8e93400000041baedadffff4589979c0200004d89a7a8020000e87e46c8fe9041baeda1ffff4589979c0200004d89a7a8020000e86446c8fe9041baed8fffffebe441baed80ffffebc241bacd92ffffebd4e868760cff90e84245c8fe90f4  <||@
  Comment 0 2  <||@
  Comment 11 {Field[name=CompilerToVM::Data::SharedRuntime_ic_miss_stub, type=address, offset=0, address=0x105aa1f78, value=0x106805e60]:0x106805e60}  <||@
  Comment 32 [stack overflow check]  <||@
  Comment 32 3  <||@
  Comment 32 1  <||@
  Comment 43 block B0 null  <||@
  Comment 43 0 [rsi|QWORD[.], rdx|QWORD[.], rcx|DWORD, r8|DWORD, rbp|QWORD] = LABEL numbPhis: 0 align: false label: ?  <||@
  Comment 43 2 stack:16|QWORD = MOVE rbp|QWORD moveKind: QWORD  <||@
  Comment 48 4 [] = HOTSPOTLOCKSTACK frameMapBuilder: org.graalvm.compiler.lir.amd64.AMD64FrameMapBuilder@3c736a5f slotKind: QWORD  <||@
  Comment 48 14 TEST (x: rcx|DWORD, y: rcx|DWORD) size: DWORD  <||@
  Comment 50 16 BRANCH trueDestinationProbability: 0.0 condition: < trueDestination: B0 -> B1 falseDestination: B0 -> B2  <||@
  Comment 56 block B2 null  <||@
  Comment 56 18 [] = LABEL numbPhis: 0 align: false label: ?  <||@
  Comment 56 20 NULLCHECK [rdx|QWORD[.]] state [bci:0]  <||@
  Comment 56 [rdx:0, rsi:0]at java.util.SubList.<init>(AbstractList.java:618) [bci: 0, duringCall: false, rethrow: false]
              |0             |1             |2          |3        
     locals:  |rsi|QWORD[.]  |rdx|QWORD[.]  |rcx|DWORD  |r8|DWORD   <||@
  Comment 56 {infopoint: IMPLICIT_EXCEPTION}  <||@
  Comment 58 22 CMP (x: rcx|DWORD, y: r8|DWORD) size: DWORD  <||@
  Comment 61 24 BRANCH trueDestinationProbability: 0.0 condition: > trueDestination: B2 -> B3 falseDestination: B2 -> B5  <||@
  Comment 67 block B5 null  <||@
  Comment 67 26 [] = LABEL numbPhis: 0 align: false label: ?  <||@
  Comment 67 28 MOV (x: [rsi|QWORD[.] + 12], y: r12|ILLEGAL) size: DWORD  <||@
  Comment 71 30 r10|DWORD = MOV [rdx|QWORD[.] + 8] size: DWORD  <||@
  Comment 75 32 CMP r10|DWORD y: -559030611 size: DWORD c: meta{HotSpotType<Ljava/util/Arrays$ArrayList;, resolved>;compressed}  <||@
  Comment 75 {meta{HotSpotType<Ljava/util/Arrays$ArrayList;, resolved>;compressed}}  <||@
  Comment 82 34 BRANCH trueDestinationProbability: 0.7936731773025761 condition: = trueDestination: B5 -> B6 falseDestination: B5 -> B9  <||@
  Comment 88 block B6 null  <||@
  Comment 88 36 [] = LABEL numbPhis: 0 align: false label: ?  <||@
  Comment 88 38 r10|DWORD[.] = MOV [rdx|QWORD[.] + 16] size: DWORD  <||@
  Comment 92 40 CMP (x: r8|DWORD, y: [r10|DWORD[.] * 8 + 12]) size: DWORD state [bci:9, 1]  <||@
  Comment 92 [rdx:0, rsi:0]at java.util.AbstractList.<init>(AbstractList.java:77) [bci: 9, duringCall: false, rethrow: false]
              |0            
     locals:  |rsi|QWORD[.] 
  at java.util.SubList.<init>(AbstractList.java:618) [bci: 1, duringCall: true, rethrow: false]
              |0             |1             |2          |3        
     locals:  |rsi|QWORD[.]  |rdx|QWORD[.]  |rcx|DWORD  |r8|DWORD   <||@
  Comment 92 {infopoint: IMPLICIT_EXCEPTION}  <||@
  Comment 100 42 BRANCH trueDestinationProbability: 0.0 condition: > trueDestination: B6 -> B7 falseDestination: B6 -> B13  <||@
  Comment 106 block B13 null  <||@
  Comment 106 64 [] = LABEL numbPhis: 0 align: false label: ?  <||@
  Comment 106 66 r10|DWORD[.] = COMPRESSPOINTER (input: rdx|QWORD[.], ~baseRegister: r12|ILLEGAL) nonNull: false lirKindTool: com.oracle.graal.enterprise.z.a@2c336164 encoding: base: 0 shift: 3  <||@
  Comment 113 68 MOV (x: [rsi|QWORD[.] + 24], y: r10|DWORD[.]) size: DWORD  <||@
  Comment 117 70 r10|QWORD[*] = SHR rsi|QWORD[.] y: 9 size: QWORD  <||@
  Comment 124 72 r11|QWORD = MOVE input: long[4682670080|0x1171be000]  <||@
  Comment 134 74 MOVB (x: [r10|QWORD[*] + r11|QWORD * 1], y: r12|ILLEGAL) size: BYTE  <||@
  Comment 138 76 MOV (x: [rsi|QWORD[.] + 16], y: rcx|DWORD) size: DWORD  <||@
  Comment 141 78 r8|DWORD = SUB (x: r8|DWORD, ~y: rcx|DWORD) size: DWORD  <||@
  Comment 144 80 MOV (x: [rsi|QWORD[.] + 20], y: r8|DWORD) size: DWORD  <||@
  Comment 148 82 r10|DWORD = MOV [rdx|QWORD[.] + 12] size: DWORD  <||@
  Comment 152 84 MOV (x: [rsi|QWORD[.] + 12], y: r10|DWORD) size: DWORD  <||@
  Comment 156 86 RETURN (savedRbp: stack:16|QWORD, value: -) isStub: false thread: r15 scratchForSafepointOnReturn: rcx config: org.graalvm.compiler.hotspot.GraalHotSpotVMConfig@7222fe45  <||@
  Comment 165 12  <||@
  Comment 175 block B9 null  <||@
  Comment 175 48 [] = LABEL numbPhis: 0 align: false label: ?  <||@
  Comment 175 50 CMP r10|DWORD y: -559030611 size: DWORD c: meta{HotSpotType<Lorg/graalvm/compiler/graph/NodeInputList;, resolved>;compressed}  <||@
  Comment 175 {meta{HotSpotType<Lorg/graalvm/compiler/graph/NodeInputList;, resolved>;compressed}}  <||@
  Comment 182 52 BRANCH trueDestinationProbability: 1.0 condition: = trueDestination: B9 -> B10 falseDestination: B9 -> B14  <||@
  Comment 188 block B10 null  <||@
  Comment 188 54 [] = LABEL numbPhis: 0 align: false label: ?  <||@
  Comment 188 56 CMP (x: r8|DWORD, y: [rdx|QWORD[.] + 16]) size: DWORD  <||@
  Comment 192 58 BRANCH trueDestinationProbability: 0.0 condition: > trueDestination: B10 -> B11 falseDestination: B10 -> B13  <||@
  Comment 199 block B1 null  <||@
  Comment 199 88 [] = LABEL numbPhis: 0 align: false label: ?  <||@
  Comment 199 -1 r10|DWORD = MOVE input: int[-21011|0xffffffffffffaded]  <||@
  Comment 205 90 JUMP ~[] destination: B1 -> B4  <||@
  Comment 205 block B4 null  <||@
  Comment 205 104 [] = LABEL numbPhis: 1 align: false label: ?  <||@
  Comment 205 106 MOV (x: [r15|QWORD + 668], y: r10|DWORD) size: DWORD  <||@
  Comment 212 108 MOV (x: [r15|QWORD + 680], y: r12|ILLEGAL) size: QWORD  <||@
  Comment 219 110 DEOPT info [bci:0]  <||@
  Comment 219 {Field[name=CompilerToVM::Data::SharedRuntime_deopt_blob_uncommon_trap, type=address, offset=0, address=0x105aa1f90, value=0x1068075fe]:0x1068075fe}  <||@
  Comment 224 [rdx:0, rsi:0]at java.util.SubList.<init>(AbstractList.java:618) [bci: 0, duringCall: false, rethrow: false]
              |0             |1             |2          |3        
     locals:  |rsi|QWORD[.]  |rdx|QWORD[.]  |rcx|DWORD  |r8|DWORD   <||@
  Comment 225 block B7 null  <||@
  Comment 225 92 [] = LABEL numbPhis: 0 align: false label: ?  <||@
  Comment 225 -1 r10|DWORD = MOVE input: int[-24083|0xffffffffffffa1ed]  <||@
  Comment 231 94 JUMP ~[] destination: B7 -> B15  <||@
  Comment 231 block B15 null  <||@
  Comment 231 116 [] = LABEL numbPhis: 1 align: false label: ?  <||@
  Comment 231 118 MOV (x: [r15|QWORD + 668], y: r10|DWORD) size: DWORD  <||@
  Comment 238 120 MOV (x: [r15|QWORD + 680], y: r12|ILLEGAL) size: QWORD  <||@
  Comment 245 122 DEOPT info [bci:9, 1]  <||@
  Comment 245 {Field[name=CompilerToVM::Data::SharedRuntime_deopt_blob_uncommon_trap, type=address, offset=0, address=0x105aa1f90, value=0x1068075fe]:0x1068075fe}  <||@
  Comment 250 [rdx:0, rsi:0]at java.util.AbstractList.<init>(AbstractList.java:77) [bci: 9, duringCall: false, rethrow: false]
              |0            
     locals:  |rsi|QWORD[.] 
  at java.util.SubList.<init>(AbstractList.java:618) [bci: 1, duringCall: true, rethrow: false]
              |0             |1             |2          |3        
     locals:  |rsi|QWORD[.]  |rdx|QWORD[.]  |rcx|DWORD  |r8|DWORD   <||@
  Comment 251 block B11 null  <||@
  Comment 251 96 [] = LABEL numbPhis: 0 align: false label: ?  <||@
  Comment 251 -1 r10|DWORD = MOVE input: int[-28691|0xffffffffffff8fed]  <||@
  Comment 257 98 JUMP ~[] destination: B11 -> B15  <||@
  Comment 259 block B3 null  <||@
  Comment 259 100 [] = LABEL numbPhis: 0 align: false label: ?  <||@
  Comment 259 -1 r10|DWORD = MOVE input: int[-32531|0xffffffffffff80ed]  <||@
  Comment 265 102 JUMP ~[] destination: B3 -> B4  <||@
  Comment 267 block B14 null  <||@
  Comment 267 112 [] = LABEL numbPhis: 0 align: false label: ?  <||@
  Comment 267 -1 r10|DWORD = MOVE input: int[-27955|0xffffffffffff92cd]  <||@
  Comment 273 114 JUMP ~[] destination: B14 -> B15  <||@
  Comment 275 {Stub<ExceptionHandlerStub.exceptionHandler>@0x106c4a620:CallingConvention[rax|QWORD[.], rdx|QWORD]:CallingConvention[rax|QWORD[.], rdx|QWORD]; temps=rdi|ILLEGAL,xmm0|ILLEGAL,xmm1|ILLEGAL,xmm2|ILLEGAL,xmm3|ILLEGAL,xmm4|ILLEGAL,xmm5|ILLEGAL,xmm6|ILLEGAL,xmm7|ILLEGAL,xmm8|ILLEGAL,xmm9|ILLEGAL,xmm10|ILLEGAL,xmm11|ILLEGAL,xmm12|ILLEGAL,xmm13|ILLEGAL,xmm14|ILLEGAL,xmm15|ILLEGAL,xmm16|ILLEGAL,xmm17|ILLEGAL,xmm18|ILLEGAL,xmm19|ILLEGAL,xmm20|ILLEGAL,xmm21|ILLEGAL,xmm22|ILLEGAL,xmm23|ILLEGAL,xmm24|ILLEGAL,xmm25|ILLEGAL,xmm26|ILLEGAL,xmm27|ILLEGAL,xmm28|ILLEGAL,xmm29|ILLEGAL,xmm30|ILLEGAL,xmm31|ILLEGAL,rax|ILLEGAL,rcx|ILLEGAL,rdx|ILLEGAL,rsi|ILLEGAL,r8|ILLEGAL,r9|ILLEGAL,r10|ILLEGAL,r11|ILLEGAL}  <||@
  Comment 275 4  <||@
  Comment 281 {Field[name=CompilerToVM::Data::SharedRuntime_deopt_blob_unpack, type=address, offset=0, address=0x105aa1f88, value=0x106807500]:0x106807500}  <||@
  Comment 281 5  <||@
  HexCodeFile>>> <|@
end_nmethod
