begin_compilation
  name " HotSpotCompilation-5857[org.graalvm.collections.EconomicMapImpl.clear()]"
  method "HotSpotCompilation-5857[org.graalvm.collections.EconomicMapImpl.clear()]"
  date 1527005198085
end_compilation
begin_cfg
  name "Final HIR schedule"
  begin_block
    name "B0"
    from_bci -1
    to_bci -1
    predecessors 
    successors 
    xhandlers
    flags 
    probability 4607182418800017408
    begin_IR
      HIR
f <@#|@fixed with next>@ <|@
tid v0 <|@
d <@d|@=== Debug Properties ===
stamp: void
=== Inputs ===
stateAfter: - 
=== Succesors ===
next: v17 
=== Usages ===
=== Predecessor ===
- >@ <|@
instruction <@StartNode|@org.graalvm.compiler.nodes.StartNode>@ stateAfter: - #next: v17  <|@  <|@
f <@~|@floating>@ <|@
tid a1 <|@
d <@d|@=== Debug Properties ===
index: 0
stamp: a!# Lorg/graalvm/collections/EconomicMapImpl;
uncheckedStamp: [null]
=== Inputs ===
=== Succesors ===
=== Usages ===
v30 v28 v31 v29 
=== Predecessor ===
- >@ <|@
instruction <@Parameter|@org.graalvm.compiler.nodes.ParameterNode>@  <|@  <|@
f <@~|@floating>@ <|@
tid v28 <|@
d <@d|@=== Debug Properties ===
displacement: 24
scale: Times1
stamp: void*
=== Inputs ===
base: a1 
index: - 
=== Succesors ===
=== Usages ===
v17 
=== Predecessor ===
- >@ <|@
instruction <@AMD64Address|@org.graalvm.compiler.core.amd64.AMD64AddressNode>@ base: a1 index: -  <|@  <|@
f <@~|@floating>@ <|@
tid a27 <|@
d <@d|@=== Debug Properties ===
isDefaultStable: false
nodeSourcePosition: at org.graalvm.collections.EconomicMapImpl.clear(EconomicMapImpl.java:597) [bci: 2]
rawvalue: null
stableDimension: 0
stamp: n - NULL
stampKind: n -
value: Object[null]
=== Inputs ===
=== Succesors ===
=== Usages ===
v17 v20 
=== Predecessor ===
- >@ <|@
instruction <@Constant|@org.graalvm.compiler.nodes.ConstantNode>@  <|@  <|@
f <@#|@fixed with next>@ <|@
tid v17 <|@
d <@d|@=== Debug Properties ===
barrierType: IMPRECISE
location: EconomicMapImpl.entries
nodeSourcePosition: at org.graalvm.collections.EconomicMapImpl.clear(EconomicMapImpl.java:597) [bci: 2]
nullCheck: false
stamp: void
=== Inputs ===
stateBefore: - 
guard: - 
address: v28 
value: a27 
stateAfter: - 
lastLocationAccess: - 
=== Succesors ===
next: v20 
=== Usages ===
=== Predecessor ===
v0 >@ <|@
instruction <@Write|@org.graalvm.compiler.nodes.memory.WriteNode>@ stateBefore: - guard: - address: v28 value: a27 stateAfter: - lastLocationAccess: - #next: v20  <|@  <|@
f <@~|@floating>@ <|@
tid v29 <|@
d <@d|@=== Debug Properties ===
displacement: 28
scale: Times1
stamp: void*
=== Inputs ===
base: a1 
index: - 
=== Succesors ===
=== Usages ===
v20 
=== Predecessor ===
- >@ <|@
instruction <@AMD64Address|@org.graalvm.compiler.core.amd64.AMD64AddressNode>@ base: a1 index: -  <|@  <|@
f <@#|@fixed with next>@ <|@
tid v20 <|@
d <@d|@=== Debug Properties ===
barrierType: IMPRECISE
location: EconomicMapImpl.hashArray
nodeSourcePosition: at org.graalvm.collections.EconomicMapImpl.clear(EconomicMapImpl.java:598) [bci: 7]
nullCheck: false
stamp: void
=== Inputs ===
stateBefore: - 
guard: - 
address: v29 
value: a27 
stateAfter: - 
lastLocationAccess: - 
=== Succesors ===
next: v23 
=== Usages ===
=== Predecessor ===
v17 >@ <|@
instruction <@Write|@org.graalvm.compiler.nodes.memory.WriteNode>@ stateBefore: - guard: - address: v29 value: a27 stateAfter: - lastLocationAccess: - #next: v23  <|@  <|@
f <@~|@floating>@ <|@
tid v30 <|@
d <@d|@=== Debug Properties ===
displacement: 16
scale: Times1
stamp: void*
=== Inputs ===
base: a1 
index: - 
=== Succesors ===
=== Usages ===
v23 
=== Predecessor ===
- >@ <|@
instruction <@AMD64Address|@org.graalvm.compiler.core.amd64.AMD64AddressNode>@ base: a1 index: -  <|@  <|@
f <@~|@floating>@ <|@
tid i8 <|@
d <@d|@=== Debug Properties ===
isDefaultStable: false
nodeSourcePosition: at org.graalvm.collections.EconomicMapImpl.clear(EconomicMapImpl.java:599) [bci: 12]
rawvalue: 0
stableDimension: 0
stamp: i32 [0] ⇈0000000000000000
stampKind: i32
value: int[0|0x0]
=== Inputs ===
=== Succesors ===
=== Usages ===
v23 v26 
=== Predecessor ===
- >@ <|@
instruction <@Constant|@org.graalvm.compiler.nodes.ConstantNode>@  <|@  <|@
f <@#|@fixed with next>@ <|@
tid v23 <|@
d <@d|@=== Debug Properties ===
barrierType: NONE
location: EconomicMapImpl.deletedEntries
nodeSourcePosition: at org.graalvm.collections.EconomicMapImpl.clear(EconomicMapImpl.java:599) [bci: 14]
nullCheck: false
stamp: void
=== Inputs ===
stateBefore: - 
guard: - 
address: v30 
value: i8 
stateAfter: - 
lastLocationAccess: - 
=== Succesors ===
next: v26 
=== Usages ===
=== Predecessor ===
v20 >@ <|@
instruction <@Write|@org.graalvm.compiler.nodes.memory.WriteNode>@ stateBefore: - guard: - address: v30 value: i8 stateAfter: - lastLocationAccess: - #next: v26  <|@  <|@
f <@~|@floating>@ <|@
tid v31 <|@
d <@d|@=== Debug Properties ===
displacement: 12
scale: Times1
stamp: void*
=== Inputs ===
base: a1 
index: - 
=== Succesors ===
=== Usages ===
v26 
=== Predecessor ===
- >@ <|@
instruction <@AMD64Address|@org.graalvm.compiler.core.amd64.AMD64AddressNode>@ base: a1 index: -  <|@  <|@
f <@#|@fixed with next>@ <|@
tid v26 <|@
d <@d|@=== Debug Properties ===
barrierType: NONE
location: EconomicMapImpl.totalEntries
nodeSourcePosition: at org.graalvm.collections.EconomicMapImpl.clear(EconomicMapImpl.java:599) [bci: 17]
nullCheck: false
stamp: void
=== Inputs ===
stateBefore: - 
guard: - 
address: v31 
value: i8 
stateAfter: - 
lastLocationAccess: - 
=== Succesors ===
next: v13 
=== Usages ===
=== Predecessor ===
v23 >@ <|@
instruction <@Write|@org.graalvm.compiler.nodes.memory.WriteNode>@ stateBefore: - guard: - address: v31 value: i8 stateAfter: - lastLocationAccess: - #next: v13  <|@  <|@
f <@*|@fixed>@ <|@
tid v13 <|@
d <@d|@=== Debug Properties ===
nodeSourcePosition: at org.graalvm.collections.EconomicMapImpl.clear(EconomicMapImpl.java:600) [bci: 20]
stamp: void
=== Inputs ===
result: - 
memoryMap: - 
=== Succesors ===
=== Usages ===
=== Predecessor ===
v26 >@ <|@
instruction <@Return|@org.graalvm.compiler.nodes.ReturnNode>@ result: - memoryMap: -  <|@  <|@
    end_IR
  end_block
end_cfg
begin_cfg
  name "After LIR generation"
  begin_block
    name "B0"
    from_bci -1
    to_bci -1
    predecessors 
    successors 
    xhandlers
    flags 
    probability 4607182418800017408
    begin_IR
      HIR
f <@#|@fixed with next>@ <|@
tid v0 <|@
d <@d|@=== Debug Properties ===
stamp: void
=== Inputs ===
stateAfter: - 
=== Succesors ===
next: v17 
=== Usages ===
=== Predecessor ===
- >@ <|@
instruction <@StartNode|@org.graalvm.compiler.nodes.StartNode>@ stateAfter: - #next: v17  <|@  <|@
f <@~|@floating>@ <|@
tid a1 <|@
result v0|QWORD[.] <|@
d <@d|@=== Debug Properties ===
index: 0
stamp: a!# Lorg/graalvm/collections/EconomicMapImpl;
uncheckedStamp: [null]
=== Inputs ===
=== Succesors ===
=== Usages ===
v30 v28 v31 v29 
=== Predecessor ===
- >@ <|@
instruction <@Parameter|@org.graalvm.compiler.nodes.ParameterNode>@  <|@  <|@
f <@~|@floating>@ <|@
tid v28 <|@
result [v0|QWORD[.] + 24] <|@
d <@d|@=== Debug Properties ===
displacement: 24
scale: Times1
stamp: void*
=== Inputs ===
base: a1 
index: - 
=== Succesors ===
=== Usages ===
v17 
=== Predecessor ===
- >@ <|@
instruction <@AMD64Address|@org.graalvm.compiler.core.amd64.AMD64AddressNode>@ base: a1 index: -  <|@  <|@
f <@~|@floating>@ <|@
tid a27 <|@
result Object[null] <|@
d <@d|@=== Debug Properties ===
isDefaultStable: false
nodeSourcePosition: at org.graalvm.collections.EconomicMapImpl.clear(EconomicMapImpl.java:597) [bci: 2]
rawvalue: null
stableDimension: 0
stamp: n - NULL
stampKind: n -
value: Object[null]
=== Inputs ===
=== Succesors ===
=== Usages ===
v17 v20 
=== Predecessor ===
- >@ <|@
instruction <@Constant|@org.graalvm.compiler.nodes.ConstantNode>@  <|@  <|@
f <@#|@fixed with next>@ <|@
tid v17 <|@
d <@d|@=== Debug Properties ===
barrierType: IMPRECISE
location: EconomicMapImpl.entries
nodeSourcePosition: at org.graalvm.collections.EconomicMapImpl.clear(EconomicMapImpl.java:597) [bci: 2]
nullCheck: false
stamp: void
=== Inputs ===
stateBefore: - 
guard: - 
address: v28 
value: a27 
stateAfter: - 
lastLocationAccess: - 
=== Succesors ===
next: v20 
=== Usages ===
=== Predecessor ===
v0 >@ <|@
instruction <@Write|@org.graalvm.compiler.nodes.memory.WriteNode>@ stateBefore: - guard: - address: v28 value: a27 stateAfter: - lastLocationAccess: - #next: v20  <|@  <|@
f <@~|@floating>@ <|@
tid v29 <|@
result [v0|QWORD[.] + 28] <|@
d <@d|@=== Debug Properties ===
displacement: 28
scale: Times1
stamp: void*
=== Inputs ===
base: a1 
index: - 
=== Succesors ===
=== Usages ===
v20 
=== Predecessor ===
- >@ <|@
instruction <@AMD64Address|@org.graalvm.compiler.core.amd64.AMD64AddressNode>@ base: a1 index: -  <|@  <|@
f <@#|@fixed with next>@ <|@
tid v20 <|@
d <@d|@=== Debug Properties ===
barrierType: IMPRECISE
location: EconomicMapImpl.hashArray
nodeSourcePosition: at org.graalvm.collections.EconomicMapImpl.clear(EconomicMapImpl.java:598) [bci: 7]
nullCheck: false
stamp: void
=== Inputs ===
stateBefore: - 
guard: - 
address: v29 
value: a27 
stateAfter: - 
lastLocationAccess: - 
=== Succesors ===
next: v23 
=== Usages ===
=== Predecessor ===
v17 >@ <|@
instruction <@Write|@org.graalvm.compiler.nodes.memory.WriteNode>@ stateBefore: - guard: - address: v29 value: a27 stateAfter: - lastLocationAccess: - #next: v23  <|@  <|@
f <@~|@floating>@ <|@
tid v30 <|@
result [v0|QWORD[.] + 16] <|@
d <@d|@=== Debug Properties ===
displacement: 16
scale: Times1
stamp: void*
=== Inputs ===
base: a1 
index: - 
=== Succesors ===
=== Usages ===
v23 
=== Predecessor ===
- >@ <|@
instruction <@AMD64Address|@org.graalvm.compiler.core.amd64.AMD64AddressNode>@ base: a1 index: -  <|@  <|@
f <@~|@floating>@ <|@
tid i8 <|@
result int[0|0x0] <|@
d <@d|@=== Debug Properties ===
isDefaultStable: false
nodeSourcePosition: at org.graalvm.collections.EconomicMapImpl.clear(EconomicMapImpl.java:599) [bci: 12]
rawvalue: 0
stableDimension: 0
stamp: i32 [0] ⇈0000000000000000
stampKind: i32
value: int[0|0x0]
=== Inputs ===
=== Succesors ===
=== Usages ===
v23 v26 
=== Predecessor ===
- >@ <|@
instruction <@Constant|@org.graalvm.compiler.nodes.ConstantNode>@  <|@  <|@
f <@#|@fixed with next>@ <|@
tid v23 <|@
d <@d|@=== Debug Properties ===
barrierType: NONE
location: EconomicMapImpl.deletedEntries
nodeSourcePosition: at org.graalvm.collections.EconomicMapImpl.clear(EconomicMapImpl.java:599) [bci: 14]
nullCheck: false
stamp: void
=== Inputs ===
stateBefore: - 
guard: - 
address: v30 
value: i8 
stateAfter: - 
lastLocationAccess: - 
=== Succesors ===
next: v26 
=== Usages ===
=== Predecessor ===
v20 >@ <|@
instruction <@Write|@org.graalvm.compiler.nodes.memory.WriteNode>@ stateBefore: - guard: - address: v30 value: i8 stateAfter: - lastLocationAccess: - #next: v26  <|@  <|@
f <@~|@floating>@ <|@
tid v31 <|@
result [v0|QWORD[.] + 12] <|@
d <@d|@=== Debug Properties ===
displacement: 12
scale: Times1
stamp: void*
=== Inputs ===
base: a1 
index: - 
=== Succesors ===
=== Usages ===
v26 
=== Predecessor ===
- >@ <|@
instruction <@AMD64Address|@org.graalvm.compiler.core.amd64.AMD64AddressNode>@ base: a1 index: -  <|@  <|@
f <@#|@fixed with next>@ <|@
tid v26 <|@
d <@d|@=== Debug Properties ===
barrierType: NONE
location: EconomicMapImpl.totalEntries
nodeSourcePosition: at org.graalvm.collections.EconomicMapImpl.clear(EconomicMapImpl.java:599) [bci: 17]
nullCheck: false
stamp: void
=== Inputs ===
stateBefore: - 
guard: - 
address: v31 
value: i8 
stateAfter: - 
lastLocationAccess: - 
=== Succesors ===
next: v13 
=== Usages ===
=== Predecessor ===
v23 >@ <|@
instruction <@Write|@org.graalvm.compiler.nodes.memory.WriteNode>@ stateBefore: - guard: - address: v31 value: i8 stateAfter: - lastLocationAccess: - #next: v13  <|@  <|@
f <@*|@fixed>@ <|@
tid v13 <|@
d <@d|@=== Debug Properties ===
nodeSourcePosition: at org.graalvm.collections.EconomicMapImpl.clear(EconomicMapImpl.java:600) [bci: 20]
stamp: void
=== Inputs ===
result: - 
memoryMap: - 
=== Succesors ===
=== Usages ===
=== Predecessor ===
v26 >@ <|@
instruction <@Return|@org.graalvm.compiler.nodes.ReturnNode>@ result: - memoryMap: -  <|@  <|@
    end_IR
    begin_IR
      LIR
      nr   -1  <|@ instruction [rsi|QWORD[.], rbp|QWORD] = LABEL numbPhis: 0 align: false label: ? <|@ <|@
      nr   -1  <|@ instruction v1|QWORD = MOVE rbp|QWORD moveKind: QWORD <|@ <|@
      nr   -1  <|@ instruction [] = HOTSPOTLOCKSTACK frameMapBuilder: org.graalvm.compiler.lir.amd64.AMD64FrameMapBuilder@381ff811 slotKind: QWORD <|@ <|@
      nr   -1  <|@ instruction v0|QWORD[.] = MOVE rsi|QWORD[.] moveKind: QWORD <|@ <|@
      nr   -1  <|@ instruction MOV (x: [v0|QWORD[.] + 24], y: r12|ILLEGAL) size: DWORD <|@ <|@
      nr   -1  <|@ instruction MOV (x: [v0|QWORD[.] + 28], y: r12|ILLEGAL) size: DWORD <|@ <|@
      nr   -1  <|@ instruction MOV (x: [v0|QWORD[.] + 16], y: r12|ILLEGAL) size: DWORD <|@ <|@
      nr   -1  <|@ instruction MOV (x: [v0|QWORD[.] + 12], y: r12|ILLEGAL) size: DWORD <|@ <|@
      nr   -1  <|@ instruction RETURN (savedRbp: v1|QWORD, value: -) isStub: false thread: r15 scratchForSafepointOnReturn: rcx config: org.graalvm.compiler.hotspot.GraalHotSpotVMConfig@7222fe45 <|@ <|@
    end_IR
  end_block
end_cfg
begin_cfg
  name "After PreAllocationOptimizationStage"
  begin_block
    name "B0"
    from_bci -1
    to_bci -1
    predecessors 
    successors 
    xhandlers
    flags 
    probability 4607182418800017408
    begin_IR
      LIR
      nr   -1  <|@ instruction [rsi|QWORD[.], rbp|QWORD] = LABEL numbPhis: 0 align: false label: ? <|@ <|@
      nr   -1  <|@ instruction v1|QWORD = MOVE rbp|QWORD moveKind: QWORD <|@ <|@
      nr   -1  <|@ instruction [] = HOTSPOTLOCKSTACK frameMapBuilder: org.graalvm.compiler.lir.amd64.AMD64FrameMapBuilder@381ff811 slotKind: QWORD <|@ <|@
      nr   -1  <|@ instruction v0|QWORD[.] = MOVE rsi|QWORD[.] moveKind: QWORD <|@ <|@
      nr   -1  <|@ instruction MOV (x: [v0|QWORD[.] + 24], y: r12|ILLEGAL) size: DWORD <|@ <|@
      nr   -1  <|@ instruction MOV (x: [v0|QWORD[.] + 28], y: r12|ILLEGAL) size: DWORD <|@ <|@
      nr   -1  <|@ instruction MOV (x: [v0|QWORD[.] + 16], y: r12|ILLEGAL) size: DWORD <|@ <|@
      nr   -1  <|@ instruction MOV (x: [v0|QWORD[.] + 12], y: r12|ILLEGAL) size: DWORD <|@ <|@
      nr   -1  <|@ instruction RETURN (savedRbp: v1|QWORD, value: -) isStub: false thread: r15 scratchForSafepointOnReturn: rcx config: org.graalvm.compiler.hotspot.GraalHotSpotVMConfig@7222fe45 <|@ <|@
    end_IR
  end_block
end_cfg
begin_bytecodes
     0: aload_0       
     1: aconst_null   
     2: putfield      #22         // entries:java.lang.Object[]
     5: aload_0       
     6: aconst_null   
     7: putfield      #24         // hashArray:byte[]
    10: aload_0       
    11: aload_0       
    12: iconst_0      
    13: dup_x1        
    14: putfield      #21         // deletedEntries:int
    17: putfield      #5          // totalEntries:int
    20: return        
   <|@
end_bytecodes
begin_cfg
  name "After AllocationStage"
  begin_block
    name "B0"
    from_bci -1
    to_bci -1
    predecessors 
    successors 
    xhandlers
    flags 
    probability 4607182418800017408
    begin_IR
      LIR
      nr    0  <|@ instruction [rsi|QWORD[.], rbp|QWORD] = LABEL numbPhis: 0 align: false label: ? <|@ <|@
      nr    4  <|@ instruction [] = HOTSPOTLOCKSTACK frameMapBuilder: org.graalvm.compiler.lir.amd64.AMD64FrameMapBuilder@381ff811 slotKind: QWORD <|@ <|@
      nr    8  <|@ instruction MOV (x: [rsi|QWORD[.] + 24], y: r12|ILLEGAL) size: DWORD <|@ <|@
      nr   10  <|@ instruction MOV (x: [rsi|QWORD[.] + 28], y: r12|ILLEGAL) size: DWORD <|@ <|@
      nr   12  <|@ instruction MOV (x: [rsi|QWORD[.] + 16], y: r12|ILLEGAL) size: DWORD <|@ <|@
      nr   14  <|@ instruction MOV (x: [rsi|QWORD[.] + 12], y: r12|ILLEGAL) size: DWORD <|@ <|@
      nr   16  <|@ instruction RETURN (savedRbp: rbp|QWORD, value: -) isStub: false thread: r15 scratchForSafepointOnReturn: rcx config: org.graalvm.compiler.hotspot.GraalHotSpotVMConfig@7222fe45 <|@ <|@
    end_IR
  end_block
end_cfg
begin_bytecodes
     0: aload_0       
     1: aconst_null   
     2: putfield      #22         // entries:java.lang.Object[]
     5: aload_0       
     6: aconst_null   
     7: putfield      #24         // hashArray:byte[]
    10: aload_0       
    11: aload_0       
    12: iconst_0      
    13: dup_x1        
    14: putfield      #21         // deletedEntries:int
    17: putfield      #5          // totalEntries:int
    20: return        
   <|@
end_bytecodes
begin_cfg
  name "After PostAllocationOptimizationStage"
  begin_block
    name "B0"
    from_bci -1
    to_bci -1
    predecessors 
    successors 
    xhandlers
    flags 
    probability 4607182418800017408
    begin_IR
      LIR
      nr    0  <|@ instruction [rsi|QWORD[.], rbp|QWORD] = LABEL numbPhis: 0 align: false label: ? <|@ <|@
      nr    4  <|@ instruction [] = HOTSPOTLOCKSTACK frameMapBuilder: org.graalvm.compiler.lir.amd64.AMD64FrameMapBuilder@381ff811 slotKind: QWORD <|@ <|@
      nr    8  <|@ instruction MOV (x: [rsi|QWORD[.] + 24], y: r12|ILLEGAL) size: DWORD <|@ <|@
      nr   10  <|@ instruction MOV (x: [rsi|QWORD[.] + 28], y: r12|ILLEGAL) size: DWORD <|@ <|@
      nr   12  <|@ instruction MOV (x: [rsi|QWORD[.] + 16], y: r12|ILLEGAL) size: DWORD <|@ <|@
      nr   14  <|@ instruction MOV (x: [rsi|QWORD[.] + 12], y: r12|ILLEGAL) size: DWORD <|@ <|@
      nr   16  <|@ instruction RETURN (savedRbp: rbp|QWORD, value: -) isStub: false thread: r15 scratchForSafepointOnReturn: rcx config: org.graalvm.compiler.hotspot.GraalHotSpotVMConfig@7222fe45 <|@ <|@
    end_IR
  end_block
end_cfg
begin_bytecodes
     0: aload_0       
     1: aconst_null   
     2: putfield      #22         // entries:java.lang.Object[]
     5: aload_0       
     6: aconst_null   
     7: putfield      #24         // hashArray:byte[]
    10: aload_0       
    11: aload_0       
    12: iconst_0      
    13: dup_x1        
    14: putfield      #21         // deletedEntries:int
    17: putfield      #5          // totalEntries:int
    20: return        
   <|@
end_bytecodes
begin_cfg
  name "After code generation"
end_cfg
begin_nmethod
  <<<HexCodeFile
  Platform AMD64 64  <||@
  HexCode 0 448b560849c1e203493bc20f85efffffff900f1f80000000000f1f80000000000f1f440000448966184489661c448966104489660c850500000000c5f877c3e80000000090e80000000090  <||@
  Comment 0 2  <||@
  Comment 11 {Field[name=CompilerToVM::Data::SharedRuntime_ic_miss_stub, type=address, offset=0, address=0x105aa1f78, value=0x106805e60]:0x106805e60}  <||@
  Comment 32 3  <||@
  Comment 32 1  <||@
  Comment 37 block B0 null  <||@
  Comment 37 0 [rsi|QWORD[.], rbp|QWORD] = LABEL numbPhis: 0 align: false label: ?  <||@
  Comment 37 4 [] = HOTSPOTLOCKSTACK frameMapBuilder: org.graalvm.compiler.lir.amd64.AMD64FrameMapBuilder@381ff811 slotKind: QWORD  <||@
  Comment 37 8 MOV (x: [rsi|QWORD[.] + 24], y: r12|ILLEGAL) size: DWORD  <||@
  Comment 41 10 MOV (x: [rsi|QWORD[.] + 28], y: r12|ILLEGAL) size: DWORD  <||@
  Comment 45 12 MOV (x: [rsi|QWORD[.] + 16], y: r12|ILLEGAL) size: DWORD  <||@
  Comment 49 14 MOV (x: [rsi|QWORD[.] + 12], y: r12|ILLEGAL) size: DWORD  <||@
  Comment 53 16 RETURN (savedRbp: rbp|QWORD, value: -) isStub: false thread: r15 scratchForSafepointOnReturn: rcx config: org.graalvm.compiler.hotspot.GraalHotSpotVMConfig@7222fe45  <||@
  Comment 53 12  <||@
  Comment 63 {Stub<ExceptionHandlerStub.exceptionHandler>@0x106c4a620:CallingConvention[rax|QWORD[.], rdx|QWORD]:CallingConvention[rax|QWORD[.], rdx|QWORD]; temps=rdi|ILLEGAL,xmm0|ILLEGAL,xmm1|ILLEGAL,xmm2|ILLEGAL,xmm3|ILLEGAL,xmm4|ILLEGAL,xmm5|ILLEGAL,xmm6|ILLEGAL,xmm7|ILLEGAL,xmm8|ILLEGAL,xmm9|ILLEGAL,xmm10|ILLEGAL,xmm11|ILLEGAL,xmm12|ILLEGAL,xmm13|ILLEGAL,xmm14|ILLEGAL,xmm15|ILLEGAL,xmm16|ILLEGAL,xmm17|ILLEGAL,xmm18|ILLEGAL,xmm19|ILLEGAL,xmm20|ILLEGAL,xmm21|ILLEGAL,xmm22|ILLEGAL,xmm23|ILLEGAL,xmm24|ILLEGAL,xmm25|ILLEGAL,xmm26|ILLEGAL,xmm27|ILLEGAL,xmm28|ILLEGAL,xmm29|ILLEGAL,xmm30|ILLEGAL,xmm31|ILLEGAL,rax|ILLEGAL,rcx|ILLEGAL,rdx|ILLEGAL,rsi|ILLEGAL,r8|ILLEGAL,r9|ILLEGAL,r10|ILLEGAL,r11|ILLEGAL}  <||@
  Comment 63 4  <||@
  Comment 69 {Field[name=CompilerToVM::Data::SharedRuntime_deopt_blob_unpack, type=address, offset=0, address=0x105aa1f88, value=0x106807500]:0x106807500}  <||@
  Comment 69 5  <||@
  HexCodeFile>>> <|@
end_nmethod
begin_compilation
  name " HotSpotCompilation-5857[org.graalvm.collections.EconomicMapImpl.clear()]"
  method "HotSpotCompilation-5857[org.graalvm.collections.EconomicMapImpl.clear()]"
  date 1527005198101
end_compilation
begin_cfg
  name "After code installation"
end_cfg
begin_nmethod
  <<<HexCodeFile
  Platform AMD64 64  <||@
  HexCode 106b918a0 448b560849c1e203493bc20f85af45c7ff900f1f80000000000f1f80000000000f1f440000448966184489661c448966104489660c85052bd7cffdc5f877c3e83c8d0b0090e8165cc7ff90f4f4f4f4f4  <||@
  Comment 0 2  <||@
  Comment 11 {Field[name=CompilerToVM::Data::SharedRuntime_ic_miss_stub, type=address, offset=0, address=0x105aa1f78, value=0x106805e60]:0x106805e60}  <||@
  Comment 32 3  <||@
  Comment 32 1  <||@
  Comment 37 block B0 null  <||@
  Comment 37 0 [rsi|QWORD[.], rbp|QWORD] = LABEL numbPhis: 0 align: false label: ?  <||@
  Comment 37 4 [] = HOTSPOTLOCKSTACK frameMapBuilder: org.graalvm.compiler.lir.amd64.AMD64FrameMapBuilder@381ff811 slotKind: QWORD  <||@
  Comment 37 8 MOV (x: [rsi|QWORD[.] + 24], y: r12|ILLEGAL) size: DWORD  <||@
  Comment 41 10 MOV (x: [rsi|QWORD[.] + 28], y: r12|ILLEGAL) size: DWORD  <||@
  Comment 45 12 MOV (x: [rsi|QWORD[.] + 16], y: r12|ILLEGAL) size: DWORD  <||@
  Comment 49 14 MOV (x: [rsi|QWORD[.] + 12], y: r12|ILLEGAL) size: DWORD  <||@
  Comment 53 16 RETURN (savedRbp: rbp|QWORD, value: -) isStub: false thread: r15 scratchForSafepointOnReturn: rcx config: org.graalvm.compiler.hotspot.GraalHotSpotVMConfig@7222fe45  <||@
  Comment 53 12  <||@
  Comment 63 {Stub<ExceptionHandlerStub.exceptionHandler>@0x106c4a620:CallingConvention[rax|QWORD[.], rdx|QWORD]:CallingConvention[rax|QWORD[.], rdx|QWORD]; temps=rdi|ILLEGAL,xmm0|ILLEGAL,xmm1|ILLEGAL,xmm2|ILLEGAL,xmm3|ILLEGAL,xmm4|ILLEGAL,xmm5|ILLEGAL,xmm6|ILLEGAL,xmm7|ILLEGAL,xmm8|ILLEGAL,xmm9|ILLEGAL,xmm10|ILLEGAL,xmm11|ILLEGAL,xmm12|ILLEGAL,xmm13|ILLEGAL,xmm14|ILLEGAL,xmm15|ILLEGAL,xmm16|ILLEGAL,xmm17|ILLEGAL,xmm18|ILLEGAL,xmm19|ILLEGAL,xmm20|ILLEGAL,xmm21|ILLEGAL,xmm22|ILLEGAL,xmm23|ILLEGAL,xmm24|ILLEGAL,xmm25|ILLEGAL,xmm26|ILLEGAL,xmm27|ILLEGAL,xmm28|ILLEGAL,xmm29|ILLEGAL,xmm30|ILLEGAL,xmm31|ILLEGAL,rax|ILLEGAL,rcx|ILLEGAL,rdx|ILLEGAL,rsi|ILLEGAL,r8|ILLEGAL,r9|ILLEGAL,r10|ILLEGAL,r11|ILLEGAL}  <||@
  Comment 63 4  <||@
  Comment 69 {Field[name=CompilerToVM::Data::SharedRuntime_deopt_blob_unpack, type=address, offset=0, address=0x105aa1f88, value=0x106807500]:0x106807500}  <||@
  Comment 69 5  <||@
  HexCodeFile>>> <|@
end_nmethod
