begin_compilation
  name " HotSpotCompilation-6114[java.util.TreeMap.successor(TreeMap$Entry)]"
  method "HotSpotCompilation-6114[java.util.TreeMap.successor(TreeMap$Entry)]"
  date 1527005115636
end_compilation
begin_cfg
  name "Final HIR schedule"
  begin_block
    name "B0"
    from_bci -1
    to_bci -1
    predecessors 
    successors "B1" "B7" 
    xhandlers
    flags 
    probability 4607182418800017408
    begin_IR
      HIR
f <@#|@fixed with next>@ <|@
tid v0 <|@
d <@d|@=== Debug Properties ===
stamp: void
=== Inputs ===
stateAfter: - 
=== Succesors ===
next: a110 
=== Usages ===
=== Predecessor ===
- >@ <|@
instruction <@StartNode|@org.graalvm.compiler.nodes.StartNode>@ stateAfter: - #next: a110  <|@  <|@
f <@~|@floating>@ <|@
tid a115 <|@
d <@d|@=== Debug Properties ===
isDefaultStable: false
rawvalue: null
stableDimension: 0
stamp: a - NULL
stampKind: a -
value: Object[null]
=== Inputs ===
=== Succesors ===
=== Usages ===
?2 v57 
=== Predecessor ===
- >@ <|@
instruction <@Constant|@org.graalvm.compiler.nodes.ConstantNode>@  <|@  <|@
tid ?2 <|@
d <@d|@=== Debug Properties ===
bci: 0
code: ResolvedJavaMethodBytecode<TreeMap.successor(TreeMap$Entry)>
duringCall: false
localsSize: 3
locksSize: 0
rethrowException: false
sourceFile: TreeMap.java
sourceLine: 2149
stackSize: 0
=== Inputs ===
outerFrameState: - 
values: a115 - - 
=== Succesors ===
=== Usages ===
a110 
=== Predecessor ===
- >@ <|@
instruction <@FrameState|@org.graalvm.compiler.nodes.FrameState>@ outerFrameState: - values: a115 - -  <|@  <|@
f <@~|@floating>@ <|@
tid a1 <|@
d <@d|@=== Debug Properties ===
index: 0
stamp: a# Ljava/util/TreeMap$Entry;
uncheckedStamp: [null]
=== Inputs ===
=== Succesors ===
=== Usages ===
v116 a33 v117 
=== Predecessor ===
- >@ <|@
instruction <@Parameter|@org.graalvm.compiler.nodes.ParameterNode>@  <|@  <|@
f <@~|@floating>@ <|@
tid v116 <|@
d <@d|@=== Debug Properties ===
displacement: 28
scale: Times1
stamp: void*
=== Inputs ===
base: a1 
index: - 
=== Succesors ===
=== Usages ===
a110 
=== Predecessor ===
- >@ <|@
instruction <@AMD64Address|@org.graalvm.compiler.core.amd64.AMD64AddressNode>@ base: a1 index: -  <|@  <|@
f <@#|@fixed with next>@ <|@
tid a110 <|@
d <@d|@=== Debug Properties ===
barrierType: NONE
forceFixed: false
location: TreeMap$Entry.right
nodeSourcePosition: at java.util.TreeMap.successor(TreeMap.java:2151) [bci: 7]
nullCheck: true
stamp: n# Ljava/util/TreeMap$Entry;
=== Inputs ===
stateBefore: ?2 
guard: - 
address: v116 
=== Succesors ===
next: v10 
=== Usages ===
a72 v92 
=== Predecessor ===
v0 >@ <|@
instruction <@Read|@org.graalvm.compiler.nodes.memory.ReadNode>@ stateBefore: ?2 guard: - address: v116 #next: v10  <|@  <|@
f <@~|@floating>@ <|@
tid v92 <|@
d <@d|@=== Debug Properties ===
nodeSourcePosition: at java.util.TreeMap.successor(TreeMap.java:2151) [bci: 10]
stamp: void
=== Inputs ===
value: a110 
=== Succesors ===
=== Usages ===
v10 
=== Predecessor ===
- >@ <|@
instruction <@IsNull|@org.graalvm.compiler.nodes.calc.IsNullNode>@ value: a110  <|@  <|@
f <@*|@fixed>@ <|@
tid v10 <|@
d <@d|@=== Debug Properties ===
nodeSourcePosition: at java.util.TreeMap.successor(TreeMap.java:2151) [bci: 10]
stamp: void
trueSuccessorProbability: 0.6272184924666058
=== Inputs ===
condition: v92 
=== Succesors ===
trueSuccessor: v8 
falseSuccessor: v9 
=== Usages ===
=== Predecessor ===
a110 >@ <|@
instruction <@If|@org.graalvm.compiler.nodes.IfNode>@ condition: v92 #trueSuccessor: v8 #falseSuccessor: v9  <|@  <|@
    end_IR
  end_block
  begin_block
    name "B1"
    from_bci -1
    to_bci -1
    predecessors "B0" 
    successors "B2" 
    xhandlers
    flags 
    probability 4603824701483181396
    begin_IR
      HIR
f <@#|@fixed with next>@ <|@
tid v8 <|@
d <@d|@=== Debug Properties ===
nodeSourcePosition: at java.util.TreeMap.successor(TreeMap.java:2157) [bci: 35]
stamp: void
=== Inputs ===
=== Succesors ===
next: a111 
=== Usages ===
=== Predecessor ===
v10 >@ <|@
instruction <@Begin|@org.graalvm.compiler.nodes.BeginNode>@ #next: a111  <|@  <|@
f <@~|@floating>@ <|@
tid v117 <|@
d <@d|@=== Debug Properties ===
displacement: 32
scale: Times1
stamp: void*
=== Inputs ===
base: a1 
index: - 
=== Succesors ===
=== Usages ===
a111 
=== Predecessor ===
- >@ <|@
instruction <@AMD64Address|@org.graalvm.compiler.core.amd64.AMD64AddressNode>@ base: a1 index: -  <|@  <|@
f <@#|@fixed with next>@ <|@
tid a111 <|@
d <@d|@=== Debug Properties ===
barrierType: NONE
forceFixed: false
location: TreeMap$Entry.parent
nodeSourcePosition: at java.util.TreeMap.successor(TreeMap.java:2157) [bci: 36]
nullCheck: false
stamp: n# Ljava/util/TreeMap$Entry;
=== Inputs ===
stateBefore: - 
guard: - 
address: v117 
=== Succesors ===
next: v30 
=== Usages ===
a76 
=== Predecessor ===
v8 >@ <|@
instruction <@Read|@org.graalvm.compiler.nodes.memory.ReadNode>@ stateBefore: - guard: - address: v117 #next: v30  <|@  <|@
f <@~|@floating>@ <|@
tid a76 <|@
d <@d|@=== Debug Properties ===
encoding: base: 0 shift: 3
nodeSourcePosition: at java.util.TreeMap.successor(TreeMap.java:2157) [bci: 36]
op: Uncompress
stamp: a# Ljava/util/TreeMap$Entry;
=== Inputs ===
value: a111 
=== Succesors ===
=== Usages ===
a32 
=== Predecessor ===
- >@ <|@
instruction <@HotSpotCompression|@org.graalvm.compiler.hotspot.nodes.HotSpotCompressionNode>@ value: a111  <|@  <|@
f <@*|@fixed>@ <|@
tid v30 <|@
d <@d|@=== Debug Properties ===
nodeSourcePosition: at java.util.TreeMap.successor(TreeMap.java:2159) [bci: 42]
stamp: void
=== Inputs ===
=== Succesors ===
=== Usages ===
v31 
=== Predecessor ===
a111 >@ <|@
instruction <@EndNode|@org.graalvm.compiler.nodes.EndNode>@  <|@  <|@
    end_IR
  end_block
  begin_block
    name "B2"
    from_bci -1
    to_bci -1
    predecessors "B1" "B5" 
    successors "B3" "B4" 
    xhandlers
    flags "llh" 
    loop_index 0
    loop_depth 1
    probability 4607181169815389981
    begin_IR
      HIR
f <@~|@floating>@ <|@
tid a32 <|@
d <@d|@=== Debug Properties ===
stamp: a# Ljava/util/TreeMap$Entry;
valueDescription: a -
=== Inputs ===
merge: v31 
values: a76 a84 
=== Succesors ===
=== Usages ===
?34 v35 v118 v119 v58 a33 
=== Predecessor ===
- >@ <|@
instruction <@ValuePhi|@org.graalvm.compiler.nodes.ValuePhiNode>@ merge: v31 values: a76 a84  <|@  <|@
f <@~|@floating>@ <|@
tid a33 <|@
d <@d|@=== Debug Properties ===
stamp: a# Ljava/util/TreeMap$Entry;
valueDescription: a -
=== Inputs ===
merge: v31 
values: a1 a32 
=== Succesors ===
=== Usages ===
?34 v43 
=== Predecessor ===
- >@ <|@
instruction <@ValuePhi|@org.graalvm.compiler.nodes.ValuePhiNode>@ merge: v31 values: a1 a32  <|@  <|@
f <@#|@fixed with next>@ <|@
tid v31 <|@
d <@d|@=== Debug Properties ===
canEndsSafepoint: true
inversionCount: 0
loopFrequency: 1.594119667803253
loopOrigFrequency: 1.0
loopType: SIMPLE_LOOP
nextEndIndex: 1
nodeSourcePosition: at java.util.TreeMap.successor(TreeMap.java:2159) [bci: 42]
splits: 0
stamp: void
unrollFactor: 1
unswitches: 0
=== Inputs ===
stateAfter: - 
overflowGuard: - 
ends: v30 
=== Succesors ===
next: v41 
=== Usages ===
a32 a33 v37 v48 v54 
=== Predecessor ===
- >@ <|@
instruction <@LoopBegin|@org.graalvm.compiler.nodes.LoopBeginNode>@ stateAfter: - overflowGuard: - ends: v30 #next: v41  <|@  <|@
f <@~|@floating>@ <|@
tid v35 <|@
d <@d|@=== Debug Properties ===
nodeSourcePosition: at java.util.TreeMap.successor(TreeMap.java:2159) [bci: 43]
stamp: void
=== Inputs ===
value: a32 
=== Succesors ===
=== Usages ===
v41 
=== Predecessor ===
- >@ <|@
instruction <@IsNull|@org.graalvm.compiler.nodes.calc.IsNullNode>@ value: a32  <|@  <|@
f <@*|@fixed>@ <|@
tid v41 <|@
d <@d|@=== Debug Properties ===
nodeSourcePosition: at java.util.TreeMap.successor(TreeMap.java:2159) [bci: 43]
stamp: void
trueSuccessorProbability: 0.28169668610986476
=== Inputs ===
condition: v35 
=== Succesors ===
trueSuccessor: v37 
falseSuccessor: v40 
=== Usages ===
=== Predecessor ===
v31 >@ <|@
instruction <@If|@org.graalvm.compiler.nodes.IfNode>@ condition: v35 #trueSuccessor: v37 #falseSuccessor: v40  <|@  <|@
    end_IR
  end_block
  begin_block
    name "B3"
    from_bci -1
    to_bci -1
    predecessors "B2" 
    successors 
    xhandlers
    flags 
    probability 4598745512610628385
    begin_IR
      HIR
f <@#|@fixed with next>@ <|@
tid v37 <|@
d <@d|@=== Debug Properties ===
nodeSourcePosition: at java.util.TreeMap.successor(TreeMap.java:2163) [bci: 64]
stamp: void
=== Inputs ===
stateAfter: - 
loopBegin: v31 
=== Succesors ===
next: v57 
=== Usages ===
=== Predecessor ===
v41 >@ <|@
instruction <@LoopExit|@org.graalvm.compiler.nodes.LoopExitNode>@ stateAfter: - loopBegin: v31 #next: v57  <|@  <|@
f <@*|@fixed>@ <|@
tid v57 <|@
d <@d|@=== Debug Properties ===
nodeSourcePosition: at java.util.TreeMap.successor(TreeMap.java:2163) [bci: 64]
stamp: void
=== Inputs ===
result: a115 
memoryMap: - 
=== Succesors ===
=== Usages ===
=== Predecessor ===
v37 >@ <|@
instruction <@Return|@org.graalvm.compiler.nodes.ReturnNode>@ result: a115 memoryMap: -  <|@  <|@
    end_IR
  end_block
  begin_block
    name "B4"
    from_bci -1
    to_bci -1
    predecessors "B2" 
    successors "B5" "B6" 
    xhandlers
    flags 
    loop_index 0
    loop_depth 1
    probability 4604644223469028748
    begin_IR
      HIR
f <@#|@fixed with next>@ <|@
tid v40 <|@
d <@d|@=== Debug Properties ===
nodeSourcePosition: at java.util.TreeMap.successor(TreeMap.java:2159) [bci: 46]
stamp: void
=== Inputs ===
=== Succesors ===
next: a112 
=== Usages ===
=== Predecessor ===
v41 >@ <|@
instruction <@Begin|@org.graalvm.compiler.nodes.BeginNode>@ #next: a112  <|@  <|@
f <@~|@floating>@ <|@
tid v118 <|@
d <@d|@=== Debug Properties ===
displacement: 28
scale: Times1
stamp: void*
=== Inputs ===
base: a32 
index: - 
=== Succesors ===
=== Usages ===
a112 
=== Predecessor ===
- >@ <|@
instruction <@AMD64Address|@org.graalvm.compiler.core.amd64.AMD64AddressNode>@ base: a32 index: -  <|@  <|@
f <@#|@fixed with next>@ <|@
tid a112 <|@
d <@d|@=== Debug Properties ===
barrierType: NONE
forceFixed: false
location: TreeMap$Entry.right
nodeSourcePosition: at java.util.TreeMap.successor(TreeMap.java:2159) [bci: 48]
nullCheck: false
stamp: n# Ljava/util/TreeMap$Entry;
=== Inputs ===
stateBefore: - 
guard: - 
address: v118 
=== Succesors ===
next: v52 
=== Usages ===
a81 
=== Predecessor ===
v40 >@ <|@
instruction <@Read|@org.graalvm.compiler.nodes.memory.ReadNode>@ stateBefore: - guard: - address: v118 #next: v52  <|@  <|@
f <@~|@floating>@ <|@
tid a81 <|@
d <@d|@=== Debug Properties ===
encoding: base: 0 shift: 3
nodeSourcePosition: at java.util.TreeMap.successor(TreeMap.java:2159) [bci: 48]
op: Uncompress
stamp: a# Ljava/util/TreeMap$Entry;
=== Inputs ===
value: a112 
=== Succesors ===
=== Usages ===
v43 
=== Predecessor ===
- >@ <|@
instruction <@HotSpotCompression|@org.graalvm.compiler.hotspot.nodes.HotSpotCompressionNode>@ value: a112  <|@  <|@
f <@~|@floating>@ <|@
tid v43 <|@
d <@d|@=== Debug Properties ===
condition: EQ
nodeSourcePosition: at java.util.TreeMap.successor(TreeMap.java:2159) [bci: 51]
stamp: void
unorderedIsTrue: false
=== Inputs ===
x: a33 
y: a81 
=== Succesors ===
=== Usages ===
v52 
=== Predecessor ===
- >@ <|@
instruction <@==|@org.graalvm.compiler.nodes.calc.ObjectEqualsNode>@ x: a33 y: a81  <|@  <|@
f <@*|@fixed>@ <|@
tid v52 <|@
d <@d|@=== Debug Properties ===
nodeSourcePosition: at java.util.TreeMap.successor(TreeMap.java:2159) [bci: 51]
stamp: void
trueSuccessorProbability: 0.5188539645005614
=== Inputs ===
condition: v43 
=== Succesors ===
trueSuccessor: v44 
falseSuccessor: v48 
=== Usages ===
=== Predecessor ===
a112 >@ <|@
instruction <@If|@org.graalvm.compiler.nodes.IfNode>@ condition: v43 #trueSuccessor: v44 #falseSuccessor: v48  <|@  <|@
    end_IR
  end_block
  begin_block
    name "B5"
    from_bci -1
    to_bci -1
    predecessors "B4" 
    successors "B2" 
    xhandlers
    flags "lle" 
    loop_index 0
    loop_depth 1
    probability 4600384556582323090
    begin_IR
      HIR
f <@#|@fixed with next>@ <|@
tid v44 <|@
d <@d|@=== Debug Properties ===
nodeSourcePosition: at java.util.TreeMap.successor(TreeMap.java:2160) [bci: 54]
stamp: void
=== Inputs ===
=== Succesors ===
next: v100 
=== Usages ===
=== Predecessor ===
v52 >@ <|@
instruction <@Begin|@org.graalvm.compiler.nodes.BeginNode>@ #next: v100  <|@  <|@
tid ?34 <|@
d <@d|@=== Debug Properties ===
bci: 42
code: ResolvedJavaMethodBytecode<TreeMap.successor(TreeMap$Entry)>
duringCall: false
localsSize: 3
locksSize: 0
rethrowException: false
sourceFile: TreeMap.java
sourceLine: 2159
stackSize: 0
=== Inputs ===
outerFrameState: - 
values: - a32 a33 
=== Succesors ===
=== Usages ===
v100 
=== Predecessor ===
- >@ <|@
instruction <@FrameState|@org.graalvm.compiler.nodes.FrameState>@ outerFrameState: - values: - a32 a33  <|@  <|@
f <@#|@fixed with next>@ <|@
tid v100 <|@
d <@d|@=== Debug Properties ===
stamp: void
=== Inputs ===
stateBefore: ?34 
=== Succesors ===
next: a113 
=== Usages ===
=== Predecessor ===
v44 >@ <|@
instruction <@Safepoint|@org.graalvm.compiler.nodes.SafepointNode>@ stateBefore: ?34 #next: a113  <|@  <|@
f <@~|@floating>@ <|@
tid v119 <|@
d <@d|@=== Debug Properties ===
displacement: 32
scale: Times1
stamp: void*
=== Inputs ===
base: a32 
index: - 
=== Succesors ===
=== Usages ===
a113 
=== Predecessor ===
- >@ <|@
instruction <@AMD64Address|@org.graalvm.compiler.core.amd64.AMD64AddressNode>@ base: a32 index: -  <|@  <|@
f <@#|@fixed with next>@ <|@
tid a113 <|@
d <@d|@=== Debug Properties ===
barrierType: NONE
forceFixed: false
location: TreeMap$Entry.parent
nodeSourcePosition: at java.util.TreeMap.successor(TreeMap.java:2161) [bci: 57]
nullCheck: false
stamp: n# Ljava/util/TreeMap$Entry;
=== Inputs ===
stateBefore: - 
guard: - 
address: v119 
=== Succesors ===
next: v54 
=== Usages ===
a84 
=== Predecessor ===
v100 >@ <|@
instruction <@Read|@org.graalvm.compiler.nodes.memory.ReadNode>@ stateBefore: - guard: - address: v119 #next: v54  <|@  <|@
f <@~|@floating>@ <|@
tid a84 <|@
d <@d|@=== Debug Properties ===
encoding: base: 0 shift: 3
nodeSourcePosition: at java.util.TreeMap.successor(TreeMap.java:2161) [bci: 57]
op: Uncompress
stamp: a# Ljava/util/TreeMap$Entry;
=== Inputs ===
value: a113 
=== Succesors ===
=== Usages ===
a32 
=== Predecessor ===
- >@ <|@
instruction <@HotSpotCompression|@org.graalvm.compiler.hotspot.nodes.HotSpotCompressionNode>@ value: a113  <|@  <|@
f <@*|@fixed>@ <|@
tid v54 <|@
d <@d|@=== Debug Properties ===
canSafepoint: true
endIndex: 0
nodeSourcePosition: at java.util.TreeMap.successor(TreeMap.java:2159) [bci: 42]
stamp: void
=== Inputs ===
loopBegin: v31 
=== Succesors ===
=== Usages ===
=== Predecessor ===
a113 >@ <|@
instruction <@LoopEnd|@org.graalvm.compiler.nodes.LoopEndNode>@ loopBegin: v31  <|@  <|@
    end_IR
  end_block
  begin_block
    name "B6"
    from_bci -1
    to_bci -1
    predecessors "B4" 
    successors 
    xhandlers
    flags 
    probability 4599896691100993414
    begin_IR
      HIR
f <@#|@fixed with next>@ <|@
tid v48 <|@
d <@d|@=== Debug Properties ===
nodeSourcePosition: at java.util.TreeMap.successor(TreeMap.java:2163) [bci: 64]
stamp: void
=== Inputs ===
stateAfter: - 
loopBegin: v31 
=== Succesors ===
next: v58 
=== Usages ===
=== Predecessor ===
v52 >@ <|@
instruction <@LoopExit|@org.graalvm.compiler.nodes.LoopExitNode>@ stateAfter: - loopBegin: v31 #next: v58  <|@  <|@
f <@*|@fixed>@ <|@
tid v58 <|@
d <@d|@=== Debug Properties ===
nodeSourcePosition: at java.util.TreeMap.successor(TreeMap.java:2163) [bci: 64]
stamp: void
=== Inputs ===
result: a32 
memoryMap: - 
=== Succesors ===
=== Usages ===
=== Predecessor ===
v48 >@ <|@
instruction <@Return|@org.graalvm.compiler.nodes.ReturnNode>@ result: a32 memoryMap: -  <|@  <|@
    end_IR
  end_block
  begin_block
    name "B7"
    from_bci -1
    to_bci -1
    predecessors "B0" 
    successors "B8" 
    xhandlers
    flags 
    probability 4600387054551577944
    begin_IR
      HIR
f <@#|@fixed with next>@ <|@
tid v9 <|@
d <@d|@=== Debug Properties ===
nodeSourcePosition: at java.util.TreeMap.successor(TreeMap.java:2152) [bci: 13]
stamp: void
=== Inputs ===
=== Succesors ===
next: v13 
=== Usages ===
=== Predecessor ===
v10 >@ <|@
instruction <@Begin|@org.graalvm.compiler.nodes.BeginNode>@ #next: v13  <|@  <|@
f <@~|@floating>@ <|@
tid a72 <|@
d <@d|@=== Debug Properties ===
encoding: base: 0 shift: 3
nodeSourcePosition: at java.util.TreeMap.successor(TreeMap.java:2151) [bci: 7]
op: Uncompress
stamp: a# Ljava/util/TreeMap$Entry;
=== Inputs ===
value: a110 
=== Succesors ===
=== Usages ===
a15 
=== Predecessor ===
- >@ <|@
instruction <@HotSpotCompression|@org.graalvm.compiler.hotspot.nodes.HotSpotCompressionNode>@ value: a110  <|@  <|@
f <@*|@fixed>@ <|@
tid v13 <|@
d <@d|@=== Debug Properties ===
nodeSourcePosition: at java.util.TreeMap.successor(TreeMap.java:2153) [bci: 18]
stamp: void
=== Inputs ===
=== Succesors ===
=== Usages ===
v14 
=== Predecessor ===
v9 >@ <|@
instruction <@EndNode|@org.graalvm.compiler.nodes.EndNode>@  <|@  <|@
    end_IR
  end_block
  begin_block
    name "B8"
    from_bci -1
    to_bci -1
    predecessors "B7" "B10" 
    successors "B9" "B10" 
    xhandlers
    flags "llh" 
    loop_index 1
    loop_depth 1
    probability 4602686424645874499
    begin_IR
      HIR
f <@~|@floating>@ <|@
tid a15 <|@
d <@d|@=== Debug Properties ===
stamp: a# Ljava/util/TreeMap$Entry;
valueDescription: a -
=== Inputs ===
merge: v14 
values: a72 a91 
=== Succesors ===
=== Usages ===
?16 v120 v27 
=== Predecessor ===
- >@ <|@
instruction <@ValuePhi|@org.graalvm.compiler.nodes.ValuePhiNode>@ merge: v14 values: a72 a91  <|@  <|@
f <@#|@fixed with next>@ <|@
tid v14 <|@
d <@d|@=== Debug Properties ===
canEndsSafepoint: true
inversionCount: 0
loopFrequency: 1.3435333218726722
loopOrigFrequency: 1.0
loopType: SIMPLE_LOOP
nextEndIndex: 1
nodeSourcePosition: at java.util.TreeMap.successor(TreeMap.java:2153) [bci: 18]
splits: 0
stamp: void
unrollFactor: 1
unswitches: 0
=== Inputs ===
stateAfter: - 
overflowGuard: - 
ends: v13 
=== Succesors ===
next: a114 
=== Usages ===
a15 v20 v26 
=== Predecessor ===
- >@ <|@
instruction <@LoopBegin|@org.graalvm.compiler.nodes.LoopBeginNode>@ stateAfter: - overflowGuard: - ends: v13 #next: a114  <|@  <|@
tid ?16 <|@
d <@d|@=== Debug Properties ===
bci: 18
code: ResolvedJavaMethodBytecode<TreeMap.successor(TreeMap$Entry)>
duringCall: false
localsSize: 3
locksSize: 0
rethrowException: false
sourceFile: TreeMap.java
sourceLine: 2153
stackSize: 0
=== Inputs ===
outerFrameState: - 
values: - a15 - 
=== Succesors ===
=== Usages ===
v99 a114 
=== Predecessor ===
- >@ <|@
instruction <@FrameState|@org.graalvm.compiler.nodes.FrameState>@ outerFrameState: - values: - a15 -  <|@  <|@
f <@~|@floating>@ <|@
tid v120 <|@
d <@d|@=== Debug Properties ===
displacement: 24
scale: Times1
stamp: void*
=== Inputs ===
base: a15 
index: - 
=== Succesors ===
=== Usages ===
a114 
=== Predecessor ===
- >@ <|@
instruction <@AMD64Address|@org.graalvm.compiler.core.amd64.AMD64AddressNode>@ base: a15 index: -  <|@  <|@
f <@#|@fixed with next>@ <|@
tid a114 <|@
d <@d|@=== Debug Properties ===
barrierType: NONE
forceFixed: false
location: TreeMap$Entry.left
nodeSourcePosition: at java.util.TreeMap.successor(TreeMap.java:2153) [bci: 19]
nullCheck: true
stamp: n# Ljava/util/TreeMap$Entry;
=== Inputs ===
stateBefore: ?16 
guard: - 
address: v120 
=== Succesors ===
next: v24 
=== Usages ===
a91 v93 
=== Predecessor ===
v14 >@ <|@
instruction <@Read|@org.graalvm.compiler.nodes.memory.ReadNode>@ stateBefore: ?16 guard: - address: v120 #next: v24  <|@  <|@
f <@~|@floating>@ <|@
tid v93 <|@
d <@d|@=== Debug Properties ===
nodeSourcePosition: at java.util.TreeMap.successor(TreeMap.java:2153) [bci: 22]
stamp: void
=== Inputs ===
value: a114 
=== Succesors ===
=== Usages ===
v24 
=== Predecessor ===
- >@ <|@
instruction <@IsNull|@org.graalvm.compiler.nodes.calc.IsNullNode>@ value: a114  <|@  <|@
f <@*|@fixed>@ <|@
tid v24 <|@
d <@d|@=== Debug Properties ===
nodeSourcePosition: at java.util.TreeMap.successor(TreeMap.java:2153) [bci: 22]
stamp: void
trueSuccessorProbability: 0.7443060650004265
=== Inputs ===
condition: v93 
=== Succesors ===
trueSuccessor: v20 
falseSuccessor: v23 
=== Usages ===
=== Predecessor ===
a114 >@ <|@
instruction <@If|@org.graalvm.compiler.nodes.IfNode>@ condition: v93 #trueSuccessor: v20 #falseSuccessor: v23  <|@  <|@
    end_IR
  end_block
  begin_block
    name "B9"
    from_bci -1
    to_bci -1
    predecessors "B8" 
    successors 
    xhandlers
    flags 
    probability 4600387054551577945
    begin_IR
      HIR
f <@#|@fixed with next>@ <|@
tid v20 <|@
d <@d|@=== Debug Properties ===
nodeSourcePosition: at java.util.TreeMap.successor(TreeMap.java:2155) [bci: 33]
stamp: void
=== Inputs ===
stateAfter: - 
loopBegin: v14 
=== Succesors ===
next: v27 
=== Usages ===
=== Predecessor ===
v24 >@ <|@
instruction <@LoopExit|@org.graalvm.compiler.nodes.LoopExitNode>@ stateAfter: - loopBegin: v14 #next: v27  <|@  <|@
f <@*|@fixed>@ <|@
tid v27 <|@
d <@d|@=== Debug Properties ===
nodeSourcePosition: at java.util.TreeMap.successor(TreeMap.java:2155) [bci: 34]
stamp: void
=== Inputs ===
result: a15 
memoryMap: - 
=== Succesors ===
=== Usages ===
=== Predecessor ===
v20 >@ <|@
instruction <@Return|@org.graalvm.compiler.nodes.ReturnNode>@ result: a15 memoryMap: -  <|@  <|@
    end_IR
  end_block
  begin_block
    name "B10"
    from_bci -1
    to_bci -1
    predecessors "B8" 
    successors "B8" 
    xhandlers
    flags "lle" 
    loop_index 1
    loop_depth 1
    probability 4593781971425583707
    begin_IR
      HIR
f <@#|@fixed with next>@ <|@
tid v23 <|@
d <@d|@=== Debug Properties ===
nodeSourcePosition: at java.util.TreeMap.successor(TreeMap.java:2154) [bci: 25]
stamp: void
=== Inputs ===
=== Succesors ===
next: v99 
=== Usages ===
=== Predecessor ===
v24 >@ <|@
instruction <@Begin|@org.graalvm.compiler.nodes.BeginNode>@ #next: v99  <|@  <|@
f <@#|@fixed with next>@ <|@
tid v99 <|@
d <@d|@=== Debug Properties ===
stamp: void
=== Inputs ===
stateBefore: ?16 
=== Succesors ===
next: v26 
=== Usages ===
=== Predecessor ===
v23 >@ <|@
instruction <@Safepoint|@org.graalvm.compiler.nodes.SafepointNode>@ stateBefore: ?16 #next: v26  <|@  <|@
f <@~|@floating>@ <|@
tid a91 <|@
d <@d|@=== Debug Properties ===
encoding: base: 0 shift: 3
nodeSourcePosition: at java.util.TreeMap.successor(TreeMap.java:2153) [bci: 19]
op: Uncompress
stamp: a# Ljava/util/TreeMap$Entry;
=== Inputs ===
value: a114 
=== Succesors ===
=== Usages ===
a15 
=== Predecessor ===
- >@ <|@
instruction <@HotSpotCompression|@org.graalvm.compiler.hotspot.nodes.HotSpotCompressionNode>@ value: a114  <|@  <|@
f <@*|@fixed>@ <|@
tid v26 <|@
d <@d|@=== Debug Properties ===
canSafepoint: true
endIndex: 0
nodeSourcePosition: at java.util.TreeMap.successor(TreeMap.java:2153) [bci: 18]
stamp: void
=== Inputs ===
loopBegin: v14 
=== Succesors ===
=== Usages ===
=== Predecessor ===
v99 >@ <|@
instruction <@LoopEnd|@org.graalvm.compiler.nodes.LoopEndNode>@ loopBegin: v14  <|@  <|@
    end_IR
  end_block
end_cfg
begin_cfg
  name "After LIR generation"
  begin_block
    name "B0"
    from_bci -1
    to_bci -1
    predecessors 
    successors "B1" "B7" 
    xhandlers
    flags 
    probability 4607182418800017408
    begin_IR
      HIR
f <@#|@fixed with next>@ <|@
tid v0 <|@
d <@d|@=== Debug Properties ===
stamp: void
=== Inputs ===
stateAfter: - 
=== Succesors ===
next: a110 
=== Usages ===
=== Predecessor ===
- >@ <|@
instruction <@StartNode|@org.graalvm.compiler.nodes.StartNode>@ stateAfter: - #next: a110  <|@  <|@
f <@~|@floating>@ <|@
tid a115 <|@
result Object[null] <|@
d <@d|@=== Debug Properties ===
isDefaultStable: false
rawvalue: null
stableDimension: 0
stamp: a - NULL
stampKind: a -
value: Object[null]
=== Inputs ===
=== Succesors ===
=== Usages ===
?2 v57 
=== Predecessor ===
- >@ <|@
instruction <@Constant|@org.graalvm.compiler.nodes.ConstantNode>@  <|@  <|@
tid ?2 <|@
d <@d|@=== Debug Properties ===
bci: 0
code: ResolvedJavaMethodBytecode<TreeMap.successor(TreeMap$Entry)>
duringCall: false
localsSize: 3
locksSize: 0
rethrowException: false
sourceFile: TreeMap.java
sourceLine: 2149
stackSize: 0
=== Inputs ===
outerFrameState: - 
values: a115 - - 
=== Succesors ===
=== Usages ===
a110 
=== Predecessor ===
- >@ <|@
instruction <@FrameState|@org.graalvm.compiler.nodes.FrameState>@ outerFrameState: - values: a115 - -  <|@  <|@
f <@~|@floating>@ <|@
tid a1 <|@
result v0|QWORD[.] <|@
d <@d|@=== Debug Properties ===
index: 0
stamp: a# Ljava/util/TreeMap$Entry;
uncheckedStamp: [null]
=== Inputs ===
=== Succesors ===
=== Usages ===
v116 a33 v117 
=== Predecessor ===
- >@ <|@
instruction <@Parameter|@org.graalvm.compiler.nodes.ParameterNode>@  <|@  <|@
f <@~|@floating>@ <|@
tid v116 <|@
result [v0|QWORD[.] + 28] <|@
d <@d|@=== Debug Properties ===
displacement: 28
scale: Times1
stamp: void*
=== Inputs ===
base: a1 
index: - 
=== Succesors ===
=== Usages ===
a110 
=== Predecessor ===
- >@ <|@
instruction <@AMD64Address|@org.graalvm.compiler.core.amd64.AMD64AddressNode>@ base: a1 index: -  <|@  <|@
f <@#|@fixed with next>@ <|@
tid a110 <|@
result v1|DWORD[.] <|@
d <@d|@=== Debug Properties ===
barrierType: NONE
forceFixed: false
location: TreeMap$Entry.right
nodeSourcePosition: at java.util.TreeMap.successor(TreeMap.java:2151) [bci: 7]
nullCheck: true
stamp: n# Ljava/util/TreeMap$Entry;
=== Inputs ===
stateBefore: ?2 
guard: - 
address: v116 
=== Succesors ===
next: v10 
=== Usages ===
a72 v92 
=== Predecessor ===
v0 >@ <|@
instruction <@Read|@org.graalvm.compiler.nodes.memory.ReadNode>@ stateBefore: ?2 guard: - address: v116 #next: v10  <|@  <|@
f <@~|@floating>@ <|@
tid v92 <|@
d <@d|@=== Debug Properties ===
nodeSourcePosition: at java.util.TreeMap.successor(TreeMap.java:2151) [bci: 10]
stamp: void
=== Inputs ===
value: a110 
=== Succesors ===
=== Usages ===
v10 
=== Predecessor ===
- >@ <|@
instruction <@IsNull|@org.graalvm.compiler.nodes.calc.IsNullNode>@ value: a110  <|@  <|@
f <@*|@fixed>@ <|@
tid v10 <|@
d <@d|@=== Debug Properties ===
nodeSourcePosition: at java.util.TreeMap.successor(TreeMap.java:2151) [bci: 10]
stamp: void
trueSuccessorProbability: 0.6272184924666058
=== Inputs ===
condition: v92 
=== Succesors ===
trueSuccessor: v8 
falseSuccessor: v9 
=== Usages ===
=== Predecessor ===
a110 >@ <|@
instruction <@If|@org.graalvm.compiler.nodes.IfNode>@ condition: v92 #trueSuccessor: v8 #falseSuccessor: v9  <|@  <|@
    end_IR
    begin_IR
      LIR
      nr   -1  <|@ instruction [rsi|QWORD[.], rbp|QWORD] = LABEL numbPhis: 0 align: false label: ? <|@ <|@
      nr   -1  <|@ instruction stack:16|QWORD = MOVE rbp|QWORD moveKind: QWORD <|@ <|@
      nr   -1  <|@ instruction [] = HOTSPOTLOCKSTACK frameMapBuilder: org.graalvm.compiler.lir.amd64.AMD64FrameMapBuilder@6e875bb2 slotKind: QWORD <|@ <|@
      nr   -1  <|@ instruction v0|QWORD[.] = MOVE rsi|QWORD[.] moveKind: QWORD <|@ <|@
      nr   -1  <|@ st <@st|@java.util.TreeMap.successor(TreeMap.java:2149) [bci: 0]
locals: Object[null] - - 
>@ <|@ instruction v1|DWORD[.] = MOV [v0|QWORD[.] + 28] size: DWORD state [bci:0] <|@ <|@
      nr   -1  <|@ instruction TEST (x: v1|DWORD[.], y: v1|DWORD[.]) size: DWORD <|@ <|@
      nr   -1  <|@ instruction BRANCH trueDestinationProbability: 0.6272184924666058 condition: = trueDestination: B0 -> B1 falseDestination: B0 -> B7 <|@ <|@
    end_IR
  end_block
  begin_block
    name "B1"
    from_bci -1
    to_bci -1
    predecessors "B0" 
    successors "B2" 
    xhandlers
    flags 
    probability 4603824701483181396
    begin_IR
      HIR
f <@#|@fixed with next>@ <|@
tid v8 <|@
d <@d|@=== Debug Properties ===
nodeSourcePosition: at java.util.TreeMap.successor(TreeMap.java:2157) [bci: 35]
stamp: void
=== Inputs ===
=== Succesors ===
next: a111 
=== Usages ===
=== Predecessor ===
v10 >@ <|@
instruction <@Begin|@org.graalvm.compiler.nodes.BeginNode>@ #next: a111  <|@  <|@
f <@~|@floating>@ <|@
tid v117 <|@
result [v0|QWORD[.] + 32] <|@
d <@d|@=== Debug Properties ===
displacement: 32
scale: Times1
stamp: void*
=== Inputs ===
base: a1 
index: - 
=== Succesors ===
=== Usages ===
a111 
=== Predecessor ===
- >@ <|@
instruction <@AMD64Address|@org.graalvm.compiler.core.amd64.AMD64AddressNode>@ base: a1 index: -  <|@  <|@
f <@#|@fixed with next>@ <|@
tid a111 <|@
result v2|DWORD[.] <|@
d <@d|@=== Debug Properties ===
barrierType: NONE
forceFixed: false
location: TreeMap$Entry.parent
nodeSourcePosition: at java.util.TreeMap.successor(TreeMap.java:2157) [bci: 36]
nullCheck: false
stamp: n# Ljava/util/TreeMap$Entry;
=== Inputs ===
stateBefore: - 
guard: - 
address: v117 
=== Succesors ===
next: v30 
=== Usages ===
a76 
=== Predecessor ===
v8 >@ <|@
instruction <@Read|@org.graalvm.compiler.nodes.memory.ReadNode>@ stateBefore: - guard: - address: v117 #next: v30  <|@  <|@
f <@~|@floating>@ <|@
tid a76 <|@
result v3|QWORD[.] <|@
d <@d|@=== Debug Properties ===
encoding: base: 0 shift: 3
nodeSourcePosition: at java.util.TreeMap.successor(TreeMap.java:2157) [bci: 36]
op: Uncompress
stamp: a# Ljava/util/TreeMap$Entry;
=== Inputs ===
value: a111 
=== Succesors ===
=== Usages ===
a32 
=== Predecessor ===
- >@ <|@
instruction <@HotSpotCompression|@org.graalvm.compiler.hotspot.nodes.HotSpotCompressionNode>@ value: a111  <|@  <|@
f <@*|@fixed>@ <|@
tid v30 <|@
d <@d|@=== Debug Properties ===
nodeSourcePosition: at java.util.TreeMap.successor(TreeMap.java:2159) [bci: 42]
stamp: void
=== Inputs ===
=== Succesors ===
=== Usages ===
v31 
=== Predecessor ===
a111 >@ <|@
instruction <@EndNode|@org.graalvm.compiler.nodes.EndNode>@  <|@  <|@
    end_IR
    begin_IR
      LIR
      nr   -1  <|@ instruction [] = LABEL numbPhis: 0 align: false label: ? <|@ <|@
      nr   -1  <|@ instruction v2|DWORD[.] = MOV [v0|QWORD[.] + 32] size: DWORD <|@ <|@
      nr   -1  <|@ instruction v3|QWORD[.] = UNCOMPRESSPOINTER (input: v2|DWORD[.], ~baseRegister: r12|ILLEGAL) nonNull: false lirKindTool: com.oracle.graal.enterprise.z.a@530d7154 encoding: base: 0 shift: 3 <|@ <|@
      nr   -1  <|@ instruction JUMP ~[v3|QWORD[.], v0|QWORD[.]] destination: B1 -> B2 <|@ <|@
    end_IR
  end_block
  begin_block
    name "B2"
    from_bci -1
    to_bci -1
    predecessors "B1" "B5" 
    successors "B3" "B4" 
    xhandlers
    flags "llh" 
    loop_index 0
    loop_depth 1
    probability 4607181169815389981
    begin_IR
      HIR
f <@~|@floating>@ <|@
tid a32 <|@
result v4|QWORD[.] <|@
d <@d|@=== Debug Properties ===
stamp: a# Ljava/util/TreeMap$Entry;
valueDescription: a -
=== Inputs ===
merge: v31 
values: a76 a84 
=== Succesors ===
=== Usages ===
?34 v35 v118 v119 v58 a33 
=== Predecessor ===
- >@ <|@
instruction <@ValuePhi|@org.graalvm.compiler.nodes.ValuePhiNode>@ merge: v31 values: a76 a84  <|@  <|@
f <@~|@floating>@ <|@
tid a33 <|@
result v5|QWORD[.] <|@
d <@d|@=== Debug Properties ===
stamp: a# Ljava/util/TreeMap$Entry;
valueDescription: a -
=== Inputs ===
merge: v31 
values: a1 a32 
=== Succesors ===
=== Usages ===
?34 v43 
=== Predecessor ===
- >@ <|@
instruction <@ValuePhi|@org.graalvm.compiler.nodes.ValuePhiNode>@ merge: v31 values: a1 a32  <|@  <|@
f <@#|@fixed with next>@ <|@
tid v31 <|@
d <@d|@=== Debug Properties ===
canEndsSafepoint: true
inversionCount: 0
loopFrequency: 1.594119667803253
loopOrigFrequency: 1.0
loopType: SIMPLE_LOOP
nextEndIndex: 1
nodeSourcePosition: at java.util.TreeMap.successor(TreeMap.java:2159) [bci: 42]
splits: 0
stamp: void
unrollFactor: 1
unswitches: 0
=== Inputs ===
stateAfter: - 
overflowGuard: - 
ends: v30 
=== Succesors ===
next: v41 
=== Usages ===
a32 a33 v37 v48 v54 
=== Predecessor ===
- >@ <|@
instruction <@LoopBegin|@org.graalvm.compiler.nodes.LoopBeginNode>@ stateAfter: - overflowGuard: - ends: v30 #next: v41  <|@  <|@
f <@~|@floating>@ <|@
tid v35 <|@
d <@d|@=== Debug Properties ===
nodeSourcePosition: at java.util.TreeMap.successor(TreeMap.java:2159) [bci: 43]
stamp: void
=== Inputs ===
value: a32 
=== Succesors ===
=== Usages ===
v41 
=== Predecessor ===
- >@ <|@
instruction <@IsNull|@org.graalvm.compiler.nodes.calc.IsNullNode>@ value: a32  <|@  <|@
f <@*|@fixed>@ <|@
tid v41 <|@
d <@d|@=== Debug Properties ===
nodeSourcePosition: at java.util.TreeMap.successor(TreeMap.java:2159) [bci: 43]
stamp: void
trueSuccessorProbability: 0.28169668610986476
=== Inputs ===
condition: v35 
=== Succesors ===
trueSuccessor: v37 
falseSuccessor: v40 
=== Usages ===
=== Predecessor ===
v31 >@ <|@
instruction <@If|@org.graalvm.compiler.nodes.IfNode>@ condition: v35 #trueSuccessor: v37 #falseSuccessor: v40  <|@  <|@
    end_IR
    begin_IR
      LIR
      nr   -1  <|@ instruction [v4|QWORD[.], v5|QWORD[.]] = LABEL numbPhis: 2 align: false label: ? <|@ <|@
      nr   -1  <|@ instruction TEST (x: v4|QWORD[.], y: v4|QWORD[.]) size: QWORD <|@ <|@
      nr   -1  <|@ instruction BRANCH trueDestinationProbability: 0.28169668610986476 condition: = trueDestination: B2 -> B3 falseDestination: B2 -> B4 <|@ <|@
    end_IR
  end_block
  begin_block
    name "B3"
    from_bci -1
    to_bci -1
    predecessors "B2" 
    successors 
    xhandlers
    flags 
    probability 4598745512610628385
    begin_IR
      HIR
f <@#|@fixed with next>@ <|@
tid v37 <|@
d <@d|@=== Debug Properties ===
nodeSourcePosition: at java.util.TreeMap.successor(TreeMap.java:2163) [bci: 64]
stamp: void
=== Inputs ===
stateAfter: - 
loopBegin: v31 
=== Succesors ===
next: v57 
=== Usages ===
=== Predecessor ===
v41 >@ <|@
instruction <@LoopExit|@org.graalvm.compiler.nodes.LoopExitNode>@ stateAfter: - loopBegin: v31 #next: v57  <|@  <|@
f <@*|@fixed>@ <|@
tid v57 <|@
d <@d|@=== Debug Properties ===
nodeSourcePosition: at java.util.TreeMap.successor(TreeMap.java:2163) [bci: 64]
stamp: void
=== Inputs ===
result: a115 
memoryMap: - 
=== Succesors ===
=== Usages ===
=== Predecessor ===
v37 >@ <|@
instruction <@Return|@org.graalvm.compiler.nodes.ReturnNode>@ result: a115 memoryMap: -  <|@  <|@
    end_IR
    begin_IR
      LIR
      nr   -1  <|@ instruction [] = LABEL numbPhis: 0 align: false label: ? <|@ <|@
      nr   -1  <|@ instruction rax|QWORD[.] = MOVE input: Object[null] <|@ <|@
      nr   -1  <|@ instruction RETURN (savedRbp: stack:16|QWORD, value: rax|QWORD[.]) isStub: false thread: r15 scratchForSafepointOnReturn: rcx config: org.graalvm.compiler.hotspot.GraalHotSpotVMConfig@7222fe45 <|@ <|@
    end_IR
  end_block
  begin_block
    name "B4"
    from_bci -1
    to_bci -1
    predecessors "B2" 
    successors "B5" "B6" 
    xhandlers
    flags 
    loop_index 0
    loop_depth 1
    probability 4604644223469028748
    begin_IR
      HIR
f <@#|@fixed with next>@ <|@
tid v40 <|@
d <@d|@=== Debug Properties ===
nodeSourcePosition: at java.util.TreeMap.successor(TreeMap.java:2159) [bci: 46]
stamp: void
=== Inputs ===
=== Succesors ===
next: a112 
=== Usages ===
=== Predecessor ===
v41 >@ <|@
instruction <@Begin|@org.graalvm.compiler.nodes.BeginNode>@ #next: a112  <|@  <|@
f <@~|@floating>@ <|@
tid v118 <|@
result [v4|QWORD[.] + 28] <|@
d <@d|@=== Debug Properties ===
displacement: 28
scale: Times1
stamp: void*
=== Inputs ===
base: a32 
index: - 
=== Succesors ===
=== Usages ===
a112 
=== Predecessor ===
- >@ <|@
instruction <@AMD64Address|@org.graalvm.compiler.core.amd64.AMD64AddressNode>@ base: a32 index: -  <|@  <|@
f <@#|@fixed with next>@ <|@
tid a112 <|@
result v6|DWORD[.] <|@
d <@d|@=== Debug Properties ===
barrierType: NONE
forceFixed: false
location: TreeMap$Entry.right
nodeSourcePosition: at java.util.TreeMap.successor(TreeMap.java:2159) [bci: 48]
nullCheck: false
stamp: n# Ljava/util/TreeMap$Entry;
=== Inputs ===
stateBefore: - 
guard: - 
address: v118 
=== Succesors ===
next: v52 
=== Usages ===
a81 
=== Predecessor ===
v40 >@ <|@
instruction <@Read|@org.graalvm.compiler.nodes.memory.ReadNode>@ stateBefore: - guard: - address: v118 #next: v52  <|@  <|@
f <@~|@floating>@ <|@
tid a81 <|@
result v7|QWORD[.] <|@
d <@d|@=== Debug Properties ===
encoding: base: 0 shift: 3
nodeSourcePosition: at java.util.TreeMap.successor(TreeMap.java:2159) [bci: 48]
op: Uncompress
stamp: a# Ljava/util/TreeMap$Entry;
=== Inputs ===
value: a112 
=== Succesors ===
=== Usages ===
v43 
=== Predecessor ===
- >@ <|@
instruction <@HotSpotCompression|@org.graalvm.compiler.hotspot.nodes.HotSpotCompressionNode>@ value: a112  <|@  <|@
f <@~|@floating>@ <|@
tid v43 <|@
d <@d|@=== Debug Properties ===
condition: EQ
nodeSourcePosition: at java.util.TreeMap.successor(TreeMap.java:2159) [bci: 51]
stamp: void
unorderedIsTrue: false
=== Inputs ===
x: a33 
y: a81 
=== Succesors ===
=== Usages ===
v52 
=== Predecessor ===
- >@ <|@
instruction <@==|@org.graalvm.compiler.nodes.calc.ObjectEqualsNode>@ x: a33 y: a81  <|@  <|@
f <@*|@fixed>@ <|@
tid v52 <|@
d <@d|@=== Debug Properties ===
nodeSourcePosition: at java.util.TreeMap.successor(TreeMap.java:2159) [bci: 51]
stamp: void
trueSuccessorProbability: 0.5188539645005614
=== Inputs ===
condition: v43 
=== Succesors ===
trueSuccessor: v44 
falseSuccessor: v48 
=== Usages ===
=== Predecessor ===
a112 >@ <|@
instruction <@If|@org.graalvm.compiler.nodes.IfNode>@ condition: v43 #trueSuccessor: v44 #falseSuccessor: v48  <|@  <|@
    end_IR
    begin_IR
      LIR
      nr   -1  <|@ instruction [] = LABEL numbPhis: 0 align: true label: ? <|@ <|@
      nr   -1  <|@ instruction v6|DWORD[.] = MOV [v4|QWORD[.] + 28] size: DWORD <|@ <|@
      nr   -1  <|@ instruction v7|QWORD[.] = UNCOMPRESSPOINTER (input: v6|DWORD[.], ~baseRegister: r12|ILLEGAL) nonNull: false lirKindTool: com.oracle.graal.enterprise.z.a@530d7154 encoding: base: 0 shift: 3 <|@ <|@
      nr   -1  <|@ instruction CMP (x: v7|QWORD[.], y: v5|QWORD[.]) size: QWORD <|@ <|@
      nr   -1  <|@ instruction BRANCH trueDestinationProbability: 0.5188539645005614 condition: = trueDestination: B4 -> B5 falseDestination: B4 -> B6 <|@ <|@
    end_IR
  end_block
  begin_block
    name "B5"
    from_bci -1
    to_bci -1
    predecessors "B4" 
    successors "B2" 
    xhandlers
    flags "lle" 
    loop_index 0
    loop_depth 1
    probability 4600384556582323090
    begin_IR
      HIR
f <@#|@fixed with next>@ <|@
tid v44 <|@
d <@d|@=== Debug Properties ===
nodeSourcePosition: at java.util.TreeMap.successor(TreeMap.java:2160) [bci: 54]
stamp: void
=== Inputs ===
=== Succesors ===
next: v100 
=== Usages ===
=== Predecessor ===
v52 >@ <|@
instruction <@Begin|@org.graalvm.compiler.nodes.BeginNode>@ #next: v100  <|@  <|@
tid ?34 <|@
d <@d|@=== Debug Properties ===
bci: 42
code: ResolvedJavaMethodBytecode<TreeMap.successor(TreeMap$Entry)>
duringCall: false
localsSize: 3
locksSize: 0
rethrowException: false
sourceFile: TreeMap.java
sourceLine: 2159
stackSize: 0
=== Inputs ===
outerFrameState: - 
values: - a32 a33 
=== Succesors ===
=== Usages ===
v100 
=== Predecessor ===
- >@ <|@
instruction <@FrameState|@org.graalvm.compiler.nodes.FrameState>@ outerFrameState: - values: - a32 a33  <|@  <|@
f <@#|@fixed with next>@ <|@
tid v100 <|@
d <@d|@=== Debug Properties ===
stamp: void
=== Inputs ===
stateBefore: ?34 
=== Succesors ===
next: a113 
=== Usages ===
=== Predecessor ===
v44 >@ <|@
instruction <@Safepoint|@org.graalvm.compiler.nodes.SafepointNode>@ stateBefore: ?34 #next: a113  <|@  <|@
f <@~|@floating>@ <|@
tid v119 <|@
result [v4|QWORD[.] + 32] <|@
d <@d|@=== Debug Properties ===
displacement: 32
scale: Times1
stamp: void*
=== Inputs ===
base: a32 
index: - 
=== Succesors ===
=== Usages ===
a113 
=== Predecessor ===
- >@ <|@
instruction <@AMD64Address|@org.graalvm.compiler.core.amd64.AMD64AddressNode>@ base: a32 index: -  <|@  <|@
f <@#|@fixed with next>@ <|@
tid a113 <|@
result v8|DWORD[.] <|@
d <@d|@=== Debug Properties ===
barrierType: NONE
forceFixed: false
location: TreeMap$Entry.parent
nodeSourcePosition: at java.util.TreeMap.successor(TreeMap.java:2161) [bci: 57]
nullCheck: false
stamp: n# Ljava/util/TreeMap$Entry;
=== Inputs ===
stateBefore: - 
guard: - 
address: v119 
=== Succesors ===
next: v54 
=== Usages ===
a84 
=== Predecessor ===
v100 >@ <|@
instruction <@Read|@org.graalvm.compiler.nodes.memory.ReadNode>@ stateBefore: - guard: - address: v119 #next: v54  <|@  <|@
f <@~|@floating>@ <|@
tid a84 <|@
result v9|QWORD[.] <|@
d <@d|@=== Debug Properties ===
encoding: base: 0 shift: 3
nodeSourcePosition: at java.util.TreeMap.successor(TreeMap.java:2161) [bci: 57]
op: Uncompress
stamp: a# Ljava/util/TreeMap$Entry;
=== Inputs ===
value: a113 
=== Succesors ===
=== Usages ===
a32 
=== Predecessor ===
- >@ <|@
instruction <@HotSpotCompression|@org.graalvm.compiler.hotspot.nodes.HotSpotCompressionNode>@ value: a113  <|@  <|@
f <@*|@fixed>@ <|@
tid v54 <|@
d <@d|@=== Debug Properties ===
canSafepoint: true
endIndex: 0
nodeSourcePosition: at java.util.TreeMap.successor(TreeMap.java:2159) [bci: 42]
stamp: void
=== Inputs ===
loopBegin: v31 
=== Succesors ===
=== Usages ===
=== Predecessor ===
a113 >@ <|@
instruction <@LoopEnd|@org.graalvm.compiler.nodes.LoopEndNode>@ loopBegin: v31  <|@  <|@
    end_IR
    begin_IR
      LIR
      nr   -1  <|@ instruction [] = LABEL numbPhis: 0 align: false label: ? <|@ <|@
      nr   -1  <|@ st <@st|@java.util.TreeMap.successor(TreeMap.java:2159) [bci: 42]
locals: - v4|QWORD[.] v5|QWORD[.] 
>@ <|@ instruction SAFEPOINT - config: org.graalvm.compiler.hotspot.GraalHotSpotVMConfig@7222fe45 thread: r15 state [bci:42] <|@ <|@
      nr   -1  <|@ instruction v8|DWORD[.] = MOV [v4|QWORD[.] + 32] size: DWORD <|@ <|@
      nr   -1  <|@ instruction v9|QWORD[.] = UNCOMPRESSPOINTER (input: v8|DWORD[.], ~baseRegister: r12|ILLEGAL) nonNull: false lirKindTool: com.oracle.graal.enterprise.z.a@530d7154 encoding: base: 0 shift: 3 <|@ <|@
      nr   -1  <|@ instruction JUMP ~[v9|QWORD[.], v4|QWORD[.]] destination: B5 -> B2 <|@ <|@
    end_IR
  end_block
  begin_block
    name "B6"
    from_bci -1
    to_bci -1
    predecessors "B4" 
    successors 
    xhandlers
    flags 
    probability 4599896691100993414
    begin_IR
      HIR
f <@#|@fixed with next>@ <|@
tid v48 <|@
d <@d|@=== Debug Properties ===
nodeSourcePosition: at java.util.TreeMap.successor(TreeMap.java:2163) [bci: 64]
stamp: void
=== Inputs ===
stateAfter: - 
loopBegin: v31 
=== Succesors ===
next: v58 
=== Usages ===
=== Predecessor ===
v52 >@ <|@
instruction <@LoopExit|@org.graalvm.compiler.nodes.LoopExitNode>@ stateAfter: - loopBegin: v31 #next: v58  <|@  <|@
f <@*|@fixed>@ <|@
tid v58 <|@
d <@d|@=== Debug Properties ===
nodeSourcePosition: at java.util.TreeMap.successor(TreeMap.java:2163) [bci: 64]
stamp: void
=== Inputs ===
result: a32 
memoryMap: - 
=== Succesors ===
=== Usages ===
=== Predecessor ===
v48 >@ <|@
instruction <@Return|@org.graalvm.compiler.nodes.ReturnNode>@ result: a32 memoryMap: -  <|@  <|@
    end_IR
    begin_IR
      LIR
      nr   -1  <|@ instruction [] = LABEL numbPhis: 0 align: false label: ? <|@ <|@
      nr   -1  <|@ instruction rax|QWORD[.] = MOVE v4|QWORD[.] moveKind: QWORD <|@ <|@
      nr   -1  <|@ instruction RETURN (savedRbp: stack:16|QWORD, value: rax|QWORD[.]) isStub: false thread: r15 scratchForSafepointOnReturn: rcx config: org.graalvm.compiler.hotspot.GraalHotSpotVMConfig@7222fe45 <|@ <|@
    end_IR
  end_block
  begin_block
    name "B7"
    from_bci -1
    to_bci -1
    predecessors "B0" 
    successors "B8" 
    xhandlers
    flags 
    probability 4600387054551577944
    begin_IR
      HIR
f <@#|@fixed with next>@ <|@
tid v9 <|@
d <@d|@=== Debug Properties ===
nodeSourcePosition: at java.util.TreeMap.successor(TreeMap.java:2152) [bci: 13]
stamp: void
=== Inputs ===
=== Succesors ===
next: v13 
=== Usages ===
=== Predecessor ===
v10 >@ <|@
instruction <@Begin|@org.graalvm.compiler.nodes.BeginNode>@ #next: v13  <|@  <|@
f <@~|@floating>@ <|@
tid a72 <|@
result v10|QWORD[.] <|@
d <@d|@=== Debug Properties ===
encoding: base: 0 shift: 3
nodeSourcePosition: at java.util.TreeMap.successor(TreeMap.java:2151) [bci: 7]
op: Uncompress
stamp: a# Ljava/util/TreeMap$Entry;
=== Inputs ===
value: a110 
=== Succesors ===
=== Usages ===
a15 
=== Predecessor ===
- >@ <|@
instruction <@HotSpotCompression|@org.graalvm.compiler.hotspot.nodes.HotSpotCompressionNode>@ value: a110  <|@  <|@
f <@*|@fixed>@ <|@
tid v13 <|@
d <@d|@=== Debug Properties ===
nodeSourcePosition: at java.util.TreeMap.successor(TreeMap.java:2153) [bci: 18]
stamp: void
=== Inputs ===
=== Succesors ===
=== Usages ===
v14 
=== Predecessor ===
v9 >@ <|@
instruction <@EndNode|@org.graalvm.compiler.nodes.EndNode>@  <|@  <|@
    end_IR
    begin_IR
      LIR
      nr   -1  <|@ instruction [] = LABEL numbPhis: 0 align: false label: ? <|@ <|@
      nr   -1  <|@ instruction v10|QWORD[.] = UNCOMPRESSPOINTER (input: v1|DWORD[.], ~baseRegister: r12|ILLEGAL) nonNull: false lirKindTool: com.oracle.graal.enterprise.z.a@530d7154 encoding: base: 0 shift: 3 <|@ <|@
      nr   -1  <|@ instruction JUMP ~[v10|QWORD[.]] destination: B7 -> B8 <|@ <|@
    end_IR
  end_block
  begin_block
    name "B8"
    from_bci -1
    to_bci -1
    predecessors "B7" "B10" 
    successors "B9" "B10" 
    xhandlers
    flags "llh" 
    loop_index 1
    loop_depth 1
    probability 4602686424645874499
    begin_IR
      HIR
f <@~|@floating>@ <|@
tid a15 <|@
result v11|QWORD[.] <|@
d <@d|@=== Debug Properties ===
stamp: a# Ljava/util/TreeMap$Entry;
valueDescription: a -
=== Inputs ===
merge: v14 
values: a72 a91 
=== Succesors ===
=== Usages ===
?16 v120 v27 
=== Predecessor ===
- >@ <|@
instruction <@ValuePhi|@org.graalvm.compiler.nodes.ValuePhiNode>@ merge: v14 values: a72 a91  <|@  <|@
f <@#|@fixed with next>@ <|@
tid v14 <|@
d <@d|@=== Debug Properties ===
canEndsSafepoint: true
inversionCount: 0
loopFrequency: 1.3435333218726722
loopOrigFrequency: 1.0
loopType: SIMPLE_LOOP
nextEndIndex: 1
nodeSourcePosition: at java.util.TreeMap.successor(TreeMap.java:2153) [bci: 18]
splits: 0
stamp: void
unrollFactor: 1
unswitches: 0
=== Inputs ===
stateAfter: - 
overflowGuard: - 
ends: v13 
=== Succesors ===
next: a114 
=== Usages ===
a15 v20 v26 
=== Predecessor ===
- >@ <|@
instruction <@LoopBegin|@org.graalvm.compiler.nodes.LoopBeginNode>@ stateAfter: - overflowGuard: - ends: v13 #next: a114  <|@  <|@
tid ?16 <|@
d <@d|@=== Debug Properties ===
bci: 18
code: ResolvedJavaMethodBytecode<TreeMap.successor(TreeMap$Entry)>
duringCall: false
localsSize: 3
locksSize: 0
rethrowException: false
sourceFile: TreeMap.java
sourceLine: 2153
stackSize: 0
=== Inputs ===
outerFrameState: - 
values: - a15 - 
=== Succesors ===
=== Usages ===
v99 a114 
=== Predecessor ===
- >@ <|@
instruction <@FrameState|@org.graalvm.compiler.nodes.FrameState>@ outerFrameState: - values: - a15 -  <|@  <|@
f <@~|@floating>@ <|@
tid v120 <|@
result [v11|QWORD[.] + 24] <|@
d <@d|@=== Debug Properties ===
displacement: 24
scale: Times1
stamp: void*
=== Inputs ===
base: a15 
index: - 
=== Succesors ===
=== Usages ===
a114 
=== Predecessor ===
- >@ <|@
instruction <@AMD64Address|@org.graalvm.compiler.core.amd64.AMD64AddressNode>@ base: a15 index: -  <|@  <|@
f <@#|@fixed with next>@ <|@
tid a114 <|@
result v12|DWORD[.] <|@
d <@d|@=== Debug Properties ===
barrierType: NONE
forceFixed: false
location: TreeMap$Entry.left
nodeSourcePosition: at java.util.TreeMap.successor(TreeMap.java:2153) [bci: 19]
nullCheck: true
stamp: n# Ljava/util/TreeMap$Entry;
=== Inputs ===
stateBefore: ?16 
guard: - 
address: v120 
=== Succesors ===
next: v24 
=== Usages ===
a91 v93 
=== Predecessor ===
v14 >@ <|@
instruction <@Read|@org.graalvm.compiler.nodes.memory.ReadNode>@ stateBefore: ?16 guard: - address: v120 #next: v24  <|@  <|@
f <@~|@floating>@ <|@
tid v93 <|@
d <@d|@=== Debug Properties ===
nodeSourcePosition: at java.util.TreeMap.successor(TreeMap.java:2153) [bci: 22]
stamp: void
=== Inputs ===
value: a114 
=== Succesors ===
=== Usages ===
v24 
=== Predecessor ===
- >@ <|@
instruction <@IsNull|@org.graalvm.compiler.nodes.calc.IsNullNode>@ value: a114  <|@  <|@
f <@*|@fixed>@ <|@
tid v24 <|@
d <@d|@=== Debug Properties ===
nodeSourcePosition: at java.util.TreeMap.successor(TreeMap.java:2153) [bci: 22]
stamp: void
trueSuccessorProbability: 0.7443060650004265
=== Inputs ===
condition: v93 
=== Succesors ===
trueSuccessor: v20 
falseSuccessor: v23 
=== Usages ===
=== Predecessor ===
a114 >@ <|@
instruction <@If|@org.graalvm.compiler.nodes.IfNode>@ condition: v93 #trueSuccessor: v20 #falseSuccessor: v23  <|@  <|@
    end_IR
    begin_IR
      LIR
      nr   -1  <|@ instruction [v11|QWORD[.]] = LABEL numbPhis: 1 align: false label: ? <|@ <|@
      nr   -1  <|@ st <@st|@java.util.TreeMap.successor(TreeMap.java:2153) [bci: 18]
locals: - v11|QWORD[.] - 
>@ <|@ instruction v12|DWORD[.] = MOV [v11|QWORD[.] + 24] size: DWORD state [bci:18] <|@ <|@
      nr   -1  <|@ instruction TEST (x: v12|DWORD[.], y: v12|DWORD[.]) size: DWORD <|@ <|@
      nr   -1  <|@ instruction BRANCH trueDestinationProbability: 0.7443060650004265 condition: = trueDestination: B8 -> B9 falseDestination: B8 -> B10 <|@ <|@
    end_IR
  end_block
  begin_block
    name "B9"
    from_bci -1
    to_bci -1
    predecessors "B8" 
    successors 
    xhandlers
    flags 
    probability 4600387054551577945
    begin_IR
      HIR
f <@#|@fixed with next>@ <|@
tid v20 <|@
d <@d|@=== Debug Properties ===
nodeSourcePosition: at java.util.TreeMap.successor(TreeMap.java:2155) [bci: 33]
stamp: void
=== Inputs ===
stateAfter: - 
loopBegin: v14 
=== Succesors ===
next: v27 
=== Usages ===
=== Predecessor ===
v24 >@ <|@
instruction <@LoopExit|@org.graalvm.compiler.nodes.LoopExitNode>@ stateAfter: - loopBegin: v14 #next: v27  <|@  <|@
f <@*|@fixed>@ <|@
tid v27 <|@
d <@d|@=== Debug Properties ===
nodeSourcePosition: at java.util.TreeMap.successor(TreeMap.java:2155) [bci: 34]
stamp: void
=== Inputs ===
result: a15 
memoryMap: - 
=== Succesors ===
=== Usages ===
=== Predecessor ===
v20 >@ <|@
instruction <@Return|@org.graalvm.compiler.nodes.ReturnNode>@ result: a15 memoryMap: -  <|@  <|@
    end_IR
    begin_IR
      LIR
      nr   -1  <|@ instruction [] = LABEL numbPhis: 0 align: false label: ? <|@ <|@
      nr   -1  <|@ instruction rax|QWORD[.] = MOVE v11|QWORD[.] moveKind: QWORD <|@ <|@
      nr   -1  <|@ instruction RETURN (savedRbp: stack:16|QWORD, value: rax|QWORD[.]) isStub: false thread: r15 scratchForSafepointOnReturn: rcx config: org.graalvm.compiler.hotspot.GraalHotSpotVMConfig@7222fe45 <|@ <|@
    end_IR
  end_block
  begin_block
    name "B10"
    from_bci -1
    to_bci -1
    predecessors "B8" 
    successors "B8" 
    xhandlers
    flags "lle" 
    loop_index 1
    loop_depth 1
    probability 4593781971425583707
    begin_IR
      HIR
f <@#|@fixed with next>@ <|@
tid v23 <|@
d <@d|@=== Debug Properties ===
nodeSourcePosition: at java.util.TreeMap.successor(TreeMap.java:2154) [bci: 25]
stamp: void
=== Inputs ===
=== Succesors ===
next: v99 
=== Usages ===
=== Predecessor ===
v24 >@ <|@
instruction <@Begin|@org.graalvm.compiler.nodes.BeginNode>@ #next: v99  <|@  <|@
f <@#|@fixed with next>@ <|@
tid v99 <|@
d <@d|@=== Debug Properties ===
stamp: void
=== Inputs ===
stateBefore: ?16 
=== Succesors ===
next: v26 
=== Usages ===
=== Predecessor ===
v23 >@ <|@
instruction <@Safepoint|@org.graalvm.compiler.nodes.SafepointNode>@ stateBefore: ?16 #next: v26  <|@  <|@
f <@~|@floating>@ <|@
tid a91 <|@
result v13|QWORD[.] <|@
d <@d|@=== Debug Properties ===
encoding: base: 0 shift: 3
nodeSourcePosition: at java.util.TreeMap.successor(TreeMap.java:2153) [bci: 19]
op: Uncompress
stamp: a# Ljava/util/TreeMap$Entry;
=== Inputs ===
value: a114 
=== Succesors ===
=== Usages ===
a15 
=== Predecessor ===
- >@ <|@
instruction <@HotSpotCompression|@org.graalvm.compiler.hotspot.nodes.HotSpotCompressionNode>@ value: a114  <|@  <|@
f <@*|@fixed>@ <|@
tid v26 <|@
d <@d|@=== Debug Properties ===
canSafepoint: true
endIndex: 0
nodeSourcePosition: at java.util.TreeMap.successor(TreeMap.java:2153) [bci: 18]
stamp: void
=== Inputs ===
loopBegin: v14 
=== Succesors ===
=== Usages ===
=== Predecessor ===
v99 >@ <|@
instruction <@LoopEnd|@org.graalvm.compiler.nodes.LoopEndNode>@ loopBegin: v14  <|@  <|@
    end_IR
    begin_IR
      LIR
      nr   -1  <|@ instruction [] = LABEL numbPhis: 0 align: true label: ? <|@ <|@
      nr   -1  <|@ st <@st|@java.util.TreeMap.successor(TreeMap.java:2153) [bci: 18]
locals: - v11|QWORD[.] - 
>@ <|@ instruction SAFEPOINT - config: org.graalvm.compiler.hotspot.GraalHotSpotVMConfig@7222fe45 thread: r15 state [bci:18] <|@ <|@
      nr   -1  <|@ instruction v13|QWORD[.] = UNCOMPRESSPOINTER (input: v12|DWORD[.], ~baseRegister: r12|ILLEGAL) nonNull: false lirKindTool: com.oracle.graal.enterprise.z.a@530d7154 encoding: base: 0 shift: 3 <|@ <|@
      nr   -1  <|@ instruction JUMP ~[v13|QWORD[.]] destination: B10 -> B8 <|@ <|@
    end_IR
  end_block
end_cfg
begin_cfg
  name "After PreAllocationOptimizationStage"
  begin_block
    name "B0"
    from_bci -1
    to_bci -1
    predecessors 
    successors "B1" "B7" 
    xhandlers
    flags 
    probability 4607182418800017408
    begin_IR
      LIR
      nr   -1  <|@ instruction [rsi|QWORD[.], rbp|QWORD] = LABEL numbPhis: 0 align: false label: ? <|@ <|@
      nr   -1  <|@ instruction stack:16|QWORD = MOVE rbp|QWORD moveKind: QWORD <|@ <|@
      nr   -1  <|@ instruction [] = HOTSPOTLOCKSTACK frameMapBuilder: org.graalvm.compiler.lir.amd64.AMD64FrameMapBuilder@6e875bb2 slotKind: QWORD <|@ <|@
      nr   -1  <|@ instruction v0|QWORD[.] = MOVE rsi|QWORD[.] moveKind: QWORD <|@ <|@
      nr   -1  <|@ st <@st|@java.util.TreeMap.successor(TreeMap.java:2149) [bci: 0]
locals: Object[null] - - 
>@ <|@ instruction v1|DWORD[.] = MOV [v0|QWORD[.] + 28] size: DWORD state [bci:0] <|@ <|@
      nr   -1  <|@ instruction TEST (x: v1|DWORD[.], y: v1|DWORD[.]) size: DWORD <|@ <|@
      nr   -1  <|@ instruction BRANCH trueDestinationProbability: 0.6272184924666058 condition: = trueDestination: B0 -> B1 falseDestination: B0 -> B7 <|@ <|@
    end_IR
  end_block
  begin_block
    name "B1"
    from_bci -1
    to_bci -1
    predecessors "B0" 
    successors "B2" 
    xhandlers
    flags 
    probability 4603824701483181396
    begin_IR
      LIR
      nr   -1  <|@ instruction [] = LABEL numbPhis: 0 align: false label: ? <|@ <|@
      nr   -1  <|@ instruction v2|DWORD[.] = MOV [v0|QWORD[.] + 32] size: DWORD <|@ <|@
      nr   -1  <|@ instruction v3|QWORD[.] = UNCOMPRESSPOINTER (input: v2|DWORD[.], ~baseRegister: r12|ILLEGAL) nonNull: false lirKindTool: com.oracle.graal.enterprise.z.a@530d7154 encoding: base: 0 shift: 3 <|@ <|@
      nr   -1  <|@ instruction JUMP ~[v3|QWORD[.], v0|QWORD[.]] destination: B1 -> B2 <|@ <|@
    end_IR
  end_block
  begin_block
    name "B4"
    from_bci -1
    to_bci -1
    predecessors "B2" 
    successors "B5" "B6" 
    xhandlers
    flags 
    loop_index 0
    loop_depth 1
    probability 4604644223469028748
    begin_IR
      LIR
      nr   -1  <|@ instruction [] = LABEL numbPhis: 0 align: true label: ? <|@ <|@
      nr   -1  <|@ instruction v6|DWORD[.] = MOV [v4|QWORD[.] + 28] size: DWORD <|@ <|@
      nr   -1  <|@ instruction v7|QWORD[.] = UNCOMPRESSPOINTER (input: v6|DWORD[.], ~baseRegister: r12|ILLEGAL) nonNull: false lirKindTool: com.oracle.graal.enterprise.z.a@530d7154 encoding: base: 0 shift: 3 <|@ <|@
      nr   -1  <|@ instruction CMP (x: v7|QWORD[.], y: v5|QWORD[.]) size: QWORD <|@ <|@
      nr   -1  <|@ instruction BRANCH trueDestinationProbability: 0.5188539645005614 condition: = trueDestination: B4 -> B5 falseDestination: B4 -> B6 <|@ <|@
    end_IR
  end_block
  begin_block
    name "B5"
    from_bci -1
    to_bci -1
    predecessors "B4" 
    successors "B2" 
    xhandlers
    flags "lle" 
    loop_index 0
    loop_depth 1
    probability 4600384556582323090
    begin_IR
      LIR
      nr   -1  <|@ instruction [] = LABEL numbPhis: 0 align: false label: ? <|@ <|@
      nr   -1  <|@ st <@st|@java.util.TreeMap.successor(TreeMap.java:2159) [bci: 42]
locals: - v4|QWORD[.] v5|QWORD[.] 
>@ <|@ instruction SAFEPOINT - config: org.graalvm.compiler.hotspot.GraalHotSpotVMConfig@7222fe45 thread: r15 state [bci:42] <|@ <|@
      nr   -1  <|@ instruction v8|DWORD[.] = MOV [v4|QWORD[.] + 32] size: DWORD <|@ <|@
      nr   -1  <|@ instruction v9|QWORD[.] = UNCOMPRESSPOINTER (input: v8|DWORD[.], ~baseRegister: r12|ILLEGAL) nonNull: false lirKindTool: com.oracle.graal.enterprise.z.a@530d7154 encoding: base: 0 shift: 3 <|@ <|@
      nr   -1  <|@ instruction JUMP ~[v9|QWORD[.], v4|QWORD[.]] destination: B5 -> B2 <|@ <|@
    end_IR
  end_block
  begin_block
    name "B2"
    from_bci -1
    to_bci -1
    predecessors "B1" "B5" 
    successors "B3" "B4" 
    xhandlers
    flags "llh" 
    loop_index 0
    loop_depth 1
    probability 4607181169815389981
    begin_IR
      LIR
      nr   -1  <|@ instruction [v4|QWORD[.], v5|QWORD[.]] = LABEL numbPhis: 2 align: false label: ? <|@ <|@
      nr   -1  <|@ instruction TEST (x: v4|QWORD[.], y: v4|QWORD[.]) size: QWORD <|@ <|@
      nr   -1  <|@ instruction BRANCH trueDestinationProbability: 0.28169668610986476 condition: = trueDestination: B2 -> B3 falseDestination: B2 -> B4 <|@ <|@
    end_IR
  end_block
  begin_block
    name "B7"
    from_bci -1
    to_bci -1
    predecessors "B0" 
    successors "B8" 
    xhandlers
    flags 
    probability 4600387054551577944
    begin_IR
      LIR
      nr   -1  <|@ instruction [] = LABEL numbPhis: 0 align: false label: ? <|@ <|@
      nr   -1  <|@ instruction v10|QWORD[.] = UNCOMPRESSPOINTER (input: v1|DWORD[.], ~baseRegister: r12|ILLEGAL) nonNull: false lirKindTool: com.oracle.graal.enterprise.z.a@530d7154 encoding: base: 0 shift: 3 <|@ <|@
      nr   -1  <|@ instruction JUMP ~[v10|QWORD[.]] destination: B7 -> B8 <|@ <|@
    end_IR
  end_block
  begin_block
    name "B10"
    from_bci -1
    to_bci -1
    predecessors "B8" 
    successors "B8" 
    xhandlers
    flags "lle" 
    loop_index 1
    loop_depth 1
    probability 4593781971425583707
    begin_IR
      LIR
      nr   -1  <|@ instruction [] = LABEL numbPhis: 0 align: true label: ? <|@ <|@
      nr   -1  <|@ st <@st|@java.util.TreeMap.successor(TreeMap.java:2153) [bci: 18]
locals: - v11|QWORD[.] - 
>@ <|@ instruction SAFEPOINT - config: org.graalvm.compiler.hotspot.GraalHotSpotVMConfig@7222fe45 thread: r15 state [bci:18] <|@ <|@
      nr   -1  <|@ instruction v13|QWORD[.] = UNCOMPRESSPOINTER (input: v12|DWORD[.], ~baseRegister: r12|ILLEGAL) nonNull: false lirKindTool: com.oracle.graal.enterprise.z.a@530d7154 encoding: base: 0 shift: 3 <|@ <|@
      nr   -1  <|@ instruction JUMP ~[v13|QWORD[.]] destination: B10 -> B8 <|@ <|@
    end_IR
  end_block
  begin_block
    name "B8"
    from_bci -1
    to_bci -1
    predecessors "B7" "B10" 
    successors "B9" "B10" 
    xhandlers
    flags "llh" 
    loop_index 1
    loop_depth 1
    probability 4602686424645874499
    begin_IR
      LIR
      nr   -1  <|@ instruction [v11|QWORD[.]] = LABEL numbPhis: 1 align: false label: ? <|@ <|@
      nr   -1  <|@ st <@st|@java.util.TreeMap.successor(TreeMap.java:2153) [bci: 18]
locals: - v11|QWORD[.] - 
>@ <|@ instruction v12|DWORD[.] = MOV [v11|QWORD[.] + 24] size: DWORD state [bci:18] <|@ <|@
      nr   -1  <|@ instruction TEST (x: v12|DWORD[.], y: v12|DWORD[.]) size: DWORD <|@ <|@
      nr   -1  <|@ instruction BRANCH trueDestinationProbability: 0.7443060650004265 condition: = trueDestination: B8 -> B9 falseDestination: B8 -> B10 <|@ <|@
    end_IR
  end_block
  begin_block
    name "B9"
    from_bci -1
    to_bci -1
    predecessors "B8" 
    successors 
    xhandlers
    flags 
    probability 4600387054551577945
    begin_IR
      LIR
      nr   -1  <|@ instruction [] = LABEL numbPhis: 0 align: false label: ? <|@ <|@
      nr   -1  <|@ instruction rax|QWORD[.] = MOVE v11|QWORD[.] moveKind: QWORD <|@ <|@
      nr   -1  <|@ instruction RETURN (savedRbp: stack:16|QWORD, value: rax|QWORD[.]) isStub: false thread: r15 scratchForSafepointOnReturn: rcx config: org.graalvm.compiler.hotspot.GraalHotSpotVMConfig@7222fe45 <|@ <|@
    end_IR
  end_block
  begin_block
    name "B6"
    from_bci -1
    to_bci -1
    predecessors "B4" 
    successors 
    xhandlers
    flags 
    probability 4599896691100993414
    begin_IR
      LIR
      nr   -1  <|@ instruction [] = LABEL numbPhis: 0 align: false label: ? <|@ <|@
      nr   -1  <|@ instruction rax|QWORD[.] = MOVE v4|QWORD[.] moveKind: QWORD <|@ <|@
      nr   -1  <|@ instruction RETURN (savedRbp: stack:16|QWORD, value: rax|QWORD[.]) isStub: false thread: r15 scratchForSafepointOnReturn: rcx config: org.graalvm.compiler.hotspot.GraalHotSpotVMConfig@7222fe45 <|@ <|@
    end_IR
  end_block
  begin_block
    name "B3"
    from_bci -1
    to_bci -1
    predecessors "B2" 
    successors 
    xhandlers
    flags 
    probability 4598745512610628385
    begin_IR
      LIR
      nr   -1  <|@ instruction [] = LABEL numbPhis: 0 align: false label: ? <|@ <|@
      nr   -1  <|@ instruction rax|QWORD[.] = MOVE input: Object[null] <|@ <|@
      nr   -1  <|@ instruction RETURN (savedRbp: stack:16|QWORD, value: rax|QWORD[.]) isStub: false thread: r15 scratchForSafepointOnReturn: rcx config: org.graalvm.compiler.hotspot.GraalHotSpotVMConfig@7222fe45 <|@ <|@
    end_IR
  end_block
end_cfg
begin_bytecodes
     0: aload_0       
     1: ifnonnull     6
     4: aconst_null   
     5: areturn       
     6: aload_0       
     7: getfield      #29         // java.util.TreeMap$Entry.right:java.util.TreeMap$Entry
    10: ifnull        35
    13: aload_0       
    14: getfield      #29         // java.util.TreeMap$Entry.right:java.util.TreeMap$Entry
    17: astore_1      
    18: aload_1       
    19: getfield      #28         // java.util.TreeMap$Entry.left:java.util.TreeMap$Entry
    22: ifnull        33
    25: aload_1       
    26: getfield      #28         // java.util.TreeMap$Entry.left:java.util.TreeMap$Entry
    29: astore_1      
    30: goto          18
    33: aload_1       
    34: areturn       
    35: aload_0       
    36: getfield      #32         // java.util.TreeMap$Entry.parent:java.util.TreeMap$Entry
    39: astore_1      
    40: aload_0       
    41: astore_2      
    42: aload_1       
    43: ifnull        64
    46: aload_2       
    47: aload_1       
    48: getfield      #29         // java.util.TreeMap$Entry.right:java.util.TreeMap$Entry
    51: if_acmpne     64
    54: aload_1       
    55: astore_2      
    56: aload_1       
    57: getfield      #32         // java.util.TreeMap$Entry.parent:java.util.TreeMap$Entry
    60: astore_1      
    61: goto          42
    64: aload_1       
    65: areturn       
   <|@
end_bytecodes
begin_cfg
  name "After AllocationStage"
  begin_block
    name "B0"
    from_bci -1
    to_bci -1
    predecessors 
    successors "B1" "B7" 
    xhandlers
    flags 
    probability 4607182418800017408
    begin_IR
      LIR
      nr    0  <|@ instruction [rsi|QWORD[.], rbp|QWORD] = LABEL numbPhis: 0 align: false label: ? <|@ <|@
      nr    2  <|@ instruction stack:16|QWORD = MOVE rbp|QWORD moveKind: QWORD <|@ <|@
      nr    4  <|@ instruction [] = HOTSPOTLOCKSTACK frameMapBuilder: org.graalvm.compiler.lir.amd64.AMD64FrameMapBuilder@6e875bb2 slotKind: QWORD <|@ <|@
      nr    6  <|@ st <@st|@reference-map: [rsi:0]
live-base-pointers: []
java.util.TreeMap.successor(TreeMap.java:2149) [bci: 0]
locals: Object[null] - - 
>@ <|@ instruction rax|DWORD[.] = MOV [rsi|QWORD[.] + 28] size: DWORD state [bci:0] <|@ <|@
      nr    8  <|@ instruction TEST (x: rax|DWORD[.], y: rax|DWORD[.]) size: DWORD <|@ <|@
      nr   10  <|@ instruction BRANCH trueDestinationProbability: 0.6272184924666058 condition: = trueDestination: B0 -> B1 falseDestination: B0 -> B7 <|@ <|@
    end_IR
  end_block
  begin_block
    name "B1"
    from_bci -1
    to_bci -1
    predecessors "B0" 
    successors "B2" 
    xhandlers
    flags 
    probability 4603824701483181396
    begin_IR
      LIR
      nr   12  <|@ instruction [] = LABEL numbPhis: 0 align: false label: ? <|@ <|@
      nr   14  <|@ instruction rax|DWORD[.] = MOV [rsi|QWORD[.] + 32] size: DWORD <|@ <|@
      nr   16  <|@ instruction rax|QWORD[.] = UNCOMPRESSPOINTER (input: rax|DWORD[.], ~baseRegister: r12|ILLEGAL) nonNull: false lirKindTool: com.oracle.graal.enterprise.z.a@530d7154 encoding: base: 0 shift: 3 <|@ <|@
      nr   18  <|@ instruction r10|QWORD[.] = MOVE rax|QWORD[.] moveKind: QWORD // MoveResolver resolve mapping <|@ <|@
      nr   20  <|@ instruction rax|QWORD[.] = MOVE rsi|QWORD[.] moveKind: QWORD // MoveResolver resolve mapping <|@ <|@
      nr   22  <|@ instruction JUMP ~[] destination: B1 -> B2 <|@ <|@
    end_IR
  end_block
  begin_block
    name "B4"
    from_bci -1
    to_bci -1
    predecessors "B2" 
    successors "B5" "B6" 
    xhandlers
    flags 
    loop_index 0
    loop_depth 1
    probability 4604644223469028748
    begin_IR
      LIR
      nr   36  <|@ instruction [] = LABEL numbPhis: 0 align: true label: ? <|@ <|@
      nr   38  <|@ instruction r11|DWORD[.] = MOV [r10|QWORD[.] + 28] size: DWORD <|@ <|@
      nr   40  <|@ instruction r11|QWORD[.] = UNCOMPRESSPOINTER (input: r11|DWORD[.], ~baseRegister: r12|ILLEGAL) nonNull: false lirKindTool: com.oracle.graal.enterprise.z.a@530d7154 encoding: base: 0 shift: 3 <|@ <|@
      nr   42  <|@ instruction CMP (x: r11|QWORD[.], y: rax|QWORD[.]) size: QWORD <|@ <|@
      nr   44  <|@ instruction BRANCH trueDestinationProbability: 0.5188539645005614 condition: = trueDestination: B4 -> B5 falseDestination: B4 -> B6 <|@ <|@
    end_IR
  end_block
  begin_block
    name "B5"
    from_bci -1
    to_bci -1
    predecessors "B4" 
    successors "B2" 
    xhandlers
    flags "lle" 
    loop_index 0
    loop_depth 1
    probability 4600384556582323090
    begin_IR
      LIR
      nr   46  <|@ instruction [] = LABEL numbPhis: 0 align: false label: ? <|@ <|@
      nr   48  <|@ st <@st|@reference-map: [rax:0, r10:0]
live-base-pointers: []
java.util.TreeMap.successor(TreeMap.java:2159) [bci: 42]
locals: - r10|QWORD[.] rax|QWORD[.] 
>@ <|@ instruction SAFEPOINT - config: org.graalvm.compiler.hotspot.GraalHotSpotVMConfig@7222fe45 thread: r15 state [bci:42] <|@ <|@
      nr   50  <|@ instruction rax|DWORD[.] = MOV [r10|QWORD[.] + 32] size: DWORD <|@ <|@
      nr   52  <|@ instruction rax|QWORD[.] = UNCOMPRESSPOINTER (input: rax|DWORD[.], ~baseRegister: r12|ILLEGAL) nonNull: false lirKindTool: com.oracle.graal.enterprise.z.a@530d7154 encoding: base: 0 shift: 3 <|@ <|@
      nr   54  <|@ instruction stack:32|QWORD[.] = MOVE rax|QWORD[.] moveKind: QWORD // MoveResolver break cycle <|@ <|@
      nr   56  <|@ instruction rax|QWORD[.] = MOVE r10|QWORD[.] moveKind: QWORD // MoveResolver resolve mapping <|@ <|@
      nr   58  <|@ instruction r10|QWORD[.] = MOVE stack:32|QWORD[.] moveKind: QWORD // MoveResolver resolve mapping <|@ <|@
      nr   60  <|@ instruction JUMP ~[] destination: B5 -> B2 <|@ <|@
    end_IR
  end_block
  begin_block
    name "B2"
    from_bci -1
    to_bci -1
    predecessors "B1" "B5" 
    successors "B3" "B4" 
    xhandlers
    flags "llh" 
    loop_index 0
    loop_depth 1
    probability 4607181169815389981
    begin_IR
      LIR
      nr   24  <|@ instruction [] = LABEL numbPhis: 2 align: false label: ? <|@ <|@
      nr   26  <|@ instruction TEST (x: r10|QWORD[.], y: r10|QWORD[.]) size: QWORD <|@ <|@
      nr   28  <|@ instruction BRANCH trueDestinationProbability: 0.28169668610986476 condition: = trueDestination: B2 -> B3 falseDestination: B2 -> B4 <|@ <|@
    end_IR
  end_block
  begin_block
    name "B7"
    from_bci -1
    to_bci -1
    predecessors "B0" 
    successors "B8" 
    xhandlers
    flags 
    probability 4600387054551577944
    begin_IR
      LIR
      nr   68  <|@ instruction [] = LABEL numbPhis: 0 align: false label: ? <|@ <|@
      nr   70  <|@ instruction rax|QWORD[.] = UNCOMPRESSPOINTER (input: rax|DWORD[.], ~baseRegister: r12|ILLEGAL) nonNull: false lirKindTool: com.oracle.graal.enterprise.z.a@530d7154 encoding: base: 0 shift: 3 <|@ <|@
      nr   72  <|@ instruction JUMP ~[] destination: B7 -> B8 <|@ <|@
    end_IR
  end_block
  begin_block
    name "B10"
    from_bci -1
    to_bci -1
    predecessors "B8" 
    successors "B8" 
    xhandlers
    flags "lle" 
    loop_index 1
    loop_depth 1
    probability 4593781971425583707
    begin_IR
      LIR
      nr   86  <|@ instruction [] = LABEL numbPhis: 0 align: true label: ? <|@ <|@
      nr   88  <|@ st <@st|@reference-map: [rax:0, r10:0]
live-base-pointers: []
java.util.TreeMap.successor(TreeMap.java:2153) [bci: 18]
locals: - rax|QWORD[.] - 
>@ <|@ instruction SAFEPOINT - config: org.graalvm.compiler.hotspot.GraalHotSpotVMConfig@7222fe45 thread: r15 state [bci:18] <|@ <|@
      nr   90  <|@ instruction r10|QWORD[.] = UNCOMPRESSPOINTER (input: r10|DWORD[.], ~baseRegister: r12|ILLEGAL) nonNull: false lirKindTool: com.oracle.graal.enterprise.z.a@530d7154 encoding: base: 0 shift: 3 <|@ <|@
      nr   92  <|@ instruction rax|QWORD[.] = MOVE r10|QWORD[.] moveKind: QWORD // MoveResolver resolve mapping <|@ <|@
      nr   94  <|@ instruction JUMP ~[] destination: B10 -> B8 <|@ <|@
    end_IR
  end_block
  begin_block
    name "B8"
    from_bci -1
    to_bci -1
    predecessors "B7" "B10" 
    successors "B9" "B10" 
    xhandlers
    flags "llh" 
    loop_index 1
    loop_depth 1
    probability 4602686424645874499
    begin_IR
      LIR
      nr   74  <|@ instruction [] = LABEL numbPhis: 1 align: false label: ? <|@ <|@
      nr   76  <|@ st <@st|@reference-map: [rax:0]
live-base-pointers: []
java.util.TreeMap.successor(TreeMap.java:2153) [bci: 18]
locals: - rax|QWORD[.] - 
>@ <|@ instruction r10|DWORD[.] = MOV [rax|QWORD[.] + 24] size: DWORD state [bci:18] <|@ <|@
      nr   78  <|@ instruction TEST (x: r10|DWORD[.], y: r10|DWORD[.]) size: DWORD <|@ <|@
      nr   80  <|@ instruction BRANCH trueDestinationProbability: 0.7443060650004265 condition: = trueDestination: B8 -> B9 falseDestination: B8 -> B10 <|@ <|@
    end_IR
  end_block
  begin_block
    name "B9"
    from_bci -1
    to_bci -1
    predecessors "B8" 
    successors 
    xhandlers
    flags 
    probability 4600387054551577945
    begin_IR
      LIR
      nr   82  <|@ instruction [] = LABEL numbPhis: 0 align: false label: ? <|@ <|@
      nr   84  <|@ instruction RETURN (savedRbp: stack:16|QWORD, value: rax|QWORD[.]) isStub: false thread: r15 scratchForSafepointOnReturn: rcx config: org.graalvm.compiler.hotspot.GraalHotSpotVMConfig@7222fe45 <|@ <|@
    end_IR
  end_block
  begin_block
    name "B6"
    from_bci -1
    to_bci -1
    predecessors "B4" 
    successors 
    xhandlers
    flags 
    probability 4599896691100993414
    begin_IR
      LIR
      nr   62  <|@ instruction [] = LABEL numbPhis: 0 align: false label: ? <|@ <|@
      nr   64  <|@ instruction rax|QWORD[.] = MOVE r10|QWORD[.] moveKind: QWORD <|@ <|@
      nr   66  <|@ instruction RETURN (savedRbp: stack:16|QWORD, value: rax|QWORD[.]) isStub: false thread: r15 scratchForSafepointOnReturn: rcx config: org.graalvm.compiler.hotspot.GraalHotSpotVMConfig@7222fe45 <|@ <|@
    end_IR
  end_block
  begin_block
    name "B3"
    from_bci -1
    to_bci -1
    predecessors "B2" 
    successors 
    xhandlers
    flags 
    probability 4598745512610628385
    begin_IR
      LIR
      nr   30  <|@ instruction [] = LABEL numbPhis: 0 align: false label: ? <|@ <|@
      nr   32  <|@ instruction rax|QWORD[.] = MOVE input: Object[null] <|@ <|@
      nr   34  <|@ instruction RETURN (savedRbp: stack:16|QWORD, value: rax|QWORD[.]) isStub: false thread: r15 scratchForSafepointOnReturn: rcx config: org.graalvm.compiler.hotspot.GraalHotSpotVMConfig@7222fe45 <|@ <|@
    end_IR
  end_block
end_cfg
begin_bytecodes
     0: aload_0       
     1: ifnonnull     6
     4: aconst_null   
     5: areturn       
     6: aload_0       
     7: getfield      #29         // java.util.TreeMap$Entry.right:java.util.TreeMap$Entry
    10: ifnull        35
    13: aload_0       
    14: getfield      #29         // java.util.TreeMap$Entry.right:java.util.TreeMap$Entry
    17: astore_1      
    18: aload_1       
    19: getfield      #28         // java.util.TreeMap$Entry.left:java.util.TreeMap$Entry
    22: ifnull        33
    25: aload_1       
    26: getfield      #28         // java.util.TreeMap$Entry.left:java.util.TreeMap$Entry
    29: astore_1      
    30: goto          18
    33: aload_1       
    34: areturn       
    35: aload_0       
    36: getfield      #32         // java.util.TreeMap$Entry.parent:java.util.TreeMap$Entry
    39: astore_1      
    40: aload_0       
    41: astore_2      
    42: aload_1       
    43: ifnull        64
    46: aload_2       
    47: aload_1       
    48: getfield      #29         // java.util.TreeMap$Entry.right:java.util.TreeMap$Entry
    51: if_acmpne     64
    54: aload_1       
    55: astore_2      
    56: aload_1       
    57: getfield      #32         // java.util.TreeMap$Entry.parent:java.util.TreeMap$Entry
    60: astore_1      
    61: goto          42
    64: aload_1       
    65: areturn       
   <|@
end_bytecodes
begin_cfg
  name "After PostAllocationOptimizationStage"
  begin_block
    name "B0"
    from_bci -1
    to_bci -1
    predecessors 
    successors "B1" "B7" 
    xhandlers
    flags 
    probability 4607182418800017408
    begin_IR
      LIR
      nr    0  <|@ instruction [rsi|QWORD[.], rbp|QWORD] = LABEL numbPhis: 0 align: false label: ? <|@ <|@
      nr    2  <|@ instruction stack:16|QWORD = MOVE rbp|QWORD moveKind: QWORD <|@ <|@
      nr    4  <|@ instruction [] = HOTSPOTLOCKSTACK frameMapBuilder: org.graalvm.compiler.lir.amd64.AMD64FrameMapBuilder@6e875bb2 slotKind: QWORD <|@ <|@
      nr    6  <|@ st <@st|@reference-map: [rsi:0]
live-base-pointers: []
java.util.TreeMap.successor(TreeMap.java:2149) [bci: 0]
locals: Object[null] - - 
>@ <|@ instruction rax|DWORD[.] = MOV [rsi|QWORD[.] + 28] size: DWORD state [bci:0] <|@ <|@
      nr    8  <|@ instruction TEST (x: rax|DWORD[.], y: rax|DWORD[.]) size: DWORD <|@ <|@
      nr   10  <|@ instruction BRANCH trueDestinationProbability: 0.6272184924666058 condition: = trueDestination: B0 -> B1 falseDestination: B0 -> B7 <|@ <|@
    end_IR
  end_block
  begin_block
    name "B1"
    from_bci -1
    to_bci -1
    predecessors "B0" 
    successors "B2" 
    xhandlers
    flags 
    probability 4603824701483181396
    begin_IR
      LIR
      nr   12  <|@ instruction [] = LABEL numbPhis: 0 align: false label: ? <|@ <|@
      nr   14  <|@ instruction rax|DWORD[.] = MOV [rsi|QWORD[.] + 32] size: DWORD <|@ <|@
      nr   16  <|@ instruction rax|QWORD[.] = UNCOMPRESSPOINTER (input: rax|DWORD[.], ~baseRegister: r12|ILLEGAL) nonNull: false lirKindTool: com.oracle.graal.enterprise.z.a@530d7154 encoding: base: 0 shift: 3 <|@ <|@
      nr   18  <|@ instruction r10|QWORD[.] = MOVE rax|QWORD[.] moveKind: QWORD // MoveResolver resolve mapping <|@ <|@
      nr   20  <|@ instruction rax|QWORD[.] = MOVE rsi|QWORD[.] moveKind: QWORD // MoveResolver resolve mapping <|@ <|@
      nr   22  <|@ instruction JUMP ~[] destination: B1 -> B2 <|@ <|@
    end_IR
  end_block
  begin_block
    name "B4"
    from_bci -1
    to_bci -1
    predecessors "B2" 
    successors "B5" "B6" 
    xhandlers
    flags 
    loop_index 0
    loop_depth 1
    probability 4604644223469028748
    begin_IR
      LIR
      nr   36  <|@ instruction [] = LABEL numbPhis: 0 align: true label: ? <|@ <|@
      nr   38  <|@ instruction r11|DWORD[.] = MOV [r10|QWORD[.] + 28] size: DWORD <|@ <|@
      nr   40  <|@ instruction r11|QWORD[.] = UNCOMPRESSPOINTER (input: r11|DWORD[.], ~baseRegister: r12|ILLEGAL) nonNull: false lirKindTool: com.oracle.graal.enterprise.z.a@530d7154 encoding: base: 0 shift: 3 <|@ <|@
      nr   42  <|@ instruction CMP (x: r11|QWORD[.], y: rax|QWORD[.]) size: QWORD <|@ <|@
      nr   44  <|@ instruction BRANCH trueDestinationProbability: 0.5188539645005614 condition: = trueDestination: B4 -> B5 falseDestination: B4 -> B6 <|@ <|@
    end_IR
  end_block
  begin_block
    name "B5"
    from_bci -1
    to_bci -1
    predecessors "B4" 
    successors "B2" 
    xhandlers
    flags "lle" 
    loop_index 0
    loop_depth 1
    probability 4600384556582323090
    begin_IR
      LIR
      nr   46  <|@ instruction [] = LABEL numbPhis: 0 align: false label: ? <|@ <|@
      nr   48  <|@ st <@st|@reference-map: [rax:0, r10:0]
live-base-pointers: []
java.util.TreeMap.successor(TreeMap.java:2159) [bci: 42]
locals: - r10|QWORD[.] rax|QWORD[.] 
>@ <|@ instruction SAFEPOINT - config: org.graalvm.compiler.hotspot.GraalHotSpotVMConfig@7222fe45 thread: r15 state [bci:42] <|@ <|@
      nr   50  <|@ instruction rax|DWORD[.] = MOV [r10|QWORD[.] + 32] size: DWORD <|@ <|@
      nr   52  <|@ instruction rax|QWORD[.] = UNCOMPRESSPOINTER (input: rax|DWORD[.], ~baseRegister: r12|ILLEGAL) nonNull: false lirKindTool: com.oracle.graal.enterprise.z.a@530d7154 encoding: base: 0 shift: 3 <|@ <|@
      nr   54  <|@ instruction stack:32|QWORD[.] = MOVE rax|QWORD[.] moveKind: QWORD // MoveResolver break cycle <|@ <|@
      nr   56  <|@ instruction rax|QWORD[.] = MOVE r10|QWORD[.] moveKind: QWORD // MoveResolver resolve mapping <|@ <|@
      nr   58  <|@ instruction r10|QWORD[.] = MOVE stack:32|QWORD[.] moveKind: QWORD // MoveResolver resolve mapping <|@ <|@
      nr   60  <|@ instruction JUMP ~[] destination: B5 -> B2 <|@ <|@
    end_IR
  end_block
  begin_block
    name "B2"
    from_bci -1
    to_bci -1
    predecessors "B1" "B5" 
    successors "B3" "B4" 
    xhandlers
    flags "llh" 
    loop_index 0
    loop_depth 1
    probability 4607181169815389981
    begin_IR
      LIR
      nr   24  <|@ instruction [] = LABEL numbPhis: 2 align: false label: ? <|@ <|@
      nr   26  <|@ instruction TEST (x: r10|QWORD[.], y: r10|QWORD[.]) size: QWORD <|@ <|@
      nr   28  <|@ instruction BRANCH trueDestinationProbability: 0.28169668610986476 condition: = trueDestination: B2 -> B3 falseDestination: B2 -> B4 <|@ <|@
    end_IR
  end_block
  begin_block
    name "B7"
    from_bci -1
    to_bci -1
    predecessors "B0" 
    successors "B8" 
    xhandlers
    flags 
    probability 4600387054551577944
    begin_IR
      LIR
      nr   68  <|@ instruction [] = LABEL numbPhis: 0 align: false label: ? <|@ <|@
      nr   70  <|@ instruction rax|QWORD[.] = UNCOMPRESSPOINTER (input: rax|DWORD[.], ~baseRegister: r12|ILLEGAL) nonNull: false lirKindTool: com.oracle.graal.enterprise.z.a@530d7154 encoding: base: 0 shift: 3 <|@ <|@
      nr   72  <|@ instruction JUMP ~[] destination: B7 -> B8 <|@ <|@
    end_IR
  end_block
  begin_block
    name "B10"
    from_bci -1
    to_bci -1
    predecessors "B8" 
    successors "B8" 
    xhandlers
    flags "lle" 
    loop_index 1
    loop_depth 1
    probability 4593781971425583707
    begin_IR
      LIR
      nr   86  <|@ instruction [] = LABEL numbPhis: 0 align: true label: ? <|@ <|@
      nr   88  <|@ st <@st|@reference-map: [rax:0, r10:0]
live-base-pointers: []
java.util.TreeMap.successor(TreeMap.java:2153) [bci: 18]
locals: - rax|QWORD[.] - 
>@ <|@ instruction SAFEPOINT - config: org.graalvm.compiler.hotspot.GraalHotSpotVMConfig@7222fe45 thread: r15 state [bci:18] <|@ <|@
      nr   90  <|@ instruction r10|QWORD[.] = UNCOMPRESSPOINTER (input: r10|DWORD[.], ~baseRegister: r12|ILLEGAL) nonNull: false lirKindTool: com.oracle.graal.enterprise.z.a@530d7154 encoding: base: 0 shift: 3 <|@ <|@
      nr   92  <|@ instruction rax|QWORD[.] = MOVE r10|QWORD[.] moveKind: QWORD // MoveResolver resolve mapping <|@ <|@
      nr   94  <|@ instruction JUMP ~[] destination: B10 -> B8 <|@ <|@
    end_IR
  end_block
  begin_block
    name "B8"
    from_bci -1
    to_bci -1
    predecessors "B7" "B10" 
    successors "B9" "B10" 
    xhandlers
    flags "llh" 
    loop_index 1
    loop_depth 1
    probability 4602686424645874499
    begin_IR
      LIR
      nr   74  <|@ instruction [] = LABEL numbPhis: 1 align: false label: ? <|@ <|@
      nr   76  <|@ st <@st|@reference-map: [rax:0]
live-base-pointers: []
java.util.TreeMap.successor(TreeMap.java:2153) [bci: 18]
locals: - rax|QWORD[.] - 
>@ <|@ instruction r10|DWORD[.] = MOV [rax|QWORD[.] + 24] size: DWORD state [bci:18] <|@ <|@
      nr   78  <|@ instruction TEST (x: r10|DWORD[.], y: r10|DWORD[.]) size: DWORD <|@ <|@
      nr   80  <|@ instruction BRANCH trueDestinationProbability: 0.7443060650004265 condition: = trueDestination: B8 -> B9 falseDestination: B8 -> B10 <|@ <|@
    end_IR
  end_block
  begin_block
    name "B9"
    from_bci -1
    to_bci -1
    predecessors "B8" 
    successors 
    xhandlers
    flags 
    probability 4600387054551577945
    begin_IR
      LIR
      nr   82  <|@ instruction [] = LABEL numbPhis: 0 align: false label: ? <|@ <|@
      nr   84  <|@ instruction RETURN (savedRbp: stack:16|QWORD, value: rax|QWORD[.]) isStub: false thread: r15 scratchForSafepointOnReturn: rcx config: org.graalvm.compiler.hotspot.GraalHotSpotVMConfig@7222fe45 <|@ <|@
    end_IR
  end_block
  begin_block
    name "B6"
    from_bci -1
    to_bci -1
    predecessors "B4" 
    successors 
    xhandlers
    flags 
    probability 4599896691100993414
    begin_IR
      LIR
      nr   62  <|@ instruction [] = LABEL numbPhis: 0 align: false label: ? <|@ <|@
      nr   64  <|@ instruction rax|QWORD[.] = MOVE r10|QWORD[.] moveKind: QWORD <|@ <|@
      nr   66  <|@ instruction RETURN (savedRbp: stack:16|QWORD, value: rax|QWORD[.]) isStub: false thread: r15 scratchForSafepointOnReturn: rcx config: org.graalvm.compiler.hotspot.GraalHotSpotVMConfig@7222fe45 <|@ <|@
    end_IR
  end_block
  begin_block
    name "B3"
    from_bci -1
    to_bci -1
    predecessors "B2" 
    successors 
    xhandlers
    flags 
    probability 4598745512610628385
    begin_IR
      LIR
      nr   30  <|@ instruction [] = LABEL numbPhis: 0 align: false label: ? <|@ <|@
      nr   32  <|@ instruction rax|QWORD[.] = MOVE input: Object[null] <|@ <|@
      nr   34  <|@ instruction RETURN (savedRbp: stack:16|QWORD, value: rax|QWORD[.]) isStub: false thread: r15 scratchForSafepointOnReturn: rcx config: org.graalvm.compiler.hotspot.GraalHotSpotVMConfig@7222fe45 <|@ <|@
    end_IR
  end_block
end_cfg
begin_bytecodes
     0: aload_0       
     1: ifnonnull     6
     4: aconst_null   
     5: areturn       
     6: aload_0       
     7: getfield      #29         // java.util.TreeMap$Entry.right:java.util.TreeMap$Entry
    10: ifnull        35
    13: aload_0       
    14: getfield      #29         // java.util.TreeMap$Entry.right:java.util.TreeMap$Entry
    17: astore_1      
    18: aload_1       
    19: getfield      #28         // java.util.TreeMap$Entry.left:java.util.TreeMap$Entry
    22: ifnull        33
    25: aload_1       
    26: getfield      #28         // java.util.TreeMap$Entry.left:java.util.TreeMap$Entry
    29: astore_1      
    30: goto          18
    33: aload_1       
    34: areturn       
    35: aload_0       
    36: getfield      #32         // java.util.TreeMap$Entry.parent:java.util.TreeMap$Entry
    39: astore_1      
    40: aload_0       
    41: astore_2      
    42: aload_1       
    43: ifnull        64
    46: aload_2       
    47: aload_1       
    48: getfield      #29         // java.util.TreeMap$Entry.right:java.util.TreeMap$Entry
    51: if_acmpne     64
    54: aload_1       
    55: astore_2      
    56: aload_1       
    57: getfield      #32         // java.util.TreeMap$Entry.parent:java.util.TreeMap$Entry
    60: astore_1      
    61: goto          42
    64: aload_1       
    65: areturn       
   <|@
end_bytecodes
begin_cfg
  name "After code generation"
end_cfg
begin_nmethod
  <<<HexCodeFile
  Platform AMD64 64  <||@
  HexCode 0 89842400c0feff4883ec1848896c24108b461c85c00f85490000008b462048c1e0034c8bd0488bc6e92d000000666690458b5a1c49c1e3034c3bd80f8558000000850500000000418b422048c1e00348890424498bc24c8b14244d85d275d1e94b00000048c1e003e91000000066669085050000000049c1e203498bc2448b50184585d275ea488b6c24104883c418850500000000c5f877c3498bc2488b6c24104883c418850500000000c5f877c348b80000000000000000488b6c24104883c418850500000000c5f877c3e80000000090e80000000090  <||@
  Comment 0 [stack overflow check]  <||@
  Comment 0 3  <||@
  Comment 0 1  <||@
  Comment 11 block B0 null  <||@
  Comment 11 0 [rsi|QWORD[.], rbp|QWORD] = LABEL numbPhis: 0 align: false label: ?  <||@
  Comment 11 2 stack:16|QWORD = MOVE rbp|QWORD moveKind: QWORD  <||@
  Comment 16 4 [] = HOTSPOTLOCKSTACK frameMapBuilder: org.graalvm.compiler.lir.amd64.AMD64FrameMapBuilder@6e875bb2 slotKind: QWORD  <||@
  Comment 16 6 rax|DWORD[.] = MOV [rsi|QWORD[.] + 28] size: DWORD state [bci:0]  <||@
  Comment 16 [rsi:0]at java.util.TreeMap.successor(TreeMap.java:2149) [bci: 0, duringCall: false, rethrow: false]
              |0             |1  |2 
     locals:  |Object[null]  |-  |-   <||@
  Comment 16 {infopoint: IMPLICIT_EXCEPTION}  <||@
  Comment 19 8 TEST (x: rax|DWORD[.], y: rax|DWORD[.]) size: DWORD  <||@
  Comment 21 10 BRANCH trueDestinationProbability: 0.6272184924666058 condition: = trueDestination: B0 -> B1 falseDestination: B0 -> B7  <||@
  Comment 27 block B1 null  <||@
  Comment 27 12 [] = LABEL numbPhis: 0 align: false label: ?  <||@
  Comment 27 14 rax|DWORD[.] = MOV [rsi|QWORD[.] + 32] size: DWORD  <||@
  Comment 30 16 rax|QWORD[.] = UNCOMPRESSPOINTER (input: rax|DWORD[.], ~baseRegister: r12|ILLEGAL) nonNull: false lirKindTool: com.oracle.graal.enterprise.z.a@530d7154 encoding: base: 0 shift: 3  <||@
  Comment 34 18 r10|QWORD[.] = MOVE rax|QWORD[.] moveKind: QWORD  <||@
  Comment 37 20 rax|QWORD[.] = MOVE rsi|QWORD[.] moveKind: QWORD  <||@
  Comment 40 22 JUMP ~[] destination: B1 -> B2  <||@
  Comment 45 block B4 loop 0 depth 1 header:31|LoopBegin  <||@
  Comment 45 36 [] = LABEL numbPhis: 0 align: true label: ?  <||@
  Comment 48 38 r11|DWORD[.] = MOV [r10|QWORD[.] + 28] size: DWORD  <||@
  Comment 52 40 r11|QWORD[.] = UNCOMPRESSPOINTER (input: r11|DWORD[.], ~baseRegister: r12|ILLEGAL) nonNull: false lirKindTool: com.oracle.graal.enterprise.z.a@530d7154 encoding: base: 0 shift: 3  <||@
  Comment 56 42 CMP (x: r11|QWORD[.], y: rax|QWORD[.]) size: QWORD  <||@
  Comment 59 44 BRANCH trueDestinationProbability: 0.5188539645005614 condition: = trueDestination: B4 -> B5 falseDestination: B4 -> B6  <||@
  Comment 65 block B5 loop 0 depth 1 header:31|LoopBegin  <||@
  Comment 65 46 [] = LABEL numbPhis: 0 align: false label: ?  <||@
  Comment 65 48 SAFEPOINT - config: org.graalvm.compiler.hotspot.GraalHotSpotVMConfig@7222fe45 thread: r15 state [bci:42]  <||@
  Comment 65 [rax:0, r10:0]at java.util.TreeMap.successor(TreeMap.java:2159) [bci: 42, duringCall: false, rethrow: false]
              |0  |1             |2            
     locals:  |-  |r10|QWORD[.]  |rax|QWORD[.]   <||@
  Comment 65 {infopoint: SAFEPOINT}  <||@
  Comment 65 11  <||@
  Comment 71 50 rax|DWORD[.] = MOV [r10|QWORD[.] + 32] size: DWORD  <||@
  Comment 75 52 rax|QWORD[.] = UNCOMPRESSPOINTER (input: rax|DWORD[.], ~baseRegister: r12|ILLEGAL) nonNull: false lirKindTool: com.oracle.graal.enterprise.z.a@530d7154 encoding: base: 0 shift: 3  <||@
  Comment 79 54 stack:32|QWORD[.] = MOVE rax|QWORD[.] moveKind: QWORD  <||@
  Comment 83 56 rax|QWORD[.] = MOVE r10|QWORD[.] moveKind: QWORD  <||@
  Comment 86 58 r10|QWORD[.] = MOVE stack:32|QWORD[.] moveKind: QWORD  <||@
  Comment 90 60 JUMP ~[] destination: B5 -> B2  <||@
  Comment 90 block B2 loop 0 depth 1 header:31|LoopBegin  <||@
  Comment 90 24 [] = LABEL numbPhis: 2 align: false label: ?  <||@
  Comment 90 26 TEST (x: r10|QWORD[.], y: r10|QWORD[.]) size: QWORD  <||@
  Comment 93 28 BRANCH trueDestinationProbability: 0.28169668610986476 condition: = trueDestination: B2 -> B3 falseDestination: B2 -> B4  <||@
  Comment 100 block B7 null  <||@
  Comment 100 68 [] = LABEL numbPhis: 0 align: false label: ?  <||@
  Comment 100 70 rax|QWORD[.] = UNCOMPRESSPOINTER (input: rax|DWORD[.], ~baseRegister: r12|ILLEGAL) nonNull: false lirKindTool: com.oracle.graal.enterprise.z.a@530d7154 encoding: base: 0 shift: 3  <||@
  Comment 104 72 JUMP ~[] destination: B7 -> B8  <||@
  Comment 109 block B10 loop 1 depth 1 header:14|LoopBegin  <||@
  Comment 109 86 [] = LABEL numbPhis: 0 align: true label: ?  <||@
  Comment 112 88 SAFEPOINT - config: org.graalvm.compiler.hotspot.GraalHotSpotVMConfig@7222fe45 thread: r15 state [bci:18]  <||@
  Comment 112 [rax:0, r10:0]at java.util.TreeMap.successor(TreeMap.java:2153) [bci: 18, duringCall: false, rethrow: false]
              |0  |1             |2 
     locals:  |-  |rax|QWORD[.]  |-   <||@
  Comment 112 {infopoint: SAFEPOINT}  <||@
  Comment 112 11  <||@
  Comment 118 90 r10|QWORD[.] = UNCOMPRESSPOINTER (input: r10|DWORD[.], ~baseRegister: r12|ILLEGAL) nonNull: false lirKindTool: com.oracle.graal.enterprise.z.a@530d7154 encoding: base: 0 shift: 3  <||@
  Comment 122 92 rax|QWORD[.] = MOVE r10|QWORD[.] moveKind: QWORD  <||@
  Comment 125 94 JUMP ~[] destination: B10 -> B8  <||@
  Comment 125 block B8 loop 1 depth 1 header:14|LoopBegin  <||@
  Comment 125 74 [] = LABEL numbPhis: 1 align: false label: ?  <||@
  Comment 125 76 r10|DWORD[.] = MOV [rax|QWORD[.] + 24] size: DWORD state [bci:18]  <||@
  Comment 125 [rax:0]at java.util.TreeMap.successor(TreeMap.java:2153) [bci: 18, duringCall: false, rethrow: false]
              |0  |1             |2 
     locals:  |-  |rax|QWORD[.]  |-   <||@
  Comment 125 {infopoint: IMPLICIT_EXCEPTION}  <||@
  Comment 129 78 TEST (x: r10|DWORD[.], y: r10|DWORD[.]) size: DWORD  <||@
  Comment 132 80 BRANCH trueDestinationProbability: 0.7443060650004265 condition: = trueDestination: B8 -> B9 falseDestination: B8 -> B10  <||@
  Comment 134 block B9 null  <||@
  Comment 134 82 [] = LABEL numbPhis: 0 align: false label: ?  <||@
  Comment 134 84 RETURN (savedRbp: stack:16|QWORD, value: rax|QWORD[.]) isStub: false thread: r15 scratchForSafepointOnReturn: rcx config: org.graalvm.compiler.hotspot.GraalHotSpotVMConfig@7222fe45  <||@
  Comment 143 12  <||@
  Comment 153 block B6 null  <||@
  Comment 153 62 [] = LABEL numbPhis: 0 align: false label: ?  <||@
  Comment 153 64 rax|QWORD[.] = MOVE r10|QWORD[.] moveKind: QWORD  <||@
  Comment 156 66 RETURN (savedRbp: stack:16|QWORD, value: rax|QWORD[.]) isStub: false thread: r15 scratchForSafepointOnReturn: rcx config: org.graalvm.compiler.hotspot.GraalHotSpotVMConfig@7222fe45  <||@
  Comment 165 12  <||@
  Comment 175 block B3 null  <||@
  Comment 175 30 [] = LABEL numbPhis: 0 align: false label: ?  <||@
  Comment 175 32 rax|QWORD[.] = MOVE input: Object[null]  <||@
  Comment 185 34 RETURN (savedRbp: stack:16|QWORD, value: rax|QWORD[.]) isStub: false thread: r15 scratchForSafepointOnReturn: rcx config: org.graalvm.compiler.hotspot.GraalHotSpotVMConfig@7222fe45  <||@
  Comment 194 12  <||@
  Comment 204 {Stub<ExceptionHandlerStub.exceptionHandler>@0x106c4a620:CallingConvention[rax|QWORD[.], rdx|QWORD]:CallingConvention[rax|QWORD[.], rdx|QWORD]; temps=rdi|ILLEGAL,xmm0|ILLEGAL,xmm1|ILLEGAL,xmm2|ILLEGAL,xmm3|ILLEGAL,xmm4|ILLEGAL,xmm5|ILLEGAL,xmm6|ILLEGAL,xmm7|ILLEGAL,xmm8|ILLEGAL,xmm9|ILLEGAL,xmm10|ILLEGAL,xmm11|ILLEGAL,xmm12|ILLEGAL,xmm13|ILLEGAL,xmm14|ILLEGAL,xmm15|ILLEGAL,xmm16|ILLEGAL,xmm17|ILLEGAL,xmm18|ILLEGAL,xmm19|ILLEGAL,xmm20|ILLEGAL,xmm21|ILLEGAL,xmm22|ILLEGAL,xmm23|ILLEGAL,xmm24|ILLEGAL,xmm25|ILLEGAL,xmm26|ILLEGAL,xmm27|ILLEGAL,xmm28|ILLEGAL,xmm29|ILLEGAL,xmm30|ILLEGAL,xmm31|ILLEGAL,rax|ILLEGAL,rcx|ILLEGAL,rdx|ILLEGAL,rsi|ILLEGAL,r8|ILLEGAL,r9|ILLEGAL,r10|ILLEGAL,r11|ILLEGAL}  <||@
  Comment 204 4  <||@
  Comment 210 {Field[name=CompilerToVM::Data::SharedRuntime_deopt_blob_unpack, type=address, offset=0, address=0x105aa1f88, value=0x106807500]:0x106807500}  <||@
  Comment 210 5  <||@
  HexCodeFile>>> <|@
end_nmethod
begin_compilation
  name " HotSpotCompilation-6114[java.util.TreeMap.successor(TreeMap$Entry)]"
  method "HotSpotCompilation-6114[java.util.TreeMap.successor(TreeMap$Entry)]"
  date 1527005115696
end_compilation
begin_cfg
  name "After code installation"
end_cfg
begin_nmethod
  <<<HexCodeFile
  Platform AMD64 64  <||@
  HexCode 107479be0 89842400c0feff4883ec1848896c24108b461c85c00f85490000008b462048c1e0034c8bd0488bc6e92d000000666690458b5a1c49c1e3034c3bd80f85580000008505df5341fd418b422048c1e00348890424498bc24c8b14244d85d275d1e94b00000048c1e003e9100000006666908505b05341fd49c1e203498bc2448b50184585d275ea488b6c24104883c4188505915341fdc5f877c3498bc2488b6c24104883c41885057b5341fdc5f877c348b80000000000000000488b6c24104883c41885055e5341fdc5f877c3e86f097dff90e849d838ff90  <||@
  Comment 0 [stack overflow check]  <||@
  Comment 0 3  <||@
  Comment 0 1  <||@
  Comment 11 block B0 null  <||@
  Comment 11 0 [rsi|QWORD[.], rbp|QWORD] = LABEL numbPhis: 0 align: false label: ?  <||@
  Comment 11 2 stack:16|QWORD = MOVE rbp|QWORD moveKind: QWORD  <||@
  Comment 16 4 [] = HOTSPOTLOCKSTACK frameMapBuilder: org.graalvm.compiler.lir.amd64.AMD64FrameMapBuilder@6e875bb2 slotKind: QWORD  <||@
  Comment 16 6 rax|DWORD[.] = MOV [rsi|QWORD[.] + 28] size: DWORD state [bci:0]  <||@
  Comment 16 [rsi:0]at java.util.TreeMap.successor(TreeMap.java:2149) [bci: 0, duringCall: false, rethrow: false]
              |0             |1  |2 
     locals:  |Object[null]  |-  |-   <||@
  Comment 16 {infopoint: IMPLICIT_EXCEPTION}  <||@
  Comment 19 8 TEST (x: rax|DWORD[.], y: rax|DWORD[.]) size: DWORD  <||@
  Comment 21 10 BRANCH trueDestinationProbability: 0.6272184924666058 condition: = trueDestination: B0 -> B1 falseDestination: B0 -> B7  <||@
  Comment 27 block B1 null  <||@
  Comment 27 12 [] = LABEL numbPhis: 0 align: false label: ?  <||@
  Comment 27 14 rax|DWORD[.] = MOV [rsi|QWORD[.] + 32] size: DWORD  <||@
  Comment 30 16 rax|QWORD[.] = UNCOMPRESSPOINTER (input: rax|DWORD[.], ~baseRegister: r12|ILLEGAL) nonNull: false lirKindTool: com.oracle.graal.enterprise.z.a@530d7154 encoding: base: 0 shift: 3  <||@
  Comment 34 18 r10|QWORD[.] = MOVE rax|QWORD[.] moveKind: QWORD  <||@
  Comment 37 20 rax|QWORD[.] = MOVE rsi|QWORD[.] moveKind: QWORD  <||@
  Comment 40 22 JUMP ~[] destination: B1 -> B2  <||@
  Comment 45 block B4 loop 0 depth 1 header:31|LoopBegin  <||@
  Comment 45 36 [] = LABEL numbPhis: 0 align: true label: ?  <||@
  Comment 48 38 r11|DWORD[.] = MOV [r10|QWORD[.] + 28] size: DWORD  <||@
  Comment 52 40 r11|QWORD[.] = UNCOMPRESSPOINTER (input: r11|DWORD[.], ~baseRegister: r12|ILLEGAL) nonNull: false lirKindTool: com.oracle.graal.enterprise.z.a@530d7154 encoding: base: 0 shift: 3  <||@
  Comment 56 42 CMP (x: r11|QWORD[.], y: rax|QWORD[.]) size: QWORD  <||@
  Comment 59 44 BRANCH trueDestinationProbability: 0.5188539645005614 condition: = trueDestination: B4 -> B5 falseDestination: B4 -> B6  <||@
  Comment 65 block B5 loop 0 depth 1 header:31|LoopBegin  <||@
  Comment 65 46 [] = LABEL numbPhis: 0 align: false label: ?  <||@
  Comment 65 48 SAFEPOINT - config: org.graalvm.compiler.hotspot.GraalHotSpotVMConfig@7222fe45 thread: r15 state [bci:42]  <||@
  Comment 65 [rax:0, r10:0]at java.util.TreeMap.successor(TreeMap.java:2159) [bci: 42, duringCall: false, rethrow: false]
              |0  |1             |2            
     locals:  |-  |r10|QWORD[.]  |rax|QWORD[.]   <||@
  Comment 65 {infopoint: SAFEPOINT}  <||@
  Comment 65 11  <||@
  Comment 71 50 rax|DWORD[.] = MOV [r10|QWORD[.] + 32] size: DWORD  <||@
  Comment 75 52 rax|QWORD[.] = UNCOMPRESSPOINTER (input: rax|DWORD[.], ~baseRegister: r12|ILLEGAL) nonNull: false lirKindTool: com.oracle.graal.enterprise.z.a@530d7154 encoding: base: 0 shift: 3  <||@
  Comment 79 54 stack:32|QWORD[.] = MOVE rax|QWORD[.] moveKind: QWORD  <||@
  Comment 83 56 rax|QWORD[.] = MOVE r10|QWORD[.] moveKind: QWORD  <||@
  Comment 86 58 r10|QWORD[.] = MOVE stack:32|QWORD[.] moveKind: QWORD  <||@
  Comment 90 60 JUMP ~[] destination: B5 -> B2  <||@
  Comment 90 block B2 loop 0 depth 1 header:31|LoopBegin  <||@
  Comment 90 24 [] = LABEL numbPhis: 2 align: false label: ?  <||@
  Comment 90 26 TEST (x: r10|QWORD[.], y: r10|QWORD[.]) size: QWORD  <||@
  Comment 93 28 BRANCH trueDestinationProbability: 0.28169668610986476 condition: = trueDestination: B2 -> B3 falseDestination: B2 -> B4  <||@
  Comment 100 block B7 null  <||@
  Comment 100 68 [] = LABEL numbPhis: 0 align: false label: ?  <||@
  Comment 100 70 rax|QWORD[.] = UNCOMPRESSPOINTER (input: rax|DWORD[.], ~baseRegister: r12|ILLEGAL) nonNull: false lirKindTool: com.oracle.graal.enterprise.z.a@530d7154 encoding: base: 0 shift: 3  <||@
  Comment 104 72 JUMP ~[] destination: B7 -> B8  <||@
  Comment 109 block B10 loop 1 depth 1 header:14|LoopBegin  <||@
  Comment 109 86 [] = LABEL numbPhis: 0 align: true label: ?  <||@
  Comment 112 88 SAFEPOINT - config: org.graalvm.compiler.hotspot.GraalHotSpotVMConfig@7222fe45 thread: r15 state [bci:18]  <||@
  Comment 112 [rax:0, r10:0]at java.util.TreeMap.successor(TreeMap.java:2153) [bci: 18, duringCall: false, rethrow: false]
              |0  |1             |2 
     locals:  |-  |rax|QWORD[.]  |-   <||@
  Comment 112 {infopoint: SAFEPOINT}  <||@
  Comment 112 11  <||@
  Comment 118 90 r10|QWORD[.] = UNCOMPRESSPOINTER (input: r10|DWORD[.], ~baseRegister: r12|ILLEGAL) nonNull: false lirKindTool: com.oracle.graal.enterprise.z.a@530d7154 encoding: base: 0 shift: 3  <||@
  Comment 122 92 rax|QWORD[.] = MOVE r10|QWORD[.] moveKind: QWORD  <||@
  Comment 125 94 JUMP ~[] destination: B10 -> B8  <||@
  Comment 125 block B8 loop 1 depth 1 header:14|LoopBegin  <||@
  Comment 125 74 [] = LABEL numbPhis: 1 align: false label: ?  <||@
  Comment 125 76 r10|DWORD[.] = MOV [rax|QWORD[.] + 24] size: DWORD state [bci:18]  <||@
  Comment 125 [rax:0]at java.util.TreeMap.successor(TreeMap.java:2153) [bci: 18, duringCall: false, rethrow: false]
              |0  |1             |2 
     locals:  |-  |rax|QWORD[.]  |-   <||@
  Comment 125 {infopoint: IMPLICIT_EXCEPTION}  <||@
  Comment 129 78 TEST (x: r10|DWORD[.], y: r10|DWORD[.]) size: DWORD  <||@
  Comment 132 80 BRANCH trueDestinationProbability: 0.7443060650004265 condition: = trueDestination: B8 -> B9 falseDestination: B8 -> B10  <||@
  Comment 134 block B9 null  <||@
  Comment 134 82 [] = LABEL numbPhis: 0 align: false label: ?  <||@
  Comment 134 84 RETURN (savedRbp: stack:16|QWORD, value: rax|QWORD[.]) isStub: false thread: r15 scratchForSafepointOnReturn: rcx config: org.graalvm.compiler.hotspot.GraalHotSpotVMConfig@7222fe45  <||@
  Comment 143 12  <||@
  Comment 153 block B6 null  <||@
  Comment 153 62 [] = LABEL numbPhis: 0 align: false label: ?  <||@
  Comment 153 64 rax|QWORD[.] = MOVE r10|QWORD[.] moveKind: QWORD  <||@
  Comment 156 66 RETURN (savedRbp: stack:16|QWORD, value: rax|QWORD[.]) isStub: false thread: r15 scratchForSafepointOnReturn: rcx config: org.graalvm.compiler.hotspot.GraalHotSpotVMConfig@7222fe45  <||@
  Comment 165 12  <||@
  Comment 175 block B3 null  <||@
  Comment 175 30 [] = LABEL numbPhis: 0 align: false label: ?  <||@
  Comment 175 32 rax|QWORD[.] = MOVE input: Object[null]  <||@
  Comment 185 34 RETURN (savedRbp: stack:16|QWORD, value: rax|QWORD[.]) isStub: false thread: r15 scratchForSafepointOnReturn: rcx config: org.graalvm.compiler.hotspot.GraalHotSpotVMConfig@7222fe45  <||@
  Comment 194 12  <||@
  Comment 204 {Stub<ExceptionHandlerStub.exceptionHandler>@0x106c4a620:CallingConvention[rax|QWORD[.], rdx|QWORD]:CallingConvention[rax|QWORD[.], rdx|QWORD]; temps=rdi|ILLEGAL,xmm0|ILLEGAL,xmm1|ILLEGAL,xmm2|ILLEGAL,xmm3|ILLEGAL,xmm4|ILLEGAL,xmm5|ILLEGAL,xmm6|ILLEGAL,xmm7|ILLEGAL,xmm8|ILLEGAL,xmm9|ILLEGAL,xmm10|ILLEGAL,xmm11|ILLEGAL,xmm12|ILLEGAL,xmm13|ILLEGAL,xmm14|ILLEGAL,xmm15|ILLEGAL,xmm16|ILLEGAL,xmm17|ILLEGAL,xmm18|ILLEGAL,xmm19|ILLEGAL,xmm20|ILLEGAL,xmm21|ILLEGAL,xmm22|ILLEGAL,xmm23|ILLEGAL,xmm24|ILLEGAL,xmm25|ILLEGAL,xmm26|ILLEGAL,xmm27|ILLEGAL,xmm28|ILLEGAL,xmm29|ILLEGAL,xmm30|ILLEGAL,xmm31|ILLEGAL,rax|ILLEGAL,rcx|ILLEGAL,rdx|ILLEGAL,rsi|ILLEGAL,r8|ILLEGAL,r9|ILLEGAL,r10|ILLEGAL,r11|ILLEGAL}  <||@
  Comment 204 4  <||@
  Comment 210 {Field[name=CompilerToVM::Data::SharedRuntime_deopt_blob_unpack, type=address, offset=0, address=0x105aa1f88, value=0x106807500]:0x106807500}  <||@
  Comment 210 5  <||@
  HexCodeFile>>> <|@
end_nmethod
