begin_compilation
  name " HotSpotCompilation-5488[sun.nio.cs.UTF_8$Decoder.decode(byte[], int, int, char[])]"
  method "HotSpotCompilation-5488[sun.nio.cs.UTF_8$Decoder.decode(byte[], int, int, char[])]"
  date 1527005023378
end_compilation
begin_cfg
  name "Final HIR schedule"
  begin_block
    name "B0"
    from_bci -1
    to_bci -1
    predecessors 
    successors "B1" "B2" 
    xhandlers
    flags 
    probability 4607182418800017408
    begin_IR
      HIR
f <@#|@fixed with next>@ <|@
tid v0 <|@
d <@d|@=== Debug Properties ===
stamp: void
=== Inputs ===
stateAfter: - 
=== Succesors ===
next: v157 
=== Usages ===
=== Predecessor ===
- >@ <|@
instruction <@StartNode|@org.graalvm.compiler.nodes.StartNode>@ stateAfter: - #next: v157  <|@  <|@
f <@~|@floating>@ <|@
tid i3 <|@
d <@d|@=== Debug Properties ===
index: 2
stamp: i32
uncheckedStamp: [null]
=== Inputs ===
=== Succesors ===
=== Usages ===
?6 i7 i17 j124 v131 
=== Predecessor ===
- >@ <|@
instruction <@Parameter|@org.graalvm.compiler.nodes.ParameterNode>@  <|@  <|@
f <@~|@floating>@ <|@
tid i4 <|@
d <@d|@=== Debug Properties ===
index: 3
stamp: i32
uncheckedStamp: [null]
=== Inputs ===
=== Succesors ===
=== Usages ===
?6 i7 i111 v54 
=== Predecessor ===
- >@ <|@
instruction <@Parameter|@org.graalvm.compiler.nodes.ParameterNode>@  <|@  <|@
f <@~|@floating>@ <|@
tid i7 <|@
d <@d|@=== Debug Properties ===
getOp: org.graalvm.compiler.nodes.calc.AddNode$$Lambda$14/562279114@1363f342
nodeSourcePosition: at sun.nio.cs.UTF_8$Decoder.decode(UTF_8.java:428) [bci: 2]
stamp: i32
=== Inputs ===
x: i3 
y: i4 
=== Succesors ===
=== Usages ===
v46 ?19 
=== Predecessor ===
- >@ <|@
instruction <@+|@org.graalvm.compiler.nodes.calc.AddNode>@ x: i3 y: i4  <|@  <|@
f <@~|@floating>@ <|@
tid a1 <|@
d <@d|@=== Debug Properties ===
index: 0
stamp: a!# Lsun/nio/cs/UTF_8$Decoder;
uncheckedStamp: [null]
=== Inputs ===
=== Succesors ===
=== Usages ===
?6 ?19 
=== Predecessor ===
- >@ <|@
instruction <@Parameter|@org.graalvm.compiler.nodes.ParameterNode>@  <|@  <|@
f <@~|@floating>@ <|@
tid a2 <|@
d <@d|@=== Debug Properties ===
index: 1
stamp: a# [B
uncheckedStamp: [null]
=== Inputs ===
=== Succesors ===
=== Usages ===
?6 v70 ?19 v242 v241 
=== Predecessor ===
- >@ <|@
instruction <@Parameter|@org.graalvm.compiler.nodes.ParameterNode>@  <|@  <|@
f <@~|@floating>@ <|@
tid a5 <|@
d <@d|@=== Debug Properties ===
index: 4
stamp: a# [C
uncheckedStamp: [null]
=== Inputs ===
=== Succesors ===
=== Usages ===
?6 v243 v240 ?19 
=== Predecessor ===
- >@ <|@
instruction <@Parameter|@org.graalvm.compiler.nodes.ParameterNode>@  <|@  <|@
tid ?6 <|@
d <@d|@=== Debug Properties ===
bci: 0
code: ResolvedJavaMethodBytecode<UTF_8$Decoder.decode(byte[], int, int, char[])>
duringCall: false
localsSize: 14
locksSize: 0
rethrowException: false
sourceFile: UTF_8.java
sourceLine: 428
stackSize: 0
=== Inputs ===
outerFrameState: - 
values: a1 a2 i3 i4 a5 - - - - - - - - - 
=== Succesors ===
=== Usages ===
v188 i236 
=== Predecessor ===
- >@ <|@
instruction <@FrameState|@org.graalvm.compiler.nodes.FrameState>@ outerFrameState: - values: a1 a2 i3 i4 a5 - - - - - - - - -  <|@  <|@
f <@~|@floating>@ <|@
tid v70 <|@
d <@d|@=== Debug Properties ===
nodeSourcePosition: at sun.nio.cs.UTF_8$Decoder.decode(UTF_8.java:434) [bci: 29]
stamp: void
=== Inputs ===
value: a2 
=== Succesors ===
=== Usages ===
v157 
=== Predecessor ===
- >@ <|@
instruction <@IsNull|@org.graalvm.compiler.nodes.calc.IsNullNode>@ value: a2  <|@  <|@
f <@*|@fixed>@ <|@
tid v157 <|@
d <@d|@=== Debug Properties ===
nodeSourcePosition: at sun.nio.cs.UTF_8$Decoder.decode(UTF_8.java:434) [bci: 29]
stamp: void
trueSuccessorProbability: 0.0
=== Inputs ===
condition: v70 
=== Succesors ===
trueSuccessor: v156 
falseSuccessor: v154 
=== Usages ===
=== Predecessor ===
v0 >@ <|@
instruction <@If|@org.graalvm.compiler.nodes.IfNode>@ condition: v70 #trueSuccessor: v156 #falseSuccessor: v154  <|@  <|@
    end_IR
  end_block
  begin_block
    name "B1"
    from_bci -1
    to_bci -1
    predecessors "B0" 
    successors "B25" 
    xhandlers
    flags 
    probability 2355382605114769408
    begin_IR
      HIR
f <@#|@fixed with next>@ <|@
tid v156 <|@
d <@d|@=== Debug Properties ===
nodeSourcePosition: at sun.nio.cs.UTF_8$Decoder.decode(UTF_8.java:434) [bci: 29]
stamp: void
=== Inputs ===
=== Succesors ===
next: v183 
=== Usages ===
=== Predecessor ===
v157 >@ <|@
instruction <@Begin|@org.graalvm.compiler.nodes.BeginNode>@ #next: v183  <|@  <|@
f <@~|@floating>@ <|@
tid a185 <|@
d <@d|@=== Debug Properties ===
isDefaultStable: false
rawvalue: d.a@206089336
stableDimension: 0
stamp: a!# Lcom/oracle/graal/enterprise/k/d$a;
stampKind: a -
value: Object[d.a@206089336]
=== Inputs ===
=== Succesors ===
=== Usages ===
a187 
=== Predecessor ===
- >@ <|@
instruction <@Constant|@org.graalvm.compiler.nodes.ConstantNode>@  <|@  <|@
f <@~|@floating>@ <|@
tid i184 <|@
d <@d|@=== Debug Properties ===
isDefaultStable: false
rawvalue: -18187
stableDimension: 0
stamp: i32 [-18187] ⇊00000000ffffb8f5 ⇈00000000ffffb8f5
stampKind: i32
value: int[-18187|0xffffffffffffb8f5]
=== Inputs ===
=== Succesors ===
=== Usages ===
i186 
=== Predecessor ===
- >@ <|@
instruction <@Constant|@org.graalvm.compiler.nodes.ConstantNode>@  <|@  <|@
f <@*|@fixed>@ <|@
tid v183 <|@
d <@d|@=== Debug Properties ===
stamp: void
=== Inputs ===
=== Succesors ===
=== Usages ===
v182 
=== Predecessor ===
v156 >@ <|@
instruction <@EndNode|@org.graalvm.compiler.nodes.EndNode>@  <|@  <|@
    end_IR
  end_block
  begin_block
    name "B2"
    from_bci -1
    to_bci -1
    predecessors "B0" 
    successors "B3" "B4" 
    xhandlers
    flags 
    probability 4607182418800017408
    begin_IR
      HIR
f <@#|@fixed with next>@ <|@
tid v154 <|@
d <@d|@=== Debug Properties ===
nodeSourcePosition: at sun.nio.cs.UTF_8$Decoder.decode(UTF_8.java:434) [bci: 29]
stamp: void
=== Inputs ===
=== Succesors ===
next: i236 
=== Usages ===
=== Predecessor ===
v157 >@ <|@
instruction <@Begin|@org.graalvm.compiler.nodes.BeginNode>@ #next: i236  <|@  <|@
f <@~|@floating>@ <|@
tid v240 <|@
d <@d|@=== Debug Properties ===
displacement: 12
scale: Times1
stamp: void*
=== Inputs ===
base: a5 
index: - 
=== Succesors ===
=== Usages ===
i236 
=== Predecessor ===
- >@ <|@
instruction <@AMD64Address|@org.graalvm.compiler.core.amd64.AMD64AddressNode>@ base: a5 index: -  <|@  <|@
f <@#|@fixed with next>@ <|@
tid i236 <|@
d <@d|@=== Debug Properties ===
barrierType: NONE
forceFixed: false
location: [].length:final
nodeSourcePosition: at sun.nio.cs.UTF_8$Decoder.decode(UTF_8.java:430) [bci: 11]
nullCheck: true
stamp: i32 [0 - 2147483647] ⇈000000007fffffff
=== Inputs ===
stateBefore: ?6 
guard: - 
address: v240 
=== Succesors ===
next: v211 
=== Usages ===
i111 v54 v150 j137 
=== Predecessor ===
v154 >@ <|@
instruction <@Read|@org.graalvm.compiler.nodes.memory.ReadNode>@ stateBefore: ?6 guard: - address: v240 #next: v211  <|@  <|@
f <@~|@floating>@ <|@
tid v54 <|@
d <@d|@=== Debug Properties ===
condition: LT
nodeSourcePosition: at java.lang.Math.min(Math.java:1336) [bci: 2]
at sun.nio.cs.UTF_8$Decoder.decode(UTF_8.java:430) [bci: 12]
op: org.graalvm.compiler.nodes.calc.IntegerLessThanNode$LessThanOp@cca0f98
stamp: void
unorderedIsTrue: false
=== Inputs ===
x: i236 
y: i4 
=== Succesors ===
=== Usages ===
i111 
=== Predecessor ===
- >@ <|@
instruction <@<|@org.graalvm.compiler.nodes.calc.IntegerLessThanNode>@ x: i236 y: i4  <|@  <|@
f <@~|@floating>@ <|@
tid i111 <|@
d <@d|@=== Debug Properties ===
stamp: i32
=== Inputs ===
condition: v54 
trueValue: i236 
falseValue: i4 
=== Succesors ===
=== Usages ===
j125 v20 ?19 v147 
=== Predecessor ===
- >@ <|@
instruction <@Conditional|@org.graalvm.compiler.nodes.calc.ConditionalNode>@ condition: v54 trueValue: i236 falseValue: i4  <|@  <|@
f <@~|@floating>@ <|@
tid j125 <|@
d <@d|@=== Debug Properties ===
getOp: org.graalvm.compiler.nodes.calc.SignExtendNode$$Lambda$10/1121602809@34736fd3
getReverseOp: org.graalvm.compiler.nodes.calc.SignExtendNode$$Lambda$11/1363241743@10f97424
inputBits: 32
resultBits: 64
stamp: i64 [-2147483648 - 2147483647]
=== Inputs ===
value: i111 
=== Succesors ===
=== Usages ===
j127 
=== Predecessor ===
- >@ <|@
instruction <@SignExtend|@org.graalvm.compiler.nodes.calc.SignExtendNode>@ value: i111  <|@  <|@
f <@~|@floating>@ <|@
tid j126 <|@
d <@d|@=== Debug Properties ===
isDefaultStable: false
rawvalue: -1
stableDimension: 0
stamp: i64 [-1] ⇊ffffffffffffffff
stampKind: i64
value: long[-1|0xffffffffffffffff]
=== Inputs ===
=== Succesors ===
=== Usages ===
j127 
=== Predecessor ===
- >@ <|@
instruction <@Constant|@org.graalvm.compiler.nodes.ConstantNode>@  <|@  <|@
f <@~|@floating>@ <|@
tid j127 <|@
d <@d|@=== Debug Properties ===
getOp: org.graalvm.compiler.nodes.calc.AddNode$$Lambda$14/562279114@1363f342
stamp: i64 [-2147483649 - 2147483646]
=== Inputs ===
x: j125 
y: j126 
=== Succesors ===
=== Usages ===
j128 v140 
=== Predecessor ===
- >@ <|@
instruction <@+|@org.graalvm.compiler.nodes.calc.AddNode>@ x: j125 y: j126  <|@  <|@
f <@~|@floating>@ <|@
tid i31 <|@
d <@d|@=== Debug Properties ===
isDefaultStable: false
nodeSourcePosition: at sun.nio.cs.UTF_8$Decoder.decode(UTF_8.java:435) [bci: 37]
rawvalue: 1
stableDimension: 0
stamp: i32 [1] ⇊0000000000000001 ⇈0000000000000001
stampKind: i32
value: int[1|0x1]
=== Inputs ===
=== Succesors ===
=== Usages ===
i32 i33 v147 
=== Predecessor ===
- >@ <|@
instruction <@Constant|@org.graalvm.compiler.nodes.ConstantNode>@  <|@  <|@
f <@~|@floating>@ <|@
tid v147 <|@
d <@d|@=== Debug Properties ===
condition: LT
op: org.graalvm.compiler.nodes.calc.IntegerLessThanNode$LessThanOp@cca0f98
stamp: void
unorderedIsTrue: false
=== Inputs ===
x: i111 
y: i31 
=== Succesors ===
=== Usages ===
v227 v211 
=== Predecessor ===
- >@ <|@
instruction <@<|@org.graalvm.compiler.nodes.calc.IntegerLessThanNode>@ x: i111 y: i31  <|@  <|@
f <@~|@floating>@ <|@
tid a193 <|@
d <@d|@=== Debug Properties ===
isDefaultStable: false
rawvalue: d.a@1183312594
stableDimension: 0
stamp: a!# Lcom/oracle/graal/enterprise/k/d$a;
stampKind: a -
value: Object[d.a@1183312594]
=== Inputs ===
=== Succesors ===
=== Usages ===
a187 a187 a187 a187 
=== Predecessor ===
- >@ <|@
instruction <@Constant|@org.graalvm.compiler.nodes.ConstantNode>@  <|@  <|@
f <@*|@fixed>@ <|@
tid v211 <|@
d <@d|@=== Debug Properties ===
nodeSourcePosition: at sun.nio.cs.UTF_8$Decoder.decode(UTF_8.java:435) [bci: 45]
stamp: void
trueSuccessorProbability: 0.5
=== Inputs ===
condition: v147 
=== Succesors ===
trueSuccessor: v207 
falseSuccessor: v210 
=== Usages ===
=== Predecessor ===
i236 >@ <|@
instruction <@If|@org.graalvm.compiler.nodes.IfNode>@ condition: v147 #trueSuccessor: v207 #falseSuccessor: v210  <|@  <|@
    end_IR
  end_block
  begin_block
    name "B3"
    from_bci -1
    to_bci -1
    predecessors "B2" 
    successors "B7" 
    xhandlers
    flags 
    probability 4602678819172646912
    begin_IR
      HIR
f <@#|@fixed with next>@ <|@
tid v207 <|@
d <@d|@=== Debug Properties ===
nodeSourcePosition: at sun.nio.cs.UTF_8$Decoder.decode(UTF_8.java:435) [bci: 45]
stamp: void
=== Inputs ===
=== Succesors ===
next: v205 
=== Usages ===
=== Predecessor ===
v211 >@ <|@
instruction <@Begin|@org.graalvm.compiler.nodes.BeginNode>@ #next: v205  <|@  <|@
f <@*|@fixed>@ <|@
tid v205 <|@
d <@d|@=== Debug Properties ===
nodeSourcePosition: at sun.nio.cs.UTF_8$Decoder.decode(UTF_8.java:435) [bci: 45]
stamp: void
=== Inputs ===
=== Succesors ===
=== Usages ===
v204 
=== Predecessor ===
v207 >@ <|@
instruction <@EndNode|@org.graalvm.compiler.nodes.EndNode>@  <|@  <|@
    end_IR
  end_block
  begin_block
    name "B4"
    from_bci -1
    to_bci -1
    predecessors "B2" 
    successors "B5" "B24" 
    xhandlers
    flags 
    probability 4602678819172646912
    begin_IR
      HIR
f <@#|@fixed with next>@ <|@
tid v210 <|@
d <@d|@=== Debug Properties ===
nodeSourcePosition: at sun.nio.cs.UTF_8$Decoder.decode(UTF_8.java:435) [bci: 45]
stamp: void
=== Inputs ===
=== Succesors ===
next: i237 
=== Usages ===
=== Predecessor ===
v211 >@ <|@
instruction <@Begin|@org.graalvm.compiler.nodes.BeginNode>@ #next: i237  <|@  <|@
f <@~|@floating>@ <|@
tid v241 <|@
d <@d|@=== Debug Properties ===
displacement: 12
scale: Times1
stamp: void*
=== Inputs ===
base: a2 
index: - 
=== Succesors ===
=== Usages ===
i237 
=== Predecessor ===
- >@ <|@
instruction <@AMD64Address|@org.graalvm.compiler.core.amd64.AMD64AddressNode>@ base: a2 index: -  <|@  <|@
f <@#|@fixed with next>@ <|@
tid i237 <|@
d <@d|@=== Debug Properties ===
barrierType: NONE
forceFixed: false
location: [].length:final
nodeSourcePosition: at sun.nio.cs.UTF_8$Decoder.decode(UTF_8.java:434) [bci: 29]
nullCheck: false
stamp: i32 [0 - 2147483647] ⇈000000007fffffff
=== Inputs ===
stateBefore: - 
guard: - 
address: v241 
=== Succesors ===
next: v219 
=== Usages ===
v131 j122 
=== Predecessor ===
v210 >@ <|@
instruction <@Read|@org.graalvm.compiler.nodes.memory.ReadNode>@ stateBefore: - guard: - address: v241 #next: v219  <|@  <|@
f <@~|@floating>@ <|@
tid j124 <|@
d <@d|@=== Debug Properties ===
getOp: org.graalvm.compiler.nodes.calc.SignExtendNode$$Lambda$10/1121602809@34736fd3
getReverseOp: org.graalvm.compiler.nodes.calc.SignExtendNode$$Lambda$11/1363241743@10f97424
inputBits: 32
resultBits: 64
stamp: i64 [-2147483648 - 2147483647]
=== Inputs ===
value: i3 
=== Succesors ===
=== Usages ===
j128 
=== Predecessor ===
- >@ <|@
instruction <@SignExtend|@org.graalvm.compiler.nodes.calc.SignExtendNode>@ value: i3  <|@  <|@
f <@~|@floating>@ <|@
tid j128 <|@
d <@d|@=== Debug Properties ===
getOp: org.graalvm.compiler.nodes.calc.AddNode$$Lambda$14/562279114@1363f342
stamp: i64 [-4294967297 - 4294967293]
=== Inputs ===
x: j124 
y: j127 
=== Succesors ===
=== Usages ===
v130 
=== Predecessor ===
- >@ <|@
instruction <@+|@org.graalvm.compiler.nodes.calc.AddNode>@ x: j124 y: j127  <|@  <|@
f <@~|@floating>@ <|@
tid j122 <|@
d <@d|@=== Debug Properties ===
getOp: org.graalvm.compiler.nodes.calc.ZeroExtendNode$$Lambda$16/1174728845@6b2a0100
getReverseOp: org.graalvm.compiler.nodes.calc.ZeroExtendNode$$Lambda$17/2049777509@675f16c4
inputAlwaysPositive: true
inputBits: 32
resultBits: 64
stamp: i64 [0 - 2147483647] ⇈000000007fffffff
=== Inputs ===
value: i237 
=== Succesors ===
=== Usages ===
v130 
=== Predecessor ===
- >@ <|@
instruction <@ZeroExtend|@org.graalvm.compiler.nodes.calc.ZeroExtendNode>@ value: i237  <|@  <|@
f <@~|@floating>@ <|@
tid v130 <|@
d <@d|@=== Debug Properties ===
condition: BT
op: org.graalvm.compiler.nodes.calc.IntegerBelowNode$BelowOp@66bde537
stamp: void
unorderedIsTrue: false
=== Inputs ===
x: j128 
y: j122 
=== Succesors ===
=== Usages ===
v219 
=== Predecessor ===
- >@ <|@
instruction <@|<||@org.graalvm.compiler.nodes.calc.IntegerBelowNode>@ x: j128 y: j122  <|@  <|@
f <@~|@floating>@ <|@
tid i192 <|@
d <@d|@=== Debug Properties ===
isDefaultStable: false
rawvalue: -22555
stableDimension: 0
stamp: i32 [-22555] ⇊00000000ffffa7e5 ⇈00000000ffffa7e5
stampKind: i32
value: int[-22555|0xffffffffffffa7e5]
=== Inputs ===
=== Succesors ===
=== Usages ===
i186 i186 
=== Predecessor ===
- >@ <|@
instruction <@Constant|@org.graalvm.compiler.nodes.ConstantNode>@  <|@  <|@
f <@*|@fixed>@ <|@
tid v219 <|@
d <@d|@=== Debug Properties ===
nodeSourcePosition: at sun.nio.cs.UTF_8$Decoder.decode(UTF_8.java:435) [bci: 45]
stamp: void
trueSuccessorProbability: 1.0
=== Inputs ===
condition: v130 
=== Succesors ===
trueSuccessor: v218 
falseSuccessor: v215 
=== Usages ===
=== Predecessor ===
i237 >@ <|@
instruction <@If|@org.graalvm.compiler.nodes.IfNode>@ condition: v130 #trueSuccessor: v218 #falseSuccessor: v215  <|@  <|@
    end_IR
  end_block
  begin_block
    name "B5"
    from_bci -1
    to_bci -1
    predecessors "B4" 
    successors "B6" "B23" 
    xhandlers
    flags 
    probability 4602678819172646912
    begin_IR
      HIR
f <@#|@fixed with next>@ <|@
tid v218 <|@
d <@d|@=== Debug Properties ===
nodeSourcePosition: at sun.nio.cs.UTF_8$Decoder.decode(UTF_8.java:435) [bci: 45]
stamp: void
=== Inputs ===
=== Succesors ===
next: v217 
=== Usages ===
=== Predecessor ===
v219 >@ <|@
instruction <@Begin|@org.graalvm.compiler.nodes.BeginNode>@ #next: v217  <|@  <|@
f <@~|@floating>@ <|@
tid v131 <|@
d <@d|@=== Debug Properties ===
condition: BT
op: org.graalvm.compiler.nodes.calc.IntegerBelowNode$BelowOp@66bde537
stamp: void
unorderedIsTrue: false
=== Inputs ===
x: i3 
y: i237 
=== Succesors ===
=== Usages ===
v217 
=== Predecessor ===
- >@ <|@
instruction <@|<||@org.graalvm.compiler.nodes.calc.IntegerBelowNode>@ x: i3 y: i237  <|@  <|@
f <@*|@fixed>@ <|@
tid v217 <|@
d <@d|@=== Debug Properties ===
nodeSourcePosition: at sun.nio.cs.UTF_8$Decoder.decode(UTF_8.java:435) [bci: 45]
stamp: void
trueSuccessorProbability: 1.0
=== Inputs ===
condition: v131 
=== Succesors ===
trueSuccessor: v208 
falseSuccessor: v216 
=== Usages ===
=== Predecessor ===
v218 >@ <|@
instruction <@If|@org.graalvm.compiler.nodes.IfNode>@ condition: v131 #trueSuccessor: v208 #falseSuccessor: v216  <|@  <|@
    end_IR
  end_block
  begin_block
    name "B6"
    from_bci -1
    to_bci -1
    predecessors "B5" 
    successors "B7" 
    xhandlers
    flags 
    probability 4602678819172646912
    begin_IR
      HIR
f <@#|@fixed with next>@ <|@
tid v208 <|@
d <@d|@=== Debug Properties ===
nodeSourcePosition: at sun.nio.cs.UTF_8$Decoder.decode(UTF_8.java:435) [bci: 45]
stamp: void
=== Inputs ===
=== Succesors ===
next: v206 
=== Usages ===
=== Predecessor ===
v217 >@ <|@
instruction <@Begin|@org.graalvm.compiler.nodes.BeginNode>@ #next: v206  <|@  <|@
f <@*|@fixed>@ <|@
tid v206 <|@
d <@d|@=== Debug Properties ===
nodeSourcePosition: at sun.nio.cs.UTF_8$Decoder.decode(UTF_8.java:435) [bci: 45]
stamp: void
=== Inputs ===
=== Succesors ===
=== Usages ===
v204 
=== Predecessor ===
v208 >@ <|@
instruction <@EndNode|@org.graalvm.compiler.nodes.EndNode>@  <|@  <|@
    end_IR
  end_block
  begin_block
    name "B7"
    from_bci -1
    to_bci -1
    predecessors "B3" "B6" 
    successors "B8" "B9" 
    xhandlers
    flags 
    probability 4607182418800017408
    begin_IR
      HIR
f <@#|@fixed with next>@ <|@
tid v204 <|@
d <@d|@=== Debug Properties ===
nodeSourcePosition: at sun.nio.cs.UTF_8$Decoder.decode(UTF_8.java:435) [bci: 45]
stamp: void
=== Inputs ===
stateAfter: - 
ends: v205 v206 
=== Succesors ===
next: v227 
=== Usages ===
v136 
=== Predecessor ===
- >@ <|@
instruction <@Merge|@org.graalvm.compiler.nodes.MergeNode>@ stateAfter: - ends: v205 v206 #next: v227  <|@  <|@
f <@~|@floating>@ <|@
tid i8 <|@
d <@d|@=== Debug Properties ===
isDefaultStable: false
nodeSourcePosition: at sun.nio.cs.UTF_8$Decoder.decode(UTF_8.java:429) [bci: 5]
rawvalue: 0
stableDimension: 0
stamp: i32 [0] ⇈0000000000000000
stampKind: i32
value: int[0|0x0]
=== Inputs ===
=== Succesors ===
=== Usages ===
v29 i18 v150 
=== Predecessor ===
- >@ <|@
instruction <@Constant|@org.graalvm.compiler.nodes.ConstantNode>@  <|@  <|@
f <@*|@fixed>@ <|@
tid v227 <|@
d <@d|@=== Debug Properties ===
nodeSourcePosition: at sun.nio.cs.UTF_8$Decoder.decode(UTF_8.java:435) [bci: 47]
stamp: void
trueSuccessorProbability: 0.5
=== Inputs ===
condition: v147 
=== Succesors ===
trueSuccessor: v223 
falseSuccessor: v226 
=== Usages ===
=== Predecessor ===
v204 >@ <|@
instruction <@If|@org.graalvm.compiler.nodes.IfNode>@ condition: v147 #trueSuccessor: v223 #falseSuccessor: v226  <|@  <|@
    end_IR
  end_block
  begin_block
    name "B8"
    from_bci -1
    to_bci -1
    predecessors "B7" 
    successors "B13" 
    xhandlers
    flags 
    probability 4602678819172646912
    begin_IR
      HIR
f <@#|@fixed with next>@ <|@
tid v223 <|@
d <@d|@=== Debug Properties ===
nodeSourcePosition: at sun.nio.cs.UTF_8$Decoder.decode(UTF_8.java:435) [bci: 47]
stamp: void
=== Inputs ===
=== Succesors ===
next: v221 
=== Usages ===
=== Predecessor ===
v227 >@ <|@
instruction <@Begin|@org.graalvm.compiler.nodes.BeginNode>@ #next: v221  <|@  <|@
f <@*|@fixed>@ <|@
tid v221 <|@
d <@d|@=== Debug Properties ===
nodeSourcePosition: at sun.nio.cs.UTF_8$Decoder.decode(UTF_8.java:435) [bci: 47]
stamp: void
=== Inputs ===
=== Succesors ===
=== Usages ===
v220 
=== Predecessor ===
v223 >@ <|@
instruction <@EndNode|@org.graalvm.compiler.nodes.EndNode>@  <|@  <|@
    end_IR
  end_block
  begin_block
    name "B9"
    from_bci -1
    to_bci -1
    predecessors "B7" 
    successors "B10" "B22" 
    xhandlers
    flags 
    probability 4602678819172646912
    begin_IR
      HIR
f <@#|@fixed with next>@ <|@
tid v226 <|@
d <@d|@=== Debug Properties ===
nodeSourcePosition: at sun.nio.cs.UTF_8$Decoder.decode(UTF_8.java:435) [bci: 47]
stamp: void
=== Inputs ===
=== Succesors ===
next: v235 
=== Usages ===
=== Predecessor ===
v227 >@ <|@
instruction <@Begin|@org.graalvm.compiler.nodes.BeginNode>@ #next: v235  <|@  <|@
f <@~|@floating>@ <|@
tid j137 <|@
d <@d|@=== Debug Properties ===
getOp: org.graalvm.compiler.nodes.calc.ZeroExtendNode$$Lambda$16/1174728845@6b2a0100
getReverseOp: org.graalvm.compiler.nodes.calc.ZeroExtendNode$$Lambda$17/2049777509@675f16c4
inputAlwaysPositive: true
inputBits: 32
resultBits: 64
stamp: i64 [0 - 2147483647] ⇈000000007fffffff
=== Inputs ===
value: i236 
=== Succesors ===
=== Usages ===
v140 
=== Predecessor ===
- >@ <|@
instruction <@ZeroExtend|@org.graalvm.compiler.nodes.calc.ZeroExtendNode>@ value: i236  <|@  <|@
f <@~|@floating>@ <|@
tid v140 <|@
d <@d|@=== Debug Properties ===
condition: BT
op: org.graalvm.compiler.nodes.calc.IntegerBelowNode$BelowOp@66bde537
stamp: void
unorderedIsTrue: false
=== Inputs ===
x: j127 
y: j137 
=== Succesors ===
=== Usages ===
v235 
=== Predecessor ===
- >@ <|@
instruction <@|<||@org.graalvm.compiler.nodes.calc.IntegerBelowNode>@ x: j127 y: j137  <|@  <|@
f <@~|@floating>@ <|@
tid i195 <|@
d <@d|@=== Debug Properties ===
isDefaultStable: false
rawvalue: -25115
stableDimension: 0
stamp: i32 [-25115] ⇊00000000ffff9de5 ⇈00000000ffff9de5
stampKind: i32
value: int[-25115|0xffffffffffff9de5]
=== Inputs ===
=== Succesors ===
=== Usages ===
i186 i186 
=== Predecessor ===
- >@ <|@
instruction <@Constant|@org.graalvm.compiler.nodes.ConstantNode>@  <|@  <|@
f <@*|@fixed>@ <|@
tid v235 <|@
d <@d|@=== Debug Properties ===
nodeSourcePosition: at sun.nio.cs.UTF_8$Decoder.decode(UTF_8.java:435) [bci: 47]
stamp: void
trueSuccessorProbability: 1.0
=== Inputs ===
condition: v140 
=== Succesors ===
trueSuccessor: v234 
falseSuccessor: v231 
=== Usages ===
=== Predecessor ===
v226 >@ <|@
instruction <@If|@org.graalvm.compiler.nodes.IfNode>@ condition: v140 #trueSuccessor: v234 #falseSuccessor: v231  <|@  <|@
    end_IR
  end_block
  begin_block
    name "B10"
    from_bci -1
    to_bci -1
    predecessors "B9" 
    successors "B11" "B12" 
    xhandlers
    flags 
    probability 4602678819172646912
    begin_IR
      HIR
f <@#|@fixed with next>@ <|@
tid v234 <|@
d <@d|@=== Debug Properties ===
nodeSourcePosition: at sun.nio.cs.UTF_8$Decoder.decode(UTF_8.java:435) [bci: 47]
stamp: void
=== Inputs ===
=== Succesors ===
next: v233 
=== Usages ===
=== Predecessor ===
v235 >@ <|@
instruction <@Begin|@org.graalvm.compiler.nodes.BeginNode>@ #next: v233  <|@  <|@
f <@~|@floating>@ <|@
tid v150 <|@
d <@d|@=== Debug Properties ===
condition: EQ
stamp: void
unorderedIsTrue: false
=== Inputs ===
x: i236 
y: i8 
=== Succesors ===
=== Usages ===
v233 
=== Predecessor ===
- >@ <|@
instruction <@==|@org.graalvm.compiler.nodes.calc.IntegerEqualsNode>@ x: i236 y: i8  <|@  <|@
f <@*|@fixed>@ <|@
tid v233 <|@
d <@d|@=== Debug Properties ===
nodeSourcePosition: at sun.nio.cs.UTF_8$Decoder.decode(UTF_8.java:435) [bci: 47]
stamp: void
trueSuccessorProbability: 0.0
=== Inputs ===
condition: v150 
=== Succesors ===
trueSuccessor: v232 
falseSuccessor: v224 
=== Usages ===
=== Predecessor ===
v234 >@ <|@
instruction <@If|@org.graalvm.compiler.nodes.IfNode>@ condition: v150 #trueSuccessor: v232 #falseSuccessor: v224  <|@  <|@
    end_IR
  end_block
  begin_block
    name "B11"
    from_bci -1
    to_bci -1
    predecessors "B10" 
    successors "B25" 
    xhandlers
    flags 
    probability 2355382605114769408
    begin_IR
      HIR
f <@#|@fixed with next>@ <|@
tid v232 <|@
d <@d|@=== Debug Properties ===
nodeSourcePosition: at sun.nio.cs.UTF_8$Decoder.decode(UTF_8.java:435) [bci: 47]
stamp: void
=== Inputs ===
=== Succesors ===
next: v245 
=== Usages ===
=== Predecessor ===
v233 >@ <|@
instruction <@Begin|@org.graalvm.compiler.nodes.BeginNode>@ #next: v245  <|@  <|@
f <@*|@fixed>@ <|@
tid v245 <|@
d <@d|@=== Debug Properties ===
nodeSourcePosition: at sun.nio.cs.UTF_8$Decoder.decode(UTF_8.java:435) [bci: 47]
stamp: void
=== Inputs ===
=== Succesors ===
=== Usages ===
v182 
=== Predecessor ===
v232 >@ <|@
instruction <@EndNode|@org.graalvm.compiler.nodes.EndNode>@  <|@  <|@
    end_IR
  end_block
  begin_block
    name "B12"
    from_bci -1
    to_bci -1
    predecessors "B10" 
    successors "B13" 
    xhandlers
    flags 
    probability 4602678819172646912
    begin_IR
      HIR
f <@#|@fixed with next>@ <|@
tid v224 <|@
d <@d|@=== Debug Properties ===
nodeSourcePosition: at sun.nio.cs.UTF_8$Decoder.decode(UTF_8.java:435) [bci: 47]
stamp: void
=== Inputs ===
=== Succesors ===
next: v222 
=== Usages ===
=== Predecessor ===
v233 >@ <|@
instruction <@Begin|@org.graalvm.compiler.nodes.BeginNode>@ #next: v222  <|@  <|@
f <@*|@fixed>@ <|@
tid v222 <|@
d <@d|@=== Debug Properties ===
nodeSourcePosition: at sun.nio.cs.UTF_8$Decoder.decode(UTF_8.java:435) [bci: 47]
stamp: void
=== Inputs ===
=== Succesors ===
=== Usages ===
v220 
=== Predecessor ===
v224 >@ <|@
instruction <@EndNode|@org.graalvm.compiler.nodes.EndNode>@  <|@  <|@
    end_IR
  end_block
  begin_block
    name "B13"
    from_bci -1
    to_bci -1
    predecessors "B8" "B12" 
    successors "B14" 
    xhandlers
    flags 
    probability 4607182418800017408
    begin_IR
      HIR
f <@#|@fixed with next>@ <|@
tid v220 <|@
d <@d|@=== Debug Properties ===
nodeSourcePosition: at sun.nio.cs.UTF_8$Decoder.decode(UTF_8.java:435) [bci: 47]
stamp: void
=== Inputs ===
stateAfter: - 
ends: v221 v222 
=== Succesors ===
next: v15 
=== Usages ===
v145 
=== Predecessor ===
- >@ <|@
instruction <@Merge|@org.graalvm.compiler.nodes.MergeNode>@ stateAfter: - ends: v221 v222 #next: v15  <|@  <|@
f <@*|@fixed>@ <|@
tid v15 <|@
d <@d|@=== Debug Properties ===
nodeSourcePosition: at sun.nio.cs.UTF_8$Decoder.decode(UTF_8.java:434) [bci: 20]
stamp: void
=== Inputs ===
=== Succesors ===
=== Usages ===
v16 
=== Predecessor ===
v220 >@ <|@
instruction <@EndNode|@org.graalvm.compiler.nodes.EndNode>@  <|@  <|@
    end_IR
  end_block
  begin_block
    name "B14"
    from_bci -1
    to_bci -1
    predecessors "B13" "B17" 
    successors "B15" "B18" 
    xhandlers
    flags "llh" 
    loop_index 0
    loop_depth 1
    probability 4647359331217820312
    begin_IR
      HIR
f <@~|@floating>@ <|@
tid i17 <|@
d <@d|@=== Debug Properties ===
stamp: i32
valueDescription: i32
=== Inputs ===
merge: v16 
values: i3 i33 
=== Succesors ===
=== Usages ===
?19 v46 v242 i33 
=== Predecessor ===
- >@ <|@
instruction <@ValuePhi|@org.graalvm.compiler.nodes.ValuePhiNode>@ merge: v16 values: i3 i33  <|@  <|@
f <@~|@floating>@ <|@
tid i18 <|@
d <@d|@=== Debug Properties ===
stamp: i32
valueDescription: i32
=== Inputs ===
merge: v16 
values: i8 i32 
=== Succesors ===
=== Usages ===
?19 v20 v52 i32 v243 
=== Predecessor ===
- >@ <|@
instruction <@ValuePhi|@org.graalvm.compiler.nodes.ValuePhiNode>@ merge: v16 values: i8 i32  <|@  <|@
f <@#|@fixed with next>@ <|@
tid v16 <|@
d <@d|@=== Debug Properties ===
canEndsSafepoint: false
inversionCount: 0
loopFrequency: 491.79306109916934
loopOrigFrequency: 1.0
loopType: SIMPLE_LOOP
nextEndIndex: 1
nodeSourcePosition: at sun.nio.cs.UTF_8$Decoder.decode(UTF_8.java:434) [bci: 20]
splits: 0
stamp: void
unrollFactor: 1
unswitches: 0
=== Inputs ===
stateAfter: - 
overflowGuard: - 
ends: v15 
=== Succesors ===
next: v27 
=== Usages ===
i17 i18 v23 v39 v173 
=== Predecessor ===
- >@ <|@
instruction <@LoopBegin|@org.graalvm.compiler.nodes.LoopBeginNode>@ stateAfter: - overflowGuard: - ends: v15 #next: v27  <|@  <|@
f <@~|@floating>@ <|@
tid v20 <|@
d <@d|@=== Debug Properties ===
condition: LT
nodeSourcePosition: at sun.nio.cs.UTF_8$Decoder.decode(UTF_8.java:434) [bci: 24]
op: org.graalvm.compiler.nodes.calc.IntegerLessThanNode$LessThanOp@cca0f98
stamp: void
unorderedIsTrue: false
=== Inputs ===
x: i18 
y: i111 
=== Succesors ===
=== Usages ===
v27 
=== Predecessor ===
- >@ <|@
instruction <@<|@org.graalvm.compiler.nodes.calc.IntegerLessThanNode>@ x: i18 y: i111  <|@  <|@
f <@*|@fixed>@ <|@
tid v27 <|@
d <@d|@=== Debug Properties ===
nodeSourcePosition: at sun.nio.cs.UTF_8$Decoder.decode(UTF_8.java:434) [bci: 24]
stamp: void
trueSuccessorProbability: 0.9979666244217335
=== Inputs ===
condition: v20 
=== Succesors ===
trueSuccessor: v21 
falseSuccessor: v23 
=== Usages ===
=== Predecessor ===
v16 >@ <|@
instruction <@If|@org.graalvm.compiler.nodes.IfNode>@ condition: v20 #trueSuccessor: v21 #falseSuccessor: v23  <|@  <|@
    end_IR
  end_block
  begin_block
    name "B15"
    from_bci -1
    to_bci -1
    predecessors "B14" 
    successors "B16" "B17" 
    xhandlers
    flags 
    loop_index 0
    loop_depth 1
    probability 4647341739031775896
    begin_IR
      HIR
f <@#|@fixed with next>@ <|@
tid v21 <|@
d <@d|@=== Debug Properties ===
nodeSourcePosition: at sun.nio.cs.UTF_8$Decoder.decode(UTF_8.java:434) [bci: 27]
stamp: void
=== Inputs ===
=== Succesors ===
next: i238 
=== Usages ===
v136 v145 
=== Predecessor ===
v27 >@ <|@
instruction <@Begin|@org.graalvm.compiler.nodes.BeginNode>@ #next: i238  <|@  <|@
f <@~|@floating>@ <|@
tid v136 <|@
d <@d|@=== Debug Properties ===
stamp: void
=== Inputs ===
kf: v204 v21 
=== Succesors ===
=== Usages ===
i238 
=== Predecessor ===
- >@ <|@
instruction <@c|@com.oracle.graal.enterprise.k.c>@ kf: v204 v21  <|@  <|@
f <@~|@floating>@ <|@
tid v242 <|@
d <@d|@=== Debug Properties ===
displacement: 16
scale: Times1
stamp: void*
=== Inputs ===
base: a2 
index: i17 
=== Succesors ===
=== Usages ===
i238 
=== Predecessor ===
- >@ <|@
instruction <@AMD64Address|@org.graalvm.compiler.core.amd64.AMD64AddressNode>@ base: a2 index: i17  <|@  <|@
f <@#|@fixed with next>@ <|@
tid i238 <|@
d <@d|@=== Debug Properties ===
barrierType: NONE
forceFixed: false
location: Array: byte
nodeSourcePosition: at sun.nio.cs.UTF_8$Decoder.decode(UTF_8.java:435) [bci: 45]
nullCheck: false
stamp: i8
=== Inputs ===
stateBefore: - 
guard: v136 
address: v242 
=== Succesors ===
next: v174 
=== Usages ===
i109 i84 
=== Predecessor ===
v21 >@ <|@
instruction <@Read|@org.graalvm.compiler.nodes.memory.ReadNode>@ stateBefore: - guard: v136 address: v242 #next: v174  <|@  <|@
f <@~|@floating>@ <|@
tid i84 <|@
d <@d|@=== Debug Properties ===
getOp: org.graalvm.compiler.nodes.calc.SignExtendNode$$Lambda$10/1121602809@34736fd3
getReverseOp: org.graalvm.compiler.nodes.calc.SignExtendNode$$Lambda$11/1363241743@10f97424
inputBits: 8
nodeSourcePosition: at sun.nio.cs.UTF_8$Decoder.decode(UTF_8.java:434) [bci: 29]
resultBits: 32
stamp: i32 [-128 - 127]
=== Inputs ===
value: i238 
=== Succesors ===
=== Usages ===
v29 
=== Predecessor ===
- >@ <|@
instruction <@SignExtend|@org.graalvm.compiler.nodes.calc.SignExtendNode>@ value: i238  <|@  <|@
f <@~|@floating>@ <|@
tid v29 <|@
d <@d|@=== Debug Properties ===
condition: LT
nodeSourcePosition: at sun.nio.cs.UTF_8$Decoder.decode(UTF_8.java:434) [bci: 30]
op: org.graalvm.compiler.nodes.calc.IntegerLessThanNode$LessThanOp@cca0f98
stamp: void
unorderedIsTrue: false
=== Inputs ===
x: i84 
y: i8 
=== Succesors ===
=== Usages ===
v174 
=== Predecessor ===
- >@ <|@
instruction <@<|@org.graalvm.compiler.nodes.calc.IntegerLessThanNode>@ x: i84 y: i8  <|@  <|@
f <@*|@fixed>@ <|@
tid v174 <|@
d <@d|@=== Debug Properties ===
nodeSourcePosition: at sun.nio.cs.UTF_8$Decoder.decode(UTF_8.java:434) [bci: 30]
stamp: void
trueSuccessorProbability: 0.0
=== Inputs ===
condition: v29 
=== Succesors ===
trueSuccessor: v173 
falseSuccessor: v170 
=== Usages ===
=== Predecessor ===
i238 >@ <|@
instruction <@If|@org.graalvm.compiler.nodes.IfNode>@ condition: v29 #trueSuccessor: v173 #falseSuccessor: v170  <|@  <|@
    end_IR
  end_block
  begin_block
    name "B16"
    from_bci -1
    to_bci -1
    predecessors "B15" 
    successors "B20" 
    xhandlers
    flags 
    probability 2355382605114769408
    begin_IR
      HIR
f <@#|@fixed with next>@ <|@
tid v173 <|@
d <@d|@=== Debug Properties ===
nodeSourcePosition: at sun.nio.cs.UTF_8$Decoder.decode(UTF_8.java:434) [bci: 30]
stamp: void
=== Inputs ===
stateAfter: - 
loopBegin: v16 
=== Succesors ===
next: v202 
=== Usages ===
=== Predecessor ===
v174 >@ <|@
instruction <@LoopExit|@org.graalvm.compiler.nodes.LoopExitNode>@ stateAfter: - loopBegin: v16 #next: v202  <|@  <|@
f <@~|@floating>@ <|@
tid i203 <|@
d <@d|@=== Debug Properties ===
isDefaultStable: false
rawvalue: -21779
stableDimension: 0
stamp: i32 [-21779] ⇊00000000ffffaaed ⇈00000000ffffaaed
stampKind: i32
value: int[-21779|0xffffffffffffaaed]
=== Inputs ===
=== Succesors ===
=== Usages ===
i199 
=== Predecessor ===
- >@ <|@
instruction <@Constant|@org.graalvm.compiler.nodes.ConstantNode>@  <|@  <|@
f <@*|@fixed>@ <|@
tid v202 <|@
d <@d|@=== Debug Properties ===
stamp: void
=== Inputs ===
=== Succesors ===
=== Usages ===
v196 
=== Predecessor ===
v173 >@ <|@
instruction <@EndNode|@org.graalvm.compiler.nodes.EndNode>@  <|@  <|@
    end_IR
  end_block
  begin_block
    name "B17"
    from_bci -1
    to_bci -1
    predecessors "B15" 
    successors "B14" 
    xhandlers
    flags "lle" 
    loop_index 0
    loop_depth 1
    probability 4647341739031775896
    begin_IR
      HIR
f <@#|@fixed with next>@ <|@
tid v170 <|@
d <@d|@=== Debug Properties ===
nodeSourcePosition: at sun.nio.cs.UTF_8$Decoder.decode(UTF_8.java:434) [bci: 30]
stamp: void
=== Inputs ===
=== Succesors ===
next: v105 
=== Usages ===
=== Predecessor ===
v174 >@ <|@
instruction <@Begin|@org.graalvm.compiler.nodes.BeginNode>@ #next: v105  <|@  <|@
f <@~|@floating>@ <|@
tid v145 <|@
d <@d|@=== Debug Properties ===
stamp: void
=== Inputs ===
kf: v220 v21 
=== Succesors ===
=== Usages ===
v105 
=== Predecessor ===
- >@ <|@
instruction <@c|@com.oracle.graal.enterprise.k.c>@ kf: v220 v21  <|@  <|@
f <@~|@floating>@ <|@
tid v243 <|@
d <@d|@=== Debug Properties ===
displacement: 16
scale: Times2
stamp: void*
=== Inputs ===
base: a5 
index: i18 
=== Succesors ===
=== Usages ===
v105 
=== Predecessor ===
- >@ <|@
instruction <@AMD64Address|@org.graalvm.compiler.core.amd64.AMD64AddressNode>@ base: a5 index: i18  <|@  <|@
f <@~|@floating>@ <|@
tid i109 <|@
d <@d|@=== Debug Properties ===
getOp: org.graalvm.compiler.nodes.calc.SignExtendNode$$Lambda$10/1121602809@34736fd3
getReverseOp: org.graalvm.compiler.nodes.calc.SignExtendNode$$Lambda$11/1363241743@10f97424
inputBits: 8
nodeSourcePosition: at sun.nio.cs.UTF_8$Decoder.decode(UTF_8.java:435) [bci: 46]
resultBits: 16
stamp: i16 [-128 - 127]
=== Inputs ===
value: i238 
=== Succesors ===
=== Usages ===
v105 
=== Predecessor ===
- >@ <|@
instruction <@SignExtend|@org.graalvm.compiler.nodes.calc.SignExtendNode>@ value: i238  <|@  <|@
f <@#|@fixed with next>@ <|@
tid v105 <|@
d <@d|@=== Debug Properties ===
barrierType: NONE
location: Array: char
nodeSourcePosition: at sun.nio.cs.UTF_8$Decoder.decode(UTF_8.java:435) [bci: 47]
nullCheck: false
stamp: void
=== Inputs ===
stateBefore: - 
guard: v145 
address: v243 
value: i109 
stateAfter: - 
lastLocationAccess: - 
=== Succesors ===
next: v39 
=== Usages ===
=== Predecessor ===
v170 >@ <|@
instruction <@Write|@org.graalvm.compiler.nodes.memory.WriteNode>@ stateBefore: - guard: v145 address: v243 value: i109 stateAfter: - lastLocationAccess: - #next: v39  <|@  <|@
f <@~|@floating>@ <|@
tid i32 <|@
d <@d|@=== Debug Properties ===
getOp: org.graalvm.compiler.nodes.calc.AddNode$$Lambda$14/562279114@1363f342
nodeSourcePosition: at sun.nio.cs.UTF_8$Decoder.decode(UTF_8.java:435) [bci: 37]
stamp: i32
=== Inputs ===
x: i18 
y: i31 
=== Succesors ===
=== Usages ===
i18 
=== Predecessor ===
- >@ <|@
instruction <@+|@org.graalvm.compiler.nodes.calc.AddNode>@ x: i18 y: i31  <|@  <|@
f <@~|@floating>@ <|@
tid i33 <|@
d <@d|@=== Debug Properties ===
getOp: org.graalvm.compiler.nodes.calc.AddNode$$Lambda$14/562279114@1363f342
nodeSourcePosition: at sun.nio.cs.UTF_8$Decoder.decode(UTF_8.java:435) [bci: 42]
stamp: i32
=== Inputs ===
x: i17 
y: i31 
=== Succesors ===
=== Usages ===
i17 
=== Predecessor ===
- >@ <|@
instruction <@+|@org.graalvm.compiler.nodes.calc.AddNode>@ x: i17 y: i31  <|@  <|@
f <@*|@fixed>@ <|@
tid v39 <|@
d <@d|@=== Debug Properties ===
canSafepoint: false
endIndex: 0
nodeSourcePosition: at sun.nio.cs.UTF_8$Decoder.decode(UTF_8.java:434) [bci: 20]
stamp: void
=== Inputs ===
loopBegin: v16 
=== Succesors ===
=== Usages ===
=== Predecessor ===
v105 >@ <|@
instruction <@LoopEnd|@org.graalvm.compiler.nodes.LoopEndNode>@ loopBegin: v16  <|@  <|@
    end_IR
  end_block
  begin_block
    name "B18"
    from_bci -1
    to_bci -1
    predecessors "B14" 
    successors "B19" "B21" 
    xhandlers
    flags 
    probability 4607182418800017408
    begin_IR
      HIR
f <@#|@fixed with next>@ <|@
tid v23 <|@
d <@d|@=== Debug Properties ===
nodeSourcePosition: at sun.nio.cs.UTF_8$Decoder.decode(UTF_8.java:437) [bci: 51]
stamp: void
=== Inputs ===
stateAfter: - 
loopBegin: v16 
=== Succesors ===
next: v178 
=== Usages ===
=== Predecessor ===
v27 >@ <|@
instruction <@LoopExit|@org.graalvm.compiler.nodes.LoopExitNode>@ stateAfter: - loopBegin: v16 #next: v178  <|@  <|@
f <@~|@floating>@ <|@
tid v46 <|@
d <@d|@=== Debug Properties ===
condition: LT
nodeSourcePosition: at sun.nio.cs.UTF_8$Decoder.decode(UTF_8.java:437) [bci: 54]
op: org.graalvm.compiler.nodes.calc.IntegerLessThanNode$LessThanOp@cca0f98
stamp: void
unorderedIsTrue: false
=== Inputs ===
x: i17 
y: i7 
=== Succesors ===
=== Usages ===
v178 
=== Predecessor ===
- >@ <|@
instruction <@<|@org.graalvm.compiler.nodes.calc.IntegerLessThanNode>@ x: i17 y: i7  <|@  <|@
f <@*|@fixed>@ <|@
tid v178 <|@
d <@d|@=== Debug Properties ===
nodeSourcePosition: at sun.nio.cs.UTF_8$Decoder.decode(UTF_8.java:437) [bci: 54]
stamp: void
trueSuccessorProbability: 0.0
=== Inputs ===
condition: v46 
=== Succesors ===
trueSuccessor: v177 
falseSuccessor: v175 
=== Usages ===
=== Predecessor ===
v23 >@ <|@
instruction <@If|@org.graalvm.compiler.nodes.IfNode>@ condition: v46 #trueSuccessor: v177 #falseSuccessor: v175  <|@  <|@
    end_IR
  end_block
  begin_block
    name "B19"
    from_bci -1
    to_bci -1
    predecessors "B18" 
    successors "B20" 
    xhandlers
    flags 
    probability 2355382605114769408
    begin_IR
      HIR
f <@#|@fixed with next>@ <|@
tid v177 <|@
d <@d|@=== Debug Properties ===
nodeSourcePosition: at sun.nio.cs.UTF_8$Decoder.decode(UTF_8.java:437) [bci: 54]
stamp: void
=== Inputs ===
=== Succesors ===
next: v197 
=== Usages ===
=== Predecessor ===
v178 >@ <|@
instruction <@Begin|@org.graalvm.compiler.nodes.BeginNode>@ #next: v197  <|@  <|@
f <@~|@floating>@ <|@
tid i198 <|@
d <@d|@=== Debug Properties ===
isDefaultStable: false
rawvalue: -27155
stableDimension: 0
stamp: i32 [-27155] ⇊00000000ffff95ed ⇈00000000ffff95ed
stampKind: i32
value: int[-27155|0xffffffffffff95ed]
=== Inputs ===
=== Succesors ===
=== Usages ===
i199 
=== Predecessor ===
- >@ <|@
instruction <@Constant|@org.graalvm.compiler.nodes.ConstantNode>@  <|@  <|@
f <@*|@fixed>@ <|@
tid v197 <|@
d <@d|@=== Debug Properties ===
stamp: void
=== Inputs ===
=== Succesors ===
=== Usages ===
v196 
=== Predecessor ===
v177 >@ <|@
instruction <@EndNode|@org.graalvm.compiler.nodes.EndNode>@  <|@  <|@
    end_IR
  end_block
  begin_block
    name "B20"
    from_bci -1
    to_bci -1
    predecessors "B19" "B16" 
    successors 
    xhandlers
    flags 
    probability 2359886204742139904
    begin_IR
      HIR
f <@~|@floating>@ <|@
tid i199 <|@
d <@d|@=== Debug Properties ===
stamp: i32 [-27155 - -21779] ⇊00000000ffff80ed ⇈00000000ffffbfed
valueDescription: i32
=== Inputs ===
merge: v196 
values: i198 i203 
=== Succesors ===
=== Usages ===
v201 
=== Predecessor ===
- >@ <|@
instruction <@ValuePhi|@org.graalvm.compiler.nodes.ValuePhiNode>@ merge: v196 values: i198 i203  <|@  <|@
f <@#|@fixed with next>@ <|@
tid v196 <|@
d <@d|@=== Debug Properties ===
stamp: void
=== Inputs ===
stateAfter: - 
ends: v197 v202 
=== Succesors ===
next: v201 
=== Usages ===
i199 
=== Predecessor ===
- >@ <|@
instruction <@Merge|@org.graalvm.compiler.nodes.MergeNode>@ stateAfter: - ends: v197 v202 #next: v201  <|@  <|@
f <@~|@floating>@ <|@
tid a13 <|@
d <@d|@=== Debug Properties ===
isDefaultStable: false
nodeSourcePosition: at sun.nio.cs.UTF_8$Decoder.decode(UTF_8.java:431) [bci: 17]
rawvalue: null
stableDimension: 0
stamp: a - NULL
stampKind: a -
value: Object[null]
=== Inputs ===
=== Succesors ===
=== Usages ===
?19 v201 
=== Predecessor ===
- >@ <|@
instruction <@Constant|@org.graalvm.compiler.nodes.ConstantNode>@  <|@  <|@
tid ?19 <|@
d <@d|@=== Debug Properties ===
bci: 20
code: ResolvedJavaMethodBytecode<UTF_8$Decoder.decode(byte[], int, int, char[])>
duringCall: false
localsSize: 14
locksSize: 0
rethrowException: false
sourceFile: UTF_8.java
sourceLine: 434
stackSize: 0
=== Inputs ===
outerFrameState: - 
values: a1 a2 i17 - a5 i7 i18 i111 a13 - - - - - 
=== Succesors ===
=== Usages ===
v201 
=== Predecessor ===
- >@ <|@
instruction <@FrameState|@org.graalvm.compiler.nodes.FrameState>@ outerFrameState: - values: a1 a2 i17 - a5 i7 i18 i111 a13 - - - - -  <|@  <|@
f <@*|@fixed>@ <|@
tid v201 <|@
d <@d|@=== Debug Properties ===
stamp: void
=== Inputs ===
stateBefore: ?19 
actionAndReason: i199 
speculation: a13 
=== Succesors ===
=== Usages ===
=== Predecessor ===
v196 >@ <|@
instruction <@DynamicDeoptimize|@org.graalvm.compiler.nodes.DynamicDeoptimizeNode>@ stateBefore: ?19 actionAndReason: i199 speculation: a13  <|@  <|@
    end_IR
  end_block
  begin_block
    name "B21"
    from_bci -1
    to_bci -1
    predecessors "B18" 
    successors 
    xhandlers
    flags 
    probability 4607182418800017408
    begin_IR
      HIR
f <@#|@fixed with next>@ <|@
tid v175 <|@
d <@d|@=== Debug Properties ===
nodeSourcePosition: at sun.nio.cs.UTF_8$Decoder.decode(UTF_8.java:437) [bci: 54]
stamp: void
=== Inputs ===
=== Succesors ===
next: v52 
=== Usages ===
=== Predecessor ===
v178 >@ <|@
instruction <@Begin|@org.graalvm.compiler.nodes.BeginNode>@ #next: v52  <|@  <|@
f <@*|@fixed>@ <|@
tid v52 <|@
d <@d|@=== Debug Properties ===
nodeSourcePosition: at sun.nio.cs.UTF_8$Decoder.decode(UTF_8.java:550) [bci: 778]
stamp: void
=== Inputs ===
result: i18 
memoryMap: - 
=== Succesors ===
=== Usages ===
=== Predecessor ===
v175 >@ <|@
instruction <@Return|@org.graalvm.compiler.nodes.ReturnNode>@ result: i18 memoryMap: -  <|@  <|@
    end_IR
  end_block
  begin_block
    name "B22"
    from_bci -1
    to_bci -1
    predecessors "B9" 
    successors "B25" 
    xhandlers
    flags 
    probability 2355382605114769408
    begin_IR
      HIR
f <@#|@fixed with next>@ <|@
tid v231 <|@
d <@d|@=== Debug Properties ===
nodeSourcePosition: at sun.nio.cs.UTF_8$Decoder.decode(UTF_8.java:435) [bci: 47]
stamp: void
=== Inputs ===
=== Succesors ===
next: v194 
=== Usages ===
=== Predecessor ===
v235 >@ <|@
instruction <@Begin|@org.graalvm.compiler.nodes.BeginNode>@ #next: v194  <|@  <|@
f <@*|@fixed>@ <|@
tid v194 <|@
d <@d|@=== Debug Properties ===
stamp: void
=== Inputs ===
=== Succesors ===
=== Usages ===
v182 
=== Predecessor ===
v231 >@ <|@
instruction <@EndNode|@org.graalvm.compiler.nodes.EndNode>@  <|@  <|@
    end_IR
  end_block
  begin_block
    name "B23"
    from_bci -1
    to_bci -1
    predecessors "B5" 
    successors "B25" 
    xhandlers
    flags 
    probability 2355382605114769408
    begin_IR
      HIR
f <@#|@fixed with next>@ <|@
tid v216 <|@
d <@d|@=== Debug Properties ===
nodeSourcePosition: at sun.nio.cs.UTF_8$Decoder.decode(UTF_8.java:435) [bci: 45]
stamp: void
=== Inputs ===
=== Succesors ===
next: v244 
=== Usages ===
=== Predecessor ===
v217 >@ <|@
instruction <@Begin|@org.graalvm.compiler.nodes.BeginNode>@ #next: v244  <|@  <|@
f <@*|@fixed>@ <|@
tid v244 <|@
d <@d|@=== Debug Properties ===
nodeSourcePosition: at sun.nio.cs.UTF_8$Decoder.decode(UTF_8.java:435) [bci: 45]
stamp: void
=== Inputs ===
=== Succesors ===
=== Usages ===
v182 
=== Predecessor ===
v216 >@ <|@
instruction <@EndNode|@org.graalvm.compiler.nodes.EndNode>@  <|@  <|@
    end_IR
  end_block
  begin_block
    name "B24"
    from_bci -1
    to_bci -1
    predecessors "B4" 
    successors "B25" 
    xhandlers
    flags 
    probability 2355382605114769408
    begin_IR
      HIR
f <@#|@fixed with next>@ <|@
tid v215 <|@
d <@d|@=== Debug Properties ===
nodeSourcePosition: at sun.nio.cs.UTF_8$Decoder.decode(UTF_8.java:435) [bci: 45]
stamp: void
=== Inputs ===
=== Succesors ===
next: v191 
=== Usages ===
=== Predecessor ===
v219 >@ <|@
instruction <@Begin|@org.graalvm.compiler.nodes.BeginNode>@ #next: v191  <|@  <|@
f <@*|@fixed>@ <|@
tid v191 <|@
d <@d|@=== Debug Properties ===
stamp: void
=== Inputs ===
=== Succesors ===
=== Usages ===
v182 
=== Predecessor ===
v215 >@ <|@
instruction <@EndNode|@org.graalvm.compiler.nodes.EndNode>@  <|@  <|@
    end_IR
  end_block
  begin_block
    name "B25"
    from_bci -1
    to_bci -1
    predecessors "B1" "B24" "B22" "B23" "B11" 
    successors 
    xhandlers
    flags 
    probability 2365515704276353024
    begin_IR
      HIR
f <@~|@floating>@ <|@
tid i186 <|@
d <@d|@=== Debug Properties ===
stamp: i32 [-25115 - -16651] ⇊00000000ffff80e5 ⇈00000000ffffbff5
valueDescription: i32
=== Inputs ===
merge: v182 
values: i184 i192 i195 i192 i195 
=== Succesors ===
=== Usages ===
v188 
=== Predecessor ===
- >@ <|@
instruction <@ValuePhi|@org.graalvm.compiler.nodes.ValuePhiNode>@ merge: v182 values: i184 i192 i195 i192 i195  <|@  <|@
f <@~|@floating>@ <|@
tid a187 <|@
d <@d|@=== Debug Properties ===
stamp: a# Lcom/oracle/graal/enterprise/k/d$a;
valueDescription: a -
=== Inputs ===
merge: v182 
values: a185 a193 a193 a193 a193 
=== Succesors ===
=== Usages ===
v188 
=== Predecessor ===
- >@ <|@
instruction <@ValuePhi|@org.graalvm.compiler.nodes.ValuePhiNode>@ merge: v182 values: a185 a193 a193 a193 a193  <|@  <|@
f <@#|@fixed with next>@ <|@
tid v182 <|@
d <@d|@=== Debug Properties ===
stamp: void
=== Inputs ===
stateAfter: - 
ends: v183 v191 v194 v244 v245 
=== Succesors ===
next: v188 
=== Usages ===
i186 a187 
=== Predecessor ===
- >@ <|@
instruction <@Merge|@org.graalvm.compiler.nodes.MergeNode>@ stateAfter: - ends: v183 v191 v194 v244 v245 #next: v188  <|@  <|@
f <@*|@fixed>@ <|@
tid v188 <|@
d <@d|@=== Debug Properties ===
stamp: void
=== Inputs ===
stateBefore: ?6 
actionAndReason: i186 
speculation: a187 
=== Succesors ===
=== Usages ===
=== Predecessor ===
v182 >@ <|@
instruction <@DynamicDeoptimize|@org.graalvm.compiler.nodes.DynamicDeoptimizeNode>@ stateBefore: ?6 actionAndReason: i186 speculation: a187  <|@  <|@
    end_IR
  end_block
end_cfg
begin_cfg
  name "After LIR generation"
  begin_block
    name "B0"
    from_bci -1
    to_bci -1
    predecessors 
    successors "B1" "B2" 
    xhandlers
    flags 
    probability 4607182418800017408
    begin_IR
      HIR
f <@#|@fixed with next>@ <|@
tid v0 <|@
d <@d|@=== Debug Properties ===
stamp: void
=== Inputs ===
stateAfter: - 
=== Succesors ===
next: v157 
=== Usages ===
=== Predecessor ===
- >@ <|@
instruction <@StartNode|@org.graalvm.compiler.nodes.StartNode>@ stateAfter: - #next: v157  <|@  <|@
f <@~|@floating>@ <|@
tid i3 <|@
result v2|DWORD <|@
d <@d|@=== Debug Properties ===
index: 2
stamp: i32
uncheckedStamp: [null]
=== Inputs ===
=== Succesors ===
=== Usages ===
?6 i7 i17 j124 v131 
=== Predecessor ===
- >@ <|@
instruction <@Parameter|@org.graalvm.compiler.nodes.ParameterNode>@  <|@  <|@
f <@~|@floating>@ <|@
tid i4 <|@
result v3|DWORD <|@
d <@d|@=== Debug Properties ===
index: 3
stamp: i32
uncheckedStamp: [null]
=== Inputs ===
=== Succesors ===
=== Usages ===
?6 i7 i111 v54 
=== Predecessor ===
- >@ <|@
instruction <@Parameter|@org.graalvm.compiler.nodes.ParameterNode>@  <|@  <|@
f <@~|@floating>@ <|@
tid i7 <|@
result v5|DWORD <|@
d <@d|@=== Debug Properties ===
getOp: org.graalvm.compiler.nodes.calc.AddNode$$Lambda$14/562279114@1363f342
nodeSourcePosition: at sun.nio.cs.UTF_8$Decoder.decode(UTF_8.java:428) [bci: 2]
stamp: i32
=== Inputs ===
x: i3 
y: i4 
=== Succesors ===
=== Usages ===
v46 ?19 
=== Predecessor ===
- >@ <|@
instruction <@+|@org.graalvm.compiler.nodes.calc.AddNode>@ x: i3 y: i4  <|@  <|@
f <@~|@floating>@ <|@
tid a1 <|@
result v0|QWORD[.] <|@
d <@d|@=== Debug Properties ===
index: 0
stamp: a!# Lsun/nio/cs/UTF_8$Decoder;
uncheckedStamp: [null]
=== Inputs ===
=== Succesors ===
=== Usages ===
?6 ?19 
=== Predecessor ===
- >@ <|@
instruction <@Parameter|@org.graalvm.compiler.nodes.ParameterNode>@  <|@  <|@
f <@~|@floating>@ <|@
tid a2 <|@
result v1|QWORD[.] <|@
d <@d|@=== Debug Properties ===
index: 1
stamp: a# [B
uncheckedStamp: [null]
=== Inputs ===
=== Succesors ===
=== Usages ===
?6 v70 ?19 v242 v241 
=== Predecessor ===
- >@ <|@
instruction <@Parameter|@org.graalvm.compiler.nodes.ParameterNode>@  <|@  <|@
f <@~|@floating>@ <|@
tid a5 <|@
result v4|QWORD[.] <|@
d <@d|@=== Debug Properties ===
index: 4
stamp: a# [C
uncheckedStamp: [null]
=== Inputs ===
=== Succesors ===
=== Usages ===
?6 v243 v240 ?19 
=== Predecessor ===
- >@ <|@
instruction <@Parameter|@org.graalvm.compiler.nodes.ParameterNode>@  <|@  <|@
tid ?6 <|@
d <@d|@=== Debug Properties ===
bci: 0
code: ResolvedJavaMethodBytecode<UTF_8$Decoder.decode(byte[], int, int, char[])>
duringCall: false
localsSize: 14
locksSize: 0
rethrowException: false
sourceFile: UTF_8.java
sourceLine: 428
stackSize: 0
=== Inputs ===
outerFrameState: - 
values: a1 a2 i3 i4 a5 - - - - - - - - - 
=== Succesors ===
=== Usages ===
v188 i236 
=== Predecessor ===
- >@ <|@
instruction <@FrameState|@org.graalvm.compiler.nodes.FrameState>@ outerFrameState: - values: a1 a2 i3 i4 a5 - - - - - - - - -  <|@  <|@
f <@~|@floating>@ <|@
tid v70 <|@
d <@d|@=== Debug Properties ===
nodeSourcePosition: at sun.nio.cs.UTF_8$Decoder.decode(UTF_8.java:434) [bci: 29]
stamp: void
=== Inputs ===
value: a2 
=== Succesors ===
=== Usages ===
v157 
=== Predecessor ===
- >@ <|@
instruction <@IsNull|@org.graalvm.compiler.nodes.calc.IsNullNode>@ value: a2  <|@  <|@
f <@*|@fixed>@ <|@
tid v157 <|@
d <@d|@=== Debug Properties ===
nodeSourcePosition: at sun.nio.cs.UTF_8$Decoder.decode(UTF_8.java:434) [bci: 29]
stamp: void
trueSuccessorProbability: 0.0
=== Inputs ===
condition: v70 
=== Succesors ===
trueSuccessor: v156 
falseSuccessor: v154 
=== Usages ===
=== Predecessor ===
v0 >@ <|@
instruction <@If|@org.graalvm.compiler.nodes.IfNode>@ condition: v70 #trueSuccessor: v156 #falseSuccessor: v154  <|@  <|@
    end_IR
    begin_IR
      LIR
      nr   -1  <|@ instruction [rsi|QWORD[.], rdx|QWORD[.], rcx|DWORD, r8|DWORD, r9|QWORD[.], rbp|QWORD] = LABEL numbPhis: 0 align: false label: ? <|@ <|@
      nr   -1  <|@ instruction stack:16|QWORD = MOVE rbp|QWORD moveKind: QWORD <|@ <|@
      nr   -1  <|@ instruction [] = HOTSPOTLOCKSTACK frameMapBuilder: org.graalvm.compiler.lir.amd64.AMD64FrameMapBuilder@51ff0cce slotKind: QWORD <|@ <|@
      nr   -1  <|@ instruction v0|QWORD[.] = MOVE rsi|QWORD[.] moveKind: QWORD <|@ <|@
      nr   -1  <|@ instruction v1|QWORD[.] = MOVE rdx|QWORD[.] moveKind: QWORD <|@ <|@
      nr   -1  <|@ instruction v2|DWORD = MOVE rcx|DWORD moveKind: DWORD <|@ <|@
      nr   -1  <|@ instruction v3|DWORD = MOVE r8|DWORD moveKind: DWORD <|@ <|@
      nr   -1  <|@ instruction v4|QWORD[.] = MOVE r9|QWORD[.] moveKind: QWORD <|@ <|@
      nr   -1  <|@ instruction v5|DWORD = ADD (x: v2|DWORD, y: v3|DWORD) size: DWORD <|@ <|@
      nr   -1  <|@ instruction TEST (x: v1|QWORD[.], y: v1|QWORD[.]) size: QWORD <|@ <|@
      nr   -1  <|@ instruction BRANCH trueDestinationProbability: 0.0 condition: = trueDestination: B0 -> B1 falseDestination: B0 -> B2 <|@ <|@
    end_IR
  end_block
  begin_block
    name "B1"
    from_bci -1
    to_bci -1
    predecessors "B0" 
    successors "B25" 
    xhandlers
    flags 
    probability 2355382605114769408
    begin_IR
      HIR
f <@#|@fixed with next>@ <|@
tid v156 <|@
d <@d|@=== Debug Properties ===
nodeSourcePosition: at sun.nio.cs.UTF_8$Decoder.decode(UTF_8.java:434) [bci: 29]
stamp: void
=== Inputs ===
=== Succesors ===
next: v183 
=== Usages ===
=== Predecessor ===
v157 >@ <|@
instruction <@Begin|@org.graalvm.compiler.nodes.BeginNode>@ #next: v183  <|@  <|@
f <@~|@floating>@ <|@
tid a185 <|@
result v6|QWORD[.] <|@
d <@d|@=== Debug Properties ===
isDefaultStable: false
rawvalue: d.a@206089336
stableDimension: 0
stamp: a!# Lcom/oracle/graal/enterprise/k/d$a;
stampKind: a -
value: Object[d.a@206089336]
=== Inputs ===
=== Succesors ===
=== Usages ===
a187 
=== Predecessor ===
- >@ <|@
instruction <@Constant|@org.graalvm.compiler.nodes.ConstantNode>@  <|@  <|@
f <@~|@floating>@ <|@
tid i184 <|@
result int[-18187|0xffffffffffffb8f5] <|@
d <@d|@=== Debug Properties ===
isDefaultStable: false
rawvalue: -18187
stableDimension: 0
stamp: i32 [-18187] ⇊00000000ffffb8f5 ⇈00000000ffffb8f5
stampKind: i32
value: int[-18187|0xffffffffffffb8f5]
=== Inputs ===
=== Succesors ===
=== Usages ===
i186 
=== Predecessor ===
- >@ <|@
instruction <@Constant|@org.graalvm.compiler.nodes.ConstantNode>@  <|@  <|@
f <@*|@fixed>@ <|@
tid v183 <|@
d <@d|@=== Debug Properties ===
stamp: void
=== Inputs ===
=== Succesors ===
=== Usages ===
v182 
=== Predecessor ===
v156 >@ <|@
instruction <@EndNode|@org.graalvm.compiler.nodes.EndNode>@  <|@  <|@
    end_IR
    begin_IR
      LIR
      nr   -1  <|@ instruction [] = LABEL numbPhis: 0 align: false label: ? <|@ <|@
      nr   -1  <|@ instruction v6|QWORD[.] = HOTSPOTLOADOBJECTCONSTANT input: Object[d.a@206089336] <|@ <|@
      nr   -1  <|@ instruction JUMP ~[int[-18187|0xffffffffffffb8f5], v6|QWORD[.]] destination: B1 -> B25 <|@ <|@
    end_IR
  end_block
  begin_block
    name "B2"
    from_bci -1
    to_bci -1
    predecessors "B0" 
    successors "B3" "B4" 
    xhandlers
    flags 
    probability 4607182418800017408
    begin_IR
      HIR
f <@#|@fixed with next>@ <|@
tid v154 <|@
d <@d|@=== Debug Properties ===
nodeSourcePosition: at sun.nio.cs.UTF_8$Decoder.decode(UTF_8.java:434) [bci: 29]
stamp: void
=== Inputs ===
=== Succesors ===
next: i236 
=== Usages ===
=== Predecessor ===
v157 >@ <|@
instruction <@Begin|@org.graalvm.compiler.nodes.BeginNode>@ #next: i236  <|@  <|@
f <@~|@floating>@ <|@
tid v240 <|@
result [v4|QWORD[.] + 12] <|@
d <@d|@=== Debug Properties ===
displacement: 12
scale: Times1
stamp: void*
=== Inputs ===
base: a5 
index: - 
=== Succesors ===
=== Usages ===
i236 
=== Predecessor ===
- >@ <|@
instruction <@AMD64Address|@org.graalvm.compiler.core.amd64.AMD64AddressNode>@ base: a5 index: -  <|@  <|@
f <@#|@fixed with next>@ <|@
tid i236 <|@
result v7|DWORD <|@
d <@d|@=== Debug Properties ===
barrierType: NONE
forceFixed: false
location: [].length:final
nodeSourcePosition: at sun.nio.cs.UTF_8$Decoder.decode(UTF_8.java:430) [bci: 11]
nullCheck: true
stamp: i32 [0 - 2147483647] ⇈000000007fffffff
=== Inputs ===
stateBefore: ?6 
guard: - 
address: v240 
=== Succesors ===
next: v211 
=== Usages ===
i111 v54 v150 j137 
=== Predecessor ===
v154 >@ <|@
instruction <@Read|@org.graalvm.compiler.nodes.memory.ReadNode>@ stateBefore: ?6 guard: - address: v240 #next: v211  <|@  <|@
f <@~|@floating>@ <|@
tid v54 <|@
d <@d|@=== Debug Properties ===
condition: LT
nodeSourcePosition: at java.lang.Math.min(Math.java:1336) [bci: 2]
at sun.nio.cs.UTF_8$Decoder.decode(UTF_8.java:430) [bci: 12]
op: org.graalvm.compiler.nodes.calc.IntegerLessThanNode$LessThanOp@cca0f98
stamp: void
unorderedIsTrue: false
=== Inputs ===
x: i236 
y: i4 
=== Succesors ===
=== Usages ===
i111 
=== Predecessor ===
- >@ <|@
instruction <@<|@org.graalvm.compiler.nodes.calc.IntegerLessThanNode>@ x: i236 y: i4  <|@  <|@
f <@~|@floating>@ <|@
tid i111 <|@
result v8|DWORD <|@
d <@d|@=== Debug Properties ===
stamp: i32
=== Inputs ===
condition: v54 
trueValue: i236 
falseValue: i4 
=== Succesors ===
=== Usages ===
j125 v20 ?19 v147 
=== Predecessor ===
- >@ <|@
instruction <@Conditional|@org.graalvm.compiler.nodes.calc.ConditionalNode>@ condition: v54 trueValue: i236 falseValue: i4  <|@  <|@
f <@~|@floating>@ <|@
tid j125 <|@
result v9|QWORD <|@
d <@d|@=== Debug Properties ===
getOp: org.graalvm.compiler.nodes.calc.SignExtendNode$$Lambda$10/1121602809@34736fd3
getReverseOp: org.graalvm.compiler.nodes.calc.SignExtendNode$$Lambda$11/1363241743@10f97424
inputBits: 32
resultBits: 64
stamp: i64 [-2147483648 - 2147483647]
=== Inputs ===
value: i111 
=== Succesors ===
=== Usages ===
j127 
=== Predecessor ===
- >@ <|@
instruction <@SignExtend|@org.graalvm.compiler.nodes.calc.SignExtendNode>@ value: i111  <|@  <|@
f <@~|@floating>@ <|@
tid j126 <|@
result long[-1|0xffffffffffffffff] <|@
d <@d|@=== Debug Properties ===
isDefaultStable: false
rawvalue: -1
stableDimension: 0
stamp: i64 [-1] ⇊ffffffffffffffff
stampKind: i64
value: long[-1|0xffffffffffffffff]
=== Inputs ===
=== Succesors ===
=== Usages ===
j127 
=== Predecessor ===
- >@ <|@
instruction <@Constant|@org.graalvm.compiler.nodes.ConstantNode>@  <|@  <|@
f <@~|@floating>@ <|@
tid j127 <|@
result v10|QWORD <|@
d <@d|@=== Debug Properties ===
getOp: org.graalvm.compiler.nodes.calc.AddNode$$Lambda$14/562279114@1363f342
stamp: i64 [-2147483649 - 2147483646]
=== Inputs ===
x: j125 
y: j126 
=== Succesors ===
=== Usages ===
j128 v140 
=== Predecessor ===
- >@ <|@
instruction <@+|@org.graalvm.compiler.nodes.calc.AddNode>@ x: j125 y: j126  <|@  <|@
f <@~|@floating>@ <|@
tid i31 <|@
result int[1|0x1] <|@
d <@d|@=== Debug Properties ===
isDefaultStable: false
nodeSourcePosition: at sun.nio.cs.UTF_8$Decoder.decode(UTF_8.java:435) [bci: 37]
rawvalue: 1
stableDimension: 0
stamp: i32 [1] ⇊0000000000000001 ⇈0000000000000001
stampKind: i32
value: int[1|0x1]
=== Inputs ===
=== Succesors ===
=== Usages ===
i32 i33 v147 
=== Predecessor ===
- >@ <|@
instruction <@Constant|@org.graalvm.compiler.nodes.ConstantNode>@  <|@  <|@
f <@~|@floating>@ <|@
tid v147 <|@
d <@d|@=== Debug Properties ===
condition: LT
op: org.graalvm.compiler.nodes.calc.IntegerLessThanNode$LessThanOp@cca0f98
stamp: void
unorderedIsTrue: false
=== Inputs ===
x: i111 
y: i31 
=== Succesors ===
=== Usages ===
v227 v211 
=== Predecessor ===
- >@ <|@
instruction <@<|@org.graalvm.compiler.nodes.calc.IntegerLessThanNode>@ x: i111 y: i31  <|@  <|@
f <@~|@floating>@ <|@
tid a193 <|@
result v11|QWORD[.] <|@
d <@d|@=== Debug Properties ===
isDefaultStable: false
rawvalue: d.a@1183312594
stableDimension: 0
stamp: a!# Lcom/oracle/graal/enterprise/k/d$a;
stampKind: a -
value: Object[d.a@1183312594]
=== Inputs ===
=== Succesors ===
=== Usages ===
a187 a187 a187 a187 
=== Predecessor ===
- >@ <|@
instruction <@Constant|@org.graalvm.compiler.nodes.ConstantNode>@  <|@  <|@
f <@*|@fixed>@ <|@
tid v211 <|@
d <@d|@=== Debug Properties ===
nodeSourcePosition: at sun.nio.cs.UTF_8$Decoder.decode(UTF_8.java:435) [bci: 45]
stamp: void
trueSuccessorProbability: 0.5
=== Inputs ===
condition: v147 
=== Succesors ===
trueSuccessor: v207 
falseSuccessor: v210 
=== Usages ===
=== Predecessor ===
i236 >@ <|@
instruction <@If|@org.graalvm.compiler.nodes.IfNode>@ condition: v147 #trueSuccessor: v207 #falseSuccessor: v210  <|@  <|@
    end_IR
    begin_IR
      LIR
      nr   -1  <|@ instruction [] = LABEL numbPhis: 0 align: false label: ? <|@ <|@
      nr   -1  <|@ st <@st|@sun.nio.cs.UTF_8$Decoder.decode(UTF_8.java:428) [bci: 0]
locals: v0|QWORD[.] v1|QWORD[.] v2|DWORD v3|DWORD v4|QWORD[.] - - - - - - - - - 
>@ <|@ instruction v7|DWORD = MOV [v4|QWORD[.] + 12] size: DWORD state [bci:0] <|@ <|@
      nr   -1  <|@ instruction CMP (x: v3|DWORD, y: v7|DWORD) size: DWORD <|@ <|@
      nr   -1  <|@ instruction v8|DWORD = CMOVE (falseValue: v3|DWORD, ~trueValue: v7|DWORD) condition: > <|@ <|@
      nr   -1  <|@ instruction v9|QWORD = MOVSXD v8|DWORD size: QWORD <|@ <|@
      nr   -1  <|@ instruction v10|QWORD = DEC v9|QWORD size: QWORD <|@ <|@
      nr   -1  <|@ instruction v11|QWORD[.] = HOTSPOTLOADOBJECTCONSTANT input: Object[d.a@1183312594] <|@ <|@
      nr   -1  <|@ instruction CMP v8|DWORD y: 1 size: DWORD <|@ <|@
      nr   -1  <|@ instruction BRANCH trueDestinationProbability: 0.5 condition: < trueDestination: B2 -> B3 falseDestination: B2 -> B4 <|@ <|@
    end_IR
  end_block
  begin_block
    name "B3"
    from_bci -1
    to_bci -1
    predecessors "B2" 
    successors "B7" 
    xhandlers
    flags 
    probability 4602678819172646912
    begin_IR
      HIR
f <@#|@fixed with next>@ <|@
tid v207 <|@
d <@d|@=== Debug Properties ===
nodeSourcePosition: at sun.nio.cs.UTF_8$Decoder.decode(UTF_8.java:435) [bci: 45]
stamp: void
=== Inputs ===
=== Succesors ===
next: v205 
=== Usages ===
=== Predecessor ===
v211 >@ <|@
instruction <@Begin|@org.graalvm.compiler.nodes.BeginNode>@ #next: v205  <|@  <|@
f <@*|@fixed>@ <|@
tid v205 <|@
d <@d|@=== Debug Properties ===
nodeSourcePosition: at sun.nio.cs.UTF_8$Decoder.decode(UTF_8.java:435) [bci: 45]
stamp: void
=== Inputs ===
=== Succesors ===
=== Usages ===
v204 
=== Predecessor ===
v207 >@ <|@
instruction <@EndNode|@org.graalvm.compiler.nodes.EndNode>@  <|@  <|@
    end_IR
    begin_IR
      LIR
      nr   -1  <|@ instruction [] = LABEL numbPhis: 0 align: false label: ? <|@ <|@
      nr   -1  <|@ instruction JUMP ~[] destination: B3 -> B7 <|@ <|@
    end_IR
  end_block
  begin_block
    name "B4"
    from_bci -1
    to_bci -1
    predecessors "B2" 
    successors "B5" "B24" 
    xhandlers
    flags 
    probability 4602678819172646912
    begin_IR
      HIR
f <@#|@fixed with next>@ <|@
tid v210 <|@
d <@d|@=== Debug Properties ===
nodeSourcePosition: at sun.nio.cs.UTF_8$Decoder.decode(UTF_8.java:435) [bci: 45]
stamp: void
=== Inputs ===
=== Succesors ===
next: i237 
=== Usages ===
=== Predecessor ===
v211 >@ <|@
instruction <@Begin|@org.graalvm.compiler.nodes.BeginNode>@ #next: i237  <|@  <|@
f <@~|@floating>@ <|@
tid v241 <|@
result [v1|QWORD[.] + 12] <|@
d <@d|@=== Debug Properties ===
displacement: 12
scale: Times1
stamp: void*
=== Inputs ===
base: a2 
index: - 
=== Succesors ===
=== Usages ===
i237 
=== Predecessor ===
- >@ <|@
instruction <@AMD64Address|@org.graalvm.compiler.core.amd64.AMD64AddressNode>@ base: a2 index: -  <|@  <|@
f <@#|@fixed with next>@ <|@
tid i237 <|@
result v12|DWORD <|@
d <@d|@=== Debug Properties ===
barrierType: NONE
forceFixed: false
location: [].length:final
nodeSourcePosition: at sun.nio.cs.UTF_8$Decoder.decode(UTF_8.java:434) [bci: 29]
nullCheck: false
stamp: i32 [0 - 2147483647] ⇈000000007fffffff
=== Inputs ===
stateBefore: - 
guard: - 
address: v241 
=== Succesors ===
next: v219 
=== Usages ===
v131 j122 
=== Predecessor ===
v210 >@ <|@
instruction <@Read|@org.graalvm.compiler.nodes.memory.ReadNode>@ stateBefore: - guard: - address: v241 #next: v219  <|@  <|@
f <@~|@floating>@ <|@
tid j124 <|@
result v13|QWORD <|@
d <@d|@=== Debug Properties ===
getOp: org.graalvm.compiler.nodes.calc.SignExtendNode$$Lambda$10/1121602809@34736fd3
getReverseOp: org.graalvm.compiler.nodes.calc.SignExtendNode$$Lambda$11/1363241743@10f97424
inputBits: 32
resultBits: 64
stamp: i64 [-2147483648 - 2147483647]
=== Inputs ===
value: i3 
=== Succesors ===
=== Usages ===
j128 
=== Predecessor ===
- >@ <|@
instruction <@SignExtend|@org.graalvm.compiler.nodes.calc.SignExtendNode>@ value: i3  <|@  <|@
f <@~|@floating>@ <|@
tid j128 <|@
result v14|QWORD <|@
d <@d|@=== Debug Properties ===
getOp: org.graalvm.compiler.nodes.calc.AddNode$$Lambda$14/562279114@1363f342
stamp: i64 [-4294967297 - 4294967293]
=== Inputs ===
x: j124 
y: j127 
=== Succesors ===
=== Usages ===
v130 
=== Predecessor ===
- >@ <|@
instruction <@+|@org.graalvm.compiler.nodes.calc.AddNode>@ x: j124 y: j127  <|@  <|@
f <@~|@floating>@ <|@
tid j122 <|@
result v15|QWORD <|@
d <@d|@=== Debug Properties ===
getOp: org.graalvm.compiler.nodes.calc.ZeroExtendNode$$Lambda$16/1174728845@6b2a0100
getReverseOp: org.graalvm.compiler.nodes.calc.ZeroExtendNode$$Lambda$17/2049777509@675f16c4
inputAlwaysPositive: true
inputBits: 32
resultBits: 64
stamp: i64 [0 - 2147483647] ⇈000000007fffffff
=== Inputs ===
value: i237 
=== Succesors ===
=== Usages ===
v130 
=== Predecessor ===
- >@ <|@
instruction <@ZeroExtend|@org.graalvm.compiler.nodes.calc.ZeroExtendNode>@ value: i237  <|@  <|@
f <@~|@floating>@ <|@
tid v130 <|@
d <@d|@=== Debug Properties ===
condition: BT
op: org.graalvm.compiler.nodes.calc.IntegerBelowNode$BelowOp@66bde537
stamp: void
unorderedIsTrue: false
=== Inputs ===
x: j128 
y: j122 
=== Succesors ===
=== Usages ===
v219 
=== Predecessor ===
- >@ <|@
instruction <@|<||@org.graalvm.compiler.nodes.calc.IntegerBelowNode>@ x: j128 y: j122  <|@  <|@
f <@~|@floating>@ <|@
tid i192 <|@
result int[-22555|0xffffffffffffa7e5] <|@
d <@d|@=== Debug Properties ===
isDefaultStable: false
rawvalue: -22555
stableDimension: 0
stamp: i32 [-22555] ⇊00000000ffffa7e5 ⇈00000000ffffa7e5
stampKind: i32
value: int[-22555|0xffffffffffffa7e5]
=== Inputs ===
=== Succesors ===
=== Usages ===
i186 i186 
=== Predecessor ===
- >@ <|@
instruction <@Constant|@org.graalvm.compiler.nodes.ConstantNode>@  <|@  <|@
f <@*|@fixed>@ <|@
tid v219 <|@
d <@d|@=== Debug Properties ===
nodeSourcePosition: at sun.nio.cs.UTF_8$Decoder.decode(UTF_8.java:435) [bci: 45]
stamp: void
trueSuccessorProbability: 1.0
=== Inputs ===
condition: v130 
=== Succesors ===
trueSuccessor: v218 
falseSuccessor: v215 
=== Usages ===
=== Predecessor ===
i237 >@ <|@
instruction <@If|@org.graalvm.compiler.nodes.IfNode>@ condition: v130 #trueSuccessor: v218 #falseSuccessor: v215  <|@  <|@
    end_IR
    begin_IR
      LIR
      nr   -1  <|@ instruction [] = LABEL numbPhis: 0 align: false label: ? <|@ <|@
      nr   -1  <|@ instruction v12|DWORD = MOV [v1|QWORD[.] + 12] size: DWORD <|@ <|@
      nr   -1  <|@ instruction v13|QWORD = MOVSXD v2|DWORD size: QWORD <|@ <|@
      nr   -1  <|@ instruction v14|QWORD = ADD (x: v13|QWORD, y: v10|QWORD) size: QWORD <|@ <|@
      nr   -1  <|@ instruction v15|QWORD = MOV v12|DWORD size: DWORD <|@ <|@
      nr   -1  <|@ instruction CMP (x: v15|QWORD, y: v14|QWORD) size: QWORD <|@ <|@
      nr   -1  <|@ instruction BRANCH trueDestinationProbability: 1.0 condition: |>| trueDestination: B4 -> B5 falseDestination: B4 -> B24 <|@ <|@
    end_IR
  end_block
  begin_block
    name "B5"
    from_bci -1
    to_bci -1
    predecessors "B4" 
    successors "B6" "B23" 
    xhandlers
    flags 
    probability 4602678819172646912
    begin_IR
      HIR
f <@#|@fixed with next>@ <|@
tid v218 <|@
d <@d|@=== Debug Properties ===
nodeSourcePosition: at sun.nio.cs.UTF_8$Decoder.decode(UTF_8.java:435) [bci: 45]
stamp: void
=== Inputs ===
=== Succesors ===
next: v217 
=== Usages ===
=== Predecessor ===
v219 >@ <|@
instruction <@Begin|@org.graalvm.compiler.nodes.BeginNode>@ #next: v217  <|@  <|@
f <@~|@floating>@ <|@
tid v131 <|@
d <@d|@=== Debug Properties ===
condition: BT
op: org.graalvm.compiler.nodes.calc.IntegerBelowNode$BelowOp@66bde537
stamp: void
unorderedIsTrue: false
=== Inputs ===
x: i3 
y: i237 
=== Succesors ===
=== Usages ===
v217 
=== Predecessor ===
- >@ <|@
instruction <@|<||@org.graalvm.compiler.nodes.calc.IntegerBelowNode>@ x: i3 y: i237  <|@  <|@
f <@*|@fixed>@ <|@
tid v217 <|@
d <@d|@=== Debug Properties ===
nodeSourcePosition: at sun.nio.cs.UTF_8$Decoder.decode(UTF_8.java:435) [bci: 45]
stamp: void
trueSuccessorProbability: 1.0
=== Inputs ===
condition: v131 
=== Succesors ===
trueSuccessor: v208 
falseSuccessor: v216 
=== Usages ===
=== Predecessor ===
v218 >@ <|@
instruction <@If|@org.graalvm.compiler.nodes.IfNode>@ condition: v131 #trueSuccessor: v208 #falseSuccessor: v216  <|@  <|@
    end_IR
    begin_IR
      LIR
      nr   -1  <|@ instruction [] = LABEL numbPhis: 0 align: false label: ? <|@ <|@
      nr   -1  <|@ instruction CMP (x: v12|DWORD, y: v2|DWORD) size: DWORD <|@ <|@
      nr   -1  <|@ instruction BRANCH trueDestinationProbability: 1.0 condition: |>| trueDestination: B5 -> B6 falseDestination: B5 -> B23 <|@ <|@
    end_IR
  end_block
  begin_block
    name "B6"
    from_bci -1
    to_bci -1
    predecessors "B5" 
    successors "B7" 
    xhandlers
    flags 
    probability 4602678819172646912
    begin_IR
      HIR
f <@#|@fixed with next>@ <|@
tid v208 <|@
d <@d|@=== Debug Properties ===
nodeSourcePosition: at sun.nio.cs.UTF_8$Decoder.decode(UTF_8.java:435) [bci: 45]
stamp: void
=== Inputs ===
=== Succesors ===
next: v206 
=== Usages ===
=== Predecessor ===
v217 >@ <|@
instruction <@Begin|@org.graalvm.compiler.nodes.BeginNode>@ #next: v206  <|@  <|@
f <@*|@fixed>@ <|@
tid v206 <|@
d <@d|@=== Debug Properties ===
nodeSourcePosition: at sun.nio.cs.UTF_8$Decoder.decode(UTF_8.java:435) [bci: 45]
stamp: void
=== Inputs ===
=== Succesors ===
=== Usages ===
v204 
=== Predecessor ===
v208 >@ <|@
instruction <@EndNode|@org.graalvm.compiler.nodes.EndNode>@  <|@  <|@
    end_IR
    begin_IR
      LIR
      nr   -1  <|@ instruction [] = LABEL numbPhis: 0 align: false label: ? <|@ <|@
      nr   -1  <|@ instruction JUMP ~[] destination: B6 -> B7 <|@ <|@
    end_IR
  end_block
  begin_block
    name "B7"
    from_bci -1
    to_bci -1
    predecessors "B3" "B6" 
    successors "B8" "B9" 
    xhandlers
    flags 
    probability 4607182418800017408
    begin_IR
      HIR
f <@#|@fixed with next>@ <|@
tid v204 <|@
d <@d|@=== Debug Properties ===
nodeSourcePosition: at sun.nio.cs.UTF_8$Decoder.decode(UTF_8.java:435) [bci: 45]
stamp: void
=== Inputs ===
stateAfter: - 
ends: v205 v206 
=== Succesors ===
next: v227 
=== Usages ===
v136 
=== Predecessor ===
- >@ <|@
instruction <@Merge|@org.graalvm.compiler.nodes.MergeNode>@ stateAfter: - ends: v205 v206 #next: v227  <|@  <|@
f <@~|@floating>@ <|@
tid i8 <|@
result int[0|0x0] <|@
d <@d|@=== Debug Properties ===
isDefaultStable: false
nodeSourcePosition: at sun.nio.cs.UTF_8$Decoder.decode(UTF_8.java:429) [bci: 5]
rawvalue: 0
stableDimension: 0
stamp: i32 [0] ⇈0000000000000000
stampKind: i32
value: int[0|0x0]
=== Inputs ===
=== Succesors ===
=== Usages ===
v29 i18 v150 
=== Predecessor ===
- >@ <|@
instruction <@Constant|@org.graalvm.compiler.nodes.ConstantNode>@  <|@  <|@
f <@*|@fixed>@ <|@
tid v227 <|@
d <@d|@=== Debug Properties ===
nodeSourcePosition: at sun.nio.cs.UTF_8$Decoder.decode(UTF_8.java:435) [bci: 47]
stamp: void
trueSuccessorProbability: 0.5
=== Inputs ===
condition: v147 
=== Succesors ===
trueSuccessor: v223 
falseSuccessor: v226 
=== Usages ===
=== Predecessor ===
v204 >@ <|@
instruction <@If|@org.graalvm.compiler.nodes.IfNode>@ condition: v147 #trueSuccessor: v223 #falseSuccessor: v226  <|@  <|@
    end_IR
    begin_IR
      LIR
      nr   -1  <|@ instruction [] = LABEL numbPhis: 0 align: false label: ? <|@ <|@
      nr   -1  <|@ instruction CMP v8|DWORD y: 1 size: DWORD <|@ <|@
      nr   -1  <|@ instruction BRANCH trueDestinationProbability: 0.5 condition: < trueDestination: B7 -> B8 falseDestination: B7 -> B9 <|@ <|@
    end_IR
  end_block
  begin_block
    name "B8"
    from_bci -1
    to_bci -1
    predecessors "B7" 
    successors "B13" 
    xhandlers
    flags 
    probability 4602678819172646912
    begin_IR
      HIR
f <@#|@fixed with next>@ <|@
tid v223 <|@
d <@d|@=== Debug Properties ===
nodeSourcePosition: at sun.nio.cs.UTF_8$Decoder.decode(UTF_8.java:435) [bci: 47]
stamp: void
=== Inputs ===
=== Succesors ===
next: v221 
=== Usages ===
=== Predecessor ===
v227 >@ <|@
instruction <@Begin|@org.graalvm.compiler.nodes.BeginNode>@ #next: v221  <|@  <|@
f <@*|@fixed>@ <|@
tid v221 <|@
d <@d|@=== Debug Properties ===
nodeSourcePosition: at sun.nio.cs.UTF_8$Decoder.decode(UTF_8.java:435) [bci: 47]
stamp: void
=== Inputs ===
=== Succesors ===
=== Usages ===
v220 
=== Predecessor ===
v223 >@ <|@
instruction <@EndNode|@org.graalvm.compiler.nodes.EndNode>@  <|@  <|@
    end_IR
    begin_IR
      LIR
      nr   -1  <|@ instruction [] = LABEL numbPhis: 0 align: false label: ? <|@ <|@
      nr   -1  <|@ instruction JUMP ~[] destination: B8 -> B13 <|@ <|@
    end_IR
  end_block
  begin_block
    name "B9"
    from_bci -1
    to_bci -1
    predecessors "B7" 
    successors "B10" "B22" 
    xhandlers
    flags 
    probability 4602678819172646912
    begin_IR
      HIR
f <@#|@fixed with next>@ <|@
tid v226 <|@
d <@d|@=== Debug Properties ===
nodeSourcePosition: at sun.nio.cs.UTF_8$Decoder.decode(UTF_8.java:435) [bci: 47]
stamp: void
=== Inputs ===
=== Succesors ===
next: v235 
=== Usages ===
=== Predecessor ===
v227 >@ <|@
instruction <@Begin|@org.graalvm.compiler.nodes.BeginNode>@ #next: v235  <|@  <|@
f <@~|@floating>@ <|@
tid j137 <|@
result v16|QWORD <|@
d <@d|@=== Debug Properties ===
getOp: org.graalvm.compiler.nodes.calc.ZeroExtendNode$$Lambda$16/1174728845@6b2a0100
getReverseOp: org.graalvm.compiler.nodes.calc.ZeroExtendNode$$Lambda$17/2049777509@675f16c4
inputAlwaysPositive: true
inputBits: 32
resultBits: 64
stamp: i64 [0 - 2147483647] ⇈000000007fffffff
=== Inputs ===
value: i236 
=== Succesors ===
=== Usages ===
v140 
=== Predecessor ===
- >@ <|@
instruction <@ZeroExtend|@org.graalvm.compiler.nodes.calc.ZeroExtendNode>@ value: i236  <|@  <|@
f <@~|@floating>@ <|@
tid v140 <|@
d <@d|@=== Debug Properties ===
condition: BT
op: org.graalvm.compiler.nodes.calc.IntegerBelowNode$BelowOp@66bde537
stamp: void
unorderedIsTrue: false
=== Inputs ===
x: j127 
y: j137 
=== Succesors ===
=== Usages ===
v235 
=== Predecessor ===
- >@ <|@
instruction <@|<||@org.graalvm.compiler.nodes.calc.IntegerBelowNode>@ x: j127 y: j137  <|@  <|@
f <@~|@floating>@ <|@
tid i195 <|@
result int[-25115|0xffffffffffff9de5] <|@
d <@d|@=== Debug Properties ===
isDefaultStable: false
rawvalue: -25115
stableDimension: 0
stamp: i32 [-25115] ⇊00000000ffff9de5 ⇈00000000ffff9de5
stampKind: i32
value: int[-25115|0xffffffffffff9de5]
=== Inputs ===
=== Succesors ===
=== Usages ===
i186 i186 
=== Predecessor ===
- >@ <|@
instruction <@Constant|@org.graalvm.compiler.nodes.ConstantNode>@  <|@  <|@
f <@*|@fixed>@ <|@
tid v235 <|@
d <@d|@=== Debug Properties ===
nodeSourcePosition: at sun.nio.cs.UTF_8$Decoder.decode(UTF_8.java:435) [bci: 47]
stamp: void
trueSuccessorProbability: 1.0
=== Inputs ===
condition: v140 
=== Succesors ===
trueSuccessor: v234 
falseSuccessor: v231 
=== Usages ===
=== Predecessor ===
v226 >@ <|@
instruction <@If|@org.graalvm.compiler.nodes.IfNode>@ condition: v140 #trueSuccessor: v234 #falseSuccessor: v231  <|@  <|@
    end_IR
    begin_IR
      LIR
      nr   -1  <|@ instruction [] = LABEL numbPhis: 0 align: false label: ? <|@ <|@
      nr   -1  <|@ instruction v16|QWORD = MOV v7|DWORD size: DWORD <|@ <|@
      nr   -1  <|@ instruction CMP (x: v16|QWORD, y: v10|QWORD) size: QWORD <|@ <|@
      nr   -1  <|@ instruction BRANCH trueDestinationProbability: 1.0 condition: |>| trueDestination: B9 -> B10 falseDestination: B9 -> B22 <|@ <|@
    end_IR
  end_block
  begin_block
    name "B10"
    from_bci -1
    to_bci -1
    predecessors "B9" 
    successors "B11" "B12" 
    xhandlers
    flags 
    probability 4602678819172646912
    begin_IR
      HIR
f <@#|@fixed with next>@ <|@
tid v234 <|@
d <@d|@=== Debug Properties ===
nodeSourcePosition: at sun.nio.cs.UTF_8$Decoder.decode(UTF_8.java:435) [bci: 47]
stamp: void
=== Inputs ===
=== Succesors ===
next: v233 
=== Usages ===
=== Predecessor ===
v235 >@ <|@
instruction <@Begin|@org.graalvm.compiler.nodes.BeginNode>@ #next: v233  <|@  <|@
f <@~|@floating>@ <|@
tid v150 <|@
d <@d|@=== Debug Properties ===
condition: EQ
stamp: void
unorderedIsTrue: false
=== Inputs ===
x: i236 
y: i8 
=== Succesors ===
=== Usages ===
v233 
=== Predecessor ===
- >@ <|@
instruction <@==|@org.graalvm.compiler.nodes.calc.IntegerEqualsNode>@ x: i236 y: i8  <|@  <|@
f <@*|@fixed>@ <|@
tid v233 <|@
d <@d|@=== Debug Properties ===
nodeSourcePosition: at sun.nio.cs.UTF_8$Decoder.decode(UTF_8.java:435) [bci: 47]
stamp: void
trueSuccessorProbability: 0.0
=== Inputs ===
condition: v150 
=== Succesors ===
trueSuccessor: v232 
falseSuccessor: v224 
=== Usages ===
=== Predecessor ===
v234 >@ <|@
instruction <@If|@org.graalvm.compiler.nodes.IfNode>@ condition: v150 #trueSuccessor: v232 #falseSuccessor: v224  <|@  <|@
    end_IR
    begin_IR
      LIR
      nr   -1  <|@ instruction [] = LABEL numbPhis: 0 align: false label: ? <|@ <|@
      nr   -1  <|@ instruction TEST (x: v7|DWORD, y: v7|DWORD) size: DWORD <|@ <|@
      nr   -1  <|@ instruction BRANCH trueDestinationProbability: 0.0 condition: = trueDestination: B10 -> B11 falseDestination: B10 -> B12 <|@ <|@
    end_IR
  end_block
  begin_block
    name "B11"
    from_bci -1
    to_bci -1
    predecessors "B10" 
    successors "B25" 
    xhandlers
    flags 
    probability 2355382605114769408
    begin_IR
      HIR
f <@#|@fixed with next>@ <|@
tid v232 <|@
d <@d|@=== Debug Properties ===
nodeSourcePosition: at sun.nio.cs.UTF_8$Decoder.decode(UTF_8.java:435) [bci: 47]
stamp: void
=== Inputs ===
=== Succesors ===
next: v245 
=== Usages ===
=== Predecessor ===
v233 >@ <|@
instruction <@Begin|@org.graalvm.compiler.nodes.BeginNode>@ #next: v245  <|@  <|@
f <@*|@fixed>@ <|@
tid v245 <|@
d <@d|@=== Debug Properties ===
nodeSourcePosition: at sun.nio.cs.UTF_8$Decoder.decode(UTF_8.java:435) [bci: 47]
stamp: void
=== Inputs ===
=== Succesors ===
=== Usages ===
v182 
=== Predecessor ===
v232 >@ <|@
instruction <@EndNode|@org.graalvm.compiler.nodes.EndNode>@  <|@  <|@
    end_IR
    begin_IR
      LIR
      nr   -1  <|@ instruction [] = LABEL numbPhis: 0 align: false label: ? <|@ <|@
      nr   -1  <|@ instruction JUMP ~[int[-25115|0xffffffffffff9de5], v11|QWORD[.]] destination: B11 -> B25 <|@ <|@
    end_IR
  end_block
  begin_block
    name "B12"
    from_bci -1
    to_bci -1
    predecessors "B10" 
    successors "B13" 
    xhandlers
    flags 
    probability 4602678819172646912
    begin_IR
      HIR
f <@#|@fixed with next>@ <|@
tid v224 <|@
d <@d|@=== Debug Properties ===
nodeSourcePosition: at sun.nio.cs.UTF_8$Decoder.decode(UTF_8.java:435) [bci: 47]
stamp: void
=== Inputs ===
=== Succesors ===
next: v222 
=== Usages ===
=== Predecessor ===
v233 >@ <|@
instruction <@Begin|@org.graalvm.compiler.nodes.BeginNode>@ #next: v222  <|@  <|@
f <@*|@fixed>@ <|@
tid v222 <|@
d <@d|@=== Debug Properties ===
nodeSourcePosition: at sun.nio.cs.UTF_8$Decoder.decode(UTF_8.java:435) [bci: 47]
stamp: void
=== Inputs ===
=== Succesors ===
=== Usages ===
v220 
=== Predecessor ===
v224 >@ <|@
instruction <@EndNode|@org.graalvm.compiler.nodes.EndNode>@  <|@  <|@
    end_IR
    begin_IR
      LIR
      nr   -1  <|@ instruction [] = LABEL numbPhis: 0 align: false label: ? <|@ <|@
      nr   -1  <|@ instruction JUMP ~[] destination: B12 -> B13 <|@ <|@
    end_IR
  end_block
  begin_block
    name "B13"
    from_bci -1
    to_bci -1
    predecessors "B8" "B12" 
    successors "B14" 
    xhandlers
    flags 
    probability 4607182418800017408
    begin_IR
      HIR
f <@#|@fixed with next>@ <|@
tid v220 <|@
d <@d|@=== Debug Properties ===
nodeSourcePosition: at sun.nio.cs.UTF_8$Decoder.decode(UTF_8.java:435) [bci: 47]
stamp: void
=== Inputs ===
stateAfter: - 
ends: v221 v222 
=== Succesors ===
next: v15 
=== Usages ===
v145 
=== Predecessor ===
- >@ <|@
instruction <@Merge|@org.graalvm.compiler.nodes.MergeNode>@ stateAfter: - ends: v221 v222 #next: v15  <|@  <|@
f <@*|@fixed>@ <|@
tid v15 <|@
d <@d|@=== Debug Properties ===
nodeSourcePosition: at sun.nio.cs.UTF_8$Decoder.decode(UTF_8.java:434) [bci: 20]
stamp: void
=== Inputs ===
=== Succesors ===
=== Usages ===
v16 
=== Predecessor ===
v220 >@ <|@
instruction <@EndNode|@org.graalvm.compiler.nodes.EndNode>@  <|@  <|@
    end_IR
    begin_IR
      LIR
      nr   -1  <|@ instruction [] = LABEL numbPhis: 0 align: false label: ? <|@ <|@
      nr   -1  <|@ instruction JUMP ~[v2|DWORD, int[0|0x0]] destination: B13 -> B14 <|@ <|@
    end_IR
  end_block
  begin_block
    name "B14"
    from_bci -1
    to_bci -1
    predecessors "B13" "B17" 
    successors "B15" "B18" 
    xhandlers
    flags "llh" 
    loop_index 0
    loop_depth 1
    probability 4647359331217820312
    begin_IR
      HIR
f <@~|@floating>@ <|@
tid i17 <|@
result v17|DWORD <|@
d <@d|@=== Debug Properties ===
stamp: i32
valueDescription: i32
=== Inputs ===
merge: v16 
values: i3 i33 
=== Succesors ===
=== Usages ===
?19 v46 v242 i33 
=== Predecessor ===
- >@ <|@
instruction <@ValuePhi|@org.graalvm.compiler.nodes.ValuePhiNode>@ merge: v16 values: i3 i33  <|@  <|@
f <@~|@floating>@ <|@
tid i18 <|@
result v18|DWORD <|@
d <@d|@=== Debug Properties ===
stamp: i32
valueDescription: i32
=== Inputs ===
merge: v16 
values: i8 i32 
=== Succesors ===
=== Usages ===
?19 v20 v52 i32 v243 
=== Predecessor ===
- >@ <|@
instruction <@ValuePhi|@org.graalvm.compiler.nodes.ValuePhiNode>@ merge: v16 values: i8 i32  <|@  <|@
f <@#|@fixed with next>@ <|@
tid v16 <|@
d <@d|@=== Debug Properties ===
canEndsSafepoint: false
inversionCount: 0
loopFrequency: 491.79306109916934
loopOrigFrequency: 1.0
loopType: SIMPLE_LOOP
nextEndIndex: 1
nodeSourcePosition: at sun.nio.cs.UTF_8$Decoder.decode(UTF_8.java:434) [bci: 20]
splits: 0
stamp: void
unrollFactor: 1
unswitches: 0
=== Inputs ===
stateAfter: - 
overflowGuard: - 
ends: v15 
=== Succesors ===
next: v27 
=== Usages ===
i17 i18 v23 v39 v173 
=== Predecessor ===
- >@ <|@
instruction <@LoopBegin|@org.graalvm.compiler.nodes.LoopBeginNode>@ stateAfter: - overflowGuard: - ends: v15 #next: v27  <|@  <|@
f <@~|@floating>@ <|@
tid v20 <|@
d <@d|@=== Debug Properties ===
condition: LT
nodeSourcePosition: at sun.nio.cs.UTF_8$Decoder.decode(UTF_8.java:434) [bci: 24]
op: org.graalvm.compiler.nodes.calc.IntegerLessThanNode$LessThanOp@cca0f98
stamp: void
unorderedIsTrue: false
=== Inputs ===
x: i18 
y: i111 
=== Succesors ===
=== Usages ===
v27 
=== Predecessor ===
- >@ <|@
instruction <@<|@org.graalvm.compiler.nodes.calc.IntegerLessThanNode>@ x: i18 y: i111  <|@  <|@
f <@*|@fixed>@ <|@
tid v27 <|@
d <@d|@=== Debug Properties ===
nodeSourcePosition: at sun.nio.cs.UTF_8$Decoder.decode(UTF_8.java:434) [bci: 24]
stamp: void
trueSuccessorProbability: 0.9979666244217335
=== Inputs ===
condition: v20 
=== Succesors ===
trueSuccessor: v21 
falseSuccessor: v23 
=== Usages ===
=== Predecessor ===
v16 >@ <|@
instruction <@If|@org.graalvm.compiler.nodes.IfNode>@ condition: v20 #trueSuccessor: v21 #falseSuccessor: v23  <|@  <|@
    end_IR
    begin_IR
      LIR
      nr   -1  <|@ instruction [v17|DWORD, v18|DWORD] = LABEL numbPhis: 2 align: false label: ? <|@ <|@
      nr   -1  <|@ instruction CMP (x: v8|DWORD, y: v18|DWORD) size: DWORD <|@ <|@
      nr   -1  <|@ instruction BRANCH trueDestinationProbability: 0.9979666244217335 condition: > trueDestination: B14 -> B15 falseDestination: B14 -> B18 <|@ <|@
    end_IR
  end_block
  begin_block
    name "B15"
    from_bci -1
    to_bci -1
    predecessors "B14" 
    successors "B16" "B17" 
    xhandlers
    flags 
    loop_index 0
    loop_depth 1
    probability 4647341739031775896
    begin_IR
      HIR
f <@#|@fixed with next>@ <|@
tid v21 <|@
d <@d|@=== Debug Properties ===
nodeSourcePosition: at sun.nio.cs.UTF_8$Decoder.decode(UTF_8.java:434) [bci: 27]
stamp: void
=== Inputs ===
=== Succesors ===
next: i238 
=== Usages ===
v136 v145 
=== Predecessor ===
v27 >@ <|@
instruction <@Begin|@org.graalvm.compiler.nodes.BeginNode>@ #next: i238  <|@  <|@
f <@~|@floating>@ <|@
tid v136 <|@
d <@d|@=== Debug Properties ===
stamp: void
=== Inputs ===
kf: v204 v21 
=== Succesors ===
=== Usages ===
i238 
=== Predecessor ===
- >@ <|@
instruction <@c|@com.oracle.graal.enterprise.k.c>@ kf: v204 v21  <|@  <|@
f <@~|@floating>@ <|@
tid v242 <|@
result [v1|QWORD[.] + v17|DWORD * 1 + 16] <|@
d <@d|@=== Debug Properties ===
displacement: 16
scale: Times1
stamp: void*
=== Inputs ===
base: a2 
index: i17 
=== Succesors ===
=== Usages ===
i238 
=== Predecessor ===
- >@ <|@
instruction <@AMD64Address|@org.graalvm.compiler.core.amd64.AMD64AddressNode>@ base: a2 index: i17  <|@  <|@
f <@#|@fixed with next>@ <|@
tid i238 <|@
result v19|DWORD <|@
d <@d|@=== Debug Properties ===
barrierType: NONE
forceFixed: false
location: Array: byte
nodeSourcePosition: at sun.nio.cs.UTF_8$Decoder.decode(UTF_8.java:435) [bci: 45]
nullCheck: false
stamp: i8
=== Inputs ===
stateBefore: - 
guard: v136 
address: v242 
=== Succesors ===
next: v174 
=== Usages ===
i109 i84 
=== Predecessor ===
v21 >@ <|@
instruction <@Read|@org.graalvm.compiler.nodes.memory.ReadNode>@ stateBefore: - guard: v136 address: v242 #next: v174  <|@  <|@
f <@~|@floating>@ <|@
tid i84 <|@
result v20|DWORD <|@
d <@d|@=== Debug Properties ===
getOp: org.graalvm.compiler.nodes.calc.SignExtendNode$$Lambda$10/1121602809@34736fd3
getReverseOp: org.graalvm.compiler.nodes.calc.SignExtendNode$$Lambda$11/1363241743@10f97424
inputBits: 8
nodeSourcePosition: at sun.nio.cs.UTF_8$Decoder.decode(UTF_8.java:434) [bci: 29]
resultBits: 32
stamp: i32 [-128 - 127]
=== Inputs ===
value: i238 
=== Succesors ===
=== Usages ===
v29 
=== Predecessor ===
- >@ <|@
instruction <@SignExtend|@org.graalvm.compiler.nodes.calc.SignExtendNode>@ value: i238  <|@  <|@
f <@~|@floating>@ <|@
tid v29 <|@
d <@d|@=== Debug Properties ===
condition: LT
nodeSourcePosition: at sun.nio.cs.UTF_8$Decoder.decode(UTF_8.java:434) [bci: 30]
op: org.graalvm.compiler.nodes.calc.IntegerLessThanNode$LessThanOp@cca0f98
stamp: void
unorderedIsTrue: false
=== Inputs ===
x: i84 
y: i8 
=== Succesors ===
=== Usages ===
v174 
=== Predecessor ===
- >@ <|@
instruction <@<|@org.graalvm.compiler.nodes.calc.IntegerLessThanNode>@ x: i84 y: i8  <|@  <|@
f <@*|@fixed>@ <|@
tid v174 <|@
d <@d|@=== Debug Properties ===
nodeSourcePosition: at sun.nio.cs.UTF_8$Decoder.decode(UTF_8.java:434) [bci: 30]
stamp: void
trueSuccessorProbability: 0.0
=== Inputs ===
condition: v29 
=== Succesors ===
trueSuccessor: v173 
falseSuccessor: v170 
=== Usages ===
=== Predecessor ===
i238 >@ <|@
instruction <@If|@org.graalvm.compiler.nodes.IfNode>@ condition: v29 #trueSuccessor: v173 #falseSuccessor: v170  <|@  <|@
    end_IR
    begin_IR
      LIR
      nr   -1  <|@ instruction [] = LABEL numbPhis: 0 align: true label: ? <|@ <|@
      nr   -1  <|@ instruction v19|DWORD = MOVSXB [v1|QWORD[.] + v17|DWORD * 1 + 16] size: DWORD <|@ <|@
      nr   -1  <|@ instruction v20|DWORD = MOVSXB v19|DWORD size: DWORD <|@ <|@
      nr   -1  <|@ instruction TEST (x: v20|DWORD, y: v20|DWORD) size: DWORD <|@ <|@
      nr   -1  <|@ instruction BRANCH trueDestinationProbability: 0.0 condition: < trueDestination: B15 -> B16 falseDestination: B15 -> B17 <|@ <|@
    end_IR
  end_block
  begin_block
    name "B16"
    from_bci -1
    to_bci -1
    predecessors "B15" 
    successors "B20" 
    xhandlers
    flags 
    probability 2355382605114769408
    begin_IR
      HIR
f <@#|@fixed with next>@ <|@
tid v173 <|@
d <@d|@=== Debug Properties ===
nodeSourcePosition: at sun.nio.cs.UTF_8$Decoder.decode(UTF_8.java:434) [bci: 30]
stamp: void
=== Inputs ===
stateAfter: - 
loopBegin: v16 
=== Succesors ===
next: v202 
=== Usages ===
=== Predecessor ===
v174 >@ <|@
instruction <@LoopExit|@org.graalvm.compiler.nodes.LoopExitNode>@ stateAfter: - loopBegin: v16 #next: v202  <|@  <|@
f <@~|@floating>@ <|@
tid i203 <|@
result int[-21779|0xffffffffffffaaed] <|@
d <@d|@=== Debug Properties ===
isDefaultStable: false
rawvalue: -21779
stableDimension: 0
stamp: i32 [-21779] ⇊00000000ffffaaed ⇈00000000ffffaaed
stampKind: i32
value: int[-21779|0xffffffffffffaaed]
=== Inputs ===
=== Succesors ===
=== Usages ===
i199 
=== Predecessor ===
- >@ <|@
instruction <@Constant|@org.graalvm.compiler.nodes.ConstantNode>@  <|@  <|@
f <@*|@fixed>@ <|@
tid v202 <|@
d <@d|@=== Debug Properties ===
stamp: void
=== Inputs ===
=== Succesors ===
=== Usages ===
v196 
=== Predecessor ===
v173 >@ <|@
instruction <@EndNode|@org.graalvm.compiler.nodes.EndNode>@  <|@  <|@
    end_IR
    begin_IR
      LIR
      nr   -1  <|@ instruction [] = LABEL numbPhis: 0 align: false label: ? <|@ <|@
      nr   -1  <|@ instruction JUMP ~[int[-21779|0xffffffffffffaaed]] destination: B16 -> B20 <|@ <|@
    end_IR
  end_block
  begin_block
    name "B17"
    from_bci -1
    to_bci -1
    predecessors "B15" 
    successors "B14" 
    xhandlers
    flags "lle" 
    loop_index 0
    loop_depth 1
    probability 4647341739031775896
    begin_IR
      HIR
f <@#|@fixed with next>@ <|@
tid v170 <|@
d <@d|@=== Debug Properties ===
nodeSourcePosition: at sun.nio.cs.UTF_8$Decoder.decode(UTF_8.java:434) [bci: 30]
stamp: void
=== Inputs ===
=== Succesors ===
next: v105 
=== Usages ===
=== Predecessor ===
v174 >@ <|@
instruction <@Begin|@org.graalvm.compiler.nodes.BeginNode>@ #next: v105  <|@  <|@
f <@~|@floating>@ <|@
tid v145 <|@
d <@d|@=== Debug Properties ===
stamp: void
=== Inputs ===
kf: v220 v21 
=== Succesors ===
=== Usages ===
v105 
=== Predecessor ===
- >@ <|@
instruction <@c|@com.oracle.graal.enterprise.k.c>@ kf: v220 v21  <|@  <|@
f <@~|@floating>@ <|@
tid v243 <|@
result [v4|QWORD[.] + v18|DWORD * 2 + 16] <|@
d <@d|@=== Debug Properties ===
displacement: 16
scale: Times2
stamp: void*
=== Inputs ===
base: a5 
index: i18 
=== Succesors ===
=== Usages ===
v105 
=== Predecessor ===
- >@ <|@
instruction <@AMD64Address|@org.graalvm.compiler.core.amd64.AMD64AddressNode>@ base: a5 index: i18  <|@  <|@
f <@~|@floating>@ <|@
tid i109 <|@
result v21|DWORD <|@
d <@d|@=== Debug Properties ===
getOp: org.graalvm.compiler.nodes.calc.SignExtendNode$$Lambda$10/1121602809@34736fd3
getReverseOp: org.graalvm.compiler.nodes.calc.SignExtendNode$$Lambda$11/1363241743@10f97424
inputBits: 8
nodeSourcePosition: at sun.nio.cs.UTF_8$Decoder.decode(UTF_8.java:435) [bci: 46]
resultBits: 16
stamp: i16 [-128 - 127]
=== Inputs ===
value: i238 
=== Succesors ===
=== Usages ===
v105 
=== Predecessor ===
- >@ <|@
instruction <@SignExtend|@org.graalvm.compiler.nodes.calc.SignExtendNode>@ value: i238  <|@  <|@
f <@#|@fixed with next>@ <|@
tid v105 <|@
d <@d|@=== Debug Properties ===
barrierType: NONE
location: Array: char
nodeSourcePosition: at sun.nio.cs.UTF_8$Decoder.decode(UTF_8.java:435) [bci: 47]
nullCheck: false
stamp: void
=== Inputs ===
stateBefore: - 
guard: v145 
address: v243 
value: i109 
stateAfter: - 
lastLocationAccess: - 
=== Succesors ===
next: v39 
=== Usages ===
=== Predecessor ===
v170 >@ <|@
instruction <@Write|@org.graalvm.compiler.nodes.memory.WriteNode>@ stateBefore: - guard: v145 address: v243 value: i109 stateAfter: - lastLocationAccess: - #next: v39  <|@  <|@
f <@~|@floating>@ <|@
tid i32 <|@
result v22|DWORD <|@
d <@d|@=== Debug Properties ===
getOp: org.graalvm.compiler.nodes.calc.AddNode$$Lambda$14/562279114@1363f342
nodeSourcePosition: at sun.nio.cs.UTF_8$Decoder.decode(UTF_8.java:435) [bci: 37]
stamp: i32
=== Inputs ===
x: i18 
y: i31 
=== Succesors ===
=== Usages ===
i18 
=== Predecessor ===
- >@ <|@
instruction <@+|@org.graalvm.compiler.nodes.calc.AddNode>@ x: i18 y: i31  <|@  <|@
f <@~|@floating>@ <|@
tid i33 <|@
result v23|DWORD <|@
d <@d|@=== Debug Properties ===
getOp: org.graalvm.compiler.nodes.calc.AddNode$$Lambda$14/562279114@1363f342
nodeSourcePosition: at sun.nio.cs.UTF_8$Decoder.decode(UTF_8.java:435) [bci: 42]
stamp: i32
=== Inputs ===
x: i17 
y: i31 
=== Succesors ===
=== Usages ===
i17 
=== Predecessor ===
- >@ <|@
instruction <@+|@org.graalvm.compiler.nodes.calc.AddNode>@ x: i17 y: i31  <|@  <|@
f <@*|@fixed>@ <|@
tid v39 <|@
d <@d|@=== Debug Properties ===
canSafepoint: false
endIndex: 0
nodeSourcePosition: at sun.nio.cs.UTF_8$Decoder.decode(UTF_8.java:434) [bci: 20]
stamp: void
=== Inputs ===
loopBegin: v16 
=== Succesors ===
=== Usages ===
=== Predecessor ===
v105 >@ <|@
instruction <@LoopEnd|@org.graalvm.compiler.nodes.LoopEndNode>@ loopBegin: v16  <|@  <|@
    end_IR
    begin_IR
      LIR
      nr   -1  <|@ instruction [] = LABEL numbPhis: 0 align: false label: ? <|@ <|@
      nr   -1  <|@ instruction v21|DWORD = MOVSXB v19|DWORD size: DWORD <|@ <|@
      nr   -1  <|@ instruction MOV (x: [v4|QWORD[.] + v18|DWORD * 2 + 16], y: v21|DWORD) size: WORD <|@ <|@
      nr   -1  <|@ instruction v22|DWORD = INC v18|DWORD size: DWORD <|@ <|@
      nr   -1  <|@ instruction v23|DWORD = INC v17|DWORD size: DWORD <|@ <|@
      nr   -1  <|@ instruction JUMP ~[v23|DWORD, v22|DWORD] destination: B17 -> B14 <|@ <|@
    end_IR
  end_block
  begin_block
    name "B18"
    from_bci -1
    to_bci -1
    predecessors "B14" 
    successors "B19" "B21" 
    xhandlers
    flags 
    probability 4607182418800017408
    begin_IR
      HIR
f <@#|@fixed with next>@ <|@
tid v23 <|@
d <@d|@=== Debug Properties ===
nodeSourcePosition: at sun.nio.cs.UTF_8$Decoder.decode(UTF_8.java:437) [bci: 51]
stamp: void
=== Inputs ===
stateAfter: - 
loopBegin: v16 
=== Succesors ===
next: v178 
=== Usages ===
=== Predecessor ===
v27 >@ <|@
instruction <@LoopExit|@org.graalvm.compiler.nodes.LoopExitNode>@ stateAfter: - loopBegin: v16 #next: v178  <|@  <|@
f <@~|@floating>@ <|@
tid v46 <|@
d <@d|@=== Debug Properties ===
condition: LT
nodeSourcePosition: at sun.nio.cs.UTF_8$Decoder.decode(UTF_8.java:437) [bci: 54]
op: org.graalvm.compiler.nodes.calc.IntegerLessThanNode$LessThanOp@cca0f98
stamp: void
unorderedIsTrue: false
=== Inputs ===
x: i17 
y: i7 
=== Succesors ===
=== Usages ===
v178 
=== Predecessor ===
- >@ <|@
instruction <@<|@org.graalvm.compiler.nodes.calc.IntegerLessThanNode>@ x: i17 y: i7  <|@  <|@
f <@*|@fixed>@ <|@
tid v178 <|@
d <@d|@=== Debug Properties ===
nodeSourcePosition: at sun.nio.cs.UTF_8$Decoder.decode(UTF_8.java:437) [bci: 54]
stamp: void
trueSuccessorProbability: 0.0
=== Inputs ===
condition: v46 
=== Succesors ===
trueSuccessor: v177 
falseSuccessor: v175 
=== Usages ===
=== Predecessor ===
v23 >@ <|@
instruction <@If|@org.graalvm.compiler.nodes.IfNode>@ condition: v46 #trueSuccessor: v177 #falseSuccessor: v175  <|@  <|@
    end_IR
    begin_IR
      LIR
      nr   -1  <|@ instruction [] = LABEL numbPhis: 0 align: false label: ? <|@ <|@
      nr   -1  <|@ instruction CMP (x: v5|DWORD, y: v17|DWORD) size: DWORD <|@ <|@
      nr   -1  <|@ instruction BRANCH trueDestinationProbability: 0.0 condition: > trueDestination: B18 -> B19 falseDestination: B18 -> B21 <|@ <|@
    end_IR
  end_block
  begin_block
    name "B19"
    from_bci -1
    to_bci -1
    predecessors "B18" 
    successors "B20" 
    xhandlers
    flags 
    probability 2355382605114769408
    begin_IR
      HIR
f <@#|@fixed with next>@ <|@
tid v177 <|@
d <@d|@=== Debug Properties ===
nodeSourcePosition: at sun.nio.cs.UTF_8$Decoder.decode(UTF_8.java:437) [bci: 54]
stamp: void
=== Inputs ===
=== Succesors ===
next: v197 
=== Usages ===
=== Predecessor ===
v178 >@ <|@
instruction <@Begin|@org.graalvm.compiler.nodes.BeginNode>@ #next: v197  <|@  <|@
f <@~|@floating>@ <|@
tid i198 <|@
result int[-27155|0xffffffffffff95ed] <|@
d <@d|@=== Debug Properties ===
isDefaultStable: false
rawvalue: -27155
stableDimension: 0
stamp: i32 [-27155] ⇊00000000ffff95ed ⇈00000000ffff95ed
stampKind: i32
value: int[-27155|0xffffffffffff95ed]
=== Inputs ===
=== Succesors ===
=== Usages ===
i199 
=== Predecessor ===
- >@ <|@
instruction <@Constant|@org.graalvm.compiler.nodes.ConstantNode>@  <|@  <|@
f <@*|@fixed>@ <|@
tid v197 <|@
d <@d|@=== Debug Properties ===
stamp: void
=== Inputs ===
=== Succesors ===
=== Usages ===
v196 
=== Predecessor ===
v177 >@ <|@
instruction <@EndNode|@org.graalvm.compiler.nodes.EndNode>@  <|@  <|@
    end_IR
    begin_IR
      LIR
      nr   -1  <|@ instruction [] = LABEL numbPhis: 0 align: false label: ? <|@ <|@
      nr   -1  <|@ instruction JUMP ~[int[-27155|0xffffffffffff95ed]] destination: B19 -> B20 <|@ <|@
    end_IR
  end_block
  begin_block
    name "B20"
    from_bci -1
    to_bci -1
    predecessors "B19" "B16" 
    successors 
    xhandlers
    flags 
    probability 2359886204742139904
    begin_IR
      HIR
f <@~|@floating>@ <|@
tid i199 <|@
result v24|DWORD <|@
d <@d|@=== Debug Properties ===
stamp: i32 [-27155 - -21779] ⇊00000000ffff80ed ⇈00000000ffffbfed
valueDescription: i32
=== Inputs ===
merge: v196 
values: i198 i203 
=== Succesors ===
=== Usages ===
v201 
=== Predecessor ===
- >@ <|@
instruction <@ValuePhi|@org.graalvm.compiler.nodes.ValuePhiNode>@ merge: v196 values: i198 i203  <|@  <|@
f <@#|@fixed with next>@ <|@
tid v196 <|@
d <@d|@=== Debug Properties ===
stamp: void
=== Inputs ===
stateAfter: - 
ends: v197 v202 
=== Succesors ===
next: v201 
=== Usages ===
i199 
=== Predecessor ===
- >@ <|@
instruction <@Merge|@org.graalvm.compiler.nodes.MergeNode>@ stateAfter: - ends: v197 v202 #next: v201  <|@  <|@
f <@~|@floating>@ <|@
tid a13 <|@
result Object[null] <|@
d <@d|@=== Debug Properties ===
isDefaultStable: false
nodeSourcePosition: at sun.nio.cs.UTF_8$Decoder.decode(UTF_8.java:431) [bci: 17]
rawvalue: null
stableDimension: 0
stamp: a - NULL
stampKind: a -
value: Object[null]
=== Inputs ===
=== Succesors ===
=== Usages ===
?19 v201 
=== Predecessor ===
- >@ <|@
instruction <@Constant|@org.graalvm.compiler.nodes.ConstantNode>@  <|@  <|@
tid ?19 <|@
d <@d|@=== Debug Properties ===
bci: 20
code: ResolvedJavaMethodBytecode<UTF_8$Decoder.decode(byte[], int, int, char[])>
duringCall: false
localsSize: 14
locksSize: 0
rethrowException: false
sourceFile: UTF_8.java
sourceLine: 434
stackSize: 0
=== Inputs ===
outerFrameState: - 
values: a1 a2 i17 - a5 i7 i18 i111 a13 - - - - - 
=== Succesors ===
=== Usages ===
v201 
=== Predecessor ===
- >@ <|@
instruction <@FrameState|@org.graalvm.compiler.nodes.FrameState>@ outerFrameState: - values: a1 a2 i17 - a5 i7 i18 i111 a13 - - - - -  <|@  <|@
f <@*|@fixed>@ <|@
tid v201 <|@
d <@d|@=== Debug Properties ===
stamp: void
=== Inputs ===
stateBefore: ?19 
actionAndReason: i199 
speculation: a13 
=== Succesors ===
=== Usages ===
=== Predecessor ===
v196 >@ <|@
instruction <@DynamicDeoptimize|@org.graalvm.compiler.nodes.DynamicDeoptimizeNode>@ stateBefore: ?19 actionAndReason: i199 speculation: a13  <|@  <|@
    end_IR
    begin_IR
      LIR
      nr   -1  <|@ instruction [v24|DWORD] = LABEL numbPhis: 1 align: false label: ? <|@ <|@
      nr   -1  <|@ instruction MOV (x: [r15|QWORD + 668], y: v24|DWORD) size: DWORD <|@ <|@
      nr   -1  <|@ instruction MOV (x: [r15|QWORD + 680], y: r12|ILLEGAL) size: QWORD <|@ <|@
      nr   -1  <|@ st <@st|@sun.nio.cs.UTF_8$Decoder.decode(UTF_8.java:434) [bci: 20]
locals: v0|QWORD[.] v1|QWORD[.] v17|DWORD - v4|QWORD[.] v5|DWORD v18|DWORD v8|DWORD Object[null] - - - - - 
>@ <|@ instruction DEOPT info [bci:20] <|@ <|@
    end_IR
  end_block
  begin_block
    name "B21"
    from_bci -1
    to_bci -1
    predecessors "B18" 
    successors 
    xhandlers
    flags 
    probability 4607182418800017408
    begin_IR
      HIR
f <@#|@fixed with next>@ <|@
tid v175 <|@
d <@d|@=== Debug Properties ===
nodeSourcePosition: at sun.nio.cs.UTF_8$Decoder.decode(UTF_8.java:437) [bci: 54]
stamp: void
=== Inputs ===
=== Succesors ===
next: v52 
=== Usages ===
=== Predecessor ===
v178 >@ <|@
instruction <@Begin|@org.graalvm.compiler.nodes.BeginNode>@ #next: v52  <|@  <|@
f <@*|@fixed>@ <|@
tid v52 <|@
d <@d|@=== Debug Properties ===
nodeSourcePosition: at sun.nio.cs.UTF_8$Decoder.decode(UTF_8.java:550) [bci: 778]
stamp: void
=== Inputs ===
result: i18 
memoryMap: - 
=== Succesors ===
=== Usages ===
=== Predecessor ===
v175 >@ <|@
instruction <@Return|@org.graalvm.compiler.nodes.ReturnNode>@ result: i18 memoryMap: -  <|@  <|@
    end_IR
    begin_IR
      LIR
      nr   -1  <|@ instruction [] = LABEL numbPhis: 0 align: false label: ? <|@ <|@
      nr   -1  <|@ instruction rax|DWORD = MOVE v18|DWORD moveKind: DWORD <|@ <|@
      nr   -1  <|@ instruction RETURN (savedRbp: stack:16|QWORD, value: rax|DWORD) isStub: false thread: r15 scratchForSafepointOnReturn: rcx config: org.graalvm.compiler.hotspot.GraalHotSpotVMConfig@f96b858 <|@ <|@
    end_IR
  end_block
  begin_block
    name "B22"
    from_bci -1
    to_bci -1
    predecessors "B9" 
    successors "B25" 
    xhandlers
    flags 
    probability 2355382605114769408
    begin_IR
      HIR
f <@#|@fixed with next>@ <|@
tid v231 <|@
d <@d|@=== Debug Properties ===
nodeSourcePosition: at sun.nio.cs.UTF_8$Decoder.decode(UTF_8.java:435) [bci: 47]
stamp: void
=== Inputs ===
=== Succesors ===
next: v194 
=== Usages ===
=== Predecessor ===
v235 >@ <|@
instruction <@Begin|@org.graalvm.compiler.nodes.BeginNode>@ #next: v194  <|@  <|@
f <@*|@fixed>@ <|@
tid v194 <|@
d <@d|@=== Debug Properties ===
stamp: void
=== Inputs ===
=== Succesors ===
=== Usages ===
v182 
=== Predecessor ===
v231 >@ <|@
instruction <@EndNode|@org.graalvm.compiler.nodes.EndNode>@  <|@  <|@
    end_IR
    begin_IR
      LIR
      nr   -1  <|@ instruction [] = LABEL numbPhis: 0 align: false label: ? <|@ <|@
      nr   -1  <|@ instruction JUMP ~[int[-25115|0xffffffffffff9de5], v11|QWORD[.]] destination: B22 -> B25 <|@ <|@
    end_IR
  end_block
  begin_block
    name "B23"
    from_bci -1
    to_bci -1
    predecessors "B5" 
    successors "B25" 
    xhandlers
    flags 
    probability 2355382605114769408
    begin_IR
      HIR
f <@#|@fixed with next>@ <|@
tid v216 <|@
d <@d|@=== Debug Properties ===
nodeSourcePosition: at sun.nio.cs.UTF_8$Decoder.decode(UTF_8.java:435) [bci: 45]
stamp: void
=== Inputs ===
=== Succesors ===
next: v244 
=== Usages ===
=== Predecessor ===
v217 >@ <|@
instruction <@Begin|@org.graalvm.compiler.nodes.BeginNode>@ #next: v244  <|@  <|@
f <@*|@fixed>@ <|@
tid v244 <|@
d <@d|@=== Debug Properties ===
nodeSourcePosition: at sun.nio.cs.UTF_8$Decoder.decode(UTF_8.java:435) [bci: 45]
stamp: void
=== Inputs ===
=== Succesors ===
=== Usages ===
v182 
=== Predecessor ===
v216 >@ <|@
instruction <@EndNode|@org.graalvm.compiler.nodes.EndNode>@  <|@  <|@
    end_IR
    begin_IR
      LIR
      nr   -1  <|@ instruction [] = LABEL numbPhis: 0 align: false label: ? <|@ <|@
      nr   -1  <|@ instruction JUMP ~[int[-22555|0xffffffffffffa7e5], v11|QWORD[.]] destination: B23 -> B25 <|@ <|@
    end_IR
  end_block
  begin_block
    name "B24"
    from_bci -1
    to_bci -1
    predecessors "B4" 
    successors "B25" 
    xhandlers
    flags 
    probability 2355382605114769408
    begin_IR
      HIR
f <@#|@fixed with next>@ <|@
tid v215 <|@
d <@d|@=== Debug Properties ===
nodeSourcePosition: at sun.nio.cs.UTF_8$Decoder.decode(UTF_8.java:435) [bci: 45]
stamp: void
=== Inputs ===
=== Succesors ===
next: v191 
=== Usages ===
=== Predecessor ===
v219 >@ <|@
instruction <@Begin|@org.graalvm.compiler.nodes.BeginNode>@ #next: v191  <|@  <|@
f <@*|@fixed>@ <|@
tid v191 <|@
d <@d|@=== Debug Properties ===
stamp: void
=== Inputs ===
=== Succesors ===
=== Usages ===
v182 
=== Predecessor ===
v215 >@ <|@
instruction <@EndNode|@org.graalvm.compiler.nodes.EndNode>@  <|@  <|@
    end_IR
    begin_IR
      LIR
      nr   -1  <|@ instruction [] = LABEL numbPhis: 0 align: false label: ? <|@ <|@
      nr   -1  <|@ instruction JUMP ~[int[-22555|0xffffffffffffa7e5], v11|QWORD[.]] destination: B24 -> B25 <|@ <|@
    end_IR
  end_block
  begin_block
    name "B25"
    from_bci -1
    to_bci -1
    predecessors "B1" "B24" "B22" "B23" "B11" 
    successors 
    xhandlers
    flags 
    probability 2365515704276353024
    begin_IR
      HIR
f <@~|@floating>@ <|@
tid i186 <|@
result v25|DWORD <|@
d <@d|@=== Debug Properties ===
stamp: i32 [-25115 - -16651] ⇊00000000ffff80e5 ⇈00000000ffffbff5
valueDescription: i32
=== Inputs ===
merge: v182 
values: i184 i192 i195 i192 i195 
=== Succesors ===
=== Usages ===
v188 
=== Predecessor ===
- >@ <|@
instruction <@ValuePhi|@org.graalvm.compiler.nodes.ValuePhiNode>@ merge: v182 values: i184 i192 i195 i192 i195  <|@  <|@
f <@~|@floating>@ <|@
tid a187 <|@
result v26|QWORD[.] <|@
d <@d|@=== Debug Properties ===
stamp: a# Lcom/oracle/graal/enterprise/k/d$a;
valueDescription: a -
=== Inputs ===
merge: v182 
values: a185 a193 a193 a193 a193 
=== Succesors ===
=== Usages ===
v188 
=== Predecessor ===
- >@ <|@
instruction <@ValuePhi|@org.graalvm.compiler.nodes.ValuePhiNode>@ merge: v182 values: a185 a193 a193 a193 a193  <|@  <|@
f <@#|@fixed with next>@ <|@
tid v182 <|@
d <@d|@=== Debug Properties ===
stamp: void
=== Inputs ===
stateAfter: - 
ends: v183 v191 v194 v244 v245 
=== Succesors ===
next: v188 
=== Usages ===
i186 a187 
=== Predecessor ===
- >@ <|@
instruction <@Merge|@org.graalvm.compiler.nodes.MergeNode>@ stateAfter: - ends: v183 v191 v194 v244 v245 #next: v188  <|@  <|@
f <@*|@fixed>@ <|@
tid v188 <|@
d <@d|@=== Debug Properties ===
stamp: void
=== Inputs ===
stateBefore: ?6 
actionAndReason: i186 
speculation: a187 
=== Succesors ===
=== Usages ===
=== Predecessor ===
v182 >@ <|@
instruction <@DynamicDeoptimize|@org.graalvm.compiler.nodes.DynamicDeoptimizeNode>@ stateBefore: ?6 actionAndReason: i186 speculation: a187  <|@  <|@
    end_IR
    begin_IR
      LIR
      nr   -1  <|@ instruction [v25|DWORD, v26|QWORD[.]] = LABEL numbPhis: 2 align: false label: ? <|@ <|@
      nr   -1  <|@ instruction MOV (x: [r15|QWORD + 668], y: v25|DWORD) size: DWORD <|@ <|@
      nr   -1  <|@ instruction MOV (x: [r15|QWORD + 680], y: v26|QWORD[.]) size: QWORD <|@ <|@
      nr   -1  <|@ st <@st|@sun.nio.cs.UTF_8$Decoder.decode(UTF_8.java:428) [bci: 0]
locals: v0|QWORD[.] v1|QWORD[.] v2|DWORD v3|DWORD v4|QWORD[.] - - - - - - - - - 
>@ <|@ instruction DEOPT info [bci:0] <|@ <|@
    end_IR
  end_block
end_cfg
begin_cfg
  name "After PreAllocationOptimizationStage"
  begin_block
    name "B0"
    from_bci -1
    to_bci -1
    predecessors 
    successors "B1" "B2" 
    xhandlers
    flags 
    probability 4607182418800017408
    begin_IR
      LIR
      nr   -1  <|@ instruction [rsi|QWORD[.], rdx|QWORD[.], rcx|DWORD, r8|DWORD, r9|QWORD[.], rbp|QWORD] = LABEL numbPhis: 0 align: false label: ? <|@ <|@
      nr   -1  <|@ instruction stack:16|QWORD = MOVE rbp|QWORD moveKind: QWORD <|@ <|@
      nr   -1  <|@ instruction [] = HOTSPOTLOCKSTACK frameMapBuilder: org.graalvm.compiler.lir.amd64.AMD64FrameMapBuilder@51ff0cce slotKind: QWORD <|@ <|@
      nr   -1  <|@ instruction v0|QWORD[.] = MOVE rsi|QWORD[.] moveKind: QWORD <|@ <|@
      nr   -1  <|@ instruction v1|QWORD[.] = MOVE rdx|QWORD[.] moveKind: QWORD <|@ <|@
      nr   -1  <|@ instruction v2|DWORD = MOVE rcx|DWORD moveKind: DWORD <|@ <|@
      nr   -1  <|@ instruction v3|DWORD = MOVE r8|DWORD moveKind: DWORD <|@ <|@
      nr   -1  <|@ instruction v4|QWORD[.] = MOVE r9|QWORD[.] moveKind: QWORD <|@ <|@
      nr   -1  <|@ instruction v5|DWORD = ADD (x: v2|DWORD, y: v3|DWORD) size: DWORD <|@ <|@
      nr   -1  <|@ instruction TEST (x: v1|QWORD[.], y: v1|QWORD[.]) size: QWORD <|@ <|@
      nr   -1  <|@ instruction BRANCH trueDestinationProbability: 0.0 condition: = trueDestination: B0 -> B1 falseDestination: B0 -> B2 <|@ <|@
    end_IR
  end_block
  begin_block
    name "B2"
    from_bci -1
    to_bci -1
    predecessors "B0" 
    successors "B3" "B4" 
    xhandlers
    flags 
    probability 4607182418800017408
    begin_IR
      LIR
      nr   -1  <|@ instruction [] = LABEL numbPhis: 0 align: false label: ? <|@ <|@
      nr   -1  <|@ st <@st|@sun.nio.cs.UTF_8$Decoder.decode(UTF_8.java:428) [bci: 0]
locals: v0|QWORD[.] v1|QWORD[.] v2|DWORD v3|DWORD v4|QWORD[.] - - - - - - - - - 
>@ <|@ instruction v7|DWORD = MOV [v4|QWORD[.] + 12] size: DWORD state [bci:0] <|@ <|@
      nr   -1  <|@ instruction CMP (x: v3|DWORD, y: v7|DWORD) size: DWORD <|@ <|@
      nr   -1  <|@ instruction v8|DWORD = CMOVE (falseValue: v3|DWORD, ~trueValue: v7|DWORD) condition: > <|@ <|@
      nr   -1  <|@ instruction v9|QWORD = MOVSXD v8|DWORD size: QWORD <|@ <|@
      nr   -1  <|@ instruction v10|QWORD = DEC v9|QWORD size: QWORD <|@ <|@
      nr   -1  <|@ instruction CMP v8|DWORD y: 1 size: DWORD <|@ <|@
      nr   -1  <|@ instruction BRANCH trueDestinationProbability: 0.5 condition: < trueDestination: B2 -> B3 falseDestination: B2 -> B4 <|@ <|@
    end_IR
  end_block
  begin_block
    name "B4"
    from_bci -1
    to_bci -1
    predecessors "B2" 
    successors "B5" "B24" 
    xhandlers
    flags 
    probability 4602678819172646912
    begin_IR
      LIR
      nr   -1  <|@ instruction [] = LABEL numbPhis: 0 align: false label: ? <|@ <|@
      nr   -1  <|@ instruction v12|DWORD = MOV [v1|QWORD[.] + 12] size: DWORD <|@ <|@
      nr   -1  <|@ instruction v13|QWORD = MOVSXD v2|DWORD size: QWORD <|@ <|@
      nr   -1  <|@ instruction v14|QWORD = ADD (x: v13|QWORD, y: v10|QWORD) size: QWORD <|@ <|@
      nr   -1  <|@ instruction v15|QWORD = MOV v12|DWORD size: DWORD <|@ <|@
      nr   -1  <|@ instruction CMP (x: v15|QWORD, y: v14|QWORD) size: QWORD <|@ <|@
      nr   -1  <|@ instruction BRANCH trueDestinationProbability: 1.0 condition: |>| trueDestination: B4 -> B5 falseDestination: B4 -> B24 <|@ <|@
    end_IR
  end_block
  begin_block
    name "B5"
    from_bci -1
    to_bci -1
    predecessors "B4" 
    successors "B6" "B23" 
    xhandlers
    flags 
    probability 4602678819172646912
    begin_IR
      LIR
      nr   -1  <|@ instruction [] = LABEL numbPhis: 0 align: false label: ? <|@ <|@
      nr   -1  <|@ instruction CMP (x: v12|DWORD, y: v2|DWORD) size: DWORD <|@ <|@
      nr   -1  <|@ instruction BRANCH trueDestinationProbability: 1.0 condition: |>| trueDestination: B5 -> B6 falseDestination: B5 -> B23 <|@ <|@
    end_IR
  end_block
  begin_block
    name "B6"
    from_bci -1
    to_bci -1
    predecessors "B5" 
    successors "B7" 
    xhandlers
    flags 
    probability 4602678819172646912
    begin_IR
      LIR
      nr   -1  <|@ instruction [] = LABEL numbPhis: 0 align: false label: ? <|@ <|@
      nr   -1  <|@ instruction JUMP ~[] destination: B6 -> B7 <|@ <|@
    end_IR
  end_block
  begin_block
    name "B7"
    from_bci -1
    to_bci -1
    predecessors "B3" "B6" 
    successors "B8" "B9" 
    xhandlers
    flags 
    probability 4607182418800017408
    begin_IR
      LIR
      nr   -1  <|@ instruction [] = LABEL numbPhis: 0 align: false label: ? <|@ <|@
      nr   -1  <|@ instruction CMP v8|DWORD y: 1 size: DWORD <|@ <|@
      nr   -1  <|@ instruction BRANCH trueDestinationProbability: 0.5 condition: < trueDestination: B7 -> B8 falseDestination: B7 -> B9 <|@ <|@
    end_IR
  end_block
  begin_block
    name "B9"
    from_bci -1
    to_bci -1
    predecessors "B7" 
    successors "B10" "B22" 
    xhandlers
    flags 
    probability 4602678819172646912
    begin_IR
      LIR
      nr   -1  <|@ instruction [] = LABEL numbPhis: 0 align: false label: ? <|@ <|@
      nr   -1  <|@ instruction v16|QWORD = MOV v7|DWORD size: DWORD <|@ <|@
      nr   -1  <|@ instruction CMP (x: v16|QWORD, y: v10|QWORD) size: QWORD <|@ <|@
      nr   -1  <|@ instruction BRANCH trueDestinationProbability: 1.0 condition: |>| trueDestination: B9 -> B10 falseDestination: B9 -> B22 <|@ <|@
    end_IR
  end_block
  begin_block
    name "B10"
    from_bci -1
    to_bci -1
    predecessors "B9" 
    successors "B11" "B12" 
    xhandlers
    flags 
    probability 4602678819172646912
    begin_IR
      LIR
      nr   -1  <|@ instruction [] = LABEL numbPhis: 0 align: false label: ? <|@ <|@
      nr   -1  <|@ instruction TEST (x: v7|DWORD, y: v7|DWORD) size: DWORD <|@ <|@
      nr   -1  <|@ instruction BRANCH trueDestinationProbability: 0.0 condition: = trueDestination: B10 -> B11 falseDestination: B10 -> B12 <|@ <|@
    end_IR
  end_block
  begin_block
    name "B12"
    from_bci -1
    to_bci -1
    predecessors "B10" 
    successors "B13" 
    xhandlers
    flags 
    probability 4602678819172646912
    begin_IR
      LIR
      nr   -1  <|@ instruction [] = LABEL numbPhis: 0 align: false label: ? <|@ <|@
      nr   -1  <|@ instruction JUMP ~[] destination: B12 -> B13 <|@ <|@
    end_IR
  end_block
  begin_block
    name "B13"
    from_bci -1
    to_bci -1
    predecessors "B8" "B12" 
    successors "B14" 
    xhandlers
    flags 
    probability 4607182418800017408
    begin_IR
      LIR
      nr   -1  <|@ instruction [] = LABEL numbPhis: 0 align: false label: ? <|@ <|@
      nr   -1  <|@ instruction JUMP ~[v2|DWORD, int[0|0x0]] destination: B13 -> B14 <|@ <|@
    end_IR
  end_block
  begin_block
    name "B15"
    from_bci -1
    to_bci -1
    predecessors "B14" 
    successors "B16" "B17" 
    xhandlers
    flags 
    loop_index 0
    loop_depth 1
    probability 4647341739031775896
    begin_IR
      LIR
      nr   -1  <|@ instruction [] = LABEL numbPhis: 0 align: true label: ? <|@ <|@
      nr   -1  <|@ instruction v19|DWORD = MOVSXB [v1|QWORD[.] + v17|DWORD * 1 + 16] size: DWORD <|@ <|@
      nr   -1  <|@ instruction v20|DWORD = MOVSXB v19|DWORD size: DWORD <|@ <|@
      nr   -1  <|@ instruction TEST (x: v20|DWORD, y: v20|DWORD) size: DWORD <|@ <|@
      nr   -1  <|@ instruction BRANCH trueDestinationProbability: 0.0 condition: < trueDestination: B15 -> B16 falseDestination: B15 -> B17 <|@ <|@
    end_IR
  end_block
  begin_block
    name "B17"
    from_bci -1
    to_bci -1
    predecessors "B15" 
    successors "B14" 
    xhandlers
    flags "lle" 
    loop_index 0
    loop_depth 1
    probability 4647341739031775896
    begin_IR
      LIR
      nr   -1  <|@ instruction [] = LABEL numbPhis: 0 align: false label: ? <|@ <|@
      nr   -1  <|@ instruction v21|DWORD = MOVSXB v19|DWORD size: DWORD <|@ <|@
      nr   -1  <|@ instruction MOV (x: [v4|QWORD[.] + v18|DWORD * 2 + 16], y: v21|DWORD) size: WORD <|@ <|@
      nr   -1  <|@ instruction v22|DWORD = INC v18|DWORD size: DWORD <|@ <|@
      nr   -1  <|@ instruction v23|DWORD = INC v17|DWORD size: DWORD <|@ <|@
      nr   -1  <|@ instruction JUMP ~[v23|DWORD, v22|DWORD] destination: B17 -> B14 <|@ <|@
    end_IR
  end_block
  begin_block
    name "B14"
    from_bci -1
    to_bci -1
    predecessors "B13" "B17" 
    successors "B15" "B18" 
    xhandlers
    flags "llh" 
    loop_index 0
    loop_depth 1
    probability 4647359331217820312
    begin_IR
      LIR
      nr   -1  <|@ instruction [v17|DWORD, v18|DWORD] = LABEL numbPhis: 2 align: false label: ? <|@ <|@
      nr   -1  <|@ instruction CMP (x: v8|DWORD, y: v18|DWORD) size: DWORD <|@ <|@
      nr   -1  <|@ instruction BRANCH trueDestinationProbability: 0.9979666244217335 condition: > trueDestination: B14 -> B15 falseDestination: B14 -> B18 <|@ <|@
    end_IR
  end_block
  begin_block
    name "B18"
    from_bci -1
    to_bci -1
    predecessors "B14" 
    successors "B19" "B21" 
    xhandlers
    flags 
    probability 4607182418800017408
    begin_IR
      LIR
      nr   -1  <|@ instruction [] = LABEL numbPhis: 0 align: false label: ? <|@ <|@
      nr   -1  <|@ instruction CMP (x: v5|DWORD, y: v17|DWORD) size: DWORD <|@ <|@
      nr   -1  <|@ instruction BRANCH trueDestinationProbability: 0.0 condition: > trueDestination: B18 -> B19 falseDestination: B18 -> B21 <|@ <|@
    end_IR
  end_block
  begin_block
    name "B21"
    from_bci -1
    to_bci -1
    predecessors "B18" 
    successors 
    xhandlers
    flags 
    probability 4607182418800017408
    begin_IR
      LIR
      nr   -1  <|@ instruction [] = LABEL numbPhis: 0 align: false label: ? <|@ <|@
      nr   -1  <|@ instruction rax|DWORD = MOVE v18|DWORD moveKind: DWORD <|@ <|@
      nr   -1  <|@ instruction RETURN (savedRbp: stack:16|QWORD, value: rax|DWORD) isStub: false thread: r15 scratchForSafepointOnReturn: rcx config: org.graalvm.compiler.hotspot.GraalHotSpotVMConfig@f96b858 <|@ <|@
    end_IR
  end_block
  begin_block
    name "B3"
    from_bci -1
    to_bci -1
    predecessors "B2" 
    successors "B7" 
    xhandlers
    flags 
    probability 4602678819172646912
    begin_IR
      LIR
      nr   -1  <|@ instruction [] = LABEL numbPhis: 0 align: false label: ? <|@ <|@
      nr   -1  <|@ instruction JUMP ~[] destination: B3 -> B7 <|@ <|@
    end_IR
  end_block
  begin_block
    name "B8"
    from_bci -1
    to_bci -1
    predecessors "B7" 
    successors "B13" 
    xhandlers
    flags 
    probability 4602678819172646912
    begin_IR
      LIR
      nr   -1  <|@ instruction [] = LABEL numbPhis: 0 align: false label: ? <|@ <|@
      nr   -1  <|@ instruction JUMP ~[] destination: B8 -> B13 <|@ <|@
    end_IR
  end_block
  begin_block
    name "B24"
    from_bci -1
    to_bci -1
    predecessors "B4" 
    successors "B25" 
    xhandlers
    flags 
    probability 2355382605114769408
    begin_IR
      LIR
      nr   -1  <|@ instruction [] = LABEL numbPhis: 0 align: false label: ? <|@ <|@
      nr   -1  <|@ instruction v29|QWORD[.] = HOTSPOTLOADOBJECTCONSTANT input: Object[d.a@1183312594] <|@ <|@
      nr   -1  <|@ instruction JUMP ~[int[-22555|0xffffffffffffa7e5], v29|QWORD[.]] destination: B24 -> B25 <|@ <|@
    end_IR
  end_block
  begin_block
    name "B25"
    from_bci -1
    to_bci -1
    predecessors "B1" "B24" "B22" "B23" "B11" 
    successors 
    xhandlers
    flags 
    probability 2365515704276353024
    begin_IR
      LIR
      nr   -1  <|@ instruction [v25|DWORD, v26|QWORD[.]] = LABEL numbPhis: 2 align: false label: ? <|@ <|@
      nr   -1  <|@ instruction MOV (x: [r15|QWORD + 668], y: v25|DWORD) size: DWORD <|@ <|@
      nr   -1  <|@ instruction MOV (x: [r15|QWORD + 680], y: v26|QWORD[.]) size: QWORD <|@ <|@
      nr   -1  <|@ st <@st|@sun.nio.cs.UTF_8$Decoder.decode(UTF_8.java:428) [bci: 0]
locals: v0|QWORD[.] v1|QWORD[.] v2|DWORD v3|DWORD v4|QWORD[.] - - - - - - - - - 
>@ <|@ instruction DEOPT info [bci:0] <|@ <|@
    end_IR
  end_block
  begin_block
    name "B11"
    from_bci -1
    to_bci -1
    predecessors "B10" 
    successors "B25" 
    xhandlers
    flags 
    probability 2355382605114769408
    begin_IR
      LIR
      nr   -1  <|@ instruction [] = LABEL numbPhis: 0 align: false label: ? <|@ <|@
      nr   -1  <|@ instruction v28|QWORD[.] = HOTSPOTLOADOBJECTCONSTANT input: Object[d.a@1183312594] <|@ <|@
      nr   -1  <|@ instruction JUMP ~[int[-25115|0xffffffffffff9de5], v28|QWORD[.]] destination: B11 -> B25 <|@ <|@
    end_IR
  end_block
  begin_block
    name "B22"
    from_bci -1
    to_bci -1
    predecessors "B9" 
    successors "B25" 
    xhandlers
    flags 
    probability 2355382605114769408
    begin_IR
      LIR
      nr   -1  <|@ instruction [] = LABEL numbPhis: 0 align: false label: ? <|@ <|@
      nr   -1  <|@ instruction v27|QWORD[.] = HOTSPOTLOADOBJECTCONSTANT input: Object[d.a@1183312594] <|@ <|@
      nr   -1  <|@ instruction JUMP ~[int[-25115|0xffffffffffff9de5], v27|QWORD[.]] destination: B22 -> B25 <|@ <|@
    end_IR
  end_block
  begin_block
    name "B16"
    from_bci -1
    to_bci -1
    predecessors "B15" 
    successors "B20" 
    xhandlers
    flags 
    probability 2355382605114769408
    begin_IR
      LIR
      nr   -1  <|@ instruction [] = LABEL numbPhis: 0 align: false label: ? <|@ <|@
      nr   -1  <|@ instruction JUMP ~[int[-21779|0xffffffffffffaaed]] destination: B16 -> B20 <|@ <|@
    end_IR
  end_block
  begin_block
    name "B20"
    from_bci -1
    to_bci -1
    predecessors "B19" "B16" 
    successors 
    xhandlers
    flags 
    probability 2359886204742139904
    begin_IR
      LIR
      nr   -1  <|@ instruction [v24|DWORD] = LABEL numbPhis: 1 align: false label: ? <|@ <|@
      nr   -1  <|@ instruction MOV (x: [r15|QWORD + 668], y: v24|DWORD) size: DWORD <|@ <|@
      nr   -1  <|@ instruction MOV (x: [r15|QWORD + 680], y: r12|ILLEGAL) size: QWORD <|@ <|@
      nr   -1  <|@ st <@st|@sun.nio.cs.UTF_8$Decoder.decode(UTF_8.java:434) [bci: 20]
locals: v0|QWORD[.] v1|QWORD[.] v17|DWORD - v4|QWORD[.] v5|DWORD v18|DWORD v8|DWORD Object[null] - - - - - 
>@ <|@ instruction DEOPT info [bci:20] <|@ <|@
    end_IR
  end_block
  begin_block
    name "B19"
    from_bci -1
    to_bci -1
    predecessors "B18" 
    successors "B20" 
    xhandlers
    flags 
    probability 2355382605114769408
    begin_IR
      LIR
      nr   -1  <|@ instruction [] = LABEL numbPhis: 0 align: false label: ? <|@ <|@
      nr   -1  <|@ instruction JUMP ~[int[-27155|0xffffffffffff95ed]] destination: B19 -> B20 <|@ <|@
    end_IR
  end_block
  begin_block
    name "B1"
    from_bci -1
    to_bci -1
    predecessors "B0" 
    successors "B25" 
    xhandlers
    flags 
    probability 2355382605114769408
    begin_IR
      LIR
      nr   -1  <|@ instruction [] = LABEL numbPhis: 0 align: false label: ? <|@ <|@
      nr   -1  <|@ instruction v6|QWORD[.] = HOTSPOTLOADOBJECTCONSTANT input: Object[d.a@206089336] <|@ <|@
      nr   -1  <|@ instruction JUMP ~[int[-18187|0xffffffffffffb8f5], v6|QWORD[.]] destination: B1 -> B25 <|@ <|@
    end_IR
  end_block
  begin_block
    name "B23"
    from_bci -1
    to_bci -1
    predecessors "B5" 
    successors "B25" 
    xhandlers
    flags 
    probability 2355382605114769408
    begin_IR
      LIR
      nr   -1  <|@ instruction [] = LABEL numbPhis: 0 align: false label: ? <|@ <|@
      nr   -1  <|@ instruction v30|QWORD[.] = HOTSPOTLOADOBJECTCONSTANT input: Object[d.a@1183312594] <|@ <|@
      nr   -1  <|@ instruction JUMP ~[int[-22555|0xffffffffffffa7e5], v30|QWORD[.]] destination: B23 -> B25 <|@ <|@
    end_IR
  end_block
end_cfg
begin_bytecodes
     0: iload_2       
     1: iload_3       
     2: iadd          
     3: istore        5
     5: iconst_0      
     6: istore        6
     8: iload_3       
     9: aload         4
    11: arraylength   
    12: invokestatic  #22         // java.lang.Math.min:(int, int)int
    15: istore        7
    17: aconst_null   
    18: astore        8
    20: iload         6
    22: iload         7
    24: if_icmpge     51
    27: aload_1       
    28: iload_2       
    29: baload        
    30: iflt          51
    33: aload         4
    35: iload         6
    37: iinc          
    40: aload_1       
    41: iload_2       
    42: iinc          
    45: baload        
    46: i2c           
    47: castore       
    48: goto          20
    51: iload_2       
    52: iload         5
    54: if_icmpge     776
    57: aload_1       
    58: iload_2       
    59: iinc          
    62: baload        
    63: istore        9
    65: iload         9
    67: iflt          84
    70: aload         4
    72: iload         6
    74: iinc          
    77: iload         9
    79: i2c           
    80: castore       
    81: goto          773
    84: iload         9
    86: iconst_5      
    87: ishr          
    88: bipush        -2
    90: if_icmpne     212
    93: iload         9
    95: bipush        30
    97: iand          
    98: ifeq          212
   101: iload_2       
   102: iload         5
   104: if_icmpge     181
   107: aload_1       
   108: iload_2       
   109: iinc          
   112: baload        
   113: istore        10
   115: iload         10
   117: invokestatic  #3          // isNotContinuation:(int)boolean
   120: ifeq          157
   123: aload_0       
   124: invokevirtual #45         // java.nio.charset.CharsetDecoder.malformedInputAction:()java.nio.charset.CodingErrorAction
   127: getstatic     #46         // java.nio.charset.CodingErrorAction.REPLACE:java.nio.charset.CodingErrorAction
   130: if_acmpeq     135
   133: iconst_m1     
   134: ireturn       
   135: aload         4
   137: iload         6
   139: iinc          
   142: aload_0       
   143: invokevirtual #47         // java.nio.charset.CharsetDecoder.replacement:()java.lang.String
   146: iconst_0      
   147: invokevirtual #48         // java.lang.String.charAt:(int)char
   150: castore       
   151: iinc          
   154: goto          51
   157: aload         4
   159: iload         6
   161: iinc          
   164: iload         9
   166: bipush        6
   168: ishl          
   169: iload         10
   171: ixor          
   172: sipush        3968
   175: ixor          
   176: i2c           
   177: castore       
   178: goto          51
   181: aload_0       
   182: invokevirtual #45         // java.nio.charset.CharsetDecoder.malformedInputAction:()java.nio.charset.CodingErrorAction
   185: getstatic     #46         // java.nio.charset.CodingErrorAction.REPLACE:java.nio.charset.CodingErrorAction
   188: if_acmpeq     193
   191: iconst_m1     
   192: ireturn       
   193: aload         4
   195: iload         6
   197: iinc          
   200: aload_0       
   201: invokevirtual #47         // java.nio.charset.CharsetDecoder.replacement:()java.lang.String
   204: iconst_0      
   205: invokevirtual #48         // java.lang.String.charAt:(int)char
   208: castore       
   209: iload         6
   211: ireturn       
   212: iload         9
   214: iconst_4      
   215: ishr          
   216: bipush        -2
   218: if_icmpne     451
   221: iload_2       
   222: iconst_1      
   223: iadd          
   224: iload         5
   226: if_icmpge     384
   229: aload_1       
   230: iload_2       
   231: iinc          
   234: baload        
   235: istore        10
   237: aload_1       
   238: iload_2       
   239: iinc          
   242: baload        
   243: istore        11
   245: iload         9
   247: iload         10
   249: iload         11
   251: invokestatic  #26         // isMalformed3:(int, int, int)boolean
   254: ifeq          312
   257: aload_0       
   258: invokevirtual #45         // java.nio.charset.CharsetDecoder.malformedInputAction:()java.nio.charset.CodingErrorAction
   261: getstatic     #46         // java.nio.charset.CodingErrorAction.REPLACE:java.nio.charset.CodingErrorAction
   264: if_acmpeq     269
   267: iconst_m1     
   268: ireturn       
   269: aload         4
   271: iload         6
   273: iinc          
   276: aload_0       
   277: invokevirtual #47         // java.nio.charset.CharsetDecoder.replacement:()java.lang.String
   280: iconst_0      
   281: invokevirtual #48         // java.lang.String.charAt:(int)char
   284: castore       
   285: iinc          
   288: aload         8
   290: aload_1       
   291: iload_2       
   292: invokestatic  #49         // getByteBuffer:(java.nio.ByteBuffer, byte[], int)java.nio.ByteBuffer
   295: astore        8
   297: iload_2       
   298: aload         8
   300: iconst_3      
   301: invokestatic  #9          // malformedN:(java.nio.ByteBuffer, int)java.nio.charset.CoderResult
   304: invokevirtual #50         // java.nio.charset.CoderResult.length:()int
   307: iadd          
   308: istore_2      
   309: goto          51
   312: iload         9
   314: bipush        12
   316: ishl          
   317: iload         10
   319: bipush        6
   321: ishl          
   322: ixor          
   323: iload         11
   325: ldc           #30         // -123008
   327: ixor          
   328: ixor          
   329: i2c           
   330: istore        12
   332: iload         12
   334: invokestatic  #28         // java.lang.Character.isSurrogate:(char)boolean
   337: ifeq          371
   340: aload_0       
   341: invokevirtual #45         // java.nio.charset.CharsetDecoder.malformedInputAction:()java.nio.charset.CodingErrorAction
   344: getstatic     #46         // java.nio.charset.CodingErrorAction.REPLACE:java.nio.charset.CodingErrorAction
   347: if_acmpeq     352
   350: iconst_m1     
   351: ireturn       
   352: aload         4
   354: iload         6
   356: iinc          
   359: aload_0       
   360: invokevirtual #47         // java.nio.charset.CharsetDecoder.replacement:()java.lang.String
   363: iconst_0      
   364: invokevirtual #48         // java.lang.String.charAt:(int)char
   367: castore       
   368: goto          381
   371: aload         4
   373: iload         6
   375: iinc          
   378: iload         12
   380: castore       
   381: goto          51
   384: aload_0       
   385: invokevirtual #45         // java.nio.charset.CharsetDecoder.malformedInputAction:()java.nio.charset.CodingErrorAction
   388: getstatic     #46         // java.nio.charset.CodingErrorAction.REPLACE:java.nio.charset.CodingErrorAction
   391: if_acmpeq     396
   394: iconst_m1     
   395: ireturn       
   396: iload_2       
   397: iload         5
   399: if_icmpge     432
   402: iload         9
   404: aload_1       
   405: iload_2       
   406: baload        
   407: invokestatic  #25         // isMalformed3_2:(int, int)boolean
   410: ifeq          432
   413: aload         4
   415: iload         6
   417: iinc          
   420: aload_0       
   421: invokevirtual #47         // java.nio.charset.CharsetDecoder.replacement:()java.lang.String
   424: iconst_0      
   425: invokevirtual #48         // java.lang.String.charAt:(int)char
   428: castore       
   429: goto          51
   432: aload         4
   434: iload         6
   436: iinc          
   439: aload_0       
   440: invokevirtual #47         // java.nio.charset.CharsetDecoder.replacement:()java.lang.String
   443: iconst_0      
   444: invokevirtual #48         // java.lang.String.charAt:(int)char
   447: castore       
   448: iload         6
   450: ireturn       
   451: iload         9
   453: iconst_3      
   454: ishr          
   455: bipush        -2
   457: if_icmpne     745
   460: iload_2       
   461: iconst_2      
   462: iadd          
   463: iload         5
   465: if_icmpge     621
   468: aload_1       
   469: iload_2       
   470: iinc          
   473: baload        
   474: istore        10
   476: aload_1       
   477: iload_2       
   478: iinc          
   481: baload        
   482: istore        11
   484: aload_1       
   485: iload_2       
   486: iinc          
   489: baload        
   490: istore        12
   492: iload         9
   494: bipush        18
   496: ishl          
   497: iload         10
   499: bipush        12
   501: ishl          
   502: ixor          
   503: iload         11
   505: bipush        6
   507: ishl          
   508: ixor          
   509: iload         12
   511: ldc           #34         // 3678080
   513: ixor          
   514: ixor          
   515: istore        13
   517: iload         10
   519: iload         11
   521: iload         12
   523: invokestatic  #31         // isMalformed4:(int, int, int)boolean
   526: ifne          537
   529: iload         13
   531: invokestatic  #32         // java.lang.Character.isSupplementaryCodePoint:(int)boolean
   534: ifne          592
   537: aload_0       
   538: invokevirtual #45         // java.nio.charset.CharsetDecoder.malformedInputAction:()java.nio.charset.CodingErrorAction
   541: getstatic     #46         // java.nio.charset.CodingErrorAction.REPLACE:java.nio.charset.CodingErrorAction
   544: if_acmpeq     549
   547: iconst_m1     
   548: ireturn       
   549: aload         4
   551: iload         6
   553: iinc          
   556: aload_0       
   557: invokevirtual #47         // java.nio.charset.CharsetDecoder.replacement:()java.lang.String
   560: iconst_0      
   561: invokevirtual #48         // java.lang.String.charAt:(int)char
   564: castore       
   565: iinc          
   568: aload         8
   570: aload_1       
   571: iload_2       
   572: invokestatic  #49         // getByteBuffer:(java.nio.ByteBuffer, byte[], int)java.nio.ByteBuffer
   575: astore        8
   577: iload_2       
   578: aload         8
   580: iconst_4      
   581: invokestatic  #9          // malformedN:(java.nio.ByteBuffer, int)java.nio.charset.CoderResult
   584: invokevirtual #50         // java.nio.charset.CoderResult.length:()int
   587: iadd          
   588: istore_2      
   589: goto          51
   592: aload         4
   594: iload         6
   596: iinc          
   599: iload         13
   601: invokestatic  #33         // java.lang.Character.highSurrogate:(int)char
   604: castore       
   605: aload         4
   607: iload         6
   609: iinc          
   612: iload         13
   614: invokestatic  #34         // java.lang.Character.lowSurrogate:(int)char
   617: castore       
   618: goto          51
   621: aload_0       
   622: invokevirtual #45         // java.nio.charset.CharsetDecoder.malformedInputAction:()java.nio.charset.CodingErrorAction
   625: getstatic     #46         // java.nio.charset.CodingErrorAction.REPLACE:java.nio.charset.CodingErrorAction
   628: if_acmpeq     633
   631: iconst_m1     
   632: ireturn       
   633: iload         9
   635: sipush        255
   638: iand          
   639: istore        9
   641: iload         9
   643: sipush        244
   646: if_icmpgt     670
   649: iload_2       
   650: iload         5
   652: if_icmpge     689
   655: iload         9
   657: aload_1       
   658: iload_2       
   659: baload        
   660: sipush        255
   663: iand          
   664: invokestatic  #29         // isMalformed4_2:(int, int)boolean
   667: ifeq          689
   670: aload         4
   672: iload         6
   674: iinc          
   677: aload_0       
   678: invokevirtual #47         // java.nio.charset.CharsetDecoder.replacement:()java.lang.String
   681: iconst_0      
   682: invokevirtual #48         // java.lang.String.charAt:(int)char
   685: castore       
   686: goto          51
   689: iinc          
   692: iload_2       
   693: iload         5
   695: if_icmpge     726
   698: aload_1       
   699: iload_2       
   700: baload        
   701: invokestatic  #30         // isMalformed4_3:(int)boolean
   704: ifeq          726
   707: aload         4
   709: iload         6
   711: iinc          
   714: aload_0       
   715: invokevirtual #47         // java.nio.charset.CharsetDecoder.replacement:()java.lang.String
   718: iconst_0      
   719: invokevirtual #48         // java.lang.String.charAt:(int)char
   722: castore       
   723: goto          51
   726: aload         4
   728: iload         6
   730: iinc          
   733: aload_0       
   734: invokevirtual #47         // java.nio.charset.CharsetDecoder.replacement:()java.lang.String
   737: iconst_0      
   738: invokevirtual #48         // java.lang.String.charAt:(int)char
   741: castore       
   742: iload         6
   744: ireturn       
   745: aload_0       
   746: invokevirtual #45         // java.nio.charset.CharsetDecoder.malformedInputAction:()java.nio.charset.CodingErrorAction
   749: getstatic     #46         // java.nio.charset.CodingErrorAction.REPLACE:java.nio.charset.CodingErrorAction
   752: if_acmpeq     757
   755: iconst_m1     
   756: ireturn       
   757: aload         4
   759: iload         6
   761: iinc          
   764: aload_0       
   765: invokevirtual #47         // java.nio.charset.CharsetDecoder.replacement:()java.lang.String
   768: iconst_0      
   769: invokevirtual #48         // java.lang.String.charAt:(int)char
   772: castore       
   773: goto          51
   776: iload         6
   778: ireturn       
   <|@
end_bytecodes
begin_cfg
  name "After AllocationStage"
  begin_block
    name "B0"
    from_bci -1
    to_bci -1
    predecessors 
    successors "B1" "B2" 
    xhandlers
    flags 
    probability 4607182418800017408
    begin_IR
      LIR
      nr    0  <|@ instruction [rsi|QWORD[.], rdx|QWORD[.], rcx|DWORD, r8|DWORD, r9|QWORD[.], rbp|QWORD] = LABEL numbPhis: 0 align: false label: ? <|@ <|@
      nr    2  <|@ instruction stack:16|QWORD = MOVE rbp|QWORD moveKind: QWORD <|@ <|@
      nr    4  <|@ instruction [] = HOTSPOTLOCKSTACK frameMapBuilder: org.graalvm.compiler.lir.amd64.AMD64FrameMapBuilder@51ff0cce slotKind: QWORD <|@ <|@
      nr   16  <|@ instruction r10|DWORD = ADD (x: rcx|DWORD, y: r8|DWORD) size: DWORD <|@ <|@
      nr   18  <|@ instruction TEST (x: rdx|QWORD[.], y: rdx|QWORD[.]) size: QWORD <|@ <|@
      nr   20  <|@ instruction BRANCH trueDestinationProbability: 0.0 condition: = trueDestination: B0 -> B1 falseDestination: B0 -> B2 <|@ <|@
    end_IR
  end_block
  begin_block
    name "B2"
    from_bci -1
    to_bci -1
    predecessors "B0" 
    successors "B3" "B4" 
    xhandlers
    flags 
    probability 4607182418800017408
    begin_IR
      LIR
      nr   22  <|@ instruction [] = LABEL numbPhis: 0 align: false label: ? <|@ <|@
      nr   24  <|@ st <@st|@reference-map: [rdx:0, rsi:0, r9:0]
live-base-pointers: []
sun.nio.cs.UTF_8$Decoder.decode(UTF_8.java:428) [bci: 0]
locals: rsi|QWORD[.] rdx|QWORD[.] rcx|DWORD r8|DWORD r9|QWORD[.] - - - - - - - - - 
>@ <|@ instruction rax|DWORD = MOV [r9|QWORD[.] + 12] size: DWORD state [bci:0] <|@ <|@
      nr   26  <|@ instruction CMP (x: r8|DWORD, y: rax|DWORD) size: DWORD <|@ <|@
      nr   28  <|@ instruction r11|DWORD = CMOVE (falseValue: r8|DWORD, ~trueValue: rax|DWORD) condition: > <|@ <|@
      nr   30  <|@ instruction rbx|QWORD = MOVSXD r11|DWORD size: QWORD <|@ <|@
      nr   32  <|@ instruction rbx|QWORD = DEC rbx|QWORD size: QWORD <|@ <|@
      nr   34  <|@ instruction CMP r11|DWORD y: 1 size: DWORD <|@ <|@
      nr   36  <|@ instruction BRANCH trueDestinationProbability: 0.5 condition: < trueDestination: B2 -> B3 falseDestination: B2 -> B4 <|@ <|@
    end_IR
  end_block
  begin_block
    name "B4"
    from_bci -1
    to_bci -1
    predecessors "B2" 
    successors "B5" "B24" 
    xhandlers
    flags 
    probability 4602678819172646912
    begin_IR
      LIR
      nr   38  <|@ instruction [] = LABEL numbPhis: 0 align: false label: ? <|@ <|@
      nr   40  <|@ instruction rdi|DWORD = MOV [rdx|QWORD[.] + 12] size: DWORD <|@ <|@
      nr   42  <|@ instruction rbp|QWORD = MOVSXD rcx|DWORD size: QWORD <|@ <|@
      nr   44  <|@ instruction rbp|QWORD = ADD (x: rbp|QWORD, y: rbx|QWORD) size: QWORD <|@ <|@
      nr   46  <|@ instruction r13|QWORD = MOV rdi|DWORD size: DWORD <|@ <|@
      nr   48  <|@ instruction CMP (x: r13|QWORD, y: rbp|QWORD) size: QWORD <|@ <|@
      nr   50  <|@ instruction BRANCH trueDestinationProbability: 1.0 condition: |>| trueDestination: B4 -> B5 falseDestination: B4 -> B24 <|@ <|@
    end_IR
  end_block
  begin_block
    name "B5"
    from_bci -1
    to_bci -1
    predecessors "B4" 
    successors "B6" "B23" 
    xhandlers
    flags 
    probability 4602678819172646912
    begin_IR
      LIR
      nr   52  <|@ instruction [] = LABEL numbPhis: 0 align: false label: ? <|@ <|@
      nr   54  <|@ instruction CMP (x: rdi|DWORD, y: rcx|DWORD) size: DWORD <|@ <|@
      nr   56  <|@ instruction BRANCH trueDestinationProbability: 1.0 condition: |>| trueDestination: B5 -> B6 falseDestination: B5 -> B23 <|@ <|@
    end_IR
  end_block
  begin_block
    name "B6"
    from_bci -1
    to_bci -1
    predecessors "B5" 
    successors "B7" 
    xhandlers
    flags 
    probability 4602678819172646912
    begin_IR
      LIR
      nr   58  <|@ instruction [] = LABEL numbPhis: 0 align: false label: ? <|@ <|@
      nr   60  <|@ instruction JUMP ~[] destination: B6 -> B7 <|@ <|@
    end_IR
  end_block
  begin_block
    name "B7"
    from_bci -1
    to_bci -1
    predecessors "B3" "B6" 
    successors "B8" "B9" 
    xhandlers
    flags 
    probability 4607182418800017408
    begin_IR
      LIR
      nr   66  <|@ instruction [] = LABEL numbPhis: 0 align: false label: ? <|@ <|@
      nr   68  <|@ instruction CMP r11|DWORD y: 1 size: DWORD <|@ <|@
      nr   70  <|@ instruction BRANCH trueDestinationProbability: 0.5 condition: < trueDestination: B7 -> B8 falseDestination: B7 -> B9 <|@ <|@
    end_IR
  end_block
  begin_block
    name "B9"
    from_bci -1
    to_bci -1
    predecessors "B7" 
    successors "B10" "B22" 
    xhandlers
    flags 
    probability 4602678819172646912
    begin_IR
      LIR
      nr   72  <|@ instruction [] = LABEL numbPhis: 0 align: false label: ? <|@ <|@
      nr   74  <|@ instruction rdi|QWORD = MOV rax|DWORD size: DWORD <|@ <|@
      nr   76  <|@ instruction CMP (x: rdi|QWORD, y: rbx|QWORD) size: QWORD <|@ <|@
      nr   78  <|@ instruction BRANCH trueDestinationProbability: 1.0 condition: |>| trueDestination: B9 -> B10 falseDestination: B9 -> B22 <|@ <|@
    end_IR
  end_block
  begin_block
    name "B10"
    from_bci -1
    to_bci -1
    predecessors "B9" 
    successors "B11" "B12" 
    xhandlers
    flags 
    probability 4602678819172646912
    begin_IR
      LIR
      nr   80  <|@ instruction [] = LABEL numbPhis: 0 align: false label: ? <|@ <|@
      nr   82  <|@ instruction TEST (x: rax|DWORD, y: rax|DWORD) size: DWORD <|@ <|@
      nr   84  <|@ instruction BRANCH trueDestinationProbability: 0.0 condition: = trueDestination: B10 -> B11 falseDestination: B10 -> B12 <|@ <|@
    end_IR
  end_block
  begin_block
    name "B12"
    from_bci -1
    to_bci -1
    predecessors "B10" 
    successors "B13" 
    xhandlers
    flags 
    probability 4602678819172646912
    begin_IR
      LIR
      nr   86  <|@ instruction [] = LABEL numbPhis: 0 align: false label: ? <|@ <|@
      nr   88  <|@ instruction JUMP ~[] destination: B12 -> B13 <|@ <|@
    end_IR
  end_block
  begin_block
    name "B13"
    from_bci -1
    to_bci -1
    predecessors "B8" "B12" 
    successors "B14" 
    xhandlers
    flags 
    probability 4607182418800017408
    begin_IR
      LIR
      nr   94  <|@ instruction [] = LABEL numbPhis: 0 align: false label: ? <|@ <|@
      nr   -1  <|@ instruction r8|DWORD = MOVE rcx|DWORD moveKind: DWORD // MoveResolver resolve mapping <|@ <|@
      nr   -1  <|@ instruction rcx|DWORD = MOVE input: int[0|0x0] // MoveResolver resolve mapping <|@ <|@
      nr   96  <|@ instruction JUMP ~[] destination: B13 -> B14 <|@ <|@
    end_IR
  end_block
  begin_block
    name "B15"
    from_bci -1
    to_bci -1
    predecessors "B14" 
    successors "B16" "B17" 
    xhandlers
    flags 
    loop_index 0
    loop_depth 1
    probability 4647341739031775896
    begin_IR
      LIR
      nr  104  <|@ instruction [] = LABEL numbPhis: 0 align: true label: ? <|@ <|@
      nr  106  <|@ instruction rax|DWORD = MOVSXB [rdx|QWORD[.] + r8|DWORD * 1 + 16] size: DWORD <|@ <|@
      nr  108  <|@ instruction rbx|DWORD = MOVSXB rax|DWORD size: DWORD <|@ <|@
      nr  110  <|@ instruction TEST (x: rbx|DWORD, y: rbx|DWORD) size: DWORD <|@ <|@
      nr  112  <|@ instruction BRANCH trueDestinationProbability: 0.0 condition: < trueDestination: B15 -> B16 falseDestination: B15 -> B17 <|@ <|@
    end_IR
  end_block
  begin_block
    name "B17"
    from_bci -1
    to_bci -1
    predecessors "B15" 
    successors "B14" 
    xhandlers
    flags "lle" 
    loop_index 0
    loop_depth 1
    probability 4647341739031775896
    begin_IR
      LIR
      nr  114  <|@ instruction [] = LABEL numbPhis: 0 align: false label: ? <|@ <|@
      nr  116  <|@ instruction rax|DWORD = MOVSXB rax|DWORD size: DWORD <|@ <|@
      nr  118  <|@ instruction MOV (x: [r9|QWORD[.] + rcx|DWORD * 2 + 16], y: rax|DWORD) size: WORD <|@ <|@
      nr  120  <|@ instruction rcx|DWORD = INC rcx|DWORD size: DWORD <|@ <|@
      nr  122  <|@ instruction r8|DWORD = INC r8|DWORD size: DWORD <|@ <|@
      nr  124  <|@ instruction JUMP ~[] destination: B17 -> B14 <|@ <|@
    end_IR
  end_block
  begin_block
    name "B14"
    from_bci -1
    to_bci -1
    predecessors "B13" "B17" 
    successors "B15" "B18" 
    xhandlers
    flags "llh" 
    loop_index 0
    loop_depth 1
    probability 4647359331217820312
    begin_IR
      LIR
      nr   98  <|@ instruction [] = LABEL numbPhis: 2 align: false label: ? <|@ <|@
      nr  100  <|@ instruction CMP (x: r11|DWORD, y: rcx|DWORD) size: DWORD <|@ <|@
      nr  102  <|@ instruction BRANCH trueDestinationProbability: 0.9979666244217335 condition: > trueDestination: B14 -> B15 falseDestination: B14 -> B18 <|@ <|@
    end_IR
  end_block
  begin_block
    name "B18"
    from_bci -1
    to_bci -1
    predecessors "B14" 
    successors "B19" "B21" 
    xhandlers
    flags 
    probability 4607182418800017408
    begin_IR
      LIR
      nr  126  <|@ instruction [] = LABEL numbPhis: 0 align: false label: ? <|@ <|@
      nr  128  <|@ instruction CMP (x: r10|DWORD, y: r8|DWORD) size: DWORD <|@ <|@
      nr  130  <|@ instruction BRANCH trueDestinationProbability: 0.0 condition: > trueDestination: B18 -> B19 falseDestination: B18 -> B21 <|@ <|@
    end_IR
  end_block
  begin_block
    name "B21"
    from_bci -1
    to_bci -1
    predecessors "B18" 
    successors 
    xhandlers
    flags 
    probability 4607182418800017408
    begin_IR
      LIR
      nr  132  <|@ instruction [] = LABEL numbPhis: 0 align: false label: ? <|@ <|@
      nr  134  <|@ instruction rax|DWORD = MOVE rcx|DWORD moveKind: DWORD <|@ <|@
      nr  136  <|@ instruction RETURN (savedRbp: stack:16|QWORD, value: rax|DWORD) isStub: false thread: r15 scratchForSafepointOnReturn: rcx config: org.graalvm.compiler.hotspot.GraalHotSpotVMConfig@f96b858 <|@ <|@
    end_IR
  end_block
  begin_block
    name "B3"
    from_bci -1
    to_bci -1
    predecessors "B2" 
    successors "B7" 
    xhandlers
    flags 
    probability 4602678819172646912
    begin_IR
      LIR
      nr   62  <|@ instruction [] = LABEL numbPhis: 0 align: false label: ? <|@ <|@
      nr   64  <|@ instruction JUMP ~[] destination: B3 -> B7 <|@ <|@
    end_IR
  end_block
  begin_block
    name "B8"
    from_bci -1
    to_bci -1
    predecessors "B7" 
    successors "B13" 
    xhandlers
    flags 
    probability 4602678819172646912
    begin_IR
      LIR
      nr   90  <|@ instruction [] = LABEL numbPhis: 0 align: false label: ? <|@ <|@
      nr   92  <|@ instruction JUMP ~[] destination: B8 -> B13 <|@ <|@
    end_IR
  end_block
  begin_block
    name "B24"
    from_bci -1
    to_bci -1
    predecessors "B4" 
    successors "B25" 
    xhandlers
    flags 
    probability 2355382605114769408
    begin_IR
      LIR
      nr  172  <|@ instruction [] = LABEL numbPhis: 0 align: false label: ? <|@ <|@
      nr  174  <|@ instruction r10|QWORD[.] = HOTSPOTLOADOBJECTCONSTANT input: Object[d.a@1183312594] <|@ <|@
      nr   -1  <|@ instruction r11|QWORD[.] = MOVE r10|QWORD[.] moveKind: QWORD // MoveResolver resolve mapping <|@ <|@
      nr   -1  <|@ instruction r10|DWORD = MOVE input: int[-22555|0xffffffffffffa7e5] // MoveResolver resolve mapping <|@ <|@
      nr  176  <|@ instruction JUMP ~[] destination: B24 -> B25 <|@ <|@
    end_IR
  end_block
  begin_block
    name "B25"
    from_bci -1
    to_bci -1
    predecessors "B1" "B24" "B22" "B23" "B11" 
    successors 
    xhandlers
    flags 
    probability 2365515704276353024
    begin_IR
      LIR
      nr  184  <|@ instruction [] = LABEL numbPhis: 2 align: false label: ? <|@ <|@
      nr  186  <|@ instruction MOV (x: [r15|QWORD + 668], y: r10|DWORD) size: DWORD <|@ <|@
      nr  188  <|@ instruction MOV (x: [r15|QWORD + 680], y: r11|QWORD[.]) size: QWORD <|@ <|@
      nr  190  <|@ st <@st|@reference-map: [rdx:0, rsi:0, r9:0]
live-base-pointers: []
sun.nio.cs.UTF_8$Decoder.decode(UTF_8.java:428) [bci: 0]
locals: rsi|QWORD[.] rdx|QWORD[.] rcx|DWORD r8|DWORD r9|QWORD[.] - - - - - - - - - 
>@ <|@ instruction DEOPT info [bci:0] <|@ <|@
    end_IR
  end_block
  begin_block
    name "B11"
    from_bci -1
    to_bci -1
    predecessors "B10" 
    successors "B25" 
    xhandlers
    flags 
    probability 2355382605114769408
    begin_IR
      LIR
      nr  144  <|@ instruction [] = LABEL numbPhis: 0 align: false label: ? <|@ <|@
      nr  146  <|@ instruction r10|QWORD[.] = HOTSPOTLOADOBJECTCONSTANT input: Object[d.a@1183312594] <|@ <|@
      nr   -1  <|@ instruction r11|QWORD[.] = MOVE r10|QWORD[.] moveKind: QWORD // MoveResolver resolve mapping <|@ <|@
      nr   -1  <|@ instruction r10|DWORD = MOVE input: int[-25115|0xffffffffffff9de5] // MoveResolver resolve mapping <|@ <|@
      nr  148  <|@ instruction JUMP ~[] destination: B11 -> B25 <|@ <|@
    end_IR
  end_block
  begin_block
    name "B22"
    from_bci -1
    to_bci -1
    predecessors "B9" 
    successors "B25" 
    xhandlers
    flags 
    probability 2355382605114769408
    begin_IR
      LIR
      nr  166  <|@ instruction [] = LABEL numbPhis: 0 align: false label: ? <|@ <|@
      nr  168  <|@ instruction r10|QWORD[.] = HOTSPOTLOADOBJECTCONSTANT input: Object[d.a@1183312594] <|@ <|@
      nr   -1  <|@ instruction r11|QWORD[.] = MOVE r10|QWORD[.] moveKind: QWORD // MoveResolver resolve mapping <|@ <|@
      nr   -1  <|@ instruction r10|DWORD = MOVE input: int[-25115|0xffffffffffff9de5] // MoveResolver resolve mapping <|@ <|@
      nr  170  <|@ instruction JUMP ~[] destination: B22 -> B25 <|@ <|@
    end_IR
  end_block
  begin_block
    name "B16"
    from_bci -1
    to_bci -1
    predecessors "B15" 
    successors "B20" 
    xhandlers
    flags 
    probability 2355382605114769408
    begin_IR
      LIR
      nr  150  <|@ instruction [] = LABEL numbPhis: 0 align: false label: ? <|@ <|@
      nr   -1  <|@ instruction rbx|DWORD = MOVE input: int[-21779|0xffffffffffffaaed] // MoveResolver resolve mapping <|@ <|@
      nr  152  <|@ instruction JUMP ~[] destination: B16 -> B20 <|@ <|@
    end_IR
  end_block
  begin_block
    name "B20"
    from_bci -1
    to_bci -1
    predecessors "B19" "B16" 
    successors 
    xhandlers
    flags 
    probability 2359886204742139904
    begin_IR
      LIR
      nr  158  <|@ instruction [] = LABEL numbPhis: 1 align: false label: ? <|@ <|@
      nr  160  <|@ instruction MOV (x: [r15|QWORD + 668], y: rbx|DWORD) size: DWORD <|@ <|@
      nr  162  <|@ instruction MOV (x: [r15|QWORD + 680], y: r12|ILLEGAL) size: QWORD <|@ <|@
      nr  164  <|@ st <@st|@reference-map: [rdx:0, rsi:0, r9:0]
live-base-pointers: []
sun.nio.cs.UTF_8$Decoder.decode(UTF_8.java:434) [bci: 20]
locals: rsi|QWORD[.] rdx|QWORD[.] r8|DWORD - r9|QWORD[.] r10|DWORD rcx|DWORD r11|DWORD Object[null] - - - - - 
>@ <|@ instruction DEOPT info [bci:20] <|@ <|@
    end_IR
  end_block
  begin_block
    name "B19"
    from_bci -1
    to_bci -1
    predecessors "B18" 
    successors "B20" 
    xhandlers
    flags 
    probability 2355382605114769408
    begin_IR
      LIR
      nr  154  <|@ instruction [] = LABEL numbPhis: 0 align: false label: ? <|@ <|@
      nr   -1  <|@ instruction rbx|DWORD = MOVE input: int[-27155|0xffffffffffff95ed] // MoveResolver resolve mapping <|@ <|@
      nr  156  <|@ instruction JUMP ~[] destination: B19 -> B20 <|@ <|@
    end_IR
  end_block
  begin_block
    name "B1"
    from_bci -1
    to_bci -1
    predecessors "B0" 
    successors "B25" 
    xhandlers
    flags 
    probability 2355382605114769408
    begin_IR
      LIR
      nr  178  <|@ instruction [] = LABEL numbPhis: 0 align: false label: ? <|@ <|@
      nr  180  <|@ instruction r10|QWORD[.] = HOTSPOTLOADOBJECTCONSTANT input: Object[d.a@206089336] <|@ <|@
      nr   -1  <|@ instruction r11|QWORD[.] = MOVE r10|QWORD[.] moveKind: QWORD // MoveResolver resolve mapping <|@ <|@
      nr   -1  <|@ instruction r10|DWORD = MOVE input: int[-18187|0xffffffffffffb8f5] // MoveResolver resolve mapping <|@ <|@
      nr  182  <|@ instruction JUMP ~[] destination: B1 -> B25 <|@ <|@
    end_IR
  end_block
  begin_block
    name "B23"
    from_bci -1
    to_bci -1
    predecessors "B5" 
    successors "B25" 
    xhandlers
    flags 
    probability 2355382605114769408
    begin_IR
      LIR
      nr  138  <|@ instruction [] = LABEL numbPhis: 0 align: false label: ? <|@ <|@
      nr  140  <|@ instruction r10|QWORD[.] = HOTSPOTLOADOBJECTCONSTANT input: Object[d.a@1183312594] <|@ <|@
      nr   -1  <|@ instruction r11|QWORD[.] = MOVE r10|QWORD[.] moveKind: QWORD // MoveResolver resolve mapping <|@ <|@
      nr   -1  <|@ instruction r10|DWORD = MOVE input: int[-22555|0xffffffffffffa7e5] // MoveResolver resolve mapping <|@ <|@
      nr  142  <|@ instruction JUMP ~[] destination: B23 -> B25 <|@ <|@
    end_IR
  end_block
end_cfg
begin_bytecodes
     0: iload_2       
     1: iload_3       
     2: iadd          
     3: istore        5
     5: iconst_0      
     6: istore        6
     8: iload_3       
     9: aload         4
    11: arraylength   
    12: invokestatic  #22         // java.lang.Math.min:(int, int)int
    15: istore        7
    17: aconst_null   
    18: astore        8
    20: iload         6
    22: iload         7
    24: if_icmpge     51
    27: aload_1       
    28: iload_2       
    29: baload        
    30: iflt          51
    33: aload         4
    35: iload         6
    37: iinc          
    40: aload_1       
    41: iload_2       
    42: iinc          
    45: baload        
    46: i2c           
    47: castore       
    48: goto          20
    51: iload_2       
    52: iload         5
    54: if_icmpge     776
    57: aload_1       
    58: iload_2       
    59: iinc          
    62: baload        
    63: istore        9
    65: iload         9
    67: iflt          84
    70: aload         4
    72: iload         6
    74: iinc          
    77: iload         9
    79: i2c           
    80: castore       
    81: goto          773
    84: iload         9
    86: iconst_5      
    87: ishr          
    88: bipush        -2
    90: if_icmpne     212
    93: iload         9
    95: bipush        30
    97: iand          
    98: ifeq          212
   101: iload_2       
   102: iload         5
   104: if_icmpge     181
   107: aload_1       
   108: iload_2       
   109: iinc          
   112: baload        
   113: istore        10
   115: iload         10
   117: invokestatic  #3          // isNotContinuation:(int)boolean
   120: ifeq          157
   123: aload_0       
   124: invokevirtual #45         // java.nio.charset.CharsetDecoder.malformedInputAction:()java.nio.charset.CodingErrorAction
   127: getstatic     #46         // java.nio.charset.CodingErrorAction.REPLACE:java.nio.charset.CodingErrorAction
   130: if_acmpeq     135
   133: iconst_m1     
   134: ireturn       
   135: aload         4
   137: iload         6
   139: iinc          
   142: aload_0       
   143: invokevirtual #47         // java.nio.charset.CharsetDecoder.replacement:()java.lang.String
   146: iconst_0      
   147: invokevirtual #48         // java.lang.String.charAt:(int)char
   150: castore       
   151: iinc          
   154: goto          51
   157: aload         4
   159: iload         6
   161: iinc          
   164: iload         9
   166: bipush        6
   168: ishl          
   169: iload         10
   171: ixor          
   172: sipush        3968
   175: ixor          
   176: i2c           
   177: castore       
   178: goto          51
   181: aload_0       
   182: invokevirtual #45         // java.nio.charset.CharsetDecoder.malformedInputAction:()java.nio.charset.CodingErrorAction
   185: getstatic     #46         // java.nio.charset.CodingErrorAction.REPLACE:java.nio.charset.CodingErrorAction
   188: if_acmpeq     193
   191: iconst_m1     
   192: ireturn       
   193: aload         4
   195: iload         6
   197: iinc          
   200: aload_0       
   201: invokevirtual #47         // java.nio.charset.CharsetDecoder.replacement:()java.lang.String
   204: iconst_0      
   205: invokevirtual #48         // java.lang.String.charAt:(int)char
   208: castore       
   209: iload         6
   211: ireturn       
   212: iload         9
   214: iconst_4      
   215: ishr          
   216: bipush        -2
   218: if_icmpne     451
   221: iload_2       
   222: iconst_1      
   223: iadd          
   224: iload         5
   226: if_icmpge     384
   229: aload_1       
   230: iload_2       
   231: iinc          
   234: baload        
   235: istore        10
   237: aload_1       
   238: iload_2       
   239: iinc          
   242: baload        
   243: istore        11
   245: iload         9
   247: iload         10
   249: iload         11
   251: invokestatic  #26         // isMalformed3:(int, int, int)boolean
   254: ifeq          312
   257: aload_0       
   258: invokevirtual #45         // java.nio.charset.CharsetDecoder.malformedInputAction:()java.nio.charset.CodingErrorAction
   261: getstatic     #46         // java.nio.charset.CodingErrorAction.REPLACE:java.nio.charset.CodingErrorAction
   264: if_acmpeq     269
   267: iconst_m1     
   268: ireturn       
   269: aload         4
   271: iload         6
   273: iinc          
   276: aload_0       
   277: invokevirtual #47         // java.nio.charset.CharsetDecoder.replacement:()java.lang.String
   280: iconst_0      
   281: invokevirtual #48         // java.lang.String.charAt:(int)char
   284: castore       
   285: iinc          
   288: aload         8
   290: aload_1       
   291: iload_2       
   292: invokestatic  #49         // getByteBuffer:(java.nio.ByteBuffer, byte[], int)java.nio.ByteBuffer
   295: astore        8
   297: iload_2       
   298: aload         8
   300: iconst_3      
   301: invokestatic  #9          // malformedN:(java.nio.ByteBuffer, int)java.nio.charset.CoderResult
   304: invokevirtual #50         // java.nio.charset.CoderResult.length:()int
   307: iadd          
   308: istore_2      
   309: goto          51
   312: iload         9
   314: bipush        12
   316: ishl          
   317: iload         10
   319: bipush        6
   321: ishl          
   322: ixor          
   323: iload         11
   325: ldc           #30         // -123008
   327: ixor          
   328: ixor          
   329: i2c           
   330: istore        12
   332: iload         12
   334: invokestatic  #28         // java.lang.Character.isSurrogate:(char)boolean
   337: ifeq          371
   340: aload_0       
   341: invokevirtual #45         // java.nio.charset.CharsetDecoder.malformedInputAction:()java.nio.charset.CodingErrorAction
   344: getstatic     #46         // java.nio.charset.CodingErrorAction.REPLACE:java.nio.charset.CodingErrorAction
   347: if_acmpeq     352
   350: iconst_m1     
   351: ireturn       
   352: aload         4
   354: iload         6
   356: iinc          
   359: aload_0       
   360: invokevirtual #47         // java.nio.charset.CharsetDecoder.replacement:()java.lang.String
   363: iconst_0      
   364: invokevirtual #48         // java.lang.String.charAt:(int)char
   367: castore       
   368: goto          381
   371: aload         4
   373: iload         6
   375: iinc          
   378: iload         12
   380: castore       
   381: goto          51
   384: aload_0       
   385: invokevirtual #45         // java.nio.charset.CharsetDecoder.malformedInputAction:()java.nio.charset.CodingErrorAction
   388: getstatic     #46         // java.nio.charset.CodingErrorAction.REPLACE:java.nio.charset.CodingErrorAction
   391: if_acmpeq     396
   394: iconst_m1     
   395: ireturn       
   396: iload_2       
   397: iload         5
   399: if_icmpge     432
   402: iload         9
   404: aload_1       
   405: iload_2       
   406: baload        
   407: invokestatic  #25         // isMalformed3_2:(int, int)boolean
   410: ifeq          432
   413: aload         4
   415: iload         6
   417: iinc          
   420: aload_0       
   421: invokevirtual #47         // java.nio.charset.CharsetDecoder.replacement:()java.lang.String
   424: iconst_0      
   425: invokevirtual #48         // java.lang.String.charAt:(int)char
   428: castore       
   429: goto          51
   432: aload         4
   434: iload         6
   436: iinc          
   439: aload_0       
   440: invokevirtual #47         // java.nio.charset.CharsetDecoder.replacement:()java.lang.String
   443: iconst_0      
   444: invokevirtual #48         // java.lang.String.charAt:(int)char
   447: castore       
   448: iload         6
   450: ireturn       
   451: iload         9
   453: iconst_3      
   454: ishr          
   455: bipush        -2
   457: if_icmpne     745
   460: iload_2       
   461: iconst_2      
   462: iadd          
   463: iload         5
   465: if_icmpge     621
   468: aload_1       
   469: iload_2       
   470: iinc          
   473: baload        
   474: istore        10
   476: aload_1       
   477: iload_2       
   478: iinc          
   481: baload        
   482: istore        11
   484: aload_1       
   485: iload_2       
   486: iinc          
   489: baload        
   490: istore        12
   492: iload         9
   494: bipush        18
   496: ishl          
   497: iload         10
   499: bipush        12
   501: ishl          
   502: ixor          
   503: iload         11
   505: bipush        6
   507: ishl          
   508: ixor          
   509: iload         12
   511: ldc           #34         // 3678080
   513: ixor          
   514: ixor          
   515: istore        13
   517: iload         10
   519: iload         11
   521: iload         12
   523: invokestatic  #31         // isMalformed4:(int, int, int)boolean
   526: ifne          537
   529: iload         13
   531: invokestatic  #32         // java.lang.Character.isSupplementaryCodePoint:(int)boolean
   534: ifne          592
   537: aload_0       
   538: invokevirtual #45         // java.nio.charset.CharsetDecoder.malformedInputAction:()java.nio.charset.CodingErrorAction
   541: getstatic     #46         // java.nio.charset.CodingErrorAction.REPLACE:java.nio.charset.CodingErrorAction
   544: if_acmpeq     549
   547: iconst_m1     
   548: ireturn       
   549: aload         4
   551: iload         6
   553: iinc          
   556: aload_0       
   557: invokevirtual #47         // java.nio.charset.CharsetDecoder.replacement:()java.lang.String
   560: iconst_0      
   561: invokevirtual #48         // java.lang.String.charAt:(int)char
   564: castore       
   565: iinc          
   568: aload         8
   570: aload_1       
   571: iload_2       
   572: invokestatic  #49         // getByteBuffer:(java.nio.ByteBuffer, byte[], int)java.nio.ByteBuffer
   575: astore        8
   577: iload_2       
   578: aload         8
   580: iconst_4      
   581: invokestatic  #9          // malformedN:(java.nio.ByteBuffer, int)java.nio.charset.CoderResult
   584: invokevirtual #50         // java.nio.charset.CoderResult.length:()int
   587: iadd          
   588: istore_2      
   589: goto          51
   592: aload         4
   594: iload         6
   596: iinc          
   599: iload         13
   601: invokestatic  #33         // java.lang.Character.highSurrogate:(int)char
   604: castore       
   605: aload         4
   607: iload         6
   609: iinc          
   612: iload         13
   614: invokestatic  #34         // java.lang.Character.lowSurrogate:(int)char
   617: castore       
   618: goto          51
   621: aload_0       
   622: invokevirtual #45         // java.nio.charset.CharsetDecoder.malformedInputAction:()java.nio.charset.CodingErrorAction
   625: getstatic     #46         // java.nio.charset.CodingErrorAction.REPLACE:java.nio.charset.CodingErrorAction
   628: if_acmpeq     633
   631: iconst_m1     
   632: ireturn       
   633: iload         9
   635: sipush        255
   638: iand          
   639: istore        9
   641: iload         9
   643: sipush        244
   646: if_icmpgt     670
   649: iload_2       
   650: iload         5
   652: if_icmpge     689
   655: iload         9
   657: aload_1       
   658: iload_2       
   659: baload        
   660: sipush        255
   663: iand          
   664: invokestatic  #29         // isMalformed4_2:(int, int)boolean
   667: ifeq          689
   670: aload         4
   672: iload         6
   674: iinc          
   677: aload_0       
   678: invokevirtual #47         // java.nio.charset.CharsetDecoder.replacement:()java.lang.String
   681: iconst_0      
   682: invokevirtual #48         // java.lang.String.charAt:(int)char
   685: castore       
   686: goto          51
   689: iinc          
   692: iload_2       
   693: iload         5
   695: if_icmpge     726
   698: aload_1       
   699: iload_2       
   700: baload        
   701: invokestatic  #30         // isMalformed4_3:(int)boolean
   704: ifeq          726
   707: aload         4
   709: iload         6
   711: iinc          
   714: aload_0       
   715: invokevirtual #47         // java.nio.charset.CharsetDecoder.replacement:()java.lang.String
   718: iconst_0      
   719: invokevirtual #48         // java.lang.String.charAt:(int)char
   722: castore       
   723: goto          51
   726: aload         4
   728: iload         6
   730: iinc          
   733: aload_0       
   734: invokevirtual #47         // java.nio.charset.CharsetDecoder.replacement:()java.lang.String
   737: iconst_0      
   738: invokevirtual #48         // java.lang.String.charAt:(int)char
   741: castore       
   742: iload         6
   744: ireturn       
   745: aload_0       
   746: invokevirtual #45         // java.nio.charset.CharsetDecoder.malformedInputAction:()java.nio.charset.CodingErrorAction
   749: getstatic     #46         // java.nio.charset.CodingErrorAction.REPLACE:java.nio.charset.CodingErrorAction
   752: if_acmpeq     757
   755: iconst_m1     
   756: ireturn       
   757: aload         4
   759: iload         6
   761: iinc          
   764: aload_0       
   765: invokevirtual #47         // java.nio.charset.CharsetDecoder.replacement:()java.lang.String
   768: iconst_0      
   769: invokevirtual #48         // java.lang.String.charAt:(int)char
   772: castore       
   773: goto          51
   776: iload         6
   778: ireturn       
   <|@
end_bytecodes
begin_cfg
  name "After PostAllocationOptimizationStage"
  begin_block
    name "B0"
    from_bci -1
    to_bci -1
    predecessors 
    successors "B1" "B2" 
    xhandlers
    flags 
    probability 4607182418800017408
    begin_IR
      LIR
      nr    0  <|@ instruction [rsi|QWORD[.], rdx|QWORD[.], rcx|DWORD, r8|DWORD, r9|QWORD[.], rbp|QWORD] = LABEL numbPhis: 0 align: false label: ? <|@ <|@
      nr    2  <|@ instruction stack:16|QWORD = MOVE rbp|QWORD moveKind: QWORD <|@ <|@
      nr    4  <|@ instruction [] = HOTSPOTLOCKSTACK frameMapBuilder: org.graalvm.compiler.lir.amd64.AMD64FrameMapBuilder@51ff0cce slotKind: QWORD <|@ <|@
      nr   16  <|@ instruction r10|DWORD = ADD (x: rcx|DWORD, y: r8|DWORD) size: DWORD <|@ <|@
      nr   18  <|@ instruction TEST (x: rdx|QWORD[.], y: rdx|QWORD[.]) size: QWORD <|@ <|@
      nr   20  <|@ instruction BRANCH trueDestinationProbability: 0.0 condition: = trueDestination: B0 -> B1 falseDestination: B0 -> B2 <|@ <|@
    end_IR
  end_block
  begin_block
    name "B2"
    from_bci -1
    to_bci -1
    predecessors "B0" 
    successors "B7" "B4" 
    xhandlers
    flags 
    probability 4607182418800017408
    begin_IR
      LIR
      nr   22  <|@ instruction [] = LABEL numbPhis: 0 align: false label: ? <|@ <|@
      nr   24  <|@ st <@st|@reference-map: [rdx:0, rsi:0, r9:0]
live-base-pointers: []
sun.nio.cs.UTF_8$Decoder.decode(UTF_8.java:428) [bci: 0]
locals: rsi|QWORD[.] rdx|QWORD[.] rcx|DWORD r8|DWORD r9|QWORD[.] - - - - - - - - - 
>@ <|@ instruction rax|DWORD = MOV [r9|QWORD[.] + 12] size: DWORD state [bci:0] <|@ <|@
      nr   26  <|@ instruction CMP (x: r8|DWORD, y: rax|DWORD) size: DWORD <|@ <|@
      nr   28  <|@ instruction r11|DWORD = CMOVE (falseValue: r8|DWORD, ~trueValue: rax|DWORD) condition: > <|@ <|@
      nr   30  <|@ instruction rbx|QWORD = MOVSXD r11|DWORD size: QWORD <|@ <|@
      nr   32  <|@ instruction rbx|QWORD = DEC rbx|QWORD size: QWORD <|@ <|@
      nr   34  <|@ instruction CMP r11|DWORD y: 1 size: DWORD <|@ <|@
      nr   36  <|@ instruction BRANCH trueDestinationProbability: 0.5 condition: < trueDestination: B2 -> B7 falseDestination: B2 -> B4 <|@ <|@
    end_IR
  end_block
  begin_block
    name "B4"
    from_bci -1
    to_bci -1
    predecessors "B2" 
    successors "B5" "B24" 
    xhandlers
    flags 
    probability 4602678819172646912
    begin_IR
      LIR
      nr   38  <|@ instruction [] = LABEL numbPhis: 0 align: false label: ? <|@ <|@
      nr   40  <|@ instruction rdi|DWORD = MOV [rdx|QWORD[.] + 12] size: DWORD <|@ <|@
      nr   42  <|@ instruction rbp|QWORD = MOVSXD rcx|DWORD size: QWORD <|@ <|@
      nr   44  <|@ instruction rbp|QWORD = ADD (x: rbp|QWORD, y: rbx|QWORD) size: QWORD <|@ <|@
      nr   46  <|@ instruction r13|QWORD = MOV rdi|DWORD size: DWORD <|@ <|@
      nr   48  <|@ instruction CMP (x: r13|QWORD, y: rbp|QWORD) size: QWORD <|@ <|@
      nr   50  <|@ instruction BRANCH trueDestinationProbability: 1.0 condition: |>| trueDestination: B4 -> B5 falseDestination: B4 -> B24 <|@ <|@
    end_IR
  end_block
  begin_block
    name "B5"
    from_bci -1
    to_bci -1
    predecessors "B4" 
    successors "B7" "B23" 
    xhandlers
    flags 
    probability 4602678819172646912
    begin_IR
      LIR
      nr   52  <|@ instruction [] = LABEL numbPhis: 0 align: false label: ? <|@ <|@
      nr   54  <|@ instruction CMP (x: rdi|DWORD, y: rcx|DWORD) size: DWORD <|@ <|@
      nr   56  <|@ instruction BRANCH trueDestinationProbability: 1.0 condition: |>| trueDestination: B5 -> B7 falseDestination: B5 -> B23 <|@ <|@
    end_IR
  end_block
  begin_block
    name "B7"
    from_bci -1
    to_bci -1
    predecessors "B2" "B5" 
    successors "B13" "B9" 
    xhandlers
    flags 
    probability 4607182418800017408
    begin_IR
      LIR
      nr   66  <|@ instruction [] = LABEL numbPhis: 0 align: false label: ? <|@ <|@
      nr   68  <|@ instruction CMP r11|DWORD y: 1 size: DWORD <|@ <|@
      nr   70  <|@ instruction BRANCH trueDestinationProbability: 0.5 condition: < trueDestination: B7 -> B13 falseDestination: B7 -> B9 <|@ <|@
    end_IR
  end_block
  begin_block
    name "B9"
    from_bci -1
    to_bci -1
    predecessors "B7" 
    successors "B10" "B22" 
    xhandlers
    flags 
    probability 4602678819172646912
    begin_IR
      LIR
      nr   72  <|@ instruction [] = LABEL numbPhis: 0 align: false label: ? <|@ <|@
      nr   74  <|@ instruction rdi|QWORD = MOV rax|DWORD size: DWORD <|@ <|@
      nr   76  <|@ instruction CMP (x: rdi|QWORD, y: rbx|QWORD) size: QWORD <|@ <|@
      nr   78  <|@ instruction BRANCH trueDestinationProbability: 1.0 condition: |>| trueDestination: B9 -> B10 falseDestination: B9 -> B22 <|@ <|@
    end_IR
  end_block
  begin_block
    name "B10"
    from_bci -1
    to_bci -1
    predecessors "B9" 
    successors "B11" "B13" 
    xhandlers
    flags 
    probability 4602678819172646912
    begin_IR
      LIR
      nr   80  <|@ instruction [] = LABEL numbPhis: 0 align: false label: ? <|@ <|@
      nr   82  <|@ instruction TEST (x: rax|DWORD, y: rax|DWORD) size: DWORD <|@ <|@
      nr   84  <|@ instruction BRANCH trueDestinationProbability: 0.0 condition: = trueDestination: B10 -> B11 falseDestination: B10 -> B13 <|@ <|@
    end_IR
  end_block
  begin_block
    name "B13"
    from_bci -1
    to_bci -1
    predecessors "B7" "B10" 
    successors "B14" 
    xhandlers
    flags 
    probability 4607182418800017408
    begin_IR
      LIR
      nr   94  <|@ instruction [] = LABEL numbPhis: 0 align: false label: ? <|@ <|@
      nr   -1  <|@ instruction r8|DWORD = MOVE rcx|DWORD moveKind: DWORD // MoveResolver resolve mapping <|@ <|@
      nr   -1  <|@ instruction rcx|DWORD = MOVE input: int[0|0x0] // MoveResolver resolve mapping <|@ <|@
      nr   96  <|@ instruction JUMP ~[] destination: B13 -> B14 <|@ <|@
    end_IR
  end_block
  begin_block
    name "B15"
    from_bci -1
    to_bci -1
    predecessors "B14" 
    successors "B16" "B17" 
    xhandlers
    flags 
    loop_index 0
    loop_depth 1
    probability 4647341739031775896
    begin_IR
      LIR
      nr  104  <|@ instruction [] = LABEL numbPhis: 0 align: true label: ? <|@ <|@
      nr  106  <|@ instruction rax|DWORD = MOVSXB [rdx|QWORD[.] + r8|DWORD * 1 + 16] size: DWORD <|@ <|@
      nr  108  <|@ instruction rbx|DWORD = MOVSXB rax|DWORD size: DWORD <|@ <|@
      nr  110  <|@ instruction TEST (x: rbx|DWORD, y: rbx|DWORD) size: DWORD <|@ <|@
      nr  112  <|@ instruction BRANCH trueDestinationProbability: 0.0 condition: < trueDestination: B15 -> B16 falseDestination: B15 -> B17 <|@ <|@
    end_IR
  end_block
  begin_block
    name "B17"
    from_bci -1
    to_bci -1
    predecessors "B15" 
    successors "B14" 
    xhandlers
    flags "lle" 
    loop_index 0
    loop_depth 1
    probability 4647341739031775896
    begin_IR
      LIR
      nr  114  <|@ instruction [] = LABEL numbPhis: 0 align: false label: ? <|@ <|@
      nr  116  <|@ instruction rax|DWORD = MOVSXB rax|DWORD size: DWORD <|@ <|@
      nr  118  <|@ instruction MOV (x: [r9|QWORD[.] + rcx|DWORD * 2 + 16], y: rax|DWORD) size: WORD <|@ <|@
      nr  120  <|@ instruction rcx|DWORD = INC rcx|DWORD size: DWORD <|@ <|@
      nr  122  <|@ instruction r8|DWORD = INC r8|DWORD size: DWORD <|@ <|@
      nr  124  <|@ instruction JUMP ~[] destination: B17 -> B14 <|@ <|@
    end_IR
  end_block
  begin_block
    name "B14"
    from_bci -1
    to_bci -1
    predecessors "B13" "B17" 
    successors "B15" "B18" 
    xhandlers
    flags "llh" 
    loop_index 0
    loop_depth 1
    probability 4647359331217820312
    begin_IR
      LIR
      nr   98  <|@ instruction [] = LABEL numbPhis: 2 align: false label: ? <|@ <|@
      nr  100  <|@ instruction CMP (x: r11|DWORD, y: rcx|DWORD) size: DWORD <|@ <|@
      nr  102  <|@ instruction BRANCH trueDestinationProbability: 0.9979666244217335 condition: > trueDestination: B14 -> B15 falseDestination: B14 -> B18 <|@ <|@
    end_IR
  end_block
  begin_block
    name "B18"
    from_bci -1
    to_bci -1
    predecessors "B14" 
    successors "B19" "B21" 
    xhandlers
    flags 
    probability 4607182418800017408
    begin_IR
      LIR
      nr  126  <|@ instruction [] = LABEL numbPhis: 0 align: false label: ? <|@ <|@
      nr  128  <|@ instruction CMP (x: r10|DWORD, y: r8|DWORD) size: DWORD <|@ <|@
      nr  130  <|@ instruction BRANCH trueDestinationProbability: 0.0 condition: > trueDestination: B18 -> B19 falseDestination: B18 -> B21 <|@ <|@
    end_IR
  end_block
  begin_block
    name "B21"
    from_bci -1
    to_bci -1
    predecessors "B18" 
    successors 
    xhandlers
    flags 
    probability 4607182418800017408
    begin_IR
      LIR
      nr  132  <|@ instruction [] = LABEL numbPhis: 0 align: false label: ? <|@ <|@
      nr  134  <|@ instruction rax|DWORD = MOVE rcx|DWORD moveKind: DWORD <|@ <|@
      nr  136  <|@ instruction RETURN (savedRbp: stack:16|QWORD, value: rax|DWORD) isStub: false thread: r15 scratchForSafepointOnReturn: rcx config: org.graalvm.compiler.hotspot.GraalHotSpotVMConfig@f96b858 <|@ <|@
    end_IR
  end_block
  begin_block
    name "B24"
    from_bci -1
    to_bci -1
    predecessors "B4" 
    successors "B25" 
    xhandlers
    flags 
    probability 2355382605114769408
    begin_IR
      LIR
      nr  172  <|@ instruction [] = LABEL numbPhis: 0 align: false label: ? <|@ <|@
      nr  174  <|@ instruction r10|QWORD[.] = HOTSPOTLOADOBJECTCONSTANT input: Object[d.a@1183312594] <|@ <|@
      nr   -1  <|@ instruction r11|QWORD[.] = MOVE r10|QWORD[.] moveKind: QWORD // MoveResolver resolve mapping <|@ <|@
      nr   -1  <|@ instruction r10|DWORD = MOVE input: int[-22555|0xffffffffffffa7e5] // MoveResolver resolve mapping <|@ <|@
      nr  176  <|@ instruction JUMP ~[] destination: B24 -> B25 <|@ <|@
    end_IR
  end_block
  begin_block
    name "B25"
    from_bci -1
    to_bci -1
    predecessors "B1" "B24" "B22" "B23" "B11" 
    successors 
    xhandlers
    flags 
    probability 2365515704276353024
    begin_IR
      LIR
      nr  184  <|@ instruction [] = LABEL numbPhis: 2 align: false label: ? <|@ <|@
      nr  186  <|@ instruction MOV (x: [r15|QWORD + 668], y: r10|DWORD) size: DWORD <|@ <|@
      nr  188  <|@ instruction MOV (x: [r15|QWORD + 680], y: r11|QWORD[.]) size: QWORD <|@ <|@
      nr  190  <|@ st <@st|@reference-map: [rdx:0, rsi:0, r9:0]
live-base-pointers: []
sun.nio.cs.UTF_8$Decoder.decode(UTF_8.java:428) [bci: 0]
locals: rsi|QWORD[.] rdx|QWORD[.] rcx|DWORD r8|DWORD r9|QWORD[.] - - - - - - - - - 
>@ <|@ instruction DEOPT info [bci:0] <|@ <|@
    end_IR
  end_block
  begin_block
    name "B11"
    from_bci -1
    to_bci -1
    predecessors "B10" 
    successors "B25" 
    xhandlers
    flags 
    probability 2355382605114769408
    begin_IR
      LIR
      nr  144  <|@ instruction [] = LABEL numbPhis: 0 align: false label: ? <|@ <|@
      nr  146  <|@ instruction r10|QWORD[.] = HOTSPOTLOADOBJECTCONSTANT input: Object[d.a@1183312594] <|@ <|@
      nr   -1  <|@ instruction r11|QWORD[.] = MOVE r10|QWORD[.] moveKind: QWORD // MoveResolver resolve mapping <|@ <|@
      nr   -1  <|@ instruction r10|DWORD = MOVE input: int[-25115|0xffffffffffff9de5] // MoveResolver resolve mapping <|@ <|@
      nr  148  <|@ instruction JUMP ~[] destination: B11 -> B25 <|@ <|@
    end_IR
  end_block
  begin_block
    name "B22"
    from_bci -1
    to_bci -1
    predecessors "B9" 
    successors "B25" 
    xhandlers
    flags 
    probability 2355382605114769408
    begin_IR
      LIR
      nr  166  <|@ instruction [] = LABEL numbPhis: 0 align: false label: ? <|@ <|@
      nr  168  <|@ instruction r10|QWORD[.] = HOTSPOTLOADOBJECTCONSTANT input: Object[d.a@1183312594] <|@ <|@
      nr   -1  <|@ instruction r11|QWORD[.] = MOVE r10|QWORD[.] moveKind: QWORD // MoveResolver resolve mapping <|@ <|@
      nr   -1  <|@ instruction r10|DWORD = MOVE input: int[-25115|0xffffffffffff9de5] // MoveResolver resolve mapping <|@ <|@
      nr  170  <|@ instruction JUMP ~[] destination: B22 -> B25 <|@ <|@
    end_IR
  end_block
  begin_block
    name "B16"
    from_bci -1
    to_bci -1
    predecessors "B15" 
    successors "B20" 
    xhandlers
    flags 
    probability 2355382605114769408
    begin_IR
      LIR
      nr  150  <|@ instruction [] = LABEL numbPhis: 0 align: false label: ? <|@ <|@
      nr   -1  <|@ instruction rbx|DWORD = MOVE input: int[-21779|0xffffffffffffaaed] // MoveResolver resolve mapping <|@ <|@
      nr  152  <|@ instruction JUMP ~[] destination: B16 -> B20 <|@ <|@
    end_IR
  end_block
  begin_block
    name "B20"
    from_bci -1
    to_bci -1
    predecessors "B19" "B16" 
    successors 
    xhandlers
    flags 
    probability 2359886204742139904
    begin_IR
      LIR
      nr  158  <|@ instruction [] = LABEL numbPhis: 1 align: false label: ? <|@ <|@
      nr  160  <|@ instruction MOV (x: [r15|QWORD + 668], y: rbx|DWORD) size: DWORD <|@ <|@
      nr  162  <|@ instruction MOV (x: [r15|QWORD + 680], y: r12|ILLEGAL) size: QWORD <|@ <|@
      nr  164  <|@ st <@st|@reference-map: [rdx:0, rsi:0, r9:0]
live-base-pointers: []
sun.nio.cs.UTF_8$Decoder.decode(UTF_8.java:434) [bci: 20]
locals: rsi|QWORD[.] rdx|QWORD[.] r8|DWORD - r9|QWORD[.] r10|DWORD rcx|DWORD r11|DWORD Object[null] - - - - - 
>@ <|@ instruction DEOPT info [bci:20] <|@ <|@
    end_IR
  end_block
  begin_block
    name "B19"
    from_bci -1
    to_bci -1
    predecessors "B18" 
    successors "B20" 
    xhandlers
    flags 
    probability 2355382605114769408
    begin_IR
      LIR
      nr  154  <|@ instruction [] = LABEL numbPhis: 0 align: false label: ? <|@ <|@
      nr   -1  <|@ instruction rbx|DWORD = MOVE input: int[-27155|0xffffffffffff95ed] // MoveResolver resolve mapping <|@ <|@
      nr  156  <|@ instruction JUMP ~[] destination: B19 -> B20 <|@ <|@
    end_IR
  end_block
  begin_block
    name "B1"
    from_bci -1
    to_bci -1
    predecessors "B0" 
    successors "B25" 
    xhandlers
    flags 
    probability 2355382605114769408
    begin_IR
      LIR
      nr  178  <|@ instruction [] = LABEL numbPhis: 0 align: false label: ? <|@ <|@
      nr  180  <|@ instruction r10|QWORD[.] = HOTSPOTLOADOBJECTCONSTANT input: Object[d.a@206089336] <|@ <|@
      nr   -1  <|@ instruction r11|QWORD[.] = MOVE r10|QWORD[.] moveKind: QWORD // MoveResolver resolve mapping <|@ <|@
      nr   -1  <|@ instruction r10|DWORD = MOVE input: int[-18187|0xffffffffffffb8f5] // MoveResolver resolve mapping <|@ <|@
      nr  182  <|@ instruction JUMP ~[] destination: B1 -> B25 <|@ <|@
    end_IR
  end_block
  begin_block
    name "B23"
    from_bci -1
    to_bci -1
    predecessors "B5" 
    successors "B25" 
    xhandlers
    flags 
    probability 2355382605114769408
    begin_IR
      LIR
      nr  138  <|@ instruction [] = LABEL numbPhis: 0 align: false label: ? <|@ <|@
      nr  140  <|@ instruction r10|QWORD[.] = HOTSPOTLOADOBJECTCONSTANT input: Object[d.a@1183312594] <|@ <|@
      nr   -1  <|@ instruction r11|QWORD[.] = MOVE r10|QWORD[.] moveKind: QWORD // MoveResolver resolve mapping <|@ <|@
      nr   -1  <|@ instruction r10|DWORD = MOVE input: int[-22555|0xffffffffffffa7e5] // MoveResolver resolve mapping <|@ <|@
      nr  142  <|@ instruction JUMP ~[] destination: B23 -> B25 <|@ <|@
    end_IR
  end_block
end_cfg
begin_bytecodes
     0: iload_2       
     1: iload_3       
     2: iadd          
     3: istore        5
     5: iconst_0      
     6: istore        6
     8: iload_3       
     9: aload         4
    11: arraylength   
    12: invokestatic  #22         // java.lang.Math.min:(int, int)int
    15: istore        7
    17: aconst_null   
    18: astore        8
    20: iload         6
    22: iload         7
    24: if_icmpge     51
    27: aload_1       
    28: iload_2       
    29: baload        
    30: iflt          51
    33: aload         4
    35: iload         6
    37: iinc          
    40: aload_1       
    41: iload_2       
    42: iinc          
    45: baload        
    46: i2c           
    47: castore       
    48: goto          20
    51: iload_2       
    52: iload         5
    54: if_icmpge     776
    57: aload_1       
    58: iload_2       
    59: iinc          
    62: baload        
    63: istore        9
    65: iload         9
    67: iflt          84
    70: aload         4
    72: iload         6
    74: iinc          
    77: iload         9
    79: i2c           
    80: castore       
    81: goto          773
    84: iload         9
    86: iconst_5      
    87: ishr          
    88: bipush        -2
    90: if_icmpne     212
    93: iload         9
    95: bipush        30
    97: iand          
    98: ifeq          212
   101: iload_2       
   102: iload         5
   104: if_icmpge     181
   107: aload_1       
   108: iload_2       
   109: iinc          
   112: baload        
   113: istore        10
   115: iload         10
   117: invokestatic  #3          // isNotContinuation:(int)boolean
   120: ifeq          157
   123: aload_0       
   124: invokevirtual #45         // java.nio.charset.CharsetDecoder.malformedInputAction:()java.nio.charset.CodingErrorAction
   127: getstatic     #46         // java.nio.charset.CodingErrorAction.REPLACE:java.nio.charset.CodingErrorAction
   130: if_acmpeq     135
   133: iconst_m1     
   134: ireturn       
   135: aload         4
   137: iload         6
   139: iinc          
   142: aload_0       
   143: invokevirtual #47         // java.nio.charset.CharsetDecoder.replacement:()java.lang.String
   146: iconst_0      
   147: invokevirtual #48         // java.lang.String.charAt:(int)char
   150: castore       
   151: iinc          
   154: goto          51
   157: aload         4
   159: iload         6
   161: iinc          
   164: iload         9
   166: bipush        6
   168: ishl          
   169: iload         10
   171: ixor          
   172: sipush        3968
   175: ixor          
   176: i2c           
   177: castore       
   178: goto          51
   181: aload_0       
   182: invokevirtual #45         // java.nio.charset.CharsetDecoder.malformedInputAction:()java.nio.charset.CodingErrorAction
   185: getstatic     #46         // java.nio.charset.CodingErrorAction.REPLACE:java.nio.charset.CodingErrorAction
   188: if_acmpeq     193
   191: iconst_m1     
   192: ireturn       
   193: aload         4
   195: iload         6
   197: iinc          
   200: aload_0       
   201: invokevirtual #47         // java.nio.charset.CharsetDecoder.replacement:()java.lang.String
   204: iconst_0      
   205: invokevirtual #48         // java.lang.String.charAt:(int)char
   208: castore       
   209: iload         6
   211: ireturn       
   212: iload         9
   214: iconst_4      
   215: ishr          
   216: bipush        -2
   218: if_icmpne     451
   221: iload_2       
   222: iconst_1      
   223: iadd          
   224: iload         5
   226: if_icmpge     384
   229: aload_1       
   230: iload_2       
   231: iinc          
   234: baload        
   235: istore        10
   237: aload_1       
   238: iload_2       
   239: iinc          
   242: baload        
   243: istore        11
   245: iload         9
   247: iload         10
   249: iload         11
   251: invokestatic  #26         // isMalformed3:(int, int, int)boolean
   254: ifeq          312
   257: aload_0       
   258: invokevirtual #45         // java.nio.charset.CharsetDecoder.malformedInputAction:()java.nio.charset.CodingErrorAction
   261: getstatic     #46         // java.nio.charset.CodingErrorAction.REPLACE:java.nio.charset.CodingErrorAction
   264: if_acmpeq     269
   267: iconst_m1     
   268: ireturn       
   269: aload         4
   271: iload         6
   273: iinc          
   276: aload_0       
   277: invokevirtual #47         // java.nio.charset.CharsetDecoder.replacement:()java.lang.String
   280: iconst_0      
   281: invokevirtual #48         // java.lang.String.charAt:(int)char
   284: castore       
   285: iinc          
   288: aload         8
   290: aload_1       
   291: iload_2       
   292: invokestatic  #49         // getByteBuffer:(java.nio.ByteBuffer, byte[], int)java.nio.ByteBuffer
   295: astore        8
   297: iload_2       
   298: aload         8
   300: iconst_3      
   301: invokestatic  #9          // malformedN:(java.nio.ByteBuffer, int)java.nio.charset.CoderResult
   304: invokevirtual #50         // java.nio.charset.CoderResult.length:()int
   307: iadd          
   308: istore_2      
   309: goto          51
   312: iload         9
   314: bipush        12
   316: ishl          
   317: iload         10
   319: bipush        6
   321: ishl          
   322: ixor          
   323: iload         11
   325: ldc           #30         // -123008
   327: ixor          
   328: ixor          
   329: i2c           
   330: istore        12
   332: iload         12
   334: invokestatic  #28         // java.lang.Character.isSurrogate:(char)boolean
   337: ifeq          371
   340: aload_0       
   341: invokevirtual #45         // java.nio.charset.CharsetDecoder.malformedInputAction:()java.nio.charset.CodingErrorAction
   344: getstatic     #46         // java.nio.charset.CodingErrorAction.REPLACE:java.nio.charset.CodingErrorAction
   347: if_acmpeq     352
   350: iconst_m1     
   351: ireturn       
   352: aload         4
   354: iload         6
   356: iinc          
   359: aload_0       
   360: invokevirtual #47         // java.nio.charset.CharsetDecoder.replacement:()java.lang.String
   363: iconst_0      
   364: invokevirtual #48         // java.lang.String.charAt:(int)char
   367: castore       
   368: goto          381
   371: aload         4
   373: iload         6
   375: iinc          
   378: iload         12
   380: castore       
   381: goto          51
   384: aload_0       
   385: invokevirtual #45         // java.nio.charset.CharsetDecoder.malformedInputAction:()java.nio.charset.CodingErrorAction
   388: getstatic     #46         // java.nio.charset.CodingErrorAction.REPLACE:java.nio.charset.CodingErrorAction
   391: if_acmpeq     396
   394: iconst_m1     
   395: ireturn       
   396: iload_2       
   397: iload         5
   399: if_icmpge     432
   402: iload         9
   404: aload_1       
   405: iload_2       
   406: baload        
   407: invokestatic  #25         // isMalformed3_2:(int, int)boolean
   410: ifeq          432
   413: aload         4
   415: iload         6
   417: iinc          
   420: aload_0       
   421: invokevirtual #47         // java.nio.charset.CharsetDecoder.replacement:()java.lang.String
   424: iconst_0      
   425: invokevirtual #48         // java.lang.String.charAt:(int)char
   428: castore       
   429: goto          51
   432: aload         4
   434: iload         6
   436: iinc          
   439: aload_0       
   440: invokevirtual #47         // java.nio.charset.CharsetDecoder.replacement:()java.lang.String
   443: iconst_0      
   444: invokevirtual #48         // java.lang.String.charAt:(int)char
   447: castore       
   448: iload         6
   450: ireturn       
   451: iload         9
   453: iconst_3      
   454: ishr          
   455: bipush        -2
   457: if_icmpne     745
   460: iload_2       
   461: iconst_2      
   462: iadd          
   463: iload         5
   465: if_icmpge     621
   468: aload_1       
   469: iload_2       
   470: iinc          
   473: baload        
   474: istore        10
   476: aload_1       
   477: iload_2       
   478: iinc          
   481: baload        
   482: istore        11
   484: aload_1       
   485: iload_2       
   486: iinc          
   489: baload        
   490: istore        12
   492: iload         9
   494: bipush        18
   496: ishl          
   497: iload         10
   499: bipush        12
   501: ishl          
   502: ixor          
   503: iload         11
   505: bipush        6
   507: ishl          
   508: ixor          
   509: iload         12
   511: ldc           #34         // 3678080
   513: ixor          
   514: ixor          
   515: istore        13
   517: iload         10
   519: iload         11
   521: iload         12
   523: invokestatic  #31         // isMalformed4:(int, int, int)boolean
   526: ifne          537
   529: iload         13
   531: invokestatic  #32         // java.lang.Character.isSupplementaryCodePoint:(int)boolean
   534: ifne          592
   537: aload_0       
   538: invokevirtual #45         // java.nio.charset.CharsetDecoder.malformedInputAction:()java.nio.charset.CodingErrorAction
   541: getstatic     #46         // java.nio.charset.CodingErrorAction.REPLACE:java.nio.charset.CodingErrorAction
   544: if_acmpeq     549
   547: iconst_m1     
   548: ireturn       
   549: aload         4
   551: iload         6
   553: iinc          
   556: aload_0       
   557: invokevirtual #47         // java.nio.charset.CharsetDecoder.replacement:()java.lang.String
   560: iconst_0      
   561: invokevirtual #48         // java.lang.String.charAt:(int)char
   564: castore       
   565: iinc          
   568: aload         8
   570: aload_1       
   571: iload_2       
   572: invokestatic  #49         // getByteBuffer:(java.nio.ByteBuffer, byte[], int)java.nio.ByteBuffer
   575: astore        8
   577: iload_2       
   578: aload         8
   580: iconst_4      
   581: invokestatic  #9          // malformedN:(java.nio.ByteBuffer, int)java.nio.charset.CoderResult
   584: invokevirtual #50         // java.nio.charset.CoderResult.length:()int
   587: iadd          
   588: istore_2      
   589: goto          51
   592: aload         4
   594: iload         6
   596: iinc          
   599: iload         13
   601: invokestatic  #33         // java.lang.Character.highSurrogate:(int)char
   604: castore       
   605: aload         4
   607: iload         6
   609: iinc          
   612: iload         13
   614: invokestatic  #34         // java.lang.Character.lowSurrogate:(int)char
   617: castore       
   618: goto          51
   621: aload_0       
   622: invokevirtual #45         // java.nio.charset.CharsetDecoder.malformedInputAction:()java.nio.charset.CodingErrorAction
   625: getstatic     #46         // java.nio.charset.CodingErrorAction.REPLACE:java.nio.charset.CodingErrorAction
   628: if_acmpeq     633
   631: iconst_m1     
   632: ireturn       
   633: iload         9
   635: sipush        255
   638: iand          
   639: istore        9
   641: iload         9
   643: sipush        244
   646: if_icmpgt     670
   649: iload_2       
   650: iload         5
   652: if_icmpge     689
   655: iload         9
   657: aload_1       
   658: iload_2       
   659: baload        
   660: sipush        255
   663: iand          
   664: invokestatic  #29         // isMalformed4_2:(int, int)boolean
   667: ifeq          689
   670: aload         4
   672: iload         6
   674: iinc          
   677: aload_0       
   678: invokevirtual #47         // java.nio.charset.CharsetDecoder.replacement:()java.lang.String
   681: iconst_0      
   682: invokevirtual #48         // java.lang.String.charAt:(int)char
   685: castore       
   686: goto          51
   689: iinc          
   692: iload_2       
   693: iload         5
   695: if_icmpge     726
   698: aload_1       
   699: iload_2       
   700: baload        
   701: invokestatic  #30         // isMalformed4_3:(int)boolean
   704: ifeq          726
   707: aload         4
   709: iload         6
   711: iinc          
   714: aload_0       
   715: invokevirtual #47         // java.nio.charset.CharsetDecoder.replacement:()java.lang.String
   718: iconst_0      
   719: invokevirtual #48         // java.lang.String.charAt:(int)char
   722: castore       
   723: goto          51
   726: aload         4
   728: iload         6
   730: iinc          
   733: aload_0       
   734: invokevirtual #47         // java.nio.charset.CharsetDecoder.replacement:()java.lang.String
   737: iconst_0      
   738: invokevirtual #48         // java.lang.String.charAt:(int)char
   741: castore       
   742: iload         6
   744: ireturn       
   745: aload_0       
   746: invokevirtual #45         // java.nio.charset.CharsetDecoder.malformedInputAction:()java.nio.charset.CodingErrorAction
   749: getstatic     #46         // java.nio.charset.CodingErrorAction.REPLACE:java.nio.charset.CodingErrorAction
   752: if_acmpeq     757
   755: iconst_m1     
   756: ireturn       
   757: aload         4
   759: iload         6
   761: iinc          
   764: aload_0       
   765: invokevirtual #47         // java.nio.charset.CharsetDecoder.replacement:()java.lang.String
   768: iconst_0      
   769: invokevirtual #48         // java.lang.String.charAt:(int)char
   772: castore       
   773: goto          51
   776: iload         6
   778: ireturn       
   <|@
end_bytecodes
begin_cfg
  name "After code generation"
end_cfg
begin_nmethod
  <<<HexCodeFile
  Platform AMD64 64  <||@
  HexCode 0 448b560849c1e203493bc20f85efffffff900f1f80000000000f1f800000000089842400c0feff4883ec1848896c2410448bd14503d04885d20f8424010000418b410c443bc0458bd8440f4fd84963db48ffcb4183fb010f8c1d0000008b7a0c4863e94803eb448bef4c3bed0f86800000003bf90f86fe0000004183fb010f8c130000008bf8483bfb0f869f00000085c00f8482000000448bc1b900000000e92b000000660f1f440000660f1f440000420fbe4402100fbed885db0f8c820000000fbec0664189444910ffc141ffc0443bd97fdc453bd00f8f7f0000008bc1488b6c24104883c418850500000000c5f877c349baaddeaddeaddeadde4d8bda41bae5a7ffff4589979c0200004d899fa8020000e8000000009049baaddeaddeaddeadde4d8bda41bae59dffffebd749baaddeaddeaddeadde4d8bda41bae59dffffebc2bbedaaffff41899f9c0200004d89a7a8020000e80000000090bbed95ffffebe549baaddeaddeaddeadde4d8bda41baf5b8ffffeb8d49baaddeaddeaddeadde4d8bda41bae5a7ffffe975ffffffe80000000090e80000000090  <||@
  Comment 0 2  <||@
  Comment 11 {Field[name=CompilerToVM::Data::SharedRuntime_ic_miss_stub, type=address, offset=0, address=0x1024a1f78, value=0x10ba1de60]:0x10ba1de60}  <||@
  Comment 32 [stack overflow check]  <||@
  Comment 32 3  <||@
  Comment 32 1  <||@
  Comment 43 block B0 null  <||@
  Comment 43 0 [rsi|QWORD[.], rdx|QWORD[.], rcx|DWORD, r8|DWORD, r9|QWORD[.], rbp|QWORD] = LABEL numbPhis: 0 align: false label: ?  <||@
  Comment 43 2 stack:16|QWORD = MOVE rbp|QWORD moveKind: QWORD  <||@
  Comment 48 4 [] = HOTSPOTLOCKSTACK frameMapBuilder: org.graalvm.compiler.lir.amd64.AMD64FrameMapBuilder@51ff0cce slotKind: QWORD  <||@
  Comment 48 16 r10|DWORD = ADD (x: rcx|DWORD, y: r8|DWORD) size: DWORD  <||@
  Comment 54 18 TEST (x: rdx|QWORD[.], y: rdx|QWORD[.]) size: QWORD  <||@
  Comment 57 20 BRANCH trueDestinationProbability: 0.0 condition: = trueDestination: B0 -> B1 falseDestination: B0 -> B2  <||@
  Comment 63 block B2 null  <||@
  Comment 63 22 [] = LABEL numbPhis: 0 align: false label: ?  <||@
  Comment 63 24 rax|DWORD = MOV [r9|QWORD[.] + 12] size: DWORD state [bci:0]  <||@
  Comment 63 [rdx:0, rsi:0, r9:0]at sun.nio.cs.UTF_8$Decoder.decode(UTF_8.java:428) [bci: 0, duringCall: false, rethrow: false]
              |0             |1             |2          |3         |4            |5  |6  |7  |8  |9  |10  |11  |12  |13 
     locals:  |rsi|QWORD[.]  |rdx|QWORD[.]  |rcx|DWORD  |r8|DWORD  |r9|QWORD[.]  |-  |-  |-  |-  |-  |-   |-   |-   |-    <||@
  Comment 63 {infopoint: IMPLICIT_EXCEPTION}  <||@
  Comment 67 26 CMP (x: r8|DWORD, y: rax|DWORD) size: DWORD  <||@
  Comment 70 28 r11|DWORD = CMOVE (falseValue: r8|DWORD, ~trueValue: rax|DWORD) condition: >  <||@
  Comment 77 30 rbx|QWORD = MOVSXD r11|DWORD size: QWORD  <||@
  Comment 80 32 rbx|QWORD = DEC rbx|QWORD size: QWORD  <||@
  Comment 83 34 CMP r11|DWORD y: 1 size: DWORD  <||@
  Comment 87 36 BRANCH trueDestinationProbability: 0.5 condition: < trueDestination: B2 -> B7 falseDestination: B2 -> B4  <||@
  Comment 93 block B4 null  <||@
  Comment 93 38 [] = LABEL numbPhis: 0 align: false label: ?  <||@
  Comment 93 40 rdi|DWORD = MOV [rdx|QWORD[.] + 12] size: DWORD  <||@
  Comment 96 42 rbp|QWORD = MOVSXD rcx|DWORD size: QWORD  <||@
  Comment 99 44 rbp|QWORD = ADD (x: rbp|QWORD, y: rbx|QWORD) size: QWORD  <||@
  Comment 102 46 r13|QWORD = MOV rdi|DWORD size: DWORD  <||@
  Comment 105 48 CMP (x: r13|QWORD, y: rbp|QWORD) size: QWORD  <||@
  Comment 108 50 BRANCH trueDestinationProbability: 1.0 condition: |>| trueDestination: B4 -> B5 falseDestination: B4 -> B24  <||@
  Comment 114 block B5 null  <||@
  Comment 114 52 [] = LABEL numbPhis: 0 align: false label: ?  <||@
  Comment 114 54 CMP (x: rdi|DWORD, y: rcx|DWORD) size: DWORD  <||@
  Comment 116 56 BRANCH trueDestinationProbability: 1.0 condition: |>| trueDestination: B5 -> B7 falseDestination: B5 -> B23  <||@
  Comment 122 block B7 null  <||@
  Comment 122 66 [] = LABEL numbPhis: 0 align: false label: ?  <||@
  Comment 122 68 CMP r11|DWORD y: 1 size: DWORD  <||@
  Comment 126 70 BRANCH trueDestinationProbability: 0.5 condition: < trueDestination: B7 -> B13 falseDestination: B7 -> B9  <||@
  Comment 132 block B9 null  <||@
  Comment 132 72 [] = LABEL numbPhis: 0 align: false label: ?  <||@
  Comment 132 74 rdi|QWORD = MOV rax|DWORD size: DWORD  <||@
  Comment 134 76 CMP (x: rdi|QWORD, y: rbx|QWORD) size: QWORD  <||@
  Comment 137 78 BRANCH trueDestinationProbability: 1.0 condition: |>| trueDestination: B9 -> B10 falseDestination: B9 -> B22  <||@
  Comment 143 block B10 null  <||@
  Comment 143 80 [] = LABEL numbPhis: 0 align: false label: ?  <||@
  Comment 143 82 TEST (x: rax|DWORD, y: rax|DWORD) size: DWORD  <||@
  Comment 145 84 BRANCH trueDestinationProbability: 0.0 condition: = trueDestination: B10 -> B11 falseDestination: B10 -> B13  <||@
  Comment 151 block B13 null  <||@
  Comment 151 94 [] = LABEL numbPhis: 0 align: false label: ?  <||@
  Comment 151 -1 r8|DWORD = MOVE rcx|DWORD moveKind: DWORD  <||@
  Comment 154 -1 rcx|DWORD = MOVE input: int[0|0x0]  <||@
  Comment 159 96 JUMP ~[] destination: B13 -> B14  <||@
  Comment 164 block B15 loop 0 depth 1 header:16|LoopBegin  <||@
  Comment 164 104 [] = LABEL numbPhis: 0 align: true label: ?  <||@
  Comment 176 106 rax|DWORD = MOVSXB [rdx|QWORD[.] + r8|DWORD * 1 + 16] size: DWORD  <||@
  Comment 182 108 rbx|DWORD = MOVSXB rax|DWORD size: DWORD  <||@
  Comment 185 110 TEST (x: rbx|DWORD, y: rbx|DWORD) size: DWORD  <||@
  Comment 187 112 BRANCH trueDestinationProbability: 0.0 condition: < trueDestination: B15 -> B16 falseDestination: B15 -> B17  <||@
  Comment 193 block B17 loop 0 depth 1 header:16|LoopBegin  <||@
  Comment 193 114 [] = LABEL numbPhis: 0 align: false label: ?  <||@
  Comment 193 116 rax|DWORD = MOVSXB rax|DWORD size: DWORD  <||@
  Comment 196 118 MOV (x: [r9|QWORD[.] + rcx|DWORD * 2 + 16], y: rax|DWORD) size: WORD  <||@
  Comment 202 120 rcx|DWORD = INC rcx|DWORD size: DWORD  <||@
  Comment 204 122 r8|DWORD = INC r8|DWORD size: DWORD  <||@
  Comment 207 124 JUMP ~[] destination: B17 -> B14  <||@
  Comment 207 block B14 loop 0 depth 1 header:16|LoopBegin  <||@
  Comment 207 98 [] = LABEL numbPhis: 2 align: false label: ?  <||@
  Comment 207 100 CMP (x: r11|DWORD, y: rcx|DWORD) size: DWORD  <||@
  Comment 210 102 BRANCH trueDestinationProbability: 0.9979666244217335 condition: > trueDestination: B14 -> B15 falseDestination: B14 -> B18  <||@
  Comment 212 block B18 null  <||@
  Comment 212 126 [] = LABEL numbPhis: 0 align: false label: ?  <||@
  Comment 212 128 CMP (x: r10|DWORD, y: r8|DWORD) size: DWORD  <||@
  Comment 215 130 BRANCH trueDestinationProbability: 0.0 condition: > trueDestination: B18 -> B19 falseDestination: B18 -> B21  <||@
  Comment 221 block B21 null  <||@
  Comment 221 132 [] = LABEL numbPhis: 0 align: false label: ?  <||@
  Comment 221 134 rax|DWORD = MOVE rcx|DWORD moveKind: DWORD  <||@
  Comment 223 136 RETURN (savedRbp: stack:16|QWORD, value: rax|DWORD) isStub: false thread: r15 scratchForSafepointOnReturn: rcx config: org.graalvm.compiler.hotspot.GraalHotSpotVMConfig@f96b858  <||@
  Comment 232 12  <||@
  Comment 242 block B24 null  <||@
  Comment 242 172 [] = LABEL numbPhis: 0 align: false label: ?  <||@
  Comment 242 174 r10|QWORD[.] = HOTSPOTLOADOBJECTCONSTANT input: Object[d.a@1183312594]  <||@
  Comment 242 {Object[d.a@1183312594]}  <||@
  Comment 252 -1 r11|QWORD[.] = MOVE r10|QWORD[.] moveKind: QWORD  <||@
  Comment 255 -1 r10|DWORD = MOVE input: int[-22555|0xffffffffffffa7e5]  <||@
  Comment 261 176 JUMP ~[] destination: B24 -> B25  <||@
  Comment 261 block B25 null  <||@
  Comment 261 184 [] = LABEL numbPhis: 2 align: false label: ?  <||@
  Comment 261 186 MOV (x: [r15|QWORD + 668], y: r10|DWORD) size: DWORD  <||@
  Comment 268 188 MOV (x: [r15|QWORD + 680], y: r11|QWORD[.]) size: QWORD  <||@
  Comment 275 190 DEOPT info [bci:0]  <||@
  Comment 275 {Field[name=CompilerToVM::Data::SharedRuntime_deopt_blob_uncommon_trap, type=address, offset=0, address=0x1024a1f90, value=0x10ba1f5fe]:0x10ba1f5fe}  <||@
  Comment 280 [rdx:0, rsi:0, r9:0]at sun.nio.cs.UTF_8$Decoder.decode(UTF_8.java:428) [bci: 0, duringCall: false, rethrow: false]
              |0             |1             |2          |3         |4            |5  |6  |7  |8  |9  |10  |11  |12  |13 
     locals:  |rsi|QWORD[.]  |rdx|QWORD[.]  |rcx|DWORD  |r8|DWORD  |r9|QWORD[.]  |-  |-  |-  |-  |-  |-   |-   |-   |-    <||@
  Comment 281 block B11 null  <||@
  Comment 281 144 [] = LABEL numbPhis: 0 align: false label: ?  <||@
  Comment 281 146 r10|QWORD[.] = HOTSPOTLOADOBJECTCONSTANT input: Object[d.a@1183312594]  <||@
  Comment 281 {Object[d.a@1183312594]}  <||@
  Comment 291 -1 r11|QWORD[.] = MOVE r10|QWORD[.] moveKind: QWORD  <||@
  Comment 294 -1 r10|DWORD = MOVE input: int[-25115|0xffffffffffff9de5]  <||@
  Comment 300 148 JUMP ~[] destination: B11 -> B25  <||@
  Comment 302 block B22 null  <||@
  Comment 302 166 [] = LABEL numbPhis: 0 align: false label: ?  <||@
  Comment 302 168 r10|QWORD[.] = HOTSPOTLOADOBJECTCONSTANT input: Object[d.a@1183312594]  <||@
  Comment 302 {Object[d.a@1183312594]}  <||@
  Comment 312 -1 r11|QWORD[.] = MOVE r10|QWORD[.] moveKind: QWORD  <||@
  Comment 315 -1 r10|DWORD = MOVE input: int[-25115|0xffffffffffff9de5]  <||@
  Comment 321 170 JUMP ~[] destination: B22 -> B25  <||@
  Comment 323 block B16 null  <||@
  Comment 323 150 [] = LABEL numbPhis: 0 align: false label: ?  <||@
  Comment 323 -1 rbx|DWORD = MOVE input: int[-21779|0xffffffffffffaaed]  <||@
  Comment 328 152 JUMP ~[] destination: B16 -> B20  <||@
  Comment 328 block B20 null  <||@
  Comment 328 158 [] = LABEL numbPhis: 1 align: false label: ?  <||@
  Comment 328 160 MOV (x: [r15|QWORD + 668], y: rbx|DWORD) size: DWORD  <||@
  Comment 335 162 MOV (x: [r15|QWORD + 680], y: r12|ILLEGAL) size: QWORD  <||@
  Comment 342 164 DEOPT info [bci:20]  <||@
  Comment 342 {Field[name=CompilerToVM::Data::SharedRuntime_deopt_blob_uncommon_trap, type=address, offset=0, address=0x1024a1f90, value=0x10ba1f5fe]:0x10ba1f5fe}  <||@
  Comment 347 [rdx:0, rsi:0, r9:0]at sun.nio.cs.UTF_8$Decoder.decode(UTF_8.java:434) [bci: 20, duringCall: false, rethrow: false]
              |0             |1             |2         |3  |4            |5          |6          |7          |8             |9  |10  |11  |12  |13 
     locals:  |rsi|QWORD[.]  |rdx|QWORD[.]  |r8|DWORD  |-  |r9|QWORD[.]  |r10|DWORD  |rcx|DWORD  |r11|DWORD  |Object[null]  |-  |-   |-   |-   |-    <||@
  Comment 348 block B19 null  <||@
  Comment 348 154 [] = LABEL numbPhis: 0 align: false label: ?  <||@
  Comment 348 -1 rbx|DWORD = MOVE input: int[-27155|0xffffffffffff95ed]  <||@
  Comment 353 156 JUMP ~[] destination: B19 -> B20  <||@
  Comment 355 block B1 null  <||@
  Comment 355 178 [] = LABEL numbPhis: 0 align: false label: ?  <||@
  Comment 355 180 r10|QWORD[.] = HOTSPOTLOADOBJECTCONSTANT input: Object[d.a@206089336]  <||@
  Comment 355 {Object[d.a@206089336]}  <||@
  Comment 365 -1 r11|QWORD[.] = MOVE r10|QWORD[.] moveKind: QWORD  <||@
  Comment 368 -1 r10|DWORD = MOVE input: int[-18187|0xffffffffffffb8f5]  <||@
  Comment 374 182 JUMP ~[] destination: B1 -> B25  <||@
  Comment 376 block B23 null  <||@
  Comment 376 138 [] = LABEL numbPhis: 0 align: false label: ?  <||@
  Comment 376 140 r10|QWORD[.] = HOTSPOTLOADOBJECTCONSTANT input: Object[d.a@1183312594]  <||@
  Comment 376 {Object[d.a@1183312594]}  <||@
  Comment 386 -1 r11|QWORD[.] = MOVE r10|QWORD[.] moveKind: QWORD  <||@
  Comment 389 -1 r10|DWORD = MOVE input: int[-22555|0xffffffffffffa7e5]  <||@
  Comment 395 142 JUMP ~[] destination: B23 -> B25  <||@
  Comment 400 {Stub<ExceptionHandlerStub.exceptionHandler>@0x10be4bf20:CallingConvention[rax|QWORD[.], rdx|QWORD]:CallingConvention[rax|QWORD[.], rdx|QWORD]; temps=rdi|ILLEGAL,xmm0|ILLEGAL,xmm1|ILLEGAL,xmm2|ILLEGAL,xmm3|ILLEGAL,xmm4|ILLEGAL,xmm5|ILLEGAL,xmm6|ILLEGAL,xmm7|ILLEGAL,xmm8|ILLEGAL,xmm9|ILLEGAL,xmm10|ILLEGAL,xmm11|ILLEGAL,xmm12|ILLEGAL,xmm13|ILLEGAL,xmm14|ILLEGAL,xmm15|ILLEGAL,xmm16|ILLEGAL,xmm17|ILLEGAL,xmm18|ILLEGAL,xmm19|ILLEGAL,xmm20|ILLEGAL,xmm21|ILLEGAL,xmm22|ILLEGAL,xmm23|ILLEGAL,xmm24|ILLEGAL,xmm25|ILLEGAL,xmm26|ILLEGAL,xmm27|ILLEGAL,xmm28|ILLEGAL,xmm29|ILLEGAL,xmm30|ILLEGAL,xmm31|ILLEGAL,rax|ILLEGAL,rcx|ILLEGAL,rdx|ILLEGAL,rsi|ILLEGAL,r8|ILLEGAL,r9|ILLEGAL,r10|ILLEGAL,r11|ILLEGAL}  <||@
  Comment 400 4  <||@
  Comment 406 {Field[name=CompilerToVM::Data::SharedRuntime_deopt_blob_unpack, type=address, offset=0, address=0x1024a1f88, value=0x10ba1f500]:0x10ba1f500}  <||@
  Comment 406 5  <||@
  HexCodeFile>>> <|@
end_nmethod
begin_compilation
  name " HotSpotCompilation-5488[sun.nio.cs.UTF_8$Decoder.decode(byte[], int, int, char[])]"
  method "HotSpotCompilation-5488[sun.nio.cs.UTF_8$Decoder.decode(byte[], int, int, char[])]"
  date 1527005023529
end_compilation
begin_cfg
  name "After code installation"
end_cfg
begin_nmethod
  <<<HexCodeFile
  Platform AMD64 64  <||@
  HexCode 10c4f2c20 448b560849c1e203493bc20f852fb252ff900f1f80000000000f1f800000000089842400c0feff4883ec1848896c2410448bd14503d04885d20f8424010000418b410c443bc0458bd8440f4fd84963db48ffcb4183fb010f8c1d0000008b7a0c4863e94803eb448bef4c3bed0f86800000003bf90f86fe0000004183fb010f8c130000008bf8483bfb0f869f00000085c00f8482000000448bc1b900000000e92b000000660f1f440000660f1f440000420fbe4402100fbed885db0f8c820000000fbec0664189444910ffc141ffc0443bd97fdc453bd00f8f7f0000008bc1488b6c24104883c4188505f862eff4c5f877c349bae0bb6470070000004d8bda41bae5a7ffff4589979c0200004d899fa8020000e8c6c852ff9049bae0bb6470070000004d8bda41bae59dffffebd749bae0bb6470070000004d8bda41bae59dffffebc2bbedaaffff41899f9c0200004d89a7a8020000e883c852ff90bbed95ffffebe549bac0b76470070000004d8bda41baf5b8ffffeb8d49bae0bb6470070000004d8bda41bae5a7ffffe975ffffffe86b9195ff90e845c752ff90f4f4f4f4  <||@
  Comment 0 2  <||@
  Comment 11 {Field[name=CompilerToVM::Data::SharedRuntime_ic_miss_stub, type=address, offset=0, address=0x1024a1f78, value=0x10ba1de60]:0x10ba1de60}  <||@
  Comment 32 [stack overflow check]  <||@
  Comment 32 3  <||@
  Comment 32 1  <||@
  Comment 43 block B0 null  <||@
  Comment 43 0 [rsi|QWORD[.], rdx|QWORD[.], rcx|DWORD, r8|DWORD, r9|QWORD[.], rbp|QWORD] = LABEL numbPhis: 0 align: false label: ?  <||@
  Comment 43 2 stack:16|QWORD = MOVE rbp|QWORD moveKind: QWORD  <||@
  Comment 48 4 [] = HOTSPOTLOCKSTACK frameMapBuilder: org.graalvm.compiler.lir.amd64.AMD64FrameMapBuilder@51ff0cce slotKind: QWORD  <||@
  Comment 48 16 r10|DWORD = ADD (x: rcx|DWORD, y: r8|DWORD) size: DWORD  <||@
  Comment 54 18 TEST (x: rdx|QWORD[.], y: rdx|QWORD[.]) size: QWORD  <||@
  Comment 57 20 BRANCH trueDestinationProbability: 0.0 condition: = trueDestination: B0 -> B1 falseDestination: B0 -> B2  <||@
  Comment 63 block B2 null  <||@
  Comment 63 22 [] = LABEL numbPhis: 0 align: false label: ?  <||@
  Comment 63 24 rax|DWORD = MOV [r9|QWORD[.] + 12] size: DWORD state [bci:0]  <||@
  Comment 63 [rdx:0, rsi:0, r9:0]at sun.nio.cs.UTF_8$Decoder.decode(UTF_8.java:428) [bci: 0, duringCall: false, rethrow: false]
              |0             |1             |2          |3         |4            |5  |6  |7  |8  |9  |10  |11  |12  |13 
     locals:  |rsi|QWORD[.]  |rdx|QWORD[.]  |rcx|DWORD  |r8|DWORD  |r9|QWORD[.]  |-  |-  |-  |-  |-  |-   |-   |-   |-    <||@
  Comment 63 {infopoint: IMPLICIT_EXCEPTION}  <||@
  Comment 67 26 CMP (x: r8|DWORD, y: rax|DWORD) size: DWORD  <||@
  Comment 70 28 r11|DWORD = CMOVE (falseValue: r8|DWORD, ~trueValue: rax|DWORD) condition: >  <||@
  Comment 77 30 rbx|QWORD = MOVSXD r11|DWORD size: QWORD  <||@
  Comment 80 32 rbx|QWORD = DEC rbx|QWORD size: QWORD  <||@
  Comment 83 34 CMP r11|DWORD y: 1 size: DWORD  <||@
  Comment 87 36 BRANCH trueDestinationProbability: 0.5 condition: < trueDestination: B2 -> B7 falseDestination: B2 -> B4  <||@
  Comment 93 block B4 null  <||@
  Comment 93 38 [] = LABEL numbPhis: 0 align: false label: ?  <||@
  Comment 93 40 rdi|DWORD = MOV [rdx|QWORD[.] + 12] size: DWORD  <||@
  Comment 96 42 rbp|QWORD = MOVSXD rcx|DWORD size: QWORD  <||@
  Comment 99 44 rbp|QWORD = ADD (x: rbp|QWORD, y: rbx|QWORD) size: QWORD  <||@
  Comment 102 46 r13|QWORD = MOV rdi|DWORD size: DWORD  <||@
  Comment 105 48 CMP (x: r13|QWORD, y: rbp|QWORD) size: QWORD  <||@
  Comment 108 50 BRANCH trueDestinationProbability: 1.0 condition: |>| trueDestination: B4 -> B5 falseDestination: B4 -> B24  <||@
  Comment 114 block B5 null  <||@
  Comment 114 52 [] = LABEL numbPhis: 0 align: false label: ?  <||@
  Comment 114 54 CMP (x: rdi|DWORD, y: rcx|DWORD) size: DWORD  <||@
  Comment 116 56 BRANCH trueDestinationProbability: 1.0 condition: |>| trueDestination: B5 -> B7 falseDestination: B5 -> B23  <||@
  Comment 122 block B7 null  <||@
  Comment 122 66 [] = LABEL numbPhis: 0 align: false label: ?  <||@
  Comment 122 68 CMP r11|DWORD y: 1 size: DWORD  <||@
  Comment 126 70 BRANCH trueDestinationProbability: 0.5 condition: < trueDestination: B7 -> B13 falseDestination: B7 -> B9  <||@
  Comment 132 block B9 null  <||@
  Comment 132 72 [] = LABEL numbPhis: 0 align: false label: ?  <||@
  Comment 132 74 rdi|QWORD = MOV rax|DWORD size: DWORD  <||@
  Comment 134 76 CMP (x: rdi|QWORD, y: rbx|QWORD) size: QWORD  <||@
  Comment 137 78 BRANCH trueDestinationProbability: 1.0 condition: |>| trueDestination: B9 -> B10 falseDestination: B9 -> B22  <||@
  Comment 143 block B10 null  <||@
  Comment 143 80 [] = LABEL numbPhis: 0 align: false label: ?  <||@
  Comment 143 82 TEST (x: rax|DWORD, y: rax|DWORD) size: DWORD  <||@
  Comment 145 84 BRANCH trueDestinationProbability: 0.0 condition: = trueDestination: B10 -> B11 falseDestination: B10 -> B13  <||@
  Comment 151 block B13 null  <||@
  Comment 151 94 [] = LABEL numbPhis: 0 align: false label: ?  <||@
  Comment 151 -1 r8|DWORD = MOVE rcx|DWORD moveKind: DWORD  <||@
  Comment 154 -1 rcx|DWORD = MOVE input: int[0|0x0]  <||@
  Comment 159 96 JUMP ~[] destination: B13 -> B14  <||@
  Comment 164 block B15 loop 0 depth 1 header:16|LoopBegin  <||@
  Comment 164 104 [] = LABEL numbPhis: 0 align: true label: ?  <||@
  Comment 176 106 rax|DWORD = MOVSXB [rdx|QWORD[.] + r8|DWORD * 1 + 16] size: DWORD  <||@
  Comment 182 108 rbx|DWORD = MOVSXB rax|DWORD size: DWORD  <||@
  Comment 185 110 TEST (x: rbx|DWORD, y: rbx|DWORD) size: DWORD  <||@
  Comment 187 112 BRANCH trueDestinationProbability: 0.0 condition: < trueDestination: B15 -> B16 falseDestination: B15 -> B17  <||@
  Comment 193 block B17 loop 0 depth 1 header:16|LoopBegin  <||@
  Comment 193 114 [] = LABEL numbPhis: 0 align: false label: ?  <||@
  Comment 193 116 rax|DWORD = MOVSXB rax|DWORD size: DWORD  <||@
  Comment 196 118 MOV (x: [r9|QWORD[.] + rcx|DWORD * 2 + 16], y: rax|DWORD) size: WORD  <||@
  Comment 202 120 rcx|DWORD = INC rcx|DWORD size: DWORD  <||@
  Comment 204 122 r8|DWORD = INC r8|DWORD size: DWORD  <||@
  Comment 207 124 JUMP ~[] destination: B17 -> B14  <||@
  Comment 207 block B14 loop 0 depth 1 header:16|LoopBegin  <||@
  Comment 207 98 [] = LABEL numbPhis: 2 align: false label: ?  <||@
  Comment 207 100 CMP (x: r11|DWORD, y: rcx|DWORD) size: DWORD  <||@
  Comment 210 102 BRANCH trueDestinationProbability: 0.9979666244217335 condition: > trueDestination: B14 -> B15 falseDestination: B14 -> B18  <||@
  Comment 212 block B18 null  <||@
  Comment 212 126 [] = LABEL numbPhis: 0 align: false label: ?  <||@
  Comment 212 128 CMP (x: r10|DWORD, y: r8|DWORD) size: DWORD  <||@
  Comment 215 130 BRANCH trueDestinationProbability: 0.0 condition: > trueDestination: B18 -> B19 falseDestination: B18 -> B21  <||@
  Comment 221 block B21 null  <||@
  Comment 221 132 [] = LABEL numbPhis: 0 align: false label: ?  <||@
  Comment 221 134 rax|DWORD = MOVE rcx|DWORD moveKind: DWORD  <||@
  Comment 223 136 RETURN (savedRbp: stack:16|QWORD, value: rax|DWORD) isStub: false thread: r15 scratchForSafepointOnReturn: rcx config: org.graalvm.compiler.hotspot.GraalHotSpotVMConfig@f96b858  <||@
  Comment 232 12  <||@
  Comment 242 block B24 null  <||@
  Comment 242 172 [] = LABEL numbPhis: 0 align: false label: ?  <||@
  Comment 242 174 r10|QWORD[.] = HOTSPOTLOADOBJECTCONSTANT input: Object[d.a@1183312594]  <||@
  Comment 242 {Object[d.a@1183312594]}  <||@
  Comment 252 -1 r11|QWORD[.] = MOVE r10|QWORD[.] moveKind: QWORD  <||@
  Comment 255 -1 r10|DWORD = MOVE input: int[-22555|0xffffffffffffa7e5]  <||@
  Comment 261 176 JUMP ~[] destination: B24 -> B25  <||@
  Comment 261 block B25 null  <||@
  Comment 261 184 [] = LABEL numbPhis: 2 align: false label: ?  <||@
  Comment 261 186 MOV (x: [r15|QWORD + 668], y: r10|DWORD) size: DWORD  <||@
  Comment 268 188 MOV (x: [r15|QWORD + 680], y: r11|QWORD[.]) size: QWORD  <||@
  Comment 275 190 DEOPT info [bci:0]  <||@
  Comment 275 {Field[name=CompilerToVM::Data::SharedRuntime_deopt_blob_uncommon_trap, type=address, offset=0, address=0x1024a1f90, value=0x10ba1f5fe]:0x10ba1f5fe}  <||@
  Comment 280 [rdx:0, rsi:0, r9:0]at sun.nio.cs.UTF_8$Decoder.decode(UTF_8.java:428) [bci: 0, duringCall: false, rethrow: false]
              |0             |1             |2          |3         |4            |5  |6  |7  |8  |9  |10  |11  |12  |13 
     locals:  |rsi|QWORD[.]  |rdx|QWORD[.]  |rcx|DWORD  |r8|DWORD  |r9|QWORD[.]  |-  |-  |-  |-  |-  |-   |-   |-   |-    <||@
  Comment 281 block B11 null  <||@
  Comment 281 144 [] = LABEL numbPhis: 0 align: false label: ?  <||@
  Comment 281 146 r10|QWORD[.] = HOTSPOTLOADOBJECTCONSTANT input: Object[d.a@1183312594]  <||@
  Comment 281 {Object[d.a@1183312594]}  <||@
  Comment 291 -1 r11|QWORD[.] = MOVE r10|QWORD[.] moveKind: QWORD  <||@
  Comment 294 -1 r10|DWORD = MOVE input: int[-25115|0xffffffffffff9de5]  <||@
  Comment 300 148 JUMP ~[] destination: B11 -> B25  <||@
  Comment 302 block B22 null  <||@
  Comment 302 166 [] = LABEL numbPhis: 0 align: false label: ?  <||@
  Comment 302 168 r10|QWORD[.] = HOTSPOTLOADOBJECTCONSTANT input: Object[d.a@1183312594]  <||@
  Comment 302 {Object[d.a@1183312594]}  <||@
  Comment 312 -1 r11|QWORD[.] = MOVE r10|QWORD[.] moveKind: QWORD  <||@
  Comment 315 -1 r10|DWORD = MOVE input: int[-25115|0xffffffffffff9de5]  <||@
  Comment 321 170 JUMP ~[] destination: B22 -> B25  <||@
  Comment 323 block B16 null  <||@
  Comment 323 150 [] = LABEL numbPhis: 0 align: false label: ?  <||@
  Comment 323 -1 rbx|DWORD = MOVE input: int[-21779|0xffffffffffffaaed]  <||@
  Comment 328 152 JUMP ~[] destination: B16 -> B20  <||@
  Comment 328 block B20 null  <||@
  Comment 328 158 [] = LABEL numbPhis: 1 align: false label: ?  <||@
  Comment 328 160 MOV (x: [r15|QWORD + 668], y: rbx|DWORD) size: DWORD  <||@
  Comment 335 162 MOV (x: [r15|QWORD + 680], y: r12|ILLEGAL) size: QWORD  <||@
  Comment 342 164 DEOPT info [bci:20]  <||@
  Comment 342 {Field[name=CompilerToVM::Data::SharedRuntime_deopt_blob_uncommon_trap, type=address, offset=0, address=0x1024a1f90, value=0x10ba1f5fe]:0x10ba1f5fe}  <||@
  Comment 347 [rdx:0, rsi:0, r9:0]at sun.nio.cs.UTF_8$Decoder.decode(UTF_8.java:434) [bci: 20, duringCall: false, rethrow: false]
              |0             |1             |2         |3  |4            |5          |6          |7          |8             |9  |10  |11  |12  |13 
     locals:  |rsi|QWORD[.]  |rdx|QWORD[.]  |r8|DWORD  |-  |r9|QWORD[.]  |r10|DWORD  |rcx|DWORD  |r11|DWORD  |Object[null]  |-  |-   |-   |-   |-    <||@
  Comment 348 block B19 null  <||@
  Comment 348 154 [] = LABEL numbPhis: 0 align: false label: ?  <||@
  Comment 348 -1 rbx|DWORD = MOVE input: int[-27155|0xffffffffffff95ed]  <||@
  Comment 353 156 JUMP ~[] destination: B19 -> B20  <||@
  Comment 355 block B1 null  <||@
  Comment 355 178 [] = LABEL numbPhis: 0 align: false label: ?  <||@
  Comment 355 180 r10|QWORD[.] = HOTSPOTLOADOBJECTCONSTANT input: Object[d.a@206089336]  <||@
  Comment 355 {Object[d.a@206089336]}  <||@
  Comment 365 -1 r11|QWORD[.] = MOVE r10|QWORD[.] moveKind: QWORD  <||@
  Comment 368 -1 r10|DWORD = MOVE input: int[-18187|0xffffffffffffb8f5]  <||@
  Comment 374 182 JUMP ~[] destination: B1 -> B25  <||@
  Comment 376 block B23 null  <||@
  Comment 376 138 [] = LABEL numbPhis: 0 align: false label: ?  <||@
  Comment 376 140 r10|QWORD[.] = HOTSPOTLOADOBJECTCONSTANT input: Object[d.a@1183312594]  <||@
  Comment 376 {Object[d.a@1183312594]}  <||@
  Comment 386 -1 r11|QWORD[.] = MOVE r10|QWORD[.] moveKind: QWORD  <||@
  Comment 389 -1 r10|DWORD = MOVE input: int[-22555|0xffffffffffffa7e5]  <||@
  Comment 395 142 JUMP ~[] destination: B23 -> B25  <||@
  Comment 400 {Stub<ExceptionHandlerStub.exceptionHandler>@0x10be4bf20:CallingConvention[rax|QWORD[.], rdx|QWORD]:CallingConvention[rax|QWORD[.], rdx|QWORD]; temps=rdi|ILLEGAL,xmm0|ILLEGAL,xmm1|ILLEGAL,xmm2|ILLEGAL,xmm3|ILLEGAL,xmm4|ILLEGAL,xmm5|ILLEGAL,xmm6|ILLEGAL,xmm7|ILLEGAL,xmm8|ILLEGAL,xmm9|ILLEGAL,xmm10|ILLEGAL,xmm11|ILLEGAL,xmm12|ILLEGAL,xmm13|ILLEGAL,xmm14|ILLEGAL,xmm15|ILLEGAL,xmm16|ILLEGAL,xmm17|ILLEGAL,xmm18|ILLEGAL,xmm19|ILLEGAL,xmm20|ILLEGAL,xmm21|ILLEGAL,xmm22|ILLEGAL,xmm23|ILLEGAL,xmm24|ILLEGAL,xmm25|ILLEGAL,xmm26|ILLEGAL,xmm27|ILLEGAL,xmm28|ILLEGAL,xmm29|ILLEGAL,xmm30|ILLEGAL,xmm31|ILLEGAL,rax|ILLEGAL,rcx|ILLEGAL,rdx|ILLEGAL,rsi|ILLEGAL,r8|ILLEGAL,r9|ILLEGAL,r10|ILLEGAL,r11|ILLEGAL}  <||@
  Comment 400 4  <||@
  Comment 406 {Field[name=CompilerToVM::Data::SharedRuntime_deopt_blob_unpack, type=address, offset=0, address=0x1024a1f88, value=0x10ba1f500]:0x10ba1f500}  <||@
  Comment 406 5  <||@
  HexCodeFile>>> <|@
end_nmethod
